Workbook
Name acq: [1]Assumptions!$H$8
Name acq_fye: [1]Assumptions!$H$32
Name acq_price: [1]Assumptions!$J$11
Name assume: [1]Assumptions!$T$11
Name base_year: [2]Control!$D$11
Name case: [1]Assumptions!$T$7
Name cash_rate: [1]Assumptions!$T$20
Name circ: [2]Control!$D$13
Name curr: [2]Control!$D$9
Name debt_rate: [1]Assumptions!$T$16
Name eps: [1]Assumptions!$T$41
Name fees: [1]Assumptions!$T$24
Name libor: [3]LBO!$AF$34
Name min_cash: [1]Assumptions!$T$21
Name pct_cash: [1]Assumptions!$T$8
Name project: [2]Control!$D$5
Name sec_338: [1]Assumptions!$T$13
Name synergies: [1]Assumptions!$T$28
Name tax_rate: [1]Assumptions!$T$39
Name tgt: [1]Assumptions!$L$8
Name tgt_price: [1]Assumptions!$N$11
Name type: [1]Assumptions!$T$12
Name year: [1]Assumptions!$T$40

Sheet WACC >>>>

Sheet Cost of Equity
B1: equity beta (daily) | C1: Index | D1: Marginal tax rate(2010) | E1: E/V | F1: unlevered Beta | G1: D/V | H1: D/E | I1: Return on Asset | J1: Asset Beta
A2: pfizer | B2: 0.708 | C2: SPX | D2: 0.4 | E2: 0.824 | F2: =B2*E2 -> 0.583392 | G2: =1-E2 -> 0.176 | H2: =G2/E2 -> 0.21359223 | I2: =$B$30+F2*$B$29 -> 0.10661959 | J2: =B2/(1+H2*(1-D2)) -> 0.62757315
A3: roche | B3: 0.681 | C3: SMI | D3: 0.1875 | E3: 0.798 | F3: =B3*E3 -> 0.543438 | G3: =1-E3 -> 0.202 | H3: =G3/E3 -> 0.25313283 | I3: =$B$30+F3*$B$29 -> 0.099399907 | J3: =B3/(1+H3*(1-D3)) -> 0.56483097
A4: Bayer | B4: 0.706 | C4: DAX | D4: 0.2941 | E4: 0.802 | F4: =B4*E4 -> 0.566212 | G4: =1-E4 -> 0.198 | H4: =G4/E4 -> 0.24688279 | I4: =$B$30+F4*$B$29 -> 0.10351517 | J4: =B4/(1+H4*(1-D4)) -> 0.60122225
A5: Merck | B5: 0.715 | C5: SPX | D5: 0.4 | E5: 0.861 | F5: =B5*E5 -> 0.615615 | G5: =1-E5 -> 0.139 | H5: =G5/E5 -> 0.16144019 | I5: =$B$30+F5*$B$29 -> 0.11244229 | J5: =B5/(1+H5*(1-D5)) -> 0.65185832
A6: gilead | B6: 0.401 | C6: SPX | D6: 0.4 | E6: 0.911 | F6: =B6*E6 -> 0.365311 | G6: =1-E6 -> 0.089 | H6: =G6/E6 -> 0.097694841 | I6: =$B$30+F6*$B$29 -> 0.067212358 | J6: =B6/(1+H6*(1-D6)) -> 0.37879614
A7: GSK | B7: 0.464 | C7: UKX | D7: 0.28 | E7: 0.81 | F7: =B7*E7 -> 0.37584 | G7: =1-E7 -> 0.19 | H7: =G7/E7 -> 0.2345679 | I7: =$B$30+F7*$B$29 -> 0.069114948 | J7: =B7/(1+H7*(1-D7)) -> 0.39695817
A8: ELI LILLY & CO | B8: 0.786 | C8: SPX | D8: 0.4 | E8: 0.854 | F8: =B8*E8 -> 0.671244 | G8: =1-E8 -> 0.146 | H8: =G8/E8 -> 0.17096019 | I8: =$B$30+F8*$B$29 -> 0.12249445 | J8: =B8/(1+H8*(1-D8)) -> 0.71287596
A9: astrazeneca | B9: 0.378 | C9: UKX | D9: 0.28 | E9: 0.874 | F9: =B9*E9 -> 0.330372 | G9: =1-E9 -> 0.126 | H9: =G9/E9 -> 0.14416476 | I9: =$B$30+F9*$B$29 -> 0.060898881 | J9: =B9/(1+H9*(1-D9)) -> 0.34245377
A10: amgen | B10: 0.468 | C10: SPX | D10: 0.4 | E10: 0.793 | F10: =B10*E10 -> 0.371124 | G10: =1-E10 -> 0.207 | H10: =G10/E10 -> 0.26103405 | I10: =$B$30+F10*$B$29 -> 0.068262767 | J10: =B10/(1+H10*(1-D10)) -> 0.40462713
A11: allergan | B11: 0.47 | C11: SPX | D11: 0.4 | E11: 0.865 | F11: =B11*E11 -> 0.40655 | G11: =1-E11 -> 0.135 | H11: =G11/E11 -> 0.15606936 | I11: =$B$30+F11*$B$29 -> 0.074664245 | J11: =B11/(1+H11*(1-D11)) -> 0.42975687
A12: Teva | B12: 0.205 | C12: SPX | D12: 0.4 | E12: 0.897 | F12: =B12*E12 -> 0.183885 | G12: =1-E12 -> 0.103 | H12: =G12/E12 -> 0.1148272 | I12: =$B$30+F12*$B$29 -> 0.03442868 | J12: =B12/(1+H12*(1-D12)) -> 0.19178661
A13: NOVO NORDISK | B13: 0.33 | C13: KFX | D13: 0.25 | E13: 0.997 | F13: =B13*E13 -> 0.32901 | G13: =1-E13 -> 0.003 | H13: =G13/E13 -> 0.0030090271 | I13: =$B$30+F13*$B$29 -> 0.060652767 | J13: =B13/(1+H13*(1-D13)) -> 0.32925694
... A24: CHUGAI | B24: 0.782 | C24: TPX | D24: 0.4069 | E24: 1 | F24: =B24*E24 -> 0.782 | G24: =1-E24 -> 0 | H24: =G24/E24 -> 0 | I24: =$B$30+F24*$B$29 -> 0.14250806 | J24: =B24/(1+H24*(1-D24)) -> 0.782
A25: Average | E25: =AVERAGE(E2:E24) -> 0.847 | F25: =AVERAGE(F2:F24) -> 0.508153 | G25: =AVERAGE(G2:G24) -> 0.153 | H25: =AVERAGE(H2:H24) -> 0.33826071 | I25: =AVERAGE(I2:I24) -> 0.093023907 | J25: =AVERAGE(J2:J24) -> 0.53261406
A28: Tax Rate | B28: 0.4 | C28: marginal tax rate for US in 2010 | F28: Genzyme | G28: D= | H28: 1439386
A29: market premium | B29: =I55 -> 0.1807 | C29: Fama French Average Annual Mkt-RF from 1991-2010 (North American) | F29: (thousands of USD) | G29: E= | H29: 18621007 | I29: V= | J29: =H29+H28 -> 20060393
A30: risk free return | B30: 0.0012006602 | G30: D/V= | H30: =H28/J29 -> 0.071752632
G31: E/V= | H31: =1-H30 -> 0.92824737
A33: return on asset | B33: =$B$30+F25*$B$29 -> 0.093023907
A34: Asset Beta | B34: =J25 -> 0.53261406
A35: Equity Beta | B35: =B34/H31 -> 0.57378462 | H35: Mkt-RF % | I35: Mkt-RF
G36: 1991 | H36: 27.07 | I36: =H36/100 -> 0.2707
A37: Cost of Equity | B37: =$B$30+$B$29*$B$35 -> 0.10488354 | G37: 1992 | H37: 5.13 | I37: =H37/100 -> 0.0513
A38: Cost of Debt | B38: 0.05228 | G38: 1993 | H38: 8.83 | I38: =H38/100 -> 0.0883
G39: 1994 | H39: -3.92 | I39: =H39/100 -> -0.0392
G40: 1995 | H40: 30.08 | I40: =H40/100 -> 0.3008
G41: 1996 | H41: 17.06 | I41: =H41/100 -> 0.1706
G42: 1997 | H42: 25.51 | I42: =H42/100 -> 0.2551
A43: WACC | B43: =B37*H31+B38*H30*(1-B28) -> 0.099608607 | G43: 1998 | H43: 18.11 | I43: =H43/100 -> 0.1811
G44: 1999 | H44: 18.59 | I44: =H44/100 -> 0.1859
G45: 2000 | H45: -13.73 | I45: =H45/100 -> -0.1373
G46: 2001 | H46: -14.83 | I46: =H46/100 -> -0.1483
G47: 2002 | H47: -22.69 | I47: =H47/100 -> -0.2269
G48: 2003 | H48: 31.57 | I48: =H48/100 -> 0.3157
G49: 2004 | H49: 11.75 | I49: =H49/100 -> 0.1175
G50: 2005 | H50: 4.94 | I50: =H50/100 -> 0.0494
G51: 2006 | H51: 10.63 | I51: =H51/100 -> 0.1063
G52: 2007 | H52: 3.28 | I52: =H52/100 -> 0.0328
G53: 2008 | H53: -39.48 | I53: =H53/100 -> -0.3948
G54: 2009 | H54: 31.7 | I54: =H54/100 -> 0.317
G55: 2010 | H55: 18.07 | I55: =H55/100 -> 0.1807

Sheet WACC
B2: Marginal tax rate | D2: 0.4
B4: List of debt instruments
C5: Nominal | D5: Interest | E5: Weight | G5: Cost of Debt
B6: 2015 Notes | C6: 500000 | D6: 0.03625 | E6: =C6/$C$10 -> 0.43391478 | G6: =D6*E6+D7*E7+D8*E8+D9*E9 -> 0.052275597
B7: 2020 Notes | C7: 500000 | D7: 0.05 | E7: =C7/$C$10 -> 0.43391478
B8: Mortgage payable | C8: 18100 | D8: 0.0557 | E8: =C8/$C$10 -> 0.015707715
B9: Capital lease obligations | C9: 134200 | D9: 0.12 | E9: =C9/$C$10 -> 0.11646273
C10: =SUM(C6:C9) -> 1152300
B13: Nominal book value of debt | G13: =C10 -> 1152300
B14: Market value of Operating leases | G14: ='Operating lease converter'!C30 -> 287086.17
G15: =SUM(G13:G14) -> 1439386.2 | H15: =G15/G21 -> 0.071752639
B16: Equity (market)
B17: Number of shares | G17: 261531
B18: Share Price 31.12.2010 (market) | G18: 71.2
B19: Equity value | G19: =G18*G17 -> 18621007
B21: Debt + Equity | F21: $ | G21: =G19+G14+G13 -> 20060393
B24: Cost of equity = | D24: 0.1049
B26: After-tax WACC = | D26: =G15/G21*G6*(1-D2)+G19/G21*D24 -> 0.099623695
B28: Return on assets = | D28: =G15/G21*G6+G19/G21*D24 -> 0.10112406
B33: Product | C33: Disease | D33: Number of patients | E33: Patiens pool worldwilde
B34: Cerezyme | C34: Gaucher | D34: 4700 | E34: 10000 | F34: =D34/E34 -> 0.47
B35: Fabrazyme | C35: Fabry | D35: =8000-D34 -> 3300 | E35: 7500 | F35: =D35/E35 -> 0.44
B36: Myozyme/Lumizyme | C36: Pompe | D36: 1400 | E36: 10000 | F36: =D36/E36 -> 0.14
B37: Synvisc/Synvisc-One | C37: Osteoarthritis | D37: =E37*$G$37 -> 504000 | E37: =0.16*9000000 -> 1440000 | G37: =AVERAGE(F34:F36) -> 0.35
B38: Seprafilm | C38: Adhesions | D38: =E38*$G$37 -> 1190000 | E38: 3400000
B39: Thymoglobulin | C39: Organ transplant rejections | D39: =E39*$G$37 -> 22750 | E39: 65000
B40: Clolar | C40: Lymphoblastic leukemia | D40: =E40*$G$37 -> 245 | E40: 700
B41: Mozobil | C41: Autologous transplantation | D41: =E41*$G$37 -> 12250 | E41: 35000
B42: Alentuzumab | C42: Multiple Sclerosis | D42: =E42*$G$37 -> 735000 | E42: 2100000
D43: =SUM(D34:D42) -> 2473645 | E43: =SUM(E34:E42) -> 7068200 | F43: =D43/E43 -> 0.34996817
B45: Source: http://archive.boston.com/business/healthcare/articles/2009/06/17/genzyme_temporarily_halts_production_on_2_key_drugs/

Sheet FINANCIALS >>>>

Sheet Assumption
S1: Acquisition
E2: Choice of the scenario | H2: Acquisition | S2: Increased prices
S3: Stable growth
A4: M&A
A5: Assumptions | D5: Actual | F5: Projections
A6: €m | D6: 2006 | E6: 2007 | F6: 2008 | G6: 2009 | H6: 2010 | I6: 2011 | J6: 2012 | K6: 2013 | L6: 2014 | M6: 2015
B8: Operating assumptions
D9: 2006 | E9: 2007 | F9: 2008 | G9: 2009 | H9: 2010 | I9: 2011 | J9: 2012 | K9: 2013 | L9: 2014 | M9: 2015
B10: Income statement
B11: Product sales growth | D11: NA | E11: ='Income Statement'!E7/'Income Statement'!D7-1 -> 0.19753662 | F11: ='Income Statement'!F7/'Income Statement'!E7-1 -> 0.16837287 | G11: ='Income Statement'!G7/'Income Statement'!F7-1 -> -0.032140058 | H11: ='Income Statement'!H7/'Income Statement'!G7-1 -> 0.022970086 | I11: 0.1 | J11: 0.15 | K11: 0.2 | L11: 0.25 | M11: 0.3 | O11: Genzyme will fix the production issues and growth will look like high growth period of 2007-2008 after 3 years
B12: Service sales growth | D12: NA | E12: ='Income Statement'!E8/'Income Statement'!D8-1 -> 0.15670039 | F12: ='Income Statement'!F8/'Income Statement'!E8-1 -> -0.86084468 | G12: ='Income Statement'!G8/'Income Statement'!F8-1 -> 0.030984365 | H12: ='Income Statement'!H8/'Income Statement'!G8-1 -> -0.032552278 | I12: 0 | J12: 0 | K12: 0 | L12: 0 | M12: 0 | O12: No forecasting information. Should remain stable on average because very volatile
B13: R&D revenue growth | D13: NA | E13: ='Income Statement'!E9/'Income Statement'!D9-1 -> 0.68220291 | F13: ='Income Statement'!F9/'Income Statement'!E9-1 -> 0.42923678 | G13: ='Income Statement'!G9/'Income Statement'!F9-1 -> -0.51613901 | H13: ='Income Statement'!H9/'Income Statement'!G9-1 -> -0.82941697 | I13: =$AC$14 -> 0.45400699 | J13: =$AC$14 -> 0.45400699 | K13: =$AC$14 -> 0.45400699 | L13: =$AC$14 -> 0.45400699 | M13: =$AC$14 -> 0.45400699 | O13: Collapsed because of plant issues, we think revenues will come back to an average level of last five years in the next five years. Average = 22550, yearly growth rate = 45%
B14: COGS as % of sales | D14: =-'Income Statement'!D10/'Income Statement'!D7 -> 0.18576793 | E14: =-'Income Statement'!E10/'Income Statement'!E7 -> 0.20692595 | F14: =-'Income Statement'!F10/'Income Statement'!F7 -> 0.20443993 | G14: =-'Income Statement'!G10/'Income Statement'!G7 -> 0.26602984 | H14: =-'Income Statement'!H10/'Income Statement'!H7 -> 0.28842622 | I14: =AVERAGE($D$14:$F$14) -> 0.1990446 | J14: =AVERAGE($D$14:$F$14) -> 0.1990446 | K14: =AVERAGE($D$14:$F$14) -> 0.1990446 | L14: =AVERAGE($D$14:$F$14) -> 0.1990446 | M14: =AVERAGE($D$14:$F$14) -> 0.1990446 | O14: Average before issue with plants | AB14: =AVERAGE('Income Statement'!D9:H9) -> 22550.8 | AC14: =(AB14/'Income Statement'!H9)^(1/5)-1 -> 0.45400699
B15: COSS as % of service sales | D15: =-'Income Statement'!D11/'Income Statement'!D8 -> 0.70638173 | E15: =-'Income Statement'!E11/'Income Statement'!E8 -> 0.64912388 | F15: =-'Income Statement'!F11/'Income Statement'!F8 -> 0.64263378 | G15: =-'Income Statement'!G11/'Income Statement'!G8 -> 0.6436978 | H15: =-'Income Statement'!H11/'Income Statement'!H8 -> 0.83569205 | I15: =AVERAGE($D$15:$H$15) -> 0.69550585 | J15: =AVERAGE($D$15:$H$15) -> 0.69550585 | K15: =AVERAGE($D$15:$H$15) -> 0.69550585 | L15: =AVERAGE($D$15:$H$15) -> 0.69550585 | M15: =AVERAGE($D$15:$H$15) -> 0.69550585 | O15: Average
B16: SG&A as % of sales | D16: =-'Income Statement'!D12/'Income Statement'!D7 -> 0.34993311 | E16: =-'Income Statement'!E12/'Income Statement'!E7 -> 0.34333725 | F16: =-'Income Statement'!F12/'Income Statement'!F7 -> 0.29027415 | G16: =-'Income Statement'!G12/'Income Statement'!G7 -> 0.31824986 | H16: =-'Income Statement'!H12/'Income Statement'!H7 -> 0.38848559 | I16: =AVERAGE($D$16:$F$16) -> 0.32784817 | J16: =AVERAGE($D$16:$F$16) -> 0.32784817 | K16: =AVERAGE($D$16:$F$16) -> 0.32784817 | L16: =AVERAGE($D$16:$F$16) -> 0.32784817 | M16: =AVERAGE($D$16:$F$16) -> 0.32784817 | O16: Average before issue with plants
B17: R&D as % of sales | D17: =-'Income Statement'!D13/'Income Statement'!D7 -> 0.22509835 | E17: =-'Income Statement'!E13/'Income Statement'!E7 -> 0.21334076 | F17: =-'Income Statement'!F13/'Income Statement'!F7 -> 0.32040082 | G17: =-'Income Statement'!G13/'Income Statement'!G7 -> 0.2132546 | H17: =-'Income Statement'!H13/'Income Statement'!H7 -> 0.21182391 | I17: =AVERAGE($D$17:$H$17) -> 0.23678369 | J17: =AVERAGE($D$17:$H$17) -> 0.23678369 | K17: =AVERAGE($D$17:$H$17) -> 0.23678369 | L17: =AVERAGE($D$17:$H$17) -> 0.23678369 | M17: =AVERAGE($D$17:$H$17) -> 0.23678369 | O17: Average
B18: Effective tax rate | D18: ='Free Cash Flow'!D14 -> 0.4 | E18: ='Free Cash Flow'!E14 -> 0.4 | F18: ='Free Cash Flow'!F14 -> 0.4 | G18: ='Free Cash Flow'!G14 -> 0.4 | H18: ='Free Cash Flow'!H14 -> 0.4 | I18: 0.4 | J18: 0.4 | K18: 0.4 | L18: 0.4 | M18: 0.4
B20: Balance Sheet
B21: NC-WC as % of sales | D21: ='Balance Sheet'!D46/'Income Statement'!D7 -> 0.2951151 | E21: ='Balance Sheet'!E46/'Income Statement'!E7 -> 0.27081091 | F21: ='Balance Sheet'!F46/'Income Statement'!F7 -> 0.25676205 | G21: ='Balance Sheet'!G46/'Income Statement'!G7 -> 0.25282874 | H21: ='Balance Sheet'!H46/'Income Statement'!H7 -> 0.26786993 | I21: =AVERAGE($D$21:$H$21) -> 0.26867735 | J21: =AVERAGE($D$21:$H$21) -> 0.26867735 | K21: =AVERAGE($D$21:$H$21) -> 0.26867735 | L21: =AVERAGE($D$21:$H$21) -> 0.26867735 | M21: =AVERAGE($D$21:$H$21) -> 0.26867735 | O21: Average
B23: Cash Flow Statement
B24: D&A growth rate | D24: NA | E24: ='Cash Flow Statement'!E7/'Cash Flow Statement'!D7-1 -> 0.020540815 | F24: ='Cash Flow Statement'!F7/'Cash Flow Statement'!E7-1 -> 0.10783096 | G24: ='Cash Flow Statement'!G7/'Cash Flow Statement'!F7-1 -> 0.21806205 | H24: ='Cash Flow Statement'!H7/'Cash Flow Statement'!G7-1 -> 0.085631207 | I24: =AVERAGE($E$24:$H$24) -> 0.10801626 | J24: =AVERAGE($E$24:$H$24) -> 0.10801626 | K24: =AVERAGE($E$24:$H$24) -> 0.10801626 | L24: =AVERAGE($E$24:$H$24) -> 0.10801626 | M24: =AVERAGE($E$24:$H$24) -> 0.10801626 | O24: Average
B26: PPE as % of sales | D26: =-'Cash Flow Statement'!D9/'Income Statement'!D7 -> 0.11556208 | E26: =-'Cash Flow Statement'!E9/'Income Statement'!E7 -> 0.11940385 | F26: =-'Cash Flow Statement'!F9/'Income Statement'!F7 -> 0.14791234 | G26: =-'Cash Flow Statement'!G9/'Income Statement'!G7 -> 0.16923048 | H26: =-'Cash Flow Statement'!H9/'Income Statement'!H7 -> 0.1635285 | I26: =AVERAGE($D$26:$F$26) -> 0.12762609 | J26: =AVERAGE($D$26:$F$26) -> 0.12762609 | K26: =AVERAGE($D$26:$F$26) -> 0.12762609 | L26: =AVERAGE($D$26:$F$26) -> 0.12762609 | M26: =AVERAGE($D$26:$F$26) -> 0.12762609 | O26: Average of the 3 years before plant issues
B27: Acquisition as % of sales | D27: =-'Cash Flow Statement'!D10/'Income Statement'!D7 -> 0.19704621 | E27: =-'Cash Flow Statement'!E10/'Income Statement'!E7 -> 0.099039325 | F27: =-'Cash Flow Statement'!F10/'Income Statement'!F7 -> 0.0040992838 | G27: =-'Cash Flow Statement'!G10/'Income Statement'!G7 -> 0.013128979 | H27: =-'Cash Flow Statement'!H10/'Income Statement'!H7 -> 0 | I27: =AVERAGE($D$27:$H$27) -> 0.06266276 | J27: =AVERAGE($D$27:$H$27) -> 0.06266276 | K27: =AVERAGE($D$27:$H$27) -> 0.06266276 | L27: =AVERAGE($D$27:$H$27) -> 0.06266276 | M27: =AVERAGE($D$27:$H$27) -> 0.06266276 | O27: Average
B28: Capex as % of sales | D28: =SUM(D26,D27) -> 0.31260829 | E28: =SUM(E26,E27) -> 0.21844317 | F28: =SUM(F26,F27) -> 0.15201162 | G28: =SUM(G26,G27) -> 0.18235946 | H28: =SUM(H26,H27) -> 0.1635285 | I28: =SUM(I26:I27) -> 0.19028885 | J28: =SUM(J26:J27) -> 0.19028885 | K28: =SUM(K26:K27) -> 0.19028885 | L28: =SUM(L26:L27) -> 0.19028885 | M28: =SUM(M26:M27) -> 0.19028885
B29: Figure 3: Table of assumptions for Genzyme
B31: Value of Control estimate - Assumptions remain the same but costs are adjusted with the peer group
B33: Income statement
B34: Sales growth | D34: NA | E34: 0.19753662 | F34: 0.16837287 | G34: -0.032140058 | H34: 0.022970086 | I34: 0.1 | J34: 0.15 | K34: 0.2 | L34: 0.25 | M34: 0.3
B35: Service sales growth | D35: NA | E35: 0.15670039 | F35: -0.86084468 | G35: 0.030984365 | H35: -0.032552278 | I35: 0 | J35: 0 | K35: 0 | L35: 0 | M35: 0
B36: R&D revenue growth | D36: NA | E36: 0.68220291 | F36: 0.42923678 | G36: -0.51613901 | H36: -0.82941697 | I36: 0.45400699 | J36: 0.45400699 | K36: 0.45400699 | L36: 0.45400699 | M36: 0.45400699
B37: COGS as % of sales | D37: 0.18576793 | E37: 0.20692595 | F37: 0.20443993 | G37: 0.26602984 | H37: 0.28842622 | I37: ='Value of Control Inputs'!J18 -> 0.1913503 | J37: =$I$37 -> 0.1913503 | K37: =$I$37 -> 0.1913503 | L37: =$I$37 -> 0.1913503 | M37: =$I$37 -> 0.1913503
B38: COSS as % of service sales | D38: 0.70638173 | E38: 0.64912388 | F38: 0.64263378 | G38: 0.6436978 | H38: 0.83569205 | I38: 0 | J38: =$I$38 -> 0 | K38: =$I$38 -> 0 | L38: =$I$38 -> 0 | M38: =$I$38 -> 0
B39: SG&A as % of sales | D39: 0.34993311 | E39: 0.34333725 | F39: 0.29027415 | G39: 0.31824986 | H39: 0.38848559 | I39: ='Value of Control Inputs'!J19 -> 0.24242311 | J39: =$I$39 -> 0.24242311 | K39: =$I$39 -> 0.24242311 | L39: =$I$39 -> 0.24242311 | M39: =$I$39 -> 0.24242311
B40: R&D as % of sales | D40: 0.22509835 | E40: 0.21334076 | F40: 0.32040082 | G40: 0.2132546 | H40: 0.21182391 | I40: ='Value of Control Inputs'!J20 -> 0.15417477 | J40: =$I$40 -> 0.15417477 | K40: =$I$40 -> 0.15417477 | L40: =$I$40 -> 0.15417477 | M40: =$I$40 -> 0.15417477
B41: Effective tax rate | D41: 0.4 | E41: 0.4 | F41: 0.4 | G41: 0.4 | H41: 0.4 | I41: 0.4 | J41: 0.4 | K41: 0.4 | L41: 0.4 | M41: 0.4
B43: Balance Sheet
B44: NC-WC as % of sales | D44: 0.2951151 | E44: 0.27081091 | F44: 0.25676205 | G44: 0.25282874 | H44: 0.26786993 | I44: ='Value of Control Inputs'!$J$10 -> 0.034286305 | J44: ='Value of Control Inputs'!$J$10 -> 0.034286305 | K44: ='Value of Control Inputs'!$J$10 -> 0.034286305 | L44: ='Value of Control Inputs'!$J$10 -> 0.034286305 | M44: ='Value of Control Inputs'!$J$10 -> 0.034286305
O45: need time to liquidate invetories for example. So NC-WC decreases to reach the target value
B46: Cash Flow Statement
B47: D&A growth rate | D47: NA | E47: 0.020540815 | F47: 0.10783096 | G47: 0.21806205 | H47: 0.085631207 | I47: 0.142 | J47: 0.142 | K47: 0.142 | L47: 0.142 | M47: 0.142
B49: PPE as % of sales | D49: 0.11556208 | E49: 0.11940385 | F49: 0.14791234 | G49: 0.16923048 | H49: 0.1635285 | I49: ='Value of Control Inputs'!$B$57 -> 0.25373779 | J49: ='Value of Control Inputs'!$B$57 -> 0.25373779 | K49: ='Value of Control Inputs'!$B$57 -> 0.25373779 | L49: ='Value of Control Inputs'!$B$57 -> 0.25373779 | M49: ='Value of Control Inputs'!$B$57 -> 0.25373779 | P49: =(25-1.3)/4 -> 5.925
B50: Acquisition as % of sales | D50: 0.19704621 | E50: 0.099039325 | F50: 0.0040992838 | G50: 0.013128979 | H50: 0 | I50: 0 | J50: 0 | K50: 0 | L50: 0 | M50: 0
B51: Capex as % of sales | D51: 0.31260829 | E51: 0.21844317 | F51: 0.15201162 | G51: 0.18235946 | H51: 0.1635285 | I51: =SUM(I49:I50) -> 0.25373779 | J51: =SUM(J49:J50) -> 0.25373779 | K51: =SUM(K49:K50) -> 0.25373779 | L51: =SUM(L49:L50) -> 0.25373779 | M51: =SUM(M49:M50) -> 0.25373779

Sheet Value of Control Inputs
A1: $ million
B2: Amgen | C2: Celgen | D2: Biogen | E2: Baxter | F2: Gilead | G2: Average | H2: Minimum | I2: 25th percentile | J2: Median | K2: 75th percentile | L2: Maximum | M2: Genzyme
A3: 2010
A4: Income statement
A5: COGS as % of sales | B5: 0.14747891 | C5: 0.084540143 | D5: NA | E5: 0.49862132 | F5: 0.23522169 | G5: =AVERAGE(B5:F5) -> 0.24146552 | H5: =MIN(B5:F5) -> 0.084540143 | I5: =_xlfn.QUARTILE.INC(B5:F5,1) -> 0.13174422 | J5: =MEDIAN(B5:F5) -> 0.1913503 | K5: =_xlfn.QUARTILE.INC(B5:F5,3) -> 0.3010716 | L5: =MAX(B5:F5) -> 0.49862132 | M5: 0.28842622
A6: SG&A as % of sales | B6: 0.26459842 | C6: 0.26218998 | D6: NA | E6: 0.22265625 | F6: 0.1281106 | G6: =AVERAGE(B6:F6) -> 0.21938881 | H6: =MIN(B6:F6) -> 0.1281106 | I6: =_xlfn.QUARTILE.INC(B6:F6,1) -> 0.19901984 | J6: =MEDIAN(B6:F6) -> 0.24242311 | K6: =_xlfn.QUARTILE.INC(B6:F6,3) -> 0.26279209 | L6: =MAX(B6:F6) -> 0.26459842 | M6: 0.38848559
A7: R&D as % of sales | B7: 0.19225404 | C7: 0.311245 | D7: NA | E7: 0.067478554 | F7: 0.11609551 | G7: =AVERAGE(B7:F7) -> 0.17176828 | H7: =MIN(B7:F7) -> 0.067478554 | I7: =_xlfn.QUARTILE.INC(B7:F7,1) -> 0.10394127 | J7: =MEDIAN(B7:F7) -> 0.15417477 | K7: =_xlfn.QUARTILE.INC(B7:F7,3) -> 0.22200178 | L7: =MAX(B7:F7) -> 0.311245 | M7: 0.21182391
A9: Balance Sheet
A10: NC-WC as % of sales | B10: 0.072875839 | C10: -0.089978198 | D10: NA | E10: 0.017463235 | F10: 0.051109375 | G10: =AVERAGE(B10:F10) -> 0.012867563 | H10: =MIN(B10:F10) -> -0.089978198 | I10: =_xlfn.QUARTILE.INC(B10:F10,1) -> -0.0093971229 | J10: =MEDIAN(B10:F10) -> 0.034286305 | K10: =_xlfn.QUARTILE.INC(B10:F10,3) -> 0.056550991 | L10: =MAX(B10:F10) -> 0.072875839 | M10: 0.26786993
A12: Cash Flow Statement
A13: PPE as % of sales | B13: 0.36683718 | C13: 0.14063841 | D13: NA | E13: 0.4028799 | F13: 0.088212096 | G13: =AVERAGE(B13:F13) -> 0.24964189 | H13: =MIN(B13:F13) -> 0.088212096 | I13: =_xlfn.QUARTILE.INC(B13:F13,1) -> 0.12753183 | J13: =MEDIAN(B13:F13) -> 0.25373779 | K13: =_xlfn.QUARTILE.INC(B13:F13,3) -> 0.37584786 | L13: =MAX(B13:F13) -> 0.4028799 | M13: 0.1635285
A14: Acquisition as % of sales* | B14: 0.11777227 | C14: 0.89595325 | D14: NA | E14: 0.038296569 | F14: 0 | G14: =AVERAGE(B14:F14) -> 0.26300552 | H14: =MIN(B14:F14) -> 0 | I14: =_xlfn.QUARTILE.INC(B14:F14,1) -> 0.028722426 | J14: =MEDIAN(B14:F14) -> 0.07803442 | K14: =_xlfn.QUARTILE.INC(B14:F14,3) -> 0.31231751 | L14: =MAX(B14:F14) -> 0.89595325 | M14: 0
A15: Capex as % of sales | B15: =SUM(B13:B14) -> 0.48460945 | C15: =SUM(C13:C14) -> 1.0365917 | D15: NA | E15: =SUM(E13:E14) -> 0.44117647 | F15: =SUM(F13:F14) -> 0.088212096 | G15: =AVERAGE(B15:F15) -> 0.51264742 | H15: =MIN(B15:F15) -> 0.088212096 | I15: =_xlfn.QUARTILE.INC(B15:F15,1) -> 0.35293538 | J15: =MEDIAN(B15:F15) -> 0.46289296 | K15: =_xlfn.QUARTILE.INC(B15:F15,3) -> 0.622605 | L15: =MAX(B15:F15) -> 1.0365917 | M15: =SUM(M13:M14) -> 0.1635285
A17: *other intangible assets | G17: 2010 | H17: Minimum | I17: 25th percentile | J17: Median | K17: 75th percentile | L17: Maximum | M17: Genzyme
G18: COGS as % of sales | H18: 0.084540143 | I18: 0.13174422 | J18: 0.1913503 | K18: 0.3010716 | L18: 0.49862132 | M18: 0.28842622
G19: SG&A as % of sales | H19: 0.1281106 | I19: 0.19901984 | J19: 0.24242311 | K19: 0.26279209 | L19: 0.26459842 | M19: 0.38848559
G20: R&D as % of sales | H20: 0.067478554 | I20: 0.10394127 | J20: 0.15417477 | K20: 0.22200178 | L20: 0.311245 | M20: 0.21182391
G21: NC-WC as % of sales | H21: -0.089978198 | I21: -0.0093971229 | J21: 0.034286305 | K21: 0.056550991 | L21: 0.072875839 | M21: 0.26786993
G22: PPE as % of sales | H22: 0.088212096 | I22: 0.12753183 | J22: 0.25373779 | K22: 0.37584786 | L22: 0.4028799 | M22: 0.1635285
G23: % margin | H23: 0.21124387 | I23: 0.30932963 | J23: 0.36884676 | K23: 0.42689453 | L23: 0.52057219 | M23: 0.11
G24: Acquisition as % of sales* | H24: 0 | I24: 0.028722426 | J24: 0.07803442 | K24: 0.31231751 | L24: 0.89595325 | M24: 0
G25: Capex as % of sales | H25: 0.088212096 | I25: 0.35293538 | J25: 0.46289296 | K25: 0.622605 | L25: 1.0365917 | M25: =SUM(M22:M24) -> 0.2735285
G27: 2010 | H27: Minimum | I27: 25th percentile | J27: Median | K27: 75th percentile | L27: Maximum
G28: COGS as % of sales | H28: =H5 -> 0.084540143 | I28: =I5-H5 -> 0.047204074 | J28: =J5-I5 -> 0.059606082 | K28: =K5-J5 -> 0.1097213 | L28: =L5-K5 -> 0.19754973
G29: SG&A as % of sales | H29: =H6 -> 0.1281106 | I29: =I6-H6 -> 0.070909234 | J29: =J6-I6 -> 0.043403275 | K29: =K6-J6 -> 0.020368974 | L29: =L6-K6 -> 0.0018063311
G30: R&D as % of sales | H30: =H7 -> 0.067478554 | I30: =I7-H7 -> 0.03646272 | J30: =J7-I7 -> 0.050233501 | K30: =K7-J7 -> 0.067827002 | L30: =L7-K7 -> 0.089243223
G31: NC-WC as % of sales | H31: =H10 -> -0.089978198 | I31: =I10-H10 -> 0.080581075 | J31: =J10-I10 -> 0.043683428 | K31: =K10-J10 -> 0.022264686 | L31: =L10-K10 -> 0.016324848
G32: PPE as % of sales | H32: =H13 -> 0.088212096 | I32: =I13-H13 -> 0.039319733 | J32: =J13-I13 -> 0.12620596 | K32: =K13-J13 -> 0.12211007 | L32: =L13-K13 -> 0.027032045
G33: Acquisition as % of sales* | H33: =H14 -> 0 | I33: =I14-H14 -> 0.028722426 | J33: =J14-I14 -> 0.049311993 | K33: =K14-J14 -> 0.23428309 | L33: =L14-K14 -> 0.58363573
G34: Capex as % of sales | H34: =H15 -> 0.088212096 | I34: =I15-H15 -> 0.26472328 | J34: =J15-I15 -> 0.10995758 | K34: =K15-J15 -> 0.15971204 | L34: =L15-K15 -> 0.41398665
A38: 2010 | B38: Amgen | C38: Celgen | D38: Baxter | E38: Gilead | F38: Moyenne | G38: Minimum | H38: 25th percentile | I38: Median | J38: 75th percentile | K38: Maximum | L38: Genzyme
A39: Revenues | B39: 15053 | C39: 3625.745 | D39: 13056 | E39: 7949.42 | F39: =AVERAGE(B39:E39) -> 9921.0413 | G39: =MIN(B39:E39) -> 3625.745 | H39: =_xlfn.QUARTILE.INC(B39:E39,1) -> 6868.5013 | I39: =MEDIAN(B39:E39) -> 10502.71 | J39: =_xlfn.QUARTILE.INC(B39:E39,3) -> 13555.25 | K39: =MAX(B39:E39) -> 15053 | L39: 4048.708
A40: COGS | B40: 2220 | C40: 306.521 | D40: 6510 | E40: 1869.876 | F40: =AVERAGE(B40:E40) -> 2726.5993 | G40: =MIN(B40:E40) -> 306.521 | H40: =_xlfn.QUARTILE.INC(B40:E40,1) -> 1479.0373 | I40: =MEDIAN(B40:E40) -> 2044.938 | J40: =_xlfn.QUARTILE.INC(B40:E40,3) -> 3292.5 | K40: =MAX(B40:E40) -> 6510 | L40: 1185.1905
A41: SG&A | B41: 3983 | C41: 950.634 | D41: 2907 | E41: 1018.405 | F41: =AVERAGE(B41:E41) -> 2214.7598 | G41: =MIN(B41:E41) -> 950.634 | H41: =_xlfn.QUARTILE.INC(B41:E41,1) -> 1001.4623 | I41: =MEDIAN(B41:E41) -> 1962.7025 | J41: =_xlfn.QUARTILE.INC(B41:E41,3) -> 3176 | K41: =MAX(B41:E41) -> 3983 | L41: 1553.921 | N41: Figure 19: List of cost structure comparables minimum and maximum
A42: R&D | B42: 2894 | C42: 1128.495 | D42: 881 | E42: 922.892 | F42: =AVERAGE(B42:E42) -> 1456.5967 | G42: =MIN(B42:E42) -> 881 | H42: =_xlfn.QUARTILE.INC(B42:E42,1) -> 912.419 | I42: =MEDIAN(B42:E42) -> 1025.6935 | J42: =_xlfn.QUARTILE.INC(B42:E42,3) -> 1569.8712 | K42: =MAX(B42:E42) -> 2894 | L42: 847.284
A43: EBIDTA | B43: =B39-B40-B41-B42 -> 5956 | C43: =C39-C40-C41-C42 -> 1240.095 | D43: =D39-D40-D41-D42 -> 2758 | E43: =E39-E40-E41-E42 -> 4138.247 | F43: =AVERAGE(B43:E43) -> 3523.0855 | G43: =MIN(B43:E43) -> 1240.095 | H43: =_xlfn.QUARTILE.INC(B43:E43,1) -> 2378.5237 | I43: =MEDIAN(B43:E43) -> 3448.1235 | J43: =_xlfn.QUARTILE.INC(B43:E43,3) -> 4592.6853 | K43: =MAX(B43:E43) -> 5956 | L43: 455.963
A44: % margin | B44: =B43/B39 -> 0.39566864 | C44: =C43/C39 -> 0.34202488 | D44: =D43/D39 -> 0.21124387 | E44: =E43/E39 -> 0.52057219 | F44: =AVERAGE(B44:E44) -> 0.3673774 | G44: =MIN(B44:E44) -> 0.21124387 | H44: =_xlfn.QUARTILE.INC(B44:E44,1) -> 0.30932963 | I44: =MEDIAN(B44:E44) -> 0.36884676 | J44: =_xlfn.QUARTILE.INC(B44:E44,3) -> 0.42689453 | K44: =MAX(B44:E44) -> 0.52057219 | L44: 0.11261938
A46: D&A* | B46: 294 | C46: 203.231 | D46: -431 | E46: 0 | F46: =AVERAGE(B46:E46) -> 16.55775 | G46: =MIN(B46:E46) -> -431 | H46: =_xlfn.QUARTILE.INC(B46:E46,1) -> -107.75 | I46: =MEDIAN(B46:E46) -> 101.6155 | J46: =_xlfn.QUARTILE.INC(B46:E46,3) -> 225.92325 | K46: =MAX(B46:E46) -> 294 | L46: 495.443
A47: EBIT | B47: =B43-B46 -> 5662 | C47: =C43-C46 -> 1036.864 | D47: =D43-D46 -> 3189 | E47: =E43-E46 -> 4138.247 | F47: =AVERAGE(B47:E47) -> 3506.5278 | G47: =MIN(B47:E47) -> 1036.864 | H47: =_xlfn.QUARTILE.INC(B47:E47,1) -> 2650.966 | I47: =MEDIAN(B47:E47) -> 3663.6235 | J47: =_xlfn.QUARTILE.INC(B47:E47,3) -> 4519.1853 | K47: =MAX(B47:E47) -> 5662 | L47: -39.48
A48: % margin | B48: =B47/B39 -> 0.37613765 | C48: =C47/C39 -> 0.28597268 | D48: =D47/D39 -> 0.24425551 | E48: =E47/E39 -> 0.52057219
A50: *from Income Statement
A52: Key target inputs | B52: 2010 | C52: Genzyme
A53: COGS as % of sales | B53: 0.1913503 | C53: 0.28842622
A54: SG&A as % of sales | B54: 0.24242311 | C54: 0.38848559
A55: R&D as % of sales | B55: 0.15417477 | C55: 0.21182391
A56: NC-WC as % of sales | B56: 0.034286305 | C56: 0.26786993
A57: PPE as % of sales | B57: 0.25373779 | C57: 0.1635285 | G57: 2011 | H57: 2012 | I57: 2013 | J57: 2014 | K57: 2015
A58: EBITDA margin | B58: 0.36884676 | C58: 0.11 | D58: EBIDTA margin projected | G58: =IF(Assumption!$H$2=Assumption!$S$2,'Income Statement'!I15,"N/A") -> N/A | H58: =IF(Assumption!$H$2=Assumption!$S$2,'Income Statement'!J15,"N/A") -> N/A | I58: =IF(Assumption!$H$2=Assumption!$S$2,'Income Statement'!K15,"N/A") -> N/A | J58: =IF(Assumption!$H$2=Assumption!$S$2,'Income Statement'!L15,"N/A") -> N/A | K58: =IF(Assumption!$H$2=Assumption!$S$2,'Income Statement'!M15,"N/A") -> N/A
A59: Figure 20: Value of Control target Inputs | G59: =IF(AND(0.35<G58,G58<0.43),"ok!","N/A") -> N/A | H59: =IF(AND(0.35<H58,H58<0.43),"ok!","N/A") -> N/A | I59: =IF(AND(0.35<I58,I58<0.43),"ok!","N/A") -> N/A | J59: =IF(AND(0.35<J58,J58<0.43),"ok!","N/A") -> N/A | K59: =IF(AND(0.35<K58,K58<0.43),"ok!","N/A") -> N/A

Sheet Balance Sheet
A1: Project EBS
A2: Balance Sheet | D2: Actual | F2: Projections
A3: $thousands | D3: 2006 | E3: 2007 | F3: 2008 | G3: 2009 | H3: 2010 | I3: 2011 | J3: 2012 | K3: 2013 | L3: 2014 | M3: 2015
B5: Assets
B7: Cash & cash equivalents | D7: 492170 | E7: 867012 | F7: 572106 | G7: 742246 | H7: 1331112
B8: Inventory | D8: 374644 | E8: 439115 | F8: 453437 | G8: 608022 | H8: 586940
B9: Accounts receivable | D9: 746746 | E9: 904101 | F9: 1036940 | G9: 899731 | H9: 1089688
B10: Other current assets | D10: 375941 | E10: 398969 | F10: 453652 | G10: 552804 | H10: 693218
B11: Total current assets | D11: =SUM(D7:D10) -> 1989501 | E11: =SUM(E7:E10) -> 2609197 | F11: =SUM(F7:F10) -> 2516135 | G11: =SUM(G7:G10) -> 2802803 | H11: =SUM(H7:H10) -> 3700958
B13: PP&E | D13: 1610593 | E13: 1968402 | F13: 2306567 | G13: 2809349 | H13: 2925584
B14: Goodwill | D14: 1298781 | E14: 1403828 | F14: 1401074 | G14: 1403363 | H14: 1360978
B15: Other fixed assets | D15: 2292313 | E15: 2320314 | F15: 2447500 | G15: 3045209 | H15: 2926334
B16: Total fixed assets | D16: =SUM(D13:D15) -> 5201687 | E16: =SUM(E13:E15) -> 5692544 | F16: =SUM(F13:F15) -> 6155141 | G16: =SUM(G13:G15) -> 7257921 | H16: =SUM(H13:H15) -> 7212896
B18: Assets held for sale of exchange | D18: 0 | E18: 0 | F18: 0 | G18: 0 | H18: 0
B19: Total assets | D19: =D11+D16+D18 -> 7191188 | E19: =E11+E16+E18 -> 8301741 | F19: =F11+F16+F18 -> 8671276 | G19: =G11+G16+G18 -> 10060724 | H19: =H11+H16+H18 -> 10913854
B21: Equity and Liabilities
B23: Accounts payable | D23: 98063 | E23: 128380 | F23: 127869 | G23: 189629 | H23: 132327
B24: Current portion of long-term debt and capital lease obligations | D24: 6226 | E24: 696625 | F24: 7566 | G24: 8166 | H24: 7584
B25: Other current liabilities | D25: 547150 | E25: 677401 | F25: 778848 | G25: 882335 | H25: 1166054
B26: Total current libailities | D26: =SUM(D23:D25) -> 651439 | E26: =SUM(E23:E25) -> 1502406 | F26: =SUM(F23:F25) -> 914283 | G26: =SUM(G23:G25) -> 1080130 | H26: =SUM(H23:H25) -> 1305965
B28: Long-term debt and capital lease obligations | D28: 119803 | E28: 113748 | F28: 124341 | G28: 116434 | H28: 1098956
B29: Long-term contingent consideration obligations | D29: 0 | E29: 0 | F29: 0 | G29: 853871 | H29: 803253
B30: Other non-current liabilities | D30: 759235 | E30: 72650 | F30: 326659 | G30: 326637 | H30: 118707
B31: Total liabilities | D31: =D26+SUM(D28:D30) -> 1530477 | E31: =E26+SUM(E28:E30) -> 1688804 | F31: =F26+SUM(F28:F30) -> 1365283 | G31: =G26+SUM(G28:G30) -> 2377072 | H31: =H26+SUM(H28:H30) -> 3326881
B33: Total stockholders’ equity | D33: 5660711 | E33: 6612937 | F33: 7305993 | G33: 7683652 | H33: 7586973
B34: Total equity | D34: =SUM(D33:D33) -> 5660711 | E34: =SUM(E33:E33) -> 6612937 | F34: =SUM(F33:F33) -> 7305993 | G34: =SUM(G33:G33) -> 7683652 | H34: =SUM(H33:H33) -> 7586973
B36: Liabilities related to assets held for sale or exchange | D36: 0 | E36: 0 | F36: 0 | G36: 0 | H36: 0
B37: Total equity and liabilities | D37: =D31+D34+D36 -> 7191188 | E37: =E31+E34+E36 -> 8301741 | F37: =F31+F34+F36 -> 8671276 | G37: =G31+G34+G36 -> 10060724 | H37: =H31+H34+H36 -> 10913854
B38: check | D38: =IF(ROUND(D37-D19,1)=0,"ok!",D37-D19) -> ok! | E38: =IF(ROUND(E37-E19,1)=0,"ok!",E37-E19) -> ok! | F38: =IF(ROUND(F37-F19,1)=0,"ok!",F37-F19) -> ok! | G38: =IF(ROUND(G37-G19,1)=0,"ok!",G37-G19) -> ok! | H38: =IF(ROUND(H37-H19,1)=0,"ok!",H37-H19) -> ok!
B41: Operating Working Capital | C41: 2005 | D41: 2006 | E41: 2007 | F41: 2008 | G41: 2009 | H41: 2010 | I41: 2011 | J41: 2012 | K41: 2013 | L41: 2014 | M41: 2015
B42: Total current assets | C42: 1664999 | D42: =D11 -> 1989501 | E42: =E11 -> 2609197 | F42: =F11 -> 2516135 | G42: =G11 -> 2802803 | H42: =H11 -> 3700958
B43: - Cash and Cash equivalents | C43: 291960 | D43: =D7 -> 492170 | E43: =E7 -> 867012 | F43: =F7 -> 572106 | G43: =G7 -> 742246 | H43: =H7 -> 1331112
B44: -Total curent liabilities | C44: 550023 | D44: =D26 -> 651439 | E44: =E26 -> 1502406 | F44: =F26 -> 914283 | G44: =G26 -> 1080130 | H44: =H26 -> 1305965
B45: + Short-term debt and current portion of long-term debt | C45: 4461 | D45: =D24 -> 6226 | E45: =E24 -> 696625 | F45: =F24 -> 7566 | G45: =G24 -> 8166 | H45: =H24 -> 7584
B46: NET NON-CASH WORKING CAPITAL | C46: =C42-C43-C44+C45 -> 827477 | D46: =D42-D43-D44+D45 -> 852118 | E46: =E42-E43-E44+E45 -> 936404 | F46: =F42-F43-F44+F45 -> 1037312 | G46: =G42-G43-G44+G45 -> 988593 | H46: =H42-H43-H44+H45 -> 1071465 | I46: =IF(Assumption!$H$2=Assumption!$S$1,Assumption!I21*'Income Statement'!I7,IF(Assumption!$H$2=Assumption!$S$2,'Income Statement'!I7*Assumption!I44,Assumption!#REF!*'Income Statement'!I7)) -> 1182164.1 | J46: =IF(Assumption!$H$2=Assumption!$S$1,Assumption!J21*'Income Statement'!J7,IF(Assumption!$H$2=Assumption!$S$2,'Income Statement'!J7*Assumption!J44,Assumption!#REF!*'Income Statement'!J7)) -> 1359488.7 | K46: =IF(Assumption!$H$2=Assumption!$S$1,Assumption!K21*'Income Statement'!K7,IF(Assumption!$H$2=Assumption!$S$2,'Income Statement'!K7*Assumption!K44,Assumption!#REF!*'Income Statement'!K7)) -> 1631386.4 | L46: =IF(Assumption!$H$2=Assumption!$S$1,Assumption!L21*'Income Statement'!L7,IF(Assumption!$H$2=Assumption!$S$2,'Income Statement'!L7*Assumption!L44,Assumption!#REF!*'Income Statement'!L7)) -> 2039233 | M46: =IF(Assumption!$H$2=Assumption!$S$1,Assumption!M21*'Income Statement'!M7,IF(Assumption!$H$2=Assumption!$S$2,'Income Statement'!M7*Assumption!M44,Assumption!#REF!*'Income Statement'!M7)) -> 2651002.9
B48: Δ NET NON-CASH WORKING CAPITAL | D48: =D46-C46 -> 24641 | E48: =E46-D46 -> 84286 | F48: =F46-E46 -> 100908 | G48: =G46-F46 -> -48719 | H48: =H46-G46 -> 82872 | I48: =I46-H46 -> 110699.07 | J48: =J46-I46 -> 177324.61 | K48: =K46-J46 -> 271897.74 | ... M48: =M46-L46 -> 611769.91

Sheet Income Statement
A1: Project EBS
A2: Income Statement | D2: Actual | F2: Projections
A3: $thousands | D3: 2006 | E3: 2007 | F3: 2008 | G3: 2009 | H3: 2010 | I3: 2011 | J3: 2012 | K3: 2013 | L3: 2014 | M3: 2015
B5: Income Statement
B7: Sales | D7: 2887409 | E7: 3457778 | F7: 4039974 | G7: 3910129 | H7: 3999945 | I7: =IF(Assumption!$H$2=Assumption!$S$1,H7*(1+Assumption!I11),IF(Assumption!$H$2=Assumption!$S$2,'Income Statement'!H7*(1+Assumption!I34),'Income Statement'!H7*(1+Assumption!#REF!))) -> 4399939.5 | J7: =IF(Assumption!$H$2=Assumption!$S$1,I7*(1+Assumption!J11),IF(Assumption!$H$2=Assumption!$S$2,'Income Statement'!I7*(1+Assumption!J34),'Income Statement'!I7*(1+Assumption!#REF!))) -> 5059930.4 | K7: =IF(Assumption!$H$2=Assumption!$S$1,J7*(1+Assumption!K11),IF(Assumption!$H$2=Assumption!$S$2,'Income Statement'!J7*(1+Assumption!K34),'Income Statement'!J7*(1+Assumption!#REF!))) -> 6071916.5 | L7: =IF(Assumption!$H$2=Assumption!$S$1,K7*(1+Assumption!L11),IF(Assumption!$H$2=Assumption!$S$2,'Income Statement'!K7*(1+Assumption!L34),'Income Statement'!K7*(1+Assumption!#REF!))) -> 7589895.6 | M7: =IF(Assumption!$H$2=Assumption!$S$1,L7*(1+Assumption!M11),IF(Assumption!$H$2=Assumption!$S$2,'Income Statement'!L7*(1+Assumption!M34),'Income Statement'!L7*(1+Assumption!#REF!))) -> 9866864.3
B8: Net service sales | D8: 282118 | E8: 326326 | F8: 45410 | G8: 46817 | H8: 45293 | I8: =IF(Assumption!$H$2=Assumption!$S$1,H8*(1+Assumption!I12),IF(Assumption!$H$2=Assumption!$S$2,'Income Statement'!H8*(1+Assumption!I35),'Income Statement'!H8*(1+Assumption!#REF!))) -> 45293 | J8: =IF(Assumption!$H$2=Assumption!$S$1,I8*(1+Assumption!J12),IF(Assumption!$H$2=Assumption!$S$2,'Income Statement'!I8*(1+Assumption!J35),'Income Statement'!I8*(1+Assumption!#REF!))) -> 45293 | K8: =IF(Assumption!$H$2=Assumption!$S$1,J8*(1+Assumption!K12),IF(Assumption!$H$2=Assumption!$S$2,'Income Statement'!J8*(1+Assumption!K35),'Income Statement'!J8*(1+Assumption!#REF!))) -> 45293 | L8: =IF(Assumption!$H$2=Assumption!$S$1,K8*(1+Assumption!L12),IF(Assumption!$H$2=Assumption!$S$2,'Income Statement'!K8*(1+Assumption!L35),'Income Statement'!K8*(1+Assumption!#REF!))) -> 45293 | M8: =IF(Assumption!$H$2=Assumption!$S$1,L8*(1+Assumption!M12),IF(Assumption!$H$2=Assumption!$S$2,'Income Statement'!L8*(1+Assumption!M35),'Income Statement'!L8*(1+Assumption!#REF!))) -> 45293
B9: R&D revenue | D9: 17486 | E9: 29415 | F9: 42041 | G9: 20342 | H9: 3470 | I9: =IF(Assumption!$H$2=Assumption!$S$1,H9*(1+Assumption!I13),IF(Assumption!$H$2=Assumption!$S$2,'Income Statement'!H9*(1+Assumption!I36),'Income Statement'!H9*(1+Assumption!I54))) -> 5045.4043 | J9: =IF(Assumption!$H$2=Assumption!$S$1,I9*(1+Assumption!J13),IF(Assumption!$H$2=Assumption!$S$2,'Income Statement'!I9*(1+Assumption!J36),'Income Statement'!I9*(1+Assumption!J54))) -> 7336.0531 | K9: =IF(Assumption!$H$2=Assumption!$S$1,J9*(1+Assumption!K13),IF(Assumption!$H$2=Assumption!$S$2,'Income Statement'!J9*(1+Assumption!K36),'Income Statement'!J9*(1+Assumption!K54))) -> 10666.673 | L9: =IF(Assumption!$H$2=Assumption!$S$1,K9*(1+Assumption!L13),IF(Assumption!$H$2=Assumption!$S$2,'Income Statement'!K9*(1+Assumption!L36),'Income Statement'!K9*(1+Assumption!L54))) -> 15509.416 | M9: =IF(Assumption!$H$2=Assumption!$S$1,L9*(1+Assumption!M13),IF(Assumption!$H$2=Assumption!$S$2,'Income Statement'!L9*(1+Assumption!M36),'Income Statement'!L9*(1+Assumption!M54))) -> 22550.8
B10: Cost of sales | D10: =-536388 -> -536388 | E10: -715504 | F10: -825932 | G10: -1040211 | H10: -1153689 | I10: =IF(Assumption!$H$2=Assumption!$S$1,-I$7*Assumption!I14,IF(Assumption!$H$2=Assumption!$S$2,-'Income Statement'!I$7*Assumption!I37,-'Income Statement'!I$7*Assumption!#REF!)) -> -875784.22 | J10: =IF(Assumption!$H$2=Assumption!$S$1,-J$7*Assumption!J14,IF(Assumption!$H$2=Assumption!$S$2,-'Income Statement'!J$7*Assumption!J37,-'Income Statement'!J$7*Assumption!#REF!)) -> -1007151.8 | K10: =IF(Assumption!$H$2=Assumption!$S$1,-K$7*Assumption!K14,IF(Assumption!$H$2=Assumption!$S$2,-'Income Statement'!K$7*Assumption!K37,-'Income Statement'!K$7*Assumption!#REF!)) -> -1208582.2 | L10: =IF(Assumption!$H$2=Assumption!$S$1,-L$7*Assumption!L14,IF(Assumption!$H$2=Assumption!$S$2,-'Income Statement'!L$7*Assumption!L37,-'Income Statement'!L$7*Assumption!#REF!)) -> -1510727.8 | M10: =IF(Assumption!$H$2=Assumption!$S$1,-M$7*Assumption!M14,IF(Assumption!$H$2=Assumption!$S$2,-'Income Statement'!M$7*Assumption!M37,-'Income Statement'!M$7*Assumption!#REF!)) -> -1963946.1
B11: Cost of services sold | D11: -199283 | E11: -211826 | F11: -29182 | G11: -30136 | H11: -37851 | I11: =IF(Assumption!$H$2=Assumption!$S$1,-I$8*Assumption!I15,IF(Assumption!$H$2=Assumption!$S$2,-'Income Statement'!I$8*Assumption!I38,-'Income Statement'!I$8*Assumption!#REF!)) -> -31501.546 | J11: =IF(Assumption!$H$2=Assumption!$S$1,-J$8*Assumption!J15,IF(Assumption!$H$2=Assumption!$S$2,-'Income Statement'!J$8*Assumption!J38,-'Income Statement'!J$8*Assumption!#REF!)) -> -31501.546 | K11: =IF(Assumption!$H$2=Assumption!$S$1,-K$8*Assumption!K15,IF(Assumption!$H$2=Assumption!$S$2,-'Income Statement'!K$8*Assumption!K38,-'Income Statement'!K$8*Assumption!#REF!)) -> -31501.546 | L11: =IF(Assumption!$H$2=Assumption!$S$1,-L$8*Assumption!L15,IF(Assumption!$H$2=Assumption!$S$2,-'Income Statement'!L$8*Assumption!L38,-'Income Statement'!L$8*Assumption!#REF!)) -> -31501.546 | M11: =IF(Assumption!$H$2=Assumption!$S$1,-M$8*Assumption!M15,IF(Assumption!$H$2=Assumption!$S$2,-'Income Statement'!M$8*Assumption!M38,-'Income Statement'!M$8*Assumption!#REF!)) -> -31501.546
B12: Selling, general & administrative | D12: -1010400 | E12: -1187184 | F12: -1172700 | G12: -1244398 | H12: -1553921 | I12: =IF(Assumption!$H$2=Assumption!$S$1,-I$7*Assumption!I16,IF(Assumption!$H$2=Assumption!$S$2,-'Income Statement'!I$7*Assumption!I39,-'Income Statement'!I$7*Assumption!#REF!)) -> -1442512.1 | J12: =IF(Assumption!$H$2=Assumption!$S$1,-J$7*Assumption!J16,IF(Assumption!$H$2=Assumption!$S$2,-'Income Statement'!J$7*Assumption!J39,-'Income Statement'!J$7*Assumption!#REF!)) -> -1658888.9 | K12: =IF(Assumption!$H$2=Assumption!$S$1,-K$7*Assumption!K16,IF(Assumption!$H$2=Assumption!$S$2,-'Income Statement'!K$7*Assumption!K39,-'Income Statement'!K$7*Assumption!#REF!)) -> -1990666.7 | L12: =IF(Assumption!$H$2=Assumption!$S$1,-L$7*Assumption!L16,IF(Assumption!$H$2=Assumption!$S$2,-'Income Statement'!L$7*Assumption!L39,-'Income Statement'!L$7*Assumption!#REF!)) -> -2488333.4 | M12: =IF(Assumption!$H$2=Assumption!$S$1,-M$7*Assumption!M16,IF(Assumption!$H$2=Assumption!$S$2,-'Income Statement'!M$7*Assumption!M39,-'Income Statement'!M$7*Assumption!#REF!)) -> -3234833.4
B13: R&D expenses | D13: -649951 | E13: -737685 | F13: -1294411 | G13: -833853 | H13: -847284 | I13: =IF(Assumption!$H$2=Assumption!$S$1,-I7*Assumption!I17,IF(Assumption!$H$2=Assumption!$S$2,-I7*Assumption!I40,-'Income Statement'!I7*Assumption!#REF!)) -> -1041833.9 | J13: =IF(Assumption!$H$2=Assumption!$S$1,-J7*Assumption!J17,IF(Assumption!$H$2=Assumption!$S$2,-J7*Assumption!J40,-'Income Statement'!J7*Assumption!#REF!)) -> -1198109 | K13: =IF(Assumption!$H$2=Assumption!$S$1,-K7*Assumption!K17,IF(Assumption!$H$2=Assumption!$S$2,-K7*Assumption!K40,-'Income Statement'!K7*Assumption!#REF!)) -> -1437730.8 | L13: =IF(Assumption!$H$2=Assumption!$S$1,-L7*Assumption!L17,IF(Assumption!$H$2=Assumption!$S$2,-L7*Assumption!L40,-'Income Statement'!L7*Assumption!#REF!)) -> -1797163.5 | M13: =IF(Assumption!$H$2=Assumption!$S$1,-M7*Assumption!M17,IF(Assumption!$H$2=Assumption!$S$2,-M7*Assumption!M40,-'Income Statement'!M7*Assumption!#REF!)) -> -2336312.5
B14: EBITDA | D14: =SUM(D7:D13) -> 790991 | E14: =SUM(E7:E13) -> 961320 | F14: =SUM(F7:F13) -> 805200 | G14: =SUM(G7:G13) -> 828690 | H14: =SUM(H7:H13) -> 455963 | I14: =SUM(I7:I13) -> 1058646.1 | J14: =SUM(J7:J13) -> 1216908.2 | K14: =SUM(K7:K13) -> 1459394.9 | ... M14: =SUM(M7:M13) -> 2368114.5
B15: % margin | D15: =D14/D7 -> 0.27394491 | E15: =E14/E7 -> 0.27801669 | F15: =F14/F7 -> 0.19930821 | G15: =G14/G7 -> 0.21193418 | H15: =H14/H7 -> 0.11399232 | I15: =I14/I7 -> 0.2406047 | J15: =J14/J7 -> 0.24049899 | K15: =K14/K7 -> 0.24035161 | ... M15: =M14/M7 -> 0.2400068
B17: Depreciation & amortization* | D17: -331389 | E17: -338196 | F17: -374664 | G17: -456364 | H17: -495443 | I17: =-'Cash Flow Statement'!I7 -> -548958.9 | J17: =-'Cash Flow Statement'!J7 -> -608255.39 | K17: =-'Cash Flow Statement'!K7 -> -673956.86 | L17: =-'Cash Flow Statement'!L7 -> -746755.15 | M17: =-'Cash Flow Statement'!M7 -> -827416.85
B18: EBIT | D18: =D14+D17 -> 459602 | E18: =E14+E17 -> 623124 | F18: =F14+F17 -> 430536 | G18: =G14+G17 -> 372326 | H18: =H14+H17 -> -39480 | I18: =I14+I17 -> 509687.23 | J18: =J14+J17 -> 608652.78 | K18: =K14+K17 -> 785438.06 | ... M18: =M14+M17 -> 1540697.7
B19: % margin | D19: =D18/D7 -> 0.15917454 | E19: =E18/E7 -> 0.18020937 | F19: =F18/F7 -> 0.106569 | G19: =G18/G7 -> 0.095220899 | H19: =H18/H7 -> -0.0098701357 | I19: =I18/I7 -> 0.1158396 | J19: =J18/J7 -> 0.12028876 | K19: =K18/K7 -> 0.12935587 | ... M19: =M18/M7 -> 0.15614866
B22: *from Cash Flow Statement in AR

Sheet Cash Flow Statement
A1: Project EBS
A2: Income Statement | D2: Actual | F2: Projections
A3: €m | D3: 2006 | E3: 2007 | F3: 2008 | G3: 2009 | H3: 2010 | I3: 2011 | J3: 2012 | K3: 2013 | L3: 2014 | M3: 2015
B5: Cash Flow Statement
B7: Depreciation & amortization | D7: =-'Income Statement'!D17 -> 331389 | E7: =-'Income Statement'!E17 -> 338196 | F7: =-'Income Statement'!F17 -> 374664 | G7: =-'Income Statement'!G17 -> 456364 | H7: =-'Income Statement'!H17 -> 495443 | I7: =IF(Assumption!$H$2=Assumption!$S$1,H7*(1+Assumption!I24),IF(Assumption!$H$2=Assumption!$S$2,'Cash Flow Statement'!H7*(1+Assumption!I47),'Cash Flow Statement'!H7*(1+Assumption!#REF!))) -> 548958.9 | J7: =IF(Assumption!$H$2=Assumption!$S$1,I7*(1+Assumption!J24),IF(Assumption!$H$2=Assumption!$S$2,'Cash Flow Statement'!I7*(1+Assumption!J47),'Cash Flow Statement'!I7*(1+Assumption!#REF!))) -> 608255.39 | K7: =IF(Assumption!$H$2=Assumption!$S$1,J7*(1+Assumption!K24),IF(Assumption!$H$2=Assumption!$S$2,'Cash Flow Statement'!J7*(1+Assumption!K47),'Cash Flow Statement'!J7*(1+Assumption!#REF!))) -> 673956.86 | L7: =IF(Assumption!$H$2=Assumption!$S$1,K7*(1+Assumption!L24),IF(Assumption!$H$2=Assumption!$S$2,'Cash Flow Statement'!K7*(1+Assumption!L47),'Cash Flow Statement'!K7*(1+Assumption!#REF!))) -> 746755.15 | M7: =IF(Assumption!$H$2=Assumption!$S$1,L7*(1+Assumption!M24),IF(Assumption!$H$2=Assumption!$S$2,'Cash Flow Statement'!L7*(1+Assumption!M47),'Cash Flow Statement'!L7*(1+Assumption!#REF!))) -> 827416.85
B9: Acquisitions of property, plant and equipment and intangible assets | D9: -333675 | E9: -412872 | F9: -597562 | G9: -661713 | H9: -654105 | I9: =-Assumption!I26*'Income Statement'!I7 -> -561547.07 | J9: =-Assumption!J26*'Income Statement'!J7 -> -645779.14 | K9: =-Assumption!K26*'Income Statement'!K7 -> -774934.96 | L9: =-Assumption!L26*'Income Statement'!L7 -> -968668.7 | M9: =-Assumption!M26*'Income Statement'!M7 -> -1259269.3
B10: Acquisitions of investments in consolidated undertakings, net of cash acquired | D10: -568953 | E10: -342456 | F10: -16561 | G10: -51336 | H10: 0 | I10: =-Assumption!I27*'Income Statement'!I7 -> -275712.35 | J10: =-Assumption!J27*'Income Statement'!J7 -> -317069.2 | K10: =-Assumption!K27*'Income Statement'!K7 -> -380483.04 | L10: =-Assumption!L27*'Income Statement'!L7 -> -475603.81 | M10: =-Assumption!M27*'Income Statement'!M7 -> -618284.95
B11: Capex | D11: =D9+D10 -> -902628 | E11: =E9+E10 -> -755328 | F11: =F9+F10 -> -614123 | G11: =G9+G10 -> -713049 | H11: =H9+H10 -> -654105 | I11: =-IF(Assumption!$H$2=Assumption!$S$1,'Income Statement'!I7*Assumption!I28,IF(Assumption!$H$2=Assumption!$S$2,'Income Statement'!I7*Assumption!I51,'Income Statement'!I7*Assumption!#REF!)) -> -837259.43 | J11: =-IF(Assumption!$H$2=Assumption!$S$1,'Income Statement'!J7*Assumption!J28,IF(Assumption!$H$2=Assumption!$S$2,'Income Statement'!J7*Assumption!J51,'Income Statement'!J7*Assumption!#REF!)) -> -962848.34 | K11: =-IF(Assumption!$H$2=Assumption!$S$1,'Income Statement'!K7*Assumption!K28,IF(Assumption!$H$2=Assumption!$S$2,'Income Statement'!K7*Assumption!K51,'Income Statement'!K7*Assumption!#REF!)) -> -1155418 | L11: =-IF(Assumption!$H$2=Assumption!$S$1,'Income Statement'!L7*Assumption!L28,IF(Assumption!$H$2=Assumption!$S$2,'Income Statement'!L7*Assumption!L51,'Income Statement'!L7*Assumption!#REF!)) -> -1444272.5 | M11: =-IF(Assumption!$H$2=Assumption!$S$1,'Income Statement'!M7*Assumption!M28,IF(Assumption!$H$2=Assumption!$S$2,'Income Statement'!M7*Assumption!M51,'Income Statement'!M7*Assumption!#REF!)) -> -1877554.3
B13: Net Capex | D13: =-D11-D7 -> 571239 | E13: =-E11-E7 -> 417132 | F13: =-F11-F7 -> 239459 | G13: =-G11-G7 -> 256685 | H13: =-H11-H7 -> 158662 | I13: =-I11-I7 -> 288300.53 | J13: =-J11-J7 -> 354592.95 | K13: =-K11-K7 -> 481461.15 | ... M13: =-M11-M7 -> 1050137.4

Sheet ADJUSTMENTS >>>>

Sheet Operating lease converter
A1: Operating Lease Converter
A2: Inputs
A3: Operating lease expense in current year = | E3: 80000
A4: Operating Lease Commitments (From footnote to financials)
A5: Year | B5: Commitment | C5: ! Year 1 is next year, ….
A6: 1 | B6: 78500
A7: 2 | B7: 62800
A8: 3 | B8: 40800
A9: 4 | B9: 28400
A10: 5 | B10: 19800
A11: 6 and beyond | B11: 114500
A13: Output
A14: Pre-tax Cost of Debt = | C14: =WACC!G6 -> 0.052275597 | D14: ! If you do not have a cost of debt, use the ratings estimator
A16: From the current financial statements, enter the following
A17: Reported Operating Income (EBIT) = | D17: ='Income Statement'!H18 -> -39480 | E17: ! This is the EBIT reported in the current income statement
A18: Reported Debt = | D18: =WACC!C10 -> 1152300 | E18: ! This is the interest-bearing debt reported on the balance sheet
A20: Number of years embedded in yr 6 estimate = | D20: =IF(B11>0,ROUND(B11/AVERAGE(B6:B10),0),0) -> 2 | E20: ! I use the average lease expense over the first five years
E21: to estimate the number of years of expenses in yr 6
A22: Converting Operating Leases into debt
A23: Year | B23: Commitment | C23: Present Value
A24: =A6 -> 1 | B24: =B6 -> 78500 | C24: =B24/(1+$C$14)^A24 -> 74600.229
A25: =A7 -> 2 | B25: =B7 -> 62800 | C25: =B25/(1+$C$14)^A25 -> 56715.354
A26: =A8 -> 3 | B26: =B8 -> 40800 | C26: =B26/(1+$C$14)^A26 -> 35016.414
A27: =A9 -> 4 | B27: =B9 -> 28400 | C27: =B27/(1+$C$14)^A27 -> 23163.295
A28: =A10 -> 5 | B28: =B10 -> 19800 | C28: =B28/(1+$C$14)^A28 -> 15346.795
A29: =A11 -> 6 and beyond | B29: =IF(B11>0,IF(D20>0,B11/D20,B11),0) -> 57250 | C29: =IF(D20>0,(B29*(1-(1+C14)^(-D20))/C14)/(1+$C$14)^5,B29/(1+C14)^6) -> 82244.086 | D29: ! Commitment beyond year 6 converted into an annuity for ten years
A30: Debt Value of leases = | C30: =SUM(C24:C29) -> 287086.17
A32: Restated Financials
A33: Depreciation on Operating Lease Asset = | F33: =C30/(5+D20) -> 41012.31 | G33: ! I use straight line depreciation
A34: Adjustment to Operating Earnings = | F34: =E3-F33 -> 38987.69 | G34: ! Operating lease expense - Depreciation
A35: Adjustment to Total Debt outstanding = | F35: =C30 -> 287086.17

Sheet R&D converter
A1: R & D Converter
A2: This spreadsheet converts R&D expenses from operating to capital expenses. It makes the appropriate adjustments to operating income, net
A3: income, the book value of assets and the book value of equity.
A5: Inputs
A6: Over how many years do you want to amortize R&D expenses | F6: 10 | G6: ! If in doubt, use the lookup table below
A7: Enter the current year's R&D expense = | F7: 847284 | G7: The maximum allowed is ten years
A8: Enter R& D expenses for past years: the number of years that you will need to enter will be determined by the amortization period
A9: Do not input numbers in the first column (Year). It will get automatically updated based on the input above.
A10: Year | B10: R& D Expenses
A11: -1 | B11: 833853 | C11: ! Year -1 is the year prior to the current year
A12: =IF((0-A11)<$F$6,IF(A11>-1,,A11-1),) -> -2 | B12: 1294411 | C12: ! Year -2 is the two years prior to the current year | H12: Projetction of R&D depreciation growth rate
A13: =IF((0-A12)<$F$6,IF(A12>-1,,A12-1),) -> -3 | B13: 737685 | H13: Year | I13: R&D Expense | J13: Unamortized portion | L13: Amortization this year
A14: =IF((0-A13)<$F$6,IF(A13>-1,,A13-1),) -> -4 | B14: 649951 | H14: Current | I14: =-'Income Statement'!M13 -> 2336312.5 | J14: =1 -> 1 | K14: =I14*J14 -> 2336312.5
A15: =IF((0-A14)<$F$6,IF(A14>-1,,A14-1),) -> -5 | B15: 502657 | H15: =A11 -> -1 | I15: =-'Income Statement'!L13 -> 1797163.5 | J15: =IF(H15<0,($F$6+H15)/$F$6,0) -> 0.9 | K15: =I15*J15 -> 1617447.1 | L15: =IF(H15<0,I15/$F$6,0) -> 179716.35
A16: =IF((0-A15)<$F$6,IF(A15>-1,,A15-1),) -> -6 | B16: 391802 | H16: =A12 -> -2 | I16: =-'Income Statement'!K13 -> 1437730.8 | J16: =IF(H16<0,($F$6+H16)/$F$6,0) -> 0.8 | K16: =I16*J16 -> 1150184.6 | L16: =IF(H16<0,I16/$F$6,0) -> 143773.08
A17: =IF((0-A16)<$F$6,IF(A16>-1,,A16-1),) -> -7 | B17: 335256 | H17: =A13 -> -3 | I17: =-'Income Statement'!J13 -> 1198109 | J17: =IF(H17<0,($F$6+H17)/$F$6,0) -> 0.7 | K17: =I17*J17 -> 838676.3 | L17: =IF(H17<0,I17/$F$6,0) -> 119810.9
A18: =IF((0-A17)<$F$6,IF(A17>-1,,A17-1),) -> -8 | B18: 308487 | H18: =A14 -> -4 | I18: =-'Income Statement'!I13 -> 1041833.9 | J18: =IF(H18<0,($F$6+H18)/$F$6,0) -> 0.6 | K18: =I18*J18 -> 625100.35 | L18: =IF(H18<0,I18/$F$6,0) -> 104183.39
A19: =IF((0-A18)<$F$6,IF(A18>-1,,A18-1),) -> -9 | B19: 264004 | H19: =A15 -> -5 | I19: =F7 -> 847284 | J19: =IF(H19<0,($F$6+H19)/$F$6,0) -> 0.5 | K19: =I19*J19 -> 423642 | L19: =IF(H19<0,I19/$F$6,0) -> 84728.4
A20: =IF((0-A19)<$F$6,IF(A19>-1,,A19-1),) -> -10 | B20: 2200033 | H20: =A16 -> -6 | I20: =B11 -> 833853 | J20: =IF(H20<0,($F$6+H20)/$F$6,0) -> 0.4 | K20: =I20*J20 -> 333541.2 | L20: =IF(H20<0,I20/$F$6,0) -> 83385.3
H21: =A17 -> -7 | I21: =B12 -> 1294411 | J21: =IF(H21<0,($F$6+H21)/$F$6,0) -> 0.3 | K21: =I21*J21 -> 388323.3 | L21: =IF(H21<0,I21/$F$6,0) -> 129441.1
A22: Output | H22: =A18 -> -8 | I22: =B13 -> 737685 | J22: =IF(H22<0,($F$6+H22)/$F$6,0) -> 0.2 | K22: =I22*J22 -> 147537 | L22: =IF(H22<0,I22/$F$6,0) -> 73768.5
A23: Year | B23: R&D Expense | C23: Unamortized portion | E23: Amortization this year | H23: =A19 -> -9 | I23: =B14 -> 649951 | J23: =IF(H23<0,($F$6+H23)/$F$6,0) -> 0.1 | K23: =I23*J23 -> 64995.1 | L23: =IF(H23<0,I23/$F$6,0) -> 64995.1
A24: Current | B24: =F7 -> 847284 | C24: =1 -> 1 | D24: =B24*C24 -> 847284 | H24: =A20 -> -10 | I24: =B15 -> 502657 | J24: =IF(H24<0,($F$6+H24)/$F$6,0) -> 0 | K24: =I24*J24 -> 0 | L24: =IF(H24<0,I24/$F$6,0) -> 50265.7
A25: =A11 -> -1 | B25: =B11 -> 833853 | C25: =IF(A25<0,($F$6+A25)/$F$6,0) -> 0.9 | D25: =B25*C25 -> 750467.7 | E25: =IF(A25<0,B25/$F$6,0) -> 83385.3 | H25: Total | K25: =SUM(K14:K24) -> 7925759.6 | L25: =SUM(L15:L24) -> 1034067.8
A26: =A12 -> -2 | B26: =B12 -> 1294411 | C26: =IF(A26<0,($F$6+A26)/$F$6,0) -> 0.8 | D26: =B26*C26 -> 1035528.8 | E26: =IF(A26<0,B26/$F$6,0) -> 129441.1 | H26: Yearly growth rate of R&D depreciation | L26: =(1+L25/D37-1)^(1/5)-1 -> 0.065829495
A27: =A13 -> -3 | B27: =B13 -> 737685 | C27: =IF(A27<0,($F$6+A27)/$F$6,0) -> 0.7 | D27: =B27*C27 -> 516379.5 | E27: =IF(A27<0,B27/$F$6,0) -> 73768.5 | H27: Yearly growth rate of value of R&D asset | L27: =(1+K25/D35-1)^(1/5)-1 -> 0.13889747
A28: =A14 -> -4 | B28: =B14 -> 649951 | C28: =IF(A28<0,($F$6+A28)/$F$6,0) -> 0.6 | D28: =B28*C28 -> 389970.6 | E28: =IF(A28<0,B28/$F$6,0) -> 64995.1
A29: =A15 -> -5 | B29: =B15 -> 502657 | C29: =IF(A29<0,($F$6+A29)/$F$6,0) -> 0.5 | D29: =B29*C29 -> 251328.5 | E29: =IF(A29<0,B29/$F$6,0) -> 50265.7
A30: =A16 -> -6 | B30: =B16 -> 391802 | C30: =IF(A30<0,($F$6+A30)/$F$6,0) -> 0.4 | D30: =B30*C30 -> 156720.8 | E30: =IF(A30<0,B30/$F$6,0) -> 39180.2
A31: =A17 -> -7 | B31: =B17 -> 335256 | C31: =IF(A31<0,($F$6+A31)/$F$6,0) -> 0.3 | D31: =B31*C31 -> 100576.8 | E31: =IF(A31<0,B31/$F$6,0) -> 33525.6
A32: =A18 -> -8 | B32: =B18 -> 308487 | C32: =IF(A32<0,($F$6+A32)/$F$6,0) -> 0.2 | D32: =B32*C32 -> 61697.4 | E32: =IF(A32<0,B32/$F$6,0) -> 30848.7
A33: =A19 -> -9 | B33: =B19 -> 264004 | C33: =IF(A33<0,($F$6+A33)/$F$6,0) -> 0.1 | D33: =B33*C33 -> 26400.4 | E33: =IF(A33<0,B33/$F$6,0) -> 26400.4
A34: =A20 -> -10 | B34: =B20 -> 2200033 | C34: =IF(A34<0,($F$6+A34)/$F$6,0) -> 0 | D34: =B34*C34 -> 0 | E34: =IF(A34<0,B34/$F$6,0) -> 220003.3
A35: Value of Research Asset = | D35: =SUM(D24:D34) -> 4136354.5 | E35: =SUM(E25:E34) -> 751813.9
A37: Amortization of asset for current year = | D37: =E35 -> 751813.9
A39: Adjustment to Operating Income = | D39: =F7-D37 -> 95470.1 | E39: ! A positive number indicates an increase in operating income (add to reported EBIT) | L39: =D39/F7 -> 0.1126778
A40: Tax Effect of R&D Expensing | D40: =(F7-D37)*'Free Cash Flow'!H14 -> 38188.04
A43: Look Up Table for Amortization Periods
A44: Industry Name | B44: Amortization Period
A45: Advertising | B45: 2
A46: Aerospace/Defense | B46: 10 | D46: Non-technological Service | F46: 2 years
A47: Air Transport | B47: 10 | D47: Retail, Tech Service | F47: 3 years
A48: Aluminum | B48: 5 | D48: Light Manufacturing | F48: 5 years
A49: Apparel | B49: 3 | D49: Heavy Manufacturing | F49: 10 years
A50: Auto & Truck | B50: 10 | D50: Research, with Patenting | F50: 10 years
A51: Auto Parts (OEM) | B51: 5 | D51: Long Gestation Period | F51: 10 years
A52: Auto Parts (Replacement) | B52: 5
A53: Bank | B53: 2
A54: Bank (Canadian) | B54: 2
A55: Bank (Foreign) | B55: 2
A56: Bank (Midwest) | B56: 2
A57: Beverage (Alcoholic) | B57: 3
A58: Beverage (Soft Drink) | B58: 3
A59: Building Materials | B59: 5
A60: Cable TV | B60: 10
A61: Canadian Energy | B61: 10
A62: Cement & Aggregates | B62: 10
A63: Chemical (Basic) | B63: 10
... A142: Water Utility | B142: 10

Sheet VALUATION >>>>

Sheet Free Cash Flow
A1: Project EBS
A2: Income Statement | D2: Actual | F2: Projections
A3: €m | D3: 2006 | E3: 2007 | F3: 2008 | G3: 2009 | H3: 2010 | I3: Adj. | J3: 2010 | K3: 2011 | L3: 2012 | M3: 2013 | N3: 2014 | O3: 2015
B5: Unlevered Free Cash Flow
B7: Year (t) | K7: 1 | L7: 2 | M7: 3 | N7: 4 | O7: 5
B9: EBITDA | D9: ='Income Statement'!D14 -> 790991 | E9: ='Income Statement'!E14 -> 961320 | F9: ='Income Statement'!F14 -> 805200 | G9: ='Income Statement'!G14 -> 828690 | H9: ='Income Statement'!H14 -> 455963 | I9: 0 | J9: =H9+I9 -> 455963 | K9: ='Income Statement'!I14 -> 1058646.1 | L9: ='Income Statement'!J14 -> 1216908.2 | M9: ='Income Statement'!K14 -> 1459394.9 | N9: ='Income Statement'!L14 -> 1822971.9 | O9: ='Income Statement'!M14 -> 2368114.5
B11: Depreciation & amortization | D11: ='Income Statement'!D17 -> -331389 | E11: ='Income Statement'!E17 -> -338196 | F11: ='Income Statement'!F17 -> -374664 | G11: ='Income Statement'!G17 -> -456364 | H11: ='Income Statement'!H17 -> -495443 | I11: 0 | J11: ='Income Statement'!H17 -> -495443 | K11: ='Income Statement'!I13 -> -1041833.9 | L11: ='Income Statement'!J13 -> -1198109 | M11: ='Income Statement'!K13 -> -1437730.8 | N11: ='Income Statement'!L13 -> -1797163.5 | O11: ='Income Statement'!M13 -> -2336312.5
B12: EBIT | D12: =SUM(D9:D11) -> 459602 | E12: =SUM(E9:E11) -> 623124 | F12: =SUM(F9:F11) -> 430536 | G12: =SUM(G9:G11) -> 372326 | H12: =SUM(H9:H11) -> -39480 | I12: =D36+D38+D37 -> 172645.83 | J12: =H12+I12 -> 133165.83 | K12: ='Income Statement'!I18+E36+E37+E38 -> 885414.79 | L12: ='Income Statement'!J18+F36+F37+F38 -> 1129316.1 | M12: ='Income Statement'!K18+G36+G37+G38 -> 1562861.1 | N12: ='Income Statement'!L18+H36+H37+H38 -> 2272953.2 | O12: ='Income Statement'!M18+I36+I37+I38 -> 3402828
B14: Marginal tax rate | D14: =IF($B$14="Marginal tax rate",D32,D31) -> 0.4 | E14: =IF($B$14="Marginal tax rate",E32,E31) -> 0.4 | F14: =IF($B$14="Marginal tax rate",F32,F31) -> 0.4 | G14: =IF($B$14="Marginal tax rate",G32,G31) -> 0.4 | H14: =IF($B$14="Marginal tax rate",H32,H31) -> 0.4 | I14: 0 | J14: =IF($B$14="Marginal tax rate",H32,H31) -> 0.4 | K14: =Assumption!I18 -> 0.4 | L14: =Assumption!J18 -> 0.4 | M14: =Assumption!K18 -> 0.4 | N14: =Assumption!L18 -> 0.4 | O14: =Assumption!M18 -> 0.4
B15: EBIT*(1-Tax rate) | D15: =D12*(1-D14) -> 275761.2 | E15: =E12*(1-E14) -> 373874.4 | F15: =F12*(1-F14) -> 258321.6 | G15: =G12*(1-G14) -> 223395.6 | H15: =H12*(1-H14) -> -23688 | I15: =I12*(1-H14) -> 103587.5 | J15: =H15+I15 -> 79899.498 | K15: =K12*(1-K14) -> 531248.87 | L15: =L12*(1-L14) -> 677589.67 | M15: =M12*(1-M14) -> 937716.67 | N15: =N12*(1-N14) -> 1363771.9 | O15: =O12*(1-O14) -> 2041696.8
B17: Depreciation & amortization | D17: =-D11 -> 331389 | E17: =-E11 -> 338196 | F17: =-F11 -> 374664 | G17: =-G11 -> 456364 | H17: =-H11 -> 495443 | I17: =D41+D42 -> 792826.21 | J17: =H17+I17 -> 1288269.2 | K17: =-K11+E41+E42 -> 1884151.7 | L17: =-L11+F41+F42 -> 2093176.3 | M17: =-M11+G41+G42 -> 2389020.1 | N17: =-N11+H41+H42 -> 2808375.8 | O17: =-O11+I41+I42 -> 3411392.7
B18: Δ net Working Capital | D18: ='Balance Sheet'!D48 -> 24641 | E18: ='Balance Sheet'!E48 -> 84286 | F18: ='Balance Sheet'!F48 -> 100908 | G18: ='Balance Sheet'!G48 -> -48719 | H18: ='Balance Sheet'!H48 -> 82872 | I18: 0 | J18: =H18+I18 -> 82872 | K18: ='Balance Sheet'!I48 -> 110699.07 | L18: ='Balance Sheet'!J48 -> 177324.61 | M18: ='Balance Sheet'!K48 -> 271897.74 | N18: ='Balance Sheet'!L48 -> 407846.6 | O18: ='Balance Sheet'!M48 -> 611769.91
B19: Capex | D19: ='Cash Flow Statement'!D11 -> -902628 | E19: ='Cash Flow Statement'!E11 -> -755328 | F19: ='Cash Flow Statement'!F11 -> -614123 | G19: ='Cash Flow Statement'!G11 -> -713049 | H19: ='Cash Flow Statement'!H11 -> -654105 | I19: =D45+D46 -> -927284 | J19: =H19+I19 -> -1581389 | K19: ='Cash Flow Statement'!I11+D45+D46 -> -1764543.4 | L19: ='Cash Flow Statement'!J11+E45+E46 -> -2084682.3 | M19: ='Cash Flow Statement'!K11+F45+F46 -> -2433527 | N19: ='Cash Flow Statement'!L11+G45+G46 -> -2962003.3 | O19: ='Cash Flow Statement'!M11+H45+H46 -> -3754717.8
B21: FCF | D21: =D15+D17-D18+D19 -> -320118.8 | E21: =E15+E17-E18+E19 -> -127543.6 | F21: =F15+F17-F18+F19 -> -82045.4 | G21: =G15+G17-G18+G19 -> 15429.6 | H21: =H15+H17-H18+H19 -> -265222 | I21: NA | J21: =J15+J17-J18+J19 -> -296092.29 | K21: =K15+K17-K18+K19 -> 540158.03 | L21: =L15+L17-L18+L19 -> 508759.08 | M21: =M15+M17-M18+M19 -> 621312 | N21: =N15+N17-N18+N19 -> 802297.88 | O21: =O15+O17-O18+O19 -> 1086601.8
B23: Unleverd FCF | K23: =K21/(1+WACC!$D$24)^'Free Cash Flow'!K7 -> 488875.04 | L23: =L21/(1+WACC!$D$24)^'Free Cash Flow'!L7 -> 416741 | M23: =M21/(1+WACC!$D$24)^'Free Cash Flow'!M7 -> 460617.91 | N23: =N21/(1+WACC!$D$24)^'Free Cash Flow'!N7 -> 538324.01 | O23: =O21/(1+WACC!$D$24)^'Free Cash Flow'!O7 -> 659865.7
B24: PV of UFCF | O24: =SUM(K23:O23) -> 2564423.7
B25: Tax Shields | O25: ='Tax Shield'!G29*1000 -> 1964010.8
B26: Cost of Financial distress | O26: =-'Costs of Financial Distress'!H14 -> -297476.92
B27: TV | O27: =IF(N61<=N62,O23*(1+N61)/(WACC!D28-N61),O23*(1+N62)/(WACC!D28-N62)) -> 11901389
B28: EV | O28: =O24+O27+O25+O26 -> 16132347 | P28: =O28-WACC!G15 -> 14692961
O29: =O28/WACC!G21-1 -> -0.19581104 | P29: =P28/WACC!G19-1 -> -0.21094704
B30: Tax rate | D30: 2006 | E30: 2007 | F30: 2008 | G30: 2009 | H30: 2010
B31: Effective tax rate | D31: -0.68 | E31: 0.35 | F31: 0.33 | G31: 0.22 | H31: -3.38
B32: Marginal tax rate | D32: 0.4 | E32: 0.4 | F32: 0.4 | G32: 0.4 | H32: 0.4
B34: EBIT adjustments | D34: 2010A | E34: 2011 | F34: 2012 | G34: 2013 | H34: 2014 | I34: 2015
B35: R&D adjustments | E35: 1 | F35: 2 | G35: 3 | H35: 4 | I35: 5
B36: R&D | D36: ='R&D converter'!D39 -> 95470.1 | E36: =-'Income Statement'!I13-'R&D converter'!$D$37*POWER((1+'R&D converter'!$L$26),E35) -> 240528.48 | F36: =-'Income Statement'!J13-'R&D converter'!$D$37*POWER((1+'R&D converter'!$L$26),F35) -> 344054.04 | G36: =-'Income Statement'!K13-'R&D converter'!$D$37*POWER((1+'R&D converter'!$L$26),G35) -> 527453.83 | H36: =-'Income Statement'!L13-'R&D converter'!$D$37*POWER((1+'R&D converter'!$L$26),H35) -> 826963.46 | I36: =-'Income Statement'!M13-'R&D converter'!$D$37*POWER((1+'R&D converter'!$L$26),I35) -> 1302244.7
B37: R&D tax effect | D37: ='R&D converter'!D40 -> 38188.04 | E37: =E36*K14 -> 96211.393 | F37: =F36*L14 -> 137621.61 | G37: =G36*M14 -> 210981.53 | H37: =H36*N14 -> 330785.38 | I37: =I36*O14 -> 520897.89
B38: Operating leases | D38: ='Operating lease converter'!F34 -> 38987.69 | E38: =$D$38 -> 38987.69 | F38: =$D$38 -> 38987.69 | G38: =$D$38 -> 38987.69 | H38: =$D$38 -> 38987.69 | I38: =$D$38 -> 38987.69
B40: Depreciaton adjustments
B41: R&D | D41: ='R&D converter'!D37 -> 751813.9 | E41: =D41*(1+'R&D converter'!$L$26) -> 801305.43 | F41: =E41*(1+'R&D converter'!$L$26) -> 854054.96 | G41: =F41*(1+'R&D converter'!$L$26) -> 910276.97 | H41: =G41*(1+'R&D converter'!$L$26) -> 970200.04 | I41: =H41*(1+'R&D converter'!$L$26) -> 1034067.8
B42: Operating leases | D42: ='Operating lease converter'!F33 -> 41012.31 | E42: =$D$42 -> 41012.31 | F42: =$D$42 -> 41012.31 | G42: =$D$42 -> 41012.31 | H42: =$D$42 -> 41012.31 | I42: =$D$42 -> 41012.31
B44: Capex adjustements
B45: R&D | D45: =-'R&D converter'!F7 -> -847284 | E45: ='Income Statement'!I13 -> -1041833.9 | F45: ='Income Statement'!J13 -> -1198109 | G45: ='Income Statement'!K13 -> -1437730.8 | H45: ='Income Statement'!L13 -> -1797163.5 | I45: ='Income Statement'!M13 -> -2336312.5
B46: Operating leases | D46: =-'Operating lease converter'!E3 -> -80000 | E46: =$D$46 -> -80000 | F46: =$D$46 -> -80000 | G46: =$D$46 -> -80000 | H46: =$D$46 -> -80000 | I46: =$D$46 -> -80000
B48: Expected Growth Rate | E48: 2006 | F48: 2007 | G48: 2008 | H48: 2009 | I48: 2010 | J48: 2011 | K48: 2012 | L48: 2013 | M48: 2014 | N48: 2015
B49: Book value of equity | E49: ='Balance Sheet'!D33 -> 5660711 | F49: ='Balance Sheet'!E33 -> 6612937 | G49: ='Balance Sheet'!F33 -> 7305993 | H49: ='Balance Sheet'!G33 -> 7683652 | I49: ='Balance Sheet'!H33 -> 7586973
B50: Book value of debt | E50: ='Balance Sheet'!D28+'Balance Sheet'!D24 -> 126029 | F50: ='Balance Sheet'!E28+'Balance Sheet'!E24 -> 810373 | G50: ='Balance Sheet'!F28+'Balance Sheet'!F24 -> 131907 | H50: ='Balance Sheet'!G28+'Balance Sheet'!G24 -> 124600 | I50: ='Balance Sheet'!H28+'Balance Sheet'!H24 -> 1106540
B51: Book value of capital | E51: =SUM(E49:E50) -> 5786740 | F51: =SUM(F49:F50) -> 7423310 | G51: =SUM(G49:G50) -> 7437900 | H51: =SUM(H49:H50) -> 7808252 | I51: =SUM(I49:I50) -> 8693513 | J51: =(J48-$E$48)*619849+6*10^6 -> 9099245 | K51: =(K48-$E$48)*619849+6*10^6 -> 9719094 | L51: =(L48-$E$48)*619849+6*10^6 -> 10338943 | M51: =(M48-$E$48)*619849+6*10^6 -> 10958792 | N51: =(N48-$E$48)*619849+6*10^6 -> 11578641
B52: Value of Research Asset | I52: ='R&D converter'!D35 -> 4136354.5 | J52: ='R&D converter'!$D$35*POWER(1+'R&D converter'!$L$27,'Free Cash Flow'!K7) -> 4710883.7 | K52: ='R&D converter'!$D$35*POWER(1+'R&D converter'!$L$27,'Free Cash Flow'!L7) -> 5365213.5 | L52: ='R&D converter'!$D$35*POWER(1+'R&D converter'!$L$27,'Free Cash Flow'!M7) -> 6110428.1 | M52: ='R&D converter'!$D$35*POWER(1+'R&D converter'!$L$27,'Free Cash Flow'!N7) -> 6959151.1 | N52: ='R&D converter'!$D$35*POWER(1+'R&D converter'!$L$27,'Free Cash Flow'!O7) -> 7925759.6
B54: EBIT*(1-Tax rate) | E54: =D15 -> 275761.2 | F54: =E15 -> 373874.4 | G54: =F15 -> 258321.6 | H54: =G15 -> 223395.6 | I54: =H15 -> -23688 | J54: =K15 -> 531248.87 | K54: =L15 -> 677589.67 | L54: =M15 -> 937716.67 | M54: =N15 -> 1363771.9 | N54: =O15 -> 2041696.8
B56: Return of Capital Invested* | F56: =F54/E51 -> 0.064608813 | G56: =G54/F51 -> 0.034798708 | H56: =H54/G51 -> 0.030034768 | I56: =I54/H51 -> -0.0030337136 | J56: =(J54+E41)/(I51+I52) -> 0.10386345 | K56: =(K54+F41)/(J51+J52) -> 0.11090734 | L56: =(L54+G41)/(K51+K52) -> 0.122511 | M56: =(M54+H41)/(L51+L52) -> 0.14188822 | N56: =(N54+I41)/(M51+M52) -> 0.17165835
B58: Net Capex | E58: ='Cash Flow Statement'!D13 -> 571239 | F58: ='Cash Flow Statement'!E13 -> 417132 | G58: ='Cash Flow Statement'!F13 -> 239459 | H58: ='Cash Flow Statement'!G13 -> 256685 | I58: ='Cash Flow Statement'!H13 -> 158662 | J58: =-K19-K17 -> -119608.23 | K58: =-L19-L17 -> -8494.0195 | L58: =-M19-M17 -> 44506.928 | M58: =-N19-N17 -> 153627.46 | N58: =-O19-O17 -> 343325.08
B59: Change in NCWC | E59: ='Balance Sheet'!D48 -> 24641 | F59: ='Balance Sheet'!E48 -> 84286 | G59: ='Balance Sheet'!F48 -> 100908 | H59: ='Balance Sheet'!G48 -> -48719 | I59: ='Balance Sheet'!H48 -> 82872 | J59: =K18 -> 110699.07 | K59: =L18 -> 177324.61 | L59: =M18 -> 271897.74 | M59: =N18 -> 407846.6 | N59: =O18 -> 611769.91
B61: EBIT Growth rate | F61: =(F58+F59)/F54*F56 -> 0.086649478 | G61: =(G58+G59)/G54*G56 -> 0.04585111 | H61: =(H58+H59)/H54*H56 -> 0.027960311 | I61: =(I58+I59)/I54*I56 -> 0.030933172 | J61: =(J58+J59)/J54*J56 -> -0.0017418119 | K61: =(K58+K59)/K54*K56 -> 0.027634057 | L61: =(L58+L59)/L54*L56 -> 0.041337703 | M61: =(M58+M59)/M54*M56 -> 0.058416333 | N61: =(N58+N59)/N54*N56 -> 0.080300872
B62: Source: http://france-inflation.com/inflation-depuis-1901.php | N62: 0.04328
B63: gEBIT = (Net Capital Expenditures + Change in WC)/(EBIT(1-t) * ROC) | N63: Source: http://data.worldbank.org/indicator/NY.GDP.MKTP.KD.ZG
B64: *adjusted with R&D asset value from 2010 adj. To 2015E
B69: Unlevered Free Cash Flow Valuation | L69: Key DCF parameters
B70: $million | D70: 2011 | E70: 2012 | F70: 2013 | G70: 2014 | H70: 2015 | L70: Cost of equity | N70: =WACC!D24 -> 0.1049
B71: Unleverd FCF | D71: =K23/1000 -> 488.87504 | E71: =L23/1000 -> 416.741 | F71: =M23/1000 -> 460.61791 | G71: =N23/1000 -> 538.32401 | H71: =O23/1000 -> 659.8657 | L71: Cost of debt | N71: =WACC!G6 -> 0.052275597
B72: PV of UFCF | I72: =O24/1000 -> 2564.4237 | L72: Return on assets | N72: =WACC!D28 -> 0.10112406
B73: Tax Shields | I73: =O25/1000 -> 1964.0108 | L73: Perpetuity Growth rate | N73: =N62 -> 0.04328
B74: Cost of Financial distress | I74: =O26/1000 -> -297.47692
B75: Terminal Value (TV) | I75: =O27/1000 -> 11901.389
B76: Enterprise Value (EV) | I76: =O28/1000 -> 16132.347 | J76: -0.19
B77: Equity Value | I77: =P28/1000 -> 14692.961 | J77: -0.2
B78: Figure 8: Genzyme APV valuation
E81: Actual | I81: Projection
E82: 2010 | F82: Adj. | G82: 2010 | H82: 2011 | I82: 2012 | J82: 2013 | K82: 2014 | L82: 2015
B84: Unlevered Free Cash Flow
B86: Year (t) | H86: 1 | I86: 2 | J86: 3 | K86: 4 | L86: 5
B88: EBITDA | E88: 455.963 | F88: 0 | G88: 455.963 | H88: 1863.3415 | I88: 2137.5826 | J88: 2557.9039 | K88: 3188.2327 | L88: 4133.5031
B90: Depreciation & amortization | E90: -495.443 | F90: 0 | G90: -495.443 | H90: -678.35968 | I90: -780.11363 | J90: -936.13636 | K90: -1170.1705 | L90: -1521.2216
B91: EBIT | E91: -39.48 | F91: 172.64583 | G91: 133.16583 | H91: 1209.3049 | I91: 1520.7008 | J91: 2042.1661 | K91: 2869.2343 | L91: 4159.5837
B93: Effective tax rate | E93: 0.4 | F93: 0 | G93: 40 | H93: 0.4 | I93: 0.4 | J93: 0.4 | K93: 0.4 | L93: 0.4
B94: EBIT*(1-Tax rate) | E94: -23.688 | F94: 103.5875 | G94: 79.899498 | H94: 725.58295 | I94: 912.4205 | J94: 1225.2997 | K94: 1721.5406 | L94: 2495.7502
B96: Depreciation & amortization | E96: 495.443 | F96: 792.82621 | G96: 1288.2692 | H96: 1488.609 | I96: 1608.1899 | J96: 1782.4527 | K96: 2035.1496 | L96: 2405.296
B97: Δ net Working Capital | E97: 82.872 | G97: 82.872 | H97: -920.60733 | I97: 22.62865 | J97: 34.697264 | K97: 52.045896 | L97: 78.068843
B98: Capex | E98: -654.105 | F98: -927.284 | G98: -1581.389 | H98: -2043.7149 | I98: -2042.2553 | J98: -2400.7883 | K98: -2941.9797 | L98: -3753.7668
B100: FCF | E100: -265.222 | F100: NA | G100: -296.09229 | H100: 1091.0844 | I100: 455.72653 | J100: 572.26683 | K100: 762.66457 | L100: 1069.2106

Sheet Tax Shield
A1: Project EBS
A2: Income Statement
A3: $thousands
B5: Capital Structure | C5: 2006 | D5: 2007 | E5: 2008 | F5: 2009 | G5: 2010
B6: Current portion of long-term debt and capital lease obligations | C6: ='Balance Sheet'!D24 -> 6226 | D6: ='Balance Sheet'!E24 -> 696625 | E6: ='Balance Sheet'!F24 -> 7566 | F6: ='Balance Sheet'!G24 -> 8166 | G6: ='Balance Sheet'!H24 -> 7584
B7: Long-term debt and capital lease obligations | C7: ='Balance Sheet'!D28 -> 119803 | D7: ='Balance Sheet'!E28 -> 113748 | E7: ='Balance Sheet'!F28 -> 124341 | F7: ='Balance Sheet'!G28 -> 116434 | G7: ='Balance Sheet'!H28 -> 1098956
B8: Total debt | C8: =C7+C6 -> 126029 | D8: =D7+D6 -> 810373 | E8: =E7+E6 -> 131907 | F8: =F7+F6 -> 124600 | G8: =G7+G6 -> 1106540
B9: Total assets | C9: ='Balance Sheet'!D19 -> 7191188 | D9: ='Balance Sheet'!E19 -> 8301741 | E9: ='Balance Sheet'!F19 -> 8671276 | F9: ='Balance Sheet'!G19 -> 10060724 | G9: ='Balance Sheet'!H19 -> 10913854
B10: Debt to assets | C10: =C8/C9 -> 0.017525477 | D10: =D8/D9 -> 0.097614826 | E10: =E8/E9 -> 0.015211948 | F10: =F8/F9 -> 0.012384795 | G10: =G8/G9 -> 0.10138857
B11: Source : Genzyme Annual Report 2006 to 2010
A13: $m | B13: Oustanding debt as of 31/12/2010 | H13: =WACC!G15/1000 -> 1439.3862
B14: Obligation payment schedule | C14: 2011 | D14: 2012 | E14: 2013 | F14: 2014 | G14: 2015 | H14: After 2015
B15: Long-term debt obligations | C15: 0.5 | D15: 0.5 | E15: 0.6 | F15: 0.6 | G15: 500.6 | H15: 514.2
B16: Capital lease obligations | C16: 15.4 | D16: 15.5 | E16: 16.9 | F16: 18.9 | G16: 18.8 | H16: 48.7
B17: Operating leases | C17: 78.5 | D17: 62.8 | E17: 40.8 | F17: 28.4 | G17: 19.8 | H17: 114.5
B18: Total | C18: =SUM(C15:C17) -> 94.4 | D18: =SUM(D15:D17) -> 78.8 | E18: =SUM(E15:E17) -> 58.3 | F18: =SUM(F15:F17) -> 47.9 | G18: =SUM(G15:G17) -> 539.2 | H18: 813.2
B19: Outstanding debt | C19: =H13-C18 -> 1344.9862 | D19: =C19-D18 -> 1266.1862 | E19: =D19-E18 -> 1207.8862 | F19: =E19-F18 -> 1159.9862 | G19: =F19-G18 -> 620.78617 | H19: =G19-H18 -> -192.41383
B20: Source: Genzyme Annual Report 2010
A22: Cost of debt = | B22: =WACC!G6 -> 0.052275597
A23: Corporate tax = | B23: 0.402
A25: $m | B25: Obligation payment schedule | C25: 2011 | D25: 2012 | E25: 2013 | F25: 2014 | G25: 2015
B26: Year | C26: 1 | D26: 2 | E26: 3 | F26: 4 | G26: 5
B27: Interest tax shield | C27: =C19*$B$23 -> 540.68444 | D27: =D19*$B$23 -> 509.00684 | E27: =E19*$B$23 -> 485.57024 | F27: =F19*$B$23 -> 466.31444 | G27: =G19*$B$23 -> 249.55604
B28: PV of ITS | C28: =C27/(1+$B$22)^C26 -> 513.82399 | D28: =D27/(1+$B$22)^D26 -> 459.68954 | E28: =E27/(1+$B$22)^E26 -> 416.73844 | F28: =F27/(1+$B$22)^F26 -> 380.33025 | G28: =G27/(1+$B$22)^G26 -> 193.42856
B29: Total | G29: =SUM(C28:G28) -> 1964.0108
B30: Figure 9: Genzyme tax shield present value
A31: Limit : we cannot take into account the amount of asset retirement obligations or retirements benefits

Sheet Costs of Financial Distress
A1: Cumulative Historic Default Rates (in percent)
B2: Moody’s | D2: S&P
A3: Rating category | B3: Muni | C3: Corp | D3: Muni | E3: Corp
A4: Aaa/AAA | B4: 0 | C4: 0.52 | D4: 0 | E4: 0.6
A5: Aa/AA | B5: 0.06 | C5: 0.52 | D5: 0 | E5: 1.5 | F5: (Average Credit rating for Genzyme in 2010) | G5: Cumulative probability of distress over 10 years | H5: Cumulative probability of distress over 10 years Damodaran
A6: A/A | B6: 0.03 | C6: 1.29 | D6: 0.23 | E6: 2.91 | F6: A- | G6: =((C6+C7)/2+(E6+E7)/2)/2/100 -> 0.047825 | H6: 0.0242
A7: Baa/BBB | B7: 0.13 | C7: 4.64 | D7: 0.32 | E7: 10.29
A8: Ba/BB | B8: 2.65 | C8: 19.12 | D8: 1.74 | E8: 29.93
A9: B/B | B9: 11.86 | C9: 43.34 | D9: 8.48 | E9: 53.72
A10: Caa-C/CCC-C | B10: 16.58 | C10: 69.18 | D10: 44.81 | E10: 69.19 | F10: book value of capital | G10: ='Balance Sheet'!H24+'Balance Sheet'!H28+'Balance Sheet'!H34 -> 8693513 | H10: (in k$)
F11: the cost of bankruptcy | G11: 0.25 | H11: (result of Damodaran)
A12: Averages | F12: distress sale value | G12: =G10*G11 -> 2173378.2 | H12: (in k$)
A13: Investment grade | B13: 0.07 | C13: 2.09 | D13: 0.2 | E13: 4.14 | F13: Expected bankruptcy costs=(unlevered firm value - distress sale value)*probability of distress
A14: Non-investment grade | B14: 4.29 | C14: 31.37 | D14: 7.37 | E14: 42.35 | G14: =('Free Cash Flow'!O24+'Free Cash Flow'!O27-'Costs of Financial Distress'!G12)*'Costs of Financial Distress'!G6 -> 587885.7 | H14: =('Free Cash Flow'!O24+'Free Cash Flow'!O27-'Costs of Financial Distress'!G12)*'Costs of Financial Distress'!H6 -> 297476.92
A15: All | B15: 0.1 | C15: 9.7 | D15: 0.29 | E15: 12.98
A16: Source: U.S. Municipal Bond Fairness Act, 2008. | G16: =G12/1000 -> 2173.3783 | H16: =H14/1000 -> 297.47692
A17: http://monevator.com/bond-default-rating-probability/
F20: Costs of financial distress | G20: 2010
F21: Cumulative probability of distress over 10 years | G21: 0.0242
F22: Book value of capital | G22: =G10/1000 -> 8693.513
F23: The cost of bankruptcy
F24: Distress sa

Sheet Sensitivity Analysis
B1: 2015
A2: Unleverd FCF | B2: ='Free Cash Flow'!O23/1000 -> 659.8657
A3: PV of UFCF | B3: ='Free Cash Flow'!O24/1000 -> 2564.4237
A4: Tax Shields | B4: ='Free Cash Flow'!O25/1000 -> 1964.0108
A5: Cost of Financial distress | B5: ='Free Cash Flow'!O26/1000 -> -297.47692
A6: TV | B6: ='Free Cash Flow'!O27/1000 -> 11901.389
A7: EV | B7: =(B3+B6+B4+B5) -> 16132.347
A8: rA | B8: =[4]WACC!D28 -> 0.10112406
A9: gEBIT | B9: ='[4]Free Cash Flow'!N63 -> 0.04328
C12: $m | F12: Sensitivity Analysis
G13: rA
D14: =$B$3+$B$4+$B$5+$B$2*(1+B9)/(B8-B9) -> 16132.347 | E14: =F14-0.01 -> 0.08112406 | F14: =G14-0.01 -> 0.09112406 | G14: =B8 -> 0.10112406 | H14: =G14+0.01 -> 0.11112406 | I14: =H14+0.01 -> 0.12112406
D15: =D16-0.01 -> 0.02328 | E15: =$B$3+$B$4+$B$5+$B$2*(1+$D15)/(E$14-$D15) -> 15904.194 | F15: =$B$3+$B$4+$B$5+$B$2*(1+$D15)/(F$14-$D15) -> 14183.596 | G15: =$B$3+$B$4+$B$5+$B$2*(1+$D15)/(G$14-$D15) -> 12905.06 | H15: =$B$3+$B$4+$B$5+$B$2*(1+$D15)/(H$14-$D15) -> 11917.617 | I15: =$B$3+$B$4+$B$5+$B$2*(1+$D15)/(I$14-$D15) -> 11132.014
D16: =D17-0.01 -> 0.03328 | E16: =$B$3+$B$4+$B$5+$B$2*(1+$D16)/($E$14-$D16) -> 18481.964 | F16: =$B$3+$B$4+$B$5+$B$2*(1+$D16)/(F$14-$D16) -> 16018.27 | G16: =$B$3+$B$4+$B$5+$B$2*(1+$D16)/(G$14-$D16) -> 14280.858 | H16: =$B$3+$B$4+$B$5+$B$2*(1+$D16)/(H$14-$D16) -> 12989.828 | I16: =$B$3+$B$4+$B$5+$B$2*(1+$D16)/(I$14-$D16) -> 11992.735
C17: gEBIT | D17: =B9 -> 0.04328 | E17: =$B$3+$B$4+$B$5+$B$2*(1+$D17)/($E$14-$D17) -> 22422.047 | F17: =$B$3+$B$4+$B$5+$B$2*(1+$D17)/(F$14-$D17) -> 18619.884 | G17: =$B$3+$B$4+$B$5+$B$2*(1+$D17)/(G$14-$D17) -> 16132.347 | H17: =$B$3+$B$4+$B$5+$B$2*(1+$D17)/(H$14-$D17) -> 14378.12 | I17: =$B$3+$B$4+$B$5+$B$2*(1+$D17)/(I$14-$D17) -> 13074.596
D18: =D17+0.01 -> 0.05328 | E18: =$B$3+$B$4+$B$5+$B$2*(1+$D18)/($E$14-$D18) -> 29192.236 | F18: =$B$3+$B$4+$B$5+$B$2*(1+$D18)/(F$14-$D18) -> 22596.411 | G18: =$B$3+$B$4+$B$5+$B$2*(1+$D18)/(G$14-$D18) -> 18757.805 | H18: =$B$3+$B$4+$B$5+$B$2*(1+$D18)/(H$14-$D18) -> 16246.424 | I18: =$B$3+$B$4+$B$5+$B$2*(1+$D18)/(I$14-$D18) -> 14475.382
D19: =D18+0.01 -> 0.06328 | E19: =$B$3+$B$4+$B$5+$B$2*(1+$D19)/($E$14-$D19) -> 43550.596 | F19: =$B$3+$B$4+$B$5+$B$2*(1+$D19)/(F$14-$D19) -> 29429.222 | G19: =$B$3+$B$4+$B$5+$B$2*(1+$D19)/(G$14-$D19) -> 22770.776 | H19: =$B$3+$B$4+$B$5+$B$2*(1+$D19)/(H$14-$D19) -> 18895.725 | I19: =$B$3+$B$4+$B$5+$B$2*(1+$D19)/(I$14-$D19) -> 16360.5
H22: EV | I22: EV adjusted
C23: Sales growth decrease of 0,5% p.a. over the priod | H23: =$G$17 -> 16132.347 | I23: =15773338.0689619/1000 -> 15773.338 | J23: =I23-H23 -> -359.00891
C24: Sales growth increase of 0,5% p.a. over the priod | H24: =$G$17 -> 16132.347 | I24: =16496902.8049334/1000 -> 16496.903 | J24: =I24-H24 -> 364.55583
C25: R&D as % of sales decreases of 0,5% p.a. over the period | H25: =$G$17 -> 16132.347 | I25: =15795683.448582/1000 -> 15795.683 | J25: =I25-H25 -> -336.66353
C26: R&D as % of sales increases of 0,5% p.a. over the period | H26: =$G$17 -> 16132.347 | I26: =16468999.7681843/1000 -> 16469 | J26: =I26-H26 -> 336.65279

Sheet Multiples
B2: 2010
C4: Market Cap | D4: EV/Sales | E4: EV/EBITDA | F4: EV/EBIT
B6: Amgen | C6: 51166.8 | D6: 3.13 | E6: 7.18 | F6: 8.5
B7: Celgene | C7: 27818.8 | D7: 7.3 | E7: 21.2 | F7: 26.75 | I7: Minimum | J7: 25th percentile | K7: Median | L7: 75th percentile | M7: Maximum
B8: Biogen | C8: 16128.1 | D8: 3.27 | E8: 9.63 | F8: 12.36 | H8: EV/Sales | I8: =$D$29 -> 9759865.8 | J8: =$D$31-$D$29 -> 2759962.1 | K8: =$D$30-$D$31 -> 559992.3 | L8: =$D$32-$D$30 -> 12959822 | M8: =$D$28-$D$32 -> 3159956.6
B9: Baxter International | C9: 29396.7 | D9: 2.44 | E9: 11.11 | F9: 14.67 | H9: EV/EBITDA | I9: =$E$29 -> 3273814.3 | J9: =$E$31-$E$29 -> 706742.65 | K9: =$E$30-$E$31 -> 410366.7 | L9: =$E$32-$E$30 -> 2975158.6 | M9: =$E$28-$E$32 -> 2300333.3
B10: Gilead | C10: 29064.4 | D10: 5.72 | E10: 8.73 | F10: 9.33 | H10: EV/EBIT | I10: =$F$29 -> -335580 | J10: =$F$31-$F$29 -> -32768.4 | K10: =$F$30-$F$31 -> -119624.4 | L10: =F38 -> -329658 | M10: =$F$28-$F$32 -> -238459.2
B11: Genzyme | C11: 18519.6 | D11: 4.47 | E11: 34.04 | F11: 504.7 | H11: APV | I11: =F48 -> 15253539 | M11: =F47 -> 20060393
B13: Statistics | E13: consistent | F13: consistent
B14: Maximum | D14: =MAX(D6:D10) -> 7.3 | E14: =MAX(E6:E10) -> 21.2 | F14: =MAX(F6:F10) -> 26.75
B15: Minimum | D15: =MIN(D6:D10) -> 2.44 | E15: =MIN(E6:E10) -> 7.18 | F15: =MIN(F6:F10) -> 8.5
B16: Median | D16: =MEDIAN(D6:D10) -> 3.27 | E16: =MEDIAN(E6:E10) -> 9.63 | F16: =MEDIAN(F6:F10) -> 12.36
B17: 25th percentile | D17: =QUARTILE(D6:D10,1) -> 3.13 | E17: =QUARTILE(E6:E10,1) -> 8.73 | F17: =QUARTILE(F6:F10,1) -> 9.33
B18: 75th percentile | D18: =_xlfn.QUARTILE.EXC(D6:D10,3) -> 6.51 | E18: =_xlfn.QUARTILE.EXC(E6:E10,3) -> 16.155 | F18: =_xlfn.QUARTILE.EXC(F6:F10,3) -> 20.71
B19: Average | D19: =AVERAGE(D6:D10) -> 4.372 | E19: =AVERAGE(E6:E10) -> 11.57 | F19: =AVERAGE(F6:F10) -> 14.322
B20: Standard Deviation | D20: =_xlfn.STDEV.P(D14:D18) -> 1.9752974 | E20: =_xlfn.STDEV.P(E14:E18) -> 5.2871546 | F20: =_xlfn.STDEV.P(F14:F18) -> 7.0799802 | G20: Check whether standard deviation formula is correct
B21: Min Point | D21: =D15 -> 2.44 | E21: =E15 -> 7.18 | F21: =F15 -> 8.5
B22: 25th Point | D22: =D17-D15 -> 0.69 | E22: =E17-E15 -> 1.55 | F22: =F17-F15 -> 0.83
B23: Median Point | D23: =D16-D17 -> 0.14 | E23: =E16-E17 -> 0.9 | F23: =F16-F17 -> 3.03
B24: 75th Point | D24: =D18-D16 -> 3.24 | E24: =E18-E16 -> 6.525 | F24: =F18-F16 -> 8.35
B25: Maximum Point | D25: =D14-D18 -> 0.79 | E25: =E14-E18 -> 5.045 | F25: =F14-F18 -> 6.04
B27: Genzyme | D27: EV (X*Sales) | E27: EV (X*EBITDA) | F27: EV (X*EBIT)
B28: Maximum | D28: =D14*$C$41 -> 29199598 | E28: =E14*$C$42 -> 9666415.6 | F28: =F14*$C$43 -> -1056090
B29: Minimum | D29: =D15*$C$41 -> 9759865.8 | E29: =E15*$C$42 -> 3273814.3 | F29: =F15*$C$43 -> -335580
B30: Median | D30: =D16*$C$41 -> 13079820 | E30: =E16*$C$42 -> 4390923.7 | F30: =F16*$C$43 -> -487972.8
B31: 25th percentile | D31: =D17*$C$41 -> 12519828 | E31: =E17*$C$42 -> 3980557 | F31: =F17*$C$43 -> -368348.4
B32: 75th percentile | D32: =D18*$C$41 -> 26039642 | E32: =E18*$C$42 -> 7366082.3 | F32: =F18*$C$43 -> -817630.8
B33: Average | D33: =D19*$C$41 -> 17487760 | E33: =E19*$C$42 -> 5275491.9 | F33: =F19*$C$43 -> -565432.56
B34: Standard Deviation | D34: =D20*$C$41 -> 7901081.1 | E34: =E20*$C$42 -> 2410746.9 | F34: =F20*$C$43 -> -279517.62
B35: Min Point | D35: =$D$29 -> 9759865.8 | E35: =$E$29 -> 3273814.3 | F35: =$F$29 -> -335580
B36: 25th Point | D36: =$D$31-$D$29 -> 2759962.1 | E36: =$E$31-$E$29 -> 706742.65 | F36: =$F$31-$F$29 -> -32768.4
B37: Median Point | D37: =$D$30-$D$31 -> 559992.3 | E37: =$E$30-$E$31 -> 410366.7 | F37: =$F$30-$F$31 -> -119624.4
B38: 75th Point | D38: =$D$32-$D$30 -> 12959822 | E38: =$E$32-$E$30 -> 2975158.6 | F38: =$F$32-$F$30 -> -329658
B39: Maximum Point | D39: =$D$28-$D$32 -> 3159956.6 | E39: =$E$28-$E$32 -> 2300333.3 | F39: =$F$28-$F$32 -> -238459.2
B41: Sales | C41: 3999945 | D41: (thousand $)
B42: EBITDA | C42: 455963 | D42: (thousand $)
B43: EBIT | C43: -39480 | D43: (thousand $)
B44: EV | C44: 20056310 | D44: (thousand $)
C46: EV/EBIT | D46: EV/EBITDA | E46: EV/sales | F46: APV
B47: Max | C47: =F28 -> -1056090 | D47: =E28 -> 9666415.6 | E47: =D29 -> 9759865.8 | F47: 20060393
B48: Min | C48: =F29 -> -335580 | D48: =E29 -> 3273814.3 | E48: =D28 -> 29199598 | F48: 15253539

Sheet Opti K structure
B2: Estimate the unlevered beta for the firm
B3: Levered Beta of Genzyme | E3: ='[4]Cost of Equity'!B35 -> 0.57378462
B4: Marginal Tax rate | E4: 0.4
B5: Market value of equity | E5: =[5]WACC!G19 -> 18621007
B6: Market value of debt | E6: =[5]WACC!G15 -> 1439386.2
B7: Unlevered Beta | E7: =E3/(1+(1-E4)*E6/E5) -> 0.54835235
B8: market premium | E8: 0.1807
B9: risk free return | E9: 0.0012
B11: Genzyme curent financials | H11: Ratings comparison at current debt ratio
B12: EBITDA | E12: ='[5]Free Cash Flow'!J9 -> 455963 | H12: Current Interest coverage ratio = | K12: =E16/E15 -> 31.530453
B13: D&A | E13: =-'[5]Free Cash Flow'!J11 -> 495443 | H13: Rating based upon coverage = | K13: =VLOOKUP(K12,$N$32:$R$46,3,TRUE) -> Aaa/AAA
B14: EBIT | E14: =E12-E13 -> -39480 | H14: Interest rate based upon coverage = | K14: =VLOOKUP(K13,P32:R46,2,FALSE)+E9 -> 0.0072
B15: Interest Expenses | E15: 7026 | H15: Current rating for company = | K15: A3/A-
B16: Adjusted EBIT | E16: =AVERAGE('[5]Free Cash Flow'!D16,'[5]Free Cash Flow'!E16,'[5]Free Cash Flow'!F16,'[5]Free Cash Flow'!G16,'[5]Free Cash Flow'!H16) -> 221532.96 | F16: average of last 5 years | H16: Current interest rate on debt = | K16: =VLOOKUP(K15,$P$32:$R$46,2,FALSE)+E9 -> 0.0137
B17: Adjusted Interest Expenses | E17: =1401.33863342784+E15 -> 8427.3386 | H17: Current Bankruptcy Probability = | K17: =VLOOKUP(K15,$P$32:$R$46,3,FALSE) -> 0.025
B18: Market Value of the firm | E18: =[5]WACC!G21 -> 20060393 | H18: Cost of bankruptcy = | K18: 0.25
B20: Cost of equity
B21: Debt to Capital Ratio | C21: D/E Ratio | D21: Levered Beta | E21: Cost of Equity
B22: 0 | C22: =B22/(1-B22) -> 0 | D22: =$E$7*(1+(1-$E$4)*C22) -> 0.54835235 | E22: =$E$9+D22*$E$8 -> 0.10028727
B23: 0.1 | C23: =B23/(1-B23) -> 0.11111111 | D23: =$E$7*(1+(1-$E$4)*C23) -> 0.58490917 | E23: =$E$9+D23*$E$8 -> 0.10689309
B24: 0.2 | C24: =B24/(1-B24) -> 0.25 | D24: =$E$7*(1+(1-$E$4)*C24) -> 0.6306052 | E24: =$E$9+D24*$E$8 -> 0.11515036
B25: 0.3 | C25: =B25/(1-B25) -> 0.42857143 | D25: =$E$7*(1+(1-$E$4)*C25) -> 0.68935724 | E25: =$E$9+D25*$E$8 -> 0.12576685
B26: 0.4 | C26: =B26/(1-B26) -> 0.66666667 | D26: =$E$7*(1+(1-$E$4)*C26) -> 0.76769329 | E26: =$E$9+D26*$E$8 -> 0.13992218
B27: 0.5 | C27: =B27/(1-B27) -> 1 | D27: =$E$7*(1+(1-$E$4)*C27) -> 0.87736376 | E27: =$E$9+D27*$E$8 -> 0.15973963
B28: 0.6 | C28: =B28/(1-B28) -> 1.5 | D28: =$E$7*(1+(1-$E$4)*C28) -> 1.0418695 | E28: =$E$9+D28*$E$8 -> 0.18946581
B29: 0.7 | C29: =B29/(1-B29) -> 2.3333333 | D29: =$E$7*(1+(1-$E$4)*C29) -> 1.3160456 | E29: =$E$9+D29*$E$8 -> 0.23900945 | N29: For large non-financial service companies with market cap > $ 5 billion
B30: 0.8 | C30: =B30/(1-B30) -> 4 | D30: =$E$7*(1+(1-$E$4)*C30) -> 1.864398 | E30: =$E$9+D30*$E$8 -> 0.33809672 | N30: If interest coverage ratio is
B31: 0.9 | C31: =B31/(1-B31) -> 9 | D31: =$E$7*(1+(1-$E$4)*C31) -> 3.509455 | E31: =$E$9+D31*$E$8 -> 0.63535853 | N31: greater than | O31: ≤ to | P31: Rating is | Q31: Spread is | R31: Bankruptcy Probability
N32: -100000 | O32: 0.199999 | P32: D2/D | Q32: 0.14 | R32: 1
B33: Cost of debt | N33: 0.2 | O33: 0.649999 | P33: C2/C | Q33: 0.105 | R33: 0.85
B34: D/(D+E) | C34: 0 | D34: 0.1 | E34: 0.2 | F34: 0.3 | G34: 0.4 | H34: 0.5 | I34: 0.6 | J34: 0.7 | K34: 0.8 | L34: 0.9 | M34: 0.18 | N34: 0.65 | O34: 0.799999 | P34: Ca2/CC | Q34: 0.08 | R34: 0.7
B35: D/E | C35: =C34/(1-C34) -> 0 | D35: =D34/(1-D34) -> 0.11111111 | E35: =E34/(1-E34) -> 0.25 | F35: =F34/(1-F34) -> 0.42857143 | G35: =G34/(1-G34) -> 0.66666667 | H35: =H34/(1-H34) -> 1 | I35: =I34/(1-I34) -> 1.5 | J35: =J34/(1-J34) -> 2.3333333 | ... M35: =M34/(1-M34) -> 0.2195122 | N35: 0.8 | O35: 1.249999 | P35: Caa/CCC | Q35: 0.065 | R35: 0.5901
B36: $ Debt | C36: =C34*$E$18 -> 0 | D36: =D34*$E$18 -> 2006039.3 | E36: =E34*$E$18 -> 4012078.7 | F36: =F34*$E$18 -> 6018118 | G36: =G34*$E$18 -> 8024157.3 | H36: =H34*$E$18 -> 10030197 | I36: =I34*$E$18 -> 12036236 | J36: =J34*$E$18 -> 14042275 | ... M36: =M34*$E$18 -> 3610870.8 | N36: 1.25 | O36: 1.499999 | P36: B3/B- | Q36: 0.055 | R36: 0.45
N37: 1.5 | O37: 1.749999 | P37: Ba1/BB+ | Q37: 0.045 | R37: 0.1
B38: EBITDA | C38: =$E$12 -> 455963 | D38: =$E$12 -> 455963 | E38: =$E$12 -> 455963 | F38: =$E$12 -> 455963 | G38: =$E$12 -> 455963 | H38: =$E$12 -> 455963 | I38: =$E$12 -> 455963 | J38: =$E$12 -> 455963 | ... M38: =$E$12 -> 455963 | N38: 1.75 | O38: 1.999999 | P38: Ba2/BB | Q38: 0.0375 | R38: 0.1663
B39: D&A | C39: =$E$13 -> 495443 | D39: =$E$13 -> 495443 | E39: =$E$13 -> 495443 | F39: =$E$13 -> 495443 | G39: =$E$13 -> 495443 | H39: =$E$13 -> 495443 | I39: =$E$13 -> 495443 | J39: =$E$13 -> 495443 | ... M39: =$E$13 -> 495443 | N39: 2 | O39: 2.2499999 | P39: B1/B+ | Q39: 0.03 | R39: 0.25
B40: Ajusted EBIT | C40: =$E$16 -> 221532.96 | D40: =$E$16 -> 221532.96 | E40: =$E$16 -> 221532.96 | F40: =$E$16 -> 221532.96 | G40: =$E$16 -> 221532.96 | H40: =$E$16 -> 221532.96 | I40: =$E$16 -> 221532.96 | J40: =$E$16 -> 221532.96 | ... M40: =$E$16 -> 221532.96 | N40: 2.25 | O40: 2.49999 | P40: B2/B | Q40: 0.025 | R40: 0.368
B41: Interest | C41: 0 | D41: =D36*D45 -> 18455.562 | E41: =E36*0.0122 -> 48947.36 | F41: =F36*0.0137 -> 82448.217 | G41: =G36*0.0312 -> 250353.71 | H41: =H36*0.1062 -> 1065206.9 | I41: =I36*0.1412 -> 1699516.5 | J41: =J36*I45 -> 1982769.3 | K41: =K36*J45 -> 2266022 | L41: =L36*K45 -> 2549274.8 | M41: =M36*0.72% -> 25998.27 | N41: 2.5 | O41: 2.999999 | P41: Baa2/BBB | Q41: 0.016 | R41: 0.0754
N42: 3 | O42: 4.249999 | P42: A3/A- | Q42: 0.0125 | R42: 0.025
B43: Pre-tax Int. Cov | C43: infinite | D43: =D40/D41 -> 12.003588 | E43: =E40/E41 -> 4.525943 | F43: =F40/F41 -> 2.6869345 | G43: =G40/G41 -> 0.88487988 | H43: =H40/H41 -> 0.20797177 | I43: =I40/I41 -> 0.13035058 | J43: =J40/J41 -> 0.11172907 | K43: =K40/K41 -> 0.097762933 | ... M43: =M40/M41 -> 8.5210655 | N43: 4.25 | O43: 5.499999 | P43: A2/A | Q43: 0.011 | R43: 0.0066
B44: Likely Rating | C44: Aaa/AAA | D44: =VLOOKUP(D43,$N$32:$R$46,3,TRUE) -> Aaa/AAA | E44: =VLOOKUP(E43,$N$32:$R$46,3,TRUE) -> A2/A | F44: =VLOOKUP(F43,$N$32:$R$46,3,TRUE) -> Baa2/BBB | G44: =VLOOKUP(G43,$N$32:$R$46,3,TRUE) -> Caa/CCC | H44: =VLOOKUP(H43,$N$32:$R$46,3,TRUE) -> C2/C | I44: =VLOOKUP(I43,$N$32:$R$46,3,TRUE) -> D2/D | J44: =VLOOKUP(J43,$N$32:$R$46,3,TRUE) -> D2/D | K44: =VLOOKUP(K43,$N$32:$R$46,3,TRUE) -> D2/D | ... M44: =VLOOKUP(M43,$N$32:$R$46,3,TRUE) -> Aaa/AAA | N44: 5.5 | O44: 6.499999 | P44: A1/A+ | Q44: 0.01 | R44: 0.006
B45: Pre-tax cost of debt | C45: =$E$9+VLOOKUP(C44,$P$32:$Q$46,2,FALSE) -> 0.0072 | D45: 0.0092 | E45: =$E$9+VLOOKUP(E44,$P$32:$Q$46,2,FALSE) -> 0.0122 | F45: 0.0137 | G45: 0.0662 | H45: 0.1062 | I45: 0.1412 | J45: =$E$9+VLOOKUP(J44,$P$32:$Q$46,2,FALSE) -> 0.1412 | K45: =$E$9+VLOOKUP(K44,$P$32:$Q$46,2,FALSE) -> 0.1412 | L45: =$E$9+VLOOKUP(L44,$P$32:$Q$46,2,FALSE) -> 0.1412 | M45: =$E$9+VLOOKUP(M44,$P$32:$Q$46,2,FALSE) -> 0.0072 | N45: 6.5 | O45: 8.499999 | P45: Aa2/AA | Q45: 0.008 | R45: 0.0051
B46: Probability of Bankruptcy | C46: =VLOOKUP(C44,$P$32:$R$46,3,FALSE) -> 0.0007 | D46: =VLOOKUP(D44,$P$32:$R$46,3,FALSE) -> 0.0007 | E46: =VLOOKUP(E44,$P$32:$R$46,3,FALSE) -> 0.0066 | F46: =VLOOKUP(F44,$P$32:$R$46,3,FALSE) -> 0.0754 | G46: =VLOOKUP(G44,$P$32:$R$46,3,FALSE) -> 0.5901 | H46: =VLOOKUP(H44,$P$32:$R$46,3,FALSE) -> 0.85 | I46: =VLOOKUP(I44,$P$32:$R$46,3,FALSE) -> 1 | J46: =VLOOKUP(J44,$P$32:$R$46,3,FALSE) -> 1 | ... M46: =VLOOKUP(M44,$P$32:$R$46,3,FALSE) -> 0.0007 | N46: 8.5 | O46: 100000 | P46: Aaa/AAA | Q46: 0.006 | R46: 0.0007
B47: After-tax cost of debt | C47: =C45*(1-$E$4) -> 0.00432 | D47: =D45*(1-$E$4) -> 0.00552 | E47: =E45*(1-$E$4) -> 0.00732 | F47: =F45*(1-$E$4) -> 0.00822 | G47: =G45*(1-$E$4) -> 0.03972 | H47: =H45*(1-$E$4) -> 0.06372 | I47: =I45*(1-$E$4) -> 0.08472 | J47: =J45*(1-$E$4) -> 0.08472 | ... M47: =M45*(1-$E$4) -> 0.00432
B48: rA | C48: =$E$6/($E$5+$E$6)*C45+$E$6/($E$5+$E$6)*E22 -> 0.0077124953 | N48: source: http://pages.stern.nyu.edu/~adamodar/New_Home_Page/datafile/ratings.htm
B49: Unlev. Firm Value | C49: =$E$18-$E$6*$E$4+$E$18*$K$17*$K$18 -> 19610016 | D49: =$E$18-$E$6*$E$4+$E$18*$K$17*$K$18 -> 19610016 | E49: =$E$18-$E$6*$E$4+$E$18*$K$17*$K$18 -> 19610016 | F49: =$E$18-$E$6*$E$4+$E$18*$K$17*$K$18 -> 19610016 | G49: =$E$18-$E$6*$E$4+$E$18*$K$17*$K$18 -> 19610016 | H49: =$E$18-$E$6*$E$4+$E$18*$K$17*$K$18 -> 19610016 | I49: =$E$18-$E$6*$E$4+$E$18*$K$17*$K$18 -> 19610016 | J49: =$E$18-$E$6*$E$4+$E$18*$K$17*$K$18 -> 19610016 | ... M49: =$E$18-$E$6*$E$4+$E$18*$K$17*$K$18 -> 19610016
B50: adjusted marginal tax rate | C50: =E4 -> 0.4 | D50: =E4 -> 0.4 | E50: =E4 -> 0.4 | F50: =E4 -> 0.4 | G50: =$G$40*$E$4/G41 -> 0.35395195 | H50: =$G$40*$E$4/H41 -> 0.083188707 | I50: =$G$40*$E$4/I41 -> 0.052140231 | J50: =$G$40*$E$4/J41 -> 0.044691626 | K50: =$G$40*$E$4/K41 -> 0.039105173 | L50: =$G$40*$E$4/L41 -> 0.034760154 | M50: =E4 -> 0.4
B51: Tax Benefits | C51: =C41*C50 -> 0 | D51: =D41*D50 -> 7382.2248 | E51: =E41*E50 -> 19578.944 | F51: =F41*F50 -> 32979.287 | G51: =G41*G50 -> 88613.184 | H51: =H41*H50 -> 88613.184 | I51: =I41*I50 -> 88613.184 | J51: =J41*J50 -> 88613.184 | ... M51: =M41*M50 -> 10399.308
B52: Bankruptcy Cost | C52: =C46*$K$18*(C49+C51) -> 3431.7529 | D52: =D46*$K$18*(D49+D51) -> 3433.0448 | E52: =E46*$K$18*(E49+E51) -> 32388.832 | F52: =F46*$K$18*(F49+F51) -> 370270.47 | G52: =G46*$K$18*(G49+G51) -> 2906040.3 | H52: =H46*$K$18*(H49+H51) -> 4185958.8 | I52: =I46*$K$18*(I49+I51) -> 4924657.4 | J52: =J46*$K$18*(J49+J51) -> 4924657.4 | ... M52: =M46*$K$18*(M49+M51) -> 3433.5727
B53: Levered Firm Value | C53: =C49+C51-C52 -> 19606585 | D53: =D49+D51-D52 -> 19613966 | E53: =E49+E51-E52 -> 19597206 | F53: =F49+F51-F52 -> 19272725 | G53: =G49+G51-G52 -> 16792589 | H53: =H49+H51-H52 -> 15512671 | I53: =I49+I51-I52 -> 14773972 | J53: =J49+J51-J52 -> 14773972 | ... M53: =M49+M51-M52 -> 19616982
