Workbook
Name ScenarioSelection: '[1]Table of Contents'!$J$1:$J$3

Sheet Project Title
B2: Finance and Economics of M&A
B4: Acquisition of Pharmacia Corporation by Pfizer Inc.
B5: Standalone Valuation of Pfizer Pre-Merger
B16: by
B18: Marc Schwarz
B24: EBS Universität für Wirtschaft und Recht
B25: Spring Term 2018

Sheet Summary
D3: Pfizer Inc (Pfizer US) Summary of Results
D6: Expected Enterprise Value based on Method:
D8: In Millions of USD | I8: Min | J8: 25th | K8: Median | L8: 75th | M8: Max | O8: Min Point | P8: 25th Point | Q8: Median Point | R8: 75th Point | S8: Max Point
D9: Discounted Cash Flow Method (Base/Base Case) | K9: ='1.2 DCF Analysis'!F52 -> 275607.26
D10: Multiples based on Assets | I10: =MIN('1.1 Multiple Valuation'!K38:K41) -> 144818.26 | J10: =_xlfn.QUARTILE.EXC('1.1 Multiple Valuation'!K38:K41,1) -> 146870.73 | K10: ='1.1 Multiple Valuation'!K42 -> 194020.94 | L10: =_xlfn.QUARTILE.EXC('1.1 Multiple Valuation'!K38:K41,3) -> 235799.87 | M10: =MAX('1.1 Multiple Valuation'!K38:K41) -> 236061.91 | O10: =I10 -> 144818.26 | P10: =J10-I10 -> 2052.4746 | Q10: =K10-J10 -> 47150.208 | R10: =L10-K10 -> 41778.925 | S10: =M10-L10 -> 262.04723
D11: Price Multiples based on Cash Flow | I11: =MIN('1.1 Multiple Valuation'!I52:I55) -> 141078.44 | J11: =_xlfn.QUARTILE.EXC('1.1 Multiple Valuation'!I52:I55,1) -> 154073.4 | K11: ='1.1 Multiple Valuation'!I56 -> 207412.85 | L11: =_xlfn.QUARTILE.EXC('1.1 Multiple Valuation'!I52:I55,3) -> 235783.87 | M11: =MAX('1.1 Multiple Valuation'!I52:I55) -> 240456.01 | O11: =I11 -> 141078.44 | P11: =J11-I11 -> 12994.962 | Q11: =K11-J11 -> 53339.451 | R11: =L11-K11 -> 28371.013 | S11: =M11-L11 -> 4672.1497
D12: Value Multiples based on Cash Flow | I12: =MIN('1.1 Multiple Valuation'!I24:I27) -> 147344.77 | J12: =_xlfn.QUARTILE.EXC('1.1 Multiple Valuation'!I24:I27,1) -> 160242.81 | K12: ='1.1 Multiple Valuation'!I28 -> 208015.59 | L12: =_xlfn.QUARTILE.EXC('1.1 Multiple Valuation'!I24:I27,3) -> 239965.01 | M12: =MAX('1.1 Multiple Valuation'!I24:I27) -> 247588.6 | O12: =I12 -> 147344.77 | P12: =J12-I12 -> 12898.045 | Q12: =K12-J12 -> 47772.782 | R12: =L12-K12 -> 31949.419 | S12: =M12-L12 -> 7623.5905

Sheet 1. Valuations>>>

Sheet 1.1 Multiple Valuation
C2: Pfizer Inc (Pfizer US) Trading Multiples
B6: Comparable Pharma Companies | C6: Price per Share | D6: Market | E6: Enterprise | F6: EBITDA | G6: Bookvalue of Equity | H6: Shares Outstanding | I6: Diluted EPS | J6: P/E Ratio | K6: Price/Book Ratio | L6: Enterprise Value/EBITDA
B7: in Millions of USD except per share | D7: Capitalization | E7: Value | L7: FY 2001
B8: Pfizer Inc. | C8: ='3.4 Trading Multiples Bloomberg'!C10 -> 39.85 | D8: ='3.4 Trading Multiples Bloomberg'!F10 -> 250525.88 | E8: ='3.4 Trading Multiples Bloomberg'!E10 -> 250782.88 | F8: ='3.4 Trading Multiples Bloomberg'!U10 -> 11776 | G8: ='3.4 Trading Multiples Bloomberg'!Y10 -> 18293 | H8: ='3.4 Trading Multiples Bloomberg'!L11 -> 6162.164 | I8: ='3.4 Trading Multiples Bloomberg'!S10 -> 1.22 | J8: ='3.4 Trading Multiples Bloomberg'!Z10 -> 31.378 | K8: ='3.4 Trading Multiples Bloomberg'!AA10 -> 13.674 | L8: ='3.4 Trading Multiples Bloomberg'!V10 -> 21.2961
B9: Eli Lilly and Co | C9: ='3.4 Trading Multiples Bloomberg'!C35 -> 78.54 | D9: ='3.4 Trading Multiples Bloomberg'!F35 -> 88295.278 | E9: ='3.4 Trading Multiples Bloomberg'!E35 -> 87982.678 | F9: ='3.4 Trading Multiples Bloomberg'!U35 -> 4184.7 | G9: ='3.4 Trading Multiples Bloomberg'!Y35 -> 7104 | H9: ='3.4 Trading Multiples Bloomberg'!L36 -> 1123.374 | I9: ='3.4 Trading Multiples Bloomberg'!S35 -> 2.55 | J9: ='3.4 Trading Multiples Bloomberg'!Z35 -> 28.4565 | K9: ='3.4 Trading Multiples Bloomberg'!AA35 -> 12.4195 | L9: ='3.4 Trading Multiples Bloomberg'!V35 -> 21.0248
B10: Johnson & Johnson | C10: ='3.4 Trading Multiples Bloomberg'!C59 -> 59.1 | D10: ='3.4 Trading Multiples Bloomberg'!F59 -> 180141.11 | E10: ='3.4 Trading Multiples Bloomberg'!E59 -> 174951.11 | F10: ='3.4 Trading Multiples Bloomberg'!U59 -> 9490 | G10: ='3.4 Trading Multiples Bloomberg'!Y59 -> 24233 | H10: ='3.4 Trading Multiples Bloomberg'!L60 -> 2970.582 | I10: ='3.4 Trading Multiples Bloomberg'!S59 -> 1.84 | J10: ='3.4 Trading Multiples Bloomberg'!Z59 -> 30.9424 | K10: ='3.4 Trading Multiples Bloomberg'!AA59 -> 7.4316 | L10: ='3.4 Trading Multiples Bloomberg'!V59 -> 18.4353
B11: Merck & Co. | C11: ='3.4 Trading Multiples Bloomberg'!C83 -> 55.6517 | D11: ='3.4 Trading Multiples Bloomberg'!F83 -> 133752.95 | E11: ='3.4 Trading Multiples Bloomberg'!E83 -> 144169.15 | F11: ='3.4 Trading Multiples Bloomberg'!U83 -> 11522.2 | G11: ='3.4 Trading Multiples Bloomberg'!Y83 -> 20887.6 | H11: ='3.4 Trading Multiples Bloomberg'!L84 -> 2245.556 | I11: ='3.4 Trading Multiples Bloomberg'!S83 -> 3.14 | J11: ='3.4 Trading Multiples Bloomberg'!Z83 -> 17.7235 | K11: ='3.4 Trading Multiples Bloomberg'!AA83 -> 7.8804 | L11: ='3.4 Trading Multiples Bloomberg'!V83 -> 12.5123
B12: Bristol-Myers Squibb | C12: ='3.4 Trading Multiples Bloomberg'!C107 -> 51 | D12: ='3.4 Trading Multiples Bloomberg'!F107 -> 98677.685 | E12: ='3.4 Trading Multiples Bloomberg'!E107 -> 99434.685 | F12: ='3.4 Trading Multiples Bloomberg'!U107 -> 5886 | G12: ='3.4 Trading Multiples Bloomberg'!Y107 -> 9075 | H12: ='3.4 Trading Multiples Bloomberg'!L108 -> 1937.045 | I12: ='3.4 Trading Multiples Bloomberg'!S107 -> 2.46 | J12: ='3.4 Trading Multiples Bloomberg'!Z107 -> 24.6377 | K12: ='3.4 Trading Multiples Bloomberg'!AA107 -> 12.3622 | L12: ='3.4 Trading Multiples Bloomberg'!V107 -> 16.8934
B13: Average (excl. Pfizer) | C13: =AVERAGE(C9:C12) -> 61.072925 | D13: =AVERAGE(D9:D12) -> 125216.76 | E13: =AVERAGE(E9:E12) -> 126634.41 | F13: =AVERAGE(F9:F12) -> 7770.725 | G13: =AVERAGE(G9:G12) -> 15324.9 | H13: =AVERAGE(H9:H11) -> 2113.1707 | I13: =AVERAGE(I9:I11) -> 2.51 | J13: =AVERAGE(J9:J11) -> 25.707467 | K13: =AVERAGE(K9:K11) -> 9.2438333 | L13: =AVERAGE(L9:L11) -> 17.324133
B14: 1st Quartile (excl. Pfizer) | C14: =_xlfn.QUARTILE.EXC(C9:C12,1) -> 52.162925 | D14: =_xlfn.QUARTILE.EXC(D9:D12,1) -> 90890.88 | E14: =_xlfn.QUARTILE.EXC(E9:E12,1) -> 90845.68 | F14: =_xlfn.QUARTILE.EXC(F9:F12,1) -> 4610.025 | G14: =_xlfn.QUARTILE.EXC(G9:G12,1) -> 7596.75 | H14: =_xlfn.QUARTILE.EXC(H9:H12,1) -> 1326.7918 | I14: =_xlfn.QUARTILE.EXC(I9:I12,1) -> 1.995 | J14: =_xlfn.QUARTILE.EXC(J9:J12,1) -> 19.45205 | ... L14: =_xlfn.QUARTILE.EXC(L9:L12,1) -> 13.607575
B15: Median (excl. Pfizer) | C15: =MEDIAN(C9:C12) -> 57.37585 | D15: =MEDIAN(D9:D12) -> 116215.32 | E15: =MEDIAN(E9:E12) -> 121801.92 | F15: =MEDIAN(F9:F12) -> 7688 | G15: =MEDIAN(G9:G12) -> 14981.3 | H15: =MEDIAN(H9:H12) -> 2091.3005 | I15: =MEDIAN(I9:I12) -> 2.505 | J15: =MEDIAN(J9:J12) -> 26.5471 | ... L15: =MEDIAN(L9:L12) -> 17.66435
B16: 3rd Quartile (excl. Pfizer) | C16: =_xlfn.QUARTILE.EXC(C9:C12,3) -> 73.68 | D16: =_xlfn.QUARTILE.EXC(D9:D12,3) -> 168544.07 | E16: =_xlfn.QUARTILE.EXC(E9:E12,3) -> 167255.62 | F16: =_xlfn.QUARTILE.EXC(F9:F12,3) -> 11014.15 | G16: =_xlfn.QUARTILE.EXC(G9:G12,3) -> 23396.65 | H16: =_xlfn.QUARTILE.EXC(H9:H12,3) -> 2789.3255 | I16: =_xlfn.QUARTILE.EXC(I9:I12,3) -> 2.9925 | J16: =_xlfn.QUARTILE.EXC(J9:J12,3) -> 30.320925 | ... L16: =_xlfn.QUARTILE.EXC(L9:L12,3) -> 20.377425
B17: Bloomberg (as of 16.04.2018)
B20: 1. Value Multiples based on Cash Flows
B21: Comparable Pharma Companies | C21: Enterprise Value | D21: EBITDA (1) | E21: EBITDA (2) | F21: EV/EBITDA (1) | G21: EV/EBITDA (2) | H21: EV Pfizer (Calculated) | I21: EV Pfizer
B22: in Millions of USD except per share
B23: Pfizer Inc. | C23: =E8 -> 250782.88 | D23: =F8 -> 11776 | E23: =C23/F23 -> 11776 | F23: =L8 -> 21.2961 | G23: =C23/D23 -> 21.2961
B24: Eli Lilly and Co | C24: =E9 -> 87982.678 | D24: =F9 -> 4184.7 | E24: =C24/F24 -> 4184.7094 | F24: =L9 -> 21.0248 | G24: =C24/D24 -> 21.024847 | H24: =$D$23*F24 -> 247588.04 | I24: =$E$23*G24 -> 247588.6
B25: Johnson & Johnson | C25: =E10 -> 174951.11 | D25: =F10 -> 9490 | E25: =C25/F25 -> 9490.0064 | F25: =L10 -> 18.4353 | G25: =C25/D25 -> 18.435312 | H25: =$D$23*F25 -> 217094.09 | I25: =$E$23*G25 -> 217094.24
B26: Merck & Co. | C26: =E11 -> 144169.15 | D26: =F11 -> 11522.2 | E26: =C26/F26 -> 11522.194 | F26: =L11 -> 12.5123 | G26: =C26/D26 -> 12.512293 | H26: =$D$23*F26 -> 147344.84 | I26: =$E$23*G26 -> 147344.77
B27: Bristol-Myers Squibb | C27: =E12 -> 99434.685 | D27: =F12 -> 5886 | E27: =C27/F27 -> 5886.0078 | F27: =L12 -> 16.8934 | G27: =C27/D27 -> 16.893423 | H27: =$D$23*F27 -> 198936.68 | I27: =$E$23*G27 -> 198936.95
B28: Median Peer Group | C28: =MEDIAN(C24:C27) -> 121801.92 | D28: =MEDIAN(D24:D27) -> 7688 | E28: =MEDIAN(E24:E27) -> 7688.0071 | F28: =MEDIAN(F24:F27) -> 17.66435 | G28: =MEDIAN(G24:G27) -> 17.664367 | H28: =MEDIAN(H24:H27) -> 208015.39 | I28: =MEDIAN(I24:I27) -> 208015.59
B29: 1st Quartile (excl. Pfizer) | C29: =_xlfn.QUARTILE.EXC(C24:C27,1) -> 90845.68 | D29: =_xlfn.QUARTILE.EXC(D24:D27,1) -> 4610.025 | E29: =_xlfn.QUARTILE.EXC(E24:E27,1) -> 4610.034 | F29: =_xlfn.QUARTILE.EXC(F24:F27,1) -> 13.607575 | G29: =_xlfn.QUARTILE.EXC(G24:G27,1) -> 13.607576 | H29: =_xlfn.QUARTILE.EXC(H24:H27,1) -> 160242.8 | I29: =_xlfn.QUARTILE.EXC(I24:I27,1) -> 160242.81
B30: 3rd Quartile (excl. Pfizer) | C30: =_xlfn.QUARTILE.EXC(C24:C27,3) -> 167255.62 | D30: =_xlfn.QUARTILE.EXC(D24:D27,3) -> 11014.15 | E30: =_xlfn.QUARTILE.EXC(E24:E27,3) -> 11014.147 | F30: =_xlfn.QUARTILE.EXC(F24:F27,3) -> 20.377425 | G30: =_xlfn.QUARTILE.EXC(G24:G27,3) -> 20.377463 | H30: =_xlfn.QUARTILE.EXC(H24:H27,3) -> 239964.56 | I30: =_xlfn.QUARTILE.EXC(I24:I27,3) -> 239965.01
B31: Bloomberg (as of 16.04.2018)
B34: 2. Multiples Based on Assets
B35: Comparable Pharma Companies | C35: Price per Share | D35: Shares Outstanding | E35: MV of Equity | F35: Bookvalue of Equity | G35: Price/Book Ratio (1) | H35: Price/Book Ratio (2) | I35: BV Equity based on P/B (1) | J35: BV Equity based on P/B (1) | K35: EV Nike based on P/B (2)
B36: in Millions of USD except per share
B37: Pfizer Inc. | C37: =C8 -> 39.85 | D37: =H8 -> 6162.164 | E37: =C37*D37 -> 245562.24 | F37: =G8 -> 18293 | G37: =E37/F37 -> 13.423836 | H37: =K8 -> 13.674
B38: Eli Lilly and Co | C38: =C9 -> 78.54 | D38: =H9 -> 1123.374 | E38: =C38*D38 -> 88229.794 | F38: =G9 -> 7104 | G38: =E38/F38 -> 12.419735 | H38: =K9 -> 12.4195 | I38: =$F$37*G38 -> 227194.2 | J38: =$F$37*H38 -> 227189.91 | K38: =J38+$C$63 -> 236061.91
B39: Johnson & Johnson | C39: =C10 -> 59.1 | D39: =H10 -> 2970.582 | E39: =C39*D39 -> 175561.4 | F39: =G10 -> 24233 | G39: =E39/F39 -> 7.244724 | H39: =K10 -> 7.4316 | I39: =$F$37*G39 -> 132527.74 | J39: =$F$37*H39 -> 135946.26 | K39: =J39+$C$63 -> 144818.26
B40: Merck & Co. | C40: =C11 -> 55.6517 | D40: =H11 -> 2245.556 | E40: =C40*D40 -> 124969.01 | F40: =G11 -> 20887.6 | G40: =E40/F40 -> 5.9829281 | H40: =K11 -> 7.8804 | I40: =$F$37*G40 -> 109445.7 | J40: =$F$37*H40 -> 144156.16 | K40: =J40+$C$63 -> 153028.16
B41: Bristol-Myers Squibb | C41: =C12 -> 51 | D41: =H12 -> 1937.045 | E41: =C41*D41 -> 98789.295 | F41: =G12 -> 9075 | G41: =E41/F41 -> 10.885873 | H41: =K12 -> 12.3622 | I41: =$F$37*G41 -> 199135.27 | J41: =$F$37*H41 -> 226141.72 | K41: =J41+$C$63 -> 235013.72
B42: Median Peer Group | C42: =MEDIAN(C38:C41) -> 57.37585 | D42: =MEDIAN(D38:D41) -> 2091.3005 | E42: =MEDIAN(E38:E41) -> 111879.15 | F42: =MEDIAN(F38:F41) -> 14981.3 | G42: =MEDIAN(G38:G41) -> 9.0652984 | H42: =MEDIAN(H38:H41) -> 10.1213 | I42: =MEDIAN(I38:I41) -> 165831.5 | J42: =MEDIAN(J38:J41) -> 185148.94 | K42: =MEDIAN(K38:K41) -> 194020.94
B43: 1st Quartile (excl. Pfizer) | C43: =_xlfn.QUARTILE.EXC(C38:C41,1) -> 52.162925 | D43: =_xlfn.QUARTILE.EXC(D38:D41,1) -> 1326.7918 | E43: =_xlfn.QUARTILE.EXC(E38:E41,1) -> 90869.669 | F43: =_xlfn.QUARTILE.EXC(F38:F41,1) -> 7596.75 | G43: =_xlfn.QUARTILE.EXC(G38:G41,1) -> 6.2983771 | H43: =_xlfn.QUARTILE.EXC(H38:H41,1) -> 7.5438 | I43: =_xlfn.QUARTILE.EXC(I38:I41,1) -> 115216.21 | J43: =_xlfn.QUARTILE.EXC(J38:J41,1) -> 137998.73 | K43: =_xlfn.QUARTILE.EXC(K38:K41,1) -> 146870.73
B44: 3rd Quartile (excl. Pfizer) | C44: =_xlfn.QUARTILE.EXC(C38:C41,3) -> 73.68 | D44: =_xlfn.QUARTILE.EXC(D38:D41,3) -> 2789.3255 | E44: =_xlfn.QUARTILE.EXC(E38:E41,3) -> 162913.3 | F44: =_xlfn.QUARTILE.EXC(F38:F41,3) -> 23396.65 | G44: =_xlfn.QUARTILE.EXC(G38:G41,3) -> 12.036269 | H44: =_xlfn.QUARTILE.EXC(H38:H41,3) -> 12.405175 | I44: =_xlfn.QUARTILE.EXC(I38:I41,3) -> 220179.47 | J44: =_xlfn.QUARTILE.EXC(J38:J41,3) -> 226927.87 | K44: =_xlfn.QUARTILE.EXC(K38:K41,3) -> 235799.87
B45: Bloomberg (as of 16.04.2018)
B48: 3. Price Multiples based on Cash Flows
B49: Comparable Pharma Companies | C49: Price per Share | D49: Diluted EPS | E49: P/E (1) | F49: P/E (2) | G49: Market Share Price (2) | H49: Market Value of Equity | I49: EV Pfizer
B50: in Millions of USD except per share
B51: Pfizer Inc. | C51: =C37 -> 39.85 | D51: =I8 -> 1.22 | E51: =C51/D51 -> 32.663934 | F51: =J8 -> 31.378 | G51: =$D$51*F51 -> 38.28116
B52: Eli Lilly and Co | C52: =C38 -> 78.54 | D52: =I9 -> 2.55 | E52: =C52/D52 -> 30.8 | F52: =J9 -> 28.4565 | G52: =$D$51*F52 -> 34.71693 | H52: =G52*$H$8 -> 213931.42 | I52: =H52+$C$63-$C$64 -> 221767.42
B53: Johnson & Johnson | C53: =C39 -> 59.1 | D53: =I10 -> 1.84 | E53: =C53/D53 -> 32.119565 | F53: =J10 -> 30.9424 | G53: =$D$51*F53 -> 37.749728 | H53: =G53*$H$8 -> 232620.01 | I53: =H53+$C$63-$C$64 -> 240456.01
B54: Merck & Co. | C54: =C40 -> 55.6517 | D54: =I11 -> 3.14 | E54: =C54/D54 -> 17.723471 | F54: =J11 -> 17.7235 | G54: =$D$51*F54 -> 21.62267 | H54: =G54*$H$8 -> 133242.44 | I54: =H54+$C$63-$C$64 -> 141078.44
B55: Bristol-Myers Squibb | C55: =C41 -> 51 | D55: =I12 -> 2.46 | E55: =C55/D55 -> 20.731707 | F55: =J12 -> 24.6377 | G55: =$D$51*F55 -> 30.057994 | H55: =G55*$H$8 -> 185222.29 | I55: =H55+$C$63-$C$64 -> 193058.29
B56: Median Peer Group | C56: =MEDIAN(C52:C55) -> 57.37585 | D56: =MEDIAN(D52:D55) -> 2.505 | E56: =MEDIAN(E52:E55) -> 25.765854 | F56: =MEDIAN(F52:F55) -> 26.5471 | G56: =MEDIAN(G52:G55) -> 32.387462 | H56: =MEDIAN(H52:H55) -> 199576.85 | I56: =MEDIAN(I52:I55) -> 207412.85
B57: 1st Quartile (excl. Pfizer) | C57: =_xlfn.QUARTILE.EXC(C52:C56,1) -> 53.32585 | D57: =_xlfn.QUARTILE.EXC(D52:D56,1) -> 2.15 | E57: =_xlfn.QUARTILE.EXC(E52:E56,1) -> 19.227589 | F57: =_xlfn.QUARTILE.EXC(F52:F56,1) -> 21.1806 | G57: =_xlfn.QUARTILE.EXC(G52:G56,1) -> 25.840332 | H57: =_xlfn.QUARTILE.EXC(H52:H56,1) -> 159232.36 | I57: =_xlfn.QUARTILE.EXC(I52:I56,1) -> 167068.36
B58: 3rd Quartile (excl. Pfizer) | C58: =_xlfn.QUARTILE.EXC(C52:C55,3) -> 73.68 | D58: =_xlfn.QUARTILE.EXC(D52:D55,3) -> 2.9925 | E58: =_xlfn.QUARTILE.EXC(E52:E55,3) -> 31.789674 | F58: =_xlfn.QUARTILE.EXC(F52:F55,3) -> 30.320925 | G58: =_xlfn.QUARTILE.EXC(G52:G55,3) -> 36.991529 | H58: =_xlfn.QUARTILE.EXC(H52:H55,3) -> 227947.87 | I58: =_xlfn.QUARTILE.EXC(I52:I55,3) -> 235783.87
B59: Bloomberg (as of 16.04.2018)
B63: Bookvalue of Debt Pfizer FY2001 | C63: ='3.2 Balance Sheets'!H76+'3.2 Balance Sheets'!H86 -> 8872
B64: Cash and Equivalents FY 2001 | C64: ='3.2 Balance Sheets'!H10 -> 1036
B65: Bloomberg (as of 16.04.2018)

Sheet 1.2 DCF Analysis
E2: Pfizer Inc (Pfizer US) DCF Valuation
E5: In Millions of USD | I5: FY 1997 A | J5: FY 1998 A | K5: FY 1999 A | L5: FY 2000 A | M5: FY 2001 A | N5: Est. Growth Rates | O5: FY 2002 E | P5: FY 2003 E | Q5: FY 2004 E | R5: FY 2005 E | S5: FY 2006 E
E7: Revenues | I7: ='3.1 Income Statements'!C9 -> 12504 | J7: ='3.1 Income Statements'!D9 -> 13544 | K7: ='3.1 Income Statements'!E9 -> 27376 | L7: ='3.1 Income Statements'!F9 -> 29355 | M7: ='3.1 Income Statements'!G9 -> 29024 | N7: =MEDIAN(J10:M10) -> 0.077731491 | O7: =M7*($N$7+1) -> 31280.079 | P7: =($N$7+1)*O7 -> 33711.526 | Q7: =($N$7+1)*P7 -> 36331.973 | R7: =($N$7+1)*Q7 -> 39156.112 | S7: =($N$7+1)*R7 -> 42199.774
E8: (+) Other Operating Income | I8: ='3.1 Income Statements'!C10 -> — | J8: ='3.1 Income Statements'!D10 -> — | K8: ='3.1 Income Statements'!E10 -> — | L8: ='3.1 Income Statements'!F10 -> — | M8: ='3.1 Income Statements'!G10 -> — | O8: ='3.1 Income Statements'!I10 -> — | P8: ='3.1 Income Statements'!J10 -> — | Q8: ='3.1 Income Statements'!K10 -> — | R8: ='3.1 Income Statements'!L10 -> — | S8: ='3.1 Income Statements'!M10 -> —
E9: (-) Operating Expenses | I9: ='3.1 Income Statements'!C15 -> 6206 | J9: ='3.1 Income Statements'!D15 -> 8856 | K9: ='3.1 Income Statements'!E15 -> 14846 | L9: ='3.1 Income Statements'!F15 -> 15658 | M9: ='3.1 Income Statements'!G15 -> 14493 | O9: =M9*($N$7+1) -> 15619.562 | P9: =O9*($N$7+1) -> 16833.694 | Q9: =P9*($N$7+1) -> 18142.203 | R9: =Q9*($N$7+1) -> 19552.423 | S9: =R9*($N$7+1) -> 21072.262
E10: Revenue Growth (y-o-y) | J10: =(J7/I7)-1 -> 0.083173385 | K10: =(K7/J7)-1 -> 1.021264 | L10: =(L7/K7)-1 -> 0.072289597 | M10: =(M7/L7)-1 -> -0.011275762 | O10: =N7 -> 0.077731491 | P10: =N7 -> 0.077731491 | Q10: =N7 -> 0.077731491 | R10: =N7 -> 0.077731491 | S10: =N7 -> 0.077731491
E12: Depreciation & Amortization | I12: ='3.3 CF Statements'!Z102 -> 428 | J12: ='3.3 CF Statements'!Y102 -> 489 | K12: ='3.3 CF Statements'!X102 -> 905 | L12: ='3.3 CF Statements'!W102 -> 968 | M12: ='3.3 CF Statements'!V102 -> 1068 | N12: =N7 -> 0.077731491 | O12: =M12*($N$12+1) -> 1151.0172 | P12: =O12*($N$12+1) -> 1240.4875 | Q12: =P12*($N$12+1) -> 1336.9125 | R12: =Q12*($N$12+1) -> 1440.8327 | S12: =R12*($N$12+1) -> 1552.8307
E14: Operating Income | I14: ='3.1 Income Statements'!C19 -> 3073 | J14: ='3.1 Income Statements'!D19 -> 2594 | K14: ='3.1 Income Statements'!E19 -> 7066 | L14: ='3.1 Income Statements'!F19 -> 8690 | M14: ='3.1 Income Statements'!G19 -> 10708 | N14: =N7 -> 0.077731491 | O14: =M14*($N$14+1) -> 11540.349 | P14: =O14*($N$14+1) -> 12437.397 | Q14: =P14*($N$14+1) -> 13404.175 | R14: =Q14*($N$14+1) -> 14446.101 | S14: =R14*($N$14+1) -> 15569.018
E15: Operating Income Margin | I15: =I14/I7 -> 0.24576136 | J15: =J14/J7 -> 0.19152392 | K15: =K14/K7 -> 0.25810929 | L15: =L14/L7 -> 0.29603134 | M15: =M14/M7 -> 0.36893605 | O15: =O14/O7 -> 0.36893605 | P15: =P14/P7 -> 0.36893605 | Q15: =Q14/Q7 -> 0.36893605 | R15: =R14/R7 -> 0.36893605 | S15: =S14/S7 -> 0.36893605
E16: Operating Income Growth | J16: =(J14/I14)-1 -> -0.15587374 | K16: =(K14/J14)-1 -> 1.7239784 | L16: =(L14/K14)-1 -> 0.229833 | M16: =(M14/L14)-1 -> 0.23222094 | O16: =(O14/M14)-1 -> 0.077731491 | P16: =(P14/O14)-1 -> 0.077731491 | Q16: =(Q14/P14)-1 -> 0.077731491 | R16: =(R14/Q14)-1 -> 0.077731491 | S16: =(S14/R14)-1 -> 0.077731491
E18: Taxes | I18: ='3.1 Income Statements'!C38 -> 775 | J18: ='3.1 Income Statements'!D38 -> 642 | K18: ='3.1 Income Statements'!E38 -> 1968 | L18: ='3.1 Income Statements'!F38 -> 2049 | M18: ='3.1 Income Statements'!G38 -> 2433 | N18: =AVERAGE(I19:M19) -> 0.24824183 | O18: =$N$18*O14 -> 2864.7974 | P18: =$N$18*P14 -> 3087.4823 | Q18: =$N$18*Q14 -> 3327.4769 | R18: =$N$18*R14 -> 3586.1267 | S18: =$N$18*S14 -> 3864.8816
E19: Average Tax Rate | I19: =I18/I14 -> 0.25219655 | J19: =J18/J14 -> 0.24749422 | K19: =K18/K14 -> 0.27851684 | L19: =L18/L14 -> 0.23578826 | M19: =M18/M14 -> 0.2272133 | O19: =$N$18 -> 0.24824183 | P19: =$N$18 -> 0.24824183 | Q19: =$N$18 -> 0.24824183 | R19: =$N$18 -> 0.24824183 | S19: =$N$18 -> 0.24824183
E21: Net Income | I21: =I14-I18 -> 2298 | J21: =J14-J18 -> 1952 | K21: =K14-K18 -> 5098 | L21: =L14-L18 -> 6641 | M21: =M14-M18 -> 8275 | O21: =O14-O18 -> 8675.5514 | P21: =P14-P18 -> 9349.915 | Q21: =Q14-Q18 -> 10076.698 | R21: =R14-R18 -> 10859.975 | S21: =S14-S18 -> 11704.137
E22: Net Income Margin | I22: =I21/I7 -> 0.18378119 | J22: =J21/J7 -> 0.14412286 | K22: =K21/K7 -> 0.18622151 | L22: =L21/L7 -> 0.22623063 | M22: =M21/M7 -> 0.28510888 | O22: =O21/O7 -> 0.27735069 | P22: =P21/P7 -> 0.27735069 | Q22: =Q21/Q7 -> 0.27735069 | R22: =R21/R7 -> 0.27735069 | S22: =S21/S7 -> 0.27735069
E23: Net Income Growth | J23: =(J21/I21)-1 -> -0.15056571 | K23: =(K21/J21)-1 -> 1.6116803 | L23: =(L21/K21)-1 -> 0.30266771 | M23: =(M21/L21)-1 -> 0.24604728 | O23: =(O21/M21)-1 -> 0.048405009 | P23: =(P21/O21)-1 -> 0.077731491 | Q23: =(Q21/P21)-1 -> 0.077731491 | R23: =(R21/Q21)-1 -> 0.077731491 | S23: =(S21/R21)-1 -> 0.077731491
E25: (+) Depreciation & Amortization | I25: =I12 -> 428 | J25: =J12 -> 489 | K25: =K12 -> 905 | L25: =L12 -> 968 | M25: =M12 -> 1068 | N25: =AVERAGE(J26:M26) -> 0.29153954 | O25: =M25*($N$25+1) -> 1379.3642 | P25: =O25*($N$25+1) -> 1781.5034 | Q25: =P25*($N$25+1) -> 2300.8821 | R25: =Q25*($N$25+1) -> 2971.6802 | S25: =R25*($N$25+1) -> 3838.0425
E26: %-Change D&A | J26: =(J25/I25)-1 -> 0.14252336 | K26: =(K25/J25)-1 -> 0.85071575 | L26: =(L25/K25)-1 -> 0.06961326 | M26: =(M25/L25)-1 -> 0.10330579 | O26: =(O25/M25)-1 -> 0.29153954 | P26: =(P25/O25)-1 -> 0.29153954 | Q26: =(Q25/P25)-1 -> 0.29153954 | R26: =(R25/Q25)-1 -> 0.29153954 | S26: =(S25/R25)-1 -> 0.29153954
E27: Net Working Capital | I27: ='3.2 Balance Sheets'!D10+'3.2 Balance Sheets'!D15+'3.2 Balance Sheets'!D12+'3.2 Balance Sheets'!D11-'3.2 Balance Sheets'!D72-'3.2 Balance Sheets'!D86-'3.2 Balance Sheets'!D89-'3.2 Balance Sheets'!D76 -> 410 | J27: ='3.2 Balance Sheets'!E10+'3.2 Balance Sheets'!E15+'3.2 Balance Sheets'!E12+'3.2 Balance Sheets'!E11-'3.2 Balance Sheets'!E72-'3.2 Balance Sheets'!E86-'3.2 Balance Sheets'!E89-'3.2 Balance Sheets'!E76 -> 2671 | K27: ='3.2 Balance Sheets'!F10+'3.2 Balance Sheets'!F15+'3.2 Balance Sheets'!F12+'3.2 Balance Sheets'!F11-'3.2 Balance Sheets'!F72-'3.2 Balance Sheets'!F86-'3.2 Balance Sheets'!F89-'3.2 Balance Sheets'!F76 -> 1628 | L27: ='3.2 Balance Sheets'!G10+'3.2 Balance Sheets'!G15+'3.2 Balance Sheets'!G12+'3.2 Balance Sheets'!G11-'3.2 Balance Sheets'!G72-'3.2 Balance Sheets'!G86-'3.2 Balance Sheets'!G89-'3.2 Balance Sheets'!G76 -> 3593 | M27: ='3.2 Balance Sheets'!H10+'3.2 Balance Sheets'!H15+'3.2 Balance Sheets'!H12+'3.2 Balance Sheets'!H11-'3.2 Balance Sheets'!H72-'3.2 Balance Sheets'!H86-'3.2 Balance Sheets'!H89-'3.2 Balance Sheets'!H76 -> 1362 | N27: =MEDIAN(I27:M27) -> 1628 | O27: =N27 -> 1628 | P27: =O27 -> 1628 | Q27: =P27 -> 1628 | R27: =Q27 -> 1628 | S27: =R27 -> 1628
E28: (-) Change in Net Working Capital | I28: =I27-F35 -> -251 | J28: =J27-I27 -> 2261 | K28: =K27-J27 -> -1043 | L28: =L27-K27 -> 1965 | M28: =M27-L27 -> -2231 | O28: =O27-M27 -> 266 | P28: =P27-O27 -> 0 | Q28: =Q27-P27 -> 0 | R28: =R27-Q27 -> 0 | S28: =S27-R27 -> 0
E29: %-Change in Net Working Capital | I29: =(I27/F35)-1 -> -0.37972769 | J29: =(J27/I27)-1 -> 5.5146341 | K29: =(K27/J27)-1 -> -0.39049045 | L29: =(L27/K27)-1 -> 1.2070025 | M29: =(M27/L27)-1 -> -0.62092959
E30: (-) CAPEX | I30: ='3.2 Balance Sheets'!O156-'3.2 Balance Sheets'!N156+'3.3 CF Statements'!Z102 -> 371 | J30: ='3.2 Balance Sheets'!E33-'3.2 Balance Sheets'!D33+'3.3 CF Statements'!Y102 -> 1466 | K30: ='3.2 Balance Sheets'!F27-'3.2 Balance Sheets'!E27+'3.3 CF Statements'!X102 -> 5175 | L30: ='3.2 Balance Sheets'!G27-'3.2 Balance Sheets'!F27+'3.3 CF Statements'!W102 -> 1708 | M30: ='3.2 Balance Sheets'!H27-'3.2 Balance Sheets'!G27+'3.3 CF Statements'!V102 -> 1426 | N30: =MEDIAN(I30:M30) -> 1466 | O30: =$N$30 -> 1466 | P30: =$N$30 -> 1466 | Q30: =$N$30 -> 1466 | R30: =$N$30 -> 1466 | S30: =$N$30 -> 1466
E33: Free Cash Flow | I33: =I21+I25-I28-I30 -> 2606 | J33: =J21+J25-J28-J30 -> -1286 | K33: =K21+K25-K28-K30 -> 1871 | L33: =L21+L25-L28-L30 -> 3936 | M33: =M21+M25-M28-M30 -> 10148 | O33: =O21+O25-O28-O30 -> 8322.9157 | P33: =P21+P25-P28-P30 -> 9665.4184 | Q33: =Q21+Q25-Q28-Q30 -> 10911.58 | R33: =R21+R25-R28-R30 -> 12365.655 | S33: =S21+S25-S28-S30 -> 14076.179
E35: NWC 1996 | F35: ='3.2 Balance Sheets'!N136+'3.2 Balance Sheets'!N144+'3.2 Balance Sheets'!N142-'3.2 Balance Sheets'!N178-'3.2 Balance Sheets'!N188-'3.2 Balance Sheets'!N190-'3.2 Balance Sheets'!N180 -> 661
E38: Projected Cash Flows | L38: WACC | M38: Discounted Cash Flows
E39: In Millions of USD | G39: FY 2002 E | H39: FY 2003 E | I39: FY 2004 E | J39: FY 2005 E | K39: FY 2006 E | L39: ='2.1 WACC'!V40 -> 0.078 | M39: In Millions of USD | O39: FY 2002 E | P39: FY 2003 E | Q39: FY 2004 E | R39: FY 2005 E | S39: FY 2006 E
E41: Free Cash Flow | G41: =O33 -> 8322.9157 | H41: =P33 -> 9665.4184 | I41: =Q33 -> 10911.58 | J41: =R33 -> 12365.655 | K41: =S33 -> 14076.179 | M41: Present Value of Free Cash Flow | O41: =O43*G41 -> 7720.701 | P41: =P43*H41 -> 8317.3148 | Q41: =Q43*I41 -> 8710.2648 | R41: =R43*J41 -> 9156.7651 | S41: =S43*K41 -> 9669.2097
M42: Discounting Period | O42: 1 | P42: 2 | Q42: 3 | R42: 4 | S42: 5
E43: Present Value of Pfizer Inc. | M43: Discounting Factor | O43: =1/((1+$L$39)^O42) -> 0.92764378 | P43: =1/((1+$L$39)^P42) -> 0.86052299 | Q43: =1/((1+$L$39)^Q42) -> 0.7982588 | R43: =1/((1+$L$39)^R42) -> 0.74049982 | S43: =1/((1+$L$39)^S42) -> 0.68692005
E44: Free cash flow terminal year | F44: =K41 -> 14076.179
E45: Inflation rate (as of 12/2001) | F45: ='3.6 US Inflation Growth Rate'!G41 -> 0.027
E46: GDP growth rate (as of 12/2001) | F46: ='3.5 US GDP Growth Rate'!D32 -> 0.0375
E47: Perpetuity growth rate | F47: =0.25*F45+0.75*F46 -> 0.034875
E48: Terminal Value | F48: =F44*(1+F47)/(L39-F47) -> 337787.5
E49: Discount Factor | F49: =1/((1+L39)^S42) -> 0.68692005
E50: PV of Terminal Value | F50: =F48*F49 -> 232033.01
E52: Enterprise Value (EV) | F52: =F50+O41+P41+Q41+R41+S41 -> 275607.26
E54: Share Price (in $) | F54: =F52/'3.1 Income Statements'!G61 -> 43.324938 | G54: =IF(F54>'3.4 Trading Multiples Bloomberg'!C10,CONCATENATE("undervalued by ",(G56*100),"%"),CONCATENATE("overvalued by ",((-1*G56)*100),"%")) -> undervalued by 8,7%
E55: Source: own calculations
G56: =ROUND(((F54-'3.4 Trading Multiples Bloomberg'!C10)/'3.4 Trading Multiples Bloomberg'!C10),3) -> 0.087

Sheet 2. Input Parameters>>>

Sheet 2.1 WACC
C5: Ticker | D5: PFE US Equity
C6: Company
C7: Start Date | D7: 19871231
C8: End Date | D8: 20171231
C9: Periodicity
C10: Currency | D10: USD
C11: Filing Status Mnemonic | D11: MR
C12: Filing | D12: Most Recent
C13: Units
C15: Field | D15: Mnemonic | E15: Current | F15: FY 2017 | G15: FY 2016 | H15: FY 2015 | I15: FY 2014 | J15: FY 2013 | K15: FY 2012 | L15: FY 2011 | M15: FY 2010 | N15: FY 2009 | O15: FY 2008 | P15: FY 2007 | Q15: FY 2006 | R15: FY 2005 | S15: FY 2004 | T15: FY 2003 | U15: FY 2002 | V15: FY 2001 | W15: FY 2000
F16: Original | G16: Original | H16: Reclassified/Restated | I16: Reclassified/Restated | J16: Reclassified/Restated | K16: Reclassified/Restated | L16: Reclassified/Restated | M16: Reclassified/Restated | N16: Original | O16: Reclassified/Restated | P16: Original | Q16: Reclassified/Restated | R16: Reclassified/Restated | S16: Original | T16: Original | U16: Original | V16: Reclassified/Restated | W16: Reclassified/Restated
C17: Equity
C18: Cost of Equity | D18: WACC_COST_EQUITY | E18: 11.01 | F18: 8.1995 | G18: 7.8075 | H18: 8.9775 | I18: 9.1327 | J18: 8.0077 | K18: 8.5739 | L18: 8.7497 | M18: 9.7856 | N18: 9.4403 | O18: 10.3177 | P18: 11.4422 | Q18: 10.0012 | R18: 9.6622 | S18: 8.0599 | T18: 9.0299 | U18: 10.1052 | V18: 7.9698 | W18: 7.3506
C19: Weight of Equity | D19: WACC_WEIGHT_OF_EQUITY | E19: 83.27 | F19: 83.2692 | G19: 82.4002 | H19: 83.6624 | I19: 84.2222 | J19: 84.2932 | K19: 82.9531 | L19: 80.7861 | M19: 76.0978 | N19: 75.0798 | O19: 87.3154 | P19: 92.0724 | Q19: 95.7842 | R19: 90.4592 | S19: 91.4706 | T19: 94.7975 | U19: 94.1008 | V19: 96.5747 | W19: 98.1707
C20: + Debt
C21: Cost of Debt | D21: WACC_COST_DEBT | E21: 3.1 | F21: 2.6124 | G21: 2.1023 | H21: 1.7342 | I21: 1.6691 | J21: 2.1496 | K21: 1.3741 | L21: 1.3313 | M21: 2.9822 | N21: 3.2186 | O21: 1.2451 | P21: 3.3465 | Q21: 4.2016 | R21: 3.2506 | S21: 2.984 | T21: 1.4641 | U21: 1.7851 | V21: 2.8694 | W21: 3.4487
C22: Weight of Debt | D22: WACC_WEIGHT_OF_DEBT | E22: 16.72 | F22: 16.7227 | G22: 17.5898 | H22: 16.3267 | I22: 15.7653 | J22: 15.6926 | K22: 17.0291 | L22: 19.1918 | M22: 23.874 | N22: 24.889 | O22: 12.6312 | P22: 7.8719 | Q22: 4.1426 | R22: 9.4518 | S22: 8.4416 | T22: 5.1255 | U22: 5.8992 | V22: 3.4253 | W22: 1.8293
C23: + Preferred Equity
C24: Cost of Pref. Equity | D24: WACC_COST_PFD | E24: 0 | F24: 4.7619 | G24: 8.3333 | H24: 7.6923 | I24: 0 | J24: 6.0606 | K24: 5.1282 | L24: 6.6667 | M24: 5.7692 | N24: 8.1967 | O24: 4.1096 | P24: 4.3011 | Q24: 3.5461 | R24: 3.5503 | S24: 2.0725 | T24: 0 | U24: 0 | V24: 0 | W24: 0
C25: Weight of Pref. Equity | D25: WACC_WEIGHT_OF_PREFERRED_EQUITY | E25: 0.01 | F25: 0.0081 | G25: 0.01 | H25: 0.0109 | I25: 0.0125 | J25: 0.0142 | K25: 0.0177 | L25: 0.0222 | M25: 0.0282 | N25: 0.0312 | O25: 0.0534 | P25: 0.0557 | Q25: 0.0732 | R25: 0.0891 | S25: 0.0879 | T25: 0.077 | U25: 0 | V25: 0 | W25: 0
C26: WACC | D26: WACC | E26: 9.69 | F26: 7.2649 | G26: 6.804 | H26: 7.7947 | I26: 7.9549 | J26: 7.0881 | K26: 7.3473 | L26: 7.3255 | M26: 8.1602 | N26: 7.8914 | O26: 9.1684 | P26: 10.8009 | Q26: 9.7562 | R26: 9.0507 | S26: 7.6261 | T26: 8.6352 | U26: 9.6143 | V26: 7.7951 | W26: 7.2792
C28: Capital Structure
C29: + Historical Market Cap | D29: HISTORICAL_MARKET_CAP | E29: 216208 | F29: 216559.38 | G29: 197153.6 | H29: 199329 | I29: 195964.65 | J29: 196001.37 | K29: 182477.06 | L29: 163923 | M29: 140290.12 | N29: 146793.3 | O29: 119471.66 | P29: 153677.53 | Q29: 184511.6 | R29: 171658.52 | S29: 200948.97 | T29: 269532.57 | U29: 188372.34 | V29: 250138.45 | W29: 290444
C30: + Short Term Debt | D30: BS_ST_BORROW | E30: 9953 | F30: 9953 | G30: 10688 | H30: 10159 | I30: 5141 | J30: 6027 | K30: 6424 | L30: 4016 | M30: 5603 | N30: 5469 | O30: 9320 | P30: 5825 | Q30: 2434 | R30: 11589 | S30: 11266 | T30: 8818 | U30: 8669 | V30: 6263 | W30: 4289
C31: + Long Term Debt | D31: BS_LT_BORROW | E31: 33538 | F31: 33538 | G31: 31398 | H31: 28740 | I31: 31541 | J31: 30462 | K31: 31036 | L31: 34926 | M31: 38410 | N31: 43193 | O31: 7963 | P31: 7314 | Q31: 5546 | R31: 6347 | S31: 7279 | T31: 5755 | U31: 3140 | V31: 2609 | W31: 1123
C32: + Preferred Equity and Hybrid Capital | D32: BS_PFD_EQTY_&_HYBRID_CPTL | E32: 21 | F32: 21 | G32: 24 | H32: 26 | I32: 29 | J32: 33 | K32: 39 | L32: 45 | M32: 52 | N32: 61 | O32: 73 | P32: 93 | Q32: 141 | R32: 169 | S32: 193 | T32: 219 | U32: 0 | V32: 0 | W32: 0
C33: Total Capital | D33: WACC_TOTAL_CAPITAL | E33: 260071 | F33: 260071.38 | G33: 239263.6 | H33: 238254 | I33: 232675.65 | J33: 232523.37 | K33: 219976.06 | L33: 202910 | M33: 184355.12 | N33: 195516.3 | O33: 136827.66 | P33: 166909.53 | Q33: 192632.6 | R33: 189763.52 | S33: 219686.97 | T33: 284324.57 | U33: 200181.34 | V33: 259010.45 | W33: 295856
C35: EVA
C36: + Net Op. Profit | D36: WACC_NET_OPER_PROFIT | E36: 13852 | F36: 13851 | G36: 12262 | H36: 12562 | I36: 13179 | J36: 15569 | K36: 15583 | L36: 15167 | M36: 14093 | N36: 11794 | O36: 17174 | P36: 14695 | Q36: 14493 | R36: 14387 | S36: 17150 | T36: 16273 | U36: 12291 | V36: 10622 | W36: 8629
C37: - Cash Op. Taxes | D37: WACC_CASH_OPER_TAXES | E37: 17848 | F37: 17848 | G37: -2243.4942 | H37: -1085.3753 | I37: 6040.1961 | J37: -247.7618 | K37: -16612.403 | L37: 22141.936 | M37: -15867.692 | N37: 2270.0507 | O37: 6515.2769 | P37: 4309.6551 | Q37: 4108.7384 | R37: 8585.9528 | S37: 3631.1973 | T37: -4654.776 | U37: 2758.0119 | V37: 2591.4315 | W37: 3185.0571
C38: + NOPAT | D38: WACC_NOPAT | E38: -3996 | F38: -3997 | G38: 14505.494 | H38: 13647.375 | I38: 7138.8039 | J38: 15816.762 | K38: 32195.403 | L38: -6974.9362 | M38: 29960.692 | N38: 9523.9493 | O38: 10658.723 | P38: 10385.345 | Q38: 10384.262 | R38: 5801.0472 | S38: 13518.803 | T38: 20927.776 | U38: 9532.9881 | V38: 8030.5685 | W38: 5443.9429
C39: Total Invested Capital | D39: WACC_TOTAL_INV_CAPITAL | E39: 133441 | F39: 133441 | G39: 148538 | H39: 145675 | I39: 150193 | J39: 151813 | K39: 161031 | L39: 140542 | M39: 168015 | N39: 167021 | O39: 88132 | P39: 91700 | Q39: 104064 | R39: 106051 | S39: 110304 | T39: 102869 | U39: 38608 | V39: 31216 | W39: 24509
C40: WACC | D40: WACC | E40: 9.69 | F40: 7.2649 | G40: 6.804 | H40: 7.7947 | I40: 7.9549 | J40: 7.0881 | K40: 7.3473 | L40: 7.3255 | M40: 8.1602 | N40: 7.8914 | O40: 9.1684 | P40: 10.8009 | Q40: 9.7562 | R40: 9.0507 | S40: 7.6261 | T40: 8.6352 | U40: 9.6143 | V40: 0.078 | W40: 7.2792
C41: - Capital Charge | D41: WACC_CAPITAL_CHARGE | E41: 12924.3 | F41: 9694.394 | G41: 10106.517 | H41: 11354.985 | I41: 11947.641 | J41: 10760.722 | K41: 11831.352 | L41: 10295.405 | M41: 13710.337 | N41: 13180.261 | O41: 8080.3031 | P41: 9904.4709 | Q41: 10152.696 | R41: 9598.3652 | S41: 8411.9231 | T41: 8882.9406 | U41: 3711.9052 | V41: 2433.3104 | W41: 1784.068
C42: Economic Value Added | D42: WACC_ECON_VALUE_ADDED | E42: -16920.3 | F42: -13691.394 | G42: 4398.9776 | H42: 2292.39 | I42: -4808.837 | J42: 5056.0401 | K42: 20364.051 | L42: -17270.341 | M42: 16250.355 | N42: -3656.3113 | O42: 2578.42 | P42: 480.874 | Q42: 231.5657 | R42: -3797.318 | S42: 5106.8796 | T42: 12044.835 | U42: 5821.0829 | V42: 5597.2581 | W42: 3659.8749
C43: ROIC | D43: WACC_RETURN_ON_INV_CAPITAL | E43: -2.99 | F43: -2.9953 | G43: 9.7655 | H43: 9.3684 | I43: 4.7531 | J43: 10.4186 | K43: 19.9933 | L43: -4.9629 | M43: 17.8322 | N43: 5.7022 | O43: 12.094 | P43: 11.3253 | Q43: 9.9787 | R43: 5.4701 | S43: 12.2559 | T43: 20.3441 | U43: 24.6917 | V43: 25.7258 | W43: 22.212
C44: EVA Spread | D44: WACC_EVA_SPREAD | E44: -12.68 | F44: -10.2603 | G44: 2.9615 | H44: 1.5736 | I44: -3.2018 | J44: 3.3304 | K44: 12.646 | L44: -12.2884 | M44: 9.672 | N44: -2.1891 | O44: 2.9256 | P44: 0.5244 | Q44: 0.2225 | R44: -3.5807 | S44: 4.6298 | T44: 11.7089 | U44: 15.0774 | V44: 17.9307 | W44: 14.9328

Sheet 2.2 Stock & Index Data
B4: History Pharmacia LLC (748957Q US) in USD | K4: History Pfizer in USD | T4: History S&P 500 in USD
B5: Date | C5: Last Price | D5: Volume | E5: Dividends Paid | K5: Date | L5: Last Price | M5: Volume | N5: Dividends Paid | T5: Date | U5: Last Price | V5: Volume
B6: 37726 | C6: 45.06 | D6: 13630000 | K6: 39813 | L6: 17.71 | M6: 102260000 | N6: -2132 | T6: 39813 | U6: 903.25 | V6: 2420000000
B7: 37722 | C7: 43.89 | D7: 20060000 | K7: 39808 | L7: 17.1 | M7: 108890000 | T7: 39808 | U7: 872.8 | V7: 2400000000
B8: 37715 | C8: 45.8 | D8: 19160000 | K8: 39801 | L8: 17.3 | M8: 274720000 | T8: 39801 | U8: 887.88 | V8: 6729999872
B9: 37708 | C9: 44.49 | D9: 21250000 | K9: 39794 | L9: 16.92 | M9: 236990000 | T9: 39794 | U9: 879.73 | V9: 6230000128
B10: 37701 | C10: 44.45 | D10: 26540000 | K10: 39787 | L10: 16.55 | M10: 267130000 | T10: 39787 | U10: 876.07 | V10: 6769999872
B11: 37694 | C11: 40.13 | D11: 18970000 | K11: 39780 | L11: 16.43 | M11: 193940000 | T11: 39780 | U11: 896.24 | V11: 5110000128
B12: 37687 | C12: 41.52 | D12: 23570000 | K12: 39773 | L12: 15.67 | M12: 341940000 | T12: 39773 | U12: 800.03 | V12: 8339999744
B13: 37680 | C13: 41.32 | D13: 37670000 | K13: 39766 | L13: 16.28 | M13: 241740000 | T13: 39766 | U13: 873.29 | V13: 6630000128
B14: 37673 | C14: 39.6 | D14: 18300000 | K14: 39759 | L14: 16.86 | M14: 245500000 | T14: 39759 | U14: 930.99 | V14: 5920000000
B15: 37666 | C15: 39.05 | D15: 21620000 | K15: 39752 | L15: 17.71 | M15: 331880000 | T15: 39752 | U15: 968.75 | V15: 7059999744
B16: 37659 | C16: 40.36 | D16: 25920000 | K16: 39745 | L16: 16.57 | M16: 325489984 | T16: 39745 | U16: 876.77 | V16: 6840000000
B17: 37652 | C17: 41.77 | D17: 26910000 | K17: 39738 | L17: 16.91 | M17: 414729984 | T17: 39738 | U17: 940.55 | V17: 8510000128
B18: 37645 | C18: 41.43 | D18: 28340000 | K18: 39731 | L18: 15.14 | M18: 551670016 | T18: 39731 | U18: 899.22 | V18: 9939999744
B19: 37638 | C19: 41.11 | D19: 29430000 | K19: 39724 | L19: 19 | M19: 352750016 | T19: 39724 | U19: 1099.23 | V19: 8030000128
B20: 37631 | C20: 42.24 | D20: 23070000 | K20: 39717 | L20: 18.66 | M20: 242300000 | N20: -2132 | T20: 39717 | U20: 1213.01 | V20: 6000000000
B21: 37624 | C21: 43.52 | D21: 14240000 | E21: -175 | K21: 39710 | L21: 18.55 | M21: 402440000 | T21: 39710 | U21: 1255.07 | V21: 10350000128
B22: 37617 | C22: 40.5 | D22: 14770000 | K22: 39703 | L22: 18.62 | M22: 218510000 | T22: 39703 | U22: 1251.7 | V22: 6739999744
B23: 37610 | C23: 41.65 | D23: 29260000 | K23: 39696 | L23: 18.51 | M23: 147700000 | T23: 39696 | U23: 1242.31 | V23: 4240000000
B24: 37603 | C24: 41.4 | D24: 26870000 | K24: 39689 | L24: 19.11 | M24: 172740000 | T24: 39689 | U24: 1282.83 | V24: 3760000000
B25: 37596 | C25: 42.18 | D25: 28410000 | K25: 39682 | L25: 19.75 | M25: 158080000 | T25: 39682 | U25: 1292.2 | V25: 4030000128
B26: 37589 | C26: 42.3 | D26: 23560000 | K26: 39675 | L26: 19.97 | M26: 193400000 | T26: 39675 | U26: 1298.2 | V26: 4809999872
B27: 37582 | C27: 43.5 | D27: 36670000 | K27: 39668 | L27: 19.84 | M27: 223850000 | T27: 39668 | U27: 1296.32 | V27: 5379999744
B28: 37575 | C28: 45.24 | D28: 20940000 | K28: 39661 | L28: 18.6 | M28: 191360000 | T28: 39661 | U28: 1260.31 | V28: 5710000128
B29: 37568 | C29: 46 | D29: 27530000 | K29: 39654 | L29: 18.89 | M29: 248080000 | T29: 39654 | U29: 1257.76 | V29: 6440000000
B30: 37561 | C30: 43.55 | D30: 26620000 | K30: 39647 | L30: 18.32 | M30: 245450000 | T30: 39647 | U30: 1260.68 | V30: 7710000128
B31: 37554 | C31: 42.9 | D31: 26590000 | K31: 39640 | L31: 17.81 | M31: 258270000 | T31: 39640 | U31: 1239.49 | V31: 6990000128
B32: 37547 | C32: 45.3 | D32: 27180000 | K32: 39633 | L32: 17.75 | M32: 160140000 | T32: 39633 | U32: 1262.9 | V32: 4899999744
B33: 37540 | C33: 40.75 | D33: 25670000 | K33: 39626 | L33: 17.28 | M33: 274060000 | N33: -2139 | T33: 39626 | U33: 1278.38 | V33: 6280000000
B34: 37533 | C34: 38.33 | D34: 33700000 | E34: -178 | K34: 39619 | L34: 17.33 | M34: 324340000 | T34: 39619 | U34: 1317.93 | V34: 6070000128
B35: 37526 | C35: 38.24 | D35: 38100000 | K35: 39612 | L35: 17.99 | M35: 270689984 | T35: 39612 | U35: 1360.03 | V35: 6129999872
B36: 37519 | C36: 38.4 | D36: 24320000 | K36: 39605 | L36: 17.96 | M36: 346310016 | T36: 39605 | U36: 1360.68 | V36: 5769999872
B37: 37512 | C37: 39.9 | D37: 21400000 | K37: 39598 | L37: 19.36 | M37: 172370000 | T37: 39598 | U37: 1400.38 | V37: 4080000000
B38: 37505 | C38: 40.86 | D38: 21970000 | K38: 39591 | L38: 19.53 | M38: 288220000 | T38: 39591 | U38: 1375.93 | V38: 5249999872
B39: 37498 | C39: 43.7 | D39: 21630000 | K39: 39584 | L39: 20.03 | M39: 198980000 | T39: 39584 | U39: 1425.35 | V39: 5369999872
B40: 37491 | C40: 45.54 | D40: 19210000 | K40: 39577 | L40: 19.79 | M40: 212470000 | T40: 39577 | U40: 1388.28 | V40: 5489999872
B41: 37484 | C41: 44.1 | D41: 30710000 | K41: 39570 | L41: 20.61 | M41: 247290000 | T41: 39570 | U41: 1413.9 | V41: 5689999872
B42: 37477 | C42: 43.1617 | D42: 35790000 | K42: 39563 | L42: 20.43 | M42: 264270000 | T42: 39563 | U42: 1397.84 | V42: 5689999872
B43: 37470 | C43: 40.3795 | D43: 44560000 | K43: 39556 | L43: 20.47 | M43: 243090000 | T43: 39556 | U43: 1390.33 | V43: 5600000000
B44: 37463 | C44: 38.5373 | D44: 57130000 | K44: 39549 | L44: 20.45 | M44: 169270000 | T44: 39549 | U44: 1332.83 | V44: 5400000000
B45: 37456 | C45: 35.7081 | D45: 135100000 | K45: 39542 | L45: 21.35 | M45: 187910000 | T45: 39542 | U45: 1370.4 | V45: 5969999872
B46: 37449 | C46: 30.6324 | D46: 36270000 | K46: 39535 | L46: 20.5 | M46: 177310000 | N46: -2138 | T46: 39535 | U46: 1315.22 | V46: 6099999744
B47: 37442 | C47: 33.6402 | D47: 18090000 | K47: 39528 | L47: 20.59 | M47: 194410000 | T47: 39528 | U47: 1329.51 | V47: 7289999872
B48: 37435 | C48: 35.2005 | D48: 24080000 | E48: -179 | K48: 39521 | L48: 20.64 | M48: 204160000 | T48: 39521 | U48: 1288.14 | V48: 7779999744
B49: 37428 | C49: 35.2851 | D49: 20400000 | K49: 39514 | L49: 21.35 | M49: 192430000 | T49: 39514 | U49: 1293.37 | V49: 7240000000
B50: 37421 | C50: 35.9806 | D50: 24230000 | K50: 39507 | L50: 22.28 | M50: 186030000 | T50: 39507 | U50: 1330.63 | V50: 6729999872
B51: 37414 | C51: 36.695 | D51: 29660000 | K51: 39500 | L51: 22.5 | M51: 140400000 | T51: 39500 | U51: 1353.11 | V51: 5000000000
B52: 37407 | C52: 40.5957 | D52: 15180000 | K52: 39493 | L52: 22.33 | M52: 226600000 | T52: 39493 | U52: 1349.99 | V52: 6400000000
B53: 37400 | C53: 40.0975 | D53: 17980000 | K53: 39486 | L53: 22.3 | M53: 174610000 | T53: 39486 | U53: 1331.29 | V53: 7360000000
B54: 37393 | C54: 39.6934 | D54: 24890000 | K54: 39479 | L54: 23.59 | M54: 218660000 | T54: 39479 | U54: 1395.42 | V54: 8480000000
B55: 37386 | C55: 37.5973 | D55: 18730000 | K55: 39472 | L55: 22.61 | M55: 290209984 | T55: 39472 | U55: 1330.6 | V55: 8620000256
B56: 37379 | C56: 38.3963 | D56: 25180000 | K56: 39465 | L56: 22.5 | M56: 231100000 | T56: 39465 | U56: 1325.19 | V56: 9059999744
B57: 37372 | C57: 39.6934 | D57: 21950000 | K57: 39458 | L57: 24.02 | M57: 260050000 | T57: 39458 | U57: 1401.02 | V57: 8339999744
B58: 37365 | C58: 41.3947 | D58: 19860000 | K58: 39451 | L58: 22.83 | M58: 164380000 | N58: -1954 | T58: 39451 | U58: 1411.63 | V58: 4659999744
B59: 37358 | C59: 42.344 | D59: 24940000 | K59: 39444 | L59: 22.9 | M59: 103240000 | T59: 39444 | U59: 1478.49 | V59: 2580000000
B60: 37351 | C60: 40.3701 | D60: 20400000 | K60: 39437 | L60: 23.24 | M60: 217920000 | T60: 39437 | U60: 1484.46 | V60: 6579999744
B61: 37344 | C61: 42.3722 | D61: 15740000 | E61: -179 | K61: 39430 | L61: 23.1 | M61: 192520000 | T61: 39430 | U61: 1467.95 | V61: 6240000000
B62: 37337 | C62: 42.4944 | D62: 27690000 | K62: 39423 | L62: 24.4 | M62: 175780000 | T62: 39423 | U62: 1504.66 | V62: 5529999872
B63: 37330 | C63: 42.532 | D63: 32480000 | K63: 39416 | L63: 23.76 | M63: 226380000 | T63: 39416 | U63: 1481.14 | V63: 7009999872
B64: 37323 | C64: 39.0636 | D64: 22180000 | K64: 39409 | L64: 22.98 | M64: 197210000 | T64: 39409 | U64: 1440.7 | V64: 4969999872
B65: 37316 | C65: 39.59 | D65: 21010000 | K65: 39402 | L65: 23.39 | M65: 188530000 | T65: 39402 | U65: 1458.74 | V65: 7289999872
B66: 37309 | C66: 37.9733 | D66: 16890000 | K66: 39395 | L66: 22.83 | M66: 215310000 | T66: 39395 | U66: 1453.7 | V66: 7600000000
B67: 37302 | C67: 37.5973 | D67: 17510000 | K67: 39388 | L67: 23.67 | M67: 182680000 | T67: 39388 | U67: 1509.65 | V67: 6249999872
B68: 37295 | C68: 36.1028 | D68: 27740000 | K68: 39381 | L68: 24.31 | M68: 189530000 | T68: 39381 | U68: 1535.28 | V68: 6520000000
B69: 37288 | C69: 37.8793 | D69: 20290000 | K69: 39374 | L69: 24.07 | M69: 209380000 | T69: 39374 | U69: 1500.63 | V69: 6310000128
B70: 37281 | C70: 37.3153 | D70: 17250000 | K70: 39367 | L70: 25.26 | M70: 149930000 | T70: 39367 | U70: 1561.8 | V70: 4830000128
B71: 37274 | C71: 36.7984 | D71: 26470000 | K71: 39360 | L71: 25.58 | M71: 179710000 | T71: 39360 | U71: 1557.59 | V71: 4990000128
B72: 37267 | C72: 38.8004 | D72: 28370000 | K72: 39353 | L72: 24.43 | M72: 183790000 | N72: -1981 | T72: 39353 | U72: 1526.75 | V72: 5440000000
B73: 37260 | C73: 38.8662 | D73: 21780000 | E73: -154 | K73: 39346 | L73: 24.59 | M73: 218280000 | T73: 39346 | U73: 1525.75 | V73: 6769999872
B74: 37253 | C74: 40.4735 | D74: 9450000 | K74: 39339 | L74: 24.29 | M74: 161930000 | T74: 39339 | U74: 1484.25 | V74: 5489999872
B75: 37246 | C75: 40.8119 | D75: 24560000 | K75: 39332 | L75: 24.25 | M75: 136240000 | T75: 39332 | U75: 1453.55 | V75: 4769999872
B76: 37239 | C76: 39.7592 | D76: 27980000 | K76: 39325 | L76: 24.84 | M76: 175210000 | T76: 39325 | U76: 1473.99 | V76: 5550000128
B77: 37232 | C77: 41.4041 | D77: 30030000 | K77: 39318 | L77: 24.74 | M77: 186350000 | T77: 39318 | U77: 1479.37 | V77: 5680000000
B78: 37225 | C78: 41.733 | D78: 40040000 | K78: 39311 | L78: 23.94 | M78: 251130000 | T78: 39311 | U78: 1445.94 | V78: 8920000512
B79: 37218 | C79: 42.767 | D79: 34650000 | K79: 39304 | L79: 23.99 | M79: 259970000 | T79: 39304 | U79: 1453.64 | V79: 9639999488
B80: 37211 | C80: 38.8662 | D80: 23110000 | K80: 39297 | L80: 23.51 | M80: 265590000 | T80: 39297 | U80: 1433.06 | V80: 8730000384
B81: 37204 | C81: 37.7007 | D81: 25870000 | K81: 39290 | L81: 23.79 | M81: 248230000 | T81: 39290 | U81: 1458.95 | V81: 8700000256
B82: 37197 | C82: 38.3963 | D82: 32770000 | K82: 39283 | L82: 24.9 | M82: 271660000 | T82: 39283 | U82: 1534.09 | V82: 7059999744
B83: 37190 | C83: 36.977 | D83: 65210000 | K83: 39276 | L83: 25.91 | M83: 195430000 | T83: 39276 | U83: 1552.5 | V83: 6400000000
B84: 37183 | C84: 39.0918 | D84: 23250000 | K84: 39269 | L84: 25.92 | M84: 105750000 | T84: 39269 | U84: 1530.44 | V84: 3889999872
B85: 37176 | C85: 38.5655 | D85: 20130000 | K85: 39262 | L85: 25.57 | M85: 186600000 | N85: -2008 | T85: 39262 | U85: 1503.35 | V85: 6860000256
B86: 37169 | C86: 37.9545 | D86: 18560000 | K86: 39255 | L86: 25.38 | M86: 259840000 | T86: 39255 | U86: 1502.56 | V86: 6899999744
B87: 37162 | C87: 38.1237 | D87: 29660000 | E87: -180 | K87: 39248 | L87: 26.47 | M87: 195230000 | T87: 39248 | U87: 1532.91 | V87: 6750000128
B88: 37155 | C88: 36.0464 | D88: 41790000 | K88: 39241 | L88: 26.52 | M88: 202500000 | T88: 39241 | U88: 1507.67 | V88: 6739999744
B89: 37148 | C89: 37.7383 | D89: 6080000 | K89: 39234 | L89: 27.68 | M89: 135410000 | T89: 39234 | U89: 1536.34 | V89: 5089999872
B90: 37141 | C90: 37.8511 | D90: 24070000 | K90: 39227 | L90: 27.53 | M90: 167450000 | T90: 39227 | U90: 1515.73 | V90: 6120000000
B91: 37134 | C91: 37.2214 | D91: 21300000 | K91: 39220 | L91: 27.44 | M91: 151200000 | T91: 39220 | U91: 1522.75 | V91: 6409999872
B92: 37127 | C92: 39.2986 | D92: 30100000 | K92: 39213 | L92: 27.04 | M92: 180380000 | T92: 39213 | U92: 1505.85 | V92: 5929999872
B93: 37120 | C93: 41.7706 | D93: 12070000 | K93: 39206 | L93: 27.08 | M93: 191890000 | T93: 39206 | U93: 1505.62 | V93: 6819999744
B94: 37113 | C94: 41.9962 | D94: 18360000 | K94: 39199 | L94: 26.61 | M94: 216190000 | T94: 39199 | U94: 1494.07 | V94: 7000000000
B95: 37106 | C95: 41.3571 | D95: 26670000 | K95: 39192 | L95: 26.97 | M95: 207090000 | T95: 39192 | U95: 1484.35 | V95: 7249999872
B96: 37099 | C96: 39.59 | D96: 27770000 | K96: 39185 | L96: 26.67 | M96: 174620000 | T96: 39185 | U96: 1452.85 | V96: 5809999872
B97: 37092 | C97: 41.0281 | D97: 39840000 | K97: 39178 | L97: 25.84 | M97: 111540000 | T97: 39178 | U97: 1443.76 | V97: 4579999744
B98: 37085 | C98: 44.0359 | D98: 19060000 | K98: 39171 | L98: 25.26 | M98: 157600000 | N98: -2032 | T98: 39171 | U98: 1420.86 | V98: 6179999744
B99: 37078 | C99: 43.2369 | D99: 11560000 | K99: 39164 | L99: 25.66 | M99: 155320000 | T99: 39164 | U99: 1436.11 | V99: 6150000128
B100: 37071 | C100: 43.1899 | D100: 27750000 | E100: -164 | K100: 39157 | L100: 24.99 | M100: 195530000 | T100: 39157 | U100: 1386.94 | V100: 7609999872
B101: 37064 | C101: 45.8593 | D101: 24460000 | K101: 39150 | L101: 25.41 | M101: 179960000 | T101: 39150 | U101: 1402.85 | V101: 6750000128
B102: 37057 | C102: 45.8687 | D102: 17110000 | K102: 39143 | L102: 24.79 | M102: 232570000 | T102: 39143 | U102: 1387.17 | V102: 8400000000
B103: 37050 | C103: 46.7147 | D103: 11460000 | K103: 39136 | L103: 25.62 | M103: 127500000 | T103: 39136 | U103: 1451.19 | V103: 4470000128
...

Sheet 2.3 Assumptions Pfizer
B8: M&A | O8: Pfizer Inc. US
B9: Assumptions | F9: Actual | K9: Projected | O9: Income Statement | T9: Actual | Y9: Projected
B10: in Millions of USD | D10: 1997 | E10: 1998 | F10: 1999 | G10: 2000 | H10: 2001 | I10: 2002 | J10: 2003 | K10: 2004 | L10: 2005 | M10: 2006 | O10: in Millions of USD | R10: 1997 | S10: 1998 | T10: 1999 | U10: 2000 | V10: 2001 | W10: 2002 | X10: 2003 | Y10: 2004 | Z10: 2005 | AA10: 2006
B12: Operating assumptions - Stable growth | P12: Income Statement
D13: 1997 | E13: 1998 | F13: 1999 | G13: 2000 | H13: 2001 | I13: 2002 | J13: 2003 | K13: 2004 | L13: 2005 | M13: 2006
B14: Income statement | P14: Sales | R14: ='3.1 Income Statements'!C9 -> 12504 | S14: ='3.1 Income Statements'!D9 -> 13544 | T14: ='3.1 Income Statements'!E9 -> 27376 | U14: ='3.1 Income Statements'!F9 -> 29355 | V14: ='3.1 Income Statements'!G9 -> 29024 | W14: =(1+I15)*V14 -> 31280.079 | X14: =(1+J15)*W14 -> 33711.526 | Y14: =(1+K15)*X14 -> 36331.973 | Z14: =(1+L15)*Y14 -> 39156.112 | AA14: =(1+M15)*Z14 -> 42199.774
B15: Sales growth | D15: NA | E15: =('3.1 Income Statements'!D9/'3.1 Income Statements'!C9)-1 -> 0.083173385 | F15: =('3.1 Income Statements'!E9/'3.1 Income Statements'!D9)-1 -> 1.021264 | G15: =('3.1 Income Statements'!F9/'3.1 Income Statements'!E9)-1 -> 0.072289597 | H15: =('3.1 Income Statements'!G9/'3.1 Income Statements'!F9)-1 -> -0.011275762 | I15: ='1.2 DCF Analysis'!O10 -> 0.077731491 | J15: ='1.2 DCF Analysis'!P10 -> 0.077731491 | K15: ='1.2 DCF Analysis'!Q10 -> 0.077731491 | L15: ='1.2 DCF Analysis'!R10 -> 0.077731491 | M15: ='1.2 DCF Analysis'!S10 -> 0.077731491 | P15: Cost of sales | R15: =-('3.1 Income Statements'!C11) -> -1776 | S15: =-('3.1 Income Statements'!D11) -> -2094 | T15: =-('3.1 Income Statements'!E11) -> -5464 | U15: =-('3.1 Income Statements'!F11) -> -5007 | V15: =-('3.1 Income Statements'!G11) -> -3823 | W15: =-(I16*W14) -> -4100.8183 | X15: =-(J16*X14) -> -4251.0234 | Y15: =-(K16*Y14) -> -4399.8019 | Z15: =-(L16*Z14) -> -4546.0245 | AA15: =-(M16*AA14) -> -4688.3949
B16: COGS as % of sales | D16: =-R15/R14 -> 0.14203455 | E16: =-S15/S14 -> 0.15460721 | F16: =-T15/T14 -> 0.19959088 | G16: =-U15/U14 -> 0.17056719 | H16: =-V15/V14 -> 0.13171858 | I16: =6*-0.005+0.1611 -> 0.1311 | J16: =7*-0.005+0.1611 -> 0.1261 | K16: =8*-0.005+0.1611 -> 0.1211 | L16: =9*-0.005+0.1611 -> 0.1161 | M16: =10*-0.005+0.1611 -> 0.1111 | P16: SG&A | R16: =-('3.1 Income Statements'!C15-'3.1 Income Statements'!C17) -> -4401 | S16: =-('3.1 Income Statements'!D15-'3.1 Income Statements'!D17) -> -6577 | T16: =-('3.1 Income Statements'!E15-'3.1 Income Statements'!E17) -> -12070 | U16: =-('3.1 Income Statements'!F15-'3.1 Income Statements'!F17) -> -11223 | V16: =-('3.1 Income Statements'!G15-'3.1 Income Statements'!G17) -> -9646 | W16: =-('1.2 DCF Analysis'!O9+'2.3 Assumptions Pfizer'!W17) -> -11039.507 | X16: =-('1.2 DCF Analysis'!P9+'2.3 Assumptions Pfizer'!X17) -> -11897.624 | Y16: =-('1.2 DCF Analysis'!Q9+'2.3 Assumptions Pfizer'!Y17) -> -12822.445 | Z16: =-('1.2 DCF Analysis'!R9+'2.3 Assumptions Pfizer'!Z17) -> -13819.152 | AA16: =-('1.2 DCF Analysis'!S9+'2.3 Assumptions Pfizer'!AA17) -> -14893.336
B17: SG&A, Others as % of sales | D17: =-R16/R14 -> 0.35196737 | E17: =-S16/S14 -> 0.48560248 | F17: =-T16/T14 -> 0.44089714 | G17: =-U16/U14 -> 0.38231988 | H17: =-V16/V14 -> 0.33234564 | I17: =-W16/W14 -> 0.35292453 | J17: =-X16/X14 -> 0.35292453 | K17: =-Y16/Y14 -> 0.35292453 | ... M17: =-AA16/AA14 -> 0.35292453 | P17: R&D expenses | R17: =-('3.1 Income Statements'!C17) -> -1805 | S17: =-('3.1 Income Statements'!D17) -> -2279 | T17: =-('3.1 Income Statements'!E17) -> -2776 | U17: =-('3.1 Income Statements'!F17) -> -4435 | V17: =-('3.1 Income Statements'!G17) -> -4847 | W17: =-(I18*W14) -> -4580.0554 | X17: =-(J18*X14) -> -4936.0699 | Y17: =-(K18*Y14) -> -5319.758 | Z17: =-(L18*Z14) -> -5733.2707 | AA17: =-(M18*AA14) -> -6178.9264
B18: R&D as % of sales | D18: =-(R17/R14) -> 0.14435381 | E18: =-(S17/S14) -> 0.16826639 | F18: =-(T17/T14) -> 0.10140269 | G18: =-(U17/U14) -> 0.15108159 | H18: =-(V17/V14) -> 0.16699972 | I18: =AVERAGE($D$18,$E$18,$F$18,$G$18,$H$18) -> 0.14642084 | J18: =AVERAGE($D$18,$E$18,$F$18,$G$18,$H$18) -> 0.14642084 | K18: =AVERAGE($D$18,$E$18,$F$18,$G$18,$H$18) -> 0.14642084 | L18: =AVERAGE($D$18,$E$18,$F$18,$G$18,$H$18) -> 0.14642084 | M18: =AVERAGE($D$18,$E$18,$F$18,$G$18,$H$18) -> 0.14642084 | P18: EBITDA | R18: =SUM(R14,R15,R16,R17) -> 4522 | S18: =SUM(S14,S15,S16,S17) -> 2594 | T18: =SUM(T14,T15,T16,T17) -> 7066 | U18: =SUM(U14,U15,U16,U17) -> 8690 | V18: =SUM(V14,V15,V16,V17) -> 10708 | W18: =SUM(W14,W15,W16,W17) -> 11559.698 | X18: =SUM(X14,X15,X16,X17) -> 12626.808 | Y18: =SUM(Y14,Y15,Y16,Y17) -> 13789.969 | ... AA18: =SUM(AA14,AA15,AA16,AA17) -> 16439.118
B19: Effective tax rate | D19: 0.1967 | E19: 0.1967 | F19: 0.3119 | G19: 0.2269 | H19: 0.1873 | I19: 0.4 | J19: 0.4 | K19: 0.4 | L19: 0.4 | M19: 0.4 | P19: % margin | R19: =R18/R14 -> 0.36164427 | S19: =S18/S14 -> 0.19152392 | T19: =T18/T14 -> 0.25810929 | U19: =U18/U14 -> 0.29603134 | V19: =V18/V14 -> 0.36893605 | W19: =W18/W14 -> 0.36955463 | X19: =X18/X14 -> 0.37455463 | Y19: =Y18/Y14 -> 0.37955463 | ... AA19: =AA18/AA14 -> 0.38955463
B21: Balance Sheet | P21: Depreciation & amortization* | R21: =-('3.3 CF Statements'!Z102) -> -428 | S21: =-('3.3 CF Statements'!Y102) -> -489 | T21: =-('3.3 CF Statements'!X102) -> -905 | U21: =-('3.3 CF Statements'!W102) -> -968 | V21: =-('3.3 CF Statements'!V102) -> -1068 | W21: 0 | X21: 0 | Y21: 0 | Z21: 0 | AA21: 0
B22: NC-WC as % of sales | D22: 0.3086239 | E22: 0.33093823 | F22: 0.23744292 | G22: 0.14322978 | H22: 0.13501988 | I22: =AVERAGE($E$22:$H$22) -> 0.2116577 | J22: =AVERAGE($E$22:$H$22) -> 0.2116577 | K22: =AVERAGE($E$22:$H$22) -> 0.2116577 | L22: =AVERAGE($E$22:$H$22) -> 0.2116577 | M22: =AVERAGE($E$22:$H$22) -> 0.2116577 | P22: EBIT | R22: =R18+R21 -> 4094 | S22: =S18+S21 -> 2105 | T22: =T18+T21 -> 6161 | U22: =U18+U21 -> 7722 | V22: =V18+V21 -> 9640 | W22: =W18+W21 -> 11559.698 | X22: =X18+X21 -> 12626.808 | Y22: =Y18+Y21 -> 13789.969 | ... AA22: =AA18+AA21 -> 16439.118
P23: % margin | R23: =R22/R14 -> 0.32741523 | S23: =S22/S14 -> 0.15541937 | T23: =T22/T14 -> 0.22505114 | U23: =U22/U14 -> 0.2630557 | V23: =V22/V14 -> 0.33213892 | W23: =W22/W14 -> 0.36955463 | X23: =X22/X14 -> 0.37455463 | Y23: =Y22/Y14 -> 0.37955463 | ... AA23: =AA22/AA14 -> 0.38955463
B24: Cash Flow Statement | P24: Source: own calculations
B25: D&A as % of sales | D25: 0.06481235 | E25: 0.07157662 | F25: 0.069710807 | G25: 0.05003557 | H25: 0.044163354 | I25: =AVERAGE($D$25:$H$25) -> 0.06005974 | J25: =AVERAGE($D$25:$H$25) -> 0.06005974 | K25: =AVERAGE($D$25:$H$25) -> 0.06005974 | L25: =AVERAGE($D$25:$H$25) -> 0.06005974 | M25: =AVERAGE($D$25:$H$25) -> 0.06005974
B26: Capex as % of sales | D26: 0.085706681 | E26: 0.11869559 | F26: 0.10216134 | G26: 0.061180934 | H26: 0.073726057 | I26: =AVERAGE($E$26:$H$26) -> 0.088940981 | J26: =AVERAGE($E$26:$H$26) -> 0.088940981 | K26: =AVERAGE($E$26:$H$26) -> 0.088940981 | L26: =AVERAGE($E$26:$H$26) -> 0.088940981 | M26: =AVERAGE($E$26:$H$26) -> 0.088940981
B27: Source: own calculations
Q30: =W16/W14 -> -0.35292453

Sheet 3. Financial Statements>>>

Sheet 3.1 Income Statements
B5: Pfizer Inc (PFE US) - Adjusted
B7: In Millions of USD except Per Share | C7: FY 1997 | D7: FY 1998 | E7: FY 1999 | F7: FY 2000 | G7: FY 2001 | H7: FY 2002 | I7: FY 2003 | J7: FY 2004 | K7: FY 2005 | L7: FY 2006 | M7: FY 2007 | N7: FY 2008 | O7: FY 2009 | P7: FY 2010 | Q7: FY 2011 | R7: FY 2012 | S7: FY 2013 | T7: FY 2014 | U7: FY 2015 | V7: FY 2016 | W7: FY 2017
B8: 12 Months Ending | C8: 12/31/1997 | D8: 12/31/1998 | E8: 12/31/1999 | F8: 12/31/2000 | G8: 12/31/2001 | H8: 12/31/2002 | I8: 12/31/2003 | J8: 12/31/2004 | K8: 12/31/2005 | L8: 12/31/2006 | M8: 12/31/2007 | N8: 12/31/2008 | O8: 12/31/2009 | P8: 12/31/2010 | Q8: 12/31/2011 | R8: 12/31/2012 | S8: 12/31/2013 | T8: 12/31/2014 | U8: 12/31/2015 | V8: 12/31/2016 | W8: 12/31/2017
B9: Revenue | C9: 12504 | D9: 13544 | E9: 27376 | F9: 29355 | G9: 29024 | H9: 32373 | I9: 45188 | J9: 52516 | K9: 47405 | L9: 48371 | M9: 48418 | N9: 48296 | O9: 49934 | P9: 67039 | Q9: 65259 | R9: 54657 | S9: 51452 | T9: 49605 | U9: 48851 | V9: 52824 | W9: 52546
B10: + Sales & Services Revenue | C10: — | D10: — | E10: — | F10: — | G10: — | H10: — | I10: — | J10: — | K10: — | L10: — | M10: — | N10: — | O10: 49934 | P10: 67039 | Q10: 65259 | R10: 54657 | S10: 51452 | T10: 49605 | U10: 48851 | V10: 52824 | W10: 52546
B11: - Cost of Revenue | C11: 1776 | D11: 2094 | E11: 5464 | F11: 5007 | G11: 3823 | H11: 4045 | I11: 6932 | J11: 7541 | K11: 7232 | L11: 7640 | M11: 7745 | N11: 7040 | O11: 8649 | P11: 15083 | Q11: 13264 | R11: 9493 | S11: 9250 | T11: 9139 | U11: 9433 | V11: 11630 | W11: 11154
B12: + Cost of Goods & Services | C12: — | D12: — | E12: — | F12: — | G12: — | H12: — | I12: — | J12: — | K12: — | L12: — | M12: — | N12: — | O12: 8649 | P12: 15083 | Q12: 13264 | R12: 9493 | S12: 9250 | T12: 9139 | U12: 9433 | V12: 11630 | W12: 11154
B13: Gross Profit | C13: 10728 | D13: 11450 | E13: 21912 | F13: 24348 | G13: 25201 | H13: 28328 | I13: 38256 | J13: 44975 | K13: 40173 | L13: 40731 | M13: 40673 | N13: 41256 | O13: 41285 | P13: 51956 | Q13: 51995 | R13: 45164 | S13: 42202 | T13: 40466 | U13: 39418 | V13: 41194 | W13: 41392
B14: + Other Operating Income | C14: — | D14: — | E14: — | F14: — | G14: — | H14: — | I14: — | J14: — | K14: — | L14: — | M14: — | N14: 0 | O14: 0 | P14: 0 | Q14: 0 | R14: 0 | S14: 0 | T14: 0 | U14: 0 | V14: 0 | W14: 0
B15: - Operating Expenses | C15: 6206 | D15: 8856 | E15: 14846 | F15: 15658 | G15: 14493 | H15: 16012 | I15: 22166 | J15: 27887 | K15: 25968 | L15: 26449 | M15: 25893 | N15: 24200 | O15: 25270 | P15: 34045 | Q15: 32673 | R15: 27082 | S15: 25314 | T15: 25001 | U15: 24009 | V15: 22703 | W15: 25476
B16: + Selling, General & Admin | C16: — | D16: 5568 | E16: 10810 | F16: 11223 | G16: — | H16: — | I16: — | J16: 16903 | K16: 15313 | L16: 15589 | M16: 15626 | N16: 14537 | O16: 14637 | P16: 19302 | Q16: 18733 | R16: 15018 | S16: 14164 | T16: 13720 | U16: 14325 | V16: 14745 | W16: 14768
B17: + Research & Development | C17: 1805 | D17: 2279 | E17: 2776 | F17: 4435 | G17: 4847 | H17: — | I17: — | J17: — | K17: — | L17: — | M17: — | N17: — | O17: 7776 | P17: 9340 | Q17: 8396 | R17: 6955 | S17: 6551 | T17: 7150 | U17: 7646 | V17: 7841 | W17: 7596
B18: + Other Operating Expense | C18: — | D18: — | E18: — | F18: — | G18: — | H18: — | I18: — | J18: — | K18: — | L18: — | M18: — | N18: — | O18: 2857 | P18: 5403 | Q18: 5544 | R18: 5109 | S18: 4599 | T18: 4131 | U18: 2038 | V18: 117 | W18: 3112
B19: Operating Income (Loss) | C19: 3073 | D19: 2594 | E19: 7066 | F19: 8690 | G19: 10708 | H19: 12316 | I19: 16090 | J19: 17088 | K19: 14205 | L19: 14282 | M19: 14780 | N19: 17056 | O19: 16015 | P19: 17911 | Q19: 19322 | R19: 18082 | S19: 16888 | T19: 15465 | U19: 15409 | V19: 18491 | W19: 15916
B20: - Non-Operating (Income) Loss | C20: — | D20: — | E20: — | F20: — | G20: — | H20: — | I20: — | J20: — | K20: — | L20: — | M20: — | N20: — | O20: -771 | P20: 551 | Q20: 692 | R20: 855 | S20: 66 | T20: -393 | U20: 1075 | V20: 1351 | W20: 316
B21: + Interest Expense, Net | C21: — | D21: -42 | E21: -64 | F21: -126 | G21: -273 | H21: -131 | I21: -76 | J21: 1 | K21: -269 | L21: -408 | M21: -1099 | N21: -726 | O21: 487 | P21: 1395 | Q21: 1225 | R21: 1140 | S21: 1011 | T21: 935 | U21: 728 | V21: 716 | W21: 879
B22: + Interest Expense | C22: 147 | D22: 143 | E22: 363 | F22: 432 | G22: 266 | H22: 251 | I22: 270 | J22: 347 | K22: 471 | L22: 517 | M22: 397 | N22: 562 | O22: 1233 | P22: 1797 | Q22: 1681 | R22: 1522 | S22: 1414 | T22: 1360 | U22: 1199 | V22: 1186 | W22: 1270
B23: - Interest Income | C23: — | D23: 185 | E23: 427 | F23: 558 | G23: 539 | H23: 382 | I23: 346 | J23: 346 | K23: 740 | L23: 925 | M23: 1496 | N23: 1288 | O23: 746 | P23: 402 | Q23: 456 | R23: 382 | S23: 403 | T23: 425 | U23: 471 | V23: 470 | W23: 391
B24: + Foreign Exch (Gain) Loss | C24: 26 | D24: — | E24: 11 | F24: 59 | G24: 0 | H24: 40 | I24: 1 | J24: 81 | K24: 8 | L24: — | M24: 0 | N24: 0 | O24: 0 | P24: 0 | Q24: 0 | R24: 0 | S24: 0 | T24: 0 | U24: 806 | V24: 0 | W24: 0
B25: + Other Non-Op (Income) Loss | C25: — | D25: — | E25: — | F25: — | G25: — | H25: — | I25: — | J25: — | K25: — | L25: — | M25: — | N25: — | O25: -1258 | P25: -844 | Q25: -533 | R25: -285 | S25: -945 | T25: -1328 | U25: -459 | V25: 635 | W25: -563
B26: Pretax Income (Loss), Adjusted | C26: 2867 | D26: 2594 | E26: 6945 | F26: 5781 | G26: 9984 | H26: 11796 | I26: 3263 | J26: 14007 | K26: 10800 | L26: 13028 | M26: 9278 | N26: 9694 | O26: 16786 | P26: 17360 | Q26: 18630 | R26: 17227 | S26: 16822 | T26: 15858 | U26: 14334 | V26: 17140 | W26: 15600
B27: - Abnormal Losses (Gains) | C27: -10 | D27: 2156.769 | E27: 343 | F27: 3257 | G27: 853 | H27: 716 | I27: 13108 | J27: 4018 | K27: 9867 | L27: 6116 | M27: 6890 | N27: 3308 | O27: 5959 | P27: 8078 | Q27: 6326 | R27: 5985 | S27: 1106 | T27: 3618 | U27: 5369 | V27: 8789 | W27: 3295
B28: + Acquired In-Process R&D | C28: — | D28: — | E28: — | F28: — | G28: — | H28: — | I28: — | J28: — | K28: — | L28: — | M28: — | N28: — | O28: 20 | P28: 125 | Q28: — | R28: — | S28: — | T28: — | U28: — | V28: — | W28: —
B29: + Merger/Acquisition Expense | C29: — | D29: — | E29: — | F29: — | G29: — | H29: — | I29: — | J29: — | K29: — | L29: — | M29: — | N29: — | O29: 4026 | P29: 3989 | Q29: 1979 | R29: 946 | S29: 376 | T29: 183 | U29: 909 | V29: 1364 | W29: 502
B30: + Disposal of Assets | C30: — | D30: — | E30: — | F30: — | G30: — | H30: — | I30: — | J30: — | K30: — | L30: — | M30: — | N30: — | O30: — | P30: — | Q30: — | R30: — | S30: — | T30: -288 | U30: -232 | V30: -171 | W30: —
B31: + Early Extinguishment of Debt | C31: — | D31: — | E31: — | F31: — | G31: — | H31: — | I31: — | J31: — | K31: — | L31: — | M31: — | N31: — | O31: — | P31: — | Q31: — | R31: — | S31: — | T31: — | U31: — | V31: 162 | W31: 999
B32: + Asset Write-Down | C32: — | D32: 213 | E32: — | F32: — | G32: — | H32: — | I32: — | J32: — | K32: — | L32: — | M32: 2798 | N32: — | O32: — | P32: — | Q32: — | R32: — | S32: — | T32: 469 | U32: 1282 | V32: 3716 | W32: 434
B33: + Impairment of Intangibles | C33: — | D33: — | E33: — | F33: — | G33: — | H33: — | I33: — | J33: — | K33: — | L33: — | M33: — | N33: — | O33: — | P33: — | Q33: — | R33: — | S33: — | T33: — | U33: 323 | V33: 869 | W33: —
B34: + Legal Settlement | C34: — | D34: — | E34: — | F34: — | G34: — | H34: — | I34: — | J34: — | K34: — | L34: — | M34: — | N34: — | O34: — | P34: — | Q34: — | R34: — | S34: — | T34: 993 | U34: 968 | V34: 494 | W34: 237
B35: + Restructuring | C35: — | D35: — | E35: — | F35: — | G35: — | H35: — | I35: — | J35: — | K35: — | L35: — | M35: — | N35: — | O35: — | P35: — | Q35: — | R35: — | S35: — | T35: 168 | U35: 1451 | V35: 1685 | W35: 567
B36: + Other Abnormal Items | C36: — | D36: — | E36: — | F36: — | G36: — | H36: — | I36: — | J36: — | K36: — | L36: — | M36: — | N36: — | O36: 1913 | P36: 3964 | Q36: 4347 | R36: 5039 | S36: 730 | T36: 2093 | U36: 668 | V36: 670 | W36: 556
B37: Pretax Income (Loss), GAAP | C37: 2867 | D37: 2594 | E37: 6945 | F37: 5781 | G37: 9984 | H37: 11796 | I37: 3263 | J37: 14007 | K37: 10800 | L37: 13028 | M37: 9278 | N37: 9694 | O37: 10827 | P37: 9282 | Q37: 12304 | R37: 11242 | S37: 15716 | T37: 12240 | U37: 8965 | V37: 8351 | W37: 12305
B38: - Income Tax Expense (Benefit) | C38: 775 | D38: 642 | E38: 1968 | F38: 2049 | G38: 2433 | H38: 2609 | I38: 1621 | J38: 2665 | K38: 3178 | L38: 1992 | M38: 1023 | N38: 1645 | O38: 2197 | P38: 1071 | Q38: 3909 | R38: 2221 | S38: 4306 | T38: 3120 | U38: 1990 | V38: 1123 | W38: -9048
B39: + Current Income Tax | C39: — | D39: — | E39: — | F39: — | G39: — | H39: — | I39: — | J39: — | K39: — | L39: — | M39: — | N39: — | O39: 11779 | P39: -866 | Q39: 3602 | R39: 1435 | S39: 2580 | T39: 2800 | U39: 2010 | V39: 1823 | W39: 17156
B40: + Deferred Income Tax | C40: — | D40: — | E40: — | F40: — | G40: — | H40: — | I40: — | J40: — | K40: — | L40: — | M40: — | N40: — | O40: -9582 | P40: 1937 | Q40: 307 | R40: 786 | S40: 1726 | T40: 320 | U40: -20 | V40: -700 | W40: -26204
B41: Income (Loss) from Cont Ops | C41: 2092 | D41: 1952 | E41: 4977 | F41: 3732 | G41: 7551 | H41: 9187 | I41: 1642 | J41: 11342 | K41: 7622 | L41: 11036 | M41: 8255 | N41: 8049 | O41: 8630 | P41: 8211 | Q41: 8395 | R41: 9021 | S41: 11410 | T41: 9120 | U41: 6975 | V41: 7228 | W41: 21353
B42: - Net Extraordinary Losses (Gains) | C42: -131 | D42: -1401 | E42: 20 | F42: -8 | G42: -251 | H42: 55 | I42: -2271 | J42: -29 | K42: -475 | L42: -8313 | M42: 69 | N42: -78 | O42: -14 | P42: -77 | Q42: -1654 | R42: -5577 | S42: -10662 | T42: -48 | U42: -11 | V42: -18 | W42: -2
B43: + Discontinued Operations | C43: — | D43: -1401 | E43: 20 | F43: — | G43: — | H43: — | I43: — | J43: — | K43: -498 | L43: -8313 | M43: 69 | N43: — | O43: -14 | P43: -77 | Q43: -1654 | R43: -5577 | S43: -10662 | T43: -48 | U43: -11 | V43: -18 | W43: -2
B44: + XO & Accounting Changes | C44: — | D44: — | E44: — | F44: — | G44: — | H44: — | I44: — | J44: — | K44: 23 | L44: — | M44: — | N44: — | O44: 0 | P44: 0 | Q44: 0 | R44: 0 | S44: 0 | T44: 0 | U44: 0 | V44: 0 | W44: 0
B45: Income (Loss) Incl. MI | C45: 2223 | D45: 3353 | E45: 4957 | F45: 3740 | G45: 7802 | H45: 9132 | I45: 3913 | J45: 11371 | K45: 8097 | L45: 19349 | M45: 8186 | N45: 8127 | O45: 8644 | P45: 8288 | Q45: 10049 | R45: 14598 | S45: 22072 | T45: 9168 | U45: 6986 | V45: 7246 | W45: 21355
B46: - Minority Interest | C46: 10 | D46: 2 | E46: 5 | F46: 14 | G46: 14 | H46: 6 | I46: 3 | J46: 10 | K46: 12 | L46: 12 | M46: 42 | N46: 23 | O46: 9 | P46: 31 | Q46: 40 | R46: 28 | S46: 69 | T46: 33 | U46: 26 | V46: 31 | W46: 47
B47: Net Income, GAAP | C47: 2213 | D47: 3351 | E47: 4952 | F47: 3726 | G47: 7788 | H47: 9126 | I47: 3910 | J47: 11361 | K47: 8085 | L47: 19337 | M47: 8144 | N47: 8104 | O47: 8635 | P47: 8257 | Q47: 10009 | R47: 14570 | S47: 22003 | T47: 9135 | U47: 6960 | V47: 7215 | W47: 21308
B48: - Preferred Dividends | C48: 0 | D48: — | E48: 0 | F48: 0 | G48: 0 | H48: 0 | I48: 0 | J48: 4 | K48: 6 | L48: 5 | M48: 4 | N48: 3 | O48: 5 | P48: 3 | Q48: 3 | R48: 2 | S48: 2 | T48: 0 | U48: 2 | V48: 2 | W48: 1
B49: - Other Adjustments | C49: — | D49: — | E49: — | F49: 0 | G49: 0 | H49: 0 | I49: 0 | J49: 0 | K49: — | L49: 0 | M49: 0 | N49: 0 | O49: 0 | P49: 0 | Q49: 0 | R49: 0 | S49: 0 | T49: 0 | U49: 0 | V49: 0 | W49: 0
B50: Net Income Avail to Common, GAAP | C50: 2213 | D50: 3351 | E50: 4952 | F50: 3726 | G50: 7788 | H50: 9126 | I50: 3910 | J50: 11357 | K50: 8079 | L50: 19332 | M50: 8140 | N50: 8101 | O50: 8630 | P50: 8254 | Q50: 10006 | R50: 14568 | S50: 22001 | T50: 9135 | U50: 6958 | V50: 7213 | W50: 21307
B52: Net Income Avail to Common, Adj | C52: 2213 | D52: 3351 | E52: 4952 | F52: 3726 | G52: 7788 | H52: 9126 | I52: 3910 | J52: 11357 | K52: 8079 | L52: 19332 | M52: 8140 | N52: 8101 | O52: 11577 | P52: 11854.25 | Q52: 12836 | R52: 12185 | S52: 12101 | T52: 11438.7 | U52: 10436.85 | V52: 12907.85 | W52: 12901.859
B53: Net Abnormal Losses (Gains) | C53: — | D53: — | E53: — | F53: — | G53: 563 | H53: 716 | I53: 11083 | J53: — | K53: — | L53: — | M53: — | N53: 2150.2 | O53: 2961 | P53: 3677.25 | Q53: 4484 | R53: 3194 | S53: 762 | T53: 2351.7 | U53: 3489.85 | V53: 5712.85 | W53: -8403.1412
B54: Net Extraordinary Losses (Gains) | C54: -131 | D54: -1401 | E54: 20 | F54: -8 | G54: -251 | H54: 55 | I54: -2271 | J54: -29 | K54: -475 | L54: -8313 | M54: 69 | N54: -78 | O54: -14 | P54: -77 | Q54: -1654 | R54: -5577 | S54: -10662 | T54: -48 | U54: -11 | V54: -18 | W54: -2
B56: Basic Weighted Avg Shares | C56: 3771 | D56: 3789 | E56: 6126 | F56: 6210 | G56: 6239.1 | H56: 6156 | I56: 7213 | J56: 7531 | K56: 7361 | L56: 7242 | M56: 6917 | N56: 6727 | O56: 7007 | P56: 8036 | Q56: 7817 | R56: 7442 | S56: 6813 | T56: 6346 | U56: 6176 | V56: 6089 | W56: 5970
B57: Basic EPS, GAAP | C57: 0.586667 | D57: 0.883333 | E57: 0.81 | F57: 0.6 | G57: 1.25 | H57: 1.48 | I57: 0.54 | J57: 1.51 | K57: 1.1 | L57: 2.67 | M57: 1.18 | N57: 1.2 | O57: 1.23 | P57: 1.03 | Q57: 1.28 | R57: 1.96 | S57: 3.23 | T57: 1.44 | U57: 1.13 | V57: 1.18 | W57: 3.57
B58: Basic EPS from Cont Ops | C58: 0.553333 | D58: 0.513333 | E58: 0.81 | F58: 0.6 | G58: 1.21 | H58: 1.49 | I58: 0.22 | J58: 1.51 | K58: 1.03 | L58: 1.52 | M58: 1.19 | N58: 1.19 | O58: 1.23 | P58: 1.02 | Q58: 1.07 | R58: 1.21 | S58: 1.67 | T58: 1.431926 | U58: 1.13 | V58: 1.18 | W58: 3.57
B59: Basic EPS from Cont Ops, Adjusted | C59: 0.55 | D59: 0.513333 | E59: 0.84 | F59: 1.05 | G59: 1.3 | H59: 1.61 | I59: 1.75 | J59: 1.8 | K59: 1.96 | L59: 2.07 | M59: 2.19 | N59: 1.51 | O59: 1.652205 | P59: 1.475143 | Q59: 1.642062 | R59: 1.637329 | S59: 1.776163 | T59: 1.802506 | U59: 1.689904 | V59: 2.119864 | W59: 2.161115
B61: Diluted Weighted Avg Shares | C61: 3909 | D61: 3945 | E61: 6317 | F61: 6368 | G61: 6361.4 | H61: 6241 | I61: 7286 | J61: 7614 | K61: 7411 | L61: 7274 | M61: 6939 | N61: 6750 | O61: 7045 | P61: 8074 | Q61: 7870 | R61: 7508 | S61: 6895 | T61: 6424 | U61: 6257 | V61: 6159 | W61: 6058
B62: Diluted EPS, GAAP | C62: 0.566667 | D62: 0.85 | E62: 0.78 | F62: 0.59 | G62: 1.22 | H62: 1.46 | I62: 0.54 | J62: 1.49 | K62: 1.09 | L62: 2.66 | M62: 1.17 | N62: 1.2 | O62: 1.23 | P62: 1.02 | Q62: 1.27 | R62: 1.94 | S62: 3.19 | T62: 1.42 | U62: 1.11 | V62: 1.17 | W62: 3.52
B63: Diluted EPS from Cont Ops | C63: 0.533333 | D63: 0.493333 | E63: 0.79 | F63: 0.59 | G63: 1.18 | H63: 1.47 | I63: 0.22 | J63: 1.49 | K63: 1.02 | L63: 1.52 | M63: 1.18 | N63: 1.19 | O63: 1.23 | P63: 1.01 | Q63: 1.06 | R63: 1.2 | S63: 1.65 | T63: 1.412528 | U63: 1.11 | V63: 1.17 | W63: 3.52
B64: Diluted EPS from Cont Ops, Adjusted | C64: 0.53 | D64: 0.493333 | E64: 0.82 | F64: 1.02 | G64: 1.27 | H64: 1.59 | I64: 1.75 | J64: 1.78 | K64: 1.95 | L64: 2.07 | M64: 2.17 | N64: 1.51 | O64: 1.650298 | P64: 1.465443 | Q64: 1.629759 | R64: 1.625413 | S64: 1.760515 | T64: 1.778608 | U64: 1.667751 | V64: 2.097561 | W64: 2.132885
B66: Reference Items
B67: Accounting Standard | C67: US GAAP | D67: US GAAP | E67: US GAAP | F67: US GAAP | G67: US GAAP | H67: US GAAP | I67: US GAAP | J67: US GAAP | K67: US GAAP | L67: US GAAP | M67: US GAAP | N67: US GAAP | O67: US GAAP | P67: US GAAP | Q67: US GAAP | R67: US GAAP | S67: US GAAP | T67: US GAAP | U67: US GAAP | V67: US GAAP | W67: US GAAP
B68: EBITDA | C68: 3501 | D68: 3083 | E68: 7971 | F68: 9658 | G68: 11776 | H68: 13352 | I68: 20115 | J68: 22181 | K68: 19781 | L68: 19575 | M68: 19980 | N68: 22146 | O68: 20772 | P68: 26398 | Q68: 28229 | R68: 25737 | S68: 23298 | T68: 21002 | U68: 20566 | V68: 24248 | W68: 22185
B69: EBITDA Margin (T12M) | C69: 27.99904 | D69: 22.762847 | E69: 29.116745 | F69: 32.900698 | G69: 40.573319 | H69: 41.244247 | I69: 44.51403 | J69: 42.236652 | K69: 41.727666 | L69: 40.468463 | M69: 41.265645 | N69: 45.854729 | O69: 41.598911 | P69: 39.377079 | Q69: 43.256869 | R69: 47.088205 | S69: 45.281039 | T69: 42.338474 | U69: 42.099445 | V69: 45.903377 | W69: 42.22015
B70: EBITA | C70: 3138 | D70: — | E70: — | F70: — | G70: — | H70: — | I70: — | J70: — | K70: — | L70: — | M70: — | N70: — | O70: 19015 | P70: 23415 | Q70: 24907 | R70: 23191 | S70: 21487 | T70: 19504 | U70: 19137 | V70: 22547 | W70: 20674
B71: EBIT | C71: 3073 | D71: 2594 | E71: 7066 | F71: 8690 | G71: 10708 | H71: 12316 | I71: 16090 | J71: 17088 | K71: 14205 | L71: 14282 | M71: 14780 | N71: 17056 | O71: 16015 | P71: 17911 | Q71: 19322 | R71: 18082 | S71: 16888 | T71: 15465 | U71: 15409 | V71: 18491 | W71: 15916
B72: Gross Margin | C72: 85.796545 | D72: 84.539279 | E72: 80.040912 | F72: 82.943281 | G72: 86.828142 | H72: 87.50502 | I72: 84.659644 | J72: 85.640567 | K72: 84.744225 | L72: 84.205412 | M72: 84.003883 | N72: 85.423223 | O72: 82.679136 | P72: 77.501156 | Q72: 79.674834 | R72: 82.631685 | S72: 82.022079 | T72: 81.576454 | U72: 80.690262 | V72: 77.983492 | W72: 78.772885
B73: Operating Margin | C73: 24.576136 | D73: 19.152392 | E73: 25.810929 | F73: 29.603134 | G73: 36.893605 | H73: 38.044049 | I73: 35.606798 | J73: 32.538655 | K73: 29.965194 | L73: 29.525956 | M73: 30.525837 | N73: 35.315554 | O73: 32.072335 | P73: 26.717284 | Q73: 29.608177 | R73: 33.082679 | S73: 32.822825 | T73: 31.176293 | U73: 31.542855 | V73: 35.004922 | W73: 30.289651
B74: Profit Margin | C74: 17.698337 | D74: 24.741583 | E74: 18.088837 | F74: 12.692897 | G74: 26.832966 | H74: 28.190158 | I74: 8.65274 | J74: 21.633407 | K74: 17.055163 | L74: 39.976432 | M74: 16.820191 | N74: 16.779858 | O74: 23.194617 | P74: 17.687093 | Q74: 19.673915 | R74: 22.297235 | S74: 23.522895 | T74: 23.059571 | U74: 21.368754 | V74: 24.439365 | W74: 24.555359
B75: Sales per Employee | C75: 254146.34 | D75: — | E75: — | F75: 326166.67 | G75: 322488.89 | H75: 330336.73 | I75: 370393.44 | J75: 456660.87 | K75: — | L75: — | M75: — | N75: — | O75: — | P75: 606139.24 | Q75: 629305.69 | R75: 597344.26 | S75: 662187.9 | T75: 633524.9 | U75: 498988.76 | V75: 547398.96 | W75: 582549.89
B76: Dividends per Share | C76: 0.226667 | D76: 0.253333 | E76: 0.31 | F76: 0.36 | G76: 0.44 | H76: 0.52 | I76: 0.6 | J76: 0.68 | K76: 0.76 | L76: 0.96 | M76: 1.16 | N76: 1.28 | O76: 0.8 | P76: 0.72 | Q76: 0.8 | R76: 0.88 | S76: 0.96 | T76: 1.04 | U76: 1.12 | V76: 1.2 | W76: 1.28
B77: Total Cash Common Dividends | C77: 881 | D77: 976 | E77: 1820 | F77: 2197 | G77: 2869 | H77: 3189.131 | I77: 4327.665 | J77: 5243 | K77: 5555 | L77: 6919 | M77: 7975 | N77: 8610.56 | O77: 5605.6 | P77: 5964 | Q77: 6512 | R77: 6548.96 | S77: 6540.48 | T77: 6599.84 | U77: 6917.12 | V77: 7306.8 | W77: 7641.6
B78: Capitalized Interest Expense | C78: 2 | D78: — | E78: 40 | F78: 46 | G78: 56 | H78: 28 | I78: 20 | J78: 12 | K78: 17 | L78: 29 | M78: 43 | N78: 46 | O78: 34 | P78: 36 | Q78: 50 | R78: 41 | S78: 32 | T78: 41 | U78: 32 | V78: 61 | W78: 72
B79: Depreciation Expense | C79: 363 | D79: — | E79: — | F79: — | G79: — | H79: — | I79: — | J79: — | K79: — | L79: — | M79: — | N79: — | O79: — | P79: — | Q79: — | R79: — | S79: — | T79: — | U79: — | V79: — | W79: —
B80: Rental Expense | C80: — | D80: — | E80: 295 | F80: 292 | G80: 280 | H80: 341 | I80: 634 | J80: 708 | K80: 410 | L80: 420 | M80: 398 | N80: 370 | O80: 364 | P80: 387 | Q80: 380 | R80: 335 | S80: 233 | T80: 216 | U80: 243 | V80: 292 | W80: 314
B81: Source: Bloomberg

Sheet 3.2 Balance Sheets
C4: Pfizer Inc (PFE US) - Standardized
C6: In Millions of USD except Per Share | D6: FY 1997 | E6: FY 1998 | F6: FY 1999 | G6: FY 2000 | H6: FY 2001 | I6: FY 2002 | J6: FY 2003 | K6: FY 2004 | L6: FY 2005 | M6: FY 2006 | N6: FY 2007 | O6: FY 2008 | P6: FY 2009 | Q6: FY 2010 | R6: FY 2011 | S6: FY 2012 | T6: FY 2013 | U6: FY 2014 | V6: FY 2015 | W6: FY 2016 | X6: FY 2017
C7: 12 Months Ending | D7: 12/31/1997 | E7: 12/31/1998 | F7: 12/31/1999 | G7: 12/31/2000 | H7: 12/31/2001 | I7: 12/31/2002 | J7: 12/31/2003 | K7: 12/31/2004 | L7: 12/31/2005 | M7: 12/31/2006 | N7: 12/31/2007 | O7: 12/31/2008 | P7: 12/31/2009 | Q7: 12/31/2010 | R7: 12/31/2011 | S7: 12/31/2012 | T7: 12/31/2013 | U7: 12/31/2014 | V7: 12/31/2015 | W7: 12/31/2016 | X7: 12/31/2017
C8: Total Assets
C9: + Cash, Cash Equivalents & STI | D9: 1589 | E9: 3929 | F9: 6386 | G9: 6863 | H9: 8615 | I9: 12551 | J9: 11952 | K9: 19893 | L9: 22226 | M9: 27713 | N9: 25475 | O9: 23731 | P9: 25969 | Q9: 28012 | R9: 26452 | S9: 32399 | T9: 32408 | U9: 36122 | V9: 23290 | W9: 17850 | X9: 19992
C10: + Cash & Cash Equivalents | D10: 877 | E10: 1552 | F10: 2358 | G10: 1099 | H10: 1036 | I10: 1878 | J10: 1520 | K10: 1808 | L10: 2247 | M10: 1827 | N10: 3406 | O10: 2122 | P10: 1978 | Q10: 1735 | R10: 3182 | S10: 10081 | T10: 2183 | U10: 3343 | V10: 3641 | W10: 2595 | X10: 1342
C11: + ST Investments | D11: 712 | E11: 2377 | F11: 4028 | G11: 5764 | H11: 7579 | I11: 10673 | J11: 10432 | K11: 18085 | L11: 19979 | M11: 25886 | N11: 22069 | O11: 21609 | P11: 23991 | Q11: 26277 | R11: 23270 | S11: 22318 | T11: 30225 | U11: 32779 | V11: 19649 | W11: 15255 | X11: 18650
C12: + Accounts & Notes Receiv | D12: 2335 | E12: 2914 | F12: 5368 | G12: 5489 | H12: 5067 | I12: 6184 | J12: 8775 | K12: 9367 | L12: 9103 | M12: 9392 | N12: 9843 | O12: 8958 | P12: 14645 | Q12: 13380 | R12: 13058 | S12: 10675 | T12: 9357 | U12: 8401 | V12: 8176 | W12: 8225 | X12: 8221
C13: + Accounts Receivable, Net | D13: — | E13: 2914 | F13: 5368 | G13: 5489 | H13: 4798 | I13: 5785 | J13: 8775 | K13: 9367 | L13: 9103 | M13: 9392 | N13: 9843 | O13: 8958 | P13: 14645 | Q13: 13380 | R13: 13058 | S13: 10675 | T13: 9357 | U13: 8401 | V13: 8176 | W13: 8225 | X13: 8221
C14: + Notes Receivable, Net | D14: — | E14: — | F14: — | G14: — | H14: — | I14: — | J14: — | K14: — | L14: — | M14: — | N14: — | O14: — | P14: 0 | Q14: 0 | R14: 0 | S14: 0 | T14: 0 | U14: 0 | V14: 0 | W14: 0 | X14: 0
C15: + Inventories | D15: 1461 | E15: 1828 | F15: 2588 | G15: 2702 | H15: 2485 | I15: 2678 | J15: 5837 | K15: 6660 | L15: 5478 | M15: 6111 | N15: 5302 | O15: 4381 | P15: 12403 | Q15: 8275 | R15: 6610 | S15: 6076 | T15: 6166 | U15: 5663 | V15: 7513 | W15: 6783 | X15: 7579
C16: + Raw Materials | D16: 211 | E16: 241 | F16: 464 | G16: 433 | H16: 412 | I16: 403 | J16: 1310 | K16: 1314 | L16: 1349 | M16: 1262 | N16: 885 | O16: 830 | P16: 1378 | Q16: 883 | R16: 785 | S16: 448 | T16: 505 | U16: 510 | V16: 867 | W16: 793 | X16: 788
C17: + Work In Process | D17: 808 | E17: 890 | F17: 977 | G17: 1074 | H17: 1062 | I17: 1142 | J17: 2219 | K17: 2496 | L17: 2373 | M17: 3198 | N17: 2353 | O17: 1527 | P17: 5776 | Q17: 3727 | R17: 3514 | S17: 3374 | T17: 3445 | U17: 3248 | V17: 3932 | W17: 3696 | X17: 3908
C18: + Finished Goods | D18: 442 | E18: 697 | F18: 1147 | G18: 1195 | H18: 1011 | I18: 1133 | J18: 2308 | K18: 2850 | L18: 1756 | M18: 1651 | N18: 2064 | O18: 2024 | P18: 5249 | Q18: 3665 | R18: 2311 | S18: 2254 | T18: 2216 | U18: 1905 | V18: 2714 | W18: 2294 | X18: 2883
C19: + Other Inventory | D19: — | E19: — | F19: — | G19: 0 | H19: 0 | I19: 0 | J19: 0 | K19: 0 | L19: 0 | M19: — | N19: 0 | O19: 0 | P19: 0 | Q19: 0 | R19: 0 | S19: 0 | T19: 0 | U19: 0 | V19: 0 | W19: 0 | X19: 0
C20: + Other ST Assets | D20: 2057 | E20: 1260 | F20: 1969 | G20: 2133 | H20: 3045 | I20: 3368 | J20: 3177 | K20: 3774 | L20: 10028 | M20: 4442 | N20: 6229 | O20: 6006 | P20: 8653 | Q20: 11346 | R20: 14697 | S20: 15681 | T20: 8313 | U20: 5409 | V20: 4825 | W20: 6091 | X20: 5349
C21: + Derivative & Hedging Assets | D21: — | E21: — | F21: — | G21: — | H21: — | I21: — | J21: — | K21: — | L21: — | M21: — | N21: — | O21: — | P21: 526 | Q21: 515 | R21: 357 | S21: 296 | T21: 286 | U21: 1059 | V21: 586 | W21: 566 | X21: —
C22: + Assets Held-for-Sale | D22: — | E22: — | F22: — | G22: — | H22: — | I22: — | J22: — | K22: — | L22: — | M22: — | N22: — | O22: — | P22: 496 | Q22: — | R22: — | S22: — | T22: — | U22: — | V22: 9 | W22: 801 | X22: 12
C23: + Deferred Tax Assets | D23: — | E23: — | F23: — | G23: — | H23: — | I23: — | J23: — | K23: — | L23: — | M23: — | N23: — | O23: — | P23: — | Q23: — | R23: — | S23: 6170 | T23: 4624 | U23: 2566 | V23: 2662 | W23: 3041 | X23: 3050
C24: + Discontinued Operations | D24: — | E24: — | F24: — | G24: — | H24: — | I24: — | J24: — | K24: — | L24: — | M24: — | N24: — | O24: — | P24: — | Q24: 1439 | R24: 5317 | S24: 5944 | T24: 76 | U24: — | V24: — | W24: — | X24: —
C25: + Misc ST Assets | D25: — | E25: — | F25: — | G25: — | H25: — | I25: — | J25: — | K25: — | L25: — | M25: — | N25: — | O25: — | P25: 7631 | Q25: 9392 | R25: 9023 | S25: 3271 | T25: 3327 | U25: 1784 | V25: 1568 | W25: 1683 | X25: 2287
C26: Total Current Assets | D26: 7442 | E26: 9931 | F26: 16311 | G26: 17187 | H26: 19212 | I26: 24781 | J26: 29741 | K26: 39694 | L26: 46835 | M26: 47658 | N26: 46849 | O26: 43076 | P26: 61670 | Q26: 61013 | R26: 60817 | S26: 64831 | T26: 56244 | U26: 55595 | V26: 43804 | W26: 38949 | X26: 41141
C27: + Property, Plant & Equip, Net | D27: 3793 | E27: 4415 | F27: 8685 | G27: 9425 | H27: 9783 | I27: 10712 | J27: 18287 | K27: 18385 | L27: 16233 | M27: 16632 | N27: 15734 | O27: 13287 | P27: 22780 | Q27: 18645 | R27: 15921 | S27: 13213 | T27: 12397 | U27: 11760 | V27: 13766 | W27: 13318 | X27: 13865
C28: Geographic Segments | D28: — | E28: — | F28: — | G28: — | H28: — | I28: — | J28: — | K28: — | L28: — | M28: — | N28: — | O28: — | P28: — | Q28: — | R28: 15921 | S28: 13213 | T28: 12397 | U28: 11761 | V28: 13766 | W28: 13318 | X28: 13865
C29: United States | D29: — | E29: — | F29: — | G29: — | H29: — | I29: — | J29: — | K29: — | L29: — | M29: — | N29: — | O29: — | P29: — | Q29: — | R29: 7893 | S29: 6485 | T29: 5885 | U29: 5575 | V29: 7072 | W29: 6649 | X29: 6971
C30: Developed Europe | D30: — | E30: — | F30: — | G30: — | H30: — | I30: — | J30: — | K30: — | L30: — | M30: — | N30: — | O30: — | P30: — | Q30: — | R30: 5866 | S30: 4895 | T30: 4845 | U30: 4606 | V30: 4376 | W30: 4228 | X30: 4345
C31: Emerging Markets | D31: — | E31: — | F31: — | G31: — | H31: — | I31: — | J31: — | K31: — | L31: — | M31: — | N31: — | O31: — | P31: — | Q31: — | R31: 1259 | S31: 1017 | T31: 971 | U31: 963 | V31: 1658 | W31: 1797 | X31: 1917
C32: Developed Rest of World | D32: — | E32: — | F32: — | G32: — | H32: — | I32: — | J32: — | K32: — | L32: — | M32: — | N32: — | O32: — | P32: — | Q32: — | R32: 903 | S32: 816 | T32: 696 | U32: 617 | V32: 660 | W32: 644 | X32: 632
C33: + Property, Plant & Equip | D33: 5867 | E33: 6844 | F33: 13191 | G33: 14134 | H33: 14372 | I33: 16143 | J33: 25381 | K33: 26919 | L33: 25153 | M33: 27063 | N33: 28103 | O33: 25128 | P33: 33924 | Q33: 31377 | R33: 29237 | S33: 25965 | T33: 25678 | U33: 24986 | V33: 27268 | W33: 28125 | X33: 30037
C34: - Accumulated Depreciation | D34: 2074 | E34: 2429 | F34: 4506 | G34: 4709 | H34: 4589 | I34: 5431 | J34: 7094 | K34: 8534 | L34: 8920 | M34: 10431 | N34: 12369 | O34: 11841 | P34: 11144 | Q34: 12732 | R34: 13316 | S34: 12752 | T34: 13281 | U34: 13226 | V34: 13502 | W34: 14807 | X34: 16172
C35: + LT Investments & Receivables | D35: 1330 | E35: 1756 | F35: 1764 | G35: 2529 | H35: 5724 | I35: 5161 | J35: 6142 | K35: 3873 | L35: 2497 | M35: 3892 | N35: 4856 | O35: 11478 | P35: 13122 | Q35: 9747 | R35: 9814 | S35: 14149 | T35: 16406 | U35: 17518 | V35: 15999 | W35: 7116 | X35: 7015
C36: + LT Investments | D36: — | E36: — | F36: — | G36: — | H36: — | I36: — | J36: — | K36: — | L36: — | M36: — | N36: — | O36: — | P36: 13122 | Q36: 9747 | R36: 9814 | S36: 14149 | T36: 16406 | U36: 17518 | V36: 15999 | W36: 7116 | X36: 7015
C37: + Other LT Assets | D37: 2426 | E37: 2200 | F37: 4612 | G37: 4369 | H37: 4434 | I37: 5702 | J37: 62605 | K37: 61732 | L37: 51405 | M37: 47364 | N37: 47829 | O37: 43307 | P37: 115377 | Q37: 105609 | R37: 101450 | S37: 93605 | T37: 87054 | U37: 82692 | V37: 93812 | W37: 112232 | X37: 109777
C38: + Total Intangible Assets | D38: 989 | E38: 813 | F38: 1870 | G38: 1791 | H38: 1689 | I38: 2121 | J38: 57856 | K38: 63281 | L38: 47229 | M38: 45226 | N38: 41880 | O38: 39185 | P38: 110391 | Q38: 101483 | R38: 95753 | S38: 88807 | T38: 81904 | U38: 77236 | V38: 88598 | W38: 107097 | X38: 104692
C39: + Goodwill | D39: — | E39: 813 | F39: 1870 | G39: 1791 | H39: 1689 | I39: 1200 | J39: 22265 | K39: 23756 | L39: 20985 | M39: 20876 | N39: 21382 | O39: 21464 | P39: 42376 | Q39: 43928 | R39: 44569 | S39: 43661 | T39: 42519 | U39: 42069 | V39: 48242 | W39: 54449 | X39: 55952
C40: Product/Brand Segments | D40: — | E40: — | F40: — | G40: — | H40: — | I40: — | J40: — | K40: 22265 | L40: 21055 | M40: 20876 | N40: 21382 | O40: 21464 | P40: 42376 | Q40: 42357 | R40: 44569 | S40: 43661 | T40: 42519 | U40: 42069 | V40: 48242 | W40: 54449 | X40: 55952
C41: Pfizer's Innovative Health | D41: — | E41: — | F41: — | G41: — | H41: — | I41: — | J41: — | K41: 22102 | L41: 20966 | M41: 20798 | N41: 21256 | O41: 21317 | P41: 22165 | Q41: — | R41: — | S41: — | T41: — | U41: 24430 | V41: 23809 | W41: 30134 | X41: 31141
C42: Pfizer's Essential Health | D42: — | E42: — | F42: — | G42: — | H42: — | I42: — | J42: — | K42: — | L42: — | M42: — | N42: — | O42: — | P42: — | Q42: — | R42: — | S42: — | T42: — | U42: 17639 | V42: 24433 | W42: 24315 | X42: 24811
C43: Global Vaccines, Oncology and Consumer Healthcare | D43: — | E43: — | F43: — | G43: — | H43: — | I43: — | J43: — | K43: — | L43: — | M43: — | N43: — | O43: — | P43: — | Q43: — | R43: — | S43: — | T43: 11559 | U43: — | V43: — | W43: — | X43: —
C44: Global Established Pharmaceutical | D44: — | E44: — | F44: — | G44: — | H44: — | I44: — | J44: — | K44: — | L44: — | M44: — | N44: — | O44: — | P44: — | Q44: — | R44: — | S44: — | T44: 17750 | U44: — | V44: — | W44: — | X44: —
C45: Global Innovative Pharmaceutical | D45: — | E45: — | F45: — | G45: — | H45: — | I45: — | J45: — | K45: — | L45: — | M45: — | N45: — | O45: — | P45: — | Q45: — | R45: — | S45: — | T45: 13210 | U45: — | V45: — | W45: — | X45: —
C46: Consumer, Capsugel and Pfizer CentreSource | D46: — | E46: — | F46: — | G46: — | H46: — | I46: — | J46: — | K46: 85 | L46: 10 | M46: 17 | N46: 18 | O46: — | P46: — | Q46: — | R46: — | S46: — | T46: — | U46: — | V46: — | W46: — | X46: —
C47: Animal Health And Consumer Health | D47: — | E47: — | F47: — | G47: — | H47: — | I47: — | J47: — | K47: 78 | L47: 79 | M47: 61 | N47: 108 | O47: 129 | P47: — | Q47: 154 | R47: — | S47: 2021 | T47: — | U47: — | V47: — | W47: — | X47: —
C48: Other | D48: — | E48: — | F48: — | G48: — | H48: — | I48: — | J48: — | K48: — | L48: — | M48: — | N48: — | O48: 18 | P48: — | Q48: 20038 | R48: 2497 | S48: — | T48: — | U48: — | V48: — | W48: — | X48: —
C49: Pfizer CentreSource | D49: — | E49: — | F49: — | G49: — | H49: — | I49: — | J49: — | K49: — | L49: — | M49: — | N49: — | O49: — | P49: 20038 | Q49: — | R49: — | S49: — | T49: — | U49: — | V49: — | W49: — | X49: —
C50: Diversified | D50: — | E50: — | F50: — | G50: — | H50: — | I50: — | J50: — | K50: — | L50: — | M50: — | N50: — | O50: — | P50: 173 | Q50: — | R50: 42072 | S50: 41640 | T50: — | U50: — | V50: — | W50: — | X50: —
C51: Primary Care | D51: — | E51: — | F51: — | G51: — | H51: — | I51: — | J51: — | K51: — | L51: — | M51: — | N51: — | O51: — | P51: — | Q51: 3272 | R51: 6229 | S51: 6152 | T51: — | U51: — | V51: — | W51: — | X51: —
C52: Established Products&Emerging Market | D52: — | E52: — | F52: — | G52: — | H52: — | I52: — | J52: — | K52: — | L52: — | M52: — | N52: — | O52: — | P52: — | Q52: 9883 | R52: 18746 | S52: 18603 | T52: — | U52: — | V52: — | W52: — | X52: —
C53: Specialty Care And Oncology | D53: — | E53: — | F53: — | G53: — | H53: — | I53: — | J53: — | K53: — | L53: — | M53: — | N53: — | O53: — | P53: — | Q53: 9010 | R53: 17097 | S53: 16885 | T53: — | U53: — | V53: — | W53: — | X53: —
C54: + Other Intangible Assets | D54: — | E54: 0 | F54: 0 | G54: 0 | H54: 0 | I54: 921 | J54: 35591 | K54: 39525 | L54: 26244 | M54: 24350 | N54: 20498 | O54: 17721 | P54: 68015 | Q54: 57555 | R54: 51184 | S54: 45146 | T54: 39385 | U54: 35167 | V54: 40356 | W54: 52648 | X54: 48740
C55: + Deferred Tax Assets | D55: — | E55: — | F55: — | G55: — | H55: — | I55: — | J55: — | K55: — | L55: — | M55: — | N55: — | O55: — | P55: — | Q55: 1189 | R55: — | S55: 1565 | T55: 1554 | U55: 1944 | V55: 1794 | W55: 1812 | X55: 1855
C56: + Derivative & Hedging Assets | D56: — | E56: — | F56: — | G56: — | H56: — | I56: — | J56: — | K56: — | L56: — | M56: — | N56: — | O56: — | P56: 1050 | Q56: 710 | R56: 1017 | S56: 1050 | T56: 1225 | U56: 881 | V56: 944 | W56: 689 | X56: —
C57: + Prepaid Pension Costs | D57: — | E57: — | F57: — | G57: — | H57: — | I57: — | J57: — | K57: — | L57: — | M57: — | N57: — | O57: — | P57: 146 | Q57: 118 | R57: 327 | S57: 124 | T57: 318 | U57: 509 | V57: 572 | W57: 300 | X57: 454
C58: + Misc LT Assets | D58: 1437 | E58: 1387 | F58: 2742 | G58: 2578 | H58: 2745 | I58: 3581 | J58: 4749 | K58: -1549 | L58: 4176 | M58: 2138 | N58: 5949 | O58: 4122 | P58: 3790 | Q58: 2109 | R58: 4353 | S58: 2059 | T58: 2053 | U58: 2123 | V58: 1904 | W58: 2334 | X58: 2775
C59: Total Noncurrent Assets | D59: 7549 | E59: 8371 | F59: 15061 | G59: 16323 | H59: 19941 | I59: 21575 | J59: 87034 | K59: 83990 | L59: 70135 | M59: 67888 | N59: 68419 | O59: 68072 | P59: 151279 | Q59: 134001 | R59: 127185 | S59: 120967 | T59: 115857 | U59: 111970 | V59: 123577 | W59: 132666 | X59: 130657
C60: Total Assets | D60: 14991 | E60: 18302 | F60: 31372 | G60: 33510 | H60: 39153 | I60: 46356 | J60: 116775 | K60: 123684 | L60: 116970 | M60: 115546 | N60: 115268 | O60: 111148 | P60: 212949 | Q60: 195014 | R60: 188002 | S60: 185798 | T60: 172101 | U60: 167566 | V60: 167381 | W60: 171615 | X60: 171797
C61: Product/Brand Segments | D61: — | E61: — | F61: — | G61: — | H61: — | I61: — | J61: — | K61: 125848 | L61: 116970 | M61: 114837 | N61: 115268 | O61: 111148 | P61: 212949 | Q61: 195014 | R61: — | S61: — | T61: — | U61: — | V61: — | W61: — | X61: —
C62: Consumer, Capsugel and Pfizer CentreSource | D62: — | E62: — | F62: — | G62: — | H62: — | I62: — | J62: — | K62: 36040 | L62: 34157 | M62: 40327 | N62: 45680 | O62: — | P62: — | Q62: — | R62: — | S62: — | T62: — | U62: — | V62: — | W62: — | X62: —
C63: Discontinued operations/Held for sale | D63: — | E63: — | F63: — | G63: — | H63: — | I63: — | J63: — | K63: 6631 | L63: 6659 | M63: 62 | N63: 114 | O63: 148 | P63: 496 | Q63: 561 | R63: — | S63: — | T63: — | U63: — | V63: — | W63: — | X63: —
C64: Animal Health | D64: — | E64: — | F64: — | G64: — | H64: — | I64: — | J64: — | K64: 1992 | L64: 2098 | M64: 1951 | N64: 2043 | O64: 2075 | P64: — | Q64: — | R64: — | S64: — | T64: — | U64: — | V64: — | W64: — | X64: —
C65: Corporate/Other | D65: — | E65: — | F65: — | G65: — | H65: — | I65: — | J65: — | K65: — | L65: — | M65: — | N65: — | O65: 48334 | P65: — | Q65: — | R65: — | S65: — | T65: — | U65: — | V65: — | W65: — | X65: —
C66: Pfizer CentreSource | D66: — | E66: — | F66: — | G66: — | H66: — | I66: — | J66: — | K66: — | L66: — | M66: — | N66: — | O66: — | P66: 74980 | Q66: 52638 | R66: — | S66: — | T66: — | U66: — | V66: — | W66: — | X66: —
C67: Diversified | D67: — | E67: — | F67: — | G67: — | H67: — | I67: — | J67: — | K67: — | L67: — | M67: — | N67: — | O67: — | P67: 16684 | Q67: 18255 | R67: — | S67: — | T67: — | U67: — | V67: — | W67: — | X67: —
C68: Biopharmaceutical | D68: — | E68: — | F68: — | G68: — | H68: — | I68: — | J68: — | K68: 81185 | L68: 74056 | M68: 72497 | N68: 67431 | O68: 60591 | P68: 120789 | Q68: 123560 | R68: — | S68: — | T68: — | U68: — | V68: — | W68: — | X68: —
C70: Liabilities & Shareholders' Equity
C71: + Payables & Accruals | D71: 660 | E71: 971 | F71: 1889 | G71: 1719 | H71: 1411 | I71: 1620 | J71: 2601 | K71: 2672 | L71: 2073 | M71: 2019 | N71: 2270 | O71: 1751 | P71: 18173 | Q71: 8626 | R71: 8603 | S71: 7508 | T71: 7367 | U71: 7293 | V71: 8249 | W71: 9404 | X71: 9358
C72: + Accounts Payable | D72: 660 | E72: 971 | F72: 1889 | G72: 1719 | H72: 1411 | I72: 1620 | J72: 2601 | K72: 2672 | L72: 2073 | M72: 2019 | N72: 2270 | O72: 1751 | P72: 4370 | Q72: 3994 | R72: 3678 | S72: 2921 | T72: 3234 | U72: 3210 | V72: 3620 | W72: 4536 | X72: 4656
C73: + Accrued Taxes | D73: — | E73: — | F73: — | G73: — | H73: — | I73: — | J73: — | K73: — | L73: — | M73: — | N73: — | O73: — | P73: 10107 | Q73: 951 | R73: 1009 | S73: 979 | T73: 678 | U73: 531 | V73: 418 | W73: 437 | X73: 477
C74: + Interest & Dividends Payable | D74: — | E74: — | F74: — | G74: — | H74: — | I74: — | J74: — | K74: — | L74: — | M74: — | N74: — | O74: — | P74: 1454 | Q74: 1601 | R74: 1796 | S74: 1733 | T74: 1663 | U74: 1711 | V74: 1852 | W74: 1944 | X74: 2029
C75: + Other Payables & Accruals | D75: — | E75: — | F75: — | G75: — | H75: — | I75: — | J75: — | K75: — | L75: — | M75: — | N75: — | O75: — | P75: 2242 | Q75: 2080 | R75: 2120 | S75: 1875 | T75: 1792 | U75: 1841 | V75: 2359 | W75: 2487 | X75: 2196
C76: + ST Debt | D76: 2251 | E76: 2729 | F76: 5299 | G76: 4289 | H76: 6263 | I76: 8669 | J76: 8818 | K76: 11266 | L76: 11589 | M76: 2434 | N76: 5825 | O76: 9320 | P76: 5469 | Q76: 5603 | R76: 4016 | S76: 6424 | T76: 6027 | U76: 5141 | V76: 10159 | W76: 10688 | X76: 9953
C77: + ST Borrowings | D77: — | E77: — | F77: — | G77: — | H77: — | I77: — | J77: — | K77: — | L77: — | M77: — | N77: — | O77: — | P77: 5442 | Q77: 2101 | R77: 4010 | S77: 3975 | T77: 3967 | U77: 2130 | V77: 6439 | W77: 6463 | X77: 0
C78: + ST Capital Leases | D78: — | E78: — | F78: — | G78: — | H78: — | I78: — | J78: — | K78: — | L78: — | M78: — | N78: — | O78: — | P78: 0 | Q78: 0 | R78: 0 | S78: 0 | T78: 0 | U78: 0 | V78: 0 | W78: 0 | X78: 0
C79: + Current Portion of LT Debt | D79: — | E79: — | F79: — | G79: — | H79: — | I79: — | J79: — | K79: — | L79: — | M79: — | N79: — | O79: — | P79: 27 | Q79: 3502 | R79: 6 | S79: 2449 | T79: 2060 | U79: 3011 | V79: 3720 | W79: 4225 | X79: 9953
C80: + Other ST Liabilities | D80: 2083 | E80: 3492 | F80: 4708 | G80: 5973 | H80: 6055 | I80: 8266 | J80: 12238 | K80: 12520 | L80: 14740 | M80: 17646 | N80: 13740 | O80: 15938 | P80: 13583 | Q80: 14407 | R80: 16290 | S80: 15254 | T80: 9972 | U80: 9153 | V80: 10990 | W80: 11023 | X80: 11116
C81: + Deferred Revenue | D81: — | E81: — | F81: — | G81: — | H81: — | I81: — | J81: — | K81: — | L81: — | M81: — | N81: — | O81: — | P81: 0 | Q81: 0 | R81: 0 | S81: 0 | T81: 0 | U81: 0 | V81: 0 | W81: 0 | X81: 0
C82: + Derivatives & Hedging | D82: — | E82: — | F82: — | G82: — | H82: — | I82: — | J82: — | K82: — | L82: — | M82: — | N82: — | O82: — | P82: 369 | Q82: 339 | R82: 459 | S82: 330 | T82: 303 | U82: 92 | V82: 645 | W82: 1247 | X82: —
C83: + Discontinued Operations | D83: — | E83: — | F83: — | G83: — | H83: — | I83: — | J83: — | K83: — | L83: — | M83: — | N83: — | O83: — | P83: — | Q83: 151 | R83: 1224 | S83: 1442 | T83: 21 | U83: — | V83: — | W83: — | X83: —
C84: + Misc ST Liabilities | D84: 2083 | E84: 3492 | F84: 4708 | G84: 5973 | H84: 6055 | I84: 8266 | J84: 12238 | K84: 12520 | L84: 14740 | M84: 17646 | N84: 13740 | O84: 15938 | P84: 13214 | Q84: 13917 | R84: 14607 | S84: 13482 | T84: 9648 | U84: 9061 | V84: 10345 | W84: 9776 | X84: 11116
C85: Total Current Liabilities | D85: 4994 | E85: 7192 | F85: 11896 | G85: 11981 | H85: 13729 | I85: 18555 | J85: 23657 | K85: 26458 | L85: 28402 | M85: 22099 | N85: 21835 | O85: 27009 | P85: 37225 | Q85: 28636 | R85: 28909 | S85: 29186 | T85: 23366 | U85: 21587 | V85: 29398 | W85: 31115 | X85: 30427
C86: + LT Debt | D86: 725 | E86: 527 | F86: 1774 | G86: 1123 | H86: 2609 | I86: 3140 | J86: 5755 | K86: 7279 | L86: 6347 | M86: 5546 | N86: 7314 | O86: 7963 | P86: 43193 | Q86: 38410 | R86: 34926 | S86: 31036 | T86: 30462 | U86: 31541 | V86: 28740 | W86: 31398 | X86: 33538
C87: + LT Borrowings | D87: — | E87: — | F87: — | G87: — | H87: — | I87: — | J87: — | K87: — | L87: — | M87: — | N87: — | O87: — | P87: 43193 | Q87: 38410 | R87: 34926 | S87: 31036 | T87: 30462 | U87: 31541 | V87: 28740 | W87: 31398 | X87: 33538
C88: + LT Capital Leases | D88: — | E88: — | F88: — | G88: — | H88: — | I88: — | J88: — | K88: — | L88: — | M88: — | N88: — | O88: — | P88: 0 | Q88: 0 | R88: 0 | S88: 0 | T88: 0 | U88: 0 | V88: 0 | W88: 0 | X88: 0
C89: + Other LT Liabilities | D89: 1339 | E89: 1773 | F89: 3752 | G89: 4330 | H89: 4522 | I89: 4711 | J89: 21986 | K89: 21669 | L89: 16457 | M89: 16469 | N89: 20995 | O89: 18436 | P89: 42085 | Q89: 39703 | R89: 41546 | S89: 43898 | T89: 41653 | U89: 42817 | V89: 44245 | W89: 49262 | X89: 36176
C90: + Accrued Liabilities | D90: — | E90: — | F90: — | G90: — | H90: — | I90: — | J90: — | K90: — | L90: — | M90: — | N90: — | O90: — | P90: 0 | Q90: 0 | R90: 0 | S90: 0 | T90: 0 | U90: 0 | V90: 0 | W90: 0 | X90: 0
C91: + Pension Liabilities | D91: — | E91: — | F91: — | G91: — | H91: — | I91: — | J91: — | K91: — | L91: — | M91: — | N91: — | O91: — | P91: 9635 | Q91: 9229 | R91: 9699 | S91: 11273 | T91: 7303 | U91: 10264 | V91: 8119 | W91: 8172 | X91: 7430
C92: + Deferred Revenue | D92: — | E92: — | F92: — | G92: — | H92: — | I92: — | J92: — | K92: — | L92: — | M92: — | N92: — | O92: — | P92: 0 | Q92: 0 | R92: 0 | S92: 0 | T92: 0 | U92: 0 | V92: 0 | W92: 0 | X92: 0
C93: + Deferred Tax Liabilities | D93: — | E93: — | F93: — | G93: — | H93: — | I93: — | J93: — | K93: — | L93: — | M93: — | N93: — | O93: — | P93: 17839 | Q93: 18628 | R93: 18861 | S93: 21193 | T93: 25590 | U93: 23317 | V93: 26877 | W93: 30753 | X93: 3900
C94: + Derivatives & Hedging | D94: — | E94: — | F94: — | G94: — | H94: — | I94: — | J94: — | K94: — | L94: — | M94: — | N94: — | O94: — | P94: 421 | Q94: 545 | R94: 1314 | S94: 374 | T94: 327 | U94: 597 | V94: 1062 | W94: 444 | X94: —
C95: + Misc LT Liabilities | D95: 1339 | E95: 1773 | F95: 3752 | G95: 4330 | H95: 4522 | I95: 4711 | J95: 21986 | K95: 21669 | L95: 16457 | M95: 16469 | N95: 20995 | O95: 18436 | P95: 14190 | Q95: 11301 | R95: 11672 | S95: 11058 | T95: 8433 | U95: 8639 | V95: 8187 | W95: 9893 | X95: 24846
C96: Total Noncurrent Liabilities | D96: 2064 | E96: 2300 | F96: 5526 | G96: 5453 | H96: 7131 | I96: 7851 | J96: 27741 | K96: 28948 | L96: 22804 | M96: 22015 | N96: 28309 | O96: 26399 | P96: 85278 | Q96: 78113 | R96: 76472 | S96: 74934 | T96: 72115 | U96: 74358 | V96: 72985 | W96: 80660 | X96: 69714
C97: Total Liabilities | D97: 7058 | E97: 9492 | F97: 17422 | G97: 17434 | H97: 20860 | I97: 26406 | J97: 51398 | K97: 55406 | L97: 51206 | M97: 44114 | N97: 50144 | O97: 53408 | P97: 122503 | Q97: 106749 | R97: 105381 | S97: 104120 | T97: 95481 | U97: 95945 | V97: 102383 | W97: 111775 | X97: 100141
C98: + Preferred Equity and Hybrid Capital | D98: 0 | E98: — | F98: — | G98: 0 | H98: 0 | I98: 0 | J98: 219 | K98: 193 | L98: 169 | M98: 141 | N98: 93 | O98: 73 | P98: 61 | Q98: 52 | R98: 45 | S98: 39 | T98: 33 | U98: 29 | V98: 26 | W98: 24 | X98: 21
C99: + Share Capital & APIC | D99: 3308 | E99: 5716 | F99: 6275 | G99: 9232 | H99: 9640 | I99: 9709 | J99: 66831 | K99: 67536 | L99: 68198 | M99: 69545 | N99: 70355 | O99: 70726 | P99: 70940 | Q99: 71204 | R99: 71868 | S99: 73056 | T99: 77736 | U99: 79432 | V99: 81475 | W99: 83146 | X99: 84742
C100: + Common Stock | D100: — | E100: — | F100: — | G100: — | H100: — | I100: — | J100: — | K100: — | L100: — | M100: — | N100: — | O100: — | P100: 443 | Q100: 444 | R100: 445 | S100: 448 | T100: 453 | U100: 455 | V100: 459 | W100: 461 | X100: 464
C101: + Additional Paid in Capital | D101: — | E101: — | F101: — | G101: — | H101: — | I101: — | J101: — | K101: — | L101: — | M101: — | N101: — | O101: — | P101: 70497 | Q101: 70760 | R101: 71423 | S101: 72608 | T101: 77283 | U101: 78977 | V101: 81016 | W101: 82685 | X101: 84278
C102: - Treasury Stock | D102: 1993 | E102: 3911 | F102: 6851 | G102: 7858 | H102: 11378 | I102: 16341 | J102: 29352 | K102: 35992 | L102: 39767 | M102: 46740 | N102: 56847 | O102: 57391 | P102: 21632 | Q102: 22712 | R102: 31801 | S102: 40122 | T102: 67923 | U102: 73021 | V102: 79252 | W102: 84364 | X102: 89425
C103: + Retained Earnings | D103: — | E103: 11439 | F103: 18459 | G103: 19599 | H103: 24430 | I103: 30243 | J103: 29382 | K103: 35492 | L103: 37608 | M103: 49669 | N103: 49660 | O103: 49142 | P103: 40426 | Q103: 42716 | R103: 46210 | S103: 54240 | T103: 69732 | U103: 72176 | V103: 71993 | W103: 71774 | X103: 85291
C104: + Other Equity | D104: 6618 | E104: -4434 | F104: -3933 | G104: -4897 | H104: -4399 | I104: -3661 | J104: -1703 | K104: 1049 | L104: -444 | M104: -1257 | N104: 1749 | O104: -4994 | P104: 219 | Q104: -3447 | R104: -4132 | S104: -5953 | T104: -3271 | U104: -7316 | V104: -9522 | W104: -11036 | X104: -9321
C105: Equity Before Minority Interest | D105: 7933 | E105: 8810 | F105: 13950 | G105: 16076 | H105: 18293 | I105: 19950 | J105: 65377 | K105: 68278 | L105: 65764 | M105: 71358 | N105: 65010 | O105: 57556 | P105: 90014 | Q105: 87813 | R105: 82190 | S105: 81260 | T105: 76307 | U105: 71300 | V105: 64720 | W105: 59544 | X105: 71308
...

Sheet 3.3 CF Statements
C5: Pfizer Inc (PFE US) - Standardized
C7: In Millions of USD except Per Share | D7: FY 1998 | E7: FY 1999 | F7: FY 2000 | G7: FY 2001 | H7: FY 2002 | I7: FY 2003 | J7: FY 2004 | K7: FY 2005 | L7: FY 2006 | M7: FY 2007 | N7: FY 2008 | O7: FY 2009 | P7: FY 2010 | Q7: FY 2011 | R7: FY 2012 | S7: FY 2013 | T7: FY 2014 | U7: FY 2015 | V7: FY 2016 | W7: FY 2017 | X7: Last 12M
C8: 12 Months Ending | D8: 12/31/1998 | E8: 12/31/1999 | F8: 12/31/2000 | G8: 12/31/2001 | H8: 12/31/2002 | I8: 12/31/2003 | J8: 12/31/2004 | K8: 12/31/2005 | L8: 12/31/2006 | M8: 12/31/2007 | N8: 12/31/2008 | O8: 12/31/2009 | P8: 12/31/2010 | Q8: 12/31/2011 | R8: 12/31/2012 | S8: 12/31/2013 | T8: 12/31/2014 | U8: 12/31/2015 | V8: 12/31/2016 | W8: 12/31/2017 | X8: 12/31/2017
C9: Cash from Operating Activities
C10: + Net Income | D10: 3351 | E10: 4952 | F10: 3726 | G10: 7788 | H10: 9126 | I10: 3910 | J10: 11361 | K10: 8085 | L10: 19337 | M10: 8144 | N10: 8104 | O10: 8635 | P10: 8257 | Q10: 10009 | R10: 14570 | S10: 22003 | T10: 9135 | U10: 6960 | V10: 7215 | W10: 21308 | X10: 21308
C11: + Depreciation & Amortization | D11: 489 | E11: 905 | F11: 968 | G11: 1068 | H11: 1036 | I11: 4025 | J11: 5093 | K11: 5576 | L11: 5293 | M11: 5200 | N11: 5090 | O11: 4757 | P11: 8487 | Q11: 8907 | R11: 7655 | S11: 6410 | T11: 5537 | U11: 5157 | V11: 5757 | W11: 6269 | X11: 6269
C12: Product/Brand Segments | D12: — | E12: — | F12: — | G12: — | H12: — | I12: — | J12: 5093 | K12: 5576 | L12: 5293 | M12: 5200 | N12: 5090 | O12: 4757 | P12: 8487 | Q12: 8907 | R12: 7394 | S12: 5874 | T12: 5537 | U12: 5157 | V12: 5757 | W12: 6268
C13: Reconciling Items | D13: — | E13: — | F13: — | G13: — | H13: — | I13: — | J13: — | K13: — | L13: — | M13: — | N13: 2806 | O13: — | P13: 6997 | Q13: 7434 | R13: 6149 | S13: 4822 | T13: 4450 | U13: 4082 | V13: 4488 | W13: 5065
C14: Purchase Accounting Adjustments | D14: — | E14: — | F14: — | G14: — | H14: — | I14: — | J14: — | K14: — | L14: — | M14: — | N14: — | O14: — | P14: — | Q14: — | R14: — | S14: 4487 | T14: 3782 | U14: 3573 | V14: 3890 | W14: 4565
C15: Corporate | D15: — | E15: — | F15: — | G15: — | H15: — | I15: — | J15: — | K15: — | L15: — | M15: — | N15: — | O15: — | P15: — | Q15: — | R15: — | S15: — | T15: 384 | U15: 354 | V15: 356 | W15: 337
C16: Other Unallocated | D16: — | E16: — | F16: — | G16: — | H16: — | I16: — | J16: — | K16: — | L16: — | M16: — | N16: — | O16: — | P16: — | Q16: — | R16: — | S16: 44 | T16: 24 | U16: 32 | V16: 35 | W16: 72
C17: Certain significant items | D17: — | E17: — | F17: — | G17: — | H17: — | I17: — | J17: — | K17: — | L17: — | M17: — | N17: — | O17: — | P17: — | Q17: — | R17: — | S17: 167 | T17: 207 | U17: 48 | V17: 200 | W17: 52
C18: Acquisition-related costs | D18: — | E18: — | F18: — | G18: — | H18: — | I18: — | J18: — | K18: — | L18: — | M18: — | N18: — | O18: — | P18: — | Q18: — | R18: — | S18: 124 | T18: 53 | U18: 75 | V18: 7 | W18: 39
C19: Pfizer's Essential Health | D19: — | E19: — | F19: — | G19: — | H19: — | I19: — | J19: — | K19: — | L19: — | M19: — | N19: — | O19: — | P19: — | Q19: — | R19: — | S19: — | T19: 490 | U19: 446 | V19: 600 | W19: 579
C20: Pfizer's Innovative Health | D20: — | E20: — | F20: — | G20: — | H20: — | I20: — | J20: 1473 | K20: 1880 | L20: 1765 | M20: 1886 | N20: 2223 | O20: 1672 | P20: — | Q20: — | R20: — | S20: — | T20: 522 | U20: 552 | V20: 583 | W20: 534
C21: Other Business Activites | D21: — | E21: — | F21: — | G21: — | H21: — | I21: — | J21: — | K21: — | L21: — | M21: — | N21: — | O21: — | P21: — | Q21: — | R21: — | S21: 105 | T21: 75 | U21: 77 | V21: 86 | W21: 90
C22: Global Vaccines, Oncology & Consumer Healthcare | D22: — | E22: — | F22: — | G22: — | H22: — | I22: — | J22: — | K22: — | L22: — | M22: — | N22: — | O22: — | P22: — | Q22: — | R22: — | S22: 231 | T22: — | U22: — | V22: — | W22: —
C23: Global Innovative Pharmaceuticals | D23: — | E23: — | F23: — | G23: — | H23: — | I23: — | J23: — | K23: — | L23: — | M23: — | N23: — | O23: — | P23: — | Q23: — | R23: — | S23: 238 | T23: — | U23: — | V23: — | W23: —
C24: Global Established Pharmaceuticals | D24: — | E24: — | F24: — | G24: — | H24: — | I24: — | J24: — | K24: — | L24: — | M24: — | N24: — | O24: — | P24: — | Q24: — | R24: — | S24: 478 | T24: — | U24: — | V24: — | W24: —
C25: Consumer, Capsugel and Pfizer CentreSource | D25: — | E25: — | F25: — | G25: — | H25: — | I25: — | J25: 3482 | K25: 3559 | L25: 3408 | M25: 3262 | N25: — | O25: — | P25: — | Q25: — | R25: — | S25: — | T25: — | U25: — | V25: — | W25: —
C26: Discontinued operations/Held for sale | D26: — | E26: — | F26: — | G26: — | H26: — | I26: — | J26: 81 | K26: 78 | L26: 71 | M26: — | N26: — | O26: — | P26: — | Q26: — | R26: — | S26: — | T26: — | U26: — | V26: — | W26: —
C27: Nutrition | D27: — | E27: — | F27: — | G27: — | H27: — | I27: — | J27: — | K27: — | L27: — | M27: — | N27: — | O27: — | P27: 242 | Q27: — | R27: — | S27: — | T27: — | U27: — | V27: — | W27: —
C28: Animal Health And Consumer Health | D28: — | E28: — | F28: — | G28: — | H28: — | I28: — | J28: 57 | K28: 59 | L28: 49 | M28: 52 | N28: 61 | O28: — | P28: 197 | Q28: 232 | R28: 190 | S28: — | T28: — | U28: — | V28: — | W28: —
C29: Primary Care | D29: — | E29: — | F29: — | G29: — | H29: — | I29: — | J29: — | K29: — | L29: — | M29: — | N29: — | O29: — | P29: 201 | Q29: 247 | R29: 244 | S29: — | T29: — | U29: — | V29: — | W29: —
C30: Pfizer CentreSource | D30: — | E30: — | F30: — | G30: — | H30: — | I30: — | J30: — | K30: — | L30: — | M30: — | N30: — | O30: 2972 | P30: — | Q30: 153 | R30: — | S30: — | T30: — | U30: — | V30: — | W30: —
C31: Diversified | D31: — | E31: — | F31: — | G31: — | H31: — | I31: — | J31: — | K31: — | L31: — | M31: — | N31: — | O31: 113 | P31: — | Q31: — | R31: — | S31: — | T31: — | U31: — | V31: — | W31: —
C32: Established Products&Emerging Market | D32: — | E32: — | F32: — | G32: — | H32: — | I32: — | J32: — | K32: — | L32: — | M32: — | N32: — | O32: — | P32: 418 | Q32: 422 | R32: 408 | S32: — | T32: — | U32: — | V32: — | W32: —
C33: Specialty Care And Oncology | D33: — | E33: — | F33: — | G33: — | H33: — | I33: — | J33: — | K33: — | L33: — | M33: — | N33: — | O33: — | P33: 432 | Q33: 419 | R33: 403 | S33: — | T33: — | U33: — | V33: — | W33: —
C34: + Non-Cash Items | D34: 345 | E34: 523 | F34: -294 | G34: -39 | H34: 70 | I34: 4341 | J34: 1436 | K34: 1988 | L34: -9755 | M34: 749 | N34: 111 | O34: -9113 | P34: 4240 | Q34: 2379 | R34: 839 | S34: -897 | T34: 1351 | U34: 2724 | V34: 2561 | W34: -12501 | X34: -12501
C35: + Stock-Based Compensation | D35: — | E35: — | F35: — | G35: — | H35: — | I35: — | J35: — | K35: 157 | L35: 655 | M35: 437 | N35: 384 | O35: 349 | P35: 405 | Q35: 419 | R35: 481 | S35: 523 | T35: 586 | U35: 669 | V35: 691 | W35: 840 | X35: 840
C36: + Deferred Income Taxes | D36: 22 | E36: 213 | F36: -265 | G36: 1092 | H36: -285 | I36: -104 | J36: -1579 | K36: -1457 | L36: -1945 | M36: -2788 | N36: -1331 | O36: -9582 | P36: 1953 | Q36: 454 | R36: 2198 | S36: 1703 | T36: 317 | U36: -18 | V36: -700 | W36: -13070 | X36: -13070
C37: + Other Non-Cash Adj | D37: 323 | E37: 310 | F37: -29 | G37: -1131 | H37: 355 | I37: 4445 | J37: 3015 | K37: 3288 | L37: -8465 | M37: 3100 | N37: 1058 | O37: 120 | P37: 1882 | Q37: 1506 | R37: -1840 | S37: -3123 | T37: 448 | U37: 2073 | V37: 2570 | W37: -271 | X37: -271
C38: + Chg in Non-Cash Work Cap | D38: 498 | E38: -907 | F38: 1803 | G38: 446 | H38: -49 | I38: -549 | J38: -1550 | K38: -916 | L38: 2719 | M38: -740 | N38: 4933 | O38: 12308 | P38: -9530 | Q38: 633 | R38: 805 | S38: 614 | T38: 1112 | U38: -159 | V38: 368 | W38: 1394 | X38: 1394
C39: + (Inc) Dec in Accts Receiv | D39: -765 | E39: -1274 | F39: -498 | G39: 81 | H39: -963 | I39: 207 | J39: -465 | K39: -803 | L39: -172 | M39: -320 | N39: 195 | O39: -472 | P39: -608 | Q39: -66 | R39: 367 | S39: 940 | T39: 148 | U39: 21 | V39: -134 | W39: 259
C40: + (Inc) Dec in Inventories | D40: -439 | E40: -278 | F40: -436 | G40: -110 | H40: -129 | I40: -200 | J40: -542 | K40: 72 | L40: 118 | M40: 720 | N40: 294 | O40: 1631 | P40: 2917 | Q40: 1084 | R40: -631 | S40: -538 | T40: 175 | U40: -199 | V40: 365 | W40: -357
C41: + Inc (Dec) in Accts Payable | D41: — | E41: — | F41: — | G41: — | H41: — | I41: — | J41: — | K41: — | L41: — | M41: — | N41: — | O41: — | P41: — | Q41: -367 | R41: 579 | S41: 382 | T41: 297 | U41: 254 | V41: 871 | W41: 46
C42: + Inc (Dec) in Other | D42: 1702 | E42: 645 | F42: 2737 | G42: 475 | H42: 1043 | I42: -556 | J42: -543 | K42: -185 | L42: 2773 | M42: -1140 | N42: 4444 | O42: 11149 | P42: -11839 | Q42: -18 | R42: 490 | S42: -170 | T42: 492 | U42: -235 | V42: -734 | W42: 1446 | X42: 1394
C43: + Net Cash From Disc Ops | D43: — | E43: — | F43: — | G43: — | H43: — | I43: — | J43: — | K43: — | L43: — | M43: — | N43: — | O43: — | P43: — | Q43: -1688 | R43: -7123 | S43: -10446 | T43: -51 | U43: 6 | V43: 0 | W43: —
C44: Cash from Operating Activities | D44: 4683 | E44: 5473 | F44: 6203 | G44: 9263 | H44: 10183 | I44: 11727 | J44: 16340 | K44: 14733 | L44: 17594 | M44: 13353 | N44: 18238 | O44: 16587 | P44: 11454 | Q44: 20240 | R44: 16746 | S44: 17684 | T44: 17084 | U44: 14688 | V44: 15901 | W44: 16470 | X44: 16470
C46: Cash from Investing Activities
C47: + Change in Fixed & Intang | D47: -1119 | E47: -2410 | F47: -2100 | G47: -2135 | H47: -1758 | I47: -2629 | J47: -2601 | K47: -2106 | L47: -2050 | M47: -1880 | N47: -1701 | O47: -1205 | P47: -1513 | Q47: -1660 | R47: -1327 | S47: -1206 | T47: -1583 | U47: -1496 | V47: -1999 | W47: -2217 | X47: -2217
C48: + Disp in Fixed & Intang | D48: 79 | E48: 83 | F48: 91 | G48: 68 | H48: 0 | I48: 0 | J48: 0 | K48: — | L48: — | M48: — | N48: 0 | O48: 0 | P48: 0 | Q48: 0 | R48: 0 | S48: 0 | T48: 0 | U48: 0 | V48: 0 | W48: 0 | X48: 0
C49: + Disp of Fixed Prod Assets | D49: — | E49: — | F49: — | G49: — | H49: — | I49: — | J49: — | K49: — | L49: — | M49: — | N49: — | O49: 0 | P49: 0 | Q49: 0 | R49: 0 | S49: 0 | T49: 0 | U49: 0 | V49: 0 | W49: 0 | X49: 0
C50: + Disp of Intangible Assets | D50: — | E50: — | F50: — | G50: — | H50: — | I50: — | J50: — | K50: — | L50: — | M50: — | N50: — | O50: 0 | P50: 0 | Q50: 0 | R50: 0 | S50: 0 | T50: 0 | U50: 0 | V50: 0 | W50: 0 | X50: 0
C51: + Acq of Fixed & Intang | D51: -1198 | E51: -2493 | F51: -2191 | G51: -2203 | H51: -1758 | I51: -2629 | J51: -2601 | K51: -2106 | L51: -2050 | M51: -1880 | N51: -1701 | O51: -1205 | P51: -1513 | Q51: -1660 | R51: -1327 | S51: -1206 | T51: -1583 | U51: -1496 | V51: -1999 | W51: -2217 | X51: -2217
C52: + Acq of Fixed Prod Assets | D52: — | E52: — | F52: — | G52: — | H52: — | I52: — | J52: — | K52: — | L52: — | M52: — | N52: — | O52: -1205 | P52: -1513 | Q52: -1660 | R52: -1327 | S52: -1206 | T52: -1199 | U52: -1397 | V52: -1823 | W52: -1956 | X52: -1956
C53: + Acq of Intangible Assets | D53: — | E53: — | F53: — | G53: — | H53: — | I53: — | J53: — | K53: — | L53: — | M53: — | N53: — | O53: 0 | P53: 0 | Q53: 0 | R53: 0 | S53: 0 | T53: -384 | U53: -99 | V53: -176 | W53: -261 | X53: -261
C54: + Net Change in LT Investment | D54: -752 | E54: 2 | F54: -272 | G54: -3633 | H54: 600 | I54: -1527 | J54: 241 | K54: 622 | L54: -1692 | M54: -1463 | N54: -8348 | O54: -384 | P54: 461 | Q54: -2473 | R54: -6155 | S54: -3465 | T54: -4573 | U54: -2613 | V54: 3243 | W54: 57 | X54: 57
C55: + Dec in LT Investment | D55: 0 | E55: 42 | F55: 346 | G55: 80 | H55: 3477 | I55: 356 | J55: 1570 | K55: 1309 | L55: 233 | M55: 172 | N55: 1009 | O55: 6504 | P55: 4381 | Q55: 2147 | R55: 4990 | S55: 7555 | T55: 6145 | U55: 6929 | V55: 11254 | W55: 3594 | X55: 3594
C56: + Inc in LT Investment | D56: -752 | E56: -40 | F56: -618 | G56: -3713 | H56: -2877 | I56: -1883 | J56: -1329 | K56: -687 | L56: -1925 | M56: -1635 | N56: -9357 | O56: -6888 | P56: -3920 | Q56: -4620 | R56: -11145 | S56: -11020 | T56: -10718 | U56: -9542 | V56: -8011 | W56: -3537 | X56: -3537
C57: + Net Cash From Acq & Div | D57: — | E57: — | F57: — | G57: — | H57: — | I57: — | J57: — | K57: — | L57: — | M57: — | N57: — | O57: -43123 | P57: -273 | Q57: -906 | R57: 10708 | S57: -274 | T57: -195 | U57: -16466 | V57: -18368 | W57: -1000 | X57: -1000
C58: + Cash from Divestitures | D58: — | E58: — | F58: — | G58: — | H58: — | I58: — | J58: — | K58: — | L58: — | M58: — | N58: — | O58: 0 | P58: 0 | Q58: 2376 | R58: 11850 | S58: 0 | T58: 0 | U58: 0 | V58: 0 | W58: 0 | X58: 0
C59: + Cash for Acq of Subs | D59: — | E59: — | F59: — | G59: — | H59: — | I59: — | J59: — | K59: — | L59: — | M59: — | N59: — | O59: -43123 | P59: -273 | Q59: -3282 | R59: -1142 | S59: -274 | T59: -195 | U59: -16466 | V59: -18368 | W59: -1000 | X59: -1000
C60: + Cash for JVs | D60: — | E60: — | F60: — | G60: — | H60: — | I60: — | J60: — | K60: — | L60: — | M60: — | N60: — | O60: 0 | P60: 0 | Q60: 0 | R60: 0 | S60: 0 | T60: 0 | U60: 0 | V60: 0 | W60: 0 | X60: 0
C61: + Other Investing Activities | D61: 1536 | E61: -1498 | F61: -1381 | G61: -1457 | H61: -3180 | I61: 9006 | J61: -7062 | K61: -3588 | L61: 8843 | M61: 4138 | N61: -2786 | O61: 13440 | P61: 833 | Q61: 6882 | R61: 2928 | S61: -5599 | T61: 697 | U61: 17595 | V61: 9313 | W61: -1581 | X61: -1581
C62: Cash from Investing Activities | D62: -335 | E62: -3906 | F62: -3753 | G62: -7225 | H62: -4338 | I62: 4850 | J62: -9422 | K62: -5072 | L62: 5101 | M62: 795 | N62: -12835 | O62: -31272 | P62: -492 | Q62: 1843 | R62: 6154 | S62: -10544 | T62: -5654 | U62: -2980 | V62: -7811 | W62: -4741 | X62: -4741
C64: Cash from Financing Activities
C65: + Dividends Paid | D65: -976 | E65: -1820 | F65: -2197 | G65: -2715 | H65: -3168 | I65: -4353 | J65: -5082 | K65: -5555 | L65: -6919 | M65: -7975 | N65: -8541 | O65: -5548 | P65: -6088 | Q65: -6234 | R65: -6534 | S65: -6580 | T65: -6609 | U65: -6940 | V65: -7317 | W65: -7659 | X65: -7659
C66: + Cash From (Repayment) Debt | D66: 200 | E66: 2099 | F66: -1691 | G66: 3511 | H66: 2505 | I66: -591 | J66: 4100 | K66: -321 | L66: -9934 | M66: 4900 | N66: 2407 | O66: 20120 | P66: -4152 | Q66: -5542 | R66: -1725 | S66: 6036 | T66: 543 | U66: 1319 | V66: 2573 | W66: -1005 | X66: -1005
C67: + Cash From (Repay) ST Debt | D67: — | E67: — | F67: — | G67: — | H67: — | I67: — | J67: — | K67: — | L67: — | M67: — | N67: — | O67: -2936 | P67: -4146 | Q67: 1444 | R67: -212 | S67: 3564 | T67: -1838 | U67: 4309 | V67: -714 | W67: -125 | X67: -125
C68: + Cash From LT Debt | D68: — | E68: — | F68: — | G68: — | H68: — | I68: — | J68: — | K68: — | L68: — | M68: — | N68: — | O68: 24023 | P68: 0 | Q68: 0 | R68: 0 | S68: 6618 | T68: 4491 | U68: 0 | V68: 10976 | W68: 5274 | X68: 5274
C69: + Repayments of LT Debt | D69: — | E69: — | F69: — | G69: — | H69: — | I69: — | J69: — | K69: — | L69: — | M69: — | N69: — | O69: -967 | P69: -6 | Q69: -6986 | R69: -1513 | S69: -4146 | T69: -2110 | U69: -2990 | V69: -7689 | W69: -6154 | X69: -6154
C70: + Cash (Repurchase) of Equity | D70: -1501 | E70: -1906 | F70: 183 | G70: -3603 | H70: -4336 | I70: -11965 | J70: -5647 | K70: -3346 | L70: -6247 | M70: -9535 | N70: -426 | O70: 0 | P70: -1000 | Q70: -9000 | R70: -7660 | S70: -14540 | T70: -3998 | U70: -4897 | V70: -3981 | W70: -4138 | X70: -4138
C71: + Increase in Capital Stock | D71: 411 | E71: 636 | F71: 1188 | G71: 62 | H71: 660 | I71: 1072 | J71: 1012 | K71: 451 | L71: 732 | M71: 459 | N71: 74 | O71: 0 | P71: 0 | Q71: 0 | R71: 568 | S71: 1750 | T71: 1002 | U71: 1263 | V71: 1019 | W71: 862 | X71: 862
C72: + Decrease in Capital Stock | D72: -1912 | E72: -2542 | F72: -1005 | G72: -3665 | H72: -4996 | I72: -13037 | J72: -6659 | K72: -3797 | L72: -6979 | M72: -9994 | N72: -500 | O72: 0 | P72: -1000 | Q72: -9000 | R72: -8228 | S72: -16290 | T72: -5000 | U72: -6160 | V72: -5000 | W72: -5000 | X72: -5000
C73: + Other Financing Activities | D73: — | E73: — | F73: — | G73: — | H73: — | I73: — | J73: — | K73: — | L73: — | M73: — | N73: — | O73: -91 | P73: 66 | Q73: 169 | R73: -80 | S73: 109 | T73: -123 | U73: 109 | V73: -196 | W73: -233 | X73: -233
C74: Cash from Financing Activities | D74: -2272 | E74: -1616 | F74: -3701 | G74: -2101 | H74: -5003 | I74: -16935 | J74: -6630 | K74: -9222 | L74: -23115 | M74: -12569 | N74: -6687 | O74: 14481 | P74: -11174 | Q74: -20607 | R74: -15999 | S74: -14975 | T74: -10187 | U74: -10409 | V74: -8921 | W74: -13035 | X74: -13035
C76: Effect of Foreign Exchange Rates | D76: — | E76: — | F76: — | G76: — | H76: — | I76: — | J76: — | K76: — | L76: — | M76: — | N76: — | O76: 60 | P76: -31 | Q76: -29 | R76: -2 | S76: -63 | T76: -83 | U76: -1000 | V76: -215 | W76: 53 | X76: 53
C78: Net Changes in Cash | D78: 2076 | E78: -49 | F78: -1251 | G78: -63 | H78: 842 | I78: -358 | J78: 288 | K78: 439 | L78: -420 | M78: 1579 | N78: -1284 | O78: -144 | P78: -243 | Q78: 1447 | R78: 6899 | S78: -7898 | T78: 1160 | U78: 299 | V78: -1046 | W78: -1253 | X78: -1253
C80: Cash Paid for Taxes | D80: 1073 | E80: 379 | F80: 460 | G80: 303 | H80: 1480 | I80: 2905 | J80: 3388 | K80: 4713 | L80: 3443 | M80: 5617 | N80: 2252 | O80: 2300 | P80: 11775 | Q80: 2938 | R80: 2409 | S80: 2874 | T80: 2100 | U80: 2383 | V80: 2521 | W80: 2489 | X80: 2489
C81: Cash Paid for Interest | D81: 155 | E81: 1573 | F81: 1041 | G81: 1006 | H81: 256 | I81: 350 | J81: 496 | K81: 649 | L81: 715 | M81: 643 | N81: 782 | O81: 935 | P81: 2155 | Q81: 2085 | R81: 1873 | S81: 1729 | T81: 1550 | U81: 1302 | V81: 1451 | W81: 1518
C83: Reference Items
C84: EBITDA | D84: 3083 | E84: 7971 | F84: 9658 | G84: 11776 | H84: 13352 | I84: 20115 | J84: 22181 | K84: 19781 | L84: 19575 | M84: 19980 | N84: 22146 | O84: 15944 | P84: 22105 | Q84: 23710 | R84: 22919 | S84: 21594 | T84: 18786 | U84: 16981 | V84: 17763 | W84: 19889 | X84: 19890
C85: Trailing 12M EBITDA Margin | D85: 22.762847 | E85: 29.116745 | F85: 32.900698 | G85: 40.573319 | H85: 41.244247 | I85: 44.51403 | J85: 42.236652 | K85: 41.727666 | L85: 40.468463 | M85: 41.265645 | N85: 45.854729 | O85: 31.882261 | P85: 32.964493 | Q85: 36.332153 | R85: 41.932415 | S85: 41.861818 | T85: 37.871182 | U85: 34.760803 | V85: 33.626761 | W85: 37.850645 | X85: 37.852548
C86: Net Cash Paid for Acquisitions | D86: — | E86: — | F86: — | G86: — | H86: — | I86: — | J86: 3539 | K86: — | L86: — | M86: — | N86: 1184 | O86: 43123 | P86: 273 | Q86: 3282 | R86: 1142 | S86: 274 | T86: 195 | U86: 16466 | V86: 18368 | W86: 1000 | X86: 1000
C87: Free Cash Flow | D87: 3485 | E87: 2980 | F87: 4012 | G87: 7060 | H87: 8425 | I87: 9098 | J87: 13739 | K87: 12627 | L87: 15544 | M87: 11473 | N87: 16537 | O87: 15382 | P87: 9941 | Q87: 18580 | R87: 15419 | S87: 16478 | T87: 15885 | U87: 13291 | V87: 14078 | W87: 14514 | X87: 14514
C88: Free Cash Flow to Firm | D88: 3592.6083 | E88: 3240.1369 | F88: 4290.8832 | G88: 7261.1785 | H88: 8620.4847 | I88: 9233.8688 | J88: 14019.979 | K88: 12959.404 | L88: 15981.95 | M88: 11826.226 | N88: 17003.633 | O88: 16364.801 | P88: 11530.654 | Q88: 19726.944 | R88: 16640.31 | S88: 17504.581 | T88: 16898.333 | U88: 14223.853 | V88: 15104.513 | W88: —
C89: Free Cash Flow to Equity | D89: — | E89: — | F89: — | G89: 10639 | H89: 10930 | I89: 8726 | J89: 17809 | K89: 12276 | L89: 5577 | M89: 16321 | N89: 18921 | O89: 35485 | P89: 5777 | Q89: 13028 | R89: 13686 | S89: 22506 | T89: 16424 | U89: 14605 | V89: 16647 | W89: 13505 | X89: 13506
C90: Free Cash Flow per Basic Share | D90: 0.919768 | E90: 0.486451 | F90: 0.646055 | G90: 1.131573 | H90: 1.368583 | I90: 1.261334 | J90: 1.824326 | K90: 1.715392 | L90: 2.146368 | M90: 1.658667 | N90: 2.458302 | O90: 2.195233 | P90: 1.237058 | Q90: 2.376871 | R90: 2.071889 | S90: 2.418611 | T90: 2.503152 | U90: 2.15204 | V90: 2.312038 | W90: 2.431156 | X90: 2.4344241
C91: Price to Free Cash Flow | D91: 45.301291 | E91: 66.681921 | F91: 71.201396 | G91: 35.21645 | H91: 22.336964 | I91: 28.010034 | J91: 14.739689 | K91: 13.594561 | L91: 12.066894 | M91: 13.703775 | N91: 7.204159 | O91: 8.286135 | P91: 14.154548 | Q91: 9.104407 | R91: 12.104561 | S91: 12.664291 | T91: 12.444312 | U91: 14.99972 | V91: 14.048211 | W91: 14.898264 | X91: 14.446948
C92: Cash Flow to Net Income | D92: 1.397493 | E92: 1.10521 | F92: 1.664788 | G92: 1.189394 | H92: 1.115823 | I92: 2.999233 | J92: 1.438254 | K92: 1.822263 | L92: 0.909862 | M92: 1.639612 | N92: 2.250494 | O92: 1.920903 | P92: 1.387187 | Q92: 2.02218 | R92: 1.149348 | S92: 0.803709 | T92: 1.87017 | U92: 2.110345 | V92: 2.203881 | W92: 0.772949 | X92: 0.54929118
C93: Source: Bloomberg
C96: Pfizer Inc (PFE US) - Standardized
C98: In Millions of USD except Per Share | E98: Last 12M | F98: FY 2017 | G98: FY 2016 | H98: FY 2015 | I98: FY 2014 | J98: FY 2013 | K98: FY 2012 | L98: FY 2011 | M98: FY 2010 | N98: FY 2009 | O98: FY 2008 | P98: FY 2007 | Q98: FY 2006 | R98: FY 2005 | S98: FY 2004 | T98: FY 2003 | U98: FY 2002 | V98: FY 2001 | W98: FY 2000 | X98: FY 1999 | Y98: FY 1998 | Z98: FY 1997 | AA98: FY 1996 | AB98: FY 1995 | AC98: FY 1994
C99: 12 Months Ending | E99: 12/31/2017 | F99: 12/31/2017 | G99: 12/31/2016 | H99: 12/31/2015 | I99: 12/31/2014 | J99: 12/31/2013 | K99: 12/31/2012 | L99: 12/31/2011 | M99: 12/31/2010 | N99: 12/31/2009 | O99: 12/31/2008 | P99: 12/31/2007 | Q99: 12/31/2006 | R99: 12/31/2005 | S99: 12/31/2004 | T99: 12/31/2003 | U99: 12/31/2002 | V99: 12/31/2001 | W99: 12/31/2000 | X99: 12/31/1999 | Y99: 12/31/1998 | Z99: 12/31/1997 | AA99: 12/31/1996 | AB99: 12/31/1995 | AC99: 12/31/1994
C100: Cash from Operating Activities
C101: + Net Income | D101: CF_NET_INC | E101: 21308 | F101: 21308 | G101: 7215 | H101: 6960 | I101: 9135 | J101: 22003 | K101: 14570 | L101: 10009 | M101: 8257 | N101: 8635 | O101: 8104 | P101: 8144 | Q101: 19337 | R101: 8085 | S101: 11361 | T101: 3910 | U101: 9126 | V101: 7788 | W101: 3726 | X101: 4952 | Y101: 3351 | Z101: 2213 | AA101: 1929 | AB101: 1572.9 | AC101: 1298.4
C102: + Depreciation & Amortization | D102: CF_DEPR_AMORT | E102: 6269 | F102: 6269 | G102: 5757 | H102: 5157 | I102: 5537 | J102: 6410 | K102: 7655 | L102: 8907 | M102: 8487 | N102: 4757 | O102: 5090 | P102: 5200 | Q102: 5293 | R102: 5576 | S102: 5093 | T102: 4025 | U102: 1036 | V102: 1068 | W102: 968 | X102: 905 | Y102: 489 | Z102: 428 | AA102: 430 | AB102: 374 | AC102: 292
C103: + Non-Cash Items | D103: NON_CASH_ITEMS_DETAILED | E103: -12501 | F103: -12501 | G103: 2561 | H103: 2730 | I103: 1351 | J103: -897 | K103: 839 | L103: 2379 | M103: 4240 | N103: -9113 | O103: 111 | P103: 749 | Q103: -9755 | R103: 1988 | S103: 1436 | T103: 4341 | U103: 70 | V103: -39 | W103: -294 | X103: 523 | Y103: 345 | Z103: 59 | AA103: 231 | AB103: -47.900002 | AC103: -108.1
C104: + Stock-Based Compensation | D104: CF_STOCK_BASED_COMPENSATION | E104: 840 | F104: 840 | G104: 691 | H104: 669 | I104: 586 | J104: 523 | K104: 481 | L104: 419 | M104: 405 | N104: 349 | O104: 384 | P104: 437 | Q104: 655 | R104: 157 | S104: — | T104: — | U104: — | V104: — | W104: — | X104: — | Y104: — | Z104: — | AA104: — | AB104: — | AC104: —
C105: + Deferred Income Taxes | D105: CF_DEF_INC_TAX | E105: -13070 | F105: -13070 | G105: -700 | H105: -20 | I105: 317 | J105: 1703 | K105: 2198 | L105: 454 | M105: 1953 | N105: -9582 | O105: -1331 | P105: -2788 | Q105: -1945 | R105: -1457 | S105: -1579 | T105: -104 | U105: -285 | V105: 1092 | W105: -265 | X105: 213 | Y105: 22 | Z105: — | AA105: — | AB105: — | AC105: —
C106: + Other Non-Cash Adj | D106: OTHER_NON_CASH_ADJ_LESS_DETAILED | E106: -271 | F106: -271 | G106: 2570 | H106: 2081 | I106: 448 | J106: -3123 | K106: -1840 | L106: 1506 | M106: 1882 | N106: 120 | O106: 1058 | P106: 3100 | Q106: -8465 | R106: 3288 | S106: 3015 | T106: 4445 | U106: 355 | V106: -1131 | W106: -29 | X106: 310 | Y106: 323 | Z106: 59 | AA106: 231 | AB106: -47.900002 | AC106: -108.1
C107: + Chg in Non-Cash Work Cap | D107: CF_CHNG_NON_CASH_WORK_CAP | E107: 1394 | F107: 1394 | G107: 368 | H107: -159 | I107: 1112 | J107: 614 | K107: 805 | L107: 633 | M107: -9530 | N107: 12308 | O107: 4933 | P107: -740 | Q107: 2719 | R107: -916 | S107: -1550 | T107: -549 | U107: -49 | V107: 446 | W107: 1803 | X107: -907 | Y107: 498 | Z107: -1160 | AA107: -523 | AB107: -77.599998 | AC107: 6.2
C108: + (Inc) Dec in Accts Receiv | D108: CF_ACCT_RCV_UNBILLED_REV | F108: 259 | G108: -134 | H108: 21 | I108: 148 | J108: 940 | K108: 367 | L108: -66 | M108: -608 | N108: -472 | O108: 195 | P108: -320 | Q108: -172 | R108: -803 | S108: -465 | T108: 207 | U108: -963 | V108: 81 | W108: -498 | X108: -1274 | Y108: -765 | Z108: — | AA108: — | AB108: — | AC108: —
C109: + (Inc) Dec in Inventories | D109: CF_CHANGE_IN_INVENTORIES | F109: -357 | G109: 365 | H109: -199 | I109: 175 | J109: -538 | K109: -631 | L109: 1084 | M109: 2917 | N109: 1631 | O109: 294 | P109: 720 | Q109: 118 | R109: 72 | S109: -542 | T109: -200 | U109: -129 | V109: -110 | W109: -436 | X109: -278 | Y109: -439 | Z109: — | AA109: — | AB109: — | AC109: —
C110: + Inc (Dec) in Accts Payable | D110: CF_CHANGE_IN_ACCOUNTS_PAYABLE | F110: 46 | G110: 871 | H110: 254 | I110: 297 | J110: 382 | K110: 579 | L110: -367 | M110: — | N110: — | O110: — | P110: — | Q110: — | R110: — | S110: — | T110: — | U110: — | V110: — | W110: — | X110: — | Y110: — | Z110: — | AA110: — | AB110: — | AC110: —
C111: + Inc (Dec) in Other | D111: INC_DEC_IN_OT_OP_AST_LIAB_DETAIL | E111: 1394 | F111: 1446 | G111: -734 | H111: -235 | I111: 492 | J111: -170 | K111: 490 | L111: -18 | M111: -11839 | N111: 11149 | O111: 4444 | P111: -1140 | Q111: 2773 | R111: -185 | S111: -543 | T111: -556 | U111: 1043 | V111: 475 | W111: 2737 | X111: 645 | Y111: 1702 | Z111: -1160 | AA111: -523 | AB111: -77.599998 | AC111: 6.2
C112: + Net Cash From Disc Ops | D112: CF_NET_CASH_DISCONT_OPS_OPER | F112: — | G112: — | H112: — | I112: -51 | J112: -10446 | K112: -7123 | L112: -1688 | M112: — | N112: — | O112: — | P112: — | Q112: — | R112: — | S112: — | T112: — | U112: — | V112: — | W112: — | X112: — | Y112: — | Z112: — | AA112: — | AB112: — | AC112: —
C113: Cash from Operating Activities | D113: CF_CASH_FROM_OPER | E113: 16470 | F113: 16470 | G113: 15901 | H113: 14688 | I113: 17084 | J113: 17684 | K113: 16746 | L113: 20240 | M113: 11454 | N113: 16587 | O113: 18238 | P113: 13353 | Q113: 17594 | R113: 14733 | S113: 16340 | T113: 11727 | U113: 10183 | V113: 9263 | W113: 6203 | X113: 5473 | Y113: 4683 | Z113: 1540 | AA113: 2067 | AB113: 1821.4 | AC113: 1488.5
C115: Cash from Investing Activities
...

Sheet 3.4 Trading Multiples Bloomberg
B5: PFE US Equity
B6: Date | C6: PX_LAST | D6: BEST_CUR_EV_TO_EBITDA | E6: CURR_ENTP_VAL | F6: CUR_MKT_CAP | G6: PE_RATIO | H6: 5_YEAR_AVERAGE_ADJUSTED_ROE | I6: SALES_REV_TURN | J6: BEST_EPS | K6: EQY_DVD_YLD_12M | L6: EQY_SH_OUT | M6: CHG_PCT_1D | N6: CHG_PCT_1M | O6: BEST_PX_BPS_RATIO | P6: EBITDA | Q6: IS_ADJUSTED_EBITDA_AS_REPORTED | R6: BEST_DIV_YLD | S6: Diluted EPS | T6: EBIT | U6: EBITDA | V6: Enterprise Value/EBITDA | Y6: Total Equity | Z6: P/E Ratio | AA6: Price/Book Ratio
B7: =_xll.BDH($B$5,$C$6:$R$6,"14.03.1998","14.04.2018","Dir=V","Dts=S","Sort=A","Quote=C","QtTyp=Y","Days=T","Per=cy","DtFmt=D","UseDPDF=Y","cols=17;rows=20") -> #NAME? | C7: 41.6667 | D7: #N/A N/A | E7: 161551.24 | F7: 162224.24 | G7: 84.4595 | H7: 32.3375 | I7: 13544 | J7: #N/A N/A | K7: 0.608 | L7: 3893.382 | M7: 67.6446 | N7: #N/A N/A | O7: #N/A N/A | P7: 3083 | Q7: #N/A N/A | R7: #N/A N/A
B8: 36525 | C8: 32.4375 | D8: #N/A N/A | E8: 205231.19 | F8: 204544.19 | G8: 39.5579 | H8: 35.251 | I8: 27376 | J8: #N/A N/A | K8: 0.9454 | L8: 6305.794 | M8: -22.15 | N8: #N/A N/A | O8: #N/A N/A | P8: 7971 | Q8: #N/A N/A | R8: #N/A N/A
B9: 36889 | C9: 46 | D9: #N/A N/A | E9: 288764.82 | F9: 290215.82 | G9: 45.098 | H9: 37.5688 | I9: 29355 | J9: #N/A N/A | K9: 0.7826 | L9: 6309.04 | M9: 41.8112 | N9: #N/A N/A | O9: #N/A N/A | P9: 9658 | Q9: #N/A N/A | R9: #N/A N/A
B10: 37256 | C10: 39.85 | D10: #N/A N/A | E10: 250782.88 | F10: 250525.88 | G10: 31.378 | H10: 40.8036 | I10: 29024 | J10: #N/A N/A | K10: 1.1041 | L10: 6286.722 | M10: -13.3696 | N10: #N/A N/A | O10: #N/A N/A | P10: 11776 | Q10: #N/A N/A | R10: #N/A N/A | S10: 1.22 | T10: 10708 | U10: 11776 | V10: 21.2961 | Y10: 18293 | Z10: 31.378 | AA10: 13.674
B11: 37621 | C11: 30.57 | D11: #N/A N/A | E11: 187635.34 | F11: 188377.34 | G11: 19.2264 | H11: 45.58 | I11: 32373 | J11: #N/A N/A | K11: 1.701 | L11: 6162.164 | M11: -23.2873 | N11: #N/A N/A | O11: #N/A N/A | P11: 13352 | Q11: #N/A N/A | R11: #N/A N/A
B12: 37986 | C12: 35.33 | D12: #N/A N/A | E12: 272461.71 | F12: 269621.71 | G12: 20.1886 | H12: 43.5493 | I12: 45188 | J12: #N/A N/A | K12: 1.6983 | L12: 7631.523 | M12: 15.5708 | N12: #N/A N/A | O12: #N/A N/A | P12: 20115 | Q12: #N/A N/A | R12: #N/A N/A
B13: 38352 | C13: 26.89 | D13: #N/A N/A | E13: 201353.47 | F13: 202508.47 | G13: 15.1067 | H13: 38.4604 | I13: 52516 | J13: #N/A N/A | K13: 2.5288 | L13: 7530.996 | M13: -23.889 | N13: #N/A N/A | O13: #N/A N/A | P13: 22181 | Q13: #N/A N/A | R13: #N/A N/A
B14: 38716 | C14: 23.32 | D14: #N/A N/A | E14: 167779.97 | F14: 171900.97 | G14: 11.959 | H14: 34.1562 | I14: 47405 | J14: #N/A N/A | K14: 3.259 | L14: 7371.396 | M14: -13.2763 | N14: #N/A N/A | O14: #N/A N/A | P14: 19781 | Q14: #N/A N/A | R14: #N/A N/A
B15: 39080 | C15: 25.9 | D15: #N/A N/A | E15: 167232.52 | F15: 186750.52 | G15: 12.5121 | H15: 29.7389 | I15: 48371 | J15: #N/A N/A | K15: 3.7066 | L15: 7210.445 | M15: 11.0635 | N15: #N/A N/A | O15: #N/A N/A | P15: 19575 | Q15: #N/A N/A | R15: #N/A N/A
B16: 39447 | C16: 22.73 | D16: #N/A N/A | E16: 143112.47 | F16: 155241.47 | G16: 10.4747 | H16: 23.8237 | I16: 48418 | J16: #N/A N/A | K16: 5.1034 | L16: 6829.805 | M16: -12.2394 | N16: #N/A N/A | O16: #N/A N/A | P16: 19980 | Q16: #N/A N/A | R16: #N/A N/A
B17: 39813 | C17: 17.71 | D17: #N/A N/A | E17: 113226.39 | F17: 119417.39 | G17: 11.7285 | H17: 21.169 | I17: 48296 | J17: #N/A N/A | K17: 7.2276 | L17: 6742.936 | M17: -22.0853 | N17: #N/A N/A | O17: #N/A N/A | P17: 22146 | Q17: #N/A N/A | R17: #N/A N/A
B18: 40178 | C18: 18.19 | D18: #N/A N/A | E18: 169970.86 | F18: 146784.86 | G18: 11.0223 | H18: 20.2494 | I18: 50009 | J18: #N/A N/A | K18: 4.398 | L18: 8069.536 | M18: 2.7103 | N18: #N/A N/A | O18: #N/A N/A | P18: 15944 | Q18: #N/A N/A | R18: #N/A N/A
B19: 40543 | C19: 17.51 | D19: #N/A N/A | E19: 156759.24 | F19: 140254.24 | G19: 11.9486 | H19: 18.5799 | I19: 67057 | J19: #N/A N/A | K19: 4.1119 | L19: 8009.951 | M19: -3.7383 | N19: #N/A N/A | O19: #N/A N/A | P19: 22105 | Q19: #N/A N/A | R19: #N/A N/A
B20: 40907 | C20: 21.64 | D20: #N/A N/A | E20: 179311.96 | F20: 166345.96 | G20: 13.278 | H20: 16.592 | I20: 65259 | J20: #N/A N/A | K20: 3.6969 | L20: 7686.967 | M20: 23.5865 | N20: #N/A N/A | O20: #N/A N/A | P20: 23710 | Q20: #N/A N/A | R20: #N/A N/A
B21: 41274 | C21: 25.0793 | D21: #N/A N/A | E21: 190166.29 | F21: 184648.29 | G21: 15.4295 | H21: 15.139 | I21: 54657 | J21: #N/A N/A | K21: 3.5089 | L21: 7362.574 | M21: 15.8933 | N21: #N/A N/A | O21: #N/A N/A | P21: 22919 | Q21: #N/A N/A | R21: #N/A N/A
B22: 41639 | C22: 30.63 | D22: #N/A N/A | E22: 202942.2 | F22: 198515.2 | G22: 17.3983 | H22: 14.8878 | I22: 51584 | J22: #N/A N/A | K22: 3.1342 | L22: 6481.071 | M22: 22.1325 | N22: #N/A N/A | O22: #N/A N/A | P22: 21594 | Q22: #N/A N/A | R22: #N/A N/A
... B24: 42369 | C24: 32.28 | D24: #N/A N/A | E24: 215177.5 | F24: 199264.5 | G24: 19.3554 | H24: 15.2503 | I24: 48851 | J24: #N/A N/A | K24: 3.4696 | L24: 6173.002 | M24: 3.6276 | N24: #N/A N/A | O24: #N/A N/A | P24: 16981 | Q24: #N/A N/A | R24: #N/A N/A
B25: 42734 | C25: 32.48 | D25: #N/A N/A | E25: 221656.17 | F25: 197100.17 | G25: 15.4847 | H25: 16.385 | I25: 52824 | J25: #N/A N/A | K25: 3.6946 | L25: 6068.355 | M25: 0.6196 | N25: #N/A N/A | O25: #N/A N/A | P25: 17763 | Q25: #N/A N/A | R25: 8.99
B26: 43098 | C26: 36.22 | D26: #N/A N/A | E26: 239764.82 | F26: 215896.82 | G26: 16.9817 | H26: 17.3469 | I26: 52546 | J26: 0.69 | K26: 3.534 | L26: 5960.707 | M26: 11.5148 | N26: #N/A N/A | O26: #N/A N/A | P26: 19889 | Q26: #N/A N/A | R26: 3.81
B30: LLY US Equity
B31: Date | C31: PX_LAST | D31: BEST_CUR_EV_TO_EBITDA | E31: CURR_ENTP_VAL | F31: CUR_MKT_CAP | G31: PE_RATIO | H31: 5_YEAR_AVERAGE_ADJUSTED_ROE | I31: SALES_REV_TURN | J31: BEST_EPS | K31: EQY_DVD_YLD_12M | L31: EQY_SH_OUT | M31: CHG_PCT_1D | N31: CHG_PCT_1M | O31: BEST_PX_BPS_RATIO | P31: EBITDA | Q31: IS_ADJUSTED_EBITDA_AS_REPORTED | R31: BEST_DIV_YLD | S31: Diluted EPS | T31: EBIT | U31: EBITDA | V31: Enterprise Value/EBITDA | Y31: Total Equity | Z31: P/E Ratio | AA31: Price/Book Ratio
B32: =_xll.BDH($S$1,$T$2:$AI$2,"14.03.1998","14.04.2018","Dir=V","Dts=S","Sort=A","Quote=C","QtTyp=Y","Days=T","Per=cy","DtFmt=D","UseDPDF=Y","cols=17;rows=20") -> #NAME? | C32: 88.875 | D32: #N/A N/A | E32: 98505.633 | F32: 97735.833 | G32: 46.0492 | H32: 27.41 | I32: 9236.7998 | J32: #N/A N/A | K32: 0.9001 | L32: 1099.7 | M32: 27.6481 | N32: #N/A N/A | O32: #N/A N/A | P32: 3314.9 | Q32: #N/A N/A | R32: #N/A N/A
B33: 36525 | C33: 66.5 | D33: #N/A N/A | E33: 71737.046 | F33: 72519.646 | G33: 28.2979 | H33: 33.6623 | I33: 10002.9 | J33: #N/A N/A | K33: 1.3835 | L33: 1090.521 | M33: -25.1758 | N33: #N/A N/A | O33: #N/A N/A | P33: 3803.4 | Q33: #N/A N/A | R33: #N/A N/A
B34: 36889 | C34: 93.0625 | D34: #N/A N/A | E34: 103106.78 | F34: 104906.98 | G34: 35.1179 | H34: 39.3242 | I34: 10862.2 | J34: #N/A N/A | K34: 1.1175 | L34: 1127.274 | M34: 39.9436 | N34: #N/A N/A | O34: #N/A N/A | P34: 3995.5 | Q34: #N/A N/A | R34: #N/A N/A
B35: 37256 | C35: 78.54 | D35: #N/A N/A | E35: 87982.678 | F35: 88295.278 | G35: 28.4565 | H35: 43.2197 | I35: 11542.5 | J35: #N/A N/A | K35: 1.426 | L35: 1124.208 | M35: -15.6051 | N35: #N/A N/A | O35: #N/A N/A | P35: 4184.7 | Q35: #N/A N/A | R35: #N/A N/A | S35: 2.55 | T35: 3729.8 | U35: 4184.7 | V35: 21.0248 | Y35: 7104 | Z35: 28.4565 | AA35: 12.4195
B36: 37621 | C36: 63.5 | D36: #N/A N/A | E36: 72583.127 | F36: 71334.227 | G36: 24.902 | H36: 47.4663 | I36: 11077.5 | J36: #N/A N/A | K36: 1.9528 | L36: 1123.374 | M36: -19.1495 | N36: #N/A N/A | O36: #N/A N/A | P36: 3820.7 | Q36: #N/A N/A | R36: #N/A N/A
B37: 37986 | C37: 70.33 | D37: #N/A N/A | E37: 80144.842 | F37: 78973.842 | G37: 27.2597 | H37: 44.0825 | I37: 12582.5 | J37: #N/A N/A | K37: 1.9053 | L37: 1122.904 | M37: 10.7559 | N37: #N/A N/A | O37: #N/A N/A | P37: 4050.3 | Q37: #N/A N/A | R37: #N/A N/A
B38: 38352 | C38: 56.75 | D38: #N/A N/A | E38: 63268.622 | F38: 64220.522 | G38: 23.6458 | H38: 38.0973 | I38: 13857.9 | J38: #N/A N/A | K38: 2.5022 | L38: 1131.639 | M38: -19.309 | N38: #N/A N/A | O38: #N/A N/A | P38: 4256.2 | Q38: #N/A N/A | R38: #N/A N/A
B39: 38716 | C39: 56.59 | D39: #N/A N/A | E39: 65782.288 | F39: 64321.788 | G39: 19.7178 | H39: 33.3638 | I39: 14645.3 | J39: #N/A N/A | K39: 2.686 | L39: 1136.628 | M39: -0.2819 | N39: #N/A N/A | O39: #N/A N/A | P39: 4375 | Q39: #N/A N/A | R39: #N/A N/A
B40: 39080 | C40: 52.1 | D40: #N/A N/A | E40: 58778.561 | F40: 58955.761 | G40: 16.3836 | H40: 30.5533 | I40: 15691 | J40: #N/A N/A | K40: 3.071 | L40: 1131.589 | M40: -7.9343 | N40: #N/A N/A | O40: #N/A N/A | P40: 4927.2 | Q40: #N/A N/A | R40: #N/A N/A
B41: 39447 | C41: 53.39 | D41: #N/A N/A | E41: 60736.957 | F41: 60560.957 | G41: 15.0819 | H41: 29.6997 | I41: 18633.5 | J41: #N/A N/A | K41: 3.1841 | L41: 1134.313 | M41: 2.476 | N41: #N/A N/A | O41: #N/A N/A | P41: 5850.8 | Q41: #N/A N/A | R41: #N/A N/A
B42: 39813 | C42: 40.27 | D42: #N/A N/A | E42: 50323.412 | F42: 45785.112 | G42: 10.0174 | H42: 32.1945 | I42: 20371.9 | J42: #N/A N/A | K42: 4.6685 | L42: 1136.953 | M42: -24.5739 | N42: #N/A N/A | O42: #N/A N/A | P42: 6650.5 | Q42: #N/A N/A | R42: #N/A N/A
B43: 40178 | C43: 35.71 | D43: #N/A N/A | E43: 43197.692 | F43: 41031.592 | G43: 8.4151 | H43: 38.6209 | I43: 21836 | J43: #N/A N/A | K43: 5.4887 | L43: 1149.022 | M43: -11.3236 | N43: #N/A N/A | O43: #N/A N/A | P43: 6885.1 | Q43: #N/A N/A | R43: #N/A N/A
B44: 40543 | C44: 35.04 | D44: #N/A N/A | E44: 40598.142 | F44: 40406.142 | G44: 7.5079 | H44: 42.2643 | I44: 23076 | J44: #N/A N/A | K44: 5.5936 | L44: 1153.143 | M44: -1.8762 | N44: #N/A N/A | O44: #N/A N/A | P44: 7858.4 | Q44: #N/A N/A | R44: #N/A N/A
B45: 40907 | C45: 41.56 | D45: #N/A N/A | E45: 48200.392 | F45: 48116.592 | G45: 9.567 | H45: 43.3684 | I45: 24286.5 | J45: #N/A N/A | K45: 4.7161 | L45: 1157.762 | M45: 18.6073 | N45: #N/A N/A | O45: #N/A N/A | P45: 6902.1 | Q45: #N/A N/A | R45: #N/A N/A
B46: 41274 | C46: 49.32 | D46: #N/A N/A | E46: 57089.218 | F46: 57233.518 | G46: 13.0529 | H46: 43.0008 | I46: 22603.4 | J46: #N/A N/A | K46: 3.974 | L46: 1160.453 | M46: 18.6718 | N46: #N/A N/A | O46: #N/A N/A | P46: 6196.4 | Q46: #N/A N/A | R46: #N/A N/A
B47: 41639 | C47: 51 | D47: #N/A N/A | E47: 57284.033 | F47: 57459.133 | G47: 12.4284 | H47: 39.8059 | I47: 23113.1 | J47: #N/A N/A | K47: 3.8431 | L47: 1126.65 | M47: 3.4063 | N47: #N/A N/A | O47: #N/A N/A | P47: 6816 | Q47: #N/A N/A | R47: #N/A N/A
... B49: 42369 | C49: 84.26 | D49: #N/A N/A | E49: 93265.629 | F49: 93366.529 | G49: 30.2542 | H49: 26.0531 | I49: 19958.7 | J49: #N/A N/A | K49: 2.3736 | L49: 1108.077 | M49: 22.1336 | N49: #N/A N/A | O49: #N/A N/A | P49: 4117.1 | Q49: #N/A N/A | R49: #N/A N/A
B50: 42734 | C50: 73.55 | D50: #N/A N/A | E50: 80327.293 | F50: 81195.393 | G50: 23.9728 | H50: 23.1493 | I50: 21222.1 | J50: 0.935 | K50: 2.7736 | L50: 1103.948 | M50: -12.7107 | N50: #N/A N/A | O50: #N/A N/A | P50: 4955.4 | Q50: #N/A N/A | R50: #N/A N/A
B51: 43098 | C51: 84.46 | D51: 14.035 | E51: 93008.359 | F51: 92998.459 | G51: 22.4806 | H51: 23.3605 | I51: 22871.3 | J51: 1.086 | K51: 2.4627 | L51: 1101.095 | M51: 14.8334 | N51: #N/A N/A | O51: #N/A N/A | P51: 3712.3 | Q51: #N/A N/A | R51: 2.666
B54: JNJ US Equity
B55: Date | C55: PX_LAST | D55: BEST_CUR_EV_TO_EBITDA | E55: CURR_ENTP_VAL | F55: CUR_MKT_CAP | G55: PE_RATIO | H55: 5_YEAR_AVERAGE_ADJUSTED_ROE | I55: SALES_REV_TURN | J55: BEST_EPS | K55: EQY_DVD_YLD_12M | L55: EQY_SH_OUT | M55: CHG_PCT_1D | N55: CHG_PCT_1M | O55: BEST_PX_BPS_RATIO | P55: EBITDA | Q55: IS_ADJUSTED_EBITDA_AS_REPORTED | R55: BEST_DIV_YLD | S55: Diluted EPS | T55: EBIT | U55: EBITDA | V55: Enterprise Value/EBITDA | Y55: Total Equity | Z55: P/E Ratio | AA55: Price/Book Ratio
B56: =_xll.BDH($AK$1,$AL$2:$BA$2,"14.03.1998","14.04.2018","Dir=V","Dts=S","Sort=A","Quote=C","QtTyp=Y","Days=T","Per=cy","DtFmt=D","UseDPDF=Y","cols=17;rows=20") -> #NAME? | C56: 41.938 | D56: #N/A N/A | E56: 114068.17 | F56: 112806.17 | G56: 39.5637 | H56: 29.6046 | I56: 23995 | J56: #N/A N/A | K56: 1.1565 | L56: 2689.864 | M56: 27.3245 | N56: #N/A N/A | O56: #N/A N/A | P56: 6170 | Q56: #N/A N/A | R56: #N/A N/A
B57: 36525 | C57: 46.625 | D57: #N/A N/A | E57: 143062.16 | F57: 143126.16 | G57: 31.7177 | H57: 28.7843 | I57: 27471 | J57: #N/A N/A | K57: 1.1689 | L57: 3069.73 | M57: 11.1773 | N57: #N/A N/A | O57: #N/A N/A | P57: 7370 | Q57: #N/A N/A | R57: #N/A N/A
B58: 36889 | C58: 52.531 | D58: #N/A N/A | E58: 143277.93 | F58: 146039.93 | G58: 32.4267 | H58: 28.3028 | I58: 29846 | J58: #N/A N/A | K58: 1.1802 | L58: 2780.058 | M58: 12.6676 | N58: #N/A N/A | O58: #N/A N/A | P58: 8301 | Q58: #N/A N/A | R58: #N/A N/A
B59: 37256 | C59: 59.1 | D59: #N/A N/A | E59: 174951.11 | F59: 180141.11 | G59: 30.9424 | H59: 27.7815 | I59: 32317 | J59: #N/A N/A | K59: 1.1844 | L59: 3048.073 | M59: 12.5045 | N59: #N/A N/A | O59: #N/A N/A | P59: 9490 | Q59: #N/A N/A | R59: #N/A N/A | S59: 1.84 | T59: 7885 | U59: 9490 | V59: 18.4353 | Y59: 24233 | Z59: 30.9424 | AA59: 7.4316
B60: 37621 | C60: 53.71 | D60: #N/A N/A | E60: 156213.93 | F60: 159549.93 | G60: 24.1937 | H60: 27.8694 | I60: 36298 | J60: #N/A N/A | K60: 1.4802 | L60: 2970.582 | M60: -9.1201 | N60: #N/A N/A | O60: #N/A N/A | P60: 11340 | Q60: #N/A N/A | R60: #N/A N/A
B61: 37986 | C61: 51.66 | D61: #N/A N/A | E61: 147905.27 | F61: 153334.27 | G61: 19.4943 | H61: 28.4698 | I61: 41862 | J61: #N/A N/A | K61: 1.7906 | L61: 2968.143 | M61: -3.8168 | N61: #N/A N/A | O61: #N/A N/A | P61: 12740 | Q61: #N/A N/A | R61: #N/A N/A
B62: 38352 | C62: 63.42 | D62: #N/A N/A | E62: 178128.19 | F62: 188213.19 | G62: 20.3923 | H62: 29.313 | I62: 47348 | J62: #N/A N/A | K62: 1.7266 | L62: 2967.726 | M62: 22.7642 | N62: #N/A N/A | O62: #N/A N/A | P62: 14987 | Q62: #N/A N/A | R62: #N/A N/A
B63: 38716 | C63: 60.1 | D63: #N/A N/A | E63: 165320.29 | F63: 178793.29 | G63: 17.7286 | H63: 29.631 | I63: 50514 | J63: #N/A N/A | K63: 2.1215 | L63: 2974.93 | M63: -5.2349 | N63: #N/A N/A | O63: #N/A N/A | P63: 14924 | Q63: #N/A N/A | R63: #N/A N/A
B64: 39080 | C64: 66.02 | D64: #N/A N/A | E64: 193908.43 | F64: 191415.43 | G64: 17.5585 | H64: 30.051 | I64: 53324 | J64: #N/A N/A | K64: 2.2039 | L64: 2899.355 | M64: 9.8502 | N64: #N/A N/A | O64: #N/A N/A | P64: 15886 | Q64: #N/A N/A | R64: #N/A N/A
B65: 39447 | C65: 66.7 | D65: #N/A N/A | E65: 191098.73 | F65: 190878.73 | G65: 16.0723 | H65: 30.1167 | I65: 61095 | J65: #N/A N/A | K65: 2.4288 | L65: 2861.75 | M65: 1.03 | N65: #N/A N/A | O65: #N/A N/A | P65: 17990 | Q65: #N/A N/A | R65: #N/A N/A
B66: 39813 | C66: 59.83 | D66: #N/A N/A | E66: 165041.41 | F66: 166002.41 | G66: 13.1495 | H66: 29.6972 | I66: 63747 | J66: #N/A N/A | K66: 3.0002 | L66: 2774.568 | M66: -10.2999 | N66: #N/A N/A | O66: #N/A N/A | P66: 19001 | Q66: #N/A N/A | R66: #N/A N/A
B67: 40178 | C67: 64.41 | D67: #N/A N/A | E67: 172829.61 | F67: 177713.61 | G67: 14.2318 | H67: 28.772 | I67: 61897 | J67: #N/A N/A | K67: 2.9964 | L67: 2759.1 | M67: 7.655 | N67: #N/A N/A | O67: #N/A N/A | P67: 18364 | Q67: #N/A N/A | R67: #N/A N/A
B68: 40543 | C68: 61.85 | D68: #N/A N/A | E68: 158970.79 | F68: 169855.79 | G68: 12.9929 | H68: 27.9464 | I68: 61587 | J68: #N/A N/A | K68: 3.4115 | L68: 2746.254 | M68: -3.9745 | N68: #N/A N/A | O68: #N/A N/A | P68: 19466 | Q68: #N/A N/A | R68: #N/A N/A
B69: 40907 | C69: 65.58 | D69: #N/A N/A | E69: 166455.09 | F69: 179089.09 | G69: 13.1119 | H69: 27.1194 | I69: 65030 | J69: #N/A N/A | K69: 3.4309 | L69: 2730.849 | M69: 6.0307 | N69: #N/A N/A | O69: #N/A N/A | P69: 18742 | Q69: #N/A N/A | R69: #N/A N/A
B70: 41274 | C70: 70.1 | D70: #N/A N/A | E70: 189341.45 | F70: 194265.45 | G70: 13.7409 | H70: 25.9767 | I70: 67224 | J70: #N/A N/A | K70: 3.4237 | L70: 2771.262 | M70: 6.8923 | N70: #N/A N/A | O70: #N/A N/A | P70: 19535 | Q70: #N/A N/A | R70: #N/A N/A
B71: 41639 | C71: 91.59 | D71: #N/A N/A | E71: 247389.55 | F71: 258415.55 | G71: 16.6274 | H71: 24.5266 | I71: 71312 | J71: #N/A N/A | K71: 2.8278 | L71: 2821.438 | M71: 30.6562 | N71: #N/A N/A | O71: #N/A N/A | P71: 22481 | Q71: #N/A N/A | R71: #N/A N/A
B72: 42004 | C72: 104.57 | D72: #N/A N/A | E72: 278373.97 | F72: 292702.97 | G72: 19.25 | H72: 23.4328 | I72: 74331 | J72: #N/A N/A | K72: 2.6394 | L72: 2799.11 | M72: 14.1719 | N72: #N/A N/A | O72: #N/A N/A | P72: 24854 | Q72: #N/A N/A | R72: #N/A N/A
B73: 42369 | C73: 102.72 | D73: 9.913 | E73: 265705.45 | F73: 284220.45 | G73: 19.2813 | H73: 22.729 | I73: 70074 | J73: 1.93 | K73: 2.8719 | L73: 2766.944 | M73: -1.7691 | N73: #N/A N/A | O73: #N/A N/A | P73: 21811 | Q73: #N/A N/A | R73: #N/A N/A
B74: 42734 | C74: 115.21 | D74: 12.033 | E74: 298651.46 | F74: 313432.46 | G74: 18.4435 | H74: 22.7716 | I74: 71890 | J74: 1.83 | K74: 2.7341 | L74: 2720.532 | M74: 12.1593 | N74: #N/A N/A | O74: #N/A N/A | P74: 24890 | Q74: #N/A N/A | R74: #N/A N/A
B75: 43098 | C75: 139.72 | D75: 13.478 | E75: 391645.58 | F75: 375360.58 | G75: 21.8569 | H75: 23.4436 | I75: 76450 | J75: 1.979 | K75: 2.3762 | L75: 2686.52 | M75: 21.2742 | N75: #N/A N/A | O75: 4.882 | P75: 24356 | Q75: #N/A N/A | R75: 2.512
B78: MRK US Equity
B79: Date | C79: PX_LAST | D79: BEST_CUR_EV_TO_EBITDA | E79: CURR_ENTP_VAL | F79: CUR_MKT_CAP | G79: PE_RATIO | H79: 5_YEAR_AVERAGE_ADJUSTED_ROE | I79: SALES_REV_TURN | J79: BEST_EPS | K79: EQY_DVD_YLD_12M | L79: EQY_SH_OUT | M79: CHG_PCT_1D | N79: CHG_PCT_1M | O79: BEST_PX_BPS_RATIO | P79: EBITDA | Q79: IS_ADJUSTED_EBITDA_AS_REPORTED | R79: BEST_DIV_YLD | S79: Diluted EPS | T79: EBIT | U79: EBITDA | V79: Enterprise Value/EBITDA | Y79: Total Equity | Z79: P/E Ratio | AA79: Price/Book Ratio
B80: =_xll.BDH($BU$1,$BV$2:$CK$2,"14.03.1998","14.04.2018","Dir=V","Dts=S","Sort=A","Quote=C","QtTyp=Y","Days=T","Per=cy","DtFmt=D","UseDPDF=Y","cols=17;rows=20") -> #NAME? | C80: 69.8012 | D80: #N/A N/A | E80: 178398.59 | F80: 174204.29 | G80: 32.4657 | H80: 33.8137 | I80: 26898.199 | J80: #N/A N/A | K80: 1.4183 | L80: 2362.092 | M80: 39.1509 | N80: #N/A N/A | O80: #N/A N/A | P80: 7655.3998 | Q80: #N/A N/A | R80: #N/A N/A
B81: 36525 | C81: 63.5901 | D81: #N/A N/A | E81: 163307.81 | F81: 157046.81 | G81: 25.9551 | H81: 37.1957 | I81: 32714 | J81: #N/A N/A | K81: 1.7613 | L81: 2337.441 | M81: -8.8983 | N81: #N/A N/A | O81: #N/A N/A | P81: 9767.3 | Q81: #N/A N/A | R81: #N/A N/A
B82: 36889 | C82: 88.6121 | D82: #N/A N/A | E82: 223598.29 | F82: 215911.89 | G82: 30.5559 | H82: 41.0832 | I82: 40363.2 | J82: #N/A N/A | K82: 1.4219 | L82: 2306.135 | M82: 39.3488 | N82: #N/A N/A | O82: #N/A N/A | P82: 10366.4 | Q82: #N/A N/A | R82: #N/A N/A
B83: 37256 | C83: 55.6517 | D83: #N/A N/A | E83: 144169.15 | F83: 133752.95 | G83: 17.7235 | H83: 43.9658 | I83: 47715.7 | J83: #N/A N/A | K83: 2.4797 | L83: 2274.71 | M83: -37.1963 | N83: #N/A N/A | O83: #N/A N/A | P83: 11522.2 | Q83: #N/A N/A | R83: #N/A N/A | S83: 3.14 | T83: 10058.4 | U83: 11522.2 | V83: 12.5123 | Y83: 20887.6 | Z83: 17.7235 | AA83: 7.8804
B84: 37621 | C84: 53.579 | D84: #N/A N/A | E84: 135626.85 | F84: 127120.95 | G84: 17.0634 | H84: 44.808 | I84: 51790.3 | J84: #N/A N/A | K84: 2.6503 | L84: 2245.556 | M84: -3.7245 | N84: #N/A N/A | O84: #N/A N/A | P84: 11361 | Q84: #N/A N/A | R84: #N/A N/A
B85: 37986 | C85: 46.2 | D85: #N/A N/A | E85: 109333.06 | F85: 102794.86 | G85: 15.4515 | H85: 44.5347 | I85: 22485.9 | J85: #N/A N/A | K85: 3.1602 | L85: 2224.997 | M85: -13.7721 | N85: #N/A N/A | O85: #N/A N/A | P85: 9985.4 | Q85: #N/A N/A | R85: #N/A N/A
B86: 38352 | C86: 32.14 | D86: #N/A N/A | E86: 73462.873 | F86: 71273.173 | G86: 10.4691 | H86: 43.8193 | I86: 22938.6 | J86: #N/A N/A | K86: 4.6671 | L86: 2217.585 | M86: -30.4329 | N86: #N/A N/A | O86: #N/A N/A | P86: 9141.6 | Q86: #N/A N/A | R86: #N/A N/A
B87: 38716 | C87: 31.81 | D87: #N/A N/A | E87: 64423.974 | F87: 69556.774 | G87: 12.5731 | H87: 40.4369 | I87: 22011.9 | J87: #N/A N/A | K87: 4.7784 | L87: 2186.632 | M87: -1.0268 | N87: #N/A N/A | O87: #N/A N/A | P87: 7762.9 | Q87: #N/A N/A | R87: #N/A N/A
B88: 39080 | C88: 43.6 | D88: #N/A N/A | E88: 95184.917 | F88: 94655.717 | G88: 17.3016 | H88: 37.2131 | I88: 22636 | J88: #N/A N/A | K88: 3.4862 | L88: 2171.003 | M88: 37.0638 | N88: #N/A N/A | O88: #N/A N/A | P88: 7510.4 | Q88: #N/A N/A | R88: #N/A N/A
B89: 39447 | C89: 58.11 | D89: #N/A N/A | E89: 126395.63 | F89: 126480.33 | G89: 18.1594 | H89: 36.7175 | I89: 24197.7 | J89: #N/A N/A | K89: 2.6157 | L89: 2176.567 | M89: 33.2798 | N89: #N/A N/A | O89: #N/A N/A | P89: 7959.3 | Q89: #N/A N/A | R89: #N/A N/A
B90: 39813 | C90: 30.4 | D90: #N/A N/A | E90: 67434.056 | F90: 64271.255 | G90: 8.8889 | H90: 36.6812 | I90: 23850.3 | J90: #N/A N/A | K90: 5 | L90: 2114.186 | M90: -47.6854 | N90: #N/A N/A | O90: #N/A N/A | P90: 8070.3 | Q90: #N/A N/A | R90: #N/A N/A
B91: 40178 | C91: 36.54 | D91: #N/A N/A | E91: 122114.58 | F91: 111610.58 | G91: 5.7167 | H91: 35.8466 | I91: 27428 | J91: #N/A N/A | K91: 4.1598 | L91: 3054.477 | M91: 20.1974 | N91: #N/A N/A | O91: #N/A N/A | P91: 4963 | Q91: #N/A N/A | R91: #N/A N/A
B92: 40543 | C92: 36.04 | D92: #N/A N/A | E92: 119144.95 | F92: 111034.95 | G92: 25.4288 | H92: 31.0643 | I92: 45987 | J92: #N/A N/A | K92: 4.2175 | L92: 3080.881 | M92: -1.3684 | N92: #N/A N/A | O92: #N/A N/A | P92: 9751 | Q92: #N/A N/A | R92: #N/A N/A
B93: 40907 | C93: 37.7 | D93: #N/A N/A | E93: 119875.64 | F93: 114906.64 | G93: 13.8785 | H93: 27.9519 | I93: 48047 | J93: #N/A N/A | K93: 4.1379 | L93: 3047.921 | M93: 4.606 | N93: #N/A N/A | O93: #N/A N/A | P93: 15097 | Q93: #N/A N/A | R93: #N/A N/A
B94: 41274 | C94: 40.94 | D94: #N/A N/A | E94: 131331.55 | F94: 124460.55 | G94: 17.0036 | H94: 22.8587 | I94: 47267 | J94: #N/A N/A | K94: 4.128 | L94: 3040.072 | M94: 8.5942 | N94: #N/A N/A | O94: #N/A N/A | P94: 16191 | Q94: #N/A N/A | R94: #N/A N/A
B95: 41639 | C95: 50.05 | D95: #N/A N/A | E95: 156377.54 | F95: 146242.54 | G95: 24.2258 | H95: 17.317 | I95: 44033 | J95: #N/A N/A | K95: 3.4565 | L95: 2921.929 | M95: 22.2521 | N95: #N/A N/A | O95: #N/A N/A | P95: 12944 | Q95: #N/A N/A | R95: #N/A N/A
... B97: 42369 | C97: 52.82 | D97: #N/A N/A | E97: 160630.95 | F97: 147554.95 | G97: 14.7188 | H97: 15.0522 | I97: 39498 | J97: #N/A N/A | K97: 3.4267 | L97: 2793.543 | M97: -6.9907 | N97: #N/A N/A | O97: #N/A N/A | P97: 13303 | Q97: #N/A N/A | R97: #N/A N/A
B98: 42734 | C98: 58.87 | D98: #N/A N/A | E98: 173033.68 | F98: 162312.68 | G98: 28.256 | H98: 14.6923 | I98: 39807 | J98: 0.95 | K98: 3.1425 | L98: 2757.137 | M98: 11.454 | N98: #N/A N/A | O98: #N/A N/A | P98: 10820 | Q98: #N/A N/A | R98: #N/A N/A
B99: 43098 | C99: 56.27 | D99: 11.041 | E99: 169449.06 | F99: 153304.06 | G99: 16.8064 | H99: 16.8783 | I99: 40122 | J99: 0.96 | K99: 3.3588 | L99: 2724.437 | M99: -4.4165 | N99: #N/A N/A | O99: #N/A N/A | P99: 11170 | Q99: #N/A N/A | R99: 3.412
B102: BMY US Equity
B103: Date | C103: PX_LAST | D103: BEST_CUR_EV_TO_EBITDA | E103: CURR_ENTP_VAL | F103: CUR_MKT_CAP | G103: PE_RATIO | H103: 5_YEAR_AVERAGE_ADJUSTED_ROE | I103: SALES_REV_TURN | J103: BEST_EPS | K103: EQY_DVD_YLD_12M | L103: EQY_SH_OUT | M103: CHG_PCT_1D | N103: CHG_PCT_1M | O103: BEST_PX_BPS_RATIO | P103: EBITDA | Q103: IS_ADJUSTED_EBITDA_AS_REPORTED | R103: BEST_DIV_YLD | S103: Diluted EPS | T103: EBIT | U103: EBITDA | V103: Enterprise Value/EBITDA | Y103: Total Equity | Z103: P/E Ratio | AA103: Price/Book Ratio
B104: =_xll.BDH($CM$1,$CN$2:$DC$2,"14.03.1998","14.04.2018","Dir=V","Dts=S","Sort=A","Quote=C","QtTyp=Y","Days=T","Per=cy","DtFmt=D","UseDPDF=Y","cols=17;rows=20") -> #NAME? | C104: 63.6798 | D104: #N/A N/A | E104: 132269.36 | F104: 132952.36 | G104: 35.5753 | H104: 43.6779 | I104: 18284 | J104: #N/A N/A | K104: 1.2249 | L104: 1987.144 | M104: 41.4135 | N104: #N/A N/A | O104: #N/A N/A | P104: 5746 | Q104: #N/A N/A | R104: #N/A N/A
B105: 36525 | C105: 61.0922 | D105: #N/A N/A | E105: 126145.23 | F105: 127328.23 | G105: 32.6696 | H105: 46.6936 | I105: 16878 | J105: #N/A N/A | K105: 1.4077 | L105: 1983.692 | M105: -4.0635 | N105: #N/A N/A | O105: #N/A N/A | P105: 5917 | Q105: #N/A N/A | R105: #N/A N/A
B106: 36889 | C106: 70.372 | D106: #N/A N/A | E106: 142687.46 | F106: 144574.46 | G106: 32.5796 | H106: 47.3581 | I106: 18216 | J106: #N/A N/A | K106: 1.3926 | L106: 1955.36 | M106: 15.1899 | N106: #N/A N/A | O106: #N/A N/A | P106: 6732 | Q106: #N/A N/A | R106: #N/A N/A
B107: 37256 | C107: 51 | D107: #N/A N/A | E107: 99434.685 | F107: 98677.685 | G107: 24.6377 | H107: 47.057 | I107: 17987 | J107: #N/A N/A | K107: 2.1569 | L107: 1934.857 | M107: -27.528 | N107: #N/A N/A | O107: #N/A N/A | P107: 5886 | Q107: #N/A N/A | R107: #N/A N/A | S107: 2.46 | T107: 5158 | U107: 5886 | V107: 16.8934 | Y107: 9075 | Z107: 24.6377 | AA107: 12.3622
B108: 37621 | C108: 23.15 | D108: #N/A N/A | E108: 48493.59 | F108: 44842.59 | G108: 17.406 | H108: 43.6256 | I108: 18106 | J108: #N/A N/A | K108: 4.838 | L108: 1937.045 | M108: -54.6078 | N108: #N/A N/A | O108: #N/A N/A | P108: 4894 | Q108: #N/A N/A | R108: #N/A N/A
B109: 37986 | C109: 28.6 | D109: #N/A N/A | E109: 58655.58 | F109: 55463.58 | G109: 16.0674 | H109: 41.295 | I109: 20894 | J109: #N/A N/A | K109: 3.9161 | L109: 1939.286 | M109: 23.5421 | N109: #N/A N/A | O109: #N/A N/A | P109: 5905 | Q109: #N/A N/A | R109: #N/A N/A
B110: 38352 | C110: 25.62 | D110: #N/A N/A | E110: 52718.465 | F110: 49846.465 | G110: 15.0706 | H110: 38.6555 | I110: 19380 | J110: #N/A N/A | K110: 4.3716 | L110: 1945.608 | M110: -10.4196 | N110: #N/A N/A | O110: #N/A N/A | P110: 5608 | Q110: #N/A N/A | R110: #N/A N/A
B111: 38716 | C111: 22.98 | D111: #N/A N/A | E111: 47756.844 | F111: 44960.844 | G111: 16.0699 | H111: 34.2104 | I111: 19207 | J111: #N/A N/A | K111: 4.8738 | L111: 1956.521 | M111: -10.3044 | N111: #N/A N/A | O111: #N/A N/A | P111: 5054 | Q111: #N/A N/A | R111: #N/A N/A
B112: 39080 | C112: 26.32 | D112: #N/A N/A | E112: 55186.285 | F112: 51764.285 | G112: 26.0594 | H112: 29.0348 | I112: 17256 | J112: #N/A N/A | K112: 4.2553 | L112: 1966.728 | M112: 14.5344 | N112: #N/A N/A | O112: #N/A N/A | P112: 3313 | Q112: #N/A N/A | R112: #N/A N/A
B113: 39447 | C113: 26.52 | D113: #N/A N/A | E113: 56517.124 | F113: 52470.124 | G113: 20.8819 | H113: 28.05 | I113: 18193 | J113: #N/A N/A | K113: 4.2232 | L113: 1978.511 | M113: 0.7599 | N113: #N/A N/A | O113: #N/A N/A | P113: 4059 | Q113: #N/A N/A | R113: #N/A N/A
B114: 39813 | C114: 23.25 | D114: #N/A N/A | E114: 44278.972 | F114: 46025.972 | G114: 12.9888 | H114: 26.8253 | I114: 17715 | J114: #N/A N/A | K114: 5.3333 | L114: 1979.612 | M114: -12.3303 | N114: #N/A N/A | O114: #N/A N/A | P114: 4382 | Q114: #N/A N/A | R114: #N/A N/A
B115: 40178 | C115: 25.25 | D115: #N/A N/A | E115: 38384.285 | F115: 43220.285 | G115: 15.0361 | H115: 25.049 | I115: 18808 | J115: #N/A N/A | K115: 4.9505 | L115: 1711.694 | M115: 8.6022 | N115: #N/A N/A | O115: #N/A N/A | P115: 5378 | Q115: #N/A N/A | R115: #N/A N/A
B116: 40543 | C116: 26.48 | D116: #N/A N/A | E116: 40003.427 | F116: 45325.427 | G116: 13.4423 | H116: 24.274 | I116: 19484 | J116: #N/A N/A | K116: 4.8338 | L116: 1711.685 | M116: 4.8713 | N116: #N/A N/A | O116: #N/A N/A | P116: 6585 | Q116: #N/A N/A | R116: #N/A N/A
...

Sheet 3.5 US GDP Growth Rate
B4: Security | C4: GDPGAUSA Index
B5: Start Date | C5: 35430
B6: End Date | C6: 42369
B7: Period | C7: Y
B9: Date | C9: PX_LAST | D9: PX_MID
B10: =_xll.BDH(C4,C9:D9,C5,C6,"Dir=V","Dts=S","Sort=D","Quote=C","QtTyp=P","Days=T",CONCATENATE("Per=c",C7),"DtFmt=D","UseDPDF=Y","cols=3;rows=20") -> #NAME? | C10: 2.86 | D10: 2.86
B11: 42004 | C11: 2.57 | D11: 2.57
B12: 41639 | C12: 1.68 | D12: 1.68
B13: 41274 | C13: 2.22 | D13: 2.22
B14: 40908 | C14: 1.6 | D14: 1.6
B15: 40543 | C15: 2.53 | D15: 2.53
B16: 40178 | C16: -2.78 | D16: -2.78
B17: 39813 | C17: -0.29 | D17: -0.29
B18: 39447 | C18: 1.78 | D18: 1.78
B19: 39082 | C19: 2.67 | D19: 2.67
B20: 38717 | C20: 3.35 | D20: 3.35
B21: 38352 | C21: 3.79 | D21: 3.79
B22: 37986 | C22: 2.81 | D22: 2.81
... B29: 35430 | C29: 3.8 | D29: 0.038
B30: Source: Bloomberg
B32: Average used for calculations | D32: =AVERAGE(D24:D29) -> 0.0375

Sheet 3.6 US Inflation Growth Rate
C3: CPI-All Urban Consumers (Current Series)
C4: 12-Month Percent Change
C6: Series Id: | D6: CUUR0000SA0L1E
C7: Not Seasonally Adjusted
C8: Series Title: | D8: All items less food and energy in U.S. city average, all urban consumers, not seasonally adjusted
C9: Area: | D9: U.S. city average
C10: Item: | D10: All items less food and energy
C11: Base Period: | D11: 1982-84=100
C12: Years: | D12: 1995 to 2018
C14: Year | D14: Jan | E14: Feb | F14: Mar | G14: Apr | H14: May | I14: Jun | J14: Jul | K14: Aug | L14: Sep | M14: Oct | N14: Nov | O14: Dec | P14: HALF1 | Q14: HALF2
C15: 1995 | D15: 2.9 | E15: 3 | F15: 3 | G15: 3.1 | H15: 3.1 | I15: 3 | J15: 3 | K15: 2.9 | L15: 2.9 | M15: 3 | N15: 3 | O15: 3 | P15: 3 | Q15: 3
C16: 1996 | D16: 3 | E16: 2.9 | F16: 2.8 | G16: 2.7 | H16: 2.7 | I16: 2.7 | J16: 2.7 | K16: 2.6 | L16: 2.7 | M16: 2.6 | N16: 2.6 | O16: 2.6 | P16: 2.7 | Q16: 2.7
C17: 1997 | D17: 2.5 | E17: 2.5 | F17: 2.5 | G17: 2.7 | H17: 2.5 | I17: 2.4 | J17: 2.4 | K17: 2.3 | L17: 2.2 | M17: 2.3 | N17: 2.2 | O17: 2.2 | P17: 2.6 | Q17: 2.2
C18: 1998 | D18: 2.2 | E18: 2.3 | F18: 2.1 | G18: 2.1 | H18: 2.2 | I18: 2.2 | J18: 2.2 | K18: 2.5 | L18: 2.5 | M18: 2.3 | N18: 2.3 | O18: 2.4 | P18: 2.2 | Q18: 2.4
C19: 1999 | D19: 2.4 | E19: 2.1 | F19: 2.1 | G19: 2.2 | H19: 2 | I19: 2.1 | J19: 2.1 | K19: 1.9 | L19: 2 | M19: 2.1 | N19: 2.1 | O19: 1.9 | P19: 2.1 | Q19: 2
C20: 2000 | D20: 2 | E20: 2.2 | F20: 2.4 | G20: 2.3 | H20: 2.4 | I20: 2.5 | J20: 2.5 | K20: 2.6 | L20: 2.6 | M20: 2.5 | N20: 2.6 | O20: 2.6 | P20: 2.3 | Q20: 2.5
C21: 2001 | D21: 2.6 | E21: 2.7 | F21: 2.7 | G21: 2.6 | H21: 2.5 | I21: 2.7 | J21: 2.7 | K21: 2.7 | L21: 2.6 | M21: 2.6 | N21: 2.8 | O21: 2.7 | P21: 2.6 | Q21: 2.7
C22: 2002 | D22: 2.6 | E22: 2.6 | F22: 2.4 | G22: 2.5 | H22: 2.5 | I22: 2.3 | J22: 2.2 | K22: 2.4 | L22: 2.2 | M22: 2.2 | N22: 2 | O22: 1.9 | P22: 2.5 | Q22: 2.2
C23: 2003 | D23: 1.9 | E23: 1.7 | F23: 1.7 | G23: 1.5 | H23: 1.6 | I23: 1.5 | J23: 1.5 | K23: 1.3 | L23: 1.2 | M23: 1.3 | N23: 1.1 | O23: 1.1 | P23: 1.7 | Q23: 1.3
C24: 2004 | D24: 1.1 | E24: 1.2 | F24: 1.6 | G24: 1.8 | H24: 1.7 | I24: 1.9 | J24: 1.8 | K24: 1.7 | L24: 2 | M24: 2 | N24: 2.2 | O24: 2.2 | P24: 1.6 | Q24: 2
C25: 2005 | D25: 2.3 | E25: 2.4 | F25: 2.3 | G25: 2.2 | H25: 2.2 | I25: 2 | J25: 2.1 | K25: 2.1 | L25: 2 | M25: 2.1 | N25: 2.1 | O25: 2.2 | P25: 2.2 | Q25: 2.1
C26: 2006 | D26: 2.1 | E26: 2.1 | F26: 2.1 | G26: 2.3 | H26: 2.4 | I26: 2.6 | J26: 2.7 | K26: 2.8 | L26: 2.9 | M26: 2.7 | N26: 2.6 | O26: 2.6 | P26: 2.2 | Q26: 2.7
... C37: 2017 | D37: 2.3 | E37: 2.2 | F37: 2 | G37: 1.9 | H37: 1.7 | I37: 1.7 | J37: 1.7 | K37: 1.7 | L37: 1.7 | M37: 1.8 | N37: 1.7 | O37: 1.8 | P37: 2 | Q37: 1.7
C38: 2018 | D38: 1.8 | E38: 1.8 | F38: 2.1
C39: Source:https://data.bls.gov/pdq/SurveyOutputServlet
C41: Average Inflation Rate United States of America 2001 | F41: =AVERAGE(D21:O21) -> 2.6583333 | G41: =0.027 -> 0.027
C42: Average Inflation Rate United States of America 2001
