Workbook
Name acq: [1]Assumptions!$H$8
Name acq_fye: [1]Assumptions!$H$32
Name acq_price: [1]Assumptions!$J$11
Name assume: [1]Assumptions!$T$11
Name base_year: [2]Control!$D$11
Name case: [1]Assumptions!$T$7
Name cash_rate: [1]Assumptions!$T$20
Name circ: [2]Control!$D$13
Name curr: [2]Control!$D$9
Name debt_rate: [1]Assumptions!$T$16
Name eps: [1]Assumptions!$T$41
Name fees: [1]Assumptions!$T$24
Name libor: [3]LBO!$AF$34
Name min_cash: [1]Assumptions!$T$21
Name pct_cash: [1]Assumptions!$T$8
Name project: [2]Control!$D$5
Name sec_338: [1]Assumptions!$T$13
Name synergies: [1]Assumptions!$T$28
Name tax_rate: [1]Assumptions!$T$39
Name tgt: [1]Assumptions!$L$8
Name tgt_price: [1]Assumptions!$N$11
Name type: [1]Assumptions!$T$12
Name year: [1]Assumptions!$T$40

Sheet Overview
B2: Finance and Economics of M&A
B4: Acquisition of Pharmacia Corporation by Pfizer Inc.
B6: Pharmacia LLC Standalone Valuation
B17: by
B19: Marc Schwarz
B25: EBS Universität für Wirtschaft und Recht
B26: Spring Term 2018

Sheet 1. DATA>>>>

Sheet 1.1 Balance Sheet Raw
A2: Pharmacia LLC (748957Q US) - Balance Sheet
A4: In Millions of USD except Per Share | C4: FY 1987 | D4: FY 1988 | E4: FY 1989 | F4: FY 1990 | G4: FY 1991 | H4: FY 1992 | I4: FY 1993 | J4: FY 1994 | K4: FY 1995 | L4: FY 1996 | M4: FY 1997 | N4: FY 1998 | O4: FY 1999 | P4: FY 2000 | Q4: FY 2001 | R4: FY 2002
A5: 12 Months Ending | C5: 12/31/1987 | D5: 12/31/1988 | E5: 12/31/1989 | F5: 12/31/1990 | G5: 01/01/1992 | H5: 12/31/1992 | I5: 12/31/1993 | J5: 12/31/1994 | K5: 12/31/1995 | L5: 12/31/1996 | M5: 12/31/1997 | N5: 12/31/1998 | O5: 12/31/1999 | P5: 12/31/2000 | Q5: 12/31/2001 | R5: 12/31/2002
A6: Assets
A7: + Cash & Near Cash Items | B7: BS_CASH_NEAR_CASH_ITEM | C7: 180 | D7: 203 | E7: 198 | F7: 183 | G7: 189 | H7: 729 | I7: 273 | J7: 507 | K7: 297 | L7: 166 | M7: 134 | N7: 89 | O7: 1600 | P7: 2035 | Q7: 1276 | R7: 2241
A8: + Short-Term Investments | B8: BS_MKT_SEC_OTHER_ST_INVEST | C8: 43 | D8: 18 | E8: 55 | F8: 21 | G8: — | H8: — | I8: 0 | J8: 0 | K8: 0 | L8: 0 | M8: 0 | N8: 0 | O8: 138 | P8: 35 | Q8: 119 | R8: 469
A9: + Accounts & Notes Receivable | B9: BS_ACCT_NOTE_RCV | C9: 1209 | D9: 1234 | E9: 1309 | F9: 1498 | G9: 1594 | H9: 1405 | I9: 1445 | J9: 1530 | K9: 1629 | L9: 1515 | M9: 1823 | N9: 2119 | O9: 4131 | P9: 2510 | Q9: 2433 | R9: 2457
A10: + Inventories | B10: BS_INVENTORIES | C10: 1081 | D10: 1170 | E10: 1197 | F10: 1270 | G10: 1349 | H10: 1156 | I10: 1224 | J10: 1212 | K10: 1368 | L10: 1183 | M10: 1374 | N10: 1722 | O10: 2905 | P10: 1519 | Q10: 1683 | R10: 2177
A11: + Other Current Assets | B11: BS_OTHER_CUR_ASSET | C11: 490 | D11: 472 | E11: 489 | F11: 541 | G11: 579 | H11: 770 | I11: 730 | J11: 634 | K11: 1011 | L11: 1476 | M11: 935 | N11: 1265 | O11: 1908 | P11: 2139 | Q11: 2152 | R11: 1936
A12: Total Current Assets | B12: BS_CUR_ASSET_REPORT | C12: 3003 | D12: 3097 | E12: 3248 | F12: 3513 | G12: 3711 | H12: 4060 | I12: 3672 | J12: 3883 | K12: 4305 | L12: 4340 | M12: 4266 | N12: 5195 | O12: 10682 | P12: 8238 | Q12: 7663 | R12: 9280
A13: + LT Investments & LT Receivables | B13: BS_LT_INVEST | C13: 240 | D13: 205 | E13: 204 | F13: 248 | G13: 0 | H13: 0 | I13: 0 | J13: 0 | K13: 0 | L13: 0 | M13: 0 | N13: 0 | O13: 476 | P13: 349 | Q13: 288 | R13: 287
A14: + Net Fixed Assets | B14: BS_NET_FIX_ASSET | C14: 3076 | D14: 3146 | E14: 3173 | F14: 3492 | G14: 3191 | H14: 3005 | I14: 2802 | J14: 2817 | K14: 2832 | L14: 2095 | M14: 2400 | N14: 2865 | O14: 6825 | P14: 4512 | Q14: 4856 | R14: 5683
A15: + Gross Fixed Assets | B15: BS_GROSS_FIX_ASSET | C15: 6730 | D15: 6926 | E15: 6937 | F15: 7620 | G15: 7510 | H15: 7602 | I15: 7382 | J15: 7555 | K15: 7237 | L15: 4428 | M15: 4701 | N15: 5185 | O15: 11758 | P15: 7915 | Q15: 8248 | R15: 9688
A16: - Accumulated Depreciation | B16: BS_ACCUM_DEPR | C16: 3654 | D16: 3780 | E16: 3764 | F16: 4128 | G16: 4319 | H16: 4597 | I16: 4580 | J16: 4738 | K16: 4405 | L16: 2333 | M16: 2301 | N16: 2320 | O16: 4933 | P16: 3403 | Q16: 3392 | R16: 4005
A17: + Other Long-Term Assets | B17: BS_OTHER_ASSETS_DEF_CHRG_OTHER | C17: 2136 | D17: 2013 | E17: 1979 | F17: 1983 | G17: 2325 | H17: 2020 | I17: 2166 | J17: 2191 | K17: 3474 | L17: 4802 | M17: 4108 | N17: 8325 | O17: 9211 | P17: 9678 | Q17: 9570 | R17: 3267
A18: Total Long-Term Assets | B18: BS_TOT_NON_CUR_ASSET | C18: 5452 | D18: 5364 | E18: 5356 | F18: 5723 | G18: 5516 | H18: 5025 | I18: 4968 | J18: 5008 | K18: 6306 | L18: 6897 | M18: 6508 | N18: 11190 | O18: 16512 | P18: 14539 | Q18: 14714 | R18: 9237
A19: Total Assets | B19: BS_TOT_ASSET | C19: 8455 | D19: 8461 | E19: 8604 | F19: 9236 | G19: 9227 | H19: 9085 | I19: 8640 | J19: 8891 | K19: 10611 | L19: 11237 | M19: 10774 | N19: 16385 | O19: 27194 | P19: 22777 | Q19: 22377 | R19: 18517
A21: Liabilities & Shareholders' Equity
A22: + Accounts Payable | B22: BS_ACCT_PAYABLE | C22: 527 | D22: 545 | E22: 514 | F22: 584 | G22: 530 | H22: 525 | I22: 538 | J22: 629 | K22: 648 | L22: 479 | M22: 480 | N22: 823 | O22: 1272 | P22: 836 | Q22: 1048 | R22: 780
A23: + Short-Term Borrowings | B23: BS_ST_BORROW | C23: 539 | D23: 556 | E23: 505 | F23: 582 | G23: 335 | H23: 257 | I23: 223 | J23: 312 | K23: 365 | L23: 654 | M23: 1726 | N23: 1069 | O23: 1992 | P23: 675 | Q23: 470 | R23: 854
A24: + Other Short-Term Liabilities | B24: BS_OTHER_ST_LIAB | C24: 734 | D24: 879 | E24: 903 | F24: 1024 | G24: 1310 | H24: 1766 | I24: 1534 | J24: 1494 | K24: 1799 | L24: 2268 | M24: 1333 | N24: 1888 | O24: 3910 | P24: 3555 | Q24: 3471 | R24: 3346
A25: Total Current Liabilities | B25: BS_CUR_LIAB | C25: 1800 | D25: 1980 | E25: 1922 | F25: 2190 | G25: 2175 | H25: 2548 | I25: 2295 | J25: 2435 | K25: 2812 | L25: 3401 | M25: 3539 | N25: 3780 | O25: 7174 | P25: 5066 | Q25: 4989 | R25: 4980
A26: + Long-Term Borrowings | B26: BS_LT_BORROW | C26: 1564 | D26: 1408 | E26: 1471 | F26: 1652 | G26: 1871 | H26: 1423 | I26: 1502 | J26: 1405 | K26: 1667 | L26: 1608 | M26: 1979 | N26: 6259 | O26: 6236 | P26: 3624 | Q26: 2612 | R26: 2585
A27: + Other Long-Term Liabilities | B27: BS_OTHER_LT_LIABILITIES | C27: 1190 | D27: 1273 | E27: 1270 | F27: 1305 | G27: 1527 | H27: 2109 | I27: 1988 | J27: 2103 | K27: 2400 | L27: 2538 | M27: 1152 | N27: 1360 | O27: 2873 | P27: 2166 | Q27: 2386 | R27: 2969
A28: Total Long-Term Liabilities | B28: NON_CUR_LIAB | C28: 2754 | D28: 2681 | E28: 2741 | F28: 2957 | G28: 3398 | H28: 3532 | I28: 3490 | J28: 3508 | K28: 4067 | L28: 4146 | M28: 3131 | N28: 7619 | O28: 9109 | P28: 5790 | Q28: 4998 | R28: 5554
A29: Total Liabilities | B29: BS_TOT_LIAB2 | C29: 4554 | D29: 4661 | E29: 4663 | F29: 5147 | G29: 5573 | H29: 6080 | I29: 5785 | J29: 5943 | K29: 6879 | L29: 7547 | M29: 6670 | N29: 11399 | O29: 16283 | P29: 10856 | Q29: 9987 | R29: 10534
A30: + Total Preferred Equity | B30: BS_PFD_EQTY_&_HYBRID_CPTL | C30: — | D30: — | E30: — | F30: — | G30: — | H30: 0 | I30: 0 | J30: 0 | K30: 0 | L30: 0 | M30: 0 | N30: 0 | O30: 270 | P30: 263 | Q30: 258 | R30: 247
A31: + Minority Interest | B31: MINORITY_NONCONTROLLING_INTEREST | C31: — | D31: — | E31: — | F31: — | G31: — | H31: 0 | I31: 0 | J31: 0 | K31: 0 | L31: 0 | M31: 0 | N31: 0 | O31: 0 | P31: 0 | Q31: 0 | R31: 0
A32: + Share Capital & APIC | B32: BS_SH_CAP_AND_APIC | C32: 1036 | D32: 1038 | E32: 1041 | F32: 1043 | G32: 1055 | H32: 1149 | I32: 1155 | J32: 1178 | K32: 1231 | L32: 1709 | M32: 1965 | N32: 3083 | O32: 4722 | P32: 5667 | Q32: 6469 | R32: 6626
A33: + Retained Earnings & Other Equity | B33: BS_RETAIN_EARN | C33: 2865 | D33: 2762 | E33: 2900 | F33: 3046 | G33: 2599 | H33: 1856 | I33: 1700 | J33: 1770 | K33: 2501 | L33: 1981 | M33: 2139 | N33: 1903 | O33: 5919 | P33: 5991 | Q33: 5663 | R33: 1110
A34: Total Equity | B34: TOTAL_EQUITY | C34: 3901 | D34: 3800 | E34: 3941 | F34: 4089 | G34: 3654 | H34: 3005 | I34: 2855 | J34: 2948 | K34: 3732 | L34: 3690 | M34: 4104 | N34: 4986 | O34: 10911 | P34: 11921 | Q34: 12390 | R34: 7983
A35: Total Liabilities & Equity | B35: TOT_LIAB_AND_EQY | C35: 8455 | D35: 8461 | E35: 8604 | F35: 9236 | G35: 9227 | H35: 9085 | I35: 8640 | J35: 8891 | K35: 10611 | L35: 11237 | M35: 10774 | N35: 16385 | O35: 27194 | P35: 22777 | Q35: 22377 | R35: 18517
A37: Reference Items
A38: Accounting Standard | B38: ACCOUNTING_STANDARD | C38: US GAAP | D38: US GAAP | E38: US GAAP | F38: US GAAP | G38: US GAAP | H38: US GAAP | I38: US GAAP | J38: US GAAP | K38: US GAAP | L38: US GAAP | M38: US GAAP | N38: US GAAP | O38: US GAAP | P38: US GAAP | Q38: US GAAP | R38: US GAAP
A39: Shares Outstanding | B39: BS_SH_OUT | C39: 740 | D39: 690 | E39: 660 | F39: 630 | G39: 614.63745 | H39: 602.31998 | I39: 579.87999 | J39: 557.67502 | K39: 589.07501 | L39: 584.37598 | M39: 595.28497 | N39: 629.29498 | O39: 1284 | P39: 1299.8 | Q39: 1297.259 | R39: 1295.752
A40: Number of Treasury Shares | B40: BS_NUM_OF_TSY_SH | C40: 81.000004 | D40: 134 | E40: 161 | F40: 192.99999 | G40: 207.33353 | H40: 219.65 | I40: 242.08999 | J40: 264.29501 | K40: 244.62 | L40: 237.595 | M40: 226.686 | N40: 217.632 | O40: — | P40: — | Q40: — | R40: —
A41: Amount of Treasury Shares | B41: BS_AMT_OF_TSY_STOCK | C41: 517 | D41: 952 | E41: 1244 | F41: 1563 | G41: 1797 | H41: 2029 | I41: 2348 | J41: 2744 | K41: 2550 | L41: 2661 | M41: 2570 | N41: 2508 | O41: 2432 | P41: 2003 | Q41: 2789 | R41: 3257
A42: Pension Obligations | B42: BS_PENSION_RSRV | C42: — | D42: — | E42: — | F42: — | G42: — | H42: — | I42: — | J42: — | K42: — | L42: — | M42: — | N42: — | O42: 1578 | P42: 1511 | Q42: 996 | R42: 1213
A43: Operating Leases | B43: BS_FUTURE_MIN_OPER_LEASE_OBLIG | C43: — | D43: — | E43: — | F43: — | G43: — | H43: — | I43: — | J43: — | K43: — | L43: — | M43: — | N43: — | O43: — | P43: 1041 | Q43: 675 | R43: 696
A44: Capital Leases - Short Term | B44: ST_CAPITAL_LEASE_OBLIGATIONS | C44: — | D44: — | E44: — | F44: — | G44: — | H44: — | I44: — | J44: — | K44: — | L44: — | M44: — | N44: — | O44: 0 | P44: 0 | Q44: 0 | R44: 0
A45: Capital Leases - Long Term | B45: LT_CAPITAL_LEASE_OBLIGATIONS | C45: — | D45: — | E45: — | F45: — | G45: — | H45: — | I45: — | J45: — | K45: — | L45: — | M45: — | N45: — | O45: 0 | P45: 0 | Q45: 0 | R45: 0
A46: Capital Leases - Total | B46: BS_TOTAL_CAPITAL_LEASES | C46: — | D46: — | E46: — | F46: — | G46: — | H46: — | I46: — | J46: — | K46: — | L46: — | M46: — | N46: — | O46: 0 | P46: 0 | Q46: 0 | R46: 0
A47: Options Granted During Period | B47: BS_OPTIONS_GRANTED | C47: — | D47: — | E47: — | F47: — | G47: — | H47: — | I47: — | J47: — | K47: — | L47: — | M47: — | N47: — | O47: 17.950001 | P47: 15.286 | Q47: 26.841999 | R47: 33.297001
A48: Options Outstanding at Period End | B48: BS_OPTIONS_OUTSTANDING | C48: — | D48: — | E48: — | F48: — | G48: — | H48: — | I48: — | J48: — | K48: — | L48: — | M48: — | N48: — | O48: 129.893 | P48: 103.318 | Q48: 117.971 | R48: 134.981
A49: Net Debt | B49: NET_DEBT | C49: 1880 | D49: 1743 | E49: 1723 | F49: 2030 | G49: 2017 | H49: 951 | I49: 1452 | J49: 1210 | K49: 1735 | L49: 2096 | M49: 3571 | N49: 7239 | O49: 6490 | P49: 2229 | Q49: 1687 | R49: 729
A50: Net Debt to Equity | B50: NET_DEBT_TO_SHRHLDR_EQTY | C50: 48.192771 | D50: 45.868421 | E50: 43.719868 | F50: 49.64539 | G50: 55.199781 | H50: 31.647255 | I50: 50.858144 | J50: 41.044776 | K50: 46.489818 | L50: 56.802168 | M50: 87.012671 | N50: 145.18652 | O50: 59.481257 | P50: 18.698096 | Q50: 13.615819 | R50: 9.131905
A51: Tangible Common Equity Ratio | B51: TCE_RATIO | C51: — | D51: — | E51: — | F51: — | G51: — | H51: — | I51: — | J51: — | K51: — | L51: — | M51: 15.96321 | N51: -2.6567 | O51: 22.642303 | P51: 47.363189 | Q51: 50.919805 | R51: 36.485213
A52: Current Ratio | B52: CUR_RATIO | C52: 1.668333 | D52: 1.564141 | E52: 1.689906 | F52: 1.60411 | G52: 1.706207 | H52: 1.593407 | I52: 1.6 | J52: 1.594661 | K52: 1.530939 | L52: 1.276095 | M52: 1.205425 | N52: 1.374339 | O52: 1.488988 | P52: 1.626135 | Q52: 1.535979 | R52: 1.863454
A53: Cash Conversion Cycle | B53: CASH_CONVERSION_CYCLE | C53: — | D53: 97.997464 | E53: 101.07616 | F53: 104.01286 | G53: 133.02099 | H53: 124.94037 | I53: 119.10864 | J53: 114.03436 | K53: 112.22552 | L53: 182.03757 | M53: 178.71822 | N53: 220.49548 | O53: 169.3982 | P53: 119.4117 | Q53: 152.00105 | R53: 199.29505
A54: Inventory - Raw Materials | B54: INVTRY_RAW_MATERIALS | C54: — | D54: — | E54: — | F54: — | G54: — | H54: — | I54: — | J54: — | K54: — | L54: — | M54: 390 | N54: 224 | O54: 1794 | P54: 1415 | Q54: 1662 | R54: 2224
A55: Inventory - Work in Progress | B55: INVTRY_IN_PROGRESS | C55: — | D55: — | E55: — | F55: — | G55: — | H55: — | I55: — | J55: — | K55: — | L55: — | M55: 265 | N55: 469 | O55: — | P55: — | Q55: — | R55: —
A56: Inventory - Finished Goods | B56: INVTRY_FINISHED_GOODS | C56: — | D56: — | E56: — | F56: — | G56: — | H56: — | I56: — | J56: — | K56: — | L56: — | M56: 762 | N56: 1064 | O56: 1281 | P56: 289 | Q56: 202 | R56: 182
A57: Other Inventory/Allowances | B57: BS_OTHER_INV | C57: — | D57: — | E57: — | F57: — | G57: — | H57: — | I57: — | J57: — | K57: — | L57: — | M57: — | N57: -35 | O57: -170 | P57: -185 | Q57: -180 | R57: -229
A58: Pure Retained Earnings | B58: BS_PURE_RETAINED_EARNINGS | C58: — | D58: — | E58: — | F58: — | G58: — | H58: — | I58: — | J58: — | K58: — | L58: — | M58: — | N58: — | O58: — | P58: 10781 | Q58: 11586 | R58: 6950
A59: Goodwill | B59: BS_GOODWILL | C59: — | D59: — | E59: — | F59: — | G59: — | H59: — | I59: — | J59: — | K59: — | L59: — | M59: 0 | N59: 0 | O59: 4402 | P59: 1279 | Q59: 1059 | R59: 1150
A60: Number of Employees | B60: NUM_OF_EMPLOYEES | C60: 49734 | D60: 45635 | E60: 42179 | F60: 41081 | G60: 39281 | H60: 33797 | I60: 30019 | J60: 29354 | K60: 28500 | L60: 28000 | M60: 21900 | N60: 31800 | O60: 29900 | P60: 59000 | Q60: 59600 | R60: 43000
A61: Source: Bloomberg

Sheet 1.2 Income Statement Raw
A2: Pharmacia LLC (748957Q US) - Income Statement
A4: In Millions of USD except Per Share | C4: FY 1987 | D4: FY 1988 | E4: FY 1989 | F4: FY 1990 | G4: FY 1991 | H4: FY 1992 | I4: FY 1993 | J4: FY 1994 | K4: FY 1995 | L4: FY 1996 | M4: FY 1997 | N4: FY 1998 | O4: FY 1999 | P4: FY 2000 | Q4: FY 2001 | R4: FY 2002 | S4: Current
A5: 12 Months Ending | C5: 12/31/1987 | D5: 12/31/1988 | E5: 12/31/1989 | F5: 12/31/1990 | G5: 01/01/1992 | H5: 12/31/1992 | I5: 12/31/1993 | J5: 12/31/1994 | K5: 12/31/1995 | L5: 12/31/1996 | M5: 12/31/1997 | N5: 12/31/1998 | O5: 12/31/1999 | P5: 12/31/2000 | Q5: 12/31/2001 | R5: 12/31/2002 | S5: 04/09/2018
A6: Revenue | B6: SALES_REV_TURN | C6: 7639 | D6: 8293 | E6: 8681 | F6: 8995 | G6: 7936 | H6: 7763 | I6: 7902 | J6: 8272 | K6: 8962 | L6: 6348 | M6: 7514 | N6: 7237 | O6: 16425 | P6: 12651 | Q6: 13835 | R6: 13993
A7: - Cost of Revenue | B7: IS_COGS_TO_FE_AND_PP_AND_G | C7: 4755 | D7: 4972 | E7: 5035 | F7: 5366 | G7: 4519 | H7: 4710 | I7: 4564 | J7: 4774 | K7: 5109 | L7: 2684 | M7: 3091 | N7: 2912 | O7: 5319 | P7: 2886 | Q7: 2978 | R7: 3077
A8: Gross Profit | B8: GROSS_PROFIT | C8: 2884 | D8: 3321 | E8: 3646 | F8: 3629 | G8: 3417 | H8: 3053 | I8: 3338 | J8: 3498 | K8: 3853 | L8: 3664 | M8: 4423 | N8: 4325 | O8: 11106 | P8: 9765 | Q8: 10857 | R8: 10916
A9: - Operating Expenses | B9: IS_OPERATING_EXPN | C9: 2182 | D9: 2366 | E9: 2568 | F9: 2720 | G9: 2485 | H9: 2559 | I9: 2523 | J9: 2535 | K9: 2712 | L9: 2713 | M9: 3240 | N9: 3723 | O9: 8937 | P9: 7766 | Q9: 8366 | R9: 8538
A10: Operating Income or Losses | B10: IS_OPER_INC | C10: 702 | D10: 955 | E10: 1078 | F10: 909 | G10: 932 | H10: 494 | I10: 815 | J10: 963 | K10: 1141 | L10: 951 | M10: 1183 | N10: 602 | O10: 2169 | P10: 1999 | Q10: 2491 | R10: 2378
A11: - Interest Expense | B11: IS_INT_EXPENSE | C11: 172 | D11: 174 | E11: 182 | F11: 179 | G11: 166 | H11: 169 | I11: 129 | J11: 131 | K11: 190 | L11: 119 | M11: 170 | N11: 210 | O11: 408 | P11: 182 | Q11: 255 | R11: 154
A12: - Foreign Exchange Losses (Gains) | B12: IS_FOREIGN_EXCH_LOSS | C12: 11 | D12: 20 | E12: 31 | F12: 45 | G12: 10 | H12: 39 | I12: 6 | J12: 23 | K12: 9 | L12: 6 | M12: 68 | N12: 0 | O12: 0 | P12: 0 | Q12: 0 | R12: 0
A13: - Net Non-Operating Losses (Gains) | B13: IS_NET_NON_OPER_LOSS | C13: -154 | D13: -132 | E13: -150 | F13: -124 | G13: 402 | H13: 460 | I13: -49 | J13: -86 | K13: -145 | L13: 273 | M13: 579 | N13: 477 | O13: -137 | P13: 777 | Q13: 645 | R13: -1082
A14: Pretax Income | B14: PRETAX_INC | C14: 673 | D14: 893 | E14: 1015 | F14: 809 | G14: 354 | H14: -174 | I14: 729 | J14: 895 | K14: 1087 | L14: 553 | M14: 366 | N14: -85 | O14: 1898 | P14: 1040 | Q14: 1591 | R14: 3306
A15: - Income Tax Expense (Benefit) | B15: IS_INC_TAX_EXP | C15: 237 | D15: 302 | E15: 336 | F15: 263 | G15: 116 | H15: -48 | I15: 235 | J15: 273 | K15: 348 | L15: 140 | M15: 72 | N15: 46 | O15: 592 | P15: 236 | Q15: 298 | R15: 869
A16: Income Before XO Items | B16: IS_INC_BEF_XO_ITEM | C16: 436 | D16: 591 | E16: 679 | F16: 546 | G16: 238 | H16: -126 | I16: 494 | J16: 622 | K16: 739 | L16: 413 | M16: 294 | N16: -131 | O16: 1306 | P16: 804 | Q16: 1293 | R16: 2437
A17: - Extraordinary Loss Net of Tax | B17: XO_GL_NET_OF_TAX | C17: — | D17: — | E17: — | F17: — | G17: -58 | H17: -38 | I17: 0 | J17: 0 | K17: 0 | L17: 28 | M17: -176 | N17: 119 | O17: -72 | P17: 87 | Q17: -208 | R17: 1840
A18: - Minority/Non Controlling Interests (Credits) | B18: MIN_NONCONTROL_INTEREST_CREDITS | C18: — | D18: — | E18: — | F18: — | G18: 0 | H18: 0 | I18: 0 | J18: 0 | K18: 0 | L18: 0 | M18: 0 | N18: 0 | O18: 0 | P18: 0 | Q18: 0 | R18: 0
A19: Net Income/Net Profit (Losses) | B19: NET_INCOME | C19: 436 | D19: 591 | E19: 679 | F19: 546 | G19: 296 | H19: -88 | I19: 494 | J19: 622 | K19: 739 | L19: 385 | M19: 470 | N19: -250 | O19: 1378 | P19: 717 | Q19: 1501 | R19: 597
A20: - Total Cash Preferred Dividends | B20: IS_TOT_CASH_PFD_DVD | C20: — | D20: — | E20: — | F20: — | G20: 0 | H20: 0 | I20: 0 | J20: 0 | K20: 0 | L20: 0 | M20: 0 | N20: 0 | O20: 0 | P20: 0 | Q20: 0 | R20: 0
A21: - Other Adjustments | B21: OTHER_ADJUSTMENTS | C21: — | D21: — | E21: — | F21: — | G21: — | H21: — | I21: — | J21: — | K21: — | L21: — | M21: — | N21: — | O21: 0 | P21: 0 | Q21: 0 | R21: 0
A22: Net Inc Avail to Common Shareholders | B22: EARN_FOR_COMMON | C22: 436 | D22: 591 | E22: 679 | F22: 546 | G22: 296 | H22: -88 | I22: 494 | J22: 622 | K22: 739 | L22: 385 | M22: 470 | N22: -250 | O22: 1378 | P22: 717 | Q22: 1501 | R22: 597
A24: Abnormal Losses (Gains) | B24: IS_ABNORMAL_ITEM | C24: — | D24: — | E24: — | F24: — | G24: — | H24: — | I24: — | J24: — | K24: — | L24: 257 | M24: 684 | N24: 830 | O24: 61 | P24: 1080 | Q24: 947 | R24: -616
A25: Tax Effect on Abnormal Items | B25: IS_TAX_EFF_ON_ABNORMAL_ITEM | C25: — | D25: — | E25: — | F25: — | G25: — | H25: — | I25: — | J25: — | K25: — | L25: 0 | M25: -229 | N25: — | O25: -3 | P25: -357 | Q25: -337 | R25: 232
A26: Normalized Income | B26: NORMALIZED_INCOME | C26: 436 | D26: 591 | E26: 679 | F26: 546 | G26: 238 | H26: -126 | I26: 494 | J26: 622 | K26: 739 | L26: 670 | M26: 749 | N26: 699 | O26: 1364 | P26: 1527 | Q26: 1903 | R26: 2053
A28: Basic EPS Before Abnormal Items | B28: IS_BASIC_EPS_CONT_OPS | C28: — | D28: — | E28: — | F28: 0.846 | G28: 0.374 | H28: -0.204 | I28: 0.82 | J28: 1.064 | K28: 1.272 | L28: 1.14 | M28: 1.25 | N28: 0.93 | O28: 1.15 | P28: 1.17 | Q28: 1.44 | R28: 1.59
A29: Basic EPS Before XO Items | B29: IS_EARN_BEF_XO_ITEMS_PER_SH | C29: 0.563 | D29: 0.827 | E29: 1.003 | F29: 0.846 | G29: 0.374 | H29: -0.204 | I29: 0.82 | J29: 1.064 | K29: 1.272 | L29: 0.71 | M29: 0.5 | N29: -0.22 | O29: 1.04 | P29: 0.62 | Q29: 0.98 | R29: 1.88
A30: Basic Earnings per Share | B30: IS_EPS | C30: 0.563 | D30: 0.827 | E30: 1.003 | F30: 0.846 | G30: 0.466 | H30: -0.142 | I30: 0.82 | J30: 1.064 | K30: 1.272 | L30: 0.66 | M30: 0.8 | N30: -0.41 | O30: 1.1 | P30: 0.55 | Q30: 1.14 | R30: 0.45
A31: Basic Weighted Avg Shares | B31: IS_AVG_NUM_SH_FOR_EPS | C31: 775 | D31: 715 | E31: 676.99997 | F31: 645.50003 | G31: 635.63 | H31: 617.22 | I31: 601.89999 | J31: 584.92501 | K31: 580.63999 | L31: 581.20001 | M31: 590.20001 | N31: 603.5 | O31: 1249 | P31: 1274 | Q31: 1298 | R31: 1293 | S31: 1293
A32: Diluted EPS Before Abnormal Items | B32: IS_DIL_EPS_CONT_OPS | C32: 0.563 | D32: 0.827 | E32: 1.003 | F32: 0.846 | G32: 0.374 | H32: -0.204 | I32: 0.82 | J32: 1.064 | K32: 1.272 | L32: 1.12 | M32: 1.23 | N32: 0.93 | O32: 1.12 | P32: 1.16 | Q32: 1.43 | R32: 1.55
A33: Diluted EPS Before XO Items | B33: IS_DIL_EPS_BEF_XO | C33: 0.563 | D33: 0.827 | E33: 1.003 | F33: 0.846 | G33: 0.374 | H33: -0.204 | I33: 0.82 | J33: 1.064 | K33: 1.272 | L33: 0.69 | M33: 0.48 | N33: -0.22 | O33: 1.01 | P33: 0.61 | Q33: 0.97 | R33: 1.84
A34: Diluted EPS | B34: IS_DILUTED_EPS | C34: 0.563 | D34: 0.827 | E34: 1.003 | F34: 0.846 | G34: 0.466 | H34: -0.142 | I34: 0.82 | J34: 1.064 | K34: 1.272 | L34: 0.64 | M34: 0.77 | N34: -0.41 | O34: 1.07 | P34: 0.54 | Q34: 1.12 | R34: 0.44
A35: Diluted Weighted Avg Shares | B35: IS_SH_FOR_DILUTED_EPS | C35: 775 | D35: 715 | E35: 676.99997 | F35: 645.50003 | G35: 635.63 | H35: 617.22 | I35: 601.89999 | J35: 584.92501 | K35: 580.63999 | L35: 598.90002 | M35: 610.5 | N35: 603.5 | O35: 1284 | P35: 1307 | Q35: 1322 | R35: 1315 | S35: 1316
A37: Reference Items
A38: Accounting Standard | B38: ACCOUNTING_STANDARD | C38: US GAAP | D38: US GAAP | E38: US GAAP | F38: US GAAP | G38: US GAAP | H38: US GAAP | I38: US GAAP | J38: US GAAP | K38: US GAAP | L38: US GAAP | M38: US GAAP | N38: US GAAP | O38: US GAAP | P38: US GAAP | Q38: US GAAP | R38: US GAAP
A39: EBITDA | B39: EBITDA | C39: 1381 | D39: 1658 | E39: 1768 | F39: 1648 | G39: 1683 | H39: 1259 | I39: 1387 | J39: 1524 | K39: 1739 | L39: 1374 | M39: 1670 | N39: 1120 | O39: 3314 | P39: 2632 | Q39: 3102 | R39: 2965
A40: EBITDA Margin (T12M) | B40: EBITDA_MARGIN | C40: 18.078282 | D40: 19.992765 | E40: 20.366317 | F40: 18.32129 | G40: 21.207157 | H40: 16.217957 | I40: 17.552518 | J40: 18.423598 | K40: 19.404151 | L40: 21.644612 | M40: 22.22518 | N40: 15.476026 | O40: 20.17656 | P40: 20.804679 | Q40: 22.421395 | R40: 21.189166
A41: Gross Margin | B41: GROSS_MARGIN | C41: 37.753633 | D41: 40.045822 | E41: 41.99977 | F41: 40.344636 | G41: 43.056956 | H41: 39.32758 | I41: 42.24247 | J41: 42.287234 | K41: 42.992636 | L41: 57.718967 | M41: 58.863455 | N41: 59.762332 | O41: 67.616438 | P41: 77.187574 | Q41: 78.474883 | R41: 78.010434
A42: Operating Margin | B42: OPER_MARGIN | C42: 9.189685 | D42: 11.515736 | E42: 12.417924 | F42: 10.105614 | G42: 11.743952 | H42: 6.363519 | I42: 10.313845 | J42: 11.641683 | K42: 12.731533 | L42: 14.981096 | M42: 15.743945 | N42: 8.318364 | O42: 13.205479 | P42: 15.801122 | Q42: 18.00506 | R42: 16.994211
A43: Profit Margin | B43: PROF_MARGIN | C43: 5.707553 | D43: 7.126492 | E43: 7.82168 | F43: 6.070039 | G43: 3.729839 | H43: -1.133582 | I43: 6.251582 | J43: 7.519342 | K43: 8.245927 | L43: 6.064902 | M43: 6.254991 | N43: -3.45447 | O43: 8.38965 | P43: 5.667536 | Q43: 10.849295 | R43: 4.266419
A44: Sales per Employee | B44: ACTUAL_SALES_PER_EMPL | C44: 153597.14 | D44: 181724.55 | E44: 205813.32 | F44: 218957.67 | G44: 202031.52 | H44: 229694.94 | I44: 263233.29 | J44: 281801.46 | K44: 314456.14 | L44: 226714.29 | M44: 343105.02 | N44: 227578.62 | O44: 549331.1 | P44: 214423.73 | Q44: 232130.87 | R44: 325418.6
A45: Dividends per Share | B45: EQY_DPS | C45: 0.275 | D45: 0.295 | E45: 0.33 | F45: 0.3325 | G45: 0.409 | H45: 0.44 | I45: 0.46 | J45: 0.494 | K45: 0.54 | L45: 0.588 | M45: 0.5 | N45: 0.12 | O45: 0.12 | P45: 0.405 | Q45: 0.525 | R45: 0.54
A46: Total Cash Common Dividends | B46: IS_TOT_CASH_COM_DVD | C46: 212 | D46: 211 | E46: 221 | F46: 242 | G46: 258 | H46: 268 | I46: 272 | J46: 286 | K46: 303 | L46: 342 | M46: 292 | N46: 73 | O46: 641 | P46: 622 | Q46: 651 | R46: 710.09998
A47: Interest Income | B47: IS_INT_INC | C47: — | D47: — | E47: — | F47: — | G47: — | H47: — | I47: — | J47: — | K47: — | L47: — | M47: — | N47: — | O47: 110 | P47: 124 | Q47: 110 | R47: 65
A48: Capitalized Interest Expense | B48: IS_CAP_INT_EXP | C48: 16 | D48: 19 | E48: 22 | F48: 29 | G48: 24 | H48: 16 | I48: 12 | J48: 10 | K48: 11 | L48: 9 | M48: 14 | N48: 14 | O48: 55 | P48: 63 | Q48: — | R48: —
A49: Research & Development Expense | B49: IS_RD_EXPEND | C49: 557 | D49: 575 | E49: 598 | F49: 612 | G49: 610 | H49: 651 | I49: 626 | J49: 609 | K49: 658 | L49: 702 | M49: 1044 | N49: 1238 | O49: 2815 | P49: 2165 | Q49: 2263 | R49: 2359
A50: Export Sales | B50: IS_EXPORT_SALES | C50: — | D50: — | E50: — | F50: — | G50: 473 | H50: 393 | I50: 435 | J50: 399 | K50: 550 | L50: 177 | M50: 200 | N50: 150 | O50: 0 | P50: 0 | Q50: 0 | R50: 0
A51: Depreciation Expense | B51: IS_DEPR_EXP | C51: 421 | D51: 435 | E51: 438 | F51: 465 | G51: 453 | H51: 473 | I51: 469 | J51: 442 | K51: 459 | L51: 276 | M51: 299 | N51: 269 | O51: 666 | P51: 728 | Q51: — | R51: —
A52: Source: Bloomberg

Sheet 1.3 Cash Flow - Standardized
A2: Pharmacia LLC (748957Q US) - Standardized
A4: In Millions of USD except Per Share | C4: FY 1987 | D4: FY 1988 | E4: FY 1989 | F4: FY 1990 | G4: FY 1991 | H4: FY 1992 | I4: FY 1993 | J4: FY 1994 | K4: FY 1995 | L4: FY 1996 | M4: FY 1997 | N4: FY 1998 | O4: FY 1999 | P4: FY 2000 | Q4: FY 2001 | R4: FY 2002 | S4: Current
A5: 12 Months Ending | C5: 12/31/1987 | D5: 12/31/1988 | E5: 12/31/1989 | F5: 12/31/1990 | G5: 01/01/1992 | H5: 12/31/1992 | I5: 12/31/1993 | J5: 12/31/1994 | K5: 12/31/1995 | L5: 12/31/1996 | M5: 12/31/1997 | N5: 12/31/1998 | O5: 12/31/1999 | P5: 12/31/2000 | Q5: 12/31/2001 | R5: 12/31/2002 | S5: 04/09/2018
A6: Cash From Operating Activities
A7: + Net Income | B7: CF_NET_INC | C7: 436 | D7: 591 | E7: 679 | F7: 546 | G7: 296 | H7: -88 | I7: 494 | J7: 622 | K7: 739 | L7: 385 | M7: 470 | N7: -250 | O7: 1378 | P7: 717 | Q7: 1501 | R7: 597
A8: + Depreciation & Amortization | B8: CF_DEPR_AMORT | C8: 679 | D8: 703 | E8: 690 | F8: 739 | G8: 751 | H8: 765 | I8: 572 | J8: 561 | K8: 598 | L8: 423 | M8: 487 | N8: 518 | O8: 1145 | P8: 633 | Q8: 611 | R8: 587
A9: + Other Non-Cash Adjustments | B9: CF_OTHER_NON_CASH_ADJUST | C9: -13 | D9: 39 | E9: · | F9: -113 | G9: 425 | H9: 476 | I9: -198 | J9: 241 | K9: -15 | L9: 601 | M9: 9 | N9: 1242 | O9: 166 | P9: 42 | Q9: -166 | R9: 1358
A10: + Changes in Non-Cash Capital | B10: CF_CHNG_NON_CASH_WORK_CAP | C10: -200 | D10: -29 | E10: -286 | F10: -68 | G10: -292 | H10: -241 | I10: -137 | J10: -124 | K10: -499 | L10: -206 | M10: -750 | N10: -1078 | O10: -872 | P10: -390 | Q10: -47 | R10: -1189
A11: Cash From Operations | B11: CF_CASH_FROM_OPER | C11: 902 | D11: 1304 | E11: 1037 | F11: 1104 | G11: 1180 | H11: 912 | I11: 731 | J11: 1300 | K11: 823 | L11: 1203 | M11: 216 | N11: 432 | O11: 1817 | P11: 1002 | Q11: 1899 | R11: 1353
A13: Cash From Investing Activities
A14: + Disposal of Fixed Assets | B14: CF_DISP_FIX_ASSET | C14: 75 | D14: 121 | E14: 307 | F14: 100 | G14: 324 | H14: 177 | I14: 298 | J14: 202 | K14: 128 | L14: 165 | M14: 88 | N14: 0 | O14: 0 | P14: — | Q14: — | R14: 0
A15: + Capital Expenditures | B15: CF_CAP_EXPEND_PRPTY_ADD | C15: -505 | D15: -590 | E15: -607 | F15: -750 | G15: -554 | H15: -586 | I15: -437 | J15: -409 | K15: -500 | L15: -500 | M15: -644 | N15: -859 | O15: -1678 | P15: -774 | Q15: -1020 | R15: -1142
A16: + Increase in Investments | B16: CF_INCR_INVEST | C16: — | D16: — | E16: — | F16: — | G16: 0 | H16: 0 | I16: 0 | J16: 0 | K16: 0 | L16: 0 | M16: 0 | N16: 0 | O16: -303 | P16: -138 | Q16: -262 | R16: 0
A17: + Decrease in Investments | B17: CF_DECR_INVEST | C17: — | D17: — | E17: — | F17: — | G17: 0 | H17: 0 | I17: 0 | J17: 0 | K17: 0 | L17: 0 | M17: 0 | N17: 0 | O17: 1013 | P17: 249 | Q17: 169 | R17: 1671
A18: + Other Investing Activities | B18: CF_OTHER_INV_ACT | C18: -59 | D18: -100 | E18: -211 | F18: -201 | G18: -215 | H18: 986 | I18: -510 | J18: -185 | K18: -913 | L18: -920 | M18: -1987 | N18: -4236 | O18: 268 | P18: 1385 | Q18: 252 | R18: -314
A19: Cash From Investing Activities | B19: CF_CASH_FROM_INV_ACT | C19: -489 | D19: -569 | E19: -511 | F19: -851 | G19: -445 | H19: 577 | I19: -649 | J19: -392 | K19: -1285 | L19: -1255 | M19: -2543 | N19: -5095 | O19: -700 | P19: 722 | Q19: -861 | R19: 215
A21: Cash from Financing Activities
A22: + Dividends Paid | B22: CF_DVD_PAID | C22: -212 | D22: -211 | E22: -221 | F22: -242 | G22: -258 | H22: -270 | I22: -275 | J22: -289 | K22: -306 | L22: -343 | M22: -294 | N22: -73 | O22: -641 | P22: -622 | Q22: -651 | R22: -711
A23: + Change in Short-Term Borrowings | B23: CF_INCR_ST_BORROW | C23: 150 | D23: 53 | E23: -50 | F23: 77 | G23: -245 | H23: -78 | I23: -31 | J23: 89 | K23: 53 | L23: 297 | M23: 2372 | N23: -282 | O23: 434 | P23: 0 | Q23: -246 | R23: 416
A24: + Increase in Long-Term Borrowings | B24: CF_INCR_LT_BORROW | C24: 26 | D24: 21 | E24: 261 | F24: 523 | G24: 317 | H24: 120 | I24: 379 | J24: 49 | K24: 658 | L24: 122 | M24: 208 | N24: 3878 | O24: 135 | P24: 0 | Q24: 0 | R24: 0
A25: + Decrease In Long-Term Borrowings | B25: CF_REIMB_LT_BORROW | C25: -122 | D25: -167 | E25: -196 | F25: -351 | G25: -291 | H25: -565 | I25: -299 | J25: -152 | K25: -403 | L25: -177 | M25: -142 | N25: -85 | O25: -526 | P25: -1773 | Q25: -768 | R25: -47
A26: + Increase in Capital Stocks | B26: CF_INCR_CAP_STOCK | C26: — | D26: — | E26: — | F26: — | G26: 0 | H26: 250 | I26: 0 | J26: 0 | K26: 194 | L26: 142 | M26: 91 | N26: 1006 | O26: 202 | P26: 1268 | Q26: 872 | R26: 188
A27: + Decrease in Capital Stocks | B27: CF_DECR_CAP_STOCK | C27: -339 | D27: -457 | E27: -335 | F27: -326 | G27: -296 | H27: -417 | I27: -380 | J27: -478 | K27: 0 | L27: -253 | M27: 0 | N27: 0 | O27: -170 | P27: 0 | Q27: -864 | R27: -620
A28: + Other Financing Activities | B28: CF_OTHER_FNC_ACT | C28: 33 | D28: 24 | E28: 47 | F28: 17 | G28: 23 | H28: 11 | I28: 68 | J28: 107 | K28: 56 | L28: 133 | M28: 60 | N28: 174 | O28: 79 | P28: -136 | Q28: -140 | R28: 171
A29: Cash from Financing Activities | B29: CF_CASH_FROM_FNC_ACT | C29: -464 | D29: -737 | E29: -494 | F29: -302 | G29: -750 | H29: -949 | I29: -538 | J29: -674 | K29: 252 | L29: -79 | M29: 2295 | N29: 4618 | O29: -487 | P29: -1263 | Q29: -1797 | R29: -603
A30: Net Changes in Cash | B30: CF_NET_CHNG_CASH | C30: -51 | D30: -2 | E30: 32 | F30: -49 | G30: -15 | H30: 540 | I30: -456 | J30: 234 | K30: -210 | L30: -131 | M30: -32 | N30: -45 | O30: 630 | P30: 461 | Q30: -759 | R30: 965
A32: Reference Items
A33: EBITDA | B33: EBITDA | C33: 1381 | D33: 1658 | E33: 1768 | F33: 1648 | G33: 1683 | H33: 1259 | I33: 1387 | J33: 1524 | K33: 1739 | L33: 1374 | M33: 1670 | N33: 1120 | O33: 3314 | P33: 2632 | Q33: 3102 | R33: 2965
A34: Trailing 12M EBITDA Margin | B34: EBITDA_MARGIN | C34: 18.078282 | D34: 19.992765 | E34: 20.366317 | F34: 18.32129 | G34: 21.207157 | H34: 16.217957 | I34: 17.552518 | J34: 18.423598 | K34: 19.404151 | L34: 21.644612 | M34: 22.22518 | N34: 15.476026 | O34: 20.17656 | P34: 20.804679 | Q34: 22.421395 | R34: 21.189166
A35: Cash Paid for Taxes | B35: CF_CASH_PAID_FOR_TAX | C35: — | D35: — | E35: — | F35: — | G35: — | H35: — | I35: — | J35: — | K35: — | L35: — | M35: — | N35: — | O35: 494 | P35: 716 | Q35: 428 | R35: 660
A36: Cash Paid for Interest | B36: CF_ACT_CASH_PAID_FOR_INT_DEBT | C36: — | D36: — | E36: — | F36: — | G36: — | H36: — | I36: — | J36: — | K36: — | L36: 195 | M36: 210 | N36: 331 | O36: 386 | P36: 358 | Q36: 247 | R36: 175
A37: Free Cash Flow | B37: CF_FREE_CASH_FLOW | C37: 397 | D37: 714 | E37: 430 | F37: 354 | G37: 626 | H37: 326 | I37: 294 | J37: 891 | K37: 323 | L37: 703 | M37: -428 | N37: -427 | O37: 139 | P37: 228 | Q37: 879 | R37: 211
A38: Free Cash Flow to Firm | B38: CF_FREE_CASH_FLOW_FIRM | C38: 508.42942 | D38: 829.15566 | E38: 551.75172 | F38: 474.8084 | G38: 737.60452 | H38: — | I38: 381.41564 | J38: 982.04134 | K38: 452.17203 | L38: 791.87342 | M38: -291.44262 | N38: — | O38: 419.74183 | P38: 368.7 | Q38: 1086.2376 | R38: 324.52027
A39: Free Cash Flow to Equity | B39: FREE_CASH_FLOW_EQUITY | C39: — | D39: — | E39: — | F39: — | G39: — | H39: — | I39: 641 | J39: 1079 | K39: 759 | L39: 1110 | M39: 2098 | N39: 3084 | O39: 452 | P39: -1552 | Q39: -140 | R39: 569
A40: Free Cash Flow per Basic Share | B40: FREE_CASH_FLOW_PER_SH | C40: 0.512258 | D40: 0.998601 | E40: 0.635155 | F40: 0.548412 | G40: 0.98485 | H40: 0.528175 | I40: 0.488453 | J40: 1.523272 | K40: 0.556283 | L40: 1.209566 | M40: -0.725178 | N40: -0.707539 | O40: 0.111289 | P40: 0.178964 | Q40: 0.677196 | R40: 0.163186
A41: Price to Free Cash Flow | B41: PX_TO_FREE_CASH_FLOW | C41: 16.202771 | D41: 8.18645 | E41: 18.164854 | F41: 17.596258 | G41: 13.783829 | H41: 21.820431 | I41: 30.043817 | J41: 9.256389 | K41: 44.042352 | L41: 32.139617 | M41: — | N41: — | O41: 318.42761 | P41: 340.85088 | Q41: 62.980319 | R41: 256.14882
A42: Cash Flow to Net Income | B42: CASH_FLOW_TO_NET_INC | C42: 2.068807 | D42: 2.20643 | E42: 1.527246 | F42: 2.021978 | G42: 3.986486 | H42: — | I42: 1.479757 | J42: 2.090032 | K42: 1.113667 | L42: 3.124675 | M42: 0.459574 | N42: — | O42: 1.318578 | P42: 1.39749 | Q42: 1.265157 | R42: 2.266332 | S42: 0.2599278
A44: Direct Method Cashflow
A45: Source: Bloomberg

Sheet 1.4 CAPEX & Depreciation
A2: Pharmacia LLC (748957Q US) - CAPEX & Depreciation
A4: In Millions of USD except Per Share | C4: FY 1987 | D4: FY 1988 | E4: FY 1989 | F4: FY 1990 | G4: FY 1991 | H4: FY 1992 | I4: FY 1993 | J4: FY 1994 | K4: FY 1995 | L4: FY 1996 | M4: FY 1997 | N4: FY 1998 | O4: FY 1999 | P4: FY 2000 | Q4: FY 2001 | R4: FY 2002
A5: 12 Months Ending | C5: 12/31/1987 | D5: 12/31/1988 | E5: 12/31/1989 | F5: 12/31/1990 | G5: 01/01/1992 | H5: 12/31/1992 | I5: 12/31/1993 | J5: 12/31/1994 | K5: 12/31/1995 | L5: 12/31/1996 | M5: 12/31/1997 | N5: 12/31/1998 | O5: 12/31/1999 | P5: 12/31/2000 | Q5: 12/31/2001 | R5: 12/31/2002
A6: Depreciation Expenses | B6: IS_DEPR_EXP | C6: 421 | D6: 435 | E6: 438 | F6: 465 | G6: 453 | H6: 473 | I6: 469 | J6: 442 | K6: 459 | L6: 276 | M6: 299 | N6: 269 | O6: 666 | P6: 728 | Q6: — | R6: —
A7: Depr Exp / Net Sales | B7: DEPR_EXP_TO_NET_SALES | C7: 5.511193 | D7: 5.245388 | E7: 5.045502 | F7: 5.169539 | G7: 5.708165 | H7: 6.093005 | I7: 5.935206 | J7: 5.343327 | K7: 5.121625 | L7: 4.347826 | M7: 3.979239 | N7: 3.71701 | O7: 4.054795 | P7: 5.754486 | Q7: — | R7: —
A8: Depr Exp / Net Fixed Assets | B8: DEPR_EXP_TO_NET_FIX_ASSET | C8: — | D8: 0.139826 | E8: 0.13863 | F8: 0.139535 | G8: 0.135568 | H8: 0.152679 | I8: 0.161529 | J8: 0.157323 | K8: 0.162507 | L8: 0.112036 | M8: 0.133037 | N8: 0.102184 | O8: 0.137461 | P8: 0.128429 | Q8: — | R8: —
A9: Accum Depr / Total Assets | B9: ACCUM_DEPR_TO_TOT_ASSET | C9: 43.217031 | D9: 44.67557 | E9: 43.747094 | F9: 44.694673 | G9: 46.80828 | H9: 50.59989 | I9: 53.009259 | J9: 53.289844 | K9: 41.513524 | L9: 20.761769 | M9: 21.35697 | N9: 14.159292 | O9: 18.140031 | P9: 14.94051 | Q9: 15.158422 | R9: 21.628774
A10: Accum Depr / Gross Fixed Assets | B10: ACCUM_DEPR_TO_GROSS_FA | C10: 54.294205 | D10: 54.576956 | E10: 54.259766 | F10: 54.173228 | G10: 57.509987 | H10: 60.470929 | I10: 62.042807 | J10: 62.713435 | K10: 60.867763 | L10: 52.687444 | M10: 48.947033 | N10: 44.744455 | O10: 41.954414 | P10: 42.994315 | Q10: 41.125121 | R10: 41.339802
A11: Capitalized Int Exp | B11: IS_CAP_INT_EXP | C11: 16 | D11: 19 | E11: 22 | F11: 29 | G11: 24 | H11: 16 | I11: 12 | J11: 10 | K11: 11 | L11: 9 | M11: 14 | N11: 14 | O11: 55 | P11: 63 | Q11: — | R11: —
A12: Cap Interest/Pretax Income | B12: CAPITALIZED_INT_TO_PRETAX_INC | C12: 2.377415 | D12: 2.12766 | E12: 2.167488 | F12: 3.584672 | G12: 6.779661 | H12: — | I12: 1.646091 | J12: 1.117318 | K12: 1.01196 | L12: 1.627486 | M12: 3.825137 | N12: — | O12: 2.897787 | P12: 6.057692 | Q12: — | R12: —
A13: Capital Expenditures | B13: CF_CAP_EXPEND_PRPTY_ADD | C13: -505 | D13: -590 | E13: -607 | F13: -750 | G13: -554 | H13: -586 | I13: -437 | J13: -409 | K13: -500 | L13: -500 | M13: -644 | N13: -859 | O13: -1678 | P13: -774 | Q13: -1020 | R13: -1142
A14: CAPEX/Sales | B14: CAP_EXPEND_TO_SALES | C14: 6.610813 | D14: 7.114434 | E14: 6.992282 | F14: 8.337966 | G14: 6.980847 | H14: 7.548628 | I14: 5.530246 | J14: 4.944391 | K14: 5.579112 | L14: 7.876497 | M14: 8.570668 | N14: 11.869559 | O14: 10.216134 | P14: 6.118093 | Q14: 7.372606 | R14: 8.161223
A15: CAPEX/Total Assets | B15: CAP_EXPEND_TO_TOT_ASSET | C15: — | D15: 6.975644 | E15: 7.113976 | F15: 8.408072 | G15: 6.001192 | H15: 6.400175 | I15: 4.930889 | J15: 4.66602 | K15: 5.127679 | L15: 4.577078 | M15: 5.85162 | N15: 6.325712 | O15: 7.700957 | P15: 3.097797 | Q15: 4.517872 | R15: 5.585171
A16: Capital Expend / Depr Exp | B16: CAPEX_TO_DEPR_EXPN_RATIO | C16: 1.199525 | D16: 1.356322 | E16: 1.385845 | F16: 1.612903 | G16: 1.222958 | H16: 1.238901 | I16: 0.93177 | J16: 0.925339 | K16: 1.089325 | L16: 1.811594 | M16: 2.153846 | N16: 3.193309 | O16: 2.51952 | P16: 1.063187 | Q16: — | R16: —
A17: CAPEX to Depreciation Expense 5 Year Average | B17: 5Y_AVG_CAPEX_TO_DEPR_EXPN | C17: — | D17: — | E17: — | F17: — | G17: 1.355511 | H17: 1.363386 | I17: 1.278475 | J17: 1.186374 | K17: 1.081658 | L17: 1.199386 | M17: 1.382375 | N17: 1.834683 | O17: 2.153519 | P17: 2.148291 | Q17: — | R17: —
A18: Total Capital Expenditures - 1 Yr Growth | B18: TOT_CAP_EXPEND_GROWTH | C18: — | D18: 16.831683 | E18: 2.881356 | F18: 23.558484 | G18: -26.133333 | H18: 5.776173 | I18: -25.426621 | J18: -6.407323 | K18: 22.249389 | L18: 0 | M18: 28.8 | N18: 33.385093 | O18: 95.343423 | P18: -53.873659 | Q18: 31.782946 | R18: 11.960784
A19: Average Age of Assets in Years | B19: AVG_AGE_OF_ASSETS_IN_YEARS | C19: 8.679335 | D19: 8.689655 | E19: 8.593607 | F19: 8.877419 | G19: 9.534216 | H19: 9.718816 | I19: 9.765458 | J19: 10.719457 | K19: 9.59695 | L19: 8.452899 | M19: 7.695652 | N19: 8.624535 | O19: 7.406907 | P19: 4.674451 | Q19: — | R19: —
A20: Source: Bloomberg

Sheet 1.5 Stock Value
A2: Pharmacia LLC (748957Q US) - Stock Value
A4: In Millions of USD except Per Share | C4: FY 1982 | D4: FY 1983 | E4: FY 1984 | F4: FY 1985 | G4: FY 1986 | H4: FY 1987 | I4: FY 1988 | J4: FY 1989 | K4: FY 1990 | L4: FY 1991 | M4: FY 1992 | N4: FY 1993 | O4: FY 1994 | P4: FY 1995 | Q4: FY 1996 | R4: FY 1997 | S4: FY 1998 | T4: FY 1999 | U4: FY 2000 | V4: FY 2001 | W4: FY 2002
A5: 12 Months Ending | C5: 12/31/1982 | D5: 12/31/1983 | E5: 12/31/1984 | F5: 12/31/1985 | G5: 12/31/1986 | H5: 12/31/1987 | I5: 12/31/1988 | J5: 12/31/1989 | K5: 12/31/1990 | L5: 01/01/1992 | M5: 12/31/1992 | N5: 12/31/1993 | O5: 12/31/1994 | P5: 12/31/1995 | Q5: 12/31/1996 | R5: 12/31/1997 | S5: 12/31/1998 | T5: 12/31/1999 | U5: 12/31/2000 | V5: 12/31/2001 | W5: 12/31/2002
A6: Last Price | B6: PX_LAST | C6: 3.583495 | D6: 4.946398 | E6: 4.135706 | F6: 4.488181 | G6: 7.190489 | H6: 7.801446 | I6: 7.683954 | J6: 10.844479 | K6: 9.070355 | L6: 12.759593 | M6: 10.83273 | N6: 13.79352 | O6: 13.253058 | P6: 23.028363 | Q6: 36.539903 | R6: 39.477194 | S6: 44.646827 | T6: 33.308883 | U6: 57.335925 | V6: 40.088151 | W6: 41.8
A7: Period-over-Period % Change | B7: CHG_PCT_PERIOD | C7: 8.734403 | D7: 38.032787 | E7: -16.389549 | F7: 8.522727 | G7: 60.209424 | H7: 8.496732 | I7: -1.506024 | J7: 41.131498 | K7: -16.359697 | L7: 40.673575 | M7: -15.101289 | N7: 27.331887 | O7: -3.918228 | P7: 73.758865 | Q7: 58.673469 | R7: 8.038585 | S7: 13.095238 | T7: -25.394737 | U7: 72.134039 | V7: -30.081967 | W7: 4.270212
A8: Open Price | B8: PX_OPEN | C8: 3.325014 | D8: 3.583495 | E8: 4.940524 | F8: 4.100459 | G8: 4.488181 | H8: 7.202238 | I8: 7.730951 | J8: 7.683954 | K8: 10.820981 | L8: 9.023359 | M8: 12.759593 | N8: 10.83273 | O8: 13.840516 | P8: 13.112068 | Q8: 22.746383 | R8: 36.657395 | S8: 40.182144 | T8: 46.99666 | U8: 33.48512 | V8: 56.630975 | W8: 39.665181
A9: High Price | B9: PX_HIGH | C9: 4.182703 | D9: 5.469236 | E9: 5.06389 | F9: 5.20488 | G9: 7.660456 | H9: 9.42283 | I9: 8.682633 | J9: 11.67867 | K9: 11.302697 | L9: 14.286985 | M9: 13.394048 | N9: 14.098998 | O9: 16.260844 | P9: 23.451333 | Q9: 40.652111 | R9: 49.170256 | S9: 60.096979 | T9: 47.760356 | U9: 60.155725 | V9: 57.277179 | W9: 46.4
A10: Low Price | B10: PX_LOW | C10: 2.661186 | D10: 3.489502 | E10: 3.818479 | F10: 3.818479 | G10: 4.206201 | H10: 5.357619 | I10: 6.908509 | J10: 7.566462 | K10: 7.284482 | L10: 8.647385 | M10: 9.352335 | N10: 9.187847 | O10: 12.501112 | P10: 12.830088 | Q10: 21.688959 | R10: 32.662679 | S10: 31.722746 | T10: 30.782812 | U10: 31.722746 | V10: 34.307562 | W10: 28.536372
A12: Market Capitalization | B12: HISTORICAL_MARKET_CAP | C12: — | D12: — | E12: — | F12: — | G12: — | H12: 6142 | I12: 5640.75 | J12: 7614.75 | K12: 6079.5 | L12: 8343.7034 | M12: 6941.7378 | N12: 8509.7389 | O12: 7863.2178 | P12: 14432.338 | Q12: 22717.616 | R12: 25001.969 | S12: 29891.512 | T12: 45501.75 | U12: 79287.803 | V12: 55328.098 | W12: 54162.432
A13: Current Shares Outstanding | B13: EQY_SH_OUT | C13: — | D13: — | E13: — | F13: — | G13: — | H13: — | I13: 740 | J13: 690 | K13: 632.5 | L13: 634.00001 | M13: 609.08001 | N13: 593.30502 | O13: 568.955 | P13: 581.39 | Q13: 588.02002 | R13: 592.98602 | S13: 604.22199 | T13: 634.60797 | U13: 1289.6494 | V13: 1289.4132 | W13: 1292.9167
A14: Source: Bloomberg

Sheet 2. WACC >>>>

Sheet 2.1 WACC
B1: Pharmacia LLC
B2: WACC | E2: Actual
E3: 2000 | F3: 2001 | G3: 2002
C4: Equity
C5: Cost of Equity | E5: 0.0738 | F5: 0.0785 | G5: 0.0866
C6: Weight of Equity | E6: 0.9456 | F6: 0.9431 | G6: 0.9363
C8: Debt
C9: Cost of Debt | E9: 0.047 | F9: 0.0459 | G9: 0.0287
C10: Weight of Debt | E10: 0.0513 | F10: 0.0525 | G10: 0.0594
C12: WACC* | E12: 0.0721 | F12: 0.0765 | G12: 0.0828
C13: *from Bloomberg

Sheet 3. FINANCIALS >>>>

Sheet 3.1 Assumption
B5: Assumptions | E5: Actual | H5: Projections
B6: in Millions of USD | E6: 1997 | F6: 1998 | G6: 1999 | H6: 2000 | I6: 2001 | J6: 2002 | K6: 2003 | L6: 2004 | M6: 2005 | N6: 2006
C8: Operating assumptions - Stable growth
E9: 1997 | F9: 1998 | G9: 1999 | H9: 2000 | I9: 2001 | J9: 2002 | K9: 2003 | L9: 2004 | M9: 2005 | N9: 2006
C10: Income statement
C11: Sales growth | E11: NA | F11: ='3.3 Income Statement'!F7/'3.3 Income Statement'!E7-1 -> -0.03686452 | G11: ='3.3 Income Statement'!G7/'3.3 Income Statement'!F7-1 -> 1.2695868 | H11: ='3.3 Income Statement'!H7/'3.3 Income Statement'!G7-1 -> -0.22977169 | I11: ='3.3 Income Statement'!I7/'3.3 Income Statement'!H7-1 -> 0.09358944 | J11: 0.0479 | K11: 0.0479 | L11: 0.0479 | M11: 0.0479 | N11: 0.0479 | P11: Follow the median of Fortune 500 Drug Companies
C12: COGS as % of sales | E12: =-'3.3 Income Statement'!E8/'3.3 Income Statement'!E7 -> 0.41136545 | F12: =-'3.3 Income Statement'!F8/'3.3 Income Statement'!F7 -> 0.40237668 | G12: =-'3.3 Income Statement'!G8/'3.3 Income Statement'!G7 -> 0.32383562 | H12: =-'3.3 Income Statement'!H8/'3.3 Income Statement'!H7 -> 0.22812426 | I12: =-'3.3 Income Statement'!I8/'3.3 Income Statement'!I7 -> 0.21525117 | J12: =6*-0.0566+0.4861 -> 0.1465 | K12: =7*-0.0566+0.4861 -> 0.0899 | L12: =K12 -> 0.0899 | M12: =L12 -> 0.0899 | N12: =M12 -> 0.0899 | P12: Linear regression until 2003E and then constant
C13: SG&A, Others as % of sales | E13: =-'3.3 Income Statement'!E9/'3.3 Income Statement'!E7 -> 0.22744211 | F13: =-'3.3 Income Statement'!F9/'3.3 Income Statement'!F7 -> 0.27179771 | G13: =-'3.3 Income Statement'!G9/'3.3 Income Statement'!G7 -> 0.3030137 | H13: =-'3.3 Income Statement'!H9/'3.3 Income Statement'!H7 -> 0.39269623 | I13: =-'3.3 Income Statement'!I9/'3.3 Income Statement'!I7 -> 0.39696422 | J13: =AVERAGE($E$13:$I$13) -> 0.31838279 | K13: =AVERAGE($E$13:$I$13) -> 0.31838279 | L13: =AVERAGE($E$13:$I$13) -> 0.31838279 | M13: =AVERAGE($E$13:$I$13) -> 0.31838279 | N13: =AVERAGE($E$13:$I$13) -> 0.31838279 | P13: Average
C14: R&D as % of sales | E14: =-'3.3 Income Statement'!E10/'3.3 Income Statement'!E7 -> 0.13894064 | F14: =-'3.3 Income Statement'!F10/'3.3 Income Statement'!F7 -> 0.17106536 | G14: =-'3.3 Income Statement'!G10/'3.3 Income Statement'!G7 -> 0.17138508 | H14: =-'3.3 Income Statement'!H10/'3.3 Income Statement'!H7 -> 0.17113272 | I14: =-'3.3 Income Statement'!I10/'3.3 Income Statement'!I7 -> 0.16357065 | J14: =AVERAGE($E$14,$F$14,$G$14,$H$14,$I$14) -> 0.16321889 | K14: =AVERAGE($E$14,$F$14,$G$14,$H$14,$I$14) -> 0.16321889 | L14: =AVERAGE($E$14,$F$14,$G$14,$H$14,$I$14) -> 0.16321889 | M14: =AVERAGE($E$14,$F$14,$G$14,$H$14,$I$14) -> 0.16321889 | N14: =AVERAGE($E$14,$F$14,$G$14,$H$14,$I$14) -> 0.16321889 | P14: Average
C15: Effective tax rate | E15: ='5.1 Free Cash Flow'!E20 -> 0.1967 | F15: ='5.1 Free Cash Flow'!F20 -> 0.1967 | G15: ='5.1 Free Cash Flow'!G20 -> 0.3119 | H15: ='5.1 Free Cash Flow'!H20 -> 0.2269 | I15: ='5.1 Free Cash Flow'!I20 -> 0.1873 | J15: 0.4 | K15: 0.4 | L15: 0.4 | M15: 0.4 | N15: 0.4
C17: Balance Sheet
C18: NC-WC as % of sales | E18: ='3.2 Balance Sheet'!E47/'3.3 Income Statement'!E7 -> 0.3086239 | F18: ='3.2 Balance Sheet'!F47/'3.3 Income Statement'!F7 -> 0.33093823 | G18: ='3.2 Balance Sheet'!G47/'3.3 Income Statement'!G7 -> 0.23744292 | H18: ='3.2 Balance Sheet'!H47/'3.3 Income Statement'!H7 -> 0.14322978 | I18: ='3.2 Balance Sheet'!I47/'3.3 Income Statement'!I7 -> 0.13501988 | J18: =AVERAGE($F$18:$I$18) -> 0.2116577 | K18: =AVERAGE($F$18:$I$18) -> 0.2116577 | L18: =AVERAGE($F$18:$I$18) -> 0.2116577 | M18: =AVERAGE($F$18:$I$18) -> 0.2116577 | N18: =AVERAGE($F$18:$I$18) -> 0.2116577 | P18: Average
C20: Cash Flow Statement
C21: D&A as % of sales | E21: ='3.4 Cash Flow Statement'!E7/'3.3 Income Statement'!E7 -> 0.06481235 | F21: ='3.4 Cash Flow Statement'!F7/'3.3 Income Statement'!F7 -> 0.07157662 | G21: ='3.4 Cash Flow Statement'!G7/'3.3 Income Statement'!G7 -> 0.069710807 | H21: ='3.4 Cash Flow Statement'!H7/'3.3 Income Statement'!H7 -> 0.05003557 | I21: ='3.4 Cash Flow Statement'!I7/'3.3 Income Statement'!I7 -> 0.044163354 | J21: =AVERAGE($E$21:$I$21) -> 0.06005974 | K21: =AVERAGE($E$21:$I$21) -> 0.06005974 | L21: =AVERAGE($E$21:$I$21) -> 0.06005974 | M21: =AVERAGE($E$21:$I$21) -> 0.06005974 | N21: =AVERAGE($E$21:$I$21) -> 0.06005974 | P21: Average
C22: Capex as % of sales | E22: =ABS('3.4 Cash Flow Statement'!E9/'3.3 Income Statement'!E7) -> 0.085706681 | F22: =ABS('3.4 Cash Flow Statement'!F9/'3.3 Income Statement'!F7) -> 0.11869559 | G22: =ABS('3.4 Cash Flow Statement'!G9/'3.3 Income Statement'!G7) -> 0.10216134 | H22: =ABS('3.4 Cash Flow Statement'!H9/'3.3 Income Statement'!H7) -> 0.061180934 | I22: =ABS('3.4 Cash Flow Statement'!I9/'3.3 Income Statement'!I7) -> 0.073726057 | J22: =AVERAGE($F$22:$I$22) -> 0.088940981 | K22: =AVERAGE($F$22:$I$22) -> 0.088940981 | L22: =AVERAGE($F$22:$I$22) -> 0.088940981 | M22: =AVERAGE($F$22:$I$22) -> 0.088940981 | N22: =AVERAGE($F$22:$I$22) -> 0.088940981 | P22: Average
J82: 5951 | K82: 487
K83: =(K82-J82)/J82 -> -0.91816501
J88: 27.311 | K88: =J88/(-J89-J90) -> 0.039401682
J89: -1.143
J90: -692

Sheet 3.2 Balance Sheet
B1: Pharmacia LLC
B2: Balance Sheet | E2: Actual | H2: Projections
B3: In Millions of USD | E3: 1997 | F3: 1998 | G3: 1999 | H3: 2000 | I3: 2001 | J3: 2002 | K3: 2003 | L3: 2004 | M3: 2005 | N3: 2006
C5: Assets
C7: Cash & cash equivalents | E7: ='1.1 Balance Sheet Raw'!M7 -> 134 | F7: ='1.1 Balance Sheet Raw'!N7 -> 89 | G7: ='1.1 Balance Sheet Raw'!O7 -> 1600 | H7: ='1.1 Balance Sheet Raw'!P7 -> 2035 | I7: ='1.1 Balance Sheet Raw'!Q7 -> 1276
C8: Short-Term Investments | E8: ='1.1 Balance Sheet Raw'!M8 -> 0 | F8: ='1.1 Balance Sheet Raw'!N8 -> 0 | G8: ='1.1 Balance Sheet Raw'!O8 -> 138 | H8: ='1.1 Balance Sheet Raw'!P8 -> 35 | I8: ='1.1 Balance Sheet Raw'!Q8 -> 119
C9: Inventory | E9: ='1.1 Balance Sheet Raw'!M10 -> 1374 | F9: ='1.1 Balance Sheet Raw'!N10 -> 1722 | G9: ='1.1 Balance Sheet Raw'!O10 -> 2905 | H9: ='1.1 Balance Sheet Raw'!P10 -> 1519 | I9: ='1.1 Balance Sheet Raw'!Q10 -> 1683
C10: Accounts receivable | E10: ='1.1 Balance Sheet Raw'!M9 -> 1823 | F10: ='1.1 Balance Sheet Raw'!N9 -> 2119 | G10: ='1.1 Balance Sheet Raw'!O9 -> 4131 | H10: ='1.1 Balance Sheet Raw'!P9 -> 2510 | I10: ='1.1 Balance Sheet Raw'!Q9 -> 2433
C11: Other current assets | E11: ='1.1 Balance Sheet Raw'!M11 -> 935 | F11: ='1.1 Balance Sheet Raw'!N11 -> 1265 | G11: ='1.1 Balance Sheet Raw'!O11 -> 1908 | H11: ='1.1 Balance Sheet Raw'!P11 -> 2139 | I11: ='1.1 Balance Sheet Raw'!Q11 -> 2152
C12: Total current assets | E12: =SUM(E7:E11) -> 4266 | F12: =SUM(F7:F11) -> 5195 | G12: =SUM(G7:G11) -> 10682 | H12: =SUM(H7:H11) -> 8238 | I12: =SUM(I7:I11) -> 7663
C14: PP&E | E14: ='1.1 Balance Sheet Raw'!M14 -> 2400 | F14: ='1.1 Balance Sheet Raw'!N14 -> 2865 | G14: ='1.1 Balance Sheet Raw'!O14 -> 6825 | H14: ='1.1 Balance Sheet Raw'!P14 -> 4512 | I14: ='1.1 Balance Sheet Raw'!Q14 -> 4856
C15: Goodwill | E15: ='1.1 Balance Sheet Raw'!M59 -> 0 | F15: ='1.1 Balance Sheet Raw'!N59 -> 0 | G15: ='1.1 Balance Sheet Raw'!O59 -> 4402 | H15: ='1.1 Balance Sheet Raw'!P59 -> 1279 | I15: ='1.1 Balance Sheet Raw'!Q59 -> 1059
C16: Other fixed assets | E16: ='1.1 Balance Sheet Raw'!M17+'1.1 Balance Sheet Raw'!M13-'1.1 Balance Sheet Raw'!M59 -> 4108 | F16: ='1.1 Balance Sheet Raw'!N17+'1.1 Balance Sheet Raw'!N13-'1.1 Balance Sheet Raw'!N59 -> 8325 | G16: ='1.1 Balance Sheet Raw'!O17+'1.1 Balance Sheet Raw'!O13-'1.1 Balance Sheet Raw'!O59 -> 5285 | H16: ='1.1 Balance Sheet Raw'!P17+'1.1 Balance Sheet Raw'!P13-'1.1 Balance Sheet Raw'!P59 -> 8748 | I16: ='1.1 Balance Sheet Raw'!Q17+'1.1 Balance Sheet Raw'!Q13-'1.1 Balance Sheet Raw'!Q59 -> 8799
C17: Total fixed assets | E17: =SUM(E14:E16) -> 6508 | F17: =SUM(F14:F16) -> 11190 | G17: =SUM(G14:G16) -> 16512 | H17: =SUM(H14:H16) -> 14539 | I17: =SUM(I14:I16) -> 14714
C19: Assets held for sale of exchange | E19: 0 | F19: 0 | G19: 0 | H19: 0 | I19: 0
C20: Total assets | E20: =E12+E17+E19 -> 10774 | F20: =F12+F17+F19 -> 16385 | G20: =G12+G17+G19 -> 27194 | H20: =H12+H17+H19 -> 22777 | I20: =I12+I17+I19 -> 22377
C22: Equity and Liabilities
C24: Accounts payable | E24: ='1.1 Balance Sheet Raw'!M22 -> 480 | F24: ='1.1 Balance Sheet Raw'!N22 -> 823 | G24: ='1.1 Balance Sheet Raw'!O22 -> 1272 | H24: ='1.1 Balance Sheet Raw'!P22 -> 836 | I24: ='1.1 Balance Sheet Raw'!Q22 -> 1048
C25: Short-term debt and current portion of long-term debt | E25: ='1.1 Balance Sheet Raw'!M23 -> 1726 | F25: ='1.1 Balance Sheet Raw'!N23 -> 1069 | G25: ='1.1 Balance Sheet Raw'!O23 -> 1992 | H25: ='1.1 Balance Sheet Raw'!P23 -> 675 | I25: ='1.1 Balance Sheet Raw'!Q23 -> 470
C26: Other current liabilities | E26: ='1.1 Balance Sheet Raw'!M24 -> 1333 | F26: ='1.1 Balance Sheet Raw'!N24 -> 1888 | G26: ='1.1 Balance Sheet Raw'!O24 -> 3910 | H26: ='1.1 Balance Sheet Raw'!P24 -> 3555 | I26: ='1.1 Balance Sheet Raw'!Q24 -> 3471
C27: Total current libailities | E27: =SUM(E24:E26) -> 3539 | F27: =SUM(F24:F26) -> 3780 | G27: =SUM(G24:G26) -> 7174 | H27: =SUM(H24:H26) -> 5066 | I27: =SUM(I24:I26) -> 4989
C29: Long-term debt | E29: ='1.1 Balance Sheet Raw'!M26 -> 1979 | F29: ='1.1 Balance Sheet Raw'!N26 -> 6259 | G29: ='1.1 Balance Sheet Raw'!O26 -> 6236 | H29: ='1.1 Balance Sheet Raw'!P26 -> 3624 | I29: ='1.1 Balance Sheet Raw'!Q26 -> 2612
C30: Other non-current liabilities | E30: ='1.1 Balance Sheet Raw'!M27 -> 1152 | F30: ='1.1 Balance Sheet Raw'!N27 -> 1360 | G30: ='1.1 Balance Sheet Raw'!O27 -> 2873 | H30: ='1.1 Balance Sheet Raw'!P27 -> 2166 | I30: ='1.1 Balance Sheet Raw'!Q27 -> 2386
C31: Total liabilities | E31: =E27+SUM(E29:E30) -> 6670 | F31: =F27+SUM(F29:F30) -> 11399 | G31: =G27+SUM(G29:G30) -> 16283 | H31: =H27+SUM(H29:H30) -> 10856 | I31: =I27+SUM(I29:I30) -> 9987
C33: Equity attributable to equity holders of the Company | E33: ='1.1 Balance Sheet Raw'!M34 -> 4104 | F33: ='1.1 Balance Sheet Raw'!N34 -> 4986 | G33: ='1.1 Balance Sheet Raw'!O34 -> 10911 | H33: ='1.1 Balance Sheet Raw'!P34 -> 11921 | I33: ='1.1 Balance Sheet Raw'!Q34 -> 12390
C34: Minority interests | E34: 0 | F34: 0 | G34: 0 | H34: 0 | I34: 0
C35: Total equity | E35: =SUM(E33:E34) -> 4104 | F35: =SUM(F33:F34) -> 4986 | G35: =SUM(G33:G34) -> 10911 | H35: =SUM(H33:H34) -> 11921 | I35: =SUM(I33:I34) -> 12390
C37: Liabilities related to assets held for sale or exchange | E37: 0 | F37: 0 | G37: 0 | H37: 0 | I37: 0
C38: Total equity and liabilities | E38: =E31+E35+E37 -> 10774 | F38: =F31+F35+F37 -> 16385 | G38: =G31+G35+G37 -> 27194 | H38: =H31+H35+H37 -> 22777 | I38: =I31+I35+I37 -> 22377
C39: check | E39: =IF(ROUND(E38-E20,1)=0,"ok!",E38-E20) -> ok! | F39: =IF(ROUND(F38-F20,1)=0,"ok!",F38-F20) -> ok! | G39: =IF(ROUND(G38-G20,1)=0,"ok!",G38-G20) -> ok! | H39: =IF(ROUND(H38-H20,1)=0,"ok!",H38-H20) -> ok! | I39: =IF(ROUND(I38-I20,1)=0,"ok!",I38-I20) -> ok!
C42: Operating Working Capital | D42: 1996 | E42: 1997 | F42: 1998 | G42: 1999 | H42: 2000 | I42: 2001 | J42: 2002 | K42: 2003 | L42: 2004 | M42: 2005 | N42: 2006
C43: Total current assets | D43: ='1.1 Balance Sheet Raw'!L12 -> 4340 | E43: =E12 -> 4266 | F43: =F12 -> 5195 | G43: =G12 -> 10682 | H43: =H12 -> 8238 | I43: =I12 -> 7663
C44: - Cash and Cash equivalents | D44: ='1.1 Balance Sheet Raw'!L7 -> 166 | E44: =E7 -> 134 | F44: =F7 -> 89 | G44: =G7 -> 1600 | H44: =H7 -> 2035 | I44: =I7 -> 1276
C45: -Total curent liabilities | D45: ='1.1 Balance Sheet Raw'!L25 -> 3401 | E45: =E27 -> 3539 | F45: =F27 -> 3780 | G45: =G27 -> 7174 | H45: =H27 -> 5066 | I45: =I27 -> 4989
C46: + Short-term debt and current portion of long-term debt | D46: ='1.1 Balance Sheet Raw'!L23 -> 654 | E46: =E25 -> 1726 | F46: =F25 -> 1069 | G46: =G25 -> 1992 | H46: =H25 -> 675 | I46: =I25 -> 470
C47: NET NON-CASH WORKING CAPITAL | D47: =D43-D44-D45+D46 -> 1427 | E47: =E43-E44-E45+E46 -> 2319 | F47: =F43-F44-F45+F46 -> 2395 | G47: =G43-G44-G45+G46 -> 3900 | H47: =H43-H44-H45+H46 -> 1812 | I47: =I43-I44-I45+I46 -> 1868 | J47: ='3.1 Assumption'!J18*'3.3 Income Statement'!J7 -> 3068.5492 | K47: ='3.1 Assumption'!K18*'3.3 Income Statement'!K7 -> 3215.5327 | L47: ='3.1 Assumption'!L18*'3.3 Income Statement'!L7 -> 3369.5567 | M47: ='3.1 Assumption'!M18*'3.3 Income Statement'!M7 -> 3530.9584 | N47: ='3.1 Assumption'!N18*'3.3 Income Statement'!N7 -> 3700.0914
C49: Δ NET NON-CASH WORKING CAPITAL | E49: =E47-D47 -> 892 | F49: =F47-E47 -> 76 | G49: =G47-F47 -> 1505 | H49: =H47-G47 -> -2088 | I49: =I47-H47 -> 56 | J49: =J47-I47 -> 1200.5492 | K49: =K47-J47 -> 146.9835 | L49: =L47-K47 -> 154.02401 | ... N49: =N47-M47 -> 169.13291

Sheet 3.3 Income Statement
B1: Pharmacia LLC
B2: Income Statement | E2: Actual | H2: Projections
B3: In Millions of USD | E3: 1997 | F3: 1998 | G3: 1999 | H3: 2000 | I3: 2001 | J3: 2002 | K3: 2003 | L3: 2004 | M3: 2005 | N3: 2006
C5: Income Statement
C7: Sales | E7: ='1.2 Income Statement Raw'!M6 -> 7514 | F7: ='1.2 Income Statement Raw'!N6 -> 7237 | G7: ='1.2 Income Statement Raw'!O6 -> 16425 | H7: ='1.2 Income Statement Raw'!P6 -> 12651 | I7: ='1.2 Income Statement Raw'!Q6 -> 13835 | J7: =I7*(1+'3.1 Assumption'!J11) -> 14497.697 | K7: =J7*(1+'3.1 Assumption'!K11) -> 15192.136 | L7: =K7*(1+'3.1 Assumption'!L11) -> 15919.839 | M7: =L7*(1+'3.1 Assumption'!M11) -> 16682.4 | N7: =M7*(1+'3.1 Assumption'!N11) -> 17481.487
C8: Cost of sales | E8: =-'1.2 Income Statement Raw'!M7 -> -3091 | F8: =-'1.2 Income Statement Raw'!N7 -> -2912 | G8: =-'1.2 Income Statement Raw'!O7 -> -5319 | H8: =-'1.2 Income Statement Raw'!P7 -> -2886 | I8: =-'1.2 Income Statement Raw'!Q7 -> -2978 | J8: =-J$7*'3.1 Assumption'!J12 -> -2123.9125 | K8: =-K$7*'3.1 Assumption'!K12 -> -1365.773 | L8: =-L$7*'3.1 Assumption'!L12 -> -1431.1936 | M8: =-M$7*'3.1 Assumption'!M12 -> -1499.7477 | N8: =-N$7*'3.1 Assumption'!N12 -> -1571.5857
C9: Selling, general & administrative and others | E9: =-('1.2 Income Statement Raw'!M9-'1.2 Income Statement Raw'!M49-'1.3 Cash Flow - Standardized'!M8) -> -1709 | F9: =-('1.2 Income Statement Raw'!N9-'1.2 Income Statement Raw'!N49-'1.3 Cash Flow - Standardized'!N8) -> -1967 | G9: =-('1.2 Income Statement Raw'!O9-'1.2 Income Statement Raw'!O49-'1.3 Cash Flow - Standardized'!O8) -> -4977 | H9: =-('1.2 Income Statement Raw'!P9-'1.2 Income Statement Raw'!P49-'1.3 Cash Flow - Standardized'!P8) -> -4968 | I9: =-('1.2 Income Statement Raw'!Q9-'1.2 Income Statement Raw'!Q49-'1.3 Cash Flow - Standardized'!Q8) -> -5492 | J9: =-J$7*'3.1 Assumption'!J13 -> -4615.8171 | K9: =-K$7*'3.1 Assumption'!K13 -> -4836.9147 | L9: =-L$7*'3.1 Assumption'!L13 -> -5068.603 | M9: =-M$7*'3.1 Assumption'!M13 -> -5311.389 | N9: =-N$7*'3.1 Assumption'!N13 -> -5565.8046
C10: R&D expenses | E10: =-'1.2 Income Statement Raw'!M49 -> -1044 | F10: =-'1.2 Income Statement Raw'!N49 -> -1238 | G10: =-'1.2 Income Statement Raw'!O49 -> -2815 | H10: =-'1.2 Income Statement Raw'!P49 -> -2165 | I10: =-'1.2 Income Statement Raw'!Q49 -> -2263 | J10: =-J$7*'3.1 Assumption'!J14 -> -2366.298 | K10: =-K$7*'3.1 Assumption'!K14 -> -2479.6436 | L10: =-L$7*'3.1 Assumption'!L14 -> -2598.4186 | M10: =-M$7*'3.1 Assumption'!M14 -> -2722.8828 | N10: =-N$7*'3.1 Assumption'!N14 -> -2853.3089
C11: EBITDA | E11: =SUM(E7,E8,E9,E10) -> 1670 | F11: =SUM(F7,F8,F9,F10) -> 1120 | G11: =SUM(G7,G8,G9,G10) -> 3314 | H11: =SUM(H7,H8,H9,H10) -> 2632 | I11: =SUM(I7,I8,I9,I10) -> 3102 | J11: =SUM(J7,J8,J9,J10) -> 5391.6689 | K11: =SUM(K7,K8,K9,K10) -> 6509.8048 | L11: =SUM(L7,L8,L9,L10) -> 6821.6244 | ... N11: =SUM(N7,N8,N9,N10) -> 7490.7876
C12: % margin | E12: =E11/E7 -> 0.2222518 | F12: =F11/F7 -> 0.15476026 | G12: =G11/G7 -> 0.2017656 | H12: =H11/H7 -> 0.20804679 | I12: =I11/I7 -> 0.22421395 | J12: =J11/J7 -> 0.37189832 | K12: =K11/K7 -> 0.42849832 | L12: =L11/L7 -> 0.42849832 | ... N12: =N11/N7 -> 0.42849832
C14: Depreciation & amortization* | E14: =-'1.3 Cash Flow - Standardized'!M8 -> -487 | F14: =-'1.3 Cash Flow - Standardized'!N8 -> -518 | G14: =-'1.3 Cash Flow - Standardized'!O8 -> -1145 | H14: =-'1.3 Cash Flow - Standardized'!P8 -> -633 | I14: =-'1.3 Cash Flow - Standardized'!Q8 -> -611 | J14: =-'3.4 Cash Flow Statement'!J7 -> -870.72789 | K14: =-'3.4 Cash Flow Statement'!K7 -> -912.43575 | L14: =-'3.4 Cash Flow Statement'!L7 -> -956.14142 | M14: =-'3.4 Cash Flow Statement'!M7 -> -1001.9406 | N14: =-'3.4 Cash Flow Statement'!N7 -> -1049.9336
C15: EBIT | E15: =E11+E14 -> 1183 | F15: =F11+F14 -> 602 | G15: =G11+G14 -> 2169 | H15: =H11+H14 -> 1999 | I15: =I11+I14 -> 2491 | J15: =J11+J14 -> 4520.941 | K15: =K11+K14 -> 5597.369 | L15: =L11+L14 -> 5865.483 | ... N15: =N11+N14 -> 6440.8541
C16: % margin | E16: =E15/E7 -> 0.15743945 | F16: =F15/F7 -> 0.08318364 | G16: =G15/G7 -> 0.13205479 | H16: =H15/H7 -> 0.15801122 | I16: =I15/I7 -> 0.1800506 | J16: =J15/J7 -> 0.31183858 | K16: =K15/K7 -> 0.36843858 | L16: =L15/L7 -> 0.36843858 | ... N16: =N15/N7 -> 0.36843858
C19: *from Cash Flow Statement in AR

Sheet 3.4 Cash Flow Statement
B1: Pharmacia LLC
B2: Cash Flow Statement | E2: Actual | H2: Projections
B3: In Millions of USD | E3: 1997 | F3: 1998 | G3: 1999 | H3: 2000 | I3: 2001 | J3: 2002 | K3: 2003 | L3: 2004 | M3: 2005 | N3: 2006
C5: Cash Flow Statement
C6: Cash From Operating Activities
C7: Depreciation & amortization | E7: =-'3.3 Income Statement'!E14 -> 487 | F7: =-'3.3 Income Statement'!F14 -> 518 | G7: =-'3.3 Income Statement'!G14 -> 1145 | H7: =-'3.3 Income Statement'!H14 -> 633 | I7: =-'3.3 Income Statement'!I14 -> 611 | J7: ='3.1 Assumption'!J21*'3.3 Income Statement'!J7 -> 870.72789 | K7: ='3.1 Assumption'!K21*'3.3 Income Statement'!K7 -> 912.43575 | L7: ='3.1 Assumption'!L21*'3.3 Income Statement'!L7 -> 956.14142 | M7: ='3.1 Assumption'!M21*'3.3 Income Statement'!M7 -> 1001.9406 | N7: ='3.1 Assumption'!N21*'3.3 Income Statement'!N7 -> 1049.9336
C8: Cash From Investing Activities
C9: Capital Expenditures | E9: ='1.4 CAPEX & Depreciation'!M13 -> -644 | F9: ='1.4 CAPEX & Depreciation'!N13 -> -859 | G9: ='1.4 CAPEX & Depreciation'!O13 -> -1678 | H9: ='1.4 CAPEX & Depreciation'!P13 -> -774 | I9: ='1.4 CAPEX & Depreciation'!Q13 -> -1020 | J9: =-'3.3 Income Statement'!J7*'3.1 Assumption'!J22 -> -1289.4393 | K9: =-'3.3 Income Statement'!K7*'3.1 Assumption'!K22 -> -1351.2035 | L9: =-'3.3 Income Statement'!L7*'3.1 Assumption'!L22 -> -1415.9261 | M9: =-'3.3 Income Statement'!M7*'3.1 Assumption'!M22 -> -1483.749 | N9: =-'3.3 Income Statement'!N7*'3.1 Assumption'!N22 -> -1554.8206

Sheet 3.5 Value of Control Inputs
C2: LLY | D2: BMY | E2: SGP | F2: WYE | G2: ABT | H2: Average | I2: Minimum | J2: 25th percentile | K2: Median | L2: 75th percentile | M2: Maximum | N2: Pharmacia
B3: 2001
B4: Income statement
B5: COGS as % of sales | C5: 0.187152 | D5: 0.3031634 | E5: 0.21286622 | F5: 0.24233756 | G5: 0.47579105 | H5: =AVERAGE(C5:G5) -> 0.28426204 | I5: =MIN(C5:G5) -> 0.187152 | J5: =_xlfn.QUARTILE.INC(C5:G5,1) -> 0.21286622 | K5: =MEDIAN(C5:G5) -> 0.24233756 | L5: =_xlfn.QUARTILE.INC(C5:G5,3) -> 0.3031634 | M5: =MAX(C5:G5) -> 0.47579105 | N5: 0.215
B6: SG&A as % of sales | C6: 0.32230479 | D6: 0.25882353 | E6: NA | F6: NA | G6: 0.25009146 | H6: =AVERAGE(C6:G6) -> 0.27707326 | I6: =MIN(C6:G6) -> 0.25009146 | J6: =_xlfn.QUARTILE.INC(C6:G6,1) -> 0.2544575 | K6: =MEDIAN(C6:G6) -> 0.25882353 | L6: =_xlfn.QUARTILE.INC(C6:G6,3) -> 0.29056416 | M6: =MAX(C6:G6) -> 0.32230479 | N6: 0.397
B7: R&D as % of sales | C7: 0.19813611 | D7: NA | E7: NA | F7: NA | G7: 0.089183382 | H7: =AVERAGE(C7:G7) -> 0.14365974 | I7: =MIN(C7:G7) -> 0.089183382 | J7: =_xlfn.QUARTILE.INC(C7:G7,1) -> 0.11642156 | K7: =MEDIAN(C7:G7) -> 0.14365974 | L7: =_xlfn.QUARTILE.INC(C7:G7,3) -> 0.17089792 | M7: =MAX(C7:G7) -> 0.19813611 | N7: 0.164
B9: Balance Sheet
B10: NC-WC as % of sales | C10: -0.058921377 | D10: -0.17712793 | E10: 0.046199549 | F10: 0.2046868 | G10: 0.17121576 | H10: =AVERAGE(C10:G10) -> 0.037210561 | I10: =MIN(C10:G10) -> -0.17712793 | J10: =_xlfn.QUARTILE.INC(C10:G10,1) -> -0.058921377 | K10: =MEDIAN(C10:G10) -> 0.046199549 | L10: =_xlfn.QUARTILE.INC(C10:G10,3) -> 0.17121576 | M10: =MAX(C10:G10) -> 0.2046868 | N10: 0.26786993
B12: Cash Flow Statement
B13: Capex as % of sales | C13: 0.076586528 | D13: 0.056874409 | E13: 0.0777504 | F13: 0.13760923 | G13: 0.071457081 | H13: =AVERAGE(C13:G13) -> 0.08405553 | I13: =MIN(C13:G13) -> 0.056874409 | J13: =_xlfn.QUARTILE.INC(C13:G13,1) -> 0.071457081 | K13: =MEDIAN(C13:G13) -> 0.076586528 | L13: =_xlfn.QUARTILE.INC(C13:G13,3) -> 0.0777504 | M13: =MAX(C13:G13) -> 0.13760923 | N13: 0.135
B14: Profit margin
B15: EBITDA% margin | C15: 0.363 | D15: 0.327 | E15: 0.333 | F15: 0.307 | G15: 0.27 | H15: =AVERAGE(C15:G15) -> 0.32 | I15: =MIN(C15:G15) -> 0.27 | J15: =_xlfn.QUARTILE.INC(C15:G15,1) -> 0.307 | K15: =MEDIAN(C15:G15) -> 0.327 | L15: =_xlfn.QUARTILE.INC(C15:G15,3) -> 0.333 | M15: =MAX(C15:G15) -> 0.363 | N15: 0.224
B16: EBIT% margin | C16: 0.323 | D16: 0.287 | E16: 0.299 | F16: 0.264 | G16: 0.198 | H16: =AVERAGE(C16:G16) -> 0.2742 | I16: =MIN(C16:G16) -> 0.198 | J16: =_xlfn.QUARTILE.INC(C16:G16,1) -> 0.264 | K16: =MEDIAN(C16:G16) -> 0.287 | L16: =_xlfn.QUARTILE.INC(C16:G16,3) -> 0.299 | M16: =MAX(C16:G16) -> 0.323 | N16: 0.18
H17: 2001 | I17: Minimum | J17: 25th percentile | K17: Median | L17: 75th percentile | M17: Maximum | N17: Pharmacia
H18: COGS as % of sales | I18: =I5 -> 0.187152 | J18: =J5 -> 0.21286622 | K18: =K5 -> 0.24233756 | L18: =L5 -> 0.3031634 | M18: =M5 -> 0.47579105 | N18: =N5 -> 0.215
H19: SG&A as % of sales | I19: =I6 -> 0.25009146 | J19: =J6 -> 0.2544575 | K19: =K6 -> 0.25882353 | L19: =L6 -> 0.29056416 | M19: =M6 -> 0.32230479 | N19: =N6 -> 0.397
H20: R&D as % of sales | I20: =I7 -> 0.089183382 | J20: =J7 -> 0.11642156 | K20: =K7 -> 0.14365974 | L20: =L7 -> 0.17089792 | M20: =M7 -> 0.19813611 | N20: =N7 -> 0.164
H21: NC-WC as % of sales | I21: =I10 -> -0.17712793 | J21: =J10 -> -0.058921377 | K21: =K10 -> 0.046199549 | L21: =L10 -> 0.17121576 | M21: =M10 -> 0.2046868 | N21: =N10 -> 0.26786993
H22: Capex as % of sales | I22: =I13 -> 0.056874409 | J22: =J13 -> 0.071457081 | K22: =K13 -> 0.076586528 | L22: =L13 -> 0.0777504 | M22: =M13 -> 0.13760923 | N22: =N13 -> 0.135
H23: EBITDA% margin | I23: =I15 -> 0.27 | J23: =J15 -> 0.307 | K23: =K15 -> 0.327 | L23: =L15 -> 0.333 | M23: =M15 -> 0.363 | N23: =N15 -> 0.224
H24: EBIT% margin | I24: =I16 -> 0.198 | J24: =J16 -> 0.264 | K24: =K16 -> 0.287 | L24: =L16 -> 0.299 | M24: =M16 -> 0.323 | N24: =N16 -> 0.18 | O24: Because the EBIT margin of Pharmacia in the projection years is higher than the peer groups, therefore there will be no adjustment for this part

Sheet 4. ADJUSTMENTS >>>>

Sheet 4.1 Operating lease converter
B1: Operating Lease Converter
B2: Inputs
B3: Operating lease expense in current year = | F3: 675
B4: Operating Lease Assumptions (Average of last 3 years)
B5: Year | C5: Assumption | D5: ! Year 1 is next year, ….
B6: 1 | C6: 696
B7: 2 | C7: 804
B8: 3 | C8: 804
B9: 4 | C9: 804
B10: 5 | C10: 804
B11: 6 and beyond | C11: 804
B13: Output
B14: Pre-tax Cost of Debt = | D14: 0.0459 | E14: ! If you do not have a cost of debt, use the ratings estimator
B16: From the current financial statements, enter the following
B17: Reported Operating Income (EBIT) = | E17: 1846 | F17: ! This is the EBIT reported in the current income statement
B18: Reported Debt = | E18: 1048 | F18: ! This is the interest-bearing debt reported on the balance sheet
B20: Number of years embedded in yr 6 estimate = | E20: =IF(C11>0,ROUND(C11/AVERAGE(C6:C10),0),0) -> 1 | F20: ! I use the average lease expense over the first five years
F21: to estimate the number of years of expenses in yr 6
B22: Converting Operating Leases into debt
B23: Year | C23: Assumption | D23: Present Value
B24: =B6 -> 1 | C24: =C6 -> 696 | D24: =C24/(1+$D$14)^B24 -> 665.45559
B25: =B7 -> 2 | C25: =C7 -> 804 | D25: =C25/(1+$D$14)^B25 -> 734.98034
B26: =B8 -> 3 | C26: =C8 -> 804 | D26: =C26/(1+$D$14)^B26 -> 702.72525
B27: =B9 -> 4 | C27: =C9 -> 804 | D27: =C27/(1+$D$14)^B27 -> 671.8857
B28: =B10 -> 5 | C28: =C10 -> 804 | D28: =C28/(1+$D$14)^B28 -> 642.39956
B29: =B11 -> 6 and beyond | C29: =IF(C11>0,IF(E20>0,C11/E20,C11),0) -> 804 | D29: =IF(E20>0,(C29*(1-(1+D14)^(-E20))/D14)/(1+$D$14)^5,C29/(1+D14)^6) -> 614.20744 | E29: ! Commitment beyond year 6 converted into an annuity for ten years
B30: Debt Value of leases = | D30: =SUM(D24:D29) -> 4031.6539
B32: Restated Financials
B33: Depreciation on Operating Lease Asset = | G33: =D30/(5+E20) -> 671.94231 | H33: ! I use straight line depreciation
B34: Adjustment to Operating Earnings = | G34: =F3-G33 -> 3.0576875 | H34: ! Operating lease expense - Depreciation
B35: Adjustment to Total Debt outstanding = | G35: =D30 -> 4031.6539

Sheet 4.2 R&D converter
B1: R & D Converter
B2: This spreadsheet converts R&D expenses from operating to capital expenses. It makes the appropriate adjustments to operating income, net
B3: income, the book value of assets and the book value of equity.
B5: Inputs
B6: Over how many years do you want to amortize R&D expenses | G6: 10 | H6: ! If in doubt, use the lookup table below
B7: Enter the current year's R&D expense = | G7: 2263 | H7: The maximum allowed is ten years
B8: Enter R& D expenses for past years: the number of years that you will need to enter will be determined by the amortization period
B9: Do not input numbers in the first column (Year). It will get automatically updated based on the input above.
B10: Year | C10: R&D-Expenses
B11: -1 | C11: 2165 | D11: ! Year -1 is the year prior to the current year
B12: =IF((0-B11)<$G$6,IF(B11>-1,,B11-1),) -> -2 | C12: 2815 | D12: ! Year -2 is the two years prior to the current year | I12: Projetction of R&D depreciation growth rate
B13: =IF((0-B12)<$G$6,IF(B12>-1,,B12-1),) -> -3 | C13: 1238 | I13: Year | J13: R&D Expense | K13: Unamortized portion | M13: Amortization this year
B14: =IF((0-B13)<$G$6,IF(B13>-1,,B13-1),) -> -4 | C14: 1044 | I14: Current | J14: =-'3.3 Income Statement'!N10 -> 2853.3089 | K14: =1 -> 1 | L14: =J14*K14 -> 2853.3089
B15: =IF((0-B14)<$G$6,IF(B14>-1,,B14-1),) -> -5 | C15: 702 | I15: =B11 -> -1 | J15: =-'3.3 Income Statement'!M10 -> 2722.8828 | K15: =IF(I15<0,($G$6+I15)/$G$6,0) -> 0.9 | L15: =J15*K15 -> 2450.5945 | M15: =IF(I15<0,J15/$G$6,0) -> 272.28828
B16: =IF((0-B15)<$G$6,IF(B15>-1,,B15-1),) -> -6 | C16: 609 | I16: =B12 -> -2 | J16: =-'3.3 Income Statement'!L10 -> 2598.4186 | K16: =IF(I16<0,($G$6+I16)/$G$6,0) -> 0.8 | L16: =J16*K16 -> 2078.7348 | M16: =IF(I16<0,J16/$G$6,0) -> 259.84186
B17: =IF((0-B16)<$G$6,IF(B16>-1,,B16-1),) -> -7 | C17: 626 | I17: =B13 -> -3 | J17: =-'3.3 Income Statement'!K10 -> 2479.6436 | K17: =IF(I17<0,($G$6+I17)/$G$6,0) -> 0.7 | L17: =J17*K17 -> 1735.7505 | M17: =IF(I17<0,J17/$G$6,0) -> 247.96436
B18: =IF((0-B17)<$G$6,IF(B17>-1,,B17-1),) -> -8 | C18: 651 | I18: =B14 -> -4 | J18: =-'3.3 Income Statement'!J10 -> 2366.298 | K18: =IF(I18<0,($G$6+I18)/$G$6,0) -> 0.6 | L18: =J18*K18 -> 1419.7788 | M18: =IF(I18<0,J18/$G$6,0) -> 236.6298
B19: =IF((0-B18)<$G$6,IF(B18>-1,,B18-1),) -> -9 | C19: 610 | I19: =B15 -> -5 | J19: =G7 -> 2263 | K19: =IF(I19<0,($G$6+I19)/$G$6,0) -> 0.5 | L19: =J19*K19 -> 1131.5 | M19: =IF(I19<0,J19/$G$6,0) -> 226.3
B20: =IF((0-B19)<$G$6,IF(B19>-1,,B19-1),) -> -10 | C20: 612 | I20: =B16 -> -6 | J20: =C11 -> 2165 | K20: =IF(I20<0,($G$6+I20)/$G$6,0) -> 0.4 | L20: =J20*K20 -> 866 | M20: =IF(I20<0,J20/$G$6,0) -> 216.5
I21: =B17 -> -7 | J21: =C12 -> 2815 | K21: =IF(I21<0,($G$6+I21)/$G$6,0) -> 0.3 | L21: =J21*K21 -> 844.5 | M21: =IF(I21<0,J21/$G$6,0) -> 281.5
B22: Output | I22: =B18 -> -8 | J22: =C13 -> 1238 | K22: =IF(I22<0,($G$6+I22)/$G$6,0) -> 0.2 | L22: =J22*K22 -> 247.6 | M22: =IF(I22<0,J22/$G$6,0) -> 123.8
B23: Year | C23: R&D Expense | D23: Unamortized portion | F23: Amortization this year | I23: =B19 -> -9 | J23: =C14 -> 1044 | K23: =IF(I23<0,($G$6+I23)/$G$6,0) -> 0.1 | L23: =J23*K23 -> 104.4 | M23: =IF(I23<0,J23/$G$6,0) -> 104.4
B24: Current | C24: =G7 -> 2263 | D24: =1 -> 1 | E24: =C24*D24 -> 2263 | I24: =B20 -> -10 | J24: =C15 -> 702 | K24: =IF(I24<0,($G$6+I24)/$G$6,0) -> 0 | L24: =J24*K24 -> 0 | M24: =IF(I24<0,J24/$G$6,0) -> 70.2
B25: =B11 -> -1 | C25: =C11 -> 2165 | D25: =IF(B25<0,($G$6+B25)/$G$6,0) -> 0.9 | E25: =C25*D25 -> 1948.5 | F25: =IF(B25<0,C25/$G$6,0) -> 216.5 | I25: Total | L25: =SUM(L14:L24) -> 13732.168 | M25: =SUM(M15:M24) -> 2039.4243
B26: =B12 -> -2 | C26: =C12 -> 2815 | D26: =IF(B26<0,($G$6+B26)/$G$6,0) -> 0.8 | E26: =C26*D26 -> 2252 | F26: =IF(B26<0,C26/$G$6,0) -> 281.5 | I26: Yearly growth rate of R&D depreciation | M26: =(1+M25/E37-1)^(1/5)-1 -> 0.12994239
B27: =B13 -> -3 | C27: =C13 -> 1238 | D27: =IF(B27<0,($G$6+B27)/$G$6,0) -> 0.7 | E27: =C27*D27 -> 866.6 | F27: =IF(B27<0,C27/$G$6,0) -> 123.8 | I27: Yearly growth rate of value of R&D asset | M27: =(1+L25/E35-1)^(1/5)-1 -> 0.089874658
B28: =B14 -> -4 | C28: =C14 -> 1044 | D28: =IF(B28<0,($G$6+B28)/$G$6,0) -> 0.6 | E28: =C28*D28 -> 626.4 | F28: =IF(B28<0,C28/$G$6,0) -> 104.4
B29: =B15 -> -5 | C29: =C15 -> 702 | D29: =IF(B29<0,($G$6+B29)/$G$6,0) -> 0.5 | E29: =C29*D29 -> 351 | F29: =IF(B29<0,C29/$G$6,0) -> 70.2
B30: =B16 -> -6 | C30: =C16 -> 609 | D30: =IF(B30<0,($G$6+B30)/$G$6,0) -> 0.4 | E30: =C30*D30 -> 243.6 | F30: =IF(B30<0,C30/$G$6,0) -> 60.9
B31: =B17 -> -7 | C31: =C17 -> 626 | D31: =IF(B31<0,($G$6+B31)/$G$6,0) -> 0.3 | E31: =C31*D31 -> 187.8 | F31: =IF(B31<0,C31/$G$6,0) -> 62.6
B32: =B18 -> -8 | C32: =C18 -> 651 | D32: =IF(B32<0,($G$6+B32)/$G$6,0) -> 0.2 | E32: =C32*D32 -> 130.2 | F32: =IF(B32<0,C32/$G$6,0) -> 65.1
B33: =B19 -> -9 | C33: =C19 -> 610 | D33: =IF(B33<0,($G$6+B33)/$G$6,0) -> 0.1 | E33: =C33*D33 -> 61 | F33: =IF(B33<0,C33/$G$6,0) -> 61
B34: =B20 -> -10 | C34: =C20 -> 612 | D34: =IF(B34<0,($G$6+B34)/$G$6,0) -> 0 | E34: =C34*D34 -> 0 | F34: =IF(B34<0,C34/$G$6,0) -> 61.2
B35: Value of Research Asset = | E35: =SUM(E24:E34) -> 8930.1 | F35: =SUM(F25:F34) -> 1107.2
B37: Amortization of asset for current year = | E37: =F35 -> 1107.2
B39: Adjustment to Operating Income = | E39: =G7-E37 -> 1155.8 | F39: ! A positive number indicates an increase in operating income (add to reported EBIT) | M39: =E39/G7 -> 0.51073796
B40: Tax Effect of R&D Expensing | E40: =(G7-E37)*'5.1 Free Cash Flow'!I38 -> 462.32
B43: Look Up Table for Amortization Periods
B44: Industry Name | C44: Amortization Period
B45: Advertising | C45: 2
B46: Aerospace/Defense | C46: 10 | E46: Non-technological Service | G46: 2 years
B47: Air Transport | C47: 10 | E47: Retail, Tech Service | G47: 3 years
B48: Aluminum | C48: 5 | E48: Light Manufacturing | G48: 5 years
B49: Apparel | C49: 3 | E49: Heavy Manufacturing | G49: 10 years
B50: Auto & Truck | C50: 10 | E50: Research, with Patenting | G50: 10 years
B51: Auto Parts (OEM) | C51: 5 | E51: Long Gestation Period | G51: 10 years
B52: Auto Parts (Replacement) | C52: 5
B53: Bank | C53: 2
B54: Bank (Canadian) | C54: 2
B55: Bank (Foreign) | C55: 2
B56: Bank (Midwest) | C56: 2
B57: Beverage (Alcoholic) | C57: 3
B58: Beverage (Soft Drink) | C58: 3
B59: Building Materials | C59: 5
B60: Cable TV | C60: 10
B61: Canadian Energy | C61: 10
B62: Cement & Aggregates | C62: 10
B63: Chemical (Basic) | C63: 10
... B142: Water Utility | C142: 10

Sheet 5. VALUATION >>>>

Sheet 5.1 Free Cash Flow
B2: Free Cash Flow Analysis
B8: Income Statement | E8: Actual | G8: Projections
B9: In Millions of USD | E9: 1997 | F9: 1998 | G9: 1999 | H9: 2000 | I9: 2001 | J9: Adj. | K9: 2001 | L9: 2002 | M9: 2003 | N9: 2004 | O9: 2005 | P9: 2006
C11: Unlevered Free Cash Flow
L13: 1 | M13: 2 | N13: 3 | O13: 4 | P13: 5
C15: EBITDA | E15: ='3.3 Income Statement'!E11 -> 1670 | F15: ='3.3 Income Statement'!F11 -> 1120 | G15: ='3.3 Income Statement'!G11 -> 3314 | H15: ='3.3 Income Statement'!H11 -> 2632 | I15: ='3.3 Income Statement'!I11 -> 3102 | J15: 0 | K15: =I15+J15 -> 3102 | L15: ='3.3 Income Statement'!J11 -> 5391.6689 | M15: ='3.3 Income Statement'!K11 -> 6509.8048 | N15: ='3.3 Income Statement'!L11 -> 6821.6244 | O15: ='3.3 Income Statement'!M11 -> 7148.3802 | P15: ='3.3 Income Statement'!N11 -> 7490.7876
C17: Depreciation & Amortization | E17: ='3.3 Income Statement'!E14 -> -487 | F17: ='3.3 Income Statement'!F14 -> -518 | G17: ='3.3 Income Statement'!G14 -> -1145 | H17: ='3.3 Income Statement'!H14 -> -633 | I17: ='3.3 Income Statement'!I14 -> -611 | J17: 0 | K17: ='3.3 Income Statement'!I14 -> -611 | L17: ='3.3 Income Statement'!J14 -> -870.72789 | M17: ='3.3 Income Statement'!K14 -> -912.43575 | N17: ='3.3 Income Statement'!L14 -> -956.14142 | O17: ='3.3 Income Statement'!M14 -> -1001.9406 | P17: ='3.3 Income Statement'!N14 -> -1049.9336
C18: EBIT | E18: =SUM(E15+E17) -> 1183 | F18: =SUM(F15+F17) -> 602 | G18: =SUM(G15+G17) -> 2169 | H18: =SUM(H15+H17) -> 1999 | I18: =SUM(I15+I17) -> 2491 | J18: =E42+E44+E43 -> 1621.1777 | K18: =I18+J18 -> 4112.1777 | L18: ='3.3 Income Statement'!J15+F42+F43+F44 -> 6085.3147 | M18: ='3.3 Income Statement'!K15+G42+G43+G44 -> 7092.8324 | N18: ='3.3 Income Statement'!L15+H42+H43+H44 -> 7270.0629 | O18: ='3.3 Income Statement'!M15+I42+I43+I44 -> 7434.684 | P18: ='3.3 Income Statement'!N15+J42+J43+J44 -> 7583.3502
C20: Effective tax rate | E20: =IF($C$20="Marginal tax rate",E38,E37) -> 0.1967 | F20: =IF($C$20="Marginal tax rate",F38,F37) -> 0.1967 | G20: =IF($C$20="Marginal tax rate",G38,G37) -> 0.3119 | H20: =IF($C$20="Marginal tax rate",H38,H37) -> 0.2269 | I20: =IF($C$20="Marginal tax rate",I38,I37) -> 0.1873 | J20: 0 | K20: 0.22 | L20: 0.4 | M20: 0.4 | N20: 0.4 | O20: 0.4 | P20: 0.4
C21: EBIT*(1-Tax rate) | E21: =E18*(1-E20) -> 950.3039 | F21: =F18*(1-F20) -> 483.5866 | G21: =G18*(1-G20) -> 1492.4889 | H21: =H18*(1-H20) -> 1545.4269 | I21: =I18*(1-I20) -> 2024.4357 | J21: =J18*(1-I20) -> 1317.5311 | K21: =I21+J21 -> 3341.9668 | L21: =L18*(1-L20) -> 3651.1888 | M21: =M18*(1-M20) -> 4255.6995 | N21: =N18*(1-N20) -> 4362.0378 | O21: =O18*(1-O20) -> 4460.8104 | P21: =P18*(1-P20) -> 4550.0101
C23: Depreciation & amortization | E23: =-E17 -> 487 | F23: =-F17 -> 518 | G23: =-G17 -> 1145 | H23: =-H17 -> 633 | I23: =-I17 -> 611 | J23: =E48+E49 -> 1779.1423 | K23: =I23+J23 -> 2390.1423 | L23: =-L17+F48+F49 -> 2793.7424 | M23: =-M17+G48+G49 -> 2998.0176 | N23: =-N17+H48+H49 -> 3225.415 | O23: =-O17+I48+I49 -> 3478.7752 | P23: =-P17+J48+J49 -> 3761.3002
C24: Δ net Working Capital | E24: ='3.2 Balance Sheet'!E49 -> 892 | F24: ='3.2 Balance Sheet'!F49 -> 76 | G24: ='3.2 Balance Sheet'!G49 -> 1505 | H24: ='3.2 Balance Sheet'!H49 -> -2088 | I24: ='3.2 Balance Sheet'!I49 -> 56 | J24: 0 | K24: =I24+J24 -> 56 | L24: ='3.2 Balance Sheet'!J49 -> 1200.5492 | M24: ='3.2 Balance Sheet'!K49 -> 146.9835 | N24: ='3.2 Balance Sheet'!L49 -> 154.02401 | O24: ='3.2 Balance Sheet'!M49 -> 161.40176 | P24: ='3.2 Balance Sheet'!N49 -> 169.13291
C25: Capex | E25: ='3.4 Cash Flow Statement'!E9 -> -644 | F25: ='3.4 Cash Flow Statement'!F9 -> -859 | G25: ='3.4 Cash Flow Statement'!G9 -> -1678 | H25: ='3.4 Cash Flow Statement'!H9 -> -774 | I25: ='3.4 Cash Flow Statement'!I9 -> -1020 | J25: 0 | K25: =I25+J25 -> -1020 | L25: ='3.4 Cash Flow Statement'!J9 -> -1289.4393 | M25: ='3.4 Cash Flow Statement'!K9 -> -1351.2035 | N25: ='3.4 Cash Flow Statement'!L9 -> -1415.9261 | O25: ='3.4 Cash Flow Statement'!M9 -> -1483.749 | P25: ='3.4 Cash Flow Statement'!N9 -> -1554.8206
C27: FCF | E27: =E21+E23-E24+E25 -> -98.6961 | F27: =F21+F23-F24+F25 -> 66.5866 | G27: =G21+G23-G24+G25 -> -545.5111 | H27: =H21+H23-H24+H25 -> 3492.4269 | I27: =I21+I23-I24+I25 -> 1559.4357 | J27: NA | K27: =K21+K23-K24+K25 -> 4656.1091 | L27: =L21+L23-L24+L25 -> 3954.9428 | M27: =M21+M23-M24+M25 -> 5755.5301 | N27: =N21+N23-N24+N25 -> 6017.5026 | O27: =O21+O23-O24+O25 -> 6294.4348 | P27: =P21+P23-P24+P25 -> 6587.3568
C29: Unleverd FCF | L29: =L27/(1+$O$47)^'5.1 Free Cash Flow'!L13 -> 3673.8902 | M29: =M27/(1+$O$47)^'5.1 Free Cash Flow'!M13 -> 4966.578 | N29: =N27/(1+$O$47)^'5.1 Free Cash Flow'!N13 -> 4823.6322 | O29: =O27/(1+$O$47)^'5.1 Free Cash Flow'!O13 -> 4687.061 | P29: =P27/(1+$O$47)^'5.1 Free Cash Flow'!P13 -> 4556.6012
C30: PV of UFCF | P30: =SUM(L29:P29) -> 22707.762
C31: Terminal Value (TV) | P31: =P29*(1+O75)/(O47-O75) -> 31200.728
C32: Entreprise Value (EV) | P32: =P30+P31 -> 53908.49
C33: Equity Value | P33: =P32*'2.1 WACC'!G6 -> 50474.52
C34: Share Price ($) | P34: =P32/'1.2 Income Statement Raw'!Q35 -> 40.777981 | Q34: =IF(P34<P35,CONCATENATE("Undervalued by ",(-1*P36),"%"),CONCATENATE("Overvalued by ",(P36),"%")) -> Overvalued by 1,72078178059764%
P35: ='1.5 Stock Value'!V6 -> 40.088151
C36: Tax rate | E36: 1997 | F36: 1998 | G36: 1999 | H36: 2000 | I36: 2001 | N36: Sensitivity Analysis | P36: =(P34-P35)/P35*100 -> 1.7207818
C37: Effective tax rate | E37: 0.1967 | F37: 0.1967 | G37: 0.3119 | H37: 0.2269 | I37: 0.1873
C38: Marginal tax rate | E38: 0.4 | F38: 0.4 | G38: 0.4 | H38: 0.4 | I38: 0.4 | N38: WACC | O38: =P32 -> 53908.49
N39: =N40-0.01 -> 0.0565 | O39: =$P$30+$P$29*(1+$O$75)/(N39-$O$75) -> 59233.767
C40: EBIT adjustments | E40: 2001 | F40: 2002 | G40: 2003 | H40: 2004 | I40: 2005 | J40: 2006 | N40: =N41-0.01 -> 0.0665 | O40: =$P$30+$P$29*(1+$O$75)/(N40-$O$75) -> 56361.768
C41: R&D adjustments | F41: 1 | G41: 2 | H41: 3 | I41: 4 | J41: 5 | N41: =O47 -> 0.0765 | O41: =$P$30+$P$29*(1+$O$75)/(N41-$O$75) -> 53908.49
C42: R&D | E42: ='4.2 R&D converter'!E39 -> 1155.8 | F42: =-'3.3 Income Statement'!J10-'4.2 R&D converter'!$E$37*POWER((1+'4.2 R&D converter'!$M$26),F41) -> 1115.2257 | G42: =-'3.3 Income Statement'!K10-'4.2 R&D converter'!$E$37*POWER((1+'4.2 R&D converter'!$M$26),G41) -> 1066.0041 | H42: =-'3.3 Income Statement'!L10-'4.2 R&D converter'!$E$37*POWER((1+'4.2 R&D converter'!$M$26),H41) -> 1001.0873 | I42: =-'3.3 Income Statement'!M10-'4.2 R&D converter'!$E$37*POWER((1+'4.2 R&D converter'!$M$26),I41) -> 917.99053 | J42: =-'3.3 Income Statement'!N10-'4.2 R&D converter'!$E$37*POWER((1+'4.2 R&D converter'!$M$26),J41) -> 813.88459
C43: R&D tax effect | E43: ='4.2 R&D converter'!E40 -> 462.32 | F43: =F42*L20 -> 446.09029 | G43: =G42*M20 -> 426.40164 | H43: =H42*N20 -> 400.43493 | I43: =I42*O20 -> 367.19621 | J43: =J42*P20 -> 325.55384 | N43: =N41+0.01 -> 0.0865 | O43: =$P$30+$P$29*(1+$O$75)/(N43-$O$75) -> 51788.584
C44: Operating leases | E44: ='4.1 Operating lease converter'!G34 -> 3.0576875 | F44: =$E$44 -> 3.0576875 | G44: =$E$44 -> 3.0576875 | H44: =$E$44 -> 3.0576875 | I44: =$E$44 -> 3.0576875 | J44: =$E$44 -> 3.0576875 | N44: =N43+0.01 -> 0.0965 | O44: =$P$30+$P$29*(1+$O$75)/(N44-$O$75) -> 49938.42
N45: =N44+0.01 -> 0.1065 | O45: =$P$30+$P$29*(1+$O$75)/(N45-$O$75) -> 48309.595
C47: Depreciaton adjustments | N47: WACC | O47: ='2.1 WACC'!F12 -> 0.0765
C48: R&D | E48: ='4.2 R&D converter'!E37 -> 1107.2 | F48: =E48*(1+'4.2 R&D converter'!$M$26) -> 1251.0722 | G48: =F48*(1+'4.2 R&D converter'!$M$26) -> 1413.6395 | H48: =G48*(1+'4.2 R&D converter'!$M$26) -> 1597.3312 | I48: =H48*(1+'4.2 R&D converter'!$M$26) -> 1804.8923 | J48: =I48*(1+'4.2 R&D converter'!$M$26) -> 2039.4243
C49: Operating leases | E49: ='4.1 Operating lease converter'!G33 -> 671.94231 | F49: =$E$49 -> 671.94231 | G49: =$E$49 -> 671.94231 | H49: =$E$49 -> 671.94231 | I49: =$E$49 -> 671.94231 | J49: =$E$49 -> 671.94231
C50: Capex adjustements
C51: R&D | E51: =-'4.2 R&D converter'!G7 -> -2263 | F51: ='3.3 Income Statement'!J10 -> -2366.298 | G51: ='3.3 Income Statement'!K10 -> -2479.6436 | H51: ='3.3 Income Statement'!L10 -> -2598.4186 | I51: ='3.3 Income Statement'!M10 -> -2722.8828 | J51: ='3.3 Income Statement'!N10 -> -2853.3089
C52: Operating leases | E52: =-'4.1 Operating lease converter'!F3 -> -675 | F52: =$E$52 -> -675 | G52: =$E$52 -> -675 | H52: =$E$52 -> -675 | I52: =$E$52 -> -675 | J52: =$E$52 -> -675
C54: Expected Growth Rate | F54: 1997 | G54: 1998 | H54: 1999 | I54: 2000 | J54: 2001 | K54: 2002 | L54: 2003 | M54: 2004 | N54: 2005 | O54: 2006
C55: Book value of equity | F55: ='3.2 Balance Sheet'!E33 -> 4104 | G55: ='3.2 Balance Sheet'!F33 -> 4986 | H55: ='3.2 Balance Sheet'!G33 -> 10911 | I55: ='3.2 Balance Sheet'!H33 -> 11921 | J55: ='3.2 Balance Sheet'!I33 -> 12390
C56: Book value of debt | F56: ='3.2 Balance Sheet'!E29+'3.2 Balance Sheet'!E25 -> 3705 | G56: ='3.2 Balance Sheet'!F29+'3.2 Balance Sheet'!F25 -> 7328 | H56: ='3.2 Balance Sheet'!G29+'3.2 Balance Sheet'!G25 -> 8228 | I56: ='3.2 Balance Sheet'!H29+'3.2 Balance Sheet'!H25 -> 4299 | J56: ='3.2 Balance Sheet'!I29+'3.2 Balance Sheet'!I25 -> 3082
C57: Book value of capital | F57: =SUM(F55:F56) -> 7809 | G57: =SUM(G55:G56) -> 12314 | H57: =SUM(H55:H56) -> 19139 | I57: =SUM(I55:I56) -> 16220 | J57: =SUM(J55:J56) -> 15472 | K57: =J57+1250 -> 16722 | L57: =K57+1250 -> 17972 | M57: =L57+1250 -> 19222 | N57: =M57+1250 -> 20472 | O57: =20000+1250 -> 21250
C58: Value of Research Asset | J58: ='4.2 R&D converter'!E35 -> 8930.1 | K58: ='4.2 R&D converter'!$E$35*POWER(1+'4.2 R&D converter'!$M$27,'5.1 Free Cash Flow'!L13) -> 9732.6897 | L58: ='4.2 R&D converter'!$E$35*POWER(1+'4.2 R&D converter'!$M$27,'5.1 Free Cash Flow'!M13) -> 10607.412 | M58: ='4.2 R&D converter'!$E$35*POWER(1+'4.2 R&D converter'!$M$27,'5.1 Free Cash Flow'!N13) -> 11560.749 | N58: ='4.2 R&D converter'!$E$35*POWER(1+'4.2 R&D converter'!$M$27,'5.1 Free Cash Flow'!O13) -> 12599.768 | O58: ='4.2 R&D converter'!$E$35*POWER(1+'4.2 R&D converter'!$M$27,'5.1 Free Cash Flow'!P13) -> 13732.168
C60: EBIT*(1-Tax rate) | F60: =E21 -> 950.3039 | G60: =F21 -> 483.5866 | H60: =G21 -> 1492.4889 | I60: =H21 -> 1545.4269 | J60: =I21 -> 2024.4357 | K60: =L21 -> 3651.1888 | L60: =M21 -> 4255.6995 | M60: =N21 -> 4362.0378 | N60: =O21 -> 4460.8104 | O60: =P21 -> 4550.0101
C62: Return on invested Capital* | G62: =G60/F57 -> 0.061926828 | H62: =H60/G57 -> 0.12120261 | I62: =I60/H57 -> 0.080747526 | J62: =J60/I57 -> 0.12481108 | K62: =(K60+F48)/(J57+J58) -> 0.20089505 | L62: =(L60+G48)/(K57+K58) -> 0.21430374 | M62: =(M60+H48)/(L57+L58) -> 0.20851965 | N62: =(N60+I48)/(M57+M58) -> 0.20354591 | O62: =(O60+J48)/(N57+N58) -> 0.19924651
C64: Net Capex | F64: ='3.4 Cash Flow Statement'!E9 -> -644 | G64: ='3.4 Cash Flow Statement'!F9 -> -859 | H64: ='3.4 Cash Flow Statement'!G9 -> -1678 | I64: ='3.4 Cash Flow Statement'!H9 -> -774 | J64: ='3.4 Cash Flow Statement'!I9 -> -1020 | K64: ='3.4 Cash Flow Statement'!J9 -> -1289.4393 | L64: ='3.4 Cash Flow Statement'!K9 -> -1351.2035 | M64: ='3.4 Cash Flow Statement'!L9 -> -1415.9261 | ... O64: ='3.4 Cash Flow Statement'!N9 -> -1554.8206
C65: Change in NCWC | F65: ='3.2 Balance Sheet'!E49 -> 892 | G65: ='3.2 Balance Sheet'!F49 -> 76 | H65: ='3.2 Balance Sheet'!G49 -> 1505 | I65: ='3.2 Balance Sheet'!H49 -> -2088 | J65: ='3.2 Balance Sheet'!I49 -> 56 | K65: =L24 -> 1200.5492 | L65: =M24 -> 146.9835 | M65: =N24 -> 154.02401 | N65: =O24 -> 161.40176 | O65: =P24 -> 169.13291
C67: Gross value of assets | F67: =9339+'3.2 Balance Sheet'!E7+'3.2 Balance Sheet'!E9 -> 10847 | G67: =9339+'3.2 Balance Sheet'!F7+'3.2 Balance Sheet'!F9 -> 11150 | H67: =9339+'3.2 Balance Sheet'!G7+'3.2 Balance Sheet'!G9 -> 13844 | I67: =9339+'3.2 Balance Sheet'!H7+'3.2 Balance Sheet'!H9 -> 12893 | J67: =9339+'3.2 Balance Sheet'!I7+'3.2 Balance Sheet'!I9 -> 12298 | K67: =((K54-$F$54)*1704.2+11964)*1.01 -> 20689.85 | L67: =(L54-$F$54)*1704.2+11964 -> 22189.2 | M67: =(M54-$F$54)*1704.2+11964 -> 23893.4 | N67: =(N54-$F$54)*1704.2+11964 -> 25597.6 | O67: =(O54-$F$54)*1704.2+11964 -> 27301.8
C68: Accumulated depreciation & impairment | F68: -2320 | G68: -4933 | H68: -3403 | I68: -3392 | J68: -4005 | K68: =J68 -> -4005 | L68: =K68 -> -4005 | M68: =L68 -> -4005 | N68: =M68 -> -4005 | O68: =N68 -> -4005
C69: Book Value of Asset | F69: =SUM(F67,F68) -> 8527 | G69: =SUM(G67,G68) -> 6217 | H69: =SUM(H67,H68) -> 10441 | I69: =SUM(I67,I68) -> 9501 | J69: =SUM(J67,J68) -> 8293 | K69: =SUM(K67,K68) -> 16684.85 | L69: =SUM(L67,L68) -> 18184.2 | M69: =SUM(M67,M68) -> 19888.4 | ... O69: =SUM(O67,O68) -> 23296.8
C70: Current non-adjusted depreciation expense | F70: =E17 -> -487 | G70: =F17 -> -518 | H70: =G17 -> -1145 | I70: =H17 -> -633 | J70: =I17 -> -611 | K70: =L17 -> -870.72789 | L70: =M17 -> -912.43575 | M70: =N17 -> -956.14142 | N70: =O17 -> -1001.9406 | O70: =P17 -> -1049.9336
C71: Average age of asset | F71: =-F67/F70 -> 22.273101 | G71: =-G67/G70 -> 21.525097 | H71: =-H67/H70 -> 12.09083 | I71: =-I67/I70 -> 20.368088 | J71: =-J67/J70 -> 20.12766 | K71: =-K67/K70 -> 23.761557 | L71: =-L67/L70 -> 24.318644 | M71: =-M67/M70 -> 24.989399 | ... O71: =-O67/O70 -> 26.00336
C73: American inflation rate | F73: 0.017 | G73: 0.0161 | H73: 0.0268 | I73: 0.0339 | J73: 0.0155 | K73: 0.0238 | L73: 0.0188 | M73: 0.0326 | N73: 0.0342 | O73: 0.0254
C75: EBIT Growth rate | G75: =(G64+G65)/G60*G62 -> -0.10026892 | H75: =(H64+H65)/H60*H62 -> -0.01404905 | I75: =(I64+I65)/I60*I62 -> -0.14953759 | J75: =(J64+J65)/J60*J62 -> -0.059432799 | K75: =(K64+K65)/K60*K62 -> -0.0048908995 | L75: =(L64+L65)/L60*L62 -> -0.06064076 | M75: =(M64+M65)/M60*M62 -> -0.060323043 | N75: =(N64+N65)/N60*N62 -> -0.060338446 | O75: =(O64+O65)/O60*O62 -> -0.060679741
C76: Source: http://www.inflation.eu/inflation-rates/united-states/historic-inflation/cpi-inflation-united-states.aspx
C77: gEBIT = (Net Capital Expenditures + Change in WC)/EBIT(1-t) * ROC
C78: *adjusted with R&D asset value from 2001 adj. To 2006E
C81: Expected Growth EPS | F81: 1997 | G81: 1998 | H81: 1999 | I81: 2000 | J81: 2001 | L81: Yearly Growth Rate
C82: EPS | F82: 1.25 | G82: 0.93 | H82: 1.15 | I82: 1.17 | J82: 1.44 | L82: 0.062
C83: ln(EPS) | F83: =LN(F82) -> 0.22314355 | G83: =LN(G82) -> -0.072570693 | H83: =LN(H82) -> 0.13976194 | I83: =LN(I82) -> 0.15700375 | J83: =LN(J82) -> 0.36464311 | L83: =5.13%/5 -> 0.01026

Sheet 5.2 Sensitivity Analysis
B2: Sensitivity Analysis
C4: 2006
B5: Unleverd FCF | C5: ='5.1 Free Cash Flow'!P29 -> 4556.6012
B6: PV of UFCF | C6: ='5.1 Free Cash Flow'!P30 -> 22707.762
B7: TV | C7: ='5.1 Free Cash Flow'!$P$31 -> 31200.728
B8: EV | C8: ='5.1 Free Cash Flow'!$P$32 -> 53908.49
B9: WACC | C9: ='5.1 Free Cash Flow'!O47 -> 0.0765
B10: gEBIT | C10: ='5.1 Free Cash Flow'!$O$75 -> -0.060679741
B12: $m | E12: Sensitivity Analysis
F13: WACC
C14: =C6+C5*(1+C10)/(C9-C10) -> 53908.49 | D14: =E14-0.01 -> 0.0565 | E14: =F14-0.01 -> 0.0665 | F14: =C9 -> 0.0765 | G14: =F14+0.01 -> 0.0865 | H14: =G14+0.01 -> 0.0965
C15: =C16-0.01 -> -0.070679741 | D15: =$C$6+$C$5*(1+$C15)/(D$14-$C15) -> 56003.488 | E15: =$C$6+$C$5*(1+$C15)/(E$14-$C15) -> 53576.328 | F15: =$C$6+$C$5*(1+$C15)/(F$14-$C15) -> 51478.99 | G15: =$C$6+$C$5*(1+$C15)/(G$14-$C15) -> 49648.523 | H15: =$C$6+$C$5*(1+$C15)/(H$14-$C15) -> 48037.038
C16: =C10 -> -0.060679741 | D16: =$C$6+$C$5*(1+$C16)/(D$14-$C16) -> 59233.767 | E16: =$C$6+$C$5*(1+$C16)/(E$14-$C16) -> 56361.768 | F16: =$C$6+$C$5*(1+$C16)/(F$14-$C16) -> 53908.49 | G16: =$C$6+$C$5*(1+$C16)/(G$14-$C16) -> 51788.584 | H16: =$C$6+$C$5*(1+$C16)/(H$14-$C16) -> 49938.42
B17: gEBIT | C17: =C16+0.01 -> -0.050679741 | D17: =$C$6+$C$5*(1+$C17)/(D$14-$C17) -> 63066.824 | E17: =$C$6+$C$5*(1+$C17)/(E$14-$C17) -> 59622.623 | F17: =$C$6+$C$5*(1+$C17)/(F$14-$C17) -> 56720.049 | G17: =$C$6+$C$5*(1+$C17)/(G$14-$C17) -> 54240.653 | H17: =$C$6+$C$5*(1+$C17)/(H$14-$C17) -> 52098.178
C18: =C17+0.01 -> -0.040679741 | D18: =$C$6+$C$5*(1+$C18)/(D$14-$C18) -> 67688.74 | E18: =$C$6+$C$5*(1+$C18)/(E$14-$C18) -> 63491.961 | F18: =$C$6+$C$5*(1+$C18)/(F$14-$C18) -> 60011.479 | G18: =$C$6+$C$5*(1+$C18)/(G$14-$C18) -> 57078.329 | H18: =$C$6+$C$5*(1+$C18)/(H$14-$C18) -> 54572.816
C19: =C18+0.01 -> -0.030679741 | D19: =$C$6+$C$5*(1+$C19)/(D$14-$C19) -> 73370.976 | E19: =$C$6+$C$5*(1+$C19)/(E$14-$C19) -> 68157.624 | F19: =$C$6+$C$5*(1+$C19)/(F$14-$C19) -> 63917.097 | G19: =$C$6+$C$5*(1+$C19)/(G$14-$C19) -> 60400.334 | H19: =$C$6+$C$5*(1+$C19)/(H$14-$C19) -> 57436.61
G21: EV | H21: EV adjusted | I21: Changes
B22: Sales growth decrease of 0,5% p.a. over the period | G22: =$F$16 -> 53908.49 | H22: 53147.4 | I22: =H22-G22 -> -761.09035
B23: Sales growth increase of 0,5% p.a. over the period | G23: =$F$16 -> 53908.49 | H23: 54711.2 | I23: =H23-G23 -> 802.70965
B24: R&D as % of sales decreases of 0,5% p.a. over the period | G24: =$F$16 -> 53908.49 | H24: 53670.6 | I24: =H24-G24 -> -237.89035
B25: R&D as % of sales increases of 0,5% p.a. over the period | G25: =$F$16 -> 53908.49 | H25: 54155.5 | I25: =H25-G25 -> 247.00965

Sheet 5.3 Multiples
B4: Sensitivity Analysis
B7: 2001 | H7: Pharmacia LLC
I8: Minimum | J8: 25th percentile | K8: Median | L8: 75th percentile | M8: Maximum
B9: Company | C9: Market Cap | D9: EV/Sales | E9: EV/EBITDA | F9: EV/EBIT | H9: EV/Sales | I9: =$D$34 -> 31820500 | J9: =$D$36-$D$34 -> 2075250 | K9: =$D$35-$D$36 -> 45378800 | L9: =$D$37-$D$35 -> 16671175 | M9: =$D$33-$D$37 -> 9476975
H10: EV/EBITDA | I10: =$E$34 -> 48112020 | J10: =$E$36-$E$34 -> 4280760 | K10: =$E$35-$E$36 -> 10732920 | L10: =$E$37-$E$35 -> 2388540 | M10: =$E$33-$E$37 -> 341220
B11: Abbott Laboratories (ABT US) - Adj Highlights | C11: 86665.1 | D11: 5.73 | E11: 21.23 | F11: 28.92 | H11: EV/EBIT | I11: =$F$34 -> 42870110 | J11: =$F$36-$F$34 -> 5156370 | K11: =$F$35-$F$36 -> 10686390 | L11: =$F$37-$F$35 -> 6825340 | M11: =$F$33-$F$37 -> 6501510
B12: Bristol-Myers Squibb (BMY US) - Adj Highlights | C12: 98677.68 | D12: 2.45 | E12: 16.89 | F12: 19.28 | H12: DCF | I12: =F53 -> 48037038 | M12: =F52 -> 73370976
B13: Schering-Plough (SGP US) - Adj Highlights | C13: 52461.65 | D13: 2.3 | E13: 15.51 | F13: 17.21
B14: Wyeth LLC (WYE US) - Adj Highlights | C14: 81030.2 | D14: 6.25 | E14: 20.35 | F14: 23.7
B15: Eli Lilly & Co (LLY US) - Adj Highlights | C15: 88295.28 | D15: 7.62 | E15: 21.01 | F15: 23.57
B16: Pharmacia LLC | C16: 55328.1
B18: Statistics | D18: EV/Sales | E18: EV/EBITDA | F18: EV/EBIT
B19: Maximum | D19: =MAX(D11:D15) -> 7.62 | E19: =MAX(E11:E15) -> 21.23 | F19: =MAX(F11:F15) -> 28.92
B20: Minimum | D20: =MIN(D11:D15) -> 2.3 | E20: =MIN(E11:E15) -> 15.51 | F20: =MIN(F11:F15) -> 17.21
B21: Median | D21: =MEDIAN(D11:D15) -> 5.73 | E21: =MEDIAN(E11:E15) -> 20.35 | F21: =MEDIAN(F11:F15) -> 23.57
B22: 25th percentile | D22: =QUARTILE(D11:D15,1) -> 2.45 | E22: =QUARTILE(E11:E15,1) -> 16.89 | F22: =QUARTILE(F11:F15,1) -> 19.28
B23: 75th percentile | D23: =_xlfn.QUARTILE.EXC(D11:D15,3) -> 6.935 | E23: =_xlfn.QUARTILE.EXC(E11:E15,3) -> 21.12 | F23: =_xlfn.QUARTILE.EXC(F11:F15,3) -> 26.31
B24: Average | D24: =AVERAGE(D11:D15) -> 4.87 | E24: =AVERAGE(E11:E15) -> 18.998 | F24: =AVERAGE(F11:F15) -> 22.536
B25: Standard Deviation | D25: =_xlfn.STDEV.P(D19:D23) -> 2.2331046 | E25: =_xlfn.STDEV.P(E19:E23) -> 2.3630489 | F25: =_xlfn.STDEV.P(F19:F23) -> 4.3283503
B26: Min Point | D26: =D20 -> 2.3 | E26: =E20 -> 15.51 | F26: =F20 -> 17.21
B27: 25th Point | D27: =D22-D20 -> 0.15 | E27: =E22-E20 -> 1.38 | F27: =F22-F20 -> 2.07
B28: Median Point | D28: =D21-D22 -> 3.28 | E28: =E21-E22 -> 3.46 | F28: =F21-F22 -> 4.29
B29: 75th Point | D29: =D23-D21 -> 1.205 | E29: =E23-E21 -> 0.77 | F29: =F23-F21 -> 2.74
B30: Maximum Point | D30: =D19-D23 -> 0.685 | E30: =E19-E23 -> 0.11 | F30: =F19-F23 -> 2.61
B32: Pharmacia LLC | D32: EV (X*Sales) | E32: EV (X*EBITDA) | F32: EV (X*EBIT)
B33: Maximum | D33: =D19*$C$46 -> 105422700 | E33: =E19*$C$47 -> 65855460 | F33: =F19*$C$48 -> 72039720
B34: Minimum | D34: =D20*$C$46 -> 31820500 | E34: =E20*$C$47 -> 48112020 | F34: =F20*$C$48 -> 42870110
B35: Median | D35: =D21*$C$46 -> 79274550 | E35: =E21*$C$47 -> 63125700 | F35: =F21*$C$48 -> 58712870
B36: 25th percentile | D36: =D22*$C$46 -> 33895750 | E36: =E22*$C$47 -> 52392780 | F36: =F22*$C$48 -> 48026480
B37: 75th percentile | D37: =D23*$C$46 -> 95945725 | E37: =E23*$C$47 -> 65514240 | F37: =F23*$C$48 -> 65538210
B38: Average | D38: =D24*$C$46 -> 67376450 | E38: =E24*$C$47 -> 58931796 | F38: =F24*$C$48 -> 56137176
B39: Standard Deviation | D39: =D25*$C$46 -> 30895002 | E39: =E25*$C$47 -> 7330177.6 | F39: =F25*$C$48 -> 10781921
B40: Min Point | D40: =$D$34 -> 31820500 | E40: =$E$34 -> 48112020 | F40: =$F$34 -> 42870110
B41: 25th Point | D41: =$D$36-$D$34 -> 2075250 | E41: =$E$36-$E$34 -> 4280760 | F41: =$F$36-$F$34 -> 5156370
B42: Median Point | D42: =$D$35-$D$36 -> 45378800 | E42: =$E$35-$E$36 -> 10732920 | F42: =$F$35-$F$36 -> 10686390
B43: 75th Point | D43: =$D$37-$D$35 -> 16671175 | E43: =$E$37-$E$35 -> 2388540 | F43: =$F$37-$F$35 -> 6825340
B44: Maximum Point | D44: =$D$33-$D$37 -> 9476975 | E44: =$E$33-$E$37 -> 341220 | F44: =$F$33-$F$37 -> 6501510
B46: Sales | C46: ='3.3 Income Statement'!I7*1000 -> 13835000 | D46: (thousand $)
B47: EBITDA | C47: ='3.3 Income Statement'!I11*1000 -> 3102000 | D47: (thousand $)
B48: EBIT | C48: ='3.3 Income Statement'!I15*1000 -> 2491000 | D48: (thousand $)
B49: EV | C49: 57273100 | D49: (thousand $)
C51: EV/EBIT | D51: EV/EBITDA | E51: EV/Sales | F51: DCF
B52: Max | C52: =F33 -> 72039720 | D52: =E33 -> 65855460 | E52: =D33 -> 105422700 | F52: ='5.2 Sensitivity Analysis'!D19*1000 -> 73370976
B53: Min | C53: =F34 -> 42870110 | D53: =E34 -> 48112020 | E53: =D34 -> 31820500 | F53: ='5.2 Sensitivity Analysis'!H15*1000 -> 48037038

Sheet 5.4 Opti K structure
B3: Optimal Capital Structure
B8: Estimate the unlevered beta for the firm | G8: Ratings comparison at current debt ratio
B9: Levered Beta of Pharmacia | E9: 0.63 | G9: Current Interest coverage ratio | J9: =E22/E21 -> 16.12549
B10: Marginal Tax rate | E10: 0.4 | G10: Rating based upon coverage | J10: =VLOOKUP(J9,$G$21:$K$35,3,TRUE) -> Aaa/AAA
B11: Market value of equity | E11: 55328.1 | G11: Interest rate based upon coverage | J11: =VLOOKUP(J10,I21:K35,2,FALSE)+E15 -> 0.05651
B12: Market value of debt | E12: 3082 | G12: Current rating for company | J12: A3/A-
B13: Unlevered Beta | E13: =E9/(1+(1-E10)*E12/E11) -> 0.60962485 | G13: Current interest rate on debt | J13: =VLOOKUP(J12,$I$21:$K$35,2,FALSE)+E15 -> 0.06301
B14: Market premium | E14: 0.04452 | G14: Current Bankruptcy Probability | J14: =VLOOKUP(J12,$I$21:$K$35,3,FALSE) -> 0.025
B15: Risk free return | E15: 0.05051 | G15: Cost of bankruptcy | J15: 0.25
B17: Pharmacia curent financials
B18: EBITDA | E18: 3102 | G18: For large non-financial service companies with market cap > $ 5 billion
B19: D&A | E19: 611 | G19: If interest coverage ratio is
B20: EBIT | E20: =E18-E19 -> 2491 | G20: greater than | H20: ≤ to | I20: Rating is | J20: Spread is | K20: Bankruptcy Probability
B21: Interest Expenses | E21: 255 | G21: -100000 | H21: 0.199999 | I21: D2/D | J21: 0.14 | K21: 1
B22: Adjusted EBIT | E22: 4112 | G22: 0.2 | H22: 0.649999 | I22: C2/C | J22: 0.105 | K22: 0.85
B23: Market Value of the firm | E23: =E11+E12 -> 58410.1 | G23: 0.65 | H23: 0.799999 | I23: Ca2/CC | J23: 0.08 | K23: 0.7
B24: Market Value of the firm | E24: =E11+E12 -> 58410.1 | G24: 0.8 | H24: 1.249999 | I24: Caa/CCC | J24: 0.065 | K24: 0.5901
G25: 1.25 | H25: 1.499999 | I25: B3/B- | J25: 0.055 | K25: 0.45
B26: Cost of equity | G26: 1.5 | H26: 1.749999 | I26: Ba1/BB+ | J26: 0.045 | K26: 0.1
B27: Debt to Capital Ratio | C27: D/E Ratio | D27: Levered Beta | E27: Cost of Equity | G27: 1.75 | H27: 1.999999 | I27: Ba2/BB | J27: 0.0375 | K27: 0.1663
B28: 0 | C28: =B28/(1-B28) -> 0 | D28: =$E$13*(1+(1-$E$10)*C28) -> 0.60962485 | E28: =$E$15+D28*$E$14 -> 0.077650498 | G28: 2 | H28: 2.2499999 | I28: B1/B+ | J28: 0.03 | K28: 0.25
B29: 0.1 | C29: =B29/(1-B29) -> 0.11111111 | D29: =$E$13*(1+(1-$E$10)*C29) -> 0.65026651 | E29: =$E$15+D29*$E$14 -> 0.079459865 | G29: 2.25 | H29: 2.49999 | I29: B2/B | J29: 0.025 | K29: 0.368
B30: 0.2 | C30: =B30/(1-B30) -> 0.25 | D30: =$E$13*(1+(1-$E$10)*C30) -> 0.70106858 | E30: =$E$15+D30*$E$14 -> 0.081721573 | G30: 2.5 | H30: 2.999999 | I30: Baa2/BBB | J30: 0.016 | K30: 0.0754
B31: 0.3 | C31: =B31/(1-B31) -> 0.42857143 | D31: =$E$13*(1+(1-$E$10)*C31) -> 0.76638553 | E31: =$E$15+D31*$E$14 -> 0.084629484 | G31: 3 | H31: 4.249999 | I31: A3/A- | J31: 0.0125 | K31: 0.025
B32: 0.4 | C32: =B32/(1-B32) -> 0.66666667 | D32: =$E$13*(1+(1-$E$10)*C32) -> 0.85347479 | E32: =$E$15+D32*$E$14 -> 0.088506698 | G32: 4.25 | H32: 5.499999 | I32: A2/A | J32: 0.011 | K32: 0.0066
B33: 0.5 | C33: =B33/(1-B33) -> 1 | D33: =$E$13*(1+(1-$E$10)*C33) -> 0.97539976 | E33: =$E$15+D33*$E$14 -> 0.093934797 | G33: 5.5 | H33: 6.499999 | I33: A1/A+ | J33: 0.01 | K33: 0.006
B34: 0.6 | C34: =B34/(1-B34) -> 1.5 | D34: =$E$13*(1+(1-$E$10)*C34) -> 1.1582872 | E34: =$E$15+D34*$E$14 -> 0.10207695 | G34: 6.5 | H34: 8.499999 | I34: Aa2/AA | J34: 0.008 | K34: 0.0051
B35: 0.7 | C35: =B35/(1-B35) -> 2.3333333 | D35: =$E$13*(1+(1-$E$10)*C35) -> 1.4630996 | E35: =$E$15+D35*$E$14 -> 0.1156472 | G35: 8.5 | H35: 100000 | I35: Aaa/AAA | J35: 0.006 | K35: 0.0007
B36: 0.8 | C36: =B36/(1-B36) -> 4 | D36: =$E$13*(1+(1-$E$10)*C36) -> 2.0727245 | E36: =$E$15+D36*$E$14 -> 0.14278769
B37: 0.9 | C37: =B37/(1-B37) -> 9 | D37: =$E$13*(1+(1-$E$10)*C37) -> 3.901599 | E37: =$E$15+D37*$E$14 -> 0.22420919 | G37: source: http://pages.stern.nyu.edu/~adamodar/New_Home_Page/datafile/ratings.htm
B39: Cost of debt
B40: D/(D+E) | C40: 0 | D40: 0.1 | E40: 0.2 | F40: 0.3 | G40: 0.4 | H40: 0.5 | I40: 0.6 | J40: 0.7 | K40: 0.8 | L40: 0.9 | M40: =E12/E24 -> 0.052764847
B41: D/E | C41: =C40/(1-C40) -> 0 | D41: =D40/(1-D40) -> 0.11111111 | E41: =E40/(1-E40) -> 0.25 | F41: =F40/(1-F40) -> 0.42857143 | G41: =G40/(1-G40) -> 0.66666667 | H41: =H40/(1-H40) -> 1 | I41: =I40/(1-I40) -> 1.5 | J41: =J40/(1-J40) -> 2.3333333 | ... M41: =M40/(1-M40) -> 0.055704064
B42: $ Debt | C42: =C40*$E$24 -> 0 | D42: =D40*$E$24 -> 5841.01 | E42: =E40*$E$24 -> 11682.02 | F42: =F40*$E$24 -> 17523.03 | G42: =G40*$E$24 -> 23364.04 | H42: =H40*$E$24 -> 29205.05 | I42: =I40*$E$24 -> 35046.06 | J42: =J40*$E$24 -> 40887.07 | ... M42: =M40*$E$24 -> 3082
B44: EBITDA | C44: =$E$18 -> 3102 | D44: =$E$18 -> 3102 | E44: =$E$18 -> 3102 | F44: =$E$18 -> 3102 | G44: =$E$18 -> 3102 | H44: =$E$18 -> 3102 | I44: =$E$18 -> 3102 | J44: =$E$18 -> 3102 | ... M44: =$E$18 -> 3102
B45: D&A | C45: =$E$19 -> 611 | D45: =$E$19 -> 611 | E45: =$E$19 -> 611 | F45: =$E$19 -> 611 | G45: =$E$19 -> 611 | H45: =$E$19 -> 611 | I45: =$E$19 -> 611 | J45: =$E$19 -> 611 | ... M45: =$E$19 -> 611
B46: Ajusted EBIT | C46: =$E$22 -> 4112 | D46: =$E$22 -> 4112 | E46: =$E$22 -> 4112 | F46: =$E$22 -> 4112 | G46: =$E$22 -> 4112 | H46: =$E$22 -> 4112 | I46: =$E$22 -> 4112 | J46: =$E$22 -> 4112 | ... M46: =$E$22 -> 4112
B47: Interest | C47: 0 | D47: =D42*6.1% -> 356.30161 | E47: =E42*0.11 -> 1285.0222 | F47: =F42*0.12 -> 2102.7636 | G47: =G42*0.16 -> 3738.2464 | H47: =H42*0.16 -> 4672.808 | I47: =I42*0.16 -> 5607.3696 | J47: =J42*I51 -> 5336.1715 | K47: =K42*J51 -> 6098.4817 | L47: =L42*K51 -> 6860.7919 | M47: =M42*6.3% -> 194.166
B49: Pre-tax Int. Cov | C49: infinite | D49: =D46/D47 -> 11.540784 | E49: =E46/E47 -> 3.1999447 | F49: =F46/F47 -> 1.9555218 | G49: =G46/G47 -> 1.099981 | H49: =H46/H47 -> 0.8799848 | I49: =I46/I47 -> 0.73332066 | J49: =J46/J47 -> 0.77058992 | K49: =K46/K47 -> 0.67426618 | ... M49: =M46/M47 -> 21.177755
B50: Likely Rating | C50: Aaa/AAA | D50: Aaa/AAA | E50: =VLOOKUP(E49,$G$21:$K$35,3,TRUE) -> A3/A- | F50: =VLOOKUP(F49,$G$21:$K$35,3,TRUE) -> Ba2/BB | G50: =VLOOKUP(G49,$G$21:$K$35,3,TRUE) -> Caa/CCC | H50: =VLOOKUP(H49,$G$21:$K$35,3,TRUE) -> Caa/CCC | I50: =VLOOKUP(I49,$G$21:$K$35,3,TRUE) -> Ca2/CC | J50: =VLOOKUP(J49,$G$21:$K$35,3,TRUE) -> Ca2/CC | K50: =VLOOKUP(K49,$G$21:$K$35,3,TRUE) -> Ca2/CC | L50: =VLOOKUP(L49,$G$21:$K$35,3,TRUE) -> C2/C | M50: =VLOOKUP(M49,$G$21:$K$35,3,TRUE) -> Aaa/AAA
B51: Pre-tax cost of debt | C51: =$E$15+VLOOKUP(C50,$I$21:$J$35,2,FALSE) -> 0.05651 | D51: =$E$15+VLOOKUP(D50,$I$21:$J$35,2,FALSE) -> 0.05651 | E51: =$E$15+VLOOKUP(E50,$I$21:$J$35,2,FALSE) -> 0.06301 | F51: =$E$15+VLOOKUP(F50,$I$21:$J$35,2,FALSE) -> 0.08801 | G51: =$E$15+VLOOKUP(G50,$I$21:$J$35,2,FALSE) -> 0.11551 | H51: =$E$15+VLOOKUP(H50,$I$21:$J$35,2,FALSE) -> 0.11551 | I51: =$E$15+VLOOKUP(I50,$I$21:$J$35,2,FALSE) -> 0.13051 | J51: =$E$15+VLOOKUP(J50,$I$21:$J$35,2,FALSE) -> 0.13051 | ... M51: =$E$15+VLOOKUP(M50,$I$21:$J$35,2,FALSE) -> 0.05651
B52: Probability of Bankruptcy | C52: =VLOOKUP(C50,$I$21:$K$35,3,FALSE) -> 0.0007 | D52: =VLOOKUP(D50,$I$21:$K$35,3,FALSE) -> 0.0007 | E52: =VLOOKUP(E50,$I$21:$K$35,3,FALSE) -> 0.025 | F52: =VLOOKUP(F50,$I$21:$K$35,3,FALSE) -> 0.1663 | G52: =VLOOKUP(G50,$I$21:$K$35,3,FALSE) -> 0.5901 | H52: =VLOOKUP(H50,$I$21:$K$35,3,FALSE) -> 0.5901 | I52: =VLOOKUP(I50,$I$21:$K$35,3,FALSE) -> 0.7 | J52: =VLOOKUP(J50,$I$21:$K$35,3,FALSE) -> 0.7 | ... M52: =VLOOKUP(M50,$I$21:$K$35,3,FALSE) -> 0.0007
B53: After-tax cost of debt | C53: =C51*(1-$E$10) -> 0.033906 | D53: =D51*(1-$E$10) -> 0.033906 | E53: =E51*(1-$E$10) -> 0.037806 | F53: =F51*(1-$E$10) -> 0.052806 | G53: =G51*(1-$E$10) -> 0.069306 | H53: =H51*(1-$E$10) -> 0.069306 | I53: =I51*(1-$E$10) -> 0.078306 | J53: =J51*(1-$E$10) -> 0.078306 | ... M53: =M51*(1-$E$10) -> 0.033906
B54: rA | C54: =$E$12/($E$11+$E$12)*C51+$E$12/($E$11+$E$12)*E28 -> 0.0070789582
B55: Unlev. Firm Value | C55: =$E$24-$E$12*$E$10+$E$24*$J$14*$J$15 -> 57542.363 | D55: =$E$24-$E$12*$E$10+$E$24*$J$14*$J$15 -> 57542.363 | E55: =$E$24-$E$12*$E$10+$E$24*$J$14*$J$15 -> 57542.363 | F55: =$E$24-$E$12*$E$10+$E$24*$J$14*$J$15 -> 57542.363 | G55: =$E$24-$E$12*$E$10+$E$24*$J$14*$J$15 -> 57542.363 | H55: =$E$24-$E$12*$E$10+$E$24*$J$14*$J$15 -> 57542.363 | I55: =$E$24-$E$12*$E$10+$E$24*$J$14*$J$15 -> 57542.363 | J55: =$E$24-$E$12*$E$10+$E$24*$J$14*$J$15 -> 57542.363 | ... M55: =$E$24-$E$12*$E$10+$E$24*$J$14*$J$15 -> 57542.363
B56: adjusted marginal tax rate | C56: =E10 -> 0.4 | D56: =E10 -> 0.4 | E56: =E10 -> 0.4 | F56: =E10 -> 0.4 | G56: =$G$46*$E$10/G47 -> 0.4399924 | H56: =$G$46*$E$10/H47 -> 0.35199392 | I56: =$G$46*$E$10/I47 -> 0.29332827 | J56: =$G$46*$E$10/J47 -> 0.30823597 | K56: =$G$46*$E$10/K47 -> 0.26970647 | L56: =$G$46*$E$10/L47 -> 0.23973909 | M56: =E10 -> 0.4
B57: Tax Benefits | C57: =C47*C56 -> 0 | D57: =D47*D56 -> 142.52064 | E57: =E47*E56 -> 514.00888 | F57: =F47*F56 -> 841.10544 | G57: =G47*G56 -> 1644.8 | H57: =H47*H56 -> 1644.8 | I57: =I47*I56 -> 1644.8 | J57: =J47*J56 -> 1644.8 | ... M57: =M47*M56 -> 77.6664
B58: Bankruptcy Cost | C58: =C52*$J$15*(C55+C57) -> 10.069914 | D58: =D52*$J$15*(D55+D57) -> 10.094855 | E58: =E52*$J$15*(E55+E57) -> 362.85233 | F58: =F52*$J$15*(F55+F57) -> 2427.2927 | G58: =G52*$J$15*(G55+G57) -> 8731.5862 | H58: =H52*$J$15*(H55+H57) -> 8731.5862 | I58: =I52*$J$15*(I55+I57) -> 10357.754 | J58: =J52*$J$15*(J55+J57) -> 10357.754 | ... M58: =M52*$J$15*(M55+M57) -> 10.083505
B59: Levered Firm Value | C59: =C55+C57-C58 -> 57532.293 | D59: =D55+D57-D58 -> 57674.789 | E59: =E55+E57-E58 -> 57693.52 | F59: =F55+F57-F58 -> 55956.176 | G59: =G55+G57-G58 -> 50455.577 | H59: =H55+H57-H58 -> 50455.577 | I59: =I55+I57-I58 -> 48829.41 | J59: =J55+J57-J58 -> 48829.41 | ... M59: =M55+M57-M58 -> 57609.946
B61: Opti WACC | C61: =(1-E56)*E40*E51+(1-E40)*E30 -> 0.072938459

Sheet 5.5 Value of Control
C3: Value of Control
S8: Sensitivity Analysis
C9: Income Statement | F9: Actual | H9: Projections
C10: In Millions of USD | F10: 1997 | G10: 1998 | H10: 1999 | I10: 2000 | J10: 2001 | K10: Adj. | L10: 2001 | M10: 2002 | N10: 2003 | O10: 2004 | P10: 2005 | Q10: 2006 | S10: WACC | T10: =Q33 -> 55507.412
S11: =S12-0.01 -> 0.052938459 | T11: =$Q$31+$Q$30*(1+$P$76)/(S11-$P$76) -> 61240.219
D12: Unlevered Free Cash Flow | S12: =S13-0.01 -> 0.062938459 | T12: =$Q$31+$Q$30*(1+$P$76)/(S12-$P$76) -> 58141.94
S13: =T19 -> 0.072938459 | T13: =$Q$31+$Q$30*(1+$P$76)/(S13-$P$76) -> 55507.412
D14: Year (t) | M14: 1 | N14: 2 | O14: 3 | P14: 4 | Q14: 5
S15: =S13+0.01 -> 0.082938459 | T15: =$Q$31+$Q$30*(1+$P$76)/(S15-$P$76) -> 53239.764
D16: EBITDA | F16: ='3.3 Income Statement'!E11 -> 1670 | G16: ='3.3 Income Statement'!F11 -> 1120 | H16: ='3.3 Income Statement'!G11 -> 3314 | I16: ='3.3 Income Statement'!H11 -> 2632 | J16: ='3.3 Income Statement'!I11 -> 3102 | K16: 0 | L16: =J16+K16 -> 3102 | M16: ='3.3 Income Statement'!J11 -> 5391.6689 | N16: ='3.3 Income Statement'!K11 -> 6509.8048 | O16: ='3.3 Income Statement'!L11 -> 6821.6244 | P16: ='3.3 Income Statement'!M11 -> 7148.3802 | Q16: ='3.3 Income Statement'!N11 -> 7490.7876 | S16: =S15+0.01 -> 0.092938459 | T16: =$Q$31+$Q$30*(1+$P$76)/(S16-$P$76) -> 51267.347
S17: =S16+0.01 -> 0.10293846 | T17: =$Q$31+$Q$30*(1+$P$76)/(S17-$P$76) -> 49536.03
D18: Depreciation & Amortization | F18: ='3.3 Income Statement'!E14 -> -487 | G18: ='3.3 Income Statement'!F14 -> -518 | H18: ='3.3 Income Statement'!G14 -> -1145 | I18: ='3.3 Income Statement'!H14 -> -633 | J18: ='3.3 Income Statement'!I14 -> -611 | K18: 0 | L18: ='3.3 Income Statement'!I14 -> -611 | M18: ='3.3 Income Statement'!J14 -> -870.72789 | N18: ='3.3 Income Statement'!K14 -> -912.43575 | O18: ='3.3 Income Statement'!L14 -> -956.14142 | P18: ='3.3 Income Statement'!M14 -> -1001.9406 | Q18: ='3.3 Income Statement'!N14 -> -1049.9336
D19: EBIT | F19: =SUM(F16+F18) -> 1183 | G19: =SUM(G16+G18) -> 602 | H19: =SUM(H16+H18) -> 2169 | I19: =SUM(I16+I18) -> 1999 | J19: =SUM(J16+J18) -> 2491 | K19: =F43+F45+F44 -> 1621.1777 | L19: =J19+K19 -> 4112.1777 | M19: ='3.3 Income Statement'!J15+G43+G44+G45 -> 6085.3147 | N19: ='3.3 Income Statement'!K15+H43+H44+H45 -> 7092.8324 | O19: ='3.3 Income Statement'!L15+I43+I44+I45 -> 7270.0629 | P19: ='3.3 Income Statement'!M15+J43+J44+J45 -> 7434.684 | Q19: ='3.3 Income Statement'!N15+K43+K44+K45 -> 7583.3502 | S19: Opti WACC | T19: ='5.4 Opti K structure'!C61 -> 0.072938459
D21: Effective tax rate | F21: =IF($D$21="Marginal tax rate",F39,F38) -> 0.1967 | G21: =IF($D$21="Marginal tax rate",G39,G38) -> 0.1967 | H21: =IF($D$21="Marginal tax rate",H39,H38) -> 0.3119 | I21: =IF($D$21="Marginal tax rate",I39,I38) -> 0.2269 | J21: =IF($D$21="Marginal tax rate",J39,J38) -> 0.1873 | K21: 0 | L21: 0.22 | M21: 0.4 | N21: 0.4 | O21: 0.4 | P21: 0.4 | Q21: 0.4
D22: EBIT*(1-Tax rate) | F22: =F19*(1-F21) -> 950.3039 | G22: =G19*(1-G21) -> 483.5866 | H22: =H19*(1-H21) -> 1492.4889 | I22: =I19*(1-I21) -> 1545.4269 | J22: =J19*(1-J21) -> 2024.4357 | K22: =K19*(1-J21) -> 1317.5311 | L22: =J22+K22 -> 3341.9668 | M22: =M19*(1-M21) -> 3651.1888 | N22: =N19*(1-N21) -> 4255.6995 | O22: =O19*(1-O21) -> 4362.0378 | P22: =P19*(1-P21) -> 4460.8104 | Q22: =Q19*(1-Q21) -> 4550.0101
D24: Depreciation & amortization | F24: =-F18 -> 487 | G24: =-G18 -> 518 | H24: =-H18 -> 1145 | I24: =-I18 -> 633 | J24: =-J18 -> 611 | K24: =F48+F49 -> 1779.1423 | L24: =J24+K24 -> 2390.1423 | M24: =-M18+G48+G49 -> 2793.7424 | N24: =-N18+H48+H49 -> 2998.0176 | O24: =-O18+I48+I49 -> 3225.415 | P24: =-P18+J48+J49 -> 3478.7752 | Q24: =-Q18+K48+K49 -> 3761.3002
D25: Δ net Working Capital | F25: ='3.2 Balance Sheet'!E49 -> 892 | G25: ='3.2 Balance Sheet'!F49 -> 76 | H25: ='3.2 Balance Sheet'!G49 -> 1505 | I25: ='3.2 Balance Sheet'!H49 -> -2088 | J25: ='3.2 Balance Sheet'!I49 -> 56 | K25: 0 | L25: =J25+K25 -> 56 | M25: ='3.2 Balance Sheet'!J49 -> 1200.5492 | N25: ='3.2 Balance Sheet'!K49 -> 146.9835 | O25: ='3.2 Balance Sheet'!L49 -> 154.02401 | P25: ='3.2 Balance Sheet'!M49 -> 161.40176 | Q25: ='3.2 Balance Sheet'!N49 -> 169.13291
D26: Capex | F26: ='3.4 Cash Flow Statement'!E9 -> -644 | G26: ='3.4 Cash Flow Statement'!F9 -> -859 | H26: ='3.4 Cash Flow Statement'!G9 -> -1678 | I26: ='3.4 Cash Flow Statement'!H9 -> -774 | J26: ='3.4 Cash Flow Statement'!I9 -> -1020 | K26: 0 | L26: =J26+K26 -> -1020 | M26: ='3.4 Cash Flow Statement'!J9 -> -1289.4393 | N26: ='3.4 Cash Flow Statement'!K9 -> -1351.2035 | O26: ='3.4 Cash Flow Statement'!L9 -> -1415.9261 | P26: ='3.4 Cash Flow Statement'!M9 -> -1483.749 | Q26: ='3.4 Cash Flow Statement'!N9 -> -1554.8206
D28: FCF | F28: =F22+F24-F25+F26 -> -98.6961 | G28: =G22+G24-G25+G26 -> 66.5866 | H28: =H22+H24-H25+H26 -> -545.5111 | I28: =I22+I24-I25+I26 -> 3492.4269 | J28: =J22+J24-J25+J26 -> 1559.4357 | K28: NA | L28: =L22+L24-L25+L26 -> 4656.1091 | M28: =M22+M24-M25+M26 -> 3954.9428 | N28: =N22+N24-N25+N26 -> 5755.5301 | O28: =O22+O24-O25+O26 -> 6017.5026 | P28: =P22+P24-P25+P26 -> 6294.4348 | Q28: =Q22+Q24-Q25+Q26 -> 6587.3568
D30: Unleverd FCF | M30: =M28/(1+$T$19)^'5.5 Value of Control'!M14 -> 3686.0854 | N30: =N28/(1+$T$19)^'5.5 Value of Control'!N14 -> 4999.6051 | O30: =O28/(1+$T$19)^'5.5 Value of Control'!O14 -> 4871.8269 | P30: =P28/(1+$T$19)^'5.5 Value of Control'!P14 -> 4749.605 | Q30: =Q28/(1+$T$19)^'5.5 Value of Control'!Q14 -> 4632.7314
D31: PV of UFCF | Q31: =SUM(M30:Q30) -> 22939.854
D32: Terminal Value (TV) | Q32: =Q30*(1+P76)/(T19-P76) -> 32567.558
D33: Entreprise Value (EV) | Q33: =Q31+Q32 -> 55507.412
D34: Equity Value | Q34: =Q33*(1-'5.4 Opti K structure'!E40) -> 44405.93
D35: Value of Control | Q35: =Q33-'5.1 Free Cash Flow'!P32 -> 1598.9216
D37: Tax rate | F37: 1997 | G37: 1998 | H37: 1999 | I37: 2000 | J37: 2001
D38: Effective tax rate | F38: 0.1967 | G38: 0.1967 | H38: 0.3119 | I38: 0.2269 | J38: 0.1873
D39: Marginal tax rate | F39: 0.4 | G39: 0.4 | H39: 0.4 | I39: 0.4 | J39: 0.4
D41: EBIT adjustments | F41: 2001 | G41: 2002 | H41: 2003 | I41: 2004 | J41: 2005 | K41: 2006
D42: R&D adjustments | G42: 1 | H42: 2 | I42: 3 | J42: 4 | K42: 5
D43: R&D | F43: ='4.2 R&D converter'!E39 -> 1155.8 | G43: =-'3.3 Income Statement'!J10-'4.2 R&D converter'!$E$37*POWER((1+'4.2 R&D converter'!$M$26),G42) -> 1115.2257 | H43: =-'3.3 Income Statement'!K10-'4.2 R&D converter'!$E$37*POWER((1+'4.2 R&D converter'!$M$26),H42) -> 1066.0041 | I43: =-'3.3 Income Statement'!L10-'4.2 R&D converter'!$E$37*POWER((1+'4.2 R&D converter'!$M$26),I42) -> 1001.0873 | J43: =-'3.3 Income Statement'!M10-'4.2 R&D converter'!$E$37*POWER((1+'4.2 R&D converter'!$M$26),J42) -> 917.99053 | K43: =-'3.3 Income Statement'!N10-'4.2 R&D converter'!$E$37*POWER((1+'4.2 R&D converter'!$M$26),K42) -> 813.88459
D44: R&D tax effect | F44: ='4.2 R&D converter'!E40 -> 462.32 | G44: =G43*M21 -> 446.09029 | H44: =H43*N21 -> 426.40164 | I44: =I43*O21 -> 400.43493 | J44: =J43*P21 -> 367.19621 | K44: =K43*Q21 -> 325.55384
D45: Operating leases | F45: ='4.1 Operating lease converter'!G34 -> 3.0576875 | G45: =$F$45 -> 3.0576875 | H45: =$F$45 -> 3.0576875 | I45: =$F$45 -> 3.0576875 | J45: =$F$45 -> 3.0576875 | K45: =$F$45 -> 3.0576875
D47: Depreciaton adjustments
D48: R&D | F48: ='4.2 R&D converter'!E37 -> 1107.2 | G48: =F48*(1+'4.2 R&D converter'!$M$26) -> 1251.0722 | H48: =G48*(1+'4.2 R&D converter'!$M$26) -> 1413.6395 | I48: =H48*(1+'4.2 R&D converter'!$M$26) -> 1597.3312 | J48: =I48*(1+'4.2 R&D converter'!$M$26) -> 1804.8923 | K48: =J48*(1+'4.2 R&D converter'!$M$26) -> 2039.4243
D49: Operating leases | F49: ='4.1 Operating lease converter'!G33 -> 671.94231 | G49: =$F$49 -> 671.94231 | H49: =$F$49 -> 671.94231 | I49: =$F$49 -> 671.94231 | J49: =$F$49 -> 671.94231 | K49: =$F$49 -> 671.94231
D51: Capex adjustements
D52: R&D | F52: =-'4.2 R&D converter'!G7 -> -2263 | G52: ='3.3 Income Statement'!J10 -> -2366.298 | H52: ='3.3 Income Statement'!K10 -> -2479.6436 | I52: ='3.3 Income Statement'!L10 -> -2598.4186 | J52: ='3.3 Income Statement'!M10 -> -2722.8828 | K52: ='3.3 Income Statement'!N10 -> -2853.3089
D53: Operating leases | F53: =-'4.1 Operating lease converter'!F3 -> -675 | G53: =$F$53 -> -675 | H53: =$F$53 -> -675 | I53: =$F$53 -> -675 | J53: =$F$53 -> -675 | K53: =$F$53 -> -675
D55: Expected Growth Rate | G55: 1997 | H55: 1998 | I55: 1999 | J55: 2000 | K55: 2001 | L55: 2002 | M55: 2003 | N55: 2004 | O55: 2005 | P55: 2006
D56: Book value of equity | G56: ='3.2 Balance Sheet'!E33 -> 4104 | H56: ='3.2 Balance Sheet'!F33 -> 4986 | I56: ='3.2 Balance Sheet'!G33 -> 10911 | J56: ='3.2 Balance Sheet'!H33 -> 11921 | K56: ='3.2 Balance Sheet'!I33 -> 12390
D57: Book value of debt | G57: ='3.2 Balance Sheet'!E29+'3.2 Balance Sheet'!E25 -> 3705 | H57: ='3.2 Balance Sheet'!F29+'3.2 Balance Sheet'!F25 -> 7328 | I57: ='3.2 Balance Sheet'!G29+'3.2 Balance Sheet'!G25 -> 8228 | J57: ='3.2 Balance Sheet'!H29+'3.2 Balance Sheet'!H25 -> 4299 | K57: ='3.2 Balance Sheet'!I29+'3.2 Balance Sheet'!I25 -> 3082
D58: Book value of capital | G58: =SUM(G56:G57) -> 7809 | H58: =SUM(H56:H57) -> 12314 | I58: =SUM(I56:I57) -> 19139 | J58: =SUM(J56:J57) -> 16220 | K58: =SUM(K56:K57) -> 15472 | L58: =K58+1250 -> 16722 | M58: =L58+1250 -> 17972 | N58: =M58+1250 -> 19222 | O58: =N58+1250 -> 20472 | P58: =20000+1250 -> 21250
D59: Value of Research Asset | K59: ='4.2 R&D converter'!E35 -> 8930.1 | L59: ='4.2 R&D converter'!$E$35*POWER(1+'4.2 R&D converter'!$M$27,'5.5 Value of Control'!M14) -> 9732.6897 | M59: ='4.2 R&D converter'!$E$35*POWER(1+'4.2 R&D converter'!$M$27,'5.5 Value of Control'!N14) -> 10607.412 | N59: ='4.2 R&D converter'!$E$35*POWER(1+'4.2 R&D converter'!$M$27,'5.5 Value of Control'!O14) -> 11560.749 | O59: ='4.2 R&D converter'!$E$35*POWER(1+'4.2 R&D converter'!$M$27,'5.5 Value of Control'!P14) -> 12599.768 | P59: ='4.2 R&D converter'!$E$35*POWER(1+'4.2 R&D converter'!$M$27,'5.5 Value of Control'!Q14) -> 13732.168
D61: EBIT*(1-Tax rate) | G61: =F22 -> 950.3039 | H61: =G22 -> 483.5866 | I61: =H22 -> 1492.4889 | J61: =I22 -> 1545.4269 | K61: =J22 -> 2024.4357 | L61: =M22 -> 3651.1888 | M61: =N22 -> 4255.6995 | N61: =O22 -> 4362.0378 | O61: =P22 -> 4460.8104 | P61: =Q22 -> 4550.0101
D63: Return of Capital Invested* | H63: =H61/G58 -> 0.061926828 | I63: =I61/H58 -> 0.12120261 | J63: =J61/I58 -> 0.080747526 | K63: =K61/J58 -> 0.12481108 | L63: =(L61+G48)/(K58+K59) -> 0.20089505 | M63: =(M61+H48)/(L58+L59) -> 0.21430374 | N63: =(N61+I48)/(M58+M59) -> 0.20851965 | O63: =(O61+J48)/(N58+N59) -> 0.20354591 | P63: =(P61+K48)/(O58+O59) -> 0.19924651
D65: Net Capex | G65: ='3.4 Cash Flow Statement'!E9 -> -644 | H65: ='3.4 Cash Flow Statement'!F9 -> -859 | I65: ='3.4 Cash Flow Statement'!G9 -> -1678 | J65: ='3.4 Cash Flow Statement'!H9 -> -774 | K65: ='3.4 Cash Flow Statement'!I9 -> -1020 | L65: ='3.4 Cash Flow Statement'!J9 -> -1289.4393 | M65: ='3.4 Cash Flow Statement'!K9 -> -1351.2035 | N65: ='3.4 Cash Flow Statement'!L9 -> -1415.9261 | ... P65: ='3.4 Cash Flow Statement'!N9 -> -1554.8206
D66: Change in NCWC | G66: ='3.2 Balance Sheet'!E49 -> 892 | H66: ='3.2 Balance Sheet'!F49 -> 76 | I66: ='3.2 Balance Sheet'!G49 -> 1505 | J66: ='3.2 Balance Sheet'!H49 -> -2088 | K66: ='3.2 Balance Sheet'!I49 -> 56 | L66: =M25 -> 1200.5492 | M66: =N25 -> 146.9835 | N66: =O25 -> 154.02401 | O66: =P25 -> 161.40176 | P66: =Q25 -> 169.13291
D68: Gross value of assets | G68: =9339+'3.2 Balance Sheet'!E7+'3.2 Balance Sheet'!E9 -> 10847 | H68: =9339+'3.2 Balance Sheet'!F7+'3.2 Balance Sheet'!F9 -> 11150 | I68: =9339+'3.2 Balance Sheet'!G7+'3.2 Balance Sheet'!G9 -> 13844 | J68: =9339+'3.2 Balance Sheet'!H7+'3.2 Balance Sheet'!H9 -> 12893 | K68: =9339+'3.2 Balance Sheet'!I7+'3.2 Balance Sheet'!I9 -> 12298 | L68: =((L55-$G$55)*1704.2+11964)*1.01 -> 20689.85 | M68: =(M55-$G$55)*1704.2+11964 -> 22189.2 | N68: =(N55-$G$55)*1704.2+11964 -> 23893.4 | O68: =(O55-$G$55)*1704.2+11964 -> 25597.6 | P68: =(P55-$G$55)*1704.2+11964 -> 27301.8
D69: Accumulated depreciation & impairment | G69: -2320 | H69: -4933 | I69: -3403 | J69: -3392 | K69: -4005 | L69: =K69 -> -4005 | M69: =L69 -> -4005 | N69: =M69 -> -4005 | O69: =N69 -> -4005 | P69: =O69 -> -4005
D70: Book Value of Asset | G70: =SUM(G68,G69) -> 8527 | H70: =SUM(H68,H69) -> 6217 | I70: =SUM(I68,I69) -> 10441 | J70: =SUM(J68,J69) -> 9501 | K70: =SUM(K68,K69) -> 8293 | L70: =SUM(L68,L69) -> 16684.85 | M70: =SUM(M68,M69) -> 18184.2 | N70: =SUM(N68,N69) -> 19888.4 | ... P70: =SUM(P68,P69) -> 23296.8
D71: Current non-adjusted depreciation expense | G71: =F18 -> -487 | H71: =G18 -> -518 | I71: =H18 -> -1145 | J71: =I18 -> -633 | K71: =J18 -> -611 | L71: =M18 -> -870.72789 | M71: =N18 -> -912.43575 | N71: =O18 -> -956.14142 | O71: =P18 -> -1001.9406 | P71: =Q18 -> -1049.9336
D72: Average age of asset | G72: =-G68/G71 -> 22.273101 | H72: =-H68/H71 -> 21.525097 | I72: =-I68/I71 -> 12.09083 | J72: =-J68/J71 -> 20.368088 | K72: =-K68/K71 -> 20.12766 | L72: =-L68/L71 -> 23.761557 | M72: =-M68/M71 -> 24.318644 | N72: =-N68/N71 -> 24.989399 | ... P72: =-P68/P71 -> 26.00336
D74: American inflation rate | G74: 0.017 | H74: 0.0161 | I74: 0.0268 | J74: 0.0339 | K74: 0.0155 | L74: 0.0238 | M74: 0.0188 | N74: 0.0326 | O74: 0.0342 | P74: 0.0254
D76: EBIT Growth rate | H76: =(H65+H66)/H61*H63 -> -0.10026892 | I76: =(I65+I66)/I61*I63 -> -0.01404905 | J76: =(J65+J66)/J61*J63 -> -0.14953759 | K76: =(K65+K66)/K61*K63 -> -0.059432799 | L76: =(L65+L66)/L61*L63 -> -0.0048908995 | M76: =(M65+M66)/M61*M63 -> -0.06064076 | N76: =(N65+N66)/N61*N63 -> -0.060323043 | O76: =(O65+O66)/O61*O63 -> -0.060338446 | P76: =(P65+P66)/P61*P63 -> -0.060679741
D77: Source: http://www.inflation.eu/inflation-rates/united-states/historic-inflation/cpi-inflation-united-states.aspx
D78: gEBIT = (Net Capital Expenditures + Change in WC)/EBIT(1-t) * ROC
D79: *adjusted with R&D asset value from 2001 adj. To 2006E
D83: Expected Growth EPS | G83: 1997 | H83: 1998 | I83: 1999 | J83: 2000 | K83: 2001 | M83: Yearly Growth Rate
D84: EPS | G84: 1.25 | H84: 0.93 | I84: 1.15 | J84: 1.17 | K84: 1.44 | M84: 0.062
D85: ln(EPS) | G85: =LN(G84) -> 0.22314355 | H85: =LN(H84) -> -0.072570693 | I85: =LN(I84) -> 0.13976194 | J85: =LN(J84) -> 0.15700375 | K85: =LN(K84) -> 0.36464311 | M85: =5.13%/5 -> 0.01026
