Workbook
Name acq: [1]Assumptions!$H$8
Name acq_fye: [1]Assumptions!$H$32
Name acq_price: [1]Assumptions!$J$11
Name assume: [1]Assumptions!$T$11
Name base_year: [2]Control!$D$11
Name case: [1]Assumptions!$T$7
Name cash_rate: [1]Assumptions!$T$20
Name circ: [2]Control!$D$13
Name comments: 'France 10-Year Bond Yield'!$A$211
Name curr: [2]Control!$D$9
Name debt_rate: [1]Assumptions!$T$16
Name eps: [1]Assumptions!$T$41
Name fees: [1]Assumptions!$T$24
Name libor: [3]LBO!$AF$34
Name min_cash: [1]Assumptions!$T$21
Name pct_cash: [1]Assumptions!$T$8
Name project: [2]Control!$D$5
Name sec_338: [1]Assumptions!$T$13
Name synergies: [1]Assumptions!$T$28
Name tax_rate: [1]Assumptions!$T$39
Name tgt: [1]Assumptions!$L$8
Name tgt_price: [1]Assumptions!$N$11
Name type: [1]Assumptions!$T$12
Name year: [1]Assumptions!$T$40

Sheet DATA >>>>

Sheet Capital structure
A1: source Annual reports SANOFI 2011, 2012, 2013, 2014, 2015
A3: Capital structure of Sanofi
A4: (€ million) | B4: 2006 | C4: 2007 | D4: 2008 | E4: 2009 | F4: 2010 | G4: 2011 | H4: 2012 | I4: 2013 | J4: 2014 | K4: 2015
A5: Total Assets | B5: 77763 | C5: 71914 | D5: 71987 | E5: 80049 | F5: 85264 | G5: 100165 | H5: 100407 | I5: 96065 | J5: 97392 | K5: 102321
A6: Equity | B6: 45600 | C6: 44719 | D6: 44571 | E6: 48446 | F6: 53097 | G6: 56219 | H6: 57338 | I6: 56885 | J6: 56120 | K6: 58049
A7: LT Debt | B7: 4499 | C7: 3734 | D7: 4173 | E7: 5961 | F7: 6695 | G7: 12499 | H7: 10719 | I7: 10414 | J7: 13276 | K7: 13118
A9: Debt/Assets | B9: =B7/B5 -> 0.057855278 | C9: =C7/C5 -> 0.05192313 | D9: =D7/D5 -> 0.0579688 | E9: =E7/E5 -> 0.074466889 | F9: =F7/F5 -> 0.078520829 | G9: =G7/G5 -> 0.12478411 | H9: =H7/H5 -> 0.10675551 | I9: =I7/I5 -> 0.10840577 | ... K9: =K7/K5 -> 0.12820438 | L9: =AVERAGE(G9:K9) -> 0.12089297
A10: D/(D+E) | B10: =B7/(B6+B7) -> 0.089802192 | C10: =C7/(C6+C7) -> 0.077064372 | D10: =D7/(D6+D7) -> 0.085610537 | E10: =E7/(E6+E7) -> 0.10956311 | F10: =F7/(F6+F7) -> 0.1119715 | G10: =G7/(G6+G7) -> 0.1818883 | H10: =H7/(H6+H7) -> 0.15750033 | I10: =I7/(I6+I7) -> 0.15474227 | ... K10: =K7/(K6+K7) -> 0.18432701 | L10: =AVERAGE(G10:K10) -> 0.17395315
A11: D/E | B11: =B7/B6 -> 0.098662281 | C11: =C7/C6 -> 0.083499184 | D11: =D7/D6 -> 0.0936259 | E11: =E7/E6 -> 0.12304421 | F11: =F7/F6 -> 0.12608999 | G11: =G7/G6 -> 0.22232697 | H11: =H7/H6 -> 0.18694409 | I11: =I7/I6 -> 0.18307111 | ... K11: =K7/K6 -> 0.2259815 | L11: =AVERAGE(G11:K11) -> 0.21097763

Sheet cost of equity(use Fama French)
A1: Date | B1: Rm-Rf | C1: Year | D1: Mkt-RF % | E1: Mkt-RF | K1: Date | L1: RF | O1: Alpha
A2: 40543 | B2: 0.053727234 | C2: 1991 | D2: 4.77 | E2: =D2/100 -> 0.0477 | F2: Average Market Risk Premium (MRP) | K2: 40543 | L2: ='Raw material'!J2 -> 0.0001 | N2: Monthly: | O2: 0 | P2: Insignificant statistically
A3: 40512 | B3: -0.058287035 | C3: 1992 | D3: -11.31 | E3: =D3/100 -> -0.1131 | F3: in the last 10 years: | N3: Yearly: | O3: =(1+O2)^12-1 -> 0
A4: 40480 | B4: 0.031747717 | C4: 1993 | D4: 25.54 | E4: =D4/100 -> 0.2554 | K4: Yearly risk-free return: | L4: =(1+L2)^12-1 -> 0.0012006602
A5: 40451 | B5: 0.064180578 | C5: 1994 | D5: -0.5 | E5: =D5/100 -> -0.005 | F5: Monthly average: | G5: =AVERAGE(B2:B247) -> 0.0012702854 | O5: Beta:
A6: 40421 | B6: -0.041918322 | C6: 1995 | D6: 13.36 | E6: =D6/100 -> 0.1336 | F6: Yearly average MRP: | G6: =(1+G5)^12-1 -> 0.015350377 | O6: 0.6 | P6: Significant statistically
A7: 40389 | B7: 0.058063345 | C7: 1996 | D7: 16.54 | E7: =D7/100 -> 0.1654
A8: 40359 | B8: -0.018537318 | C8: 1997 | D8: 14.86 | E8: =D8/100 -> 0.1486 | F8: Fama French Annual Mkt-RF in 2010 (European): | G8: =E21 -> 0.0604
A9: 40329 | B9: -0.081166495 | C9: 1998 | D9: 20.51 | E9: =D9/100 -> 0.2051
A10: 40298 | B10: -0.039611727 | C10: 1999 | D10: 14.93 | E10: =D10/100 -> 0.1493
A11: 40268 | B11: 0.071408305 | C11: 2000 | D11: -15.89 | E11: =D11/100 -> -0.1589
A12: 40235 | B12: -0.0081990448 | C12: 2001 | D12: -24.15 | E12: =D12/100 -> -0.2415
A13: 40207 | B13: -0.050013591 | C13: 2002 | D13: -15.92 | E13: =D13/100 -> -0.1592
A14: 40178 | B14: 0.069511293 | C14: 2003 | D14: 41.78 | E14: =D14/100 -> 0.4178
A15: 40147 | B15: 0.020084874 | C15: 2004 | D15: 22.54 | E15: =D15/100 -> 0.2254
A16: 40116 | B16: -0.049459742 | C16: 2005 | D16: 8.73 | E16: =D16/100 -> 0.0873
A17: 40086 | B17: 0.038730833 | C17: 2006 | D17: 32.23 | E17: =D17/100 -> 0.3223
A18: 40056 | B18: 0.066231608 | C18: 2007 | D18: 9.59 | E18: =D18/100 -> 0.0959
A19: 40025 | B19: 0.090915909 | C19: 2008 | D19: -47.58 | E19: =D19/100 -> -0.4758
A20: 39994 | B20: -0.04196231 | C20: 2009 | D20: 35.24 | E20: =D20/100 -> 0.3524
A21: 39962 | B21: 0.037280251 | C21: 2010 | D21: 6.04 | E21: =D21/100 -> 0.0604
A22: 39933 | B22: 0.12546726
A23: 39903 | B23: 0.038601397
A24: 39871 | B24: -0.091373471
A25: 39843 | B25: -0.075839737
A26: 39813 | B26: -0.013703459
A27: 39780 | B27: -0.064649153
A28: 39752 | B28: -0.13597274
A29: 39721 | B29: -0.10199971
A30: 39689 | B30: 0.019244764
A31: 39660 | B31: -0.011080933
A32: 39629 | B32: -0.11725597
A33: 39598 | B33: 0.0017504569
... A247: 33085 | B247: -0.040932175

Sheet LR1
A1: SUMMARY OUTPUT
A3: 回归统计
A4: Multiple R | B4: 0.53941259
A5: R Square | B5: 0.29096594
A6: Adjusted R Square | B6: 0.27874122
A7: 标准误差 | B7: 0.051321093
A8: 观测值 | B8: 60
A10: 方差分析
B11: df | C11: SS | D11: MS | E11: F | F11: Significance F
A12: 回归分析 | B12: 1 | C12: 0.062689507 | D12: 0.062689507 | E12: 23.80143 | F12: 8.70172e-06
A13: 残差 | B13: 58 | C13: 0.15276357 | D13: 0.0026338546
A14: 总计 | B14: 59 | C14: 0.21545308
B16: Coefficients | C16: 标准误差 | D16: t Stat | E16: P-value | F16: Lower 95% | G16: Upper 95% | H16: 下限 95.0% | I16: 上限 95.0%
A17: Intercept | B17: -0.0018291615 | C17: 0.0066426816 | D17: -0.27536492 | E17: 0.78401454 | F17: -0.015125933 | G17: 0.01146761 | H17: -0.015125933 | I17: 0.01146761
A18: Market Premium | B18: 0.59595671 | C18: 0.12215555 | D18: 4.878671 | E18: 8.70172e-06 | F18: 0.35143582 | G18: 0.8404776 | H18: 0.35143582 | I18: 0.8404776
B19: 2006-2010

Sheet Raw material
A1: Date | B1: SNY Stock Price | C1: Dividend | D1: # Stocks | E1: Value | F1: Return | G1: Market Index | H1: Market Return | I1: Rf(%) | J1: Rf | K1: Market Premium | L1: SNY Premium
A2: 40543 | B2: 47.85 | D2: =(D3*C2)/B2+D3 -> 1.4976877 | E2: =B2*D2 -> 71.664355 | F2: =E2/E3-1 -> 0.027264921 | G2: 3804.78 | H2: =(G2/G3)-1 -> 0.053827234 | I2: 0.01 | J2: =I2/100 -> 0.0001 | K2: =H2-J2 -> 0.053727234 | L2: =F2-J2 -> 0.027164921
A3: 40512 | B3: 46.58 | D3: =(D4*C3)/B3+D4 -> 1.4976877 | E3: =B3*D3 -> 69.762291 | F3: =E3/E4-1 -> -0.07174173 | G3: 3610.44 | H3: =(G3/G4)-1 -> -0.058187035 | I3: 0.01 | J3: =I3/100 -> 0.0001 | K3: =H3-J3 -> -0.058287035 | L3: =F3-J3 -> -0.07184173
A4: 40480 | B4: 50.18 | D4: =(D5*C4)/B4+D5 -> 1.4976877 | E4: =B4*D4 -> 75.153967 | F4: =E4/E5-1 -> 0.026700767 | G4: 3833.5 | H4: =(G4/G5)-1 -> 0.031847717 | I4: 0.01 | J4: =I4/100 -> 0.0001 | K4: =H4-J4 -> 0.031747717 | L4: =F4-J4 -> 0.026600767
A5: 40451 | B5: 48.875 | D5: =(D6*C5)/B5+D6 -> 1.4976877 | E5: =B5*D5 -> 73.199484 | F5: =E5/E6-1 -> 0.079633311 | G5: 3715.18 | H5: =(G5/G6)-1 -> 0.064280578 | I5: 0.01 | J5: =I5/100 -> 0.0001 | K5: =H5-J5 -> 0.064180578 | L5: =F5-J5 -> 0.079533311
A6: 40421 | B6: 45.27 | D6: =(D7*C6)/B6+D7 -> 1.4976877 | E6: =B6*D6 -> 67.80032 | F6: =E6/E7-1 -> 0.015705632 | G6: 3490.79 | H6: =(G6/G7)-1 -> -0.041818322 | I6: 0.01 | J6: =I6/100 -> 0.0001 | K6: =H6-J6 -> -0.041918322 | L6: =F6-J6 -> 0.015605632
A7: 40389 | B7: 44.57 | D7: =(D8*C7)/B7+D8 -> 1.4976877 | E7: =B7*D7 -> 66.751939 | F7: =E7/E8-1 -> -0.10014133 | G7: 3643.14 | H7: =(G7/G8)-1 -> 0.058163345 | I7: 0.01 | J7: =I7/100 -> 0.0001 | K7: =H7-J7 -> 0.058063345 | L7: =F7-J7 -> -0.10024133
A8: 40359 | B8: 49.53 | D8: =(D9*C8)/B8+D9 -> 1.4976877 | E8: =B8*D8 -> 74.18047 | F8: =E8/E9-1 -> 0.0016177958 | G8: 3442.89 | H8: =(G8/G9)-1 -> -0.018437318 | I8: 0.01 | J8: =I8/100 -> 0.0001 | K8: =H8-J8 -> -0.018537318 | L8: =F8-J8 -> 0.0015177958
A9: 40329 | B9: 49.45 | C9: 2.4 | D9: =(D10*C9)/B9+D10 -> 1.4976877 | E9: =B9*D9 -> 74.060655 | F9: =E9/E10-1 -> 0.0036778939 | G9: 3507.56 | H9: =(G9/G10)-1 -> -0.081066495 | I9: 0.01 | J9: =I9/100 -> 0.0001 | K9: =H9-J9 -> -0.081166495 | L9: =F9-J9 -> 0.0035778939
A10: 40298 | B10: 51.66 | D10: =(D11*C10)/B10+D11 -> 1.4283636 | E10: =B10*D10 -> 73.789266 | F10: =E10/E11-1 -> -0.063960862 | G10: 3816.99 | H10: =(G10/G11)-1 -> -0.039511727 | I10: 0.01 | J10: =I10/100 -> 0.0001 | K10: =H10-J10 -> -0.039611727 | L10: =F10-J10 -> -0.064060862
A11: 40268 | B11: 55.19 | D11: =(D12*C11)/B11+D12 -> 1.4283636 | E11: =B11*D11 -> 78.831389 | F11: =E11/E12-1 -> 0.02736411 | G11: 3974.01 | H11: =(G11/G12)-1 -> 0.071508305 | I11: 0.01 | J11: =I11/100 -> 0.0001 | K11: =H11-J11 -> 0.071408305 | L11: =F11-J11 -> 0.02726411
A12: 40235 | B12: 53.72 | D12: =(D13*C12)/B12+D13 -> 1.4283636 | E12: =B12*D12 -> 76.731695 | F12: =E12/E13-1 -> 0.002238806 | G12: 3708.8 | H12: =(G12/G13)-1 -> -0.0081990448 | I12: 0 | J12: =I12/100 -> 0 | K12: =H12-J12 -> -0.0081990448 | L12: =F12-J12 -> 0.002238806
A13: 40207 | B13: 53.6 | D13: =(D14*C13)/B13+D14 -> 1.4283636 | E13: =B13*D13 -> 76.560291 | F13: =E13/E14-1 -> -0.026516527 | G13: 3739.46 | H13: =(G13/G14)-1 -> -0.050013591 | I13: 0 | J13: =I13/100 -> 0 | K13: =H13-J13 -> -0.050013591 | L13: =F13-J13 -> -0.026516527
A14: 40178 | B14: 55.06 | D14: =(D15*C14)/B14+D15 -> 1.4283636 | E14: =B14*D14 -> 78.645702 | F14: =E14/E15-1 -> 0.094197138 | G14: 3936.33 | H14: =(G14/G15)-1 -> 0.069611293 | I14: 0.01 | J14: =I14/100 -> 0.0001 | K14: =H14-J14 -> 0.069511293 | L14: =F14-J14 -> 0.094097138
A15: 40147 | B15: 50.32 | D15: =(D16*C15)/B15+D16 -> 1.4283636 | E15: =B15*D15 -> 71.875258 | F15: =E15/E16-1 -> 0.011558951 | G15: 3680.15 | H15: =(G15/G16)-1 -> 0.020084874 | I15: 0 | J15: =I15/100 -> 0 | K15: =H15-J15 -> 0.020084874 | L15: =F15-J15 -> 0.011558951
A16: 40116 | B16: 49.745 | D16: =(D17*C16)/B16+D17 -> 1.4283636 | E16: =B16*D16 -> 71.053949 | F16: =E16/E17-1 -> -0.0080757727 | G16: 3607.69 | H16: =(G16/G17)-1 -> -0.049459742 | I16: 0 | J16: =I16/100 -> 0 | K16: =H16-J16 -> -0.049459742 | L16: =F16-J16 -> -0.0080757727
A17: 40086 | B17: 50.15 | D17: =(D18*C17)/B17+D18 -> 1.4283636 | E17: =B17*D17 -> 71.632437 | F17: =E17/E18-1 -> 0.059805579 | G17: 3795.41 | H17: =(G17/G18)-1 -> 0.038830833 | I17: 0.01 | J17: =I17/100 -> 0.0001 | K17: =H17-J17 -> 0.038730833 | L17: =F17-J17 -> 0.059705579
A18: 40056 | B18: 47.32 | D18: =(D19*C18)/B18+D19 -> 1.4283636 | E18: =B18*D18 -> 67.590168 | F18: =E18/E19-1 -> 0.029590949 | G18: 3653.54 | H18: =(G18/G19)-1 -> 0.066331608 | I18: 0.01 | J18: =I18/100 -> 0.0001 | K18: =H18-J18 -> 0.066231608 | L18: =F18-J18 -> 0.029490949
A19: 40025 | B19: 45.96 | D19: =(D20*C19)/B19+D20 -> 1.4283636 | E19: =B19*D19 -> 65.647593 | F19: =E19/E20-1 -> 0.097683305 | G19: 3426.27 | H19: =(G19/G20)-1 -> 0.091015909 | I19: 0.01 | J19: =I19/100 -> 0.0001 | K19: =H19-J19 -> 0.090915909 | L19: =F19-J19 -> 0.097583305
A20: 39994 | B20: 41.87 | D20: =(D21*C20)/B20+D21 -> 1.4283636 | E20: =B20*D20 -> 59.805586 | F20: =E20/E21-1 -> -0.068520578 | G20: 3140.44 | H20: =(G20/G21)-1 -> -0.04186231 | I20: 0.01 | J20: =I20/100 -> 0.0001 | K20: =H20-J20 -> -0.04196231 | L20: =F20-J20 -> -0.068620578
A21: 39962 | B21: 44.95 | D21: =(D22*C21)/B21+D22 -> 1.4283636 | E21: =B21*D21 -> 64.204946 | F21: =E21/E22-1 -> 0.026959104 | G21: 3277.65 | H21: =(G21/G22)-1 -> 0.037280251 | I21: 0 | J21: =I21/100 -> 0 | K21: =H21-J21 -> 0.037280251 | L21: =F21-J21 -> 0.026959104
A22: 39933 | B22: 43.77 | C22: 2.2 | D22: =(D23*C22)/B22+D23 -> 1.4283636 | E22: =B22*D22 -> 62.519477 | F22: =E22/E23-1 -> 0.084709769 | G22: 3159.85 | H22: =(G22/G23)-1 -> 0.12556726 | I22: 0.01 | J22: =I22/100 -> 0.0001 | K22: =H22-J22 -> 0.12546726 | L22: =F22-J22 -> 0.084609769
A23: 39903 | B23: 42.38 | D23: =(D24*C23)/B23+D24 -> 1.360006 | E23: =B23*D23 -> 57.637055 | F23: =E23/E24-1 -> 0.035805939 | G23: 2807.34 | H23: =(G23/G24)-1 -> 0.038801397 | I23: 0.02 | J23: =I23/100 -> 0.0002 | K23: =H23-J23 -> 0.038601397 | L23: =F23-J23 -> 0.035605939
A24: 39871 | B24: 40.915 | D24: =(D25*C24)/B24+D25 -> 1.360006 | E24: =B24*D24 -> 55.644646 | F24: =E24/E25-1 -> -0.071906544 | G24: 2702.48 | H24: =(G24/G25)-1 -> -0.091273471 | I24: 0.01 | J24: =I24/100 -> 0.0001 | K24: =H24-J24 -> -0.091373471 | L24: =F24-J24 -> -0.072006544
A25: 39843 | B25: 44.085 | D25: =(D26*C25)/B25+D26 -> 1.360006 | E25: =B25*D25 -> 59.955865 | F25: =E25/E26-1 -> -0.028964758 | G25: 2973.92 | H25: =(G25/G26)-1 -> -0.075839737 | I25: 0 | J25: =I25/100 -> 0 | K25: =H25-J25 -> -0.075839737 | L25: =F25-J25 -> -0.028964758
A26: 39813 | B26: 45.4 | D26: =(D27*C26)/B26+D27 -> 1.360006 | E26: =B26*D26 -> 61.744273 | F26: =E26/E27-1 -> 0.044879171 | G26: 3217.97 | H26: =(G26/G27)-1 -> -0.013703459 | I26: 0 | J26: =I26/100 -> 0 | K26: =H26-J26 -> -0.013703459 | L26: =F26-J26 -> 0.044879171
A27: 39780 | B27: 43.45 | D27: =(D28*C27)/B27+D28 -> 1.360006 | E27: =B27*D27 -> 59.092261 | F27: =E27/E28-1 -> -0.12097916 | G27: 3262.68 | H27: =(G27/G28)-1 -> -0.064349153 | I27: 0.03 | J27: =I27/100 -> 0.0003 | K27: =H27-J27 -> -0.064649153 | L27: =F27-J27 -> -0.12127916
A28: 39752 | B28: 49.43 | D28: =(D29*C28)/B28+D29 -> 1.360006 | E28: =B28*D28 -> 67.225097 | F28: =E28/E29-1 -> 0.061868958 | G28: 3487.07 | H28: =(G28/G29)-1 -> -0.13517274 | I28: 0.08 | J28: =I28/100 -> 0.0008 | K28: =H28-J28 -> -0.13597274 | L28: =F28-J28 -> 0.061068958
A29: 39721 | B29: 46.55 | D29: =(D30*C29)/B29+D30 -> 1.360006 | E29: =B29*D29 -> 63.30828 | F29: =E29/E30-1 -> -0.042378111 | G29: 4032.1 | H29: =(G29/G30)-1 -> -0.10049971 | I29: 0.15 | J29: =I29/100 -> 0.0015 | K29: =H29-J29 -> -0.10199971 | L29: =F29-J29 -> -0.043878111
A30: 39689 | B30: 48.61 | D30: =(D31*C30)/B30+D31 -> 1.360006 | E30: =B30*D30 -> 66.109892 | F30: =E30/E31-1 -> 0.078544486 | G30: 4482.6 | H30: =(G30/G31)-1 -> 0.020544764 | I30: 0.13 | J30: =I30/100 -> 0.0013 | K30: =H30-J30 -> 0.019244764 | L30: =F30-J30 -> 0.077244486
A31: 39660 | B31: 45.07 | D31: =(D32*C31)/B31+D32 -> 1.360006 | E31: =B31*D31 -> 61.295471 | F31: =E31/E32-1 -> 0.062220127 | G31: 4392.36 | H31: =(G31/G32)-1 -> -0.0095809328 | I31: 0.15 | J31: =I31/100 -> 0.0015 | K31: =H31-J31 -> -0.011080933 | L31: =F31-J31 -> 0.060720127
A32: 39629 | B32: 42.43 | D32: =(D33*C32)/B32+D33 -> 1.360006 | E32: =B32*D32 -> 57.705055 | F32: =E32/E33-1 -> -0.11438113 | G32: 4434.85 | H32: =(G32/G33)-1 -> -0.11555597 | I32: 0.17 | J32: =I32/100 -> 0.0017 | K32: =H32-J32 -> -0.11725597 | L32: =F32-J32 -> -0.11608113
A33: 39598 | B33: 47.91 | C33: 2.07 | D33: =(D34*C33)/B33+D34 -> 1.360006 | E33: =B33*D33 -> 65.157888 | F33: =E33/E34-1 -> -0.0033898305 | G33: 5014.28 | H33: =(G33/G34)-1 -> 0.0035504569 | I33: 0.18 | J33: =I33/100 -> 0.0018 | K33: =H33-J33 -> 0.0017504569 | L33: =F33-J33 -> -0.0051898305
A34: 39568 | B34: 50.15 | D34: =(D35*C34)/B34+D35 -> 1.3036792 | E34: =B34*D34 -> 65.379514 | F34: =E34/E35-1 -> 0.055345118 | G34: 4996.54 | H34: =(G34/G35)-1 -> 0.061496855 | I34: 0.18 | J34: =I34/100 -> 0.0018 | K34: =H34-J34 -> 0.059696855 | L34: =F34-J34 -> 0.053545118
A35: 39538 | B35: 47.52 | D35: =(D36*C35)/B35+D36 -> 1.3036792 | E35: =B35*D35 -> 61.950837 | F35: =E35/E36-1 -> -0.026029924 | G35: 4707.07 | H35: =(G35/G36)-1 -> -0.017448535 | I35: 0.17 | J35: =I35/100 -> 0.0017 | K35: =H35-J35 -> -0.019148535 | L35: =F35-J35 -> -0.027729924
A36: 39507 | B36: 48.79 | D36: =(D37*C36)/B36+D37 -> 1.3036792 | E36: =B36*D36 -> 63.60651 | F36: =E36/E37-1 -> -0.10229991 | G36: 4790.66 | H36: =(G36/G37)-1 -> -0.016249161 | I36: 0.13 | J36: =I36/100 -> 0.0013 | K36: =H36-J36 -> -0.017549161 | L36: =F36-J36 -> -0.10359991
A37: 39478 | B37: 54.35 | D37: =(D38*C37)/B37+D38 -> 1.3036792 | E37: =B37*D37 -> 70.854967 | F37: =E37/E38-1 -> -0.13702763 | G37: 4869.79 | H37: =(G37/G38)-1 -> -0.1325756 | I37: 0.21 | J37: =I37/100 -> 0.0021 | K37: =H37-J37 -> -0.1346756 | L37: =F37-J37 -> -0.13912763
A38: 39447 | B38: 62.98 | D38: =(D39*C38)/B38+D39 -> 1.3036792 | E38: =B38*D38 -> 82.105718 | F38: =E38/E39-1 -> -0.031225965 | G38: 5614.08 | H38: =(G38/G39)-1 -> -0.0099619615 | I38: 0.27 | J38: =I38/100 -> 0.0027 | K38: =H38-J38 -> -0.012661961 | L38: =F38-J38 -> -0.033925965
A39: 39416 | B39: 65.01 | D39: =(D40*C39)/B39+D40 -> 1.3036792 | E39: =B39*D39 -> 84.752187 | F39: =E39/E40-1 -> 0.073835481 | G39: 5670.57 | H39: =(G39/G40)-1 -> -0.030331997 | I39: 0.34 | J39: =I39/100 -> 0.0034 | K39: =H39-J39 -> -0.033731997 | L39: =F39-J39 -> 0.070435481
A40: 39386 | B40: 60.54 | D40: =(D41*C40)/B40+D41 -> 1.3036792 | E40: =B40*D40 -> 78.924741 | F40: =E40/E41-1 -> 0.019535197 | G40: 5847.95 | H40: =(G40/G41)-1 -> 0.023139813 | I40: 0.32 | J40: =I40/100 -> 0.0032 | K40: =H40-J40 -> 0.019939813 | L40: =F40-J40 -> 0.016335197
A41: 39353 | B41: 59.38 | D41: =(D42*C41)/B41+D42 -> 1.3036792 | E41: =B41*D41 -> 77.412473 | F41: =E41/E42-1 -> -0.009012016 | G41: 5715.69 | H41: =(G41/G42)-1 -> 0.0093577269 | I41: 0.32 | J41: =I41/100 -> 0.0032 | K41: =H41-J41 -> 0.0061577269 | L41: =F41-J41 -> -0.012212016
A42: 39325 | B42: 59.92 | D42: =(D43*C42)/B42+D43 -> 1.3036792 | E42: =B42*D42 -> 78.11646 | F42: =E42/E43-1 -> -0.025691057 | G42: 5662.7 | H42: =(G42/G43)-1 -> -0.015367548 | I42: 0.42 | J42: =I42/100 -> 0.0042 | K42: =H42-J42 -> -0.019567548 | L42: =F42-J42 -> -0.029891057
A43: 39294 | B43: 61.5 | D43: =(D44*C43)/B43+D44 -> 1.3036792 | E43: =B43*D43 -> 80.176273 | F43: =E43/E44-1 -> 0.023294509 | G43: 5751.08 | H43: =(G43/G44)-1 -> -0.050182248 | I43: 0.4 | J43: =I43/100 -> 0.004 | K43: =H43-J43 -> -0.054182248 | L43: =F43-J43 -> 0.019294509
A44: 39262 | B44: 60.1 | C44: 1.75 | D44: =(D45*C44)/B44+D45 -> 1.3036792 | E44: =B44*D44 -> 78.351122 | F44: =E44/E45-1 -> -0.13689646 | G44: 6054.93 | H44: =(G44/G45)-1 -> -0.0080389908 | I44: 0.4 | J44: =I44/100 -> 0.004 | K44: =H44-J44 -> -0.012038991 | L44: =F44-J44 -> -0.14089646
A45: 39233 | B45: 71.66 | D45: =(D46*C45)/B45+D46 -> 1.2667926 | E45: =B45*D45 -> 90.778358 | F45: =E45/E46-1 -> 0.06194428 | G45: 6104 | H45: =(G45/G46)-1 -> 0.0241542 | I45: 0.41 | J45: =I45/100 -> 0.0041 | K45: =H45-J45 -> 0.0200542 | L45: =F45-J45 -> 0.05784428
A46: 39202 | B46: 67.48 | D46: =(D47*C46)/B46+D47 -> 1.2667926 | E46: =B46*D46 -> 85.483164 | F46: =E46/E47-1 -> 0.03655914 | G46: 5960.04 | H46: =(G46/G47)-1 -> 0.057840033 | I46: 0.44 | J46: =I46/100 -> 0.0044 | K46: =H46-J46 -> 0.053440033 | L46: =F46-J46 -> 0.03215914
A47: 39171 | B47: 65.1 | D47: =(D48*C47)/B47+D48 -> 1.2667926 | E47: =B47*D47 -> 82.468198 | F47: =E47/E48-1 -> 0.013071895 | G47: 5634.16 | H47: =(G47/G48)-1 -> 0.021362067 | I47: 0.43 | J47: =I47/100 -> 0.0043 | K47: =H47-J47 -> 0.017062067 | L47: =F47-J47 -> 0.0087718954
A48: 39141 | B48: 64.26 | D48: =(D49*C48)/B48+D49 -> 1.2667926 | E48: =B48*D48 -> 81.404092 | F48: =E48/E49-1 -> -0.047294292 | G48: 5516.32 | H48: =(G48/G49)-1 -> -0.016402446 | I48: 0.38 | J48: =I48/100 -> 0.0038 | K48: =H48-J48 -> -0.020202446 | L48: =F48-J48 -> -0.051094292
A49: 39113 | B49: 67.45 | D49: =(D50*C49)/B49+D50 -> 1.2667926 | E49: =B49*D49 -> 85.445161 | F49: =E49/E50-1 -> -0.035739814 | G49: 5608.31 | H49: =(G49/G50)-1 -> 0.01200882 | I49: 0.44 | J49: =I49/100 -> 0.0044 | K49: =H49-J49 -> 0.0076088203 | L49: =F49-J49 -> -0.040139814
A50: 39080 | B50: 69.95 | D50: =(D51*C50)/B50+D51 -> 1.2667926 | E50: =B50*D50 -> 88.612142 | F50: =E50/E51-1 -> 0.05505279 | G50: 5541.76 | H50: =(G50/G51)-1 -> 0.040190403 | I50: 0.4 | J50: =I50/100 -> 0.004 | K50: =H50-J50 -> 0.036190403 | L50: =F50-J50 -> 0.05105279
A51: 39051 | B51: 66.3 | D51: =(D52*C51)/B51+D52 -> 1.2667926 | E51: =B51*D51 -> 83.988349 | F51: =E51/E52-1 -> -0.0045045045 | G51: 5327.64 | H51: =(G51/G52)-1 -> -0.0039429921 | I51: 0.42 | J51: =I51/100 -> 0.0042 | K51: =H51-J51 -> -0.0081429921 | L51: =F51-J51 -> -0.0087045045
A52: 39021 | B52: 66.6 | D52: =(D53*C52)/B52+D53 -> 1.2667926 | E52: =B52*D52 -> 84.368387 | F52: =E52/E53-1 -> -0.051282051 | G52: 5348.73 | H52: =(G52/G53)-1 -> 0.018803774 | I52: 0.41 | J52: =I52/100 -> 0.0041 | K52: =H52-J52 -> 0.014703774 | L52: =F52-J52 -> -0.055382051
A53: 38989 | B53: 70.2 | D53: =(D54*C53)/B53+D54 -> 1.2667926 | E53: =B53*D53 -> 88.92884 | F53: =E53/E54-1 -> 0.0021413276 | G53: 5250.01 | H53: =(G53/G54)-1 -> 0.016450986 | I53: 0.41 | J53: =I53/100 -> 0.0041 | K53: =H53-J53 -> 0.012350986 | L53: =F53-J53 -> -0.0019586724
A54: 38960 | B54: 70.05 | D54: =(D55*C54)/B54+D55 -> 1.2667926 | E54: =B54*D54 -> 88.738821 | F54: =E54/E55-1 -> -0.059100067 | G54: 5165.04 | H54: =(G54/G55)-1 -> 0.031065473 | I54: 0.42 | J54: =I54/100 -> 0.0042 | K54: =H54-J54 -> 0.026865473 | L54: =F54-J54 -> -0.063300067
A55: 38929 | B55: 74.45 | D55: =(D56*C55)/B55+D56 -> 1.2667926 | E55: =B55*D55 -> 94.312709 | F55: =E55/E56-1 -> -0.024246396 | G55: 5009.42 | H55: =(G55/G56)-1 -> 0.0087515808 | I55: 0.4 | J55: =I55/100 -> 0.004 | K55: =H55-J55 -> 0.0047515808 | L55: =F55-J55 -> -0.028246396
A56: 38898 | B56: 76.3 | C56: 1.52 | D56: =(D57*C56)/B56+D57 -> 1.2667926 | E56: =B56*D56 -> 96.656275 | F56: =E56/E57-1 -> 0.058055744 | G56: 4965.96 | H56: =(G56/G57)-1 -> 0.0072573415 | I56: 0.4 | J56: =I56/100 -> 0.004 | K56: =H56-J56 -> 0.0032573415 | L56: =F56-J56 -> 0.054055744
A57: 38868 | B57: 73.55 | D57: =(D58*C57)/B57+D58 -> 1.2420493 | E57: =B57*D57 -> 91.352725 | F57: =E57/E58-1 -> -0.016053512 | G57: 4930.18 | H57: =(G57/G58)-1 -> -0.049768715 | I57: 0.43 | J57: =I57/100 -> 0.0043 | K57: =H57-J57 -> -0.054068715 | L57: =F57-J57 -> -0.020353512
A58: 38835 | B58: 74.75 | D58: =(D59*C58)/B58+D59 -> 1.2420493 | E58: =B58*D58 -> 92.843184 | F58: =E58/E59-1 -> -0.047770701 | G58: 5188.4 | H58: =(G58/G59)-1 -> -0.006215463 | I58: 0.36 | J58: =I58/100 -> 0.0036 | K58: =H58-J58 -> -0.009815463 | L58: =F58-J58 -> -0.051370701
A59: 38807 | B59: 78.5 | D59: =(D60*C59)/B59+D60 -> 1.2420493 | E59: =B59*D59 -> 97.500869 | F59: =E59/E60-1 -> 0.099439776 | G59: 5220.85 | H59: =(G59/G60)-1 -> 0.044076033 | I59: 0.37 | J59: =I59/100 -> 0.0037 | K59: =H59-J59 -> 0.040376033 | L59: =F59-J59 -> 0.095739776
A60: 38776 | B60: 71.4 | D60: =(D61*C60)/B60+D61 -> 1.2420493 | E60: =B60*D60 -> 88.682319 | F60: =E60/E61-1 -> -0.053677932 | G60: 5000.45 | H60: =(G60/G61)-1 -> 0.010602285 | I60: 0.34 | J60: =I60/100 -> 0.0034 | K60: =H60-J60 -> 0.007202285 | L60: =F60-J60 -> -0.057077932
A61: 38748 | B61: 75.45 | D61: =(D62*C61)/B61+D62 -> 1.2420493 | E61: =B61*D61 -> 93.712618 | F61: =E61/E62-1 -> 0.019594595 | G61: 4947.99 | H61: =(G61/G62)-1 -> 0.049363446 | I61: 0.35 | J61: =I61/100 -> 0.0035 | K61: =H61-J61 -> 0.045863446 | L61: =F61-J61 -> 0.016094595
A62: 38716 | B62: 74 | D62: =(D63*C62)/B62+D63 -> 1.2420493 | E62: =B62*D62 -> 91.911647 | F62: =E62/E63-1 -> 0.078717201 | G62: 4715.23 | H62: =(G62/G63)-1 -> 0.032364075 | I62: 0.32 | J62: =I62/100 -> 0.0032 | K62: =H62-J62 -> 0.029164075 | L62: =F62-J62 -> 0.075517201
A63: 38686 | B63: 68.6 | D63: =(D64*C63)/B63+D64 -> 1.2420493 | E63: =B63*D63 -> 85.204581 | F63: =E63/E64-1 -> 0.026946108 | G63: 4567.41 | H63: =(G63/G64)-1 -> 0.029519097 | I63: 0.31 | J63: =I63/100 -> 0.0031 | K63: =H63-J63 -> 0.026419097 | L63: =F63-J63 -> 0.023846108
A64: 38656 | B64: 66.8 | D64: =(D65*C64)/B64+D65 -> 1.2420493 | E64: =B64*D64 -> 82.968892 | F64: =E64/E65-1 -> -0.028363636 | G64: 4436.45 | H64: =(G64/G65)-1 -> -0.035558541 | I64: 0.27 | J64: =I64/100 -> 0.0027 | K64: =H64-J64 -> -0.038258541 | L64: =F64-J64 -> -0.031063636
A65: 38625 | B65: 68.75 | D65: =(D66*C65)/B65+D66 -> 1.2420493 | E65: =B65*D65 -> 85.390888 | F65: =E65/E66-1 -> -0.0065028902 | G65: 4600.02 | H65: =(G65/G66)-1 -> 0.04561118 | I65: 0.29 | J65: =I65/100 -> 0.0029 | K65: =H65-J65 -> 0.04271118 | L65: =F65-J65 -> -0.0094028902
A66: 38595 | B66: 69.2 | D66: =(D67*C66)/B66+D67 -> 1.2420493 | E66: =B66*D66 -> 85.94981 | F66: =E66/E67-1 -> -0.030133146 | G66: 4399.36 | H66: =(G66/G67)-1 -> -0.011766186 | I66: 0.3 | J66: =I66/100 -> 0.003 | K66: =H66-J66 -> -0.014766186 | L66: =F66-J66 -> -0.033133146
A67: 38562 | B67: 71.35 | D67: =(D68*C67)/B67+D68 -> 1.2420493 | E67: =B67*D67 -> 88.620216 | F67: =E67/E68-1 -> 0.050810015 | G67: 4451.74 | H67: =(G67/G68)-1 -> 0.052582548 | I67: 0.24 | J67: =I67/100 -> 0.0024 | K67: =H67-J67 -> 0.050182548 | L67: =F67-J67 -> 0.048410015
A68: 38533 | B68: 67.9 | C68: 1.2 | D68: =(D69*C68)/B68+D69 -> 1.2420493 | E68: =B68*D68 -> 84.335146 | F68: =E68/E69-1 -> -0.057298772 | G68: 4229.35 | H68: =(G68/G69)-1 -> 0.026359407 | I68: 0.23 | J68: =I68/100 -> 0.0023 | K68: =H68-J68 -> 0.024059407 | L68: =F68-J68 -> -0.059598772
A69: 38503 | B69: 73.3 | D69: =(D70*C69)/B69+D70 -> 1.2204797 | E69: =B69*D69 -> 89.461161 | F69: =E69/E70-1 -> 0.071637427 | G69: 4120.73 | H69: =(G69/G70)-1 -> 0.053434431 | I69: 0.24 | J69: =I69/100 -> 0.0024 | K69: =H69-J69 -> 0.051034431 | L69: =F69-J69 -> 0.069237427
A70: 38471 | B70: 68.4 | D70: =(D71*C70)/B70+D71 -> 1.2204797 | E70: =B70*D70 -> 83.480811 | F70: =E70/E71-1 -> 0.051498847 | G70: 3911.71 | H70: =(G70/G71)-1 -> -0.038367365 | I70: 0.21 | J70: =I70/100 -> 0.0021 | K70: =H70-J70 -> -0.040467365 | L70: =F70-J70 -> 0.049398847
A71: 38442 | B71: 65.05 | D71: =(D72*C71)/B71+D72 -> 1.2204797 | E71: =B71*D71 -> 79.392204 | F71: =E71/E72-1 -> 0.076986755 | G71: 4067.78 | H71: =(G71/G72)-1 -> 0.010086513 | I71: 0.21 | J71: =I71/100 -> 0.0021 | K71: =H71-J71 -> 0.0079865126 | L71: =F71-J71 -> 0.074886755
A72: 38411 | B72: 60.4 | D72: =(D73*C72)/B72+D73 -> 1.2204797 | E72: =B72*D72 -> 73.716973 | F72: =E72/E73-1 -> 0.055021834 | G72: 4027.16 | H72: =(G72/G73)-1 -> 0.028993099 | I72: 0.16 | J72: =I72/100 -> 0.0016 | K72: =H72-J72 -> 0.027393099 | L72: =F72-J72 -> 0.053421834
A73: 38383 | B73: 57.25 | D73: =(D74*C73)/B73+D74 -> 1.2204797 | E73: =B73*D73 -> 69.872462 | F73: =E73/E74-1 -> -0.026360544 | G73: 3913.69 | H73: =(G73/G74)-1 -> 0.02421516 | I73: 0.16 | J73: =I73/100 -> 0.0016 | K73: =H73-J73 -> 0.02261516 | L73: =F73-J73 -> -0.027960544
A74: 38352 | B74: 58.8 | D74: =(D75*C74)/B74+D75 -> 1.2204797 | E74: =B74*D74 -> 71.764206 | F74: =E74/E75-1 -> 0.037952339 | G74: 3821.16 | H74: =(G74/G75)-1 -> 0.017958042 | I74: 0.16 | J74: =I74/100 -> 0.0016 | K74: =H74-J74 -> 0.016358042 | L74: =F74-J74 -> 0.036352339
A75: 38321 | B75: 56.65 | D75: =(D76*C75)/B75+D76 -> 1.2204797 | E75: =B75*D75 -> 69.140174 | F75: =E75/E76-1 -> -0.011343805 | G75: 3753.75 | H75: =(G75/G76)-1 -> 0.012660447 | I75: 0.15 | J75: =I75/100 -> 0.0015 | K75: =H75-J75 -> 0.011160447 | L75: =F75-J75 -> -0.012843805
A76: 38289 | B76: 57.3 | D76: =(D77*C76)/B76+D77 -> 1.2204797 | E76: =B76*D76 -> 69.933486 | F76: =E76/E77-1 -> -0.018835616 | G76: 3706.82 | H76: =(G76/G77)-1 -> 0.018186513 | I76: 0.11 | J76: =I76/100 -> 0.0011 | K76: =H76-J76 -> 0.017086513 | L76: =F76-J76 -> -0.019935616
A77: 38260 | B77: 58.4 | D77: =(D78*C77)/B77+D78 -> 1.2204797 | E77: =B77*D77 -> 71.276014 | F77: =E77/E78-1 -> 0 | G77: 3640.61 | H77: =(G77/G78)-1 -> 0.012889925 | I77: 0.11 | J77: =I77/100 -> 0.0011 | K77: =H77-J77 -> 0.011789925 | L77: =F77-J77 -> -0.0011
A78: 38230 | B78: 58.4 | D78: =(D79*C78)/B78+D79 -> 1.2204797 | E78: =B78*D78 -> 71.276014 | F78: =E78/E79-1 -> 0.059891107 | G78: 3594.28 | H78: =(G78/G79)-1 -> -0.01448274 | I78: 0.11 | J78: =I78/100 -> 0.0011 | K78: =H78-J78 -> -0.01558274 | L78: =F78-J78 -> 0.058791107
A79: 38198 | B79: 55.1 | D79: =(D80*C79)/B79+D80 -> 1.2204797 | E79: =B79*D79 -> 67.248431 | F79: =E79/E80-1 -> 0.057581574 | G79: 3647.1 | H79: =(G79/G80)-1 -> -0.023008366 | I79: 0.1 | J79: =I79/100 -> 0.001 | K79: =H79-J79 -> -0.024008366 | L79: =F79-J79 -> 0.056581574
A80: 38168 | B80: 52.1 | D80: =(D81*C80)/B80+D81 -> 1.2204797 | E80: =B80*D80 -> 63.586992 | F80: =E80/E81-1 -> -0.037857802 | G80: 3732.99 | H80: =(G80/G81)-1 -> 0.017266046 | I80: 0.08 | J80: =I80/100 -> 0.0008 | K80: =H80-J80 -> 0.016466046 | L80: =F80-J80 -> -0.038657802
A81: 38138 | B81: 54.15 | C81: 1.02 | D81: =(D82*C81)/B81+D82 -> 1.2204797 | E81: =B81*D81 -> 66.088975 | F81: =E81/E82-1 -> 0.040943396 | G81: 3669.63 | H81: =(G81/G82)-1 -> -0.0012655541 | I81: 0.06 | J81: =I81/100 -> 0.0006 | K81: =H81-J81 -> -0.0018655541 | L81: =F81-J81 -> 0.040343396
A82: 38107 | B82: 53 | D82: =(D83*C82)/B82+D83 -> 1.1979151 | E82: =B82*D82 -> 63.489499 | F82: =E82/E83-1 -> -0.0028222013 | G82: 3674.28 | H82: =(G82/G83)-1 -> 0.013530176 | I82: 0.08 | J82: =I82/100 -> 0.0008 | K82: =H82-J82 -> 0.012730176 | L82: =F82-J82 -> -0.0036222013
A83: 38077 | B83: 53.15 | D83: =(D84*C83)/B83+D84 -> 1.1979151 | E83: =B83*D83 -> 63.669187 | F83: =E83/E84-1 -> -0.033636364 | G83: 3625.23 | H83: =(G83/G84)-1 -> -0.026898836 | I83: 0.09 | J83: =I83/100 -> 0.0009 | K83: =H83-J83 -> -0.027798836 | L83: =F83-J83 -> -0.034536364
A84: 38044 | B84: 55 | D84: =(D85*C84)/B84+D85 -> 1.1979151 | E84: =B84*D84 -> 65.885329 | F84: =E84/E85-1 -> -0.038461538 | G84: 3725.44 | H84: =(G84/G85)-1 -> 0.023911347 | I84: 0.06 | J84: =I84/100 -> 0.0006 | K84: =H84-J84 -> 0.023311347 | L84: =F84-J84 -> -0.039061538
A85: 38016 | B85: 57.2 | D85: =(D86*C85)/B85+D86 -> 1.1979151 | E85: =B85*D85 -> 68.520743 | F85: =E85/E86-1 -> -0.041876047 | G85: 3638.44 | H85: =(G85/G86)-1 -> 0.022636949 | I85: 0.07 | J85: =I85/100 -> 0.0007 | K85: =H85-J85 -> 0.021936949 | L85: =F85-J85 -> -0.042576047
A86: 37986 | B86: 59.7 | D86: =(D87*C86)/B86+D87 -> 1.1979151 | E86: =B86*D86 -> 71.51553 | F86: =E86/E87-1 -> 0.056637168 | G86: 3557.9 | H86: =(G86/G87)-1 -> 0.038866617 | I86: 0.08 | J86: =I86/100 -> 0.0008 | K86: =H86-J86 -> 0.038066617 | L86: =F86-J86 -> 0.055837168
A87: 37953 | B87: 56.5 | D87: =(D88*C87)/B87+D88 -> 1.1979151 | E87: =B87*D87 -> 67.682202 | F87: =E87/E88-1 -> 0.061032864 | G87: 3424.79 | H87: =(G87/G88)-1 -> 0.015294083 | I87: 0.07 | J87: =I87/100 -> 0.0007 | K87: =H87-J87 -> 0.014594083 | L87: =F87-J87 -> 0.060332864
A88: 37925 | B88: 53.25 | D88: =(D89*C88)/B88+D89 -> 1.1979151 | E88: =B88*D88 -> 63.788978 | F88: =E88/E89-1 -> 0.020114943 | G88: 3373.2 | H88: =(G88/G89)-1 -> 0.075984293 | I88: 0.07 | J88: =I88/100 -> 0.0007 | K88: =H88-J88 -> 0.075284293 | L88: =F88-J88 -> 0.019414943
A89: 37894 | B89: 52.2 | D89: =(D90*C89)/B89+D90 -> 1.1979151 | E89: =B89*D89 -> 62.531167 | F89: =E89/E90-1 -> 0.01953125 | G89: 3134.99 | H89: =(G89/G90)-1 -> -0.053279258 | I89: 0.08 | J89: =I89/100 -> 0.0008 | K89: =H89-J89 -> -0.054079258 | L89: =F89-J89 -> 0.01873125
A90: 37862 | B90: 51.2 | D90: =(D91*C90)/B90+D91 -> 1.1979151 | E90: =B90*D90 -> 61.333252 | F90: =E90/E91-1 -> 0.021956088 | G90: 3311.42 | H90: =(G90/G91)-1 -> 0.031508253 | I90: 0.07 | J90: =I90/100 -> 0.0007 | K90: =H90-J90 -> 0.030808253 | L90: =F90-J90 -> 0.021256088
A91: 37833 | B91: 50.1 | D91: =(D92*C91)/B91+D92 -> 1.1979151 | E91: =B91*D91 -> 60.015546 | F91: =E91/E92-1 -> -0.017647059 | G91: 3210.27 | H91: =(G91/G92)-1 -> 0.040909828 | I91: 0.07 | J91: =I91/100 -> 0.0007 | K91: =H91-J91 -> 0.040209828 | L91: =F91-J91 -> -0.018347059
A92: 37802 | B92: 51 | C92: 0.84 | D92: =(D93*C92)/B92+D93 -> 1.1979151 | E92: =B92*D92 -> 61.093669 | F92: =E92/E93-1 -> -0.046182153 | G92: 3084.1 | H92: =(G92/G93)-1 -> 0.030868221 | I92: 0.1 | J92: =I92/100 -> 0.001 | K92: =H92-J92 -> 0.029868221 | L92: =F92-J92 -> -0.047182153
A93: 37771 | B93: 54.35 | D93: =(D94*C93)/B93+D94 -> 1.1785044 | E93: =B93*D93 -> 64.051715 | F93: =E93/E94-1 -> 0.016838167 | G93: 2991.75 | H93: =(G93/G94)-1 -> 0.012892436 | I93: 0.09 | J93: =I93/100 -> 0.0009 | K93: =H93-J93 -> 0.011992436 | L93: =F93-J93 -> 0.015938167
A94: 37741 | B94: 53.45 | D94: =(D95*C94)/B94+D95 -> 1.1785044 | E94: =B94*D94 -> 62.991061 | F94: =E94/E95-1 -> 0.15918456 | G94: 2953.67 | H94: =(G94/G95)-1 -> 0.128018 | I94: 0.1 | J94: =I94/100 -> 0.001 | K94: =H94-J94 -> 0.127018 | L94: =F94-J94 -> 0.15818456
A95: 37711 | B95: 46.11 | D95: =(D96*C95)/B95+D96 -> 1.1785044 | E95: =B95*D95 -> 54.340839 | F95: =E95/E96-1 -> -0.070737606 | G95: 2618.46 | H95: =(G95/G96)-1 -> -0.049239852 | I95: 0.1 | J95: =I95/100 -> 0.001 | K95: =H95-J95 -> -0.050239852 | L95: =F95-J95 -> -0.071737606
A96: 37680 | B96: 49.62 | D96: =(D97*C96)/B96+D97 -> 1.1785044 | E96: =B96*D96 -> 58.477389 | F96: =E96/E97-1 -> 0.019938335 | G96: 2754.07 | H96: =(G96/G97)-1 -> -0.062565523 | I96: 0.09 | J96: =I96/100 -> 0.0009 | K96: =H96-J96 -> -0.063465523 | L96: =F96-J96 -> 0.019038335
A97: 37652 | B97: 48.65 | D97: =(D98*C97)/B97+D98 -> 1.1785044 | E97: =B97*D97 -> 57.33424 | F97: =E97/E98-1 -> -0.16480687 | G97: 2937.88 | H97: =(G97/G98)-1 -> -0.041133715 | I97: 0.1 | J97: =I97/100 -> 0.001 | K97: =H97-J97 -> -0.042133715 | L97: =F97-J97 -> -0.16580687
A98: 37621 | B98: 58.25 | D98: =(D99*C98)/B98+D99 -> 1.1785044 | E98: =B98*D98 -> 68.647882 | F98: =E98/E99-1 -> -0.019360269 | G98: 3063.91 | H98: =(G98/G99)-1 -> -0.078980356 | I98: 0.11 | J98: =I98/100 -> 0.0011 | K98: =H98-J98 -> -0.080080356 | L98: =F98-J98 -> -0.020460269
A99: 37589 | B99: 59.4 | D99: =(D100*C99)/B99+D100 -> 1.1785044 | E99: =B99*D99 -> 70.003163 | F99: =E99/E100-1 -> -0.03805668 | G99: 3326.65 | H99: =(G99/G100)-1 -> 0.056065955 | I99: 0.12 | J99: =I99/100 -> 0.0012 | K99: =H99-J99 -> 0.054865955 | L99: =F99-J99 -> -0.03925668
A100: 37560 | B100: 61.75 | D100: =(D101*C100)/B100+D101 -> 1.1785044 | E100: =B100*D100 -> 72.772648 | F100: =E100/E101-1 -> 0.082383874 | G100: 3150.04 | H100: =(G100/G101)-1 -> 0.13414823 | I100: 0.14 | J100: =I100/100 -> 0.0014 | K100: =H100-J100 -> 0.13274823 | L100: =F100-J100 -> 0.080983874
...

Sheet use 10-year bond
A1: Date | B1: SNY Stock Price | C1: Dividend | D1: # Stocks | E1: Value | F1: Return | G1: Market Index | H1: Market Return | I1: Rf(%) | J1: Rf | K1: Market Premium | L1: SNY Premium
A2: 40543 | B2: 47.85 | D2: =(D3*C2)/B2+D3 -> 1.4976877 | E2: =B2*D2 -> 71.664355 | F2: =E2/E3-1 -> 0.027264921 | G2: 3804.78 | H2: =(G2/G3)-1 -> 0.053827234 | I2: 3.35 | J2: =I2/100 -> 0.0335 | K2: =H2-J2 -> 0.020327234 | L2: =F2-J2 -> -0.0062350794
A3: 40512 | B3: 46.58 | D3: =(D4*C3)/B3+D4 -> 1.4976877 | E3: =B3*D3 -> 69.762291 | F3: =E3/E4-1 -> -0.07174173 | G3: 3610.44 | H3: =(G3/G4)-1 -> -0.058187035 | I3: 3.164 | J3: =I3/100 -> 0.03164 | K3: =H3-J3 -> -0.089827035 | L3: =F3-J3 -> -0.10338173
A4: 40480 | B4: 50.18 | D4: =(D5*C4)/B4+D5 -> 1.4976877 | E4: =B4*D4 -> 75.153967 | F4: =E4/E5-1 -> 0.026700767 | G4: 3833.5 | H4: =(G4/G5)-1 -> 0.031847717 | I4: 2.91 | J4: =I4/100 -> 0.0291 | K4: =H4-J4 -> 0.0027477167 | L4: =F4-J4 -> -0.0023992327
A5: 40451 | B5: 48.875 | D5: =(D6*C5)/B5+D6 -> 1.4976877 | E5: =B5*D5 -> 73.199484 | F5: =E5/E6-1 -> 0.079633311 | G5: 3715.18 | H5: =(G5/G6)-1 -> 0.064280578 | I5: 2.673 | J5: =I5/100 -> 0.02673 | K5: =H5-J5 -> 0.037550578 | L5: =F5-J5 -> 0.052903311
A6: 40421 | B6: 45.27 | D6: =(D7*C6)/B6+D7 -> 1.4976877 | E6: =B6*D6 -> 67.80032 | F6: =E6/E7-1 -> 0.015705632 | G6: 3490.79 | H6: =(G6/G7)-1 -> -0.041818322 | I6: 2.475 | J6: =I6/100 -> 0.02475 | K6: =H6-J6 -> -0.066568322 | L6: =F6-J6 -> -0.0090443684
A7: 40389 | B7: 44.57 | D7: =(D8*C7)/B7+D8 -> 1.4976877 | E7: =B7*D7 -> 66.751939 | F7: =E7/E8-1 -> -0.10014133 | G7: 3643.14 | H7: =(G7/G8)-1 -> 0.058163345 | I7: 2.956 | J7: =I7/100 -> 0.02956 | K7: =H7-J7 -> 0.028603345 | L7: =F7-J7 -> -0.12970133
A8: 40359 | B8: 49.53 | D8: =(D9*C8)/B8+D9 -> 1.4976877 | E8: =B8*D8 -> 74.18047 | F8: =E8/E9-1 -> 0.0016177958 | G8: 3442.89 | H8: =(G8/G9)-1 -> -0.018437318 | I8: 3.055 | J8: =I8/100 -> 0.03055 | K8: =H8-J8 -> -0.048987318 | L8: =F8-J8 -> -0.028932204
A9: 40329 | B9: 49.45 | C9: 2.4 | D9: =(D10*C9)/B9+D10 -> 1.4976877 | E9: =B9*D9 -> 74.060655 | F9: =E9/E10-1 -> 0.0036778939 | G9: 3507.56 | H9: =(G9/G10)-1 -> -0.081066495 | I9: 2.916 | J9: =I9/100 -> 0.02916 | K9: =H9-J9 -> -0.11022649 | L9: =F9-J9 -> -0.025482106
A10: 40298 | B10: 51.66 | D10: =(D11*C10)/B10+D11 -> 1.4283636 | E10: =B10*D10 -> 73.789266 | F10: =E10/E11-1 -> -0.063960862 | G10: 3816.99 | H10: =(G10/G11)-1 -> -0.039511727 | I10: 3.3 | J10: =I10/100 -> 0.033 | K10: =H10-J10 -> -0.072511727 | L10: =F10-J10 -> -0.096960862
A11: 40268 | B11: 55.19 | D11: =(D12*C11)/B11+D12 -> 1.4283636 | E11: =B11*D11 -> 78.831389 | F11: =E11/E12-1 -> 0.02736411 | G11: 3974.01 | H11: =(G11/G12)-1 -> 0.071508305 | I11: 3.439 | J11: =I11/100 -> 0.03439 | K11: =H11-J11 -> 0.037118305 | L11: =F11-J11 -> -0.0070258898
A12: 40235 | B12: 53.72 | D12: =(D13*C12)/B12+D13 -> 1.4283636 | E12: =B12*D12 -> 76.731695 | F12: =E12/E13-1 -> 0.002238806 | G12: 3708.8 | H12: =(G12/G13)-1 -> -0.0081990448 | I12: 3.423 | J12: =I12/100 -> 0.03423 | K12: =H12-J12 -> -0.042429045 | L12: =F12-J12 -> -0.031991194
A13: 40207 | B13: 53.6 | D13: =(D14*C13)/B13+D14 -> 1.4283636 | E13: =B13*D13 -> 76.560291 | F13: =E13/E14-1 -> -0.026516527 | G13: 3739.46 | H13: =(G13/G14)-1 -> -0.050013591 | I13: 3.468 | J13: =I13/100 -> 0.03468 | K13: =H13-J13 -> -0.084693591 | L13: =F13-J13 -> -0.061196527
A14: 40178 | B14: 55.06 | D14: =(D15*C14)/B14+D15 -> 1.4283636 | E14: =B14*D14 -> 78.645702 | F14: =E14/E15-1 -> 0.094197138 | G14: 3936.33 | H14: =(G14/G15)-1 -> 0.069611293 | I14: 3.613 | J14: =I14/100 -> 0.03613 | K14: =H14-J14 -> 0.033481293 | L14: =F14-J14 -> 0.058067138
A15: 40147 | B15: 50.32 | D15: =(D16*C15)/B15+D16 -> 1.4283636 | E15: =B15*D15 -> 71.875258 | F15: =E15/E16-1 -> 0.011558951 | G15: 3680.15 | H15: =(G15/G16)-1 -> 0.020084874 | I15: 3.421 | J15: =I15/100 -> 0.03421 | K15: =H15-J15 -> -0.014125126 | L15: =F15-J15 -> -0.022651049
A16: 40116 | B16: 49.745 | D16: =(D17*C16)/B16+D17 -> 1.4283636 | E16: =B16*D16 -> 71.053949 | F16: =E16/E17-1 -> -0.0080757727 | G16: 3607.69 | H16: =(G16/G17)-1 -> -0.049459742 | I16: 3.523 | J16: =I16/100 -> 0.03523 | K16: =H16-J16 -> -0.084689742 | L16: =F16-J16 -> -0.043305773
A17: 40086 | B17: 50.15 | D17: =(D18*C17)/B17+D18 -> 1.4283636 | E17: =B17*D17 -> 71.632437 | F17: =E17/E18-1 -> 0.059805579 | G17: 3795.41 | H17: =(G17/G18)-1 -> 0.038830833 | I17: 3.542 | J17: =I17/100 -> 0.03542 | K17: =H17-J17 -> 0.0034108326 | L17: =F17-J17 -> 0.024385579
A18: 40056 | B18: 47.32 | D18: =(D19*C18)/B18+D19 -> 1.4283636 | E18: =B18*D18 -> 67.590168 | F18: =E18/E19-1 -> 0.029590949 | G18: 3653.54 | H18: =(G18/G19)-1 -> 0.066331608 | I18: 3.534 | J18: =I18/100 -> 0.03534 | K18: =H18-J18 -> 0.030991608 | L18: =F18-J18 -> -0.0057490513
A19: 40025 | B19: 45.96 | D19: =(D20*C19)/B19+D20 -> 1.4283636 | E19: =B19*D19 -> 65.647593 | F19: =E19/E20-1 -> 0.097683305 | G19: 3426.27 | H19: =(G19/G20)-1 -> 0.091015909 | I19: 3.57 | J19: =I19/100 -> 0.0357 | K19: =H19-J19 -> 0.055315909 | L19: =F19-J19 -> 0.061983305
A20: 39994 | B20: 41.87 | D20: =(D21*C20)/B20+D21 -> 1.4283636 | E20: =B20*D20 -> 59.805586 | F20: =E20/E21-1 -> -0.068520578 | G20: 3140.44 | H20: =(G20/G21)-1 -> -0.04186231 | I20: 3.732 | J20: =I20/100 -> 0.03732 | K20: =H20-J20 -> -0.07918231 | L20: =F20-J20 -> -0.10584058
A21: 39962 | B21: 44.95 | D21: =(D22*C21)/B21+D22 -> 1.4283636 | E21: =B21*D21 -> 64.204946 | F21: =E21/E22-1 -> 0.026959104 | G21: 3277.65 | H21: =(G21/G22)-1 -> 0.037280251 | I21: 3.955 | J21: =I21/100 -> 0.03955 | K21: =H21-J21 -> -0.0022697494 | L21: =F21-J21 -> -0.012590896
A22: 39933 | B22: 43.77 | C22: 2.2 | D22: =(D23*C22)/B22+D23 -> 1.4283636 | E22: =B22*D22 -> 62.519477 | F22: =E22/E23-1 -> 0.084709769 | G22: 3159.85 | H22: =(G22/G23)-1 -> 0.12556726 | I22: 3.583 | J22: =I22/100 -> 0.03583 | K22: =H22-J22 -> 0.089737263 | L22: =F22-J22 -> 0.048879769
A23: 39903 | B23: 42.38 | D23: =(D24*C23)/B23+D24 -> 1.360006 | E23: =B23*D23 -> 57.637055 | F23: =E23/E24-1 -> 0.035805939 | G23: 2807.34 | H23: =(G23/G24)-1 -> 0.038801397 | I23: 3.633 | J23: =I23/100 -> 0.03633 | K23: =H23-J23 -> 0.0024713972 | L23: =F23-J23 -> -0.00052406086
A24: 39871 | B24: 40.915 | D24: =(D25*C24)/B24+D25 -> 1.360006 | E24: =B24*D24 -> 55.644646 | F24: =E24/E25-1 -> -0.071906544 | G24: 2702.48 | H24: =(G24/G25)-1 -> -0.091273471 | I24: 3.657 | J24: =I24/100 -> 0.03657 | K24: =H24-J24 -> -0.12784347 | L24: =F24-J24 -> -0.10847654
A25: 39843 | B25: 44.085 | D25: =(D26*C25)/B25+D26 -> 1.360006 | E25: =B25*D25 -> 59.955865 | F25: =E25/E26-1 -> -0.028964758 | G25: 2973.92 | H25: =(G25/G26)-1 -> -0.075839737 | I25: 3.819 | J25: =I25/100 -> 0.03819 | K25: =H25-J25 -> -0.11402974 | L25: =F25-J25 -> -0.067154758
A26: 39813 | B26: 45.4 | D26: =(D27*C26)/B26+D27 -> 1.360006 | E26: =B26*D26 -> 61.744273 | F26: =E26/E27-1 -> 0.044879171 | G26: 3217.97 | H26: =(G26/G27)-1 -> -0.013703459 | I26: 3.414 | J26: =I26/100 -> 0.03414 | K26: =H26-J26 -> -0.047843459 | L26: =F26-J26 -> 0.010739171
A27: 39780 | B27: 43.45 | D27: =(D28*C27)/B27+D28 -> 1.360006 | E27: =B27*D27 -> 59.092261 | F27: =E27/E28-1 -> -0.12097916 | G27: 3262.68 | H27: =(G27/G28)-1 -> -0.064349153 | I27: 3.685 | J27: =I27/100 -> 0.03685 | K27: =H27-J27 -> -0.10119915 | L27: =F27-J27 -> -0.15782916
A28: 39752 | B28: 49.43 | D28: =(D29*C28)/B28+D29 -> 1.360006 | E28: =B28*D28 -> 67.225097 | F28: =E28/E29-1 -> 0.061868958 | G28: 3487.07 | H28: =(G28/G29)-1 -> -0.13517274 | I28: 4.304 | J28: =I28/100 -> 0.04304 | K28: =H28-J28 -> -0.17821274 | L28: =F28-J28 -> 0.018828958
A29: 39721 | B29: 46.55 | D29: =(D30*C29)/B29+D30 -> 1.360006 | E29: =B29*D29 -> 63.30828 | F29: =E29/E30-1 -> -0.042378111 | G29: 4032.1 | H29: =(G29/G30)-1 -> -0.10049971 | I29: 4.339 | J29: =I29/100 -> 0.04339 | K29: =H29-J29 -> -0.14388971 | L29: =F29-J29 -> -0.085768111
A30: 39689 | B30: 48.61 | D30: =(D31*C30)/B30+D31 -> 1.360006 | E30: =B30*D30 -> 66.109892 | F30: =E30/E31-1 -> 0.078544486 | G30: 4482.6 | H30: =(G30/G31)-1 -> 0.020544764 | I30: 4.375 | J30: =I30/100 -> 0.04375 | K30: =H30-J30 -> -0.023205236 | L30: =F30-J30 -> 0.034794486
A31: 39660 | B31: 45.07 | D31: =(D32*C31)/B31+D32 -> 1.360006 | E31: =B31*D31 -> 61.295471 | F31: =E31/E32-1 -> 0.062220127 | G31: 4392.36 | H31: =(G31/G32)-1 -> -0.0095809328 | I31: 4.532 | J31: =I31/100 -> 0.04532 | K31: =H31-J31 -> -0.054900933 | L31: =F31-J31 -> 0.016900127
A32: 39629 | B32: 42.43 | D32: =(D33*C32)/B32+D33 -> 1.360006 | E32: =B32*D32 -> 57.705055 | F32: =E32/E33-1 -> -0.11438113 | G32: 4434.85 | H32: =(G32/G33)-1 -> -0.11555597 | I32: 4.825 | J32: =I32/100 -> 0.04825 | K32: =H32-J32 -> -0.16380597 | L32: =F32-J32 -> -0.16263113
A33: 39598 | B33: 47.91 | C33: 2.07 | D33: =(D34*C33)/B33+D34 -> 1.360006 | E33: =B33*D33 -> 65.157888 | F33: =E33/E34-1 -> -0.0033898305 | G33: 5014.28 | H33: =(G33/G34)-1 -> 0.0035504569 | I33: 4.606 | J33: =I33/100 -> 0.04606 | K33: =H33-J33 -> -0.042509543 | L33: =F33-J33 -> -0.049449831
A34: 39568 | B34: 50.15 | D34: =(D35*C34)/B34+D35 -> 1.3036792 | E34: =B34*D34 -> 65.379514 | F34: =E34/E35-1 -> 0.055345118 | G34: 4996.54 | H34: =(G34/G35)-1 -> 0.061496855 | I34: 4.326 | J34: =I34/100 -> 0.04326 | K34: =H34-J34 -> 0.018236855 | L34: =F34-J34 -> 0.012085118
A35: 39538 | B35: 47.52 | D35: =(D36*C35)/B35+D36 -> 1.3036792 | E35: =B35*D35 -> 61.950837 | F35: =E35/E36-1 -> -0.026029924 | G35: 4707.07 | H35: =(G35/G36)-1 -> -0.017448535 | I35: 4.114 | J35: =I35/100 -> 0.04114 | K35: =H35-J35 -> -0.058588535 | L35: =F35-J35 -> -0.067169924
A36: 39507 | B36: 48.79 | D36: =(D37*C36)/B36+D37 -> 1.3036792 | E36: =B36*D36 -> 63.60651 | F36: =E36/E37-1 -> -0.10229991 | G36: 4790.66 | H36: =(G36/G37)-1 -> -0.016249161 | I36: 4.111 | J36: =I36/100 -> 0.04111 | K36: =H36-J36 -> -0.057359161 | L36: =F36-J36 -> -0.14340991
A37: 39478 | B37: 54.35 | D37: =(D38*C37)/B37+D38 -> 1.3036792 | E37: =B37*D37 -> 70.854967 | F37: =E37/E38-1 -> -0.13702763 | G37: 4869.79 | H37: =(G37/G38)-1 -> -0.1325756 | I37: 4.139 | J37: =I37/100 -> 0.04139 | K37: =H37-J37 -> -0.1739656 | L37: =F37-J37 -> -0.17841763
A38: 39447 | B38: 62.98 | D38: =(D39*C38)/B38+D39 -> 1.3036792 | E38: =B38*D38 -> 82.105718 | F38: =E38/E39-1 -> -0.031225965 | G38: 5614.08 | H38: =(G38/G39)-1 -> -0.0099619615 | I38: 4.423 | J38: =I38/100 -> 0.04423 | K38: =H38-J38 -> -0.054191961 | L38: =F38-J38 -> -0.075455965
A39: 39416 | B39: 65.01 | D39: =(D40*C39)/B39+D40 -> 1.3036792 | E39: =B39*D39 -> 84.752187 | F39: =E39/E40-1 -> 0.073835481 | G39: 5670.57 | H39: =(G39/G40)-1 -> -0.030331997 | I39: 4.192 | J39: =I39/100 -> 0.04192 | K39: =H39-J39 -> -0.072251997 | L39: =F39-J39 -> 0.031915481
A40: 39386 | B40: 60.54 | D40: =(D41*C40)/B40+D41 -> 1.3036792 | E40: =B40*D40 -> 78.924741 | F40: =E40/E41-1 -> 0.019535197 | G40: 5847.95 | H40: =(G40/G41)-1 -> 0.023139813 | I40: 4.297 | J40: =I40/100 -> 0.04297 | K40: =H40-J40 -> -0.019830187 | L40: =F40-J40 -> -0.023434803
A41: 39353 | B41: 59.38 | D41: =(D42*C41)/B41+D42 -> 1.3036792 | E41: =B41*D41 -> 77.412473 | F41: =E41/E42-1 -> -0.009012016 | G41: 5715.69 | H41: =(G41/G42)-1 -> 0.0093577269 | I41: 4.479 | J41: =I41/100 -> 0.04479 | K41: =H41-J41 -> -0.035432273 | L41: =F41-J41 -> -0.053802016
A42: 39325 | B42: 59.92 | D42: =(D43*C42)/B42+D43 -> 1.3036792 | E42: =B42*D42 -> 78.11646 | F42: =E42/E43-1 -> -0.025691057 | G42: 5662.7 | H42: =(G42/G43)-1 -> -0.015367548 | I42: 4.298 | J42: =I42/100 -> 0.04298 | K42: =H42-J42 -> -0.058347548 | L42: =F42-J42 -> -0.068671057
A43: 39294 | B43: 61.5 | D43: =(D44*C43)/B43+D44 -> 1.3036792 | E43: =B43*D43 -> 80.176273 | F43: =E43/E44-1 -> 0.023294509 | G43: 5751.08 | H43: =(G43/G44)-1 -> -0.050182248 | I43: 4.429 | J43: =I43/100 -> 0.04429 | K43: =H43-J43 -> -0.094472248 | L43: =F43-J43 -> -0.020995491
A44: 39262 | B44: 60.1 | C44: 1.75 | D44: =(D45*C44)/B44+D45 -> 1.3036792 | E44: =B44*D44 -> 78.351122 | F44: =E44/E45-1 -> -0.13689646 | G44: 6054.93 | H44: =(G44/G45)-1 -> -0.0080389908 | I44: 4.62 | J44: =I44/100 -> 0.0462 | K44: =H44-J44 -> -0.054238991 | L44: =F44-J44 -> -0.18309646
A45: 39233 | B45: 71.66 | D45: =(D46*C45)/B45+D46 -> 1.2667926 | E45: =B45*D45 -> 90.778358 | F45: =E45/E46-1 -> 0.06194428 | G45: 6104 | H45: =(G45/G46)-1 -> 0.0241542 | I45: 4.439 | J45: =I45/100 -> 0.04439 | K45: =H45-J45 -> -0.0202358 | L45: =F45-J45 -> 0.01755428
A46: 39202 | B46: 67.48 | D46: =(D47*C46)/B46+D47 -> 1.2667926 | E46: =B46*D46 -> 85.483164 | F46: =E46/E47-1 -> 0.03655914 | G46: 5960.04 | H46: =(G46/G47)-1 -> 0.057840033 | I46: 4.267 | J46: =I46/100 -> 0.04267 | K46: =H46-J46 -> 0.015170033 | L46: =F46-J46 -> -0.0061108602
A47: 39171 | B47: 65.1 | D47: =(D48*C47)/B47+D48 -> 1.2667926 | E47: =B47*D47 -> 82.468198 | F47: =E47/E48-1 -> 0.013071895 | G47: 5634.16 | H47: =(G47/G48)-1 -> 0.021362067 | I47: 4.112 | J47: =I47/100 -> 0.04112 | K47: =H47-J47 -> -0.019757933 | L47: =F47-J47 -> -0.028048105
A48: 39141 | B48: 64.26 | D48: =(D49*C48)/B48+D49 -> 1.2667926 | E48: =B48*D48 -> 81.404092 | F48: =E48/E49-1 -> -0.047294292 | G48: 5516.32 | H48: =(G48/G49)-1 -> -0.016402446 | I48: 3.978 | J48: =I48/100 -> 0.03978 | K48: =H48-J48 -> -0.056182446 | L48: =F48-J48 -> -0.087074292
A49: 39113 | B49: 67.45 | D49: =(D50*C49)/B49+D50 -> 1.2667926 | E49: =B49*D49 -> 85.445161 | F49: =E49/E50-1 -> -0.035739814 | G49: 5608.31 | H49: =(G49/G50)-1 -> 0.01200882 | I49: 4.148 | J49: =I49/100 -> 0.04148 | K49: =H49-J49 -> -0.02947118 | L49: =F49-J49 -> -0.077219814
A50: 39080 | B50: 69.95 | D50: =(D51*C50)/B50+D51 -> 1.2667926 | E50: =B50*D50 -> 88.612142 | F50: =E50/E51-1 -> 0.05505279 | G50: 5541.76 | H50: =(G50/G51)-1 -> 0.040190403 | I50: 3.977 | J50: =I50/100 -> 0.03977 | K50: =H50-J50 -> 0.00042040326 | L50: =F50-J50 -> 0.01528279
A51: 39051 | B51: 66.3 | D51: =(D52*C51)/B51+D52 -> 1.2667926 | E51: =B51*D51 -> 83.988349 | F51: =E51/E52-1 -> -0.0045045045 | G51: 5327.64 | H51: =(G51/G52)-1 -> -0.0039429921 | I51: 3.736 | J51: =I51/100 -> 0.03736 | K51: =H51-J51 -> -0.041302992 | L51: =F51-J51 -> -0.041864505
A52: 39021 | B52: 66.6 | D52: =(D53*C52)/B52+D53 -> 1.2667926 | E52: =B52*D52 -> 84.368387 | F52: =E52/E53-1 -> -0.051282051 | G52: 5348.73 | H52: =(G52/G53)-1 -> 0.018803774 | I52: 3.797 | J52: =I52/100 -> 0.03797 | K52: =H52-J52 -> -0.019166226 | L52: =F52-J52 -> -0.089252051
A53: 38989 | B53: 70.2 | D53: =(D54*C53)/B53+D54 -> 1.2667926 | E53: =B53*D53 -> 88.92884 | F53: =E53/E54-1 -> 0.0021413276 | G53: 5250.01 | H53: =(G53/G54)-1 -> 0.016450986 | I53: 3.685 | J53: =I53/100 -> 0.03685 | K53: =H53-J53 -> -0.020399014 | L53: =F53-J53 -> -0.034708672
A54: 38960 | B54: 70.05 | D54: =(D55*C54)/B54+D55 -> 1.2667926 | E54: =B54*D54 -> 88.738821 | F54: =E54/E55-1 -> -0.059100067 | G54: 5165.04 | H54: =(G54/G55)-1 -> 0.031065473 | I54: 3.757 | J54: =I54/100 -> 0.03757 | K54: =H54-J54 -> -0.0065045274 | L54: =F54-J54 -> -0.096670067
A55: 38929 | B55: 74.45 | D55: =(D56*C55)/B55+D56 -> 1.2667926 | E55: =B55*D55 -> 94.312709 | F55: =E55/E56-1 -> -0.024246396 | G55: 5009.42 | H55: =(G55/G56)-1 -> 0.0087515808 | I55: 3.932 | J55: =I55/100 -> 0.03932 | K55: =H55-J55 -> -0.030568419 | L55: =F55-J55 -> -0.063566396
A56: 38898 | B56: 76.3 | C56: 1.52 | D56: =(D57*C56)/B56+D57 -> 1.2667926 | E56: =B56*D56 -> 96.656275 | F56: =E56/E57-1 -> 0.058055744 | G56: 4965.96 | H56: =(G56/G57)-1 -> 0.0072573415 | I56: 4.058 | J56: =I56/100 -> 0.04058 | K56: =H56-J56 -> -0.033322658 | L56: =F56-J56 -> 0.017475744
A57: 38868 | B57: 73.55 | D57: =(D58*C57)/B57+D58 -> 1.2420493 | E57: =B57*D57 -> 91.352725 | F57: =E57/E58-1 -> -0.016053512 | G57: 4930.18 | H57: =(G57/G58)-1 -> -0.049768715 | I57: 3.946 | J57: =I57/100 -> 0.03946 | K57: =H57-J57 -> -0.089228715 | L57: =F57-J57 -> -0.055513512
A58: 38835 | B58: 74.75 | D58: =(D59*C58)/B58+D59 -> 1.2420493 | E58: =B58*D58 -> 92.843184 | F58: =E58/E59-1 -> -0.047770701 | G58: 5188.4 | H58: =(G58/G59)-1 -> -0.006215463 | I58: 4.007 | J58: =I58/100 -> 0.04007 | K58: =H58-J58 -> -0.046285463 | L58: =F58-J58 -> -0.087840701
A59: 38807 | B59: 78.5 | D59: =(D60*C59)/B59+D60 -> 1.2420493 | E59: =B59*D59 -> 97.500869 | F59: =E59/E60-1 -> 0.099439776 | G59: 5220.85 | H59: =(G59/G60)-1 -> 0.044076033 | I59: 3.821 | J59: =I59/100 -> 0.03821 | K59: =H59-J59 -> 0.0058660332 | L59: =F59-J59 -> 0.061229776
A60: 38776 | B60: 71.4 | D60: =(D61*C60)/B60+D61 -> 1.2420493 | E60: =B60*D60 -> 88.682319 | F60: =E60/E61-1 -> -0.053677932 | G60: 5000.45 | H60: =(G60/G61)-1 -> 0.010602285 | I60: 3.556 | J60: =I60/100 -> 0.03556 | K60: =H60-J60 -> -0.024957715 | L60: =F60-J60 -> -0.089237932
A61: 38748 | B61: 75.45 | D61: =(D62*C61)/B61+D62 -> 1.2420493 | E61: =B61*D61 -> 93.712618 | F61: =E61/E62-1 -> 0.019594595 | G61: 4947.99 | H61: =(G61/G62)-1 -> 0.049363446 | I61: 3.481 | J61: =I61/100 -> 0.03481 | K61: =H61-J61 -> 0.014553446 | L61: =F61-J61 -> -0.015215405
A62: 38716 | B62: 74 | D62: =(D63*C62)/B62+D63 -> 1.2420493 | E62: =B62*D62 -> 91.911647 | F62: =E62/E63-1 -> 0.078717201 | G62: 4715.23 | H62: =(G62/G63)-1 -> 0.032364075 | I62: 3.322 | J62: =I62/100 -> 0.03322 | K62: =H62-J62 -> -0.00085592496 | L62: =F62-J62 -> 0.045497201
A63: 38686 | B63: 68.6 | D63: =(D64*C63)/B63+D64 -> 1.2420493 | E63: =B63*D63 -> 85.204581 | F63: =E63/E64-1 -> 0.026946108 | G63: 4567.41 | H63: =(G63/G64)-1 -> 0.029519097 | I63: 3.476 | J63: =I63/100 -> 0.03476 | K63: =H63-J63 -> -0.0052409025 | L63: =F63-J63 -> -0.0078138922
A64: 38656 | B64: 66.8 | D64: =(D65*C64)/B64+D65 -> 1.2420493 | E64: =B64*D64 -> 82.968892 | F64: =E64/E65-1 -> -0.028363636 | G64: 4436.45 | H64: =(G64/G65)-1 -> -0.035558541 | I64: 3.441 | J64: =I64/100 -> 0.03441 | K64: =H64-J64 -> -0.069968541 | L64: =F64-J64 -> -0.062773636
A65: 38625 | B65: 68.75 | D65: =(D66*C65)/B65+D66 -> 1.2420493 | E65: =B65*D65 -> 85.390888 | F65: =E65/E66-1 -> -0.0065028902 | G65: 4600.02 | H65: =(G65/G66)-1 -> 0.04561118 | I65: 3.192 | J65: =I65/100 -> 0.03192 | K65: =H65-J65 -> 0.01369118 | L65: =F65-J65 -> -0.03842289
A66: 38595 | B66: 69.2 | D66: =(D67*C66)/B66+D67 -> 1.2420493 | E66: =B66*D66 -> 85.94981 | F66: =E66/E67-1 -> -0.030133146 | G66: 4399.36 | H66: =(G66/G67)-1 -> -0.011766186 | I66: 3.203 | J66: =I66/100 -> 0.03203 | K66: =H66-J66 -> -0.043796186 | L66: =F66-J66 -> -0.062163146
A67: 38562 | B67: 71.35 | D67: =(D68*C67)/B67+D68 -> 1.2420493 | E67: =B67*D67 -> 88.620216 | F67: =E67/E68-1 -> 0.050810015 | G67: 4451.74 | H67: =(G67/G68)-1 -> 0.052582548 | I67: 3.284 | J67: =I67/100 -> 0.03284 | K67: =H67-J67 -> 0.019742548 | L67: =F67-J67 -> 0.017970015
A68: 38533 | B68: 67.9 | C68: 1.2 | D68: =(D69*C68)/B68+D69 -> 1.2420493 | E68: =B68*D68 -> 84.335146 | F68: =E68/E69-1 -> -0.057298772 | G68: 4229.35 | H68: =(G68/G69)-1 -> 0.026359407 | I68: 3.184 | J68: =I68/100 -> 0.03184 | K68: =H68-J68 -> -0.0054805928 | L68: =F68-J68 -> -0.089138772
A69: 38503 | B69: 73.3 | D69: =(D70*C69)/B69+D70 -> 1.2204797 | E69: =B69*D69 -> 89.461161 | F69: =E69/E70-1 -> 0.071637427 | G69: 4120.73 | H69: =(G69/G70)-1 -> 0.053434431 | I69: 3.351 | J69: =I69/100 -> 0.03351 | K69: =H69-J69 -> 0.019924431 | L69: =F69-J69 -> 0.038127427
A70: 38471 | B70: 68.4 | D70: =(D71*C70)/B70+D71 -> 1.2204797 | E70: =B70*D70 -> 83.480811 | F70: =E70/E71-1 -> 0.051498847 | G70: 3911.71 | H70: =(G70/G71)-1 -> -0.038367365 | I70: 3.446 | J70: =I70/100 -> 0.03446 | K70: =H70-J70 -> -0.072827365 | L70: =F70-J70 -> 0.017038847
A71: 38442 | B71: 65.05 | D71: =(D72*C71)/B71+D72 -> 1.2204797 | E71: =B71*D71 -> 79.392204 | F71: =E71/E72-1 -> 0.076986755 | G71: 4067.78 | H71: =(G71/G72)-1 -> 0.010086513 | I71: 3.705 | J71: =I71/100 -> 0.03705 | K71: =H71-J71 -> -0.026963487 | L71: =F71-J71 -> 0.039936755
A72: 38411 | B72: 60.4 | D72: =(D73*C72)/B72+D73 -> 1.2204797 | E72: =B72*D72 -> 73.716973 | F72: =E72/E73-1 -> 0.055021834 | G72: 4027.16 | H72: =(G72/G73)-1 -> 0.028993099 | I72: 3.736 | J72: =I72/100 -> 0.03736 | K72: =H72-J72 -> -0.0083669014 | L72: =F72-J72 -> 0.017661834
A73: 38383 | B73: 57.25 | D73: =(D74*C73)/B73+D74 -> 1.2204797 | E73: =B73*D73 -> 69.872462 | F73: =E73/E74-1 -> -0.026360544 | G73: 3913.69 | H73: =(G73/G74)-1 -> 0.02421516 | I73: 3.532 | J73: =I73/100 -> 0.03532 | K73: =H73-J73 -> -0.01110484 | L73: =F73-J73 -> -0.061680544
A74: 38352 | B74: 58.8 | D74: =(D75*C74)/B74+D75 -> 1.2204797 | E74: =B74*D74 -> 71.764206 | F74: =E74/E75-1 -> 0.037952339 | G74: 3821.16 | H74: =(G74/G75)-1 -> 0.017958042 | I74: 3.69 | J74: =I74/100 -> 0.0369 | K74: =H74-J74 -> -0.018941958 | L74: =F74-J74 -> 0.0010523389
A75: 38321 | B75: 56.65 | D75: =(D76*C75)/B75+D76 -> 1.2204797 | E75: =B75*D75 -> 69.140174 | F75: =E75/E76-1 -> -0.011343805 | G75: 3753.75 | H75: =(G75/G76)-1 -> 0.012660447 | I75: 3.817 | J75: =I75/100 -> 0.03817 | K75: =H75-J75 -> -0.025509553 | L75: =F75-J75 -> -0.049513805
A76: 38289 | B76: 57.3 | D76: =(D77*C76)/B76+D77 -> 1.2204797 | E76: =B76*D76 -> 69.933486 | F76: =E76/E77-1 -> -0.018835616 | G76: 3706.82 | H76: =(G76/G77)-1 -> 0.018186513 | I76: 3.926 | J76: =I76/100 -> 0.03926 | K76: =H76-J76 -> -0.021073487 | L76: =F76-J76 -> -0.058095616
A77: 38260 | B77: 58.4 | D77: =(D78*C77)/B77+D78 -> 1.2204797 | E77: =B77*D77 -> 71.276014 | F77: =E77/E78-1 -> 0 | G77: 3640.61 | H77: =(G77/G78)-1 -> 0.012889925 | I77: 4.052 | J77: =I77/100 -> 0.04052 | K77: =H77-J77 -> -0.027630075 | L77: =F77-J77 -> -0.04052
A78: 38230 | B78: 58.4 | D78: =(D79*C78)/B78+D79 -> 1.2204797 | E78: =B78*D78 -> 71.276014 | F78: =E78/E79-1 -> 0.059891107 | G78: 3594.28 | H78: =(G78/G79)-1 -> -0.01448274 | I78: 4.088 | J78: =I78/100 -> 0.04088 | K78: =H78-J78 -> -0.05536274 | L78: =F78-J78 -> 0.019011107
A79: 38198 | B79: 55.1 | D79: =(D80*C79)/B79+D80 -> 1.2204797 | E79: =B79*D79 -> 67.248431 | F79: =E79/E80-1 -> 0.057581574 | G79: 3647.1 | H79: =(G79/G80)-1 -> -0.023008366 | I79: 4.29 | J79: =I79/100 -> 0.0429 | K79: =H79-J79 -> -0.065908366 | L79: =F79-J79 -> 0.014681574
A80: 38168 | B80: 52.1 | D80: =(D81*C80)/B80+D81 -> 1.2204797 | E80: =B80*D80 -> 63.586992 | F80: =E80/E81-1 -> -0.037857802 | G80: 3732.99 | H80: =(G80/G81)-1 -> 0.017266046 | I80: 4.378 | J80: =I80/100 -> 0.04378 | K80: =H80-J80 -> -0.026513954 | L80: =F80-J80 -> -0.081637802
A81: 38138 | B81: 54.15 | C81: 1.02 | D81: =(D82*C81)/B81+D82 -> 1.2204797 | E81: =B81*D81 -> 66.088975 | F81: =E81/E82-1 -> 0.040943396 | G81: 3669.63 | H81: =(G81/G82)-1 -> -0.0012655541 | I81: 4.346 | J81: =I81/100 -> 0.04346 | K81: =H81-J81 -> -0.044725554 | L81: =F81-J81 -> -0.0025166038
A82: 38107 | B82: 53 | D82: =(D83*C82)/B82+D83 -> 1.1979151 | E82: =B82*D82 -> 63.489499 | F82: =E82/E83-1 -> -0.0028222013 | G82: 3674.28 | H82: =(G82/G83)-1 -> 0.013530176 | I82: 4.283 | J82: =I82/100 -> 0.04283 | K82: =H82-J82 -> -0.029299824 | L82: =F82-J82 -> -0.045652201
A83: 38077 | B83: 53.15 | D83: =(D84*C83)/B83+D84 -> 1.1979151 | E83: =B83*D83 -> 63.669187 | F83: =E83/E84-1 -> -0.033636364 | G83: 3625.23 | H83: =(G83/G84)-1 -> -0.026898836 | I83: 4.015 | J83: =I83/100 -> 0.04015 | K83: =H83-J83 -> -0.067048836 | L83: =F83-J83 -> -0.073786364
A84: 38044 | B84: 55 | D84: =(D85*C84)/B84+D85 -> 1.1979151 | E84: =B84*D84 -> 65.885329 | F84: =E84/E85-1 -> -0.038461538 | G84: 3725.44 | H84: =(G84/G85)-1 -> 0.023911347 | I84: 4.1 | J84: =I84/100 -> 0.041 | K84: =H84-J84 -> -0.017088653 | L84: =F84-J84 -> -0.079461538
A85: 38016 | B85: 57.2 | D85: =(D86*C85)/B85+D86 -> 1.1979151 | E85: =B85*D85 -> 68.520743 | F85: =E85/E86-1 -> -0.041876047 | G85: 3638.44 | H85: =(G85/G86)-1 -> 0.022636949 | I85: 4.256 | J85: =I85/100 -> 0.04256 | K85: =H85-J85 -> -0.019923051 | L85: =F85-J85 -> -0.084436047
A86: 37986 | B86: 59.7 | D86: =(D87*C86)/B86+D87 -> 1.1979151 | E86: =B86*D86 -> 71.51553 | F86: =E86/E87-1 -> 0.056637168 | G86: 3557.9 | H86: =(G86/G87)-1 -> 0.038866617 | I86: 4.3 | J86: =I86/100 -> 0.043 | K86: =H86-J86 -> -0.0041333834 | L86: =F86-J86 -> 0.013637168
A87: 37953 | B87: 56.5 | D87: =(D88*C87)/B87+D88 -> 1.1979151 | E87: =B87*D87 -> 67.682202 | F87: =E87/E88-1 -> 0.061032864 | G87: 3424.79 | H87: =(G87/G88)-1 -> 0.015294083 | I87: 4.473 | J87: =I87/100 -> 0.04473 | K87: =H87-J87 -> -0.029435917 | L87: =F87-J87 -> 0.016302864
A88: 37925 | B88: 53.25 | D88: =(D89*C88)/B88+D89 -> 1.1979151 | E88: =B88*D88 -> 63.788978 | F88: =E88/E89-1 -> 0.020114943 | G88: 3373.2 | H88: =(G88/G89)-1 -> 0.075984293 | I88: 4.334 | J88: =I88/100 -> 0.04334 | K88: =H88-J88 -> 0.032644293 | L88: =F88-J88 -> -0.023225057
A89: 37894 | B89: 52.2 | D89: =(D90*C89)/B89+D90 -> 1.1979151 | E89: =B89*D89 -> 62.531167 | F89: =E89/E90-1 -> 0.01953125 | G89: 3134.99 | H89: =(G89/G90)-1 -> -0.053279258 | I89: 4.066 | J89: =I89/100 -> 0.04066 | K89: =H89-J89 -> -0.093939258 | L89: =F89-J89 -> -0.02112875
A90: 37862 | B90: 51.2 | D90: =(D91*C90)/B90+D91 -> 1.1979151 | E90: =B90*D90 -> 61.333252 | F90: =E90/E91-1 -> 0.021956088 | G90: 3311.42 | H90: =(G90/G91)-1 -> 0.031508253 | I90: 4.17 | J90: =I90/100 -> 0.0417 | K90: =H90-J90 -> -0.010191747 | L90: =F90-J90 -> -0.019743912
A91: 37833 | B91: 50.1 | D91: =(D92*C91)/B91+D92 -> 1.1979151 | E91: =B91*D91 -> 60.015546 | F91: =E91/E92-1 -> -0.017647059 | G91: 3210.27 | H91: =(G91/G92)-1 -> 0.040909828 | I91: 4.211 | J91: =I91/100 -> 0.04211 | K91: =H91-J91 -> -0.0012001722 | L91: =F91-J91 -> -0.059757059
A92: 37802 | B92: 51 | C92: 0.84 | D92: =(D93*C92)/B92+D93 -> 1.1979151 | E92: =B92*D92 -> 61.093669 | F92: =E92/E93-1 -> -0.046182153 | G92: 3084.1 | H92: =(G92/G93)-1 -> 0.030868221 | I92: 3.844 | J92: =I92/100 -> 0.03844 | K92: =H92-J92 -> -0.0075717791 | L92: =F92-J92 -> -0.084622153
A93: 37771 | B93: 54.35 | D93: =(D94*C93)/B93+D94 -> 1.1785044 | E93: =B93*D93 -> 64.051715 | F93: =E93/E94-1 -> 0.016838167 | G93: 2991.75 | H93: =(G93/G94)-1 -> 0.012892436 | I93: 3.758 | J93: =I93/100 -> 0.03758 | K93: =H93-J93 -> -0.024687564 | L93: =F93-J93 -> -0.020741833
A94: 37741 | B94: 53.45 | D94: =(D95*C94)/B94+D95 -> 1.1785044 | E94: =B94*D94 -> 62.991061 | F94: =E94/E95-1 -> 0.15918456 | G94: 2953.67 | H94: =(G94/G95)-1 -> 0.128018 | I94: 4.128 | J94: =I94/100 -> 0.04128 | K94: =H94-J94 -> 0.086737995 | L94: =F94-J94 -> 0.11790456
A95: 37711 | B95: 46.11 | D95: =(D96*C95)/B95+D96 -> 1.1785044 | E95: =B95*D95 -> 54.340839 | F95: =E95/E96-1 -> -0.070737606 | G95: 2618.46 | H95: =(G95/G96)-1 -> -0.049239852 | I95: 4.114 | J95: =I95/100 -> 0.04114 | K95: =H95-J95 -> -0.090379852 | L95: =F95-J95 -> -0.11187761
A96: 37680 | B96: 49.62 | D96: =(D97*C96)/B96+D97 -> 1.1785044 | E96: =B96*D96 -> 58.477389 | F96: =E96/E97-1 -> 0.019938335 | G96: 2754.07 | H96: =(G96/G97)-1 -> -0.062565523 | I96: 3.955 | J96: =I96/100 -> 0.03955 | K96: =H96-J96 -> -0.10211552 | L96: =F96-J96 -> -0.019611665
A97: 37652 | B97: 48.65 | D97: =(D98*C97)/B97+D98 -> 1.1785044 | E97: =B97*D97 -> 57.33424 | F97: =E97/E98-1 -> -0.16480687 | G97: 2937.88 | H97: =(G97/G98)-1 -> -0.041133715 | I97: 4.116 | J97: =I97/100 -> 0.04116 | K97: =H97-J97 -> -0.082293715 | L97: =F97-J97 -> -0.20596687
A98: 37621 | B98: 58.25 | D98: =(D99*C98)/B98+D99 -> 1.1785044 | E98: =B98*D98 -> 68.647882 | F98: =E98/E99-1 -> -0.019360269 | G98: 3063.91 | H98: =(G98/G99)-1 -> -0.078980356 | I98: 4.251 | J98: =I98/100 -> 0.04251 | K98: =H98-J98 -> -0.12149036 | L98: =F98-J98 -> -0.061870269
A99: 37589 | B99: 59.4 | D99: =(D100*C99)/B99+D100 -> 1.1785044 | E99: =B99*D99 -> 70.003163 | F99: =E99/E100-1 -> -0.03805668 | G99: 3326.65 | H99: =(G99/G100)-1 -> 0.056065955 | I99: 4.558 | J99: =I99/100 -> 0.04558 | K99: =H99-J99 -> 0.010485955 | L99: =F99-J99 -> -0.08363668
A100: 37560 | B100: 61.75 | D100: =(D101*C100)/B100+D101 -> 1.1785044 | E100: =B100*D100 -> 72.772648 | F100: =E100/E101-1 -> 0.082383874 | G100: 3150.04 | H100: =(G100/G101)-1 -> 0.13414823 | I100: 4.567 | J100: =I100/100 -> 0.04567 | K100: =H100-J100 -> 0.088478229 | L100: =F100-J100 -> 0.036713874
...

Sheet France 10-Year Bond Yield
A1: Date | B1: Price | C1: Open | D1: High | E1: Low | F1: Change%
A2: 42842 | B2: 0.899 | C2: 0.964 | D2: 0.987 | E2: 0.865 | F2: -0.0684
A3: 42811 | B3: 0.965 | C3: 0.915 | D3: 1.148 | E3: 0.892 | F3: 0.0941
A4: 42783 | B4: 0.882 | C4: 1.064 | D4: 1.154 | E4: 0.866 | F4: -0.142
A5: 42752 | B5: 1.028 | C5: 0.695 | D5: 1.115 | E5: 0.631 | F5: 0.5051
A6: 43085 | B6: 0.683 | C6: 0.785 | D6: 0.922 | E6: 0.632 | F6: -0.072
A7: 43055 | B7: 0.736 | C7: 0.484 | D7: 0.885 | E7: 0.423 | F7: 0.5365
A8: 43024 | B8: 0.479 | C8: 0.132 | D8: 0.505 | E8: 0.119 | F8: 3.0252
A9: 42994 | B9: 0.119 | C9: 0.189 | D9: 0.317 | E9: 0.084 | F9: -0.2654
A10: 42963 | B10: 0.162 | C10: 0.104 | D10: 0.218 | E10: 0.095 | F10: 0.4464
A11: 42932 | B11: 0.112 | C11: 0.195 | D11: 0.269 | E11: 0.094 | F11: -0.4428
A12: 42902 | B12: 0.201 | C12: 0.49 | D12: 0.511 | E12: 0.198 | F12: -0.5864
A13: 42871 | B13: 0.486 | C13: 0.641 | D13: 0.643 | E13: 0.453 | F13: -0.2535
... A212: 36434 | B212: 5.291 | C212: 5.291 | D212: 5.291 | E212: 5.291 | F212: 0.0063
A213: 36404 | B213: 5.258 | C213: 5.258 | D213: 5.258 | E213: 5.258 | F213: 0.0445 | G213: 5.258
A214: 36373 | B214: 5.034 | C214: 5.034 | D214: 5.034 | E214: 5.034 | F214: 0.0178 | G214: 5.034
A215: 36342 | B215: 4.946 | C215: 4.946 | D215: 4.946 | E215: 4.946 | F215: 0.0577 | G215: 4.946
A216: 36312 | B216: 4.676 | C216: 4.676 | D216: 4.676 | E216: 4.676 | F216: 0.1047 | G216: 4.676
A217: 36281 | B217: 4.233 | C217: 4.233 | D217: 4.233 | E217: 4.233 | F217: 0.0851 | G217: 4.233
A218: 36251 | B218: 3.901 | C218: 3.901 | D218: 3.901 | E218: 3.901 | F218: -0.049
A219: 36220 | B219: 4.102 | C219: 4.102 | D219: 4.102 | E219: 4.102 | F219: 0.0064
A220: 36192 | B220: 4.076 | C220: 4.076 | D220: 4.076 | E220: 4.076 | F220: 0.0981
A221: 36161 | B221: 3.712 | C221: 3.712 | D221: 3.712 | E221: 3.712 | F221: -0.0453
A222: 36130 | B222: 3.888 | C222: 3.888 | D222: 3.888 | E222: 3.888 | F222: -0.0398
A223: 36100 | B223: 4.049 | C223: 4.049 | D223: 4.049 | E223: 4.049 | F223: -0.0511
A224: 36069 | B224: 4.267 | C224: 4.267 | D224: 4.267 | E224: 4.267 | F224: 0.0652
A225: 36039 | B225: 4.006 | C225: 4.006 | D225: 4.006 | E225: 4.006 | F225: -0.0733
A226: 36008 | B226: 4.323 | C226: 4.323 | D226: 4.323 | E226: 4.323 | F226: -0.0895
A227: 35977 | B227: 4.748 | C227: 4.748 | D227: 4.748 | E227: 4.748 | F227: -0.0192
A228: 35947 | B228: 4.841 | C228: 4.841 | D228: 4.841 | E228: 4.841 | F228: -0.0159
A229: 35916 | B229: 4.919 | C229: 4.919 | D229: 4.919 | E229: 4.919 | F229: -0.0393
... A279: 34394 | B279: 6.466 | C279: 6.466 | D279: 6.466 | E279: 6.466 | F279: 0.0458
A280: Highest: 8.281 | B280: Lowest: 0.084 | C280: Difference: 8.197 | D280: Average: 3.969 | E280: Change %: -85.460
A281: Add a Comment
A282: Comment Guidelines
A284: Post
A287: Latest France 10-Year Comments
A289: Miguel Vieira May 03, 2016 7:13PM GMT
A290: I can't see why general information is telling me here that french 10y bond yield has climbed 1,38% while graphics show a falling yield for the same day, and same maturity of french bonds... Is there any error on the information given? Or am I interpreting wrongly?
A291: Reply
A292: Disclaimer: Fusion Media would like to remind you that the data contained in this website is not necessarily real-time nor accurate. All CFDs (stocks, indexes, futures) and Forex prices are not provided by exchanges but rather by market makers, and so prices may not be accurate and may differ from the actual market price, meaning prices are indicative and not appropriate for trading purposes. Therefore Fusion Media doesn`t bear any responsibility for any trading losses you might incur as a result of using this data.
A294: Fusion Media or anyone involved with Fusion Media will not accept any liability for loss or damage as a result of reliance on the information including data, quotes, charts and buy/sell signals contained within this website. Please be fully informed regarding the risks and costs associated with trading the financial markets, it is one of the riskiest investment forms possible.
A295: Find A Broker
A296: Forex
A297: CFDs
... A310: 00:0012:0004:0008:0016:0020:002,350.002,340.002,360.00Investing.com (GMT +2)2,352.75
B311: S&P 500 Futures | C311: 2352.75 | D311: -1 | E311: -0.0004
B312: Nasdaq Futures | C312: 5420.62 | D312: -2.13 | E312: -0.0004
B313: Dow 30 | C313: 20656.1 | D313: -6.85 | E313: -0.0003
B314: S&P 500 VIX | C314: 12.87 | D314: 0.48 | E314: 0.0387
B315: DAX | C315: 12225.06 | D315: -5.83 | E315: -0.0005
B316: Nikkei 225 | C316: 18664.63 | D316: 67.57 | E316: 0.0036
B317: US Dollar Index | C317: 101.08 | D317: 0.47 | E317: 0.0047
B318: Euro Index | C318: 86.47 | D318: -0.26 | E318: -0.003
A319: Start Trading Today
A320: your capital is at risk
A321: Fed Rate Monitor Tool
A322: Meeting Time:May 03, 2017 02:00PM ET
A323: Future Price:99.095
A324: 0.75 - 1.00
A325: 94.7%
A326: 1.00 - 1.25
A327: 5.3%
A328: Forex
A329: Commodities
A330: Indices
... A334: EUR/USD
A335: 1.0591
A337: -0.0053 -0.50%
A338: Summary
A339: Strong Sell
A340: Moving Averages:
A341: Buy 0
A342: Sell 12
A343: Indicators:
A344: Buy 1
A345: Sell 7
C346: EUR/USD | D346: 1.0591 | E346: Strong Sell
C347: GBP/USD | D347: 1.2367 | E347: Neutral
C348: USD/JPY | D348: 111.1 | E348: Buy
C349: AUD/USD | D349: 0.7496 | E349: Strong Sell
C350: USD/CAD | D350: 1.3409 | E350: Neutral
C351: EUR/JPY | D351: 117.68 | E351: Strong Sell
C352: EUR/CHF | D352: 1.069 | E352: Strong Sell
A353: Start Trading Today
A354: your capital is at risk
A355: Recent Quotes
B356: Name | C356: Price | D356: Chg. | E356: Chg. %
B357: SASY | C357: 84.65 | D357: -0.56 | E357: -0.0066
B358: SNY | C358: 44.81 | D358: -0.5 | E358: -0.011
B359: SASY | C359: 84.65 | D359: -0.56 | E359: -0.0066
B360: France 10Y | C360: 0.899 | D360: 0.012 | E360: 0.0135
B361: France 3M | C361: -0.54 | D361: -0.005 | E361: 0
B362: US 3M Yield | C362: 0.82 | D362: 0.01 | E362: 0.0127
A363: Add to Watchlist
A364: Investing.com
A365: What's New
A366: Mobile
A367: Portfolio
A368: Webmaster Tools
...

Sheet LR2
A1: SUMMARY OUTPUT
A3: 回归统计
A4: Multiple R | B4: 0.55269065
A5: R Square | B5: 0.30546696
A6: Adjusted R Square | B6: 0.29349225
A7: 标准误差 | B7: 0.051259811
A8: 观测值 | B8: 60
A10: 方差分析
B11: df | C11: SS | D11: MS | E11: F | F11: Significance F
A12: 回归分析 | B12: 1 | C12: 0.067027546 | D12: 0.067027546 | E12: 25.509346 | F12: 4.6751591e-06
A13: 残差 | B13: 58 | C13: 0.15239896 | D13: 0.0026275682
A14: 总计 | B14: 59 | C14: 0.2194265
B16: Coefficients | C16: 标准误差 | D16: t Stat | E16: P-value | F16: Lower 95% | G16: Upper 95% | H16: 下限 95.0% | I16: 上限 95.0%
A17: Intercept | B17: -0.016237988 | C17: 0.0081735788 | D17: -1.9866436 | E17: 0.051693094 | F17: -0.032599183 | G17: 0.00012320795 | H17: -0.032599183 | I17: 0.00012320795
A18: Market Premium | B18: 0.60248109 | C18: 0.11928718 | D18: 5.0506777 | E18: 4.6751591e-06 | F18: 0.36370186 | G18: 0.84126032 | H18: 0.36370186 | I18: 0.84126032

Sheet cost of equity(use French bond)
A1: Date | B1: Rm-Rf | H1: Date | I1: RF | L1: Alpha
A2: 40543 | B2: 0.020327234 | C2: Average Market Risk Premium (MRP) | H2: 40543 | I2: 0.0335 | K2: Monthly: | L2: 0 | M2: Insignificant statistically
A3: 40512 | B3: -0.089827035 | C3: in the last 10 years: | K3: Yearly: | L3: =(1+L2)^12-1 -> 0
A4: 40480 | B4: 0.0027477167 | H4: Yearly risk-free return: | I4: =(1+I2)^12-1 -> 0.48499767
A5: 40451 | B5: 0.037550578 | C5: Monthly average: | D5: =AVERAGE(B2:B203) -> -0.043751491 | L5: Beta:
A6: 40421 | B6: -0.066568322 | C6: Yearly average MRP: | D6: =(1+D5)^12-1 -> -0.41541287 | L6: 0.6 | M6: Significant statistically
A7: 40389 | B7: 0.028603345
A8: 40359 | B8: -0.048987318
A9: 40329 | B9: -0.11022649
A10: 40298 | B10: -0.072511727
A11: 40268 | B11: 0.037118305
A12: 40235 | B12: -0.042429045
A13: 40207 | B13: -0.084693591
A14: 40178 | B14: 0.033481293
A15: 40147 | B15: -0.014125126
A16: 40116 | B16: -0.084689742
A17: 40086 | B17: 0.0034108326
A18: 40056 | B18: 0.030991608
... A20: 39994 | B20: -0.07918231
A21: 39962 | B21: -0.0022697494 | C21: 21 | E21: Using instead used beta from the Oct 2002 to Sep 2007 period we would get:
A22: 39933 | B22: 0.089737263
A23: 39903 | B23: 0.0024713972
A24: 39871 | B24: -0.12784347
A25: 39843 | B25: -0.11402974
A26: 39813 | B26: -0.047843459
A27: 39780 | B27: -0.10119915
A28: 39752 | B28: -0.17821274
A29: 39721 | B29: -0.14388971
A30: 39689 | B30: -0.023205236
A31: 39660 | B31: -0.054900933
A32: 39629 | B32: -0.16380597
A33: 39598 | B33: -0.042509543
... A203: 34424 | B203: -0.13441684

Sheet WACC >>>>

Sheet Cost of Equity
B1: equity beta (monthly) | C1: Index | D1: Marginal tax rate(2010) | E1: E/V | F1: unlevered Beta | G1: D/V | H1: D/E | I1: Return on Asset | J1: Asset Beta
A2: pfizer | B2: 0.708 | C2: SPX | D2: 0.4 | E2: 0.824 | F2: =B2*E2 -> 0.583392 | G2: =1-E2 -> 0.176 | H2: =G2/E2 -> 0.21359223 | I2: =$B$30+F2*$B$29 -> 0.036437537 | J2: =B2/(1+H2*(1-D2)) -> 0.62757315
A3: roche | B3: 0.681 | C3: SMI | D3: 0.1875 | E3: 0.798 | F3: =B3*E3 -> 0.543438 | G3: =1-E3 -> 0.202 | H3: =G3/E3 -> 0.25313283 | I3: =$B$30+F3*$B$29 -> 0.034024315 | J3: =B3/(1+H3*(1-D3)) -> 0.56483097
A4: Bayer | B4: 0.706 | C4: DAX | D4: 0.2941 | E4: 0.802 | F4: =B4*E4 -> 0.566212 | G4: =1-E4 -> 0.198 | H4: =G4/E4 -> 0.24688279 | I4: =$B$30+F4*$B$29 -> 0.035399865 | J4: =B4/(1+H4*(1-D4)) -> 0.60122225
A5: Merck | B5: 0.715 | C5: SPX | D5: 0.4 | E5: 0.861 | F5: =B5*E5 -> 0.615615 | G5: =1-E5 -> 0.139 | H5: =G5/E5 -> 0.16144019 | I5: =$B$30+F5*$B$29 -> 0.038383806 | J5: =B5/(1+H5*(1-D5)) -> 0.65185832
A6: gilead | B6: 0.401 | C6: SPX | D6: 0.4 | E6: 0.911 | F6: =B6*E6 -> 0.365311 | G6: =1-E6 -> 0.089 | H6: =G6/E6 -> 0.097694841 | I6: =$B$30+F6*$B$29 -> 0.023265445 | J6: =B6/(1+H6*(1-D6)) -> 0.37879614
A7: GSK | B7: 0.464 | C7: UKX | D7: 0.28 | E7: 0.81 | F7: =B7*E7 -> 0.37584 | G7: =1-E7 -> 0.19 | H7: =G7/E7 -> 0.2345679 | I7: =$B$30+F7*$B$29 -> 0.023901396 | J7: =B7/(1+H7*(1-D7)) -> 0.39695817
A8: ELI LILLY & CO | B8: 0.786 | C8: SPX | D8: 0.4 | E8: 0.854 | F8: =B8*E8 -> 0.671244 | G8: =1-E8 -> 0.146 | H8: =G8/E8 -> 0.17096019 | I8: =$B$30+F8*$B$29 -> 0.041743798 | J8: =B8/(1+H8*(1-D8)) -> 0.71287596
A9: astrazeneca | B9: 0.378 | C9: UKX | D9: 0.28 | E9: 0.874 | F9: =B9*E9 -> 0.330372 | G9: =1-E9 -> 0.126 | H9: =G9/E9 -> 0.14416476 | I9: =$B$30+F9*$B$29 -> 0.021155129 | J9: =B9/(1+H9*(1-D9)) -> 0.34245377
A10: amgen | B10: 0.468 | C10: SPX | D10: 0.4 | E10: 0.793 | F10: =B10*E10 -> 0.371124 | G10: =1-E10 -> 0.207 | H10: =G10/E10 -> 0.26103405 | I10: =$B$30+F10*$B$29 -> 0.02361655 | J10: =B10/(1+H10*(1-D10)) -> 0.40462713
A11: allergan | B11: 0.47 | C11: SPX | D11: 0.4 | E11: 0.865 | F11: =B11*E11 -> 0.40655 | G11: =1-E11 -> 0.135 | H11: =G11/E11 -> 0.15606936 | I11: =$B$30+F11*$B$29 -> 0.02575628 | J11: =B11/(1+H11*(1-D11)) -> 0.42975687
A12: Teva | B12: 0.205 | C12: SPX | D12: 0.4 | E12: 0.897 | F12: =B12*E12 -> 0.183885 | G12: =1-E12 -> 0.103 | H12: =G12/E12 -> 0.1148272 | I12: =$B$30+F12*$B$29 -> 0.012307314 | J12: =B12/(1+H12*(1-D12)) -> 0.19178661
A13: NOVO NORDISK | B13: 0.33 | C13: KFX | D13: 0.25 | E13: 0.997 | F13: =B13*E13 -> 0.32901 | G13: =1-E13 -> 0.003 | H13: =G13/E13 -> 0.0030090271 | I13: =$B$30+F13*$B$29 -> 0.021072864 | J13: =B13/(1+H13*(1-D13)) -> 0.32925694
... A24: CHUGAI | B24: 0.782 | C24: TPX | D24: 0.4069 | E24: 1 | F24: =B24*E24 -> 0.782 | G24: =1-E24 -> 0 | H24: =G24/E24 -> 0 | I24: =$B$30+F24*$B$29 -> 0.04843346 | J24: =B24/(1+H24*(1-D24)) -> 0.782
A25: Average | E25: =AVERAGE(E2:E24) -> 0.847 | F25: =AVERAGE(F2:F24) -> 0.508153 | G25: =AVERAGE(G2:G24) -> 0.153 | H25: =AVERAGE(H2:H24) -> 0.33826071 | I25: =AVERAGE(I2:I24) -> 0.031893101 | J25: =AVERAGE(J2:J24) -> 0.53261406
A28: Tax Rate | B28: 0.3333 | C28: marginal tax rate for France-2010
A29: market premium | B29: ='cost of equity(use Fama French)'!G8 -> 0.0604 | C29: Fama French Average Annual Mkt-RF from 1990-2010 (European) | H29: Pablo Fernandez market risk premium. Ivo Valic | K29: use bloomberg
A30: risk free return | B30: ='cost of equity(use Fama French)'!L4 -> 0.0012006602 | C30: Fama French Annual RF for 2010 (European)
A33: return on asset | B33: =B30+F25*B29 -> 0.031893101
A34: Asset Beta | B34: =J25 -> 0.53261406 | E34: Sanofi | F34: E/V= | G34: =G35/G37 -> 0.82129141 | H34: D/V= | I34: =G36/G37 -> 0.17870859
A35: Equity Beta | B35: =B34/G34 -> 0.64850802 | E35: (millions of EUR) | F35: E= | G35: =I35*I36 -> 62444.25 | H35: Outstanding shares | I35: 1305
F36: D= | G36: ='Cost of Debt'!F47+'Operating lease converter'!C30 -> 13587.533 | H36: Price | I36: 47.85
A37: Cost of Equity | B37: =$B$30+B29*$B$35 -> 0.040370545 | F37: V= | G37: =G35+G36 -> 76031.783
A38: Cost of Debt | B38: 0.0428
A43: WACC | B43: =B37*G34+B38*I34*(1-B28) -> 0.038255388

Sheet Cost of Debt
A1: Source: Annual Repot on Form 20-F 2010
A2: The weighted average interest rate on debt at December 31, 2010 was 3.6%
A4: ISIN | B4: Description | D4: Millions of euro | F4: Discount Rate | H4: Weight | J4: Weighted Discount Rate
A5: - | B5: June 2008 issue of ¥15 billion (€138 million), maturing June 2013, bearing interest at a floating rate indexed to 3-month JPY Libor, and swapped into euros at a floating rate indexed to 3-month Euribor | C5: € | D5: 138 | F5: =B18 -> 0.01001 | H5: =IF($A$22="NO",D5/(SUM($D$5:$D$12)),D5/(SUM($D$5:$D$12,$D$22,$D$23))) -> 0.013640407 | J5: =H5*F5 -> 0.00013654048
A6: XS0428037666 | B6: May 2009 issue [ISIN: XS0428037666] of €1.5 billion, maturing May 2013, bearing annual interest at 3.5% | D6: 1500 | F6: 0.035 | H6: =IF($A$22="NO",D6/(SUM($D$5:$D$12)),D6/(SUM($D$5:$D$12,$D$22,$D$23))) -> 0.1482653 | J6: =H6*F6 -> 0.0051892854
A7: XS0428037740 | B7: May 2009 issue [ISIN: XS0428037740] of €1.5 billion, maturing May 2016, bearing annual interest at 4.5% | D7: 1500 | F7: 0.045 | H7: =IF($A$22="NO",D7/(SUM($D$5:$D$12)),D7/(SUM($D$5:$D$12,$D$22,$D$23))) -> 0.1482653 | J7: =H7*F7 -> 0.0066719383
A8: XS0456451938 | B8: October 2009 issue [ISIN: XS0456451938] of €1.2 billion (including supplementary tranche issued in April 2010), maturing October 2014, bearing annual interest at 3.125% | D8: 1200 | F8: 0.03125 | H8: =IF($A$22="NO",D8/(SUM($D$5:$D$12)),D8/(SUM($D$5:$D$12,$D$22,$D$23))) -> 0.11861224 | J8: =H8*F8 -> 0.0037066324
A9: XS0456451771 | B9: October 2009 issue [ISIN: XS0456451771] of €800 million, maturing October 2019, bearing annual interest at 4.125% | D9: 800 | F9: 0.04125 | H9: =IF($A$22="NO",D9/(SUM($D$5:$D$12)),D9/(SUM($D$5:$D$12,$D$22,$D$23))) -> 0.079074825 | J9: =H9*F9 -> 0.0032618365
A10: CH0035703070 | B10: December 2007 and February 2008 issues [ISIN: CH0035703070] of CHF400 million (€320 million), maturing December 2015, bearing annual interest at 3.375%, and swapped into euros at a fixed rate of 4.867% | D10: 320 | F10: 0.04867 | H10: =IF($A$22="NO",D10/(SUM($D$5:$D$12)),D10/(SUM($D$5:$D$12,$D$22,$D$23))) -> 0.03162993 | J10: =H10*F10 -> 0.0015394287
A11: CH0048787532 | B11: December 2008 and January 2009 issues [ISIN: CH0048787532] amounting to CHF275 million at a fixed rate of 4.894%, maturing December 2012 | D11: 220 | F11: 0.04894 | H11: =IF($A$22="NO",D11/(SUM($D$5:$D$12)),D11/(SUM($D$5:$D$12,$D$22,$D$23))) -> 0.021745577 | J11: =H11*F11 -> 0.0010642285
A12: CH0048787532 | B12: December 2008 and January 2009 issues [ISIN: CH0048787532] amounting to CHF250 million at a floating rate indexed to 3-month Euribor | D12: 200 | F12: =B18 -> 0.01001 | H12: =IF($A$22="NO",D12/(SUM($D$5:$D$12)),D12/(SUM($D$5:$D$12,$D$22,$D$23))) -> 0.019768706 | J12: =H12*F12 -> 0.00019788475
J13: 0.037465903 | K13: Cost of debt without Provisions and other non current liabilities
A14: XS0176128675 | B14: September 2003 issue [ISIN: XS0176128675] with a nominal value of €1,500 million, maturing September 2010, bearing annual interest at 4.25% | D14: 1500 | F14: =(1+0.0425)^(257/365)-1 -> 0.029739873 | H14: =IF($A$22="NO",D14/(SUM($D$5:$D$12)),D14/(SUM($D$5:$D$12,$D$22,$D$23))) -> 0.1482653 | J14: =H14*F14 -> 0.0044093911
A15: ISIN: XS0282647634 | B15: January 2007 issue [ISIN: XS0282647634] amounting to £200 million (€225 million), maturing January 2010, bearing annual interest at 5.50% and swapped into euros at a floating rate indexed to 3-month Euribor | D15: 227 | F15: =(1+F12)^(18/365)-1 -> 0.00049131017 | H15: =IF($A$22="NO",D15/(SUM($D$5:$D$12)),D15/(SUM($D$5:$D$12,$D$22,$D$23))) -> 0.022437481 | J15: =H15*F15 -> 1.1023763e-05
A16: CH0035703021 | B16: December 2007 issue [ISIN: CH0035703021] amounting to CHF200 million (€135 million), maturing January 2010, bearing annual interest of 2.75%, and swapped into euros at a floating rate indexed to 6-month Euribor | D16: 136 | F16: =(1+B19)^(21/365)-1 -> 0.00070018922 | H16: =IF($A$22="NO",D16/(SUM($D$5:$D$12)),D16/(SUM($D$5:$D$12,$D$22,$D$23))) -> 0.01344272 | J16: =H16*F16 -> 9.4124478e-06
D17: =SUM(D5:D12) -> 5878
A18: Euribor 3M | B18: 0.01001
A19: Euribor 6M | B19: 0.01224
A20: Source: 3M Euribor rate = 03-01-2011 1,001 % http://www.euribor-rates.eu/euribor-2011.asp?i1=6&i2=1
A22: YES | B22: Provisions and other non-current liabilities | D22: =F36 -> 3854 | F22: =G36 -> 0.0497 | H22: =D22/SUM(D22,D23,D5:D12) -> 0.38094297 | J22: =F22*H22 -> 0.018932865
D23: =H36 -> 385 | F23: =I36 -> 0.0545 | H23: =D23/SUM(D23,D22,D6:D12) -> 0.03858102 | J23: =F23*H23 -> 0.0021026656
A25: YES | J25: =IF(A22="NO",SUM(J5:J12),SUM(J5:J12,J22,J23)) -> 0.042803306 | K25: Cost of Debt
A26: NO
B28: CONSOLIDATED BALANCE SHEET
B29: (€ million) | C29: Note | D29: December 31, 2010
B30: LIABILITIES & EQUITY
B31: Equity attributable to equity holders of sanofi-aventis | D31: 53097
B32: Equity attributable to non-controlling interests | D32: 191
B33: Total equity | D33: 53288
B34: Long-term debt | C34: D17 | D34: 6695 | E34: 1
B35: Non-current liabilities related to business combinations and to non-controlling interests | C35: D18 | D35: 388 | E35: 0
B36: Provisions and other non-current liabilities | C36: D19 | D36: 9326 | E36: 1 | F36: 3854 | G36: 0.0497 | H36: 385 | I36: 0.0545 | J36: Pensions and other long term benefits
B37: Deferred tax liabilities | C37: D14 | D37: 3808 | E37: 0
B38: Non-current liabilities | D38: 20217
B39: Accounts payable | D39: 2800 | E39: 0
B40: Other current liabilities | C40: D19,4 | D40: 5624 | E40: 0
B41: Current liabilities related to business combinations and to non-controlling interests | C41: D18 | D41: 98 | E41: 0
B42: Short-term debt and current portion of long-term debt | C42: D17 | D42: 1565 | E42: 1
B43: Current liabilities | D43: 10087 | J43: Equity | K43: 62444.25
B44: Liabilities related to assets held for sale or exchange | C44: D8 | D44: 1672 | J44: Debt | K44: =D34+D42+'Operating lease converter'!F64+H36+F36 -> 12499
B45: TOTAL LIABILITIES & EQUITY | D45: 85264 | J45: EV | K45: =K43+K44 -> 74943.25
B47: Total Debt | D47: =D34+D42 -> 8260 | F47: =D47+F36+H36 -> 12499
A48: * | B48: Interest Paid | D48: 392 | F48: 392
B49: Book Cost of Debt | D49: =D48/D47 -> 0.047457627 | F49: =F48/F47 -> 0.031362509
A51: * | B51: D.29. Financial income and expenses : Includes gains/losses on interest rate derivatives used to hedge debt: €7 million gain in 2010, €25 million gain in 2009, €2 million loss in 2008.

Sheet WACC
B2: Marginal tax rate | D2: 0.3333
B4: Value of Equity | D4: ='Cost of Equity'!G35 -> 62444.25
B5: Value of Debt | D5: ='Cost of Equity'!G36 -> 13587.533 | E5: =D5/D6 -> 0.17870859
D6: =D4+D5 -> 76031.783
B8: Cost of Equity | D8: ='Cost of Equity'!B37 -> 0.040370545 | E8: 0.1003 | F8: Bloomberg
B9: Cost of Debt | D9: ='Cost of Debt'!J25 -> 0.042803306
B11: After-tax WACC | D11: =D4/D6*E8+D5/D6*D9*(1-D2) -> 0.087475329 | E11: =D4/D6*D8+D5/D6*D9*(1-D2) -> 0.038255782

Sheet FINANCIALS >>>>

Sheet Assumption
S1: Acquisition
E2: Choice of the scenario | H2: Acquisition | S2: Increased prices
A4: M&A
A5: Assumptions | D5: Actual | F5: Projections
A6: €m | D6: 2006 | E6: 2007 | F6: 2008 | G6: 2009 | H6: 2010 | I6: 2011 | J6: 2012 | K6: 2013 | L6: 2014 | M6: 2015
B8: Operating assumptions 1 - Acquisition of a biotech to offset the loss of patents
D9: 2006 | E9: 2007 | F9: 2008 | G9: 2009 | H9: 2010 | I9: 2011 | J9: 2012 | K9: 2013 | L9: 2014 | M9: 2015
B10: Income statement
B11: Sales growth | D11: NA | E11: ='Income Statement'!E7/'Income Statement'!D7-1 -> -0.011313573 | F11: ='Income Statement'!F7/'Income Statement'!E7-1 -> -0.017253672 | G11: ='Income Statement'!G7/'Income Statement'!F7-1 -> 0.063044109 | H11: ='Income Statement'!H7/'Income Statement'!G7-1 -> 0.036784276 | I11: =H11-(G11-H11) -> 0.010524443 | J11: =I11+5% -> 0.060524443 | K11: 0.011 | L11: 0.061 | M11: 0.011 | O11: Follow acquistion trend: 2009 jump in sales then decrease
B12: Other revenues | D12: NA | E12: ='Income Statement'!E8/'Income Statement'!D8-1 -> 0.034946237 | F12: ='Income Statement'!F8/'Income Statement'!E8-1 -> 0.081385281 | G12: ='Income Statement'!G8/'Income Statement'!F8-1 -> 0.15532426 | H12: ='Income Statement'!H8/'Income Statement'!G8-1 -> 0.14414414 | I12: =AVERAGE($E$12:$H$12) -> 0.10394998 | J12: =AVERAGE($E$12:$H$12) -> 0.10394998 | K12: =AVERAGE($E$12:$H$12) -> 0.10394998 | L12: =AVERAGE($E$12:$H$12) -> 0.10394998 | M12: =AVERAGE($E$12:$H$12) -> 0.10394998 | O12: Should remain stable on average because of acquisition and loss a patents offsetting
B13: COGS as % of sales | D13: =-'Income Statement'!D9/'Income Statement'!D7 -> 0.26740211 | E13: =-'Income Statement'!E9/'Income Statement'!E7 -> 0.26989163 | F13: =-'Income Statement'!F9/'Income Statement'!F7 -> 0.2661419 | G13: =-'Income Statement'!G9/'Income Statement'!G7 -> 0.26888692 | H13: =-'Income Statement'!H9/'Income Statement'!H7 -> 0.28689442 | I13: =AVERAGE($D$13:$H$13) -> 0.2718434 | J13: =AVERAGE($D$13:$H$13) -> 0.2718434 | K13: =AVERAGE($D$13:$H$13) -> 0.2718434 | L13: =AVERAGE($D$13:$H$13) -> 0.2718434 | M13: =AVERAGE($D$13:$H$13) -> 0.2718434 | O13: Average
B14: SG&A as % of sales | D14: =-'Income Statement'!D10/'Income Statement'!D7 -> 0.2826631 | E14: =-'Income Statement'!E10/'Income Statement'!E7 -> 0.26928561 | F14: =-'Income Statement'!F10/'Income Statement'!F7 -> 0.26001161 | G14: =-'Income Statement'!G10/'Income Statement'!G7 -> 0.24994882 | H14: =-'Income Statement'!H10/'Income Statement'!H7 -> 0.24904555 | I14: =(I6-$D$6)*(-0.0087)+0.2882 -> 0.2447 | J14: =(J6-$D$6)*(-0.0087)+0.2882 -> 0.236 | K14: =(K6-$D$6)*(-0.0087)+0.2882 -> 0.2273 | L14: =(L6-$D$6)*(-0.0087)+0.2882 -> 0.2186 | M14: =(M6-$D$6)*(-0.0087)+0.2882 -> 0.2099 | O14: Follows linear regression
B15: R&D as % of sales | D15: =-'Income Statement'!D11/'Income Statement'!D7 -> 0.15613435 | E15: =-'Income Statement'!E11/'Income Statement'!E7 -> 0.16173535 | F15: =-'Income Statement'!F11/'Income Statement'!F7 -> 0.16595328 | G15: =-'Income Statement'!G11/'Income Statement'!G7 -> 0.15638436 | H15: =-'Income Statement'!H11/'Income Statement'!H7 -> 0.14484597 | I15: =AVERAGE(D15:H15) -> 0.15701066 | J15: =I15+0.02 -> 0.17701066 | K15: =AVERAGE(F15:J15) -> 0.16024099 | L15: =K15+0.02 -> 0.18024099 | M15: =AVERAGE(H15:L15) -> 0.16386985 | O15: Follows acquisition trend: loss of important patents in 2012. Loss of top 3 product patents in 2014. After acquistions we model a jump in R&D expenses because Biotech companies are R&D intensive
B16: Effective tax rate | D16: ='Free Cash Flow'!D14 -> 0.17 | E16: ='Free Cash Flow'!E14 -> 0.12 | F16: ='Free Cash Flow'!F14 -> 0.16 | G16: ='Free Cash Flow'!G14 -> 0.22 | H16: ='Free Cash Flow'!H14 -> 0.22 | I16: 0.33 | J16: 0.33 | K16: 0.33 | L16: 0.33 | M16: 0.33
B18: Balance Sheet
B19: NC-WC as % of sales | D19: ='Balance Sheet'!D47/'Income Statement'!D7 -> 0.1157086 | E19: ='Balance Sheet'!E47/'Income Statement'!E7 -> 0.12049052 | F19: ='Balance Sheet'!F47/'Income Statement'!F7 -> 0.13294399 | G19: ='Balance Sheet'!G47/'Income Statement'!G7 -> 0.16177575 | H19: ='Balance Sheet'!H47/'Income Statement'!H7 -> 0.16640337 | I19: =H19+AVERAGE(E19-D19,F19-E19) -> 0.17502107 | J19: =I19+G19-F19 -> 0.20385282 | K19: =J19+0.004 -> 0.20785282 | L19: =K19+0.013 -> 0.22085282 | M19: =L19+AVERAGE(K19-J19,L19-K19) -> 0.22935282 | O19: Follow acquisition trend: 2004, 2009, 2012 jumps in WC as observe in 2005 and 2009
B21: Cash Flow Statement
B22: D&A growth rate | D22: NA | E22: ='Cash Flow Statement'!E7/'Cash Flow Statement'!D7-1 -> -0.23703583 | F22: ='Cash Flow Statement'!F7/'Cash Flow Statement'!E7-1 -> 0.28323328 | G22: ='Cash Flow Statement'!G7/'Cash Flow Statement'!F7-1 -> -0.16274018 | H22: ='Cash Flow Statement'!H7/'Cash Flow Statement'!G7-1 -> 0.023548194 | I22: =AVERAGE($E$22:$H$22) -> -0.023248635 | J22: =AVERAGE($E$22:$H$22) -> -0.023248635 | K22: =AVERAGE($E$22:$H$22) -> -0.023248635 | L22: =AVERAGE($E$22:$H$22) -> -0.023248635 | M22: =AVERAGE($E$22:$H$22) -> -0.023248635 | O22: Should correspond to last years average because the Capex follow the same trend
B24: PPE as % of sales | D24: =-'Cash Flow Statement'!D9/'Income Statement'!D7 -> 0.051245903 | E24: =-'Cash Flow Statement'!E9/'Income Statement'!E7 -> 0.057393412 | F24: =-'Cash Flow Statement'!F9/'Income Statement'!F7 -> 0.058255949 | G24: =-'Cash Flow Statement'!G9/'Income Statement'!G7 -> 0.060909029 | H24: =-'Cash Flow Statement'!H9/'Income Statement'!H7 -> 0.051770669 | I24: =AVERAGE($D$24:$H$24) -> 0.055914992 | J24: =AVERAGE($D$24:$H$24) -> 0.055914992 | K24: =AVERAGE($D$24:$H$24) -> 0.055914992 | L24: =AVERAGE($D$24:$H$24) -> 0.055914992 | M24: =AVERAGE($D$24:$H$24) -> 0.055914992 | O24: Should remain stable on average
B25: Acquisition as % of sales | D25: =-'Cash Flow Statement'!D10/'Income Statement'!D7 -> 0.01793959 | E25: =-'Cash Flow Statement'!E10/'Income Statement'!E7 -> 0.0076286896 | F25: =-'Cash Flow Statement'!F10/'Income Statement'!F7 -> 0.023977075 | G25: =-'Cash Flow Statement'!G10/'Income Statement'!G7 -> 0.18982461 | H25: =-'Cash Flow Statement'!H10/'Income Statement'!H7 -> 0.054601106 | I25: =AVERAGE($H$25,$F$25,$E$25,$D$25) -> 0.026036615 | J25: 0.21 | K25: =AVERAGE($H$25,$F$25,$E$25,$D$25) -> 0.026036615 | L25: 0.21 | M25: =AVERAGE($H$25,$F$25,$E$25,$D$25) -> 0.026036615 | O25: Should remain stable on average except for acquistion year
B26: Capex as % of sales | D26: =SUM(D24,D25) -> 0.069185493 | E26: =SUM(E24,E25) -> 0.065022102 | F26: =SUM(F24,F25) -> 0.082233024 | G26: =SUM(G24,G25) -> 0.25073364 | H26: =SUM(H24,H25) -> 0.10637177 | I26: =SUM(I24,I25) -> 0.081951608 | J26: =SUM(J24,J25) -> 0.26591499 | K26: =SUM(K24,K25) -> 0.081951608 | ... M26: =SUM(M24,M25) -> 0.081951608 | O26: Follow acquisition trend: 2004, 2009, 2012 jumps in acquisition capex observed in 2009. We think the acquistion will be similar to Merial around 7 billion€
B27: Figure 1: Table of assumptions for scenario 1
B29: Operating assumptions 2 - Sanofi manages to keep a dynamic growth rate before the loss of patents collapse
D30: 2006 | E30: 2007 | F30: 2008 | G30: 2009 | H30: 2010 | I30: 2011 | J30: 2012 | K30: 2013 | L30: 2014 | M30: 2015
B31: Income statement
B32: Sales growth | D32: =D11 -> NA | E32: =E11 -> -0.011313573 | F32: =F11 -> -0.017253672 | G32: =G11 -> 0.063044109 | H32: =H11 -> 0.036784276 | I32: =H32 -> 0.036784276 | J32: =I32 -> 0.036784276 | K32: 0 | L32: -0.025 | M32: -0.05
B33: Other revenues | D33: =D12 -> NA | E33: =E12 -> 0.034946237 | F33: =F12 -> 0.081385281 | G33: =G12 -> 0.15532426 | H33: =H12 -> 0.14414414 | I33: =AVERAGE($E$33:$H$33) -> 0.10394998 | J33: =AVERAGE($E$33:$H$33) -> 0.10394998 | K33: =AVERAGE($E$33:$H$33) -> 0.10394998 | L33: =AVERAGE($E$33:$H$33) -> 0.10394998 | M33: =AVERAGE($E$33:$H$33) -> 0.10394998
B34: COGS as % of sales | D34: =D13 -> 0.26740211 | E34: =E13 -> 0.26989163 | F34: =F13 -> 0.2661419 | G34: =G13 -> 0.26888692 | H34: =H13 -> 0.28689442 | I34: =(H6-$E$6)*0.0038+0.2604 -> 0.2718 | J34: =(I6-$E$6)*0.0038+0.2604 -> 0.2756 | K34: =(J6-$E$6)*0.0038+0.2604 -> 0.2794 | L34: =(K6-$E$6)*0.0038+0.2604 -> 0.2832 | M34: =(L6-$E$6)*0.0038+0.2604 -> 0.287
B35: SG&A as % of sales | D35: =D14 -> 0.2826631 | E35: =E14 -> 0.26928561 | F35: =F14 -> 0.26001161 | G35: =G14 -> 0.24994882 | H35: =H14 -> 0.24904555 | I35: =(I6-$D$6)*(-0.0087)+0.2882 -> 0.2447 | J35: =(J6-$D$6)*(-0.0087)+0.2882 -> 0.236 | K35: =(K6-$D$6)*(-0.0087)+0.2882 -> 0.2273 | L35: =(L6-$D$6)*(-0.0087)+0.2882 -> 0.2186 | M35: =(M6-$D$6)*(-0.0087)+0.2882 -> 0.2099
B36: R&D as % of sales | D36: =D15 -> 0.15613435 | E36: =E15 -> 0.16173535 | F36: =F15 -> 0.16595328 | G36: =G15 -> 0.15638436 | H36: =H15 -> 0.14484597 | I36: =AVERAGE(E36:H36)+0.005 -> 0.16222974 | J36: =I36+0.005 -> 0.16722974 | K36: =J36+0.005 -> 0.17222974 | L36: =K36+0.005 -> 0.17722974 | M36: =L36+0.005 -> 0.18222974
B37: Effective tax rate | D37: =D16 -> 0.17 | E37: =E16 -> 0.12 | F37: =F16 -> 0.16 | G37: =G16 -> 0.22 | H37: =H16 -> 0.22 | I37: 0.33 | J37: 0.33 | K37: 0.33 | L37: 0.33 | M37: 0.33
B39: Balance Sheet
B40: NC-WC as % of sales | D40: 0.1157086 | E40: 0.12049052 | F40: 0.13294399 | G40: 0.16177575 | H40: 0.16640337 | I40: =AVERAGE($G$40:$H$40) -> 0.16408956 | J40: =AVERAGE($G$40:$H$40) -> 0.16408956 | K40: =AVERAGE($G$40:$H$40) -> 0.16408956 | L40: =AVERAGE($G$40:$H$40) -> 0.16408956 | M40: =AVERAGE($G$40:$H$40) -> 0.16408956
B42: Cash Flow Statement
B43: D&A growth rate | D43: NA | E43: -0.23703583 | F43: 0.28323328 | G43: -0.16274018 | H43: 0.023548194 | I43: =AVERAGE($E$43:$H$43) -> -0.023248635 | J43: =AVERAGE($E$43:$H$43) -> -0.023248635 | K43: =AVERAGE($E$43:$H$43) -> -0.023248635 | L43: =AVERAGE($E$43:$H$43) -> -0.023248635 | M43: =AVERAGE($E$43:$H$43) -> -0.023248635
B44: Capex as % of sales | D44: 0.069185493 | E44: 0.065022102 | F44: 0.082233024 | G44: 0.25073364 | H44: 0.10637177 | I44: =AVERAGE($H$44,$F$44,$E$44,$D$44) -> 0.080703098 | J44: =AVERAGE($H$44,$F$44,$E$44,$D$44) -> 0.080703098 | K44: =AVERAGE($H$44,$F$44,$E$44,$D$44) -> 0.080703098 | L44: =AVERAGE($H$44,$F$44,$E$44,$D$44) -> 0.080703098 | M44: =AVERAGE($H$44,$F$44,$E$44,$D$44) -> 0.080703098
B46: Figure 2: Table of assumptions for scenario 2
I104: 5951 | J104: =-'Income Statement'!D15 -> 6113
J105: =(J104-I104)/I104 -> 0.027222316
I110: 27.311 | J110: =I110/(-I111-I112) -> 0.039401682
I111: -1.143
I112: -692

Sheet Balance Sheet
A1: Project EBS
A2: Income Statement | D2: Actual | F2: Projections
A3: €m | D3: 2006 | E3: 2007 | F3: 2008 | G3: 2009 | H3: 2010 | I3: 2011 | J3: 2012 | K3: 2013 | L3: 2014 | M3: 2015
B5: Assets
B7: Cash & cash equivalents | D7: 1153 | E7: 1711 | F7: 4226 | G7: 4692 | H7: 6465
B8: Inventory | D8: 3659 | E8: 3729 | F8: 3590 | G8: 4444 | H8: 5020
B9: Accounts receivable | D9: 5032 | E9: 4904 | F9: 5303 | G9: 6015 | H9: 6507
B10: Other current assets | D10: 2316 | E10: 2209 | F10: 2284 | G10: 2381 | H10: 2051
B11: Total current assets | D11: =SUM(D7:D10) -> 12160 | E11: =SUM(E7:E10) -> 12553 | F11: =SUM(F7:F10) -> 15403 | G11: =SUM(G7:G10) -> 17532 | H11: =SUM(H7:H10) -> 20043
B13: PP&E | D13: 6219 | E13: 6538 | F13: 6961 | G13: 7830 | H13: 8155
B14: Goodwill | D14: 28472 | E14: 27199 | F14: 28163 | G14: 29733 | H14: 31932
B15: Other fixed assets | D15: 30912 | E15: 25624 | F15: 21460 | G15: 18612 | H15: 18098
B16: Total fixed assets | D16: =SUM(D13:D15) -> 65603 | E16: =SUM(E13:E15) -> 59361 | F16: =SUM(F13:F15) -> 56584 | G16: =SUM(G13:G15) -> 56175 | H16: =SUM(H13:H15) -> 58185
B18: Assets held for sale of exchange | D18: 0 | E18: 0 | F18: 0 | G18: 6544 | H18: 7036
B19: Total assets | D19: =D11+D16+D18 -> 77763 | E19: =E11+E16+E18 -> 71914 | F19: =F11+F16+F18 -> 71987 | G19: =G11+G16+G18 -> 80251 | H19: =H11+H16+H18 -> 85264
B21: Equity and Liabilities
B23: Accounts payable | D23: 3008 | E23: 2749 | F23: 2791 | G23: 2654 | H23: 2800
B24: Short-term debt and current portion of long-term debt | D24: 2554 | E24: 2207 | F24: 1833 | G24: 2866 | H24: 1565
B25: Other current liabilities | D25: 4716 | E25: 4713 | F25: 4721 | G25: 5445 | H25: 5722
B26: Total current libailities | D26: =SUM(D23:D25) -> 10278 | E26: =SUM(E23:E25) -> 9669 | F26: =SUM(F23:F25) -> 9345 | G26: =SUM(G23:G25) -> 10965 | H26: =SUM(H23:H25) -> 10087
B28: Long-term debt | D28: 4499 | E28: 3734 | F28: 4173 | G28: 5961 | H28: 6695
B29: Provisions and other non-current liabilities | D29: 7920 | E29: 6857 | F29: 7730 | G29: 8236 | H29: 9326
B30: Other non-current liabilities | D30: 9246 | E30: 6935 | F30: 5668 | G30: 5008 | H30: 4196
B31: Total liabilities | D31: =D26+SUM(D28:D30) -> 31943 | E31: =E26+SUM(E28:E30) -> 27195 | F31: =F26+SUM(F28:F30) -> 26916 | G31: =G26+SUM(G28:G30) -> 30170 | H31: =H26+SUM(H28:H30) -> 30304
B33: Equity attributable to equity holders of the Company | D33: 45600 | E33: 44542 | F33: 44866 | G33: 48322 | H33: 53097
B34: Minority interests | D34: 220 | E34: 177 | F34: 205 | G34: 258 | H34: 191
B35: Total equity | D35: =SUM(D33:D34) -> 45820 | E35: =SUM(E33:E34) -> 44719 | F35: =SUM(F33:F34) -> 45071 | G35: =SUM(G33:G34) -> 48580 | H35: =SUM(H33:H34) -> 53288
B37: Liabilities related to assets held for sale or exchange | D37: 0 | E37: 0 | F37: 0 | G37: 1501 | H37: 1672
B38: Total equity and liabilities | D38: =D31+D35+D37 -> 77763 | E38: =E31+E35+E37 -> 71914 | F38: =F31+F35+F37 -> 71987 | G38: =G31+G35+G37 -> 80251 | H38: =H31+H35+H37 -> 85264
B39: check | D39: =IF(ROUND(D38-D19,1)=0,"ok!",D38-D19) -> ok! | E39: =IF(ROUND(E38-E19,1)=0,"ok!",E38-E19) -> ok! | F39: =IF(ROUND(F38-F19,1)=0,"ok!",F38-F19) -> ok! | G39: =IF(ROUND(G38-G19,1)=0,"ok!",G38-G19) -> ok! | H39: =IF(ROUND(H38-H19,1)=0,"ok!",H38-H19) -> ok!
B42: Operating Working Capital | C42: 2005 | D42: 2006 | E42: 2007 | F42: 2008 | G42: 2009 | H42: 2010 | I42: 2011 | J42: 2012 | K42: 2013 | L42: 2014 | M42: 2015
B43: Total current assets | C43: 13121 | D43: =D11 -> 12160 | E43: =E11 -> 12553 | F43: =F11 -> 15403 | G43: =G11 -> 17532 | H43: =H11 -> 20043
B44: - Cash and Cash equivalents | C44: 1249 | D44: =D7 -> 1153 | E44: =E7 -> 1711 | F44: =F7 -> 4226 | G44: =G7 -> 4692 | H44: =H7 -> 6465
B45: -Total curent liabilities | C45: 15420 | D45: =D26 -> 10278 | E45: =E26 -> 9669 | F45: =F26 -> 9345 | G45: =G26 -> 10965 | H45: =H26 -> 10087
B46: + Short-term debt and current portion of long-term debt | C46: 6425 | D46: =D24 -> 2554 | E46: =E24 -> 2207 | F46: =F24 -> 1833 | G46: =G24 -> 2866 | H46: =H24 -> 1565
B47: NET NON-CASH WORKING CAPITAL | C47: =C43-C44-C45+C46 -> 2877 | D47: =D43-D44-D45+D46 -> 3283 | E47: =E43-E44-E45+E46 -> 3380 | F47: =F43-F44-F45+F46 -> 3665 | G47: =G43-G44-G45+G46 -> 4741 | H47: =H43-H44-H45+H46 -> 5056 | I47: =IF(Assumption!$H$2=Assumption!$S$1,Assumption!I19*'Income Statement'!I7,IF(Assumption!$H$2=Assumption!$S$2,'Income Statement'!I7*Assumption!I40,Assumption!#REF!*'Income Statement'!I7)) -> 5373.8075 | J47: =IF(Assumption!$H$2=Assumption!$S$1,Assumption!J19*'Income Statement'!J7,IF(Assumption!$H$2=Assumption!$S$2,'Income Statement'!J7*Assumption!J40,Assumption!#REF!*'Income Statement'!J7)) -> 6637.8767 | K47: =IF(Assumption!$H$2=Assumption!$S$1,Assumption!K19*'Income Statement'!K7,IF(Assumption!$H$2=Assumption!$S$2,'Income Statement'!K7*Assumption!K40,Assumption!#REF!*'Income Statement'!K7)) -> 6842.5745 | L47: =IF(Assumption!$H$2=Assumption!$S$1,Assumption!L19*'Income Statement'!L7,IF(Assumption!$H$2=Assumption!$S$2,'Income Statement'!L7*Assumption!L40,Assumption!#REF!*'Income Statement'!L7)) -> 7714.041 | M47: =IF(Assumption!$H$2=Assumption!$S$1,Assumption!M19*'Income Statement'!M7,IF(Assumption!$H$2=Assumption!$S$2,'Income Statement'!M7*Assumption!M40,Assumption!#REF!*'Income Statement'!M7)) -> 8099.0529
B49: Δ NET NON-CASH WORKING CAPITAL | D49: =D47-C47 -> 406 | E49: =E47-D47 -> 97 | F49: =F47-E47 -> 285 | G49: =G47-F47 -> 1076 | H49: =H47-G47 -> 315 | I49: =I47-H47 -> 317.80746 | J49: =J47-I47 -> 1264.0692 | K49: =K47-J47 -> 204.69779 | ... M49: =M47-L47 -> 385.01186

Sheet Income Statement
A1: Project EBS
A2: Income Statement | D2: Actual | F2: Projections
A3: €m | D3: 2006 | E3: 2007 | F3: 2008 | G3: 2009 | H3: 2010 | I3: 2011 | J3: 2012 | K3: 2013 | L3: 2014 | M3: 2015
B5: Income Statement
B7: Sales | D7: 28373 | E7: 28052 | F7: 27568 | G7: 29306 | H7: 30384 | I7: =IF(Assumption!$H$2=Assumption!$S$1,H7*(1+Assumption!I11),IF(Assumption!$H$2=Assumption!$S$2,'Income Statement'!H7*(1+Assumption!I32),'Income Statement'!H7*(1+Assumption!#REF!))) -> 30703.775 | J7: =IF(Assumption!$H$2=Assumption!$S$1,I7*(1+Assumption!J11),IF(Assumption!$H$2=Assumption!$S$2,'Income Statement'!I7*(1+Assumption!J32),'Income Statement'!I7*(1+Assumption!#REF!))) -> 32562.104 | K7: =IF(Assumption!$H$2=Assumption!$S$1,J7*(1+Assumption!K11),IF(Assumption!$H$2=Assumption!$S$2,'Income Statement'!J7*(1+Assumption!K32),'Income Statement'!J7*(1+Assumption!#REF!))) -> 32920.287 | L7: =IF(Assumption!$H$2=Assumption!$S$1,K7*(1+Assumption!L11),IF(Assumption!$H$2=Assumption!$S$2,'Income Statement'!K7*(1+Assumption!L32),'Income Statement'!K7*(1+Assumption!#REF!))) -> 34928.424 | M7: =IF(Assumption!$H$2=Assumption!$S$1,L7*(1+Assumption!M11),IF(Assumption!$H$2=Assumption!$S$2,'Income Statement'!L7*(1+Assumption!M32),'Income Statement'!L7*(1+Assumption!#REF!))) -> 35312.637
B8: Other Revenues | D8: 1116 | E8: 1155 | F8: 1249 | G8: 1443 | H8: 1651 | I8: =IF(Assumption!$H$2=Assumption!$S$1,H8*(1+Assumption!I12),IF(Assumption!$H$2=Assumption!$S$2,'Income Statement'!H8*(1+Assumption!I33),'Income Statement'!H8*(1+Assumption!#REF!))) -> 1822.6214 | J8: =IF(Assumption!$H$2=Assumption!$S$1,I8*(1+Assumption!J12),IF(Assumption!$H$2=Assumption!$S$2,'Income Statement'!I8*(1+Assumption!J33),'Income Statement'!I8*(1+Assumption!#REF!))) -> 2012.0829 | K8: =IF(Assumption!$H$2=Assumption!$S$1,J8*(1+Assumption!K12),IF(Assumption!$H$2=Assumption!$S$2,'Income Statement'!J8*(1+Assumption!K33),'Income Statement'!J8*(1+Assumption!#REF!))) -> 2221.2389 | L8: =IF(Assumption!$H$2=Assumption!$S$1,K8*(1+Assumption!L12),IF(Assumption!$H$2=Assumption!$S$2,'Income Statement'!K8*(1+Assumption!L33),'Income Statement'!K8*(1+Assumption!#REF!))) -> 2452.1366 | M8: =IF(Assumption!$H$2=Assumption!$S$1,L8*(1+Assumption!M12),IF(Assumption!$H$2=Assumption!$S$2,'Income Statement'!L8*(1+Assumption!M33),'Income Statement'!L8*(1+Assumption!#REF!))) -> 2707.0361
B9: Cost of sales | D9: -7587 | E9: -7571 | F9: -7337 | G9: -7880 | H9: -8717 | I9: =IF(Assumption!$H$2=Assumption!$S$1,-I$7*Assumption!I13,IF(Assumption!$H$2=Assumption!$S$2,-'Income Statement'!I$7*Assumption!I34,-'Income Statement'!I$7*Assumption!#REF!)) -> -8346.6184 | J9: =IF(Assumption!$H$2=Assumption!$S$1,-J$7*Assumption!J13,IF(Assumption!$H$2=Assumption!$S$2,-'Income Statement'!J$7*Assumption!J34,-'Income Statement'!J$7*Assumption!#REF!)) -> -8851.7928 | K9: =IF(Assumption!$H$2=Assumption!$S$1,-K$7*Assumption!K13,IF(Assumption!$H$2=Assumption!$S$2,-'Income Statement'!K$7*Assumption!K34,-'Income Statement'!K$7*Assumption!#REF!)) -> -8949.1625 | L9: =IF(Assumption!$H$2=Assumption!$S$1,-L$7*Assumption!L13,IF(Assumption!$H$2=Assumption!$S$2,-'Income Statement'!L$7*Assumption!L34,-'Income Statement'!L$7*Assumption!#REF!)) -> -9495.0614 | M9: =IF(Assumption!$H$2=Assumption!$S$1,-M$7*Assumption!M13,IF(Assumption!$H$2=Assumption!$S$2,-'Income Statement'!M$7*Assumption!M34,-'Income Statement'!M$7*Assumption!#REF!)) -> -9599.5071
B10: Selling, general & administrative | D10: -8020 | E10: -7554 | F10: -7168 | G10: -7325 | H10: -7567 | I10: =IF(Assumption!$H$2=Assumption!$S$1,-I$7*Assumption!I14,IF(Assumption!$H$2=Assumption!$S$2,-'Income Statement'!I$7*Assumption!I35,-'Income Statement'!I$7*Assumption!#REF!)) -> -7513.2137 | J10: =IF(Assumption!$H$2=Assumption!$S$1,-J$7*Assumption!J14,IF(Assumption!$H$2=Assumption!$S$2,-'Income Statement'!J$7*Assumption!J35,-'Income Statement'!J$7*Assumption!#REF!)) -> -7684.6564 | K10: =IF(Assumption!$H$2=Assumption!$S$1,-K$7*Assumption!K14,IF(Assumption!$H$2=Assumption!$S$2,-'Income Statement'!K$7*Assumption!K35,-'Income Statement'!K$7*Assumption!#REF!)) -> -7482.7812 | L10: =IF(Assumption!$H$2=Assumption!$S$1,-L$7*Assumption!L14,IF(Assumption!$H$2=Assumption!$S$2,-'Income Statement'!L$7*Assumption!L35,-'Income Statement'!L$7*Assumption!#REF!)) -> -7635.3535 | M10: =IF(Assumption!$H$2=Assumption!$S$1,-M$7*Assumption!M14,IF(Assumption!$H$2=Assumption!$S$2,-'Income Statement'!M$7*Assumption!M35,-'Income Statement'!M$7*Assumption!#REF!)) -> -7412.1225
B11: R&D expenses | D11: -4430 | E11: -4537 | F11: -4575 | G11: -4583 | H11: -4401 | I11: =IF(Assumption!$H$2=Assumption!$S$1,-I7*Assumption!I15,IF(Assumption!$H$2=Assumption!$S$2,-I7*Assumption!I36,-'Income Statement'!I7*Assumption!#REF!)) -> -4820.82 | J11: =IF(Assumption!$H$2=Assumption!$S$1,-J7*Assumption!J15,IF(Assumption!$H$2=Assumption!$S$2,-J7*Assumption!J36,-'Income Statement'!J7*Assumption!#REF!)) -> -5763.8395 | K11: =IF(Assumption!$H$2=Assumption!$S$1,-K7*Assumption!K15,IF(Assumption!$H$2=Assumption!$S$2,-K7*Assumption!K36,-'Income Statement'!K7*Assumption!#REF!)) -> -5275.1792 | L11: =IF(Assumption!$H$2=Assumption!$S$1,-L7*Assumption!L15,IF(Assumption!$H$2=Assumption!$S$2,-L7*Assumption!L36,-'Income Statement'!L7*Assumption!#REF!)) -> -6295.5336 | M11: =IF(Assumption!$H$2=Assumption!$S$1,-M7*Assumption!M15,IF(Assumption!$H$2=Assumption!$S$2,-M7*Assumption!M36,-'Income Statement'!M7*Assumption!#REF!)) -> -5786.6766
B12: EBITDA | D12: =SUM(D7,D8,D9,D10,D11) -> 9452 | E12: =SUM(E7,E8,E9,E10,E11) -> 9545 | F12: =SUM(F7,F8,F9,F10,F11) -> 9737 | G12: =SUM(G7,G8,G9,G10,G11) -> 10961 | H12: =SUM(H7,H8,H9,H10,H11) -> 11350 | I12: =SUM(I7,I8,I9,I10,I11) -> 11845.744 | J12: =SUM(J7,J8,J9,J10,J11) -> 12273.898 | K12: =SUM(K7,K8,K9,K10,K11) -> 13434.403 | ... M12: =SUM(M7,M8,M9,M10,M11) -> 15221.367
B13: % margin | D13: =D12/D7 -> 0.33313361 | E13: =E12/E7 -> 0.34026094 | F13: =F12/F7 -> 0.35319936 | G13: =G12/G7 -> 0.37401897 | H13: =H12/H7 -> 0.37355187 | I13: =I12/I7 -> 0.38580742 | J13: =J12/J7 -> 0.37693811 | K13: =K12/K7 -> 0.40808887 | ... M13: =M12/M7 -> 0.43104588
B15: Depreciation & amortization* | D15: -6113 | E15: -4664 | F15: -5985 | G15: -5011 | H15: -5129 | I15: =-'Cash Flow Statement'!I7 -> -5009.7578 | J15: =-'Cash Flow Statement'!J7 -> -4893.2877 | K15: =-'Cash Flow Statement'!K7 -> -4779.5255 | L15: =-'Cash Flow Statement'!L7 -> -4668.408 | M15: =-'Cash Flow Statement'!M7 -> -4559.8739
B16: EBIT | D16: =D12+D15 -> 3339 | E16: =E12+E15 -> 4881 | F16: =F12+F15 -> 3752 | G16: =G12+G15 -> 5950 | H16: =H12+H15 -> 6221 | I16: =I12+I15 -> 6835.9863 | J16: =J12+J15 -> 7380.61 | K16: =K12+K15 -> 8654.8772 | ... M16: =M12+M15 -> 10661.493
B17: % margin | D17: =D16/D7 -> 0.1176823 | E17: =E16/E7 -> 0.17399829 | F17: =F16/F7 -> 0.13609983 | G17: =G16/G7 -> 0.2030301 | H17: =H16/H7 -> 0.20474592 | I17: =I16/I7 -> 0.22264319 | J17: =J16/J7 -> 0.22666257 | K17: =K16/K7 -> 0.26290406 | ... M17: =M16/M7 -> 0.30191721
B20: *from Cash Flow Statement in AR

Sheet Cash Flow Statement
A1: Project EBS
A2: Income Statement | D2: Actual | F2: Projections
A3: €m | D3: 2006 | E3: 2007 | F3: 2008 | G3: 2009 | H3: 2010 | I3: 2011 | J3: 2012 | K3: 2013 | L3: 2014 | M3: 2015
B5: Cash Flow Statement
B7: Depreciation & amortization | D7: =-'Income Statement'!D15 -> 6113 | E7: =-'Income Statement'!E15 -> 4664 | F7: =-'Income Statement'!F15 -> 5985 | G7: =-'Income Statement'!G15 -> 5011 | H7: =-'Income Statement'!H15 -> 5129 | I7: =IF(Assumption!$H$2=Assumption!$S$1,H7*(1+Assumption!I22),IF(Assumption!$H$2=Assumption!$S$2,'Cash Flow Statement'!H7*(1+Assumption!I43),'Cash Flow Statement'!H7*(1+Assumption!#REF!))) -> 5009.7578 | J7: =IF(Assumption!$H$2=Assumption!$S$1,I7*(1+Assumption!J22),IF(Assumption!$H$2=Assumption!$S$2,'Cash Flow Statement'!I7*(1+Assumption!J43),'Cash Flow Statement'!I7*(1+Assumption!#REF!))) -> 4893.2877 | K7: =IF(Assumption!$H$2=Assumption!$S$1,J7*(1+Assumption!K22),IF(Assumption!$H$2=Assumption!$S$2,'Cash Flow Statement'!J7*(1+Assumption!K43),'Cash Flow Statement'!J7*(1+Assumption!#REF!))) -> 4779.5255 | L7: =IF(Assumption!$H$2=Assumption!$S$1,K7*(1+Assumption!L22),IF(Assumption!$H$2=Assumption!$S$2,'Cash Flow Statement'!K7*(1+Assumption!L43),'Cash Flow Statement'!K7*(1+Assumption!#REF!))) -> 4668.408 | M7: =IF(Assumption!$H$2=Assumption!$S$1,L7*(1+Assumption!M22),IF(Assumption!$H$2=Assumption!$S$2,'Cash Flow Statement'!L7*(1+Assumption!M43),'Cash Flow Statement'!L7*(1+Assumption!#REF!))) -> 4559.8739
B9: Acquisitions of property, plant and equipment and intangible assets | D9: -1454 | E9: -1610 | F9: -1606 | G9: -1785 | H9: -1573 | I9: =-Assumption!I24*'Income Statement'!I7 -> -1716.8013 | J9: =-Assumption!J24*'Income Statement'!J7 -> -1820.7098 | K9: =-Assumption!K24*'Income Statement'!K7 -> -1840.7376 | L9: =-Assumption!L24*'Income Statement'!L7 -> -1953.0226 | M9: =-Assumption!M24*'Income Statement'!M7 -> -1974.5058
B10: Acquisitions of investments in consolidated undertakings, net of cash acquired | D10: -509 | E10: -214 | F10: -661 | G10: -5563 | H10: -1659 | I10: =-Assumption!I25*'Income Statement'!I7 -> -799.42237 | J10: =-Assumption!J25*'Income Statement'!J7 -> -6838.0417 | K10: =-Assumption!K25*'Income Statement'!K7 -> -857.13284 | L10: =-Assumption!L25*'Income Statement'!L7 -> -7334.9691 | M10: =-Assumption!M25*'Income Statement'!M7 -> -919.42154
B11: Capex | D11: =D9+D10 -> -1963 | E11: =E9+E10 -> -1824 | F11: =F9+F10 -> -2267 | G11: =G9+G10 -> -7348 | H11: =H9+H10 -> -3232 | I11: =-IF(Assumption!$H$2=Assumption!$S$1,'Income Statement'!I7*Assumption!I26,IF(Assumption!$H$2=Assumption!$S$2,'Income Statement'!I7*Assumption!I44,'Income Statement'!I7*Assumption!#REF!)) -> -2516.2237 | J11: =-IF(Assumption!$H$2=Assumption!$S$1,'Income Statement'!J7*Assumption!J26,IF(Assumption!$H$2=Assumption!$S$2,'Income Statement'!J7*Assumption!J44,'Income Statement'!J7*Assumption!#REF!)) -> -8658.7515 | K11: =-IF(Assumption!$H$2=Assumption!$S$1,'Income Statement'!K7*Assumption!K26,IF(Assumption!$H$2=Assumption!$S$2,'Income Statement'!K7*Assumption!K44,'Income Statement'!K7*Assumption!#REF!)) -> -2697.8704 | L11: =-IF(Assumption!$H$2=Assumption!$S$1,'Income Statement'!L7*Assumption!L26,IF(Assumption!$H$2=Assumption!$S$2,'Income Statement'!L7*Assumption!L44,'Income Statement'!L7*Assumption!#REF!)) -> -9287.9917 | M11: =-IF(Assumption!$H$2=Assumption!$S$1,'Income Statement'!M7*Assumption!M26,IF(Assumption!$H$2=Assumption!$S$2,'Income Statement'!M7*Assumption!M44,'Income Statement'!M7*Assumption!#REF!)) -> -2893.9274
B13: Net Capex | D13: =-D11-D7 -> -4150 | E13: =-E11-E7 -> -2840 | F13: =-F11-F7 -> -3718 | G13: =-G11-G7 -> 2337 | H13: =-H11-H7 -> -1897 | I13: =-I11-I7 -> -2493.5341 | J13: =-J11-J7 -> 3765.4638 | K13: =-K11-K7 -> -2081.6551 | ... M13: =-M11-M7 -> -1665.9466

Sheet ADJUSTMENTS >>>>

Sheet Operating lease converter
A1: Operating Lease Converter
A2: Inputs
A3: Operating lease expense in current year = | E3: 264
A4: Operating Lease Commitments (From footnote to financials)
A5: Year | B5: Commitment | C5: ! Year 1 is next year, ….
A6: 1 | B6: 260
A7: 2 | B7: 168.5
A8: 3 | B8: 168.5
A9: 4 | B9: 108.5
A10: 5 | B10: 108.5
A11: 6 and beyond | B11: 477
A13: Output
A14: Pre-tax Cost of Debt = | C14: ='Cost of Debt'!J25 -> 0.042803306 | D14: ! If you do not have a cost of debt, use the ratings estimator
A16: From the current financial statements, enter the following
A17: Reported Operating Income (EBIT) = | D17: ='Income Statement'!H16 -> 6221 | E17: ! This is the EBIT reported in the current income statement
A18: Reported Debt = | D18: ='Balance Sheet'!H24+'Balance Sheet'!H28 -> 8260 | E18: ! This is the interest-bearing debt reported on the balance sheet
A20: Number of years embedded in yr 6 estimate = | D20: =IF(B11>0,ROUND(B11/AVERAGE(B6:B10),0),0) -> 3 | E20: ! I use the average lease expense over the first five years
E21: to estimate the number of years of expenses in yr 6
A22: Converting Operating Leases into debt
A23: Year | B23: Commitment | C23: Present Value
A24: =A6 -> 1 | B24: =B6 -> 260 | C24: =B24/(1+$C$14)^A24 -> 249.32794
A25: =A7 -> 2 | B25: =B7 -> 168.5 | C25: =B25/(1+$C$14)^A25 -> 154.95126
A26: =A8 -> 3 | B26: =B8 -> 168.5 | C26: =B26/(1+$C$14)^A26 -> 148.59107
A27: =A9 -> 4 | B27: =B9 -> 108.5 | C27: =B27/(1+$C$14)^A27 -> 91.752972
A28: =A10 -> 5 | B28: =B10 -> 108.5 | C28: =B28/(1+$C$14)^A28 -> 87.986844
A29: =A11 -> 6 and beyond | B29: =IF(B11>0,IF(D20>0,B11/D20,B11),0) -> 159 | C29: =IF(D20>0,(B29*(1-(1+C14)^(-D20))/C14)/(1+$C$14)^5,B29/(1+C14)^6) -> 355.92283 | D29: ! Commitment beyond year 6 converted into an annuity for ten years
A30: Debt Value of leases = | C30: =SUM(C24:C29) -> 1088.5329
A32: Restated Financials
A33: Depreciation on Operating Lease Asset = | F33: =C30/(5+D20) -> 136.06661 | G33: ! I use straight line depreciation
A34: Adjustment to Operating Earnings = | F34: =E3-F33 -> 127.93339 | G34: ! Operating lease expense - Depreciation
A35: Adjustment to Total Debt outstanding = | F35: =C30 -> 1088.5329

Sheet R&D converter
A1: R & D Converter
A2: This spreadsheet converts R&D expenses from operating to capital expenses. It makes the appropriate adjustments to operating income, net
A3: income, the book value of assets and the book value of equity.
A5: Inputs
A6: Over how many years do you want to amortize R&D expenses | F6: 10 | G6: ! If in doubt, use the lookup table below
A7: Enter the current year's R&D expense = | F7: =-'Income Statement'!H11 -> 4401 | G7: The maximum allowed is ten years
A8: Enter R& D expenses for past years: the number of years that you will need to enter will be determined by the amortization period
A9: Do not input numbers in the first column (Year). It will get automatically updated based on the input above.
A10: Year | B10: R& D Expenses
A11: -1 | B11: 4583 | C11: ! Year -1 is the year prior to the current year
A12: =IF((0-A11)<$F$6,IF(A11>-1,,A11-1),) -> -2 | B12: 4575 | C12: ! Year -2 is the two years prior to the current year | H12: Projetction of R&D depreciation growth rate
A13: =IF((0-A12)<$F$6,IF(A12>-1,,A12-1),) -> -3 | B13: 4537 | H13: Year | I13: R&D Expense | J13: Unamortized portion | L13: Amortization this year
A14: =IF((0-A13)<$F$6,IF(A13>-1,,A13-1),) -> -4 | B14: 4430 | H14: Current | I14: =-'Income Statement'!M11 -> 5786.6766 | J14: =1 -> 1 | K14: =I14*J14 -> 5786.6766
A15: =IF((0-A14)<$F$6,IF(A14>-1,,A14-1),) -> -5 | B15: 4044 | H15: =A11 -> -1 | I15: =-'Income Statement'!L11 -> 6295.5336 | J15: =IF(H15<0,($F$6+H15)/$F$6,0) -> 0.9 | K15: =I15*J15 -> 5665.9803 | L15: =IF(H15<0,I15/$F$6,0) -> 629.55336
A16: =IF((0-A15)<$F$6,IF(A15>-1,,A15-1),) -> -6 | B16: 2389 | H16: =A12 -> -2 | I16: =-'Income Statement'!K11 -> 5275.1792 | J16: =IF(H16<0,($F$6+H16)/$F$6,0) -> 0.8 | K16: =I16*J16 -> 4220.1434 | L16: =IF(H16<0,I16/$F$6,0) -> 527.51792
A17: =IF((0-A16)<$F$6,IF(A16>-1,,A16-1),) -> -7 | B17: 1316 | H17: =A13 -> -3 | I17: =-'Income Statement'!J11 -> 5763.8395 | J17: =IF(H17<0,($F$6+H17)/$F$6,0) -> 0.7 | K17: =I17*J17 -> 4034.6877 | L17: =IF(H17<0,I17/$F$6,0) -> 576.38395
A18: =IF((0-A17)<$F$6,IF(A17>-1,,A17-1),) -> -8 | B18: 1218 | H18: =A14 -> -4 | I18: =-'Income Statement'!I11 -> 4820.82 | J18: =IF(H18<0,($F$6+H18)/$F$6,0) -> 0.6 | K18: =I18*J18 -> 2892.492 | L18: =IF(H18<0,I18/$F$6,0) -> 482.082
A19: =IF((0-A18)<$F$6,IF(A18>-1,,A18-1),) -> -9 | B19: 1031 | H19: =A15 -> -5 | I19: =F7 -> 4401 | J19: =IF(H19<0,($F$6+H19)/$F$6,0) -> 0.5 | K19: =I19*J19 -> 2200.5 | L19: =IF(H19<0,I19/$F$6,0) -> 440.1
A20: =IF((0-A19)<$F$6,IF(A19>-1,,A19-1),) -> -10 | B20: 945 | H20: =A16 -> -6 | I20: =B11 -> 4583 | J20: =IF(H20<0,($F$6+H20)/$F$6,0) -> 0.4 | K20: =I20*J20 -> 1833.2 | L20: =IF(H20<0,I20/$F$6,0) -> 458.3
H21: =A17 -> -7 | I21: =B12 -> 4575 | J21: =IF(H21<0,($F$6+H21)/$F$6,0) -> 0.3 | K21: =I21*J21 -> 1372.5 | L21: =IF(H21<0,I21/$F$6,0) -> 457.5
A22: Output | H22: =A18 -> -8 | I22: =B13 -> 4537 | J22: =IF(H22<0,($F$6+H22)/$F$6,0) -> 0.2 | K22: =I22*J22 -> 907.4 | L22: =IF(H22<0,I22/$F$6,0) -> 453.7
A23: Year | B23: R&D Expense | C23: Unamortized portion | E23: Amortization this year | H23: =A19 -> -9 | I23: =B14 -> 4430 | J23: =IF(H23<0,($F$6+H23)/$F$6,0) -> 0.1 | K23: =I23*J23 -> 443 | L23: =IF(H23<0,I23/$F$6,0) -> 443
A24: Current | B24: =F7 -> 4401 | C24: =1 -> 1 | D24: =B24*C24 -> 4401 | H24: =A20 -> -10 | I24: =B15 -> 4044 | J24: =IF(H24<0,($F$6+H24)/$F$6,0) -> 0 | K24: =I24*J24 -> 0 | L24: =IF(H24<0,I24/$F$6,0) -> 404.4
A25: =A11 -> -1 | B25: =B11 -> 4583 | C25: =IF(A25<0,($F$6+A25)/$F$6,0) -> 0.9 | D25: =B25*C25 -> 4124.7 | E25: =IF(A25<0,B25/$F$6,0) -> 458.3 | H25: Total | K25: =SUM(K14:K24) -> 29356.58 | L25: =SUM(L15:L24) -> 4872.5372
A26: =A12 -> -2 | B26: =B12 -> 4575 | C26: =IF(A26<0,($F$6+A26)/$F$6,0) -> 0.8 | D26: =B26*C26 -> 3660 | E26: =IF(A26<0,B26/$F$6,0) -> 457.5 | H26: Yearly growth rate of R&D depreciation | L26: =(1+L25/D37-1)^(1/5)-1 -> 0.10883775
A27: =A13 -> -3 | B27: =B13 -> 4537 | C27: =IF(A27<0,($F$6+A27)/$F$6,0) -> 0.7 | D27: =B27*C27 -> 3175.9 | E27: =IF(A27<0,B27/$F$6,0) -> 453.7 | H27: Yearly growth rate of value of R&D asset | L27: =(1+K25/D35-1)^(1/5)-1 -> 0.061926303
A28: =A14 -> -4 | B28: =B14 -> 4430 | C28: =IF(A28<0,($F$6+A28)/$F$6,0) -> 0.6 | D28: =B28*C28 -> 2658 | E28: =IF(A28<0,B28/$F$6,0) -> 443
A29: =A15 -> -5 | B29: =B15 -> 4044 | C29: =IF(A29<0,($F$6+A29)/$F$6,0) -> 0.5 | D29: =B29*C29 -> 2022 | E29: =IF(A29<0,B29/$F$6,0) -> 404.4
A30: =A16 -> -6 | B30: =B16 -> 2389 | C30: =IF(A30<0,($F$6+A30)/$F$6,0) -> 0.4 | D30: =B30*C30 -> 955.6 | E30: =IF(A30<0,B30/$F$6,0) -> 238.9
A31: =A17 -> -7 | B31: =B17 -> 1316 | C31: =IF(A31<0,($F$6+A31)/$F$6,0) -> 0.3 | D31: =B31*C31 -> 394.8 | E31: =IF(A31<0,B31/$F$6,0) -> 131.6
A32: =A18 -> -8 | B32: =B18 -> 1218 | C32: =IF(A32<0,($F$6+A32)/$F$6,0) -> 0.2 | D32: =B32*C32 -> 243.6 | E32: =IF(A32<0,B32/$F$6,0) -> 121.8
A33: =A19 -> -9 | B33: =B19 -> 1031 | C33: =IF(A33<0,($F$6+A33)/$F$6,0) -> 0.1 | D33: =B33*C33 -> 103.1 | E33: =IF(A33<0,B33/$F$6,0) -> 103.1
A34: =A20 -> -10 | B34: =B20 -> 945 | C34: =IF(A34<0,($F$6+A34)/$F$6,0) -> 0 | D34: =B34*C34 -> 0 | E34: =IF(A34<0,B34/$F$6,0) -> 94.5
A35: Value of Research Asset = | D35: =SUM(D24:D34) -> 21738.7 | E35: =SUM(E25:E34) -> 2906.8
A37: Amortization of asset for current year = | D37: =E35 -> 2906.8
A39: Adjustment to Operating Income = | D39: =F7-D37 -> 1494.2 | E39: ! A positive number indicates an increase in operating income (add to reported EBIT) | L39: =D39/F7 -> 0.33951375
A40: Tax Effect of R&D Expensing | D40: =(F7-D37)*'Free Cash Flow'!H31 -> 493.086
A43: Look Up Table for Amortization Periods
A44: Industry Name | B44: Amortization Period
A45: Advertising | B45: 2
A46: Aerospace/Defense | B46: 10 | D46: Non-technological Service | F46: 2 years
A47: Air Transport | B47: 10 | D47: Retail, Tech Service | F47: 3 years
A48: Aluminum | B48: 5 | D48: Light Manufacturing | F48: 5 years
A49: Apparel | B49: 3 | D49: Heavy Manufacturing | F49: 10 years
A50: Auto & Truck | B50: 10 | D50: Research, with Patenting | F50: 10 years
A51: Auto Parts (OEM) | B51: 5 | D51: Long Gestation Period | F51: 10 years
A52: Auto Parts (Replacement) | B52: 5
A53: Bank | B53: 2
A54: Bank (Canadian) | B54: 2
A55: Bank (Foreign) | B55: 2
A56: Bank (Midwest) | B56: 2
A57: Beverage (Alcoholic) | B57: 3
A58: Beverage (Soft Drink) | B58: 3
A59: Building Materials | B59: 5
A60: Cable TV | B60: 10
A61: Canadian Energy | B61: 10
A62: Cement & Aggregates | B62: 10
A63: Chemical (Basic) | B63: 10
... A142: Water Utility | B142: 10

Sheet Free Cash Flow
A1: Project EBS
A2: Income Statement | D2: Actual | F2: Projections
A3: €m | D3: 2006 | E3: 2007 | F3: 2008 | G3: 2009 | H3: 2010 | I3: Adj. | J3: 2010 | K3: 2011 | L3: 2012 | M3: 2013 | N3: 2014 | O3: 2015
B5: Unlevered Free Cash Flow
B7: Year (t) | K7: 1 | L7: 2 | M7: 3 | N7: 4 | O7: 5
B9: EBITDA | D9: ='Income Statement'!D12 -> 9452 | E9: ='Income Statement'!E12 -> 9545 | F9: ='Income Statement'!F12 -> 9737 | G9: ='Income Statement'!G12 -> 10961 | H9: ='Income Statement'!H12 -> 11350 | I9: 0 | J9: =H9+I9 -> 11350 | K9: ='Income Statement'!I12 -> 11845.744 | L9: ='Income Statement'!J12 -> 12273.898 | M9: ='Income Statement'!K12 -> 13434.403 | N9: ='Income Statement'!L12 -> 13954.612 | O9: ='Income Statement'!M12 -> 15221.367
U10: Sensitivity Analysis
B11: Depreciation & amortization | D11: ='Income Statement'!D15 -> -6113 | E11: ='Income Statement'!E15 -> -4664 | F11: ='Income Statement'!F15 -> -5985 | G11: ='Income Statement'!G15 -> -5011 | H11: ='Income Statement'!H15 -> -5129 | I11: 0 | J11: ='Income Statement'!H15 -> -5129 | K11: ='Income Statement'!I11 -> -4820.82 | L11: ='Income Statement'!J11 -> -5763.8395 | M11: ='Income Statement'!K11 -> -5275.1792 | N11: ='Income Statement'!L11 -> -6295.5336 | O11: ='Income Statement'!M11 -> -5786.6766
B12: EBIT | D12: =SUM(D9+D11) -> 3339 | E12: =SUM(E9+E11) -> 4881 | F12: =SUM(F9+F11) -> 3752 | G12: =SUM(G9+G11) -> 5950 | H12: =SUM(H9+H11) -> 6221 | I12: =D35+D37+D36 -> 2115.2194 | J12: =H12+I12 -> 8336.2194 | K12: ='Income Statement'!I16+E35+E36+E37 -> 9088.7948 | L12: ='Income Statement'!J16+F35+F36+F37 -> 10421.067 | M12: ='Income Statement'!K16+G35+G36+G37 -> 10528.069 | N12: ='Income Statement'!L16+H35+H36+H37 -> 11942.812 | O12: ='Income Statement'!M16+I35+I36+I37 -> 12005.232 | T12: WACC | U12: =O26 -> 78369.228
T13: =T14-0.01 -> #REF! | U13: =$O$24+IF(Assumption!$H$2=Assumption!$S$1,$O$23*(1+$N$68)/(T13-$N$68),IF(Assumption!$H$2=Assumption!$S$2,$N$62*(1+$N$66)^$N$64,'Free Cash Flow'!$N$68)) -> #REF!
B14: Effective tax rate | D14: =IF($B$14="Marginal tax rate",D31,D30) -> 0.17 | E14: =IF($B$14="Marginal tax rate",E31,E30) -> 0.12 | F14: =IF($B$14="Marginal tax rate",F31,F30) -> 0.16 | G14: =IF($B$14="Marginal tax rate",G31,G30) -> 0.22 | H14: =IF($B$14="Marginal tax rate",H31,H30) -> 0.22 | I14: 0 | J14: 0.22 | K14: 0.33 | L14: 0.33 | M14: 0.33 | N14: 0.33 | O14: 0.33 | T14: =#REF!-0.01 -> #REF! | U14: =$O$24+IF(Assumption!$H$2=Assumption!$S$1,$O$23*(1+$N$68)/(T14-$N$68),IF(Assumption!$H$2=Assumption!$S$2,$N$62*(1+$N$66)^$N$64,'Free Cash Flow'!$N$68)) -> #REF!
B15: EBIT*(1-Tax rate) | D15: =D12*(1-D14) -> 2771.37 | E15: =E12*(1-E14) -> 4295.28 | F15: =F12*(1-F14) -> 3151.68 | G15: =G12*(1-G14) -> 4641 | H15: =H12*(1-H14) -> 4852.38 | I15: =I12*(1-H14) -> 1649.8711 | J15: =H15+I15 -> 6502.2511 | K15: =K12*(1-K14) -> 6089.4925 | L15: =L12*(1-L14) -> 6982.1149 | M15: =M12*(1-M14) -> 7053.8059 | N15: =N12*(1-N14) -> 8001.6843 | O15: =O12*(1-O14) -> 8043.5052 | Q15: WACC | R15: =WACC!D11 -> 0.087475329 | T15: =R15 -> 0.087475329 | U15: =$O$24+IF(Assumption!$H$2=Assumption!$S$1,$O$23*(1+$N$68)/(T15-$N$68),IF(Assumption!$H$2=Assumption!$S$2,$N$62*(1+$N$66)^$N$64,'Free Cash Flow'!$N$68)) -> 78369.228
B17: Depreciation & amortization | D17: =-D11 -> 6113 | E17: =-E11 -> 4664 | F17: =-F11 -> 5985 | G17: =-G11 -> 5011 | H17: =-H11 -> 5129 | I17: =D40+D41 -> 3042.8666 | J17: =H17+I17 -> 8171.8666 | K17: =-K11+E40+E41 -> 8180.0562 | L17: =-L11+F40+F41 -> 9473.8782 | M17: =-M11+G40+G41 -> 9374.201 | N17: =-N11+H40+H41 -> 10825.875 | O17: =-O11+I40+I41 -> 10795.28 | T17: =#REF!+0.01 -> #REF! | U17: =$O$24+IF(Assumption!$H$2=Assumption!$S$1,$O$23*(1+$N$68)/(T17-$N$68),IF(Assumption!$H$2=Assumption!$S$2,$N$62*(1+$N$66)^$N$64,'Free Cash Flow'!$N$68)) -> #REF!
B18: Δ net Working Capital | D18: ='Balance Sheet'!D49 -> 406 | E18: ='Balance Sheet'!E49 -> 97 | F18: ='Balance Sheet'!F49 -> 285 | G18: ='Balance Sheet'!G49 -> 1076 | H18: ='Balance Sheet'!H49 -> 315 | I18: 0 | J18: =H18+I18 -> 315 | K18: ='Balance Sheet'!I49 -> 317.80746 | L18: ='Balance Sheet'!J49 -> 1264.0692 | M18: ='Balance Sheet'!K49 -> 204.69779 | N18: ='Balance Sheet'!L49 -> 871.46656 | O18: ='Balance Sheet'!M49 -> 385.01186 | T18: =T17+0.01 -> #REF! | U18: =$O$24+IF(Assumption!$H$2=Assumption!$S$1,$O$23*(1+$N$68)/(T18-$N$68),IF(Assumption!$H$2=Assumption!$S$2,$N$62*(1+$N$66)^$N$64,'Free Cash Flow'!$N$68)) -> #REF!
B19: Capex | D19: ='Cash Flow Statement'!D11 -> -1963 | E19: ='Cash Flow Statement'!E11 -> -1824 | F19: ='Cash Flow Statement'!F11 -> -2267 | G19: ='Cash Flow Statement'!G11 -> -7348 | H19: ='Cash Flow Statement'!H11 -> -3232 | I19: =D44+D45 -> -4665 | J19: =H19+I19 -> -7897 | K19: ='Cash Flow Statement'!I11+D44+D45 -> -7181.2237 | L19: ='Cash Flow Statement'!J11+E44+E45 -> -13743.572 | M19: ='Cash Flow Statement'!K11+F44+F45 -> -8725.7099 | N19: ='Cash Flow Statement'!L11+G44+G45 -> -14827.171 | O19: ='Cash Flow Statement'!M11+H44+H45 -> -9453.461 | T19: =T18+0.01 -> #REF! | U19: =$O$24+IF(Assumption!$H$2=Assumption!$S$1,$O$23*(1+$N$68)/(T19-$N$68),IF(Assumption!$H$2=Assumption!$S$2,$N$62*(1+$N$66)^$N$64,'Free Cash Flow'!$N$68)) -> #REF!
B21: FCF | D21: =D15+D17-D18+D19 -> 6515.37 | E21: =E15+E17-E18+E19 -> 7038.28 | F21: =F15+F17-F18+F19 -> 6584.68 | G21: =G15+G17-G18+G19 -> 1228 | H21: =H15+H17-H18+H19 -> 6434.38 | I21: NA | J21: =J15+J17-J18+J19 -> 6462.1177 | K21: =K15+K17-K18+K19 -> 6770.5175 | L21: =L15+L17-L18+L19 -> 1448.3524 | M21: =M15+M17-M18+M19 -> 7497.5992 | N21: =N15+N17-N18+N19 -> 3128.9215 | O21: =O15+O17-O18+O19 -> 9000.3128 | T21: =#REF!+0.01 -> #REF! | U21: =$O$24+IF(Assumption!$H$2=Assumption!$S$1,$O$23*(1+$N$68)/(T21-$N$68),IF(Assumption!$H$2=Assumption!$S$2,$N$62*(1+$N$66)^$N$64,'Free Cash Flow'!$N$68)) -> #REF!
B23: Unleverd FCF | K23: =K21/(1+WACC!$D$11)^'Free Cash Flow'!K7 -> 6225.9045 | L23: =L21/(1+WACC!$D$11)^'Free Cash Flow'!L7 -> 1224.7161 | M23: =M21/(1+WACC!$D$11)^'Free Cash Flow'!M7 -> 5829.9386 | N23: =N21/(1+WACC!$D$11)^'Free Cash Flow'!N7 -> 2237.2629 | O23: =O21/(1+WACC!$D$11)^'Free Cash Flow'!O7 -> 5917.8035
B24: PV of UFCF | O24: =SUM(K23:O23) -> 21435.626
B25: Terminal Value (TV) | O25: =IF(Assumption!$H$2=Assumption!$S$1,O23*(1+N68)/(WACC!D11-N68),IF(Assumption!$H$2=Assumption!$S$2,N62*(1+N66)^N64,'Free Cash Flow'!N68)) -> 56933.602
B26: Entreprise Value (EV) | O26: =O24+O25 -> 78369.228 | P26: =O26/WACC!D6-1 -> 0.030743
B27: Equity Value | O27: =O26-WACC!D5 -> 64781.695 | P27: =O27/WACC!D4-1 -> 0.037432512
B29: Tax rate | D29: 2006 | E29: 2007 | F29: 2008 | G29: 2009 | H29: 2010
B30: Effective tax rate | D30: 0.17 | E30: 0.12 | F30: 0.16 | G30: 0.22 | H30: 0.22
B31: Marginal tax rate | D31: 0.33 | E31: 0.33 | F31: 0.33 | G31: 0.33 | H31: 0.33
B33: EBIT adjustments | D33: 2010A | E33: 2011 | F33: 2012 | G33: 2013 | H33: 2014 | I33: 2015
B34: R&D adjustments | E34: 1 | F34: 2 | G34: 3 | H34: 4 | I34: 5
B35: R&D | D35: ='R&D converter'!D39 -> 1494.2 | E35: =-'Income Statement'!I11-'R&D converter'!$D$37*POWER((1+'R&D converter'!$L$26),E34) -> 1597.6504 | F35: =-'Income Statement'!J11-'R&D converter'!$D$37*POWER((1+'R&D converter'!$L$26),F34) -> 2189.8674 | G35: =-'Income Statement'!K11-'R&D converter'!$D$37*POWER((1+'R&D converter'!$L$26),G34) -> 1312.224 | H35: =-'Income Statement'!L11-'R&D converter'!$D$37*POWER((1+'R&D converter'!$L$26),H34) -> 1901.2593 | I35: =-'Income Statement'!M11-'R&D converter'!$D$37*POWER((1+'R&D converter'!$L$26),I34) -> 914.1394
B36: R&D tax effect | D36: ='R&D converter'!D40 -> 493.086 | E36: =E35*K14 -> 527.22464 | F36: =F35*L14 -> 722.65625 | G36: =G35*M14 -> 433.03393 | H36: =H35*N14 -> 627.41558 | I36: =I35*O14 -> 301.666
B37: Operating leases | D37: ='Operating lease converter'!F34 -> 127.93339 | E37: =$D$37 -> 127.93339 | F37: =$D$37 -> 127.93339 | G37: =$D$37 -> 127.93339 | H37: =$D$37 -> 127.93339 | I37: =$D$37 -> 127.93339
B39: Depreciaton adjustments
B40: R&D | D40: ='R&D converter'!D37 -> 2906.8 | E40: =D40*(1+'R&D converter'!$L$26) -> 3223.1696 | F40: =E40*(1+'R&D converter'!$L$26) -> 3573.9721 | G40: =F40*(1+'R&D converter'!$L$26) -> 3962.9552 | H40: =G40*(1+'R&D converter'!$L$26) -> 4394.2743 | I40: =H40*(1+'R&D converter'!$L$26) -> 4872.5372
B41: Operating leases | D41: ='Operating lease converter'!F33 -> 136.06661 | E41: =$D$41 -> 136.06661 | F41: =$D$41 -> 136.06661 | G41: =$D$41 -> 136.06661 | H41: =$D$41 -> 136.06661 | I41: =$D$41 -> 136.06661
B43: Capex adjustements
B44: R&D | D44: =-'R&D converter'!F7 -> -4401 | E44: ='Income Statement'!I11 -> -4820.82 | F44: ='Income Statement'!J11 -> -5763.8395 | G44: ='Income Statement'!K11 -> -5275.1792 | H44: ='Income Statement'!L11 -> -6295.5336 | I44: ='Income Statement'!M11 -> -5786.6766
B45: Operating leases | D45: =-'Operating lease converter'!E3 -> -264 | E45: =$D$45 -> -264 | F45: =$D$45 -> -264 | G45: =$D$45 -> -264 | H45: =$D$45 -> -264 | I45: =$D$45 -> -264
B47: Expected Growth Rate | E47: 2006 | F47: 2007 | G47: 2008 | H47: 2009 | I47: 2010 | J47: 2011 | K47: 2012 | L47: 2013 | M47: 2014 | N47: 2015
B48: Book value of equity | E48: ='Balance Sheet'!D33 -> 45600 | F48: ='Balance Sheet'!E33 -> 44542 | G48: ='Balance Sheet'!F33 -> 44866 | H48: ='Balance Sheet'!G33 -> 48322 | I48: ='Balance Sheet'!H33 -> 53097
B49: Book value of debt | E49: ='Balance Sheet'!D28+'Balance Sheet'!D24 -> 7053 | F49: ='Balance Sheet'!E28+'Balance Sheet'!E24 -> 5941 | G49: ='Balance Sheet'!F28+'Balance Sheet'!F24 -> 6006 | H49: ='Balance Sheet'!G28+'Balance Sheet'!G24 -> 8827 | I49: ='Balance Sheet'!H28+'Balance Sheet'!H24 -> 8260
B50: Book value of capital | E50: =SUM(E48:E49) -> 52653 | F50: =SUM(F48:F49) -> 50483 | G50: =SUM(G48:G49) -> 50872 | H50: =SUM(H48:H49) -> 57149 | I50: =SUM(I48:I49) -> 61357 | J50: 61357 | K50: =J50+7000 -> 68357 | L50: 68357 | M50: =L50+7000 -> 75357 | N50: 75357
B51: Value of Research Asset | I51: ='R&D converter'!D35 -> 21738.7 | J51: ='R&D converter'!$D$35*POWER(1+'R&D converter'!$L$27,'Free Cash Flow'!K7) -> 23084.897 | K51: ='R&D converter'!$D$35*POWER(1+'R&D converter'!$L$27,'Free Cash Flow'!L7) -> 24514.46 | L51: ='R&D converter'!$D$35*POWER(1+'R&D converter'!$L$27,'Free Cash Flow'!M7) -> 26032.55 | M51: ='R&D converter'!$D$35*POWER(1+'R&D converter'!$L$27,'Free Cash Flow'!N7) -> 27644.649 | N51: ='R&D converter'!$D$35*POWER(1+'R&D converter'!$L$27,'Free Cash Flow'!O7) -> 29356.58
B53: EBIT*(1-Tax rate) | E53: =D15 -> 2771.37 | F53: =E15 -> 4295.28 | G53: =F15 -> 3151.68 | H53: =G15 -> 4641 | I53: =H15 -> 4852.38 | J53: =K15 -> 6089.4925 | K53: =L15 -> 6982.1149 | L53: =M15 -> 7053.8059 | M53: =N15 -> 8001.6843 | N53: =O15 -> 8043.5052
B55: Return of Capital Invested* | F55: =F53/E50 -> 0.081577118 | G55: =G53/F50 -> 0.062430521 | H55: =H53/G50 -> 0.091228967 | I55: =I53/H50 -> 0.084907522 | J55: =(J53+E40)/(I50+I51) -> 0.11207153 | K55: =(K53+F40)/(J50+J51) -> 0.12501006 | L55: =(L53+G40)/(K50+K51) -> 0.11862375 | M55: =(M53+H40)/(L50+L51) -> 0.13132766 | N55: =(N53+I40)/(M50+M51) -> 0.12539646
B57: Net Capex | E57: ='Cash Flow Statement'!D13 -> -4150 | F57: ='Cash Flow Statement'!E13 -> -2840 | G57: ='Cash Flow Statement'!F13 -> -3718 | H57: ='Cash Flow Statement'!G13 -> 2337 | I57: ='Cash Flow Statement'!H13 -> -1897 | J57: =-K19-K17 -> -998.83249 | K57: =-L19-L17 -> 4269.6933 | L57: =-M19-M17 -> -648.49109 | M57: =-N19-N17 -> 4001.2963 | N57: =-O19-O17 -> -1341.8195
B58: Change in NCWC | E58: ='Balance Sheet'!D49 -> 406 | F58: ='Balance Sheet'!E49 -> 97 | G58: ='Balance Sheet'!F49 -> 285 | H58: ='Balance Sheet'!G49 -> 1076 | I58: ='Balance Sheet'!H49 -> 315 | J58: =K18 -> 317.80746 | K58: =L18 -> 1264.0692 | L58: =M18 -> 204.69779 | M58: =N18 -> 871.46656 | N58: =O18 -> 385.01186
B60: Gross value of assets | E60: =9339+'Balance Sheet'!D7+'Balance Sheet'!D8 -> 14151 | F60: =9339+'Balance Sheet'!E7+'Balance Sheet'!E8 -> 14779 | G60: =9339+'Balance Sheet'!F7+'Balance Sheet'!F8 -> 17155 | H60: =9339+'Balance Sheet'!G7+'Balance Sheet'!G8 -> 18475 | I60: =9339+'Balance Sheet'!H7+'Balance Sheet'!H8 -> 20824 | J60: =((J47-$E$47)*1704.2+11964)*1.01 -> 20689.85 | K60: =(K47-$E$47)*1704.2+11964 -> 22189.2 | L60: =(L47-$E$47)*1704.2+11964 -> 23893.4 | M60: =(M47-$E$47)*1704.2+11964 -> 25597.6 | N60: =(N47-$E$47)*1704.2+11964 -> 27301.8
B61: Accumulated depreciation & impairment | E61: -3120 | F61: -3840 | G61: -4590 | H61: -5274 | I61: -6221 | J61: =(J47-$E$47)*(-763.6)-2318.2 -> -6136.2 | K61: =(K47-$E$47)*(-763.6)-2318.2 -> -6899.8 | L61: =(L47-$E$47)*(-763.6)-2318.2 -> -7663.4 | M61: =(M47-$E$47)*(-763.6)-2318.2 -> -8427 | N61: =(N47-$E$47)*(-763.6)-2318.2 -> -9190.6
B62: Book Value of Asset | E62: =SUM(E60,E61) -> 11031 | F62: =SUM(F60,F61) -> 10939 | G62: =SUM(G60,G61) -> 12565 | H62: =SUM(H60,H61) -> 13201 | I62: =SUM(I60,I61) -> 14603 | J62: =SUM(J60,J61) -> 14553.65 | K62: =SUM(K60,K61) -> 15289.4 | L62: =SUM(L60,L61) -> 16230 | ... N62: =SUM(N60,N61) -> 18111.2
B63: Current non-adjusted depreciation expense | E63: =D11 -> -6113 | F63: =E11 -> -4664 | G63: =F11 -> -5985 | H63: =G11 -> -5011 | I63: =H11 -> -5129 | J63: =K11 -> -4820.82 | K63: =L11 -> -5763.8395 | L63: =M11 -> -5275.1792 | M63: =N11 -> -6295.5336 | N63: =O11 -> -5786.6766
B64: Average age of asset | E64: =-E60/E63 -> 2.3149027 | F64: =-F60/F63 -> 3.1687393 | G64: =-G60/G63 -> 2.8663325 | H64: =-H60/H63 -> 3.6868888 | I64: =-I60/I63 -> 4.0600507 | J64: =-J60/J63 -> 4.2917699 | K64: =-K60/K63 -> 3.8497255 | L64: =-L60/L63 -> 4.5294006 | ... N64: =-N60/N63 -> 4.7180449
B66: French inflation rate | E66: 0.016 | F66: 0.015 | G66: 0.028 | H66: 0.001 | I66: 0.015 | J66: 0.021 | K66: 0.02 | L66: 0.009 | M66: 0.005 | N66: 0.006
B68: EBIT Growth rate | F68: =(F57+F58)/F53*F55 -> -0.052095797 | G68: =(G57+G58)/G53*G55 -> -0.06800309 | H68: =(H57+H58)/H53*H55 -> 0.067089951 | I68: =(I57+I58)/I53*I55 -> -0.027682024 | J68: =(J57+J58)/J53*J55 -> -0.012533642 | K68: =(K57+K58)/K53*K55 -> 0.09907829 | L68: =(L57+L58)/L53*L55 -> -0.0074632656 | M68: =(M57+M58)/M53*M55 -> 0.07997423 | N68: =(N57+N58)/N53*N55 -> -0.014916419
B69: Source: http://france-inflation.com/inflation-depuis-1901.php
B70: gEBIT = (Net Capital Expenditures + Change in WC)/EBIT(1-t) * ROC
B71: *adjusted with R&D asset value from 2010 adj. To 2015E
B75: Expected Growth EPS | E75: 2006 | F75: 2007 | G75: 2008 | H75: 2009 | I75: 2010 | K75: Yearly Growth Rate
B76: EPS | E76: 2.97 | F76: 3.91 | G76: 2.94 | H76: 4.03 | I76: 4.19 | K76: 0.256
B77: ln(EPS) | E77: =LN(E76) -> 1.088562 | F77: =LN(F76) -> 1.3635374 | G77: =LN(G76) -> 1.0784096 | H77: =LN(H76) -> 1.3937664 | I77: =LN(I76) -> 1.4327007 | K77: =7.19%/5 -> 0.01438
B95: Unlevered Free Cash Flow Valuation | L95: Key DCF parameters | P95: Key DCF parameters
B96: €million | D96: 2011 | E96: 2012 | F96: 2013 | G96: 2014 | H96: 2015 | L96: Cost of equity | N96: 0.1003 | P96: Cost of equity | R96: 0.1003
B97: Unleverd FCF | D97: 6225.9045 | E97: 1224.7161 | F97: 5829.9386 | G97: 2237.2629 | H97: 5917.8035 | L97: Cost of debt | N97: 0.042803306 | P97: Cost of debt | R97: 0.042803306
B98: PV of UFCF | I98: 21435.626 | L98: After-tax WACC | N98: 0.087475329 | P98: After-tax WACC | R98: 0.087475329
B99: Terminal Value (TV) | I99: 56933.602 | L99: Perpetuity Growth rate | N99: -0.014916419 | P99: Perpetuity Growth rate | R99: -0.014916419
B100: Enterprise Value (EV) | I100: 78369.228 | J100: 0.030743
B101: Equity Value | I101: 64781.695 | J101: 0.037432512
B102: Figure 6: Sanofi scenario 1 DCF valuation
N104: Actual | R104: Projection
N105: 2010 | O105: Adj. | P105: 2010 | Q105: 2011 | R105: 2012 | S105: 2013 | T105: 2014 | U105: 2015
B106: Unlevered Free Cash Flow Valuation
B107: €million | D107: 2011 | E107: 2012 | F107: 2013 | G107: 2014 | H107: 2015 | K107: Unlevered Free Cash Flow
B108: Unleverd FCF | D108: 6953.5529 | E108: 6626.0046 | F108: 6406.7941 | G108: 6012.4759 | H108: 5489.2528
B109: PV of UFCF | I109: 31488.08 | K109: Year (t) | Q109: 1 | R109: 2 | S109: 3 | T109: 4 | U109: 5
B110: Terminal Value (TV) | I110: 18655.79
B111: Enterprise Value (EV) | I111: 50143.871 | J111: -0.34048803 | K111: EBITDA | N111: 11350 | O111: 0 | P111: 11350 | Q111: 11943.166 | R111: 12501.638 | S111: 12707.528 | T111: 12673.084 | U111: 12413.911
B112: Equity Value | I112: 36556.338 | J112: -0.4145764
B113: Figure 7: Sanofi scenario 2 DCF valuation | K113: Depreciation & amortization | N113: -5129 | O113: 0 | P113: -5129 | Q113: -5110.505 | R113: -5461.7934 | S113: -5625.0954 | T113: -5643.6876 | U113: -5512.7618
K114: EBIT | N114: 6221 | O114: 2115.2194 | P114: 8336.2194 | Q114: 9577.0422 | R114: 10259.374 | S114: 10287.007 | T114: 9824.507 | U114: 8875.27
K116: Effective tax rate | N116: 0.22 | O116: 0 | P116: 0.22 | Q116: 0.33 | R116: 0.33 | S116: 0.33 | T116: 0.33 | U116: 0.33
K117: EBIT*(1-Tax rate) | N117: 4852.38 | O117: 1649.8711 | P117: 6502.2511 | Q117: 6416.6182 | R117: 6873.7806 | S117: 6892.295 | T117: 6582.4197 | U117: 5946.4309
K119: Depreciation & amortization | N119: 5129 | O119: 3042.8666 | P119: 8171.8666 | Q119: 8465.5724 | R119: 9162.593 | S119: 9708.7602 | T119: 10151.339 | U119: 10489.937
K120: Δ net Working Capital | N120: 315 | O120: 0 | P120: 315 | Q120: 113.09239 | R120: 190.14132 | S120: 0 | T120: -133.98084 | U120: -261.26264
K121: Capex | N121: -3232 | O121: -4665 | P121: -7897 | Q121: -7207.281 | R121: -8010.302 | S121: -8361.5904 | T121: -8458.9975 | U121: -8349.0946
K123: FCF | N123: 6434.38 | O123: NA | P123: 6462.1177 | Q123: 7561.8172 | R123: 7835.9302 | S123: 8239.4648 | T123: 8408.7415 | U123: 8348.5355

Sheet Sensitivity Analysis
B1: 2015 | C1: only for acquisition scenario
A2: Unleverd FCF | B2: 5917.8035
A3: PV of UFCF | B3: 21435.626
A4: TV | B4: 56933.602
A5: EV | B5: 78369.228
A6: WACC | B6: 0.087475329
A7: gEBIT | B7: -0.014916419
C10: €m | F10: Sensitivity Analysis
G11: WACC
D12: =B3+B2*(1+B7)/(B6-B7) -> 78369.228 | E12: =F12-0.01 -> 0.067475329 | F12: =G12-0.01 -> 0.077475329 | G12: =B6 -> 0.087475329 | H12: =G12+0.01 -> 0.097475329 | I12: =H12+0.01 -> 0.10747533
D13: =D14-0.01 -> -0.024916419 | E13: =$B$3+$B$2*(1+$D13)/(E$12-$D13) -> 83890.912 | F13: =$B$3+$B$2*(1+$D13)/(F$12-$D13) -> 77791.271 | G13: =$B$3+$B$2*(1+$D13)/(G$12-$D13) -> 72777.055 | H13: =$B$3+$B$2*(1+$D13)/(H$12-$D13) -> 68582.211 | I13: =$B$3+$B$2*(1+$D13)/(I$12-$D13) -> 65021.069
D14: =B7 -> -0.014916419 | E14: =$B$3+$B$2*(1+$D14)/(E$12-$D14) -> 92189.448 | F14: =$B$3+$B$2*(1+$D14)/(F$12-$D14) -> 84531.424 | G14: =$B$3+$B$2*(1+$D14)/(G$12-$D14) -> 78369.228 | H14: =$B$3+$B$2*(1+$D14)/(H$12-$D14) -> 73303.589 | I14: =$B$3+$B$2*(1+$D14)/(I$12-$D14) -> 69065.725
C15: gEBIT | D15: =D14+0.01 -> -0.0049164188 | E15: =$B$3+$B$2*(1+$D15)/(E$12-$D15) -> 102780.66 | F15: =$B$3+$B$2*(1+$D15)/(F$12-$D15) -> 92907.7 | G15: =$B$3+$B$2*(1+$D15)/(G$12-$D15) -> 85171.936 | H15: =$B$3+$B$2*(1+$D15)/(H$12-$D15) -> 78947.185 | I15: =$B$3+$B$2*(1+$D15)/(I$12-$D15) -> 73830.123
D16: =D15+0.01 -> 0.0050835812 | E16: =$B$3+$B$2*(1+$D16)/(E$12-$D16) -> 116766.94 | F16: =$B$3+$B$2*(1+$D16)/(F$12-$D16) -> 103598.13 | G16: =$B$3+$B$2*(1+$D16)/(G$12-$D16) -> 93625.952 | H16: =$B$3+$B$2*(1+$D16)/(H$12-$D16) -> 85812.448 | I16: =$B$3+$B$2*(1+$D16)/(I$12-$D16) -> 79525.142
D17: =D16+0.01 -> 0.015083581 | E17: =$B$3+$B$2*(1+$D17)/(E$12-$D17) -> 136092.33 | F17: =$B$3+$B$2*(1+$D17)/(F$12-$D17) -> 117715.43 | G17: =$B$3+$B$2*(1+$D17)/(G$12-$D17) -> 104415.6 | H17: =$B$3+$B$2*(1+$D17)/(H$12-$D17) -> 94344.204 | I17: =$B$3+$B$2*(1+$D17)/(I$12-$D17) -> 86452.96
H19: EV | I19: EV adjusted
C20: Sales growth decrease of 0,5% p.a. over the period | H20: =$G$14 -> 78369.228 | I20: 75272.6 | J20: =I20-H20 -> -3096.6283
C21: Sales growth increase of 0,5% p.a. over the period | H21: =$G$14 -> 78369.228 | I21: 81583.826 | J21: =I21-H21 -> 3214.5981
C22: R&D as % of sales decreases of 0,5% p.a. over the period | H22: =$G$14 -> 78369.228 | I22: 78100.08 | J22: =I22-H22 -> -269.14851
C23: R&D as % of sales increases of 0,5% p.a. over the period | H23: =$G$14 -> 78369.228 | I23: 78647.053 | J23: =I23-H23 -> 277.82455

Sheet Multiples
I1: Include D/V to clarify similarity of cap structure?
B2: 2010
B4: Company | C4: Market Cap | D4: EV/Sales | E4: EV/EBITDA | F4: EV/EBIT
B6: Bristol-Myers Squibb Co (BMY US) - Adj Highlights | C6: 44989.52 | D6: 2.0359 | E6: 5.9848 | F6: 6.7416 | H6: Sanofi
B7: Bayer AG (BAYN GR) - Adj Highlights | C7: 45730.214 | D7: 1.5463 | E7: 8.6314 | F7: 19.8744 | I7: Minimum | J7: 25th percentile | K7: Median | L7: 75th percentile | M7: Maximum
B8: AstraZeneca PLC (AZN LN) - Adj Highlights | C8: 64189.672 | D8: 1.8353 | E8: 4.2893 | F8: 5.3122 | H8: EV/Sales | I8: =$D$29 -> 46982779 | J8: =$D$31-$D$29 -> 6471792 | K8: =$D$30-$D$31 -> 2309184 | L8: =$D$32-$D$30 -> 14842584 | M8: =$D$28-$D$32 -> 8747553.6
B9: GlaxoSmithKline PLC (GSK LN) - Adj Highlights | C9: 64433.674 | D9: 2.6117 | E9: 13.4282 | F9: 19.295 | H9: EV/EBITDA | I9: =$E$29 -> 48683555 | J9: =$E$31-$E$29 -> 9953950 | K9: =$E$30-$E$31 -> 9289975 | L9: =$E$32-$E$30 -> 57260750 | M9: =$E$28-$E$32 -> 27221840
B10: Eli Lilly & Co (LLY US) - Adj Highlights | C10: 40406.516 | D10: 1.7593 | E10: 5.1663 | F10: 6.217 | H10: EV/EBIT | I10: =$F$29 -> 33047196 | J10: =$F$31-$F$29 -> 5628760.8 | K10: =$F$30-$F$31 -> 3263536.6 | L10: =$F$32-$F$30 -> 79896925 | M10: =$F$28-$F$32 -> 1802223.7
B11: Sanofi | C11: 62439.4 | H11: DCF | I11: =F47 -> 77449794 | M11: =F48 -> 51592687
B13: Statistics | D13: EV/Sales | E13: EV/EBITDA | F13: EV/EBIT
B14: Maximum | D14: =MAX(D6:D10) -> 2.6117 | E14: =MAX(E6:E10) -> 13.4282 | F14: =MAX(F6:F10) -> 19.8744
B15: Minimum | D15: =MIN(D6:D10) -> 1.5463 | E15: =MIN(E6:E10) -> 4.2893 | F15: =MIN(F6:F10) -> 5.3122
B16: Median | D16: =MEDIAN(D6:D10) -> 1.8353 | E16: =MEDIAN(E6:E10) -> 5.9848 | F16: =MEDIAN(F6:F10) -> 6.7416
B17: 25th percentile | D17: =QUARTILE(D6:D10,1) -> 1.7593 | E17: =QUARTILE(E6:E10,1) -> 5.1663 | F17: =QUARTILE(F6:F10,1) -> 6.217
B18: 75th percentile | D18: =_xlfn.QUARTILE.EXC(D6:D10,3) -> 2.3238 | E18: =_xlfn.QUARTILE.EXC(E6:E10,3) -> 11.0298 | F18: =_xlfn.QUARTILE.EXC(F6:F10,3) -> 19.5847
B19: Average | D19: =AVERAGE(D6:D10) -> 1.9577 | E19: =AVERAGE(E6:E10) -> 7.5 | F19: =AVERAGE(F6:F10) -> 11.48804
B20: Standard Deviation | D20: =_xlfn.STDEV.P(D14:D18) -> 0.39211279 | E20: =_xlfn.STDEV.P(E14:E18) -> 3.591745 | F20: =_xlfn.STDEV.P(F14:F18) -> 6.6981148
B21: Min Point | D21: =D15 -> 1.5463 | E21: =E15 -> 4.2893 | F21: =F15 -> 5.3122
B22: 25th Point | D22: =D17-D15 -> 0.213 | E22: =E17-E15 -> 0.877 | F22: =F17-F15 -> 0.9048
B23: Median Point | D23: =D16-D17 -> 0.076 | E23: =E16-E17 -> 0.8185 | F23: =F16-F17 -> 0.5246
B24: 75th Point | D24: =D18-D16 -> 0.4885 | E24: =E18-E16 -> 5.045 | F24: =F18-F16 -> 12.8431
B25: Maximum Point | D25: =D14-D18 -> 0.2879 | E25: =E14-E18 -> 2.3984 | F25: =F14-F18 -> 0.2897
B27: Sanofi | D27: EV (X*Sales) | E27: EV (X*EBITDA) | F27: EV (X*EBIT)
B28: Maximum | D28: =D14*$C$41 -> 79353893 | E28: =E14*$C$42 -> 152410070 | F28: =F14*$C$43 -> 1.2363864e+08
B29: Minimum | D29: =D15*$C$41 -> 46982779 | E29: =E15*$C$42 -> 48683555 | F29: =F15*$C$43 -> 33047196
B30: Median | D30: =D16*$C$41 -> 55763755 | E30: =E16*$C$42 -> 67927480 | F30: =F16*$C$43 -> 41939494
B31: 25th percentile | D31: =D17*$C$41 -> 53454571 | E31: =E17*$C$42 -> 58637505 | F31: =F17*$C$43 -> 38675957
B32: 75th percentile | D32: =D18*$C$41 -> 70606339 | E32: =E18*$C$42 -> 125188230 | F32: =F18*$C$43 -> 1.2183642e+08
B33: Average | D33: =D19*$C$41 -> 59482757 | E33: =E19*$C$42 -> 85125000 | F33: =F19*$C$43 -> 71467097
B34: Standard Deviation | D34: =D20*$C$41 -> 11913955 | E34: =E20*$C$42 -> 40766306 | F34: =F20*$C$43 -> 41668972
B35: Min Point | D35: =$D$29 -> 46982779 | E35: =$E$29 -> 48683555 | F35: =$F$29 -> 33047196
B36: 25th Point | D36: =$D$31-$D$29 -> 6471792 | E36: =$E$31-$E$29 -> 9953950 | F36: =$F$31-$F$29 -> 5628760.8
B37: Median Point | D37: =$D$30-$D$31 -> 2309184 | E37: =$E$30-$E$31 -> 9289975 | F37: =$F$30-$F$31 -> 3263536.6
B38: 75th Point | D38: =$D$32-$D$30 -> 14842584 | E38: =$E$32-$E$30 -> 57260750 | F38: =$F$32-$F$30 -> 79896925
B39: Maximum Point | D39: =$D$28-$D$32 -> 8747553.6 | E39: =$E$28-$E$32 -> 27221840 | F39: =$F$28-$F$32 -> 1802223.7
B41: Sales | C41: 30384000 | D41: (thousand $)
B42: EBITDA | C42: 11350000 | D42: (thousand $)
B43: EBIT | C43: 6221000 | D43: (thousand $)
B44: EV | C44: 76014000 | D44: (thousand $)
C46: EV/EBIT | D46: EV/EBITDA | E46: EV/Sales | F46: DCF
B47: Max | C47: =F28 -> 1.2363864e+08 | D47: =E28 -> 152410070 | E47: =D28 -> 79353893 | F47: 77449794
B48: Min | C48: =F29 -> 33047196 | D48: =E29 -> 48683555 | E48: =D29 -> 46982779 | F48: 51592687

Sheet Optimum K structure
B2: Estimate the unlevered beta for the firm
B3: Levered Beta of Sanofi | E3: 0.68
B4: Marginal Tax rate | E4: 0.33
B5: Market value of equity | E5: =[4]WACC!D4 -> 62444.25
B6: Market value of debt | E6: =[4]WACC!D5 -> 13587.533
B7: Unlevered Beta | E7: =E3/(1+(1-E4)*E6/E5) -> 0.59347782
B8: market premium | E8: 0.0979
B9: risk free return | E9: 0.0336
B11: Sanofi curent financials | H11: Ratings comparison at current debt ratio
B12: EBITDA | E12: ='[4]Free Cash Flow'!J9 -> 11350 | H12: Current Interest coverage ratio = | K12: =E16/E15 -> 22.13879
B13: D&A | E13: ='[4]Free Cash Flow'!J11 -> -5129 | H13: Rating based upon coverage = | K13: =VLOOKUP(K12,$N$32:$R$46,3,TRUE) -> Aaa/AAA
B14: EBIT | E14: =E12-E13 -> 16479 | H14: Interest rate based upon coverage = | K14: =VLOOKUP(K13,P32:R46,2,FALSE)+E9 -> 0.0396
B15: Interest Expenses | E15: 281 | H15: Current rating for company = | K15: A3/A-
B16: Adjusted EBIT | E16: ='[4]Free Cash Flow'!H12 -> 6221 | H16: Current interest rate on debt = | K16: =VLOOKUP(K15,$P$32:$R$46,2,FALSE)+E9 -> 0.0461
H17: Current Bankruptcy Probability = | K17: =VLOOKUP(K15,$P$32:$R$46,3,FALSE) -> 0.025
B18: Market Value of the firm | E18: =[4]WACC!D6 -> 76031.783 | H18: Cost of bankruptcy = | K18: 0.25
B20: Cost of equity
B21: Debt to Capital Ratio | C21: D/E Ratio | D21: Levered Beta | E21: Cost of Equity
B22: 0 | C22: =B22/(1-B22) -> 0 | D22: =$E$7*(1+(1-$E$4)*C22) -> 0.59347782 | E22: =$E$9+D22*$E$8 -> 0.091701479
B23: 0.1 | C23: =B23/(1-B23) -> 0.11111111 | D23: =$E$7*(1+(1-$E$4)*C23) -> 0.63765895 | E23: =$E$9+D23*$E$8 -> 0.096026811
B24: 0.2 | C24: =B24/(1-B24) -> 0.25 | D24: =$E$7*(1+(1-$E$4)*C24) -> 0.69288536 | E24: =$E$9+D24*$E$8 -> 0.10143348
B25: 0.3 | C25: =B25/(1-B25) -> 0.42857143 | D25: =$E$7*(1+(1-$E$4)*C25) -> 0.76389074 | E25: =$E$9+D25*$E$8 -> 0.1083849
B26: 0.4 | C26: =B26/(1-B26) -> 0.66666667 | D26: =$E$7*(1+(1-$E$4)*C26) -> 0.85856458 | E26: =$E$9+D26*$E$8 -> 0.11765347
B27: 0.5 | C27: =B27/(1-B27) -> 1 | D27: =$E$7*(1+(1-$E$4)*C27) -> 0.99110796 | E27: =$E$9+D27*$E$8 -> 0.13062947
B28: 0.6 | C28: =B28/(1-B28) -> 1.5 | D28: =$E$7*(1+(1-$E$4)*C28) -> 1.189923 | E28: =$E$9+D28*$E$8 -> 0.15009346
B29: 0.7 | C29: =B29/(1-B29) -> 2.3333333 | D29: =$E$7*(1+(1-$E$4)*C29) -> 1.5212815 | E29: =$E$9+D29*$E$8 -> 0.18253346 | N29: For large non-financial service companies with market cap > $ 5 billion
B30: 0.8 | C30: =B30/(1-B30) -> 4 | D30: =$E$7*(1+(1-$E$4)*C30) -> 2.1839984 | E30: =$E$9+D30*$E$8 -> 0.24741344 | N30: If interest coverage ratio is
B31: 0.9 | C31: =B31/(1-B31) -> 9 | D31: =$E$7*(1+(1-$E$4)*C31) -> 4.1721491 | E31: =$E$9+D31*$E$8 -> 0.44205339 | N31: greater than | O31: ≤ to | P31: Rating is | Q31: Spread is | R31: Bankruptcy Probability
N32: -100000 | O32: 0.199999 | P32: D2/D | Q32: 0.14 | R32: 1
B33: Cost of debt | N33: 0.2 | O33: 0.649999 | P33: C2/C | Q33: 0.105 | R33: 0.85
B34: D/(D+E) | C34: 0 | D34: 0.1 | E34: 0.2 | F34: 0.3 | G34: 0.4 | H34: 0.5 | I34: 0.6 | J34: 0.7 | K34: 0.8 | L34: 0.9 | N34: 0.65 | O34: 0.799999 | P34: Ca2/CC | Q34: 0.08 | R34: 0.7
B35: D/E | C35: =C34/(1-C34) -> 0 | D35: =D34/(1-D34) -> 0.11111111 | E35: =E34/(1-E34) -> 0.25 | F35: =F34/(1-F34) -> 0.42857143 | G35: =G34/(1-G34) -> 0.66666667 | H35: =H34/(1-H34) -> 1 | I35: =I34/(1-I34) -> 1.5 | J35: =J34/(1-J34) -> 2.3333333 | ... L35: =L34/(1-L34) -> 9 | N35: 0.8 | O35: 1.249999 | P35: Caa/CCC | Q35: 0.065 | R35: 0.5901
B36: $ Debt | C36: =C34*$E$18 -> 0 | D36: =D34*$E$18 -> 7603.1783 | E36: =E34*$E$18 -> 15206.357 | F36: =F34*$E$18 -> 22809.535 | G36: =G34*$E$18 -> 30412.713 | H36: =H34*$E$18 -> 38015.891 | I36: =I34*$E$18 -> 45619.07 | J36: =J34*$E$18 -> 53222.248 | ... L36: =L34*$E$18 -> 68428.605 | N36: 1.25 | O36: 1.499999 | P36: B3/B- | Q36: 0.055 | R36: 0.45
N37: 1.5 | O37: 1.749999 | P37: Ba1/BB+ | Q37: 0.045 | R37: 0.1
B38: EBITDA | C38: =$E$12 -> 11350 | D38: =$E$12 -> 11350 | E38: =$E$12 -> 11350 | F38: =$E$12 -> 11350 | G38: =$E$12 -> 11350 | H38: =$E$12 -> 11350 | I38: =$E$12 -> 11350 | J38: =$E$12 -> 11350 | ... L38: =$E$12 -> 11350 | N38: 1.75 | O38: 1.999999 | P38: Ba2/BB | Q38: 0.0375 | R38: 0.1663
B39: D&A | C39: =$E$13 -> -5129 | D39: =$E$13 -> -5129 | E39: =$E$13 -> -5129 | F39: =$E$13 -> -5129 | G39: =$E$13 -> -5129 | H39: =$E$13 -> -5129 | I39: =$E$13 -> -5129 | J39: =$E$13 -> -5129 | ... L39: =$E$13 -> -5129 | N39: 2 | O39: 2.2499999 | P39: B1/B+ | Q39: 0.03 | R39: 0.25
B40: Ajusted EBIT | C40: =$E$16 -> 6221 | D40: =$E$16 -> 6221 | E40: =$E$16 -> 6221 | F40: =$E$16 -> 6221 | G40: =$E$16 -> 6221 | H40: =$E$16 -> 6221 | I40: =$E$16 -> 6221 | J40: =$E$16 -> 6221 | ... L40: =$E$16 -> 6221 | N40: 2.25 | O40: 2.49999 | P40: B2/B | Q40: 0.025 | R40: 0.368
B41: Interest | C41: 0 | D41: =D36*3.96% -> 301.08586 | E41: =E36*3.96% -> 602.17172 | F41: =F36*4.16% -> 948.87665 | G41: =G36*4.46% -> 1356.407 | H41: =H36*4.61% -> 1752.5326 | I41: =I36*4.96% -> 2262.7059 | J41: =J36*8.86% -> 4715.4912 | K41: =K36*9.86% -> 5997.387 | L41: =L36*K45 -> 6747.0604 | N41: 2.5 | O41: 2.999999 | P41: Baa2/BBB | Q41: 0.016 | R41: 0.0754
N42: 3 | O42: 4.249999 | P42: A3/A- | Q42: 0.0125 | R42: 0.025
B43: Pre-tax Int. Cov | C43: infinite | D43: =D40/D41 -> 20.66188 | E43: =E40/E41 -> 10.33094 | F43: =F40/F41 -> 6.5561735 | G43: =G40/G41 -> 4.5863815 | H43: =H40/H41 -> 3.54972 | I43: =I40/I41 -> 2.7493631 | J43: =J40/J41 -> 1.3192687 | K43: =K40/K41 -> 1.0372851 | L43: =L40/L41 -> 0.92203117 | N43: 4.25 | O43: 5.499999 | P43: A2/A | Q43: 0.011 | R43: 0.0066
B44: Likely Rating | C44: Aaa/AAA | D44: =VLOOKUP(D43,$N$32:$R$46,3,TRUE) -> Aaa/AAA | E44: =VLOOKUP(E43,$N$32:$R$46,3,TRUE) -> Aaa/AAA | F44: =VLOOKUP(F43,$N$32:$R$46,3,TRUE) -> Aa2/AA | G44: =VLOOKUP(G43,$N$32:$R$46,3,TRUE) -> A2/A | H44: =VLOOKUP(H43,$N$32:$R$46,3,TRUE) -> A3/A- | I44: =VLOOKUP(I43,$N$32:$R$46,3,TRUE) -> Baa2/BBB | J44: =VLOOKUP(J43,$N$32:$R$46,3,TRUE) -> B3/B- | K44: =VLOOKUP(K43,$N$32:$R$46,3,TRUE) -> Caa/CCC | L44: =VLOOKUP(L43,$N$32:$R$46,3,TRUE) -> Caa/CCC | N44: 5.5 | O44: 6.499999 | P44: A1/A+ | Q44: 0.01 | R44: 0.006
B45: Pre-tax cost of debt | C45: =$E$9+VLOOKUP(C44,$P$32:$Q$46,2,FALSE) -> 0.0396 | D45: =$E$9+VLOOKUP(D44,$P$32:$Q$46,2,FALSE) -> 0.0396 | E45: =$E$9+VLOOKUP(E44,$P$32:$Q$46,2,FALSE) -> 0.0396 | F45: =$E$9+VLOOKUP(F44,$P$32:$Q$46,2,FALSE) -> 0.0416 | G45: =$E$9+VLOOKUP(G44,$P$32:$Q$46,2,FALSE) -> 0.0446 | H45: =$E$9+VLOOKUP(H44,$P$32:$Q$46,2,FALSE) -> 0.0461 | I45: =$E$9+VLOOKUP(I44,$P$32:$Q$46,2,FALSE) -> 0.0496 | J45: =$E$9+VLOOKUP(J44,$P$32:$Q$46,2,FALSE) -> 0.0886 | ... L45: =$E$9+VLOOKUP(L44,$P$32:$Q$46,2,FALSE) -> 0.0986 | N45: 6.5 | O45: 8.499999 | P45: Aa2/AA | Q45: 0.008 | R45: 0.0051
B46: Probability of Bankruptcy | C46: =VLOOKUP(C44,$P$32:$R$46,3,FALSE) -> 0.0007 | D46: =VLOOKUP(D44,$P$32:$R$46,3,FALSE) -> 0.0007 | E46: =VLOOKUP(E44,$P$32:$R$46,3,FALSE) -> 0.0007 | F46: =VLOOKUP(F44,$P$32:$R$46,3,FALSE) -> 0.0051 | G46: =VLOOKUP(G44,$P$32:$R$46,3,FALSE) -> 0.0066 | H46: =VLOOKUP(H44,$P$32:$R$46,3,FALSE) -> 0.025 | I46: =VLOOKUP(I44,$P$32:$R$46,3,FALSE) -> 0.0754 | J46: =VLOOKUP(J44,$P$32:$R$46,3,FALSE) -> 0.45 | ... L46: =VLOOKUP(L44,$P$32:$R$46,3,FALSE) -> 0.5901 | N46: 8.5 | O46: 100000 | P46: Aaa/AAA | Q46: 0.006 | R46: 0.0007
B47: After-tax cost of debt | C47: =C45*(1-$E$4) -> 0.026532 | D47: =D45*(1-$E$4) -> 0.026532 | E47: =E45*(1-$E$4) -> 0.026532 | F47: =F45*(1-$E$4) -> 0.027872 | G47: =G45*(1-$E$4) -> 0.029882 | H47: =H45*(1-$E$4) -> 0.030887 | I47: =I45*(1-$E$4) -> 0.033232 | J47: =J45*(1-$E$4) -> 0.059362 | ... L47: =L45*(1-$E$4) -> 0.066062
B48: WACC | C48: =$E$5/($E$5+$E$6)*E22+$E$5/($E$5+$E$6)*C47 -> 0.09710414 | D48: =$E$5/($E$5+$E$6)*E23+$E$5/($E$5+$E$6)*D47 -> 0.1006565 | E48: =$E$5/($E$5+$E$6)*E24+$E$5/($E$5+$E$6)*E47 -> 0.10509695 | F48: =$E$5/($E$5+$E$6)*E25+$E$5/($E$5+$E$6)*F47 -> 0.11190662 | G48: =$E$5/($E$5+$E$6)*E26+$E$5/($E$5+$E$6)*G47 -> 0.12116962 | H48: =$E$5/($E$5+$E$6)*E27+$E$5/($E$5+$E$6)*H47 -> 0.13265209 | I48: =$E$5/($E$5+$E$6)*E2824+$E$5/($E$5+$E$6)*I47 -> 0.027293156 | J48: =$E$5/($E$5+$E$6)*E29+$E$5/($E$5+$E$6)*J47 -> 0.19866666 | K48: =$E$5/($E$5+$E$6)*E30+$E$5/($E$5+$E$6)*K47 -> 0.25745469 | L48: =$E$5/($E$5+$E$6)*E31+$E$5/($E$5+$E$6)*L47 -> 0.41731081 | N48: source: http://pages.stern.nyu.edu/~adamodar/New_Home_Page/datafile/ratings.htm
B49: Unlev. Firm Value | C49: =$E$18-$E$6*$E$4+$E$18*$K$17*$K$18 -> 72023.096 | D49: =$E$18-$E$6*$E$4+$E$18*$K$17*$K$18 -> 72023.096 | E49: =$E$18-$E$6*$E$4+$E$18*$K$17*$K$18 -> 72023.096 | F49: =$E$18-$E$6*$E$4+$E$18*$K$17*$K$18 -> 72023.096 | G49: =$E$18-$E$6*$E$4+$E$18*$K$17*$K$18 -> 72023.096 | H49: =$E$18-$E$6*$E$4+$E$18*$K$17*$K$18 -> 72023.096 | I49: =$E$18-$E$6*$E$4+$E$18*$K$17*$K$18 -> 72023.096 | J49: =$E$18-$E$6*$E$4+$E$18*$K$17*$K$18 -> 72023.096 | ... L49: =$E$18-$E$6*$E$4+$E$18*$K$17*$K$18 -> 72023.096
B50: adjusted marginal tax rate | C50: =E4 -> 0.33 | D50: =E4 -> 0.33 | E50: =E4 -> 0.33 | F50: =$E$4 -> 0.33 | G50: =$E$4 -> 0.33 | H50: =$E$4 -> 0.33 | I50: =$E$4 -> 0.33 | J50: =$E$4 -> 0.33 | K50: =$E$4 -> 0.33 | L50: =L40*E4/L41 -> 0.30427029
B51: Tax Benefits | C51: =C41*C50 -> 0 | D51: =D41*D50 -> 99.358334 | E51: =E41*E50 -> 198.71667 | F51: =F41*F50 -> 313.12929 | G51: =G41*G50 -> 447.61431 | H51: =H41*H50 -> 578.33576 | I51: =I41*I50 -> 746.69293 | J51: =J41*J50 -> 1556.1121 | K51: =K41*K50 -> 1979.1377 | L51: =L40*E4 -> 2052.93
B52: Bankruptcy Cost | C52: =C46*$K$18*(C49+C51) -> 12.604042 | D52: =D46*$K$18*(D49+D51) -> 12.621429 | E52: =E46*$K$18*(E49+E51) -> 12.638817 | F52: =F46*$K$18*(F49+F51) -> 92.228687 | G52: =G46*$K$18*(G49+G51) -> 119.57667 | H52: =H46*$K$18*(H49+H51) -> 453.75895 | I52: =I46*$K$18*(I49+I51) -> 1371.7105 | J52: =J46*$K$18*(J49+J51) -> 8277.6609 | K52: =K46*$K$18*(K49+K51) -> 10917.179 | L52: =L46*$K$18*(L49+L50) -> 10625.252
B53: Levered Firm Value | C53: =C49+C51-C52 -> 72010.492 | D53: =D49+D51-D52 -> 72109.833 | E53: =E49+E51-E52 -> 72209.174 | F53: =F49+F51-F52 -> 72243.996 | G53: =G49+G51-G52 -> 72351.133 | H53: =H49+H51-H52 -> 72147.673 | I53: =I49+I51-I52 -> 71398.078 | J53: =J49+J51-J52 -> 65301.547 | K53: =K49+K51-K52 -> 63085.054 | L53: =L49+L50-L52 -> 61398.148
