Workbook
Name ScenarioSelection: '[1]Table of Contents'!$H$4:$H$7
Name ScenarioSelection: '[2]Table of Contents'!$J$1:$J$3
Name ScenarioSelection: '[1]Table of Contents'!$H$4:$H$7
Name ScenarioSelection: '[3]Table of Contents'!$H$9:$H$11
Name ScenarioSelection: '[4]Cover Sheet'!$B$1:$B$3
Name ScenarioSelection: 'Table of Contents'!$J$1:$J$3

Sheet Table of Contents
I1: Scenario Selection: | J1: Scenario 1: Base Case
A2: NIKE Inc (NKE US) - Table of Contents | J2: Scenario 2: Bull Case
J3: Scenario 3: Bear Case
A4: Table of Contents | D4: Click here:
A6: Key Results: | B6: Table of Contents | C6: >> | D6: Table of Contents'!A1
B7: Summary of Results | C7: >> | D7: Summary!A1
B8: Business Opportunity | C8: >> | D8: Business Opportunity'!A1
A10: Calculations: | B10: Free Cash Flows | C10: >> | D10: Free Cash Flows'!A1
B11: Beta Calculation | C11: >> | D11: Beta Calculation'!A1
B12: Cost of Equity | C12: >> | D12: Cost of Equity'!A1
B13: Cost of Debt | C13: >> | D13: Cost of Debt'!A1
B14: WACC | C14: >> | D14: WACC!A1
B15: DCF | C15: >> | D15: DCF!A1
B16: APV | C16: >> | D16: APV!A1
B17: Trading Multiples | C17: >> | D17: Trading Multiples'!A1
A19: Supporting Calculations: | B19: Growth Scenarios | C19: >> | D19: Growth Scenarios'!A1
B20: Marginal Tax Rate | C20: >> | D20: Marginal Tax Rate'!A1
B21: Cost of Debt per Bond | C21: >> | D21: Corporate Bond 1'!A1
A23: Appendices: | B23: Balance Sheet | C23: >> | D23: Balance Sheet'!A1
B24: Income Statement | C24: >> | D24: Income Statement'!A1
B25: Cash Flow Statement | C25: >> | D25: Cash Flow Statement '!A1
B26: Share Prices | C26: >> | D26: Share Prices'!A1
B27: SPX | C27: >> | D27: SPX!A1
B28: Trading Multiples Bloomberg | C28: >> | D28: Trading Multiples Bloomberg'!A1

Sheet Summary
A2: NIKE Inc (NKE US) - Summary of Results
A4: Method of Calculating Expected Enterprise Value | C4: Expected Enterprise Value
A6: In Million USD | C6: Min | D6: 25th | E6: Median | F6: 75th | G6: Max | H6: Min Point | I6: 25th Point | J6: Median Point | K6: 75th Point | L6: Max Point
A8: Adjusted Present Value | C8: =MIN(C16:J16) -> 70813.15 | D8: =_xlfn.QUARTILE.EXC(C16:K16,1) -> 80857.012 | E8: =_xlfn.QUARTILE.EXC(C16:K16,2) -> 91411.225 | F8: =_xlfn.QUARTILE.EXC(C16:K16,3) -> 109169.7 | G8: =MAX(C16:K16) -> 124813.49 | H8: =C8 -> 70813.15 | I8: =D8-C8 -> 10043.863 | J8: =E8-D8 -> 10554.213 | K8: =F8-E8 -> 17758.477 | L8: =G8-F8 -> 15643.788
A9: Discounted Cash Flow | C9: =MIN(C15:K15) -> 67027.38 | D9: =_xlfn.QUARTILE.EXC(C15:K15,1) -> 79496.265 | E9: =_xlfn.QUARTILE.EXC(C15:K15,2) -> 94426.94 | F9: =_xlfn.QUARTILE.EXC(C15:K15,3) -> 116407.28 | G9: =MAX(C15:K15) -> 136587.54 | H9: =C9 -> 67027.38 | I9: =D9-C9 -> 12468.885 | J9: =E9-D9 -> 14930.675 | K9: =F9-E9 -> 21980.34 | L9: =G9-F9 -> 20180.26
A10: Multiples Based on Assets | C10: =MIN('Trading Multiples'!J46:J54) -> 23420.899 | D10: =_xlfn.QUARTILE.EXC('Trading Multiples'!J46:J53,1) -> 29877.297 | E10: ='Trading Multiples'!J55 -> 42250.429 | F10: =_xlfn.QUARTILE.EXC('Trading Multiples'!J46:J54,3) -> 75465.321 | G10: =MAX('Trading Multiples'!J46:J54) -> 88060.992 | H10: =C10 -> 23420.899 | I10: =D10-C10 -> 6456.3976 | J10: =E10-D10 -> 12373.132 | K10: =F10-E10 -> 33214.892 | L10: =G10-F10 -> 12595.672
A11: Price Multiples Based on Cash Flows (1) | C11: =MIN('Trading Multiples'!I65:I74) -> 57393.359 | D11: =_xlfn.QUARTILE.EXC('Trading Multiples'!I65:I73,1) -> 83043.973 | E11: ='Trading Multiples'!I74 -> 98271.31 | F11: =_xlfn.QUARTILE.EXC('Trading Multiples'!I65:I73,3) -> 160056.7 | G11: =MAX('Trading Multiples'!I65:I72) -> 187449.75 | H11: =C11 -> 57393.359 | I11: =D11-C11 -> 25650.613 | J11: =E11-D11 -> 15227.337 | K11: =F11-E11 -> 61785.39 | L11: =G11-F11 -> 27393.053
A12: Price Multiples Based on Cash Flows (2) | C12: =MIN('Trading Multiples'!J65:J73) -> 45327.081 | D12: =_xlfn.QUARTILE.EXC('Trading Multiples'!J65:J73,1) -> 65732.888 | E12: =_xlfn.QUARTILE.EXC('Trading Multiples'!J65:J73,2) -> 85843.569 | F12: =_xlfn.QUARTILE.EXC('Trading Multiples'!J65:J73,3) -> 126347.61 | G12: =MAX('Trading Multiples'!J65:J72) -> 148790.71 | H12: =C12 -> 45327.081 | I12: =D12-C12 -> 20405.806 | J12: =E12-D12 -> 20110.681 | K12: =F12-E12 -> 40504.04 | L12: =G12-F12 -> 22443.104
A13: Value Multiples Based on Cash Flows | C13: =MIN('Trading Multiples'!H27:H35) -> 39541.859 | D13: =_xlfn.QUARTILE.EXC('Trading Multiples'!H27:H35,1) -> 58723.315 | E13: ='Trading Multiples'!H36 -> 76319.658 | F13: =_xlfn.QUARTILE.EXC('Trading Multiples'!H27:H35,3) -> 85167.465 | G13: =MAX('Trading Multiples'!H27:H35) -> 96809.615 | H13: =C13 -> 39541.859 | I13: =D13-C13 -> 19181.457 | J13: =E13-D13 -> 17596.342 | K13: =F13-E13 -> 8847.807 | L13: =G13-F13 -> 11642.151
A15: Possible values DCF | C15: 94426.94 | D15: 124160.3 | E15: 76066.06 | F15: 103643.41 | G15: 136587.54 | H15: 83309.37 | I15: 82926.47 | J15: 108654.26 | K15: 67027.38
A16: Possible values APV | C16: 70813.15 | D16: 79180.65 | E16: 85886.1 | F16: 86089.77 | G16: 96732.68 | H16: 105261.88 | I16: 110472.31 | J16: 124813.49
A17: Football Field Expected Enterprise Value
A44: Enterprise Value Based on Discounted Cash Flows
A46: In Million USD | C46: PV Terminal Value | D46: PV Cash Flows | E46: Enterprise Value
A48: Base Case / Base Case | B48: Base/Base | C48: 72210.685 | D48: 21616.73 | E48: =D48+C48 -> 93827.415
A49: Base Case / Bull Case | B49: Base/Bull | C49: 100812.78 | D49: 22474.29 | E49: =D49+C49 -> 123287.07
A50: Base Case / Bear Case | B50: Base/Bear | C50: 54805.79 | D50: 20809.24 | E50: =D50+C50 -> 75615.03
A52: Bull Case / Base Case | B52: Bull/Base | C52: 80077 | D52: 22902.31 | E52: =D52+C52 -> 102979.31
A53: Bull Case / Bull Case | B53: Bull/Bull | C53: 111794.88 | D53: 23824.96 | E53: =D53+C53 -> 135619.84
A54: Bull Case / Bear Case | B54: Bull/Bear | C54: 60776.1 | D54: 22033.93 | E54: =D54+C54 -> 82810.03
A56: Bear Case / Base Case | B56: Bear/Base | C56: 62398.72 | D56: 20008.8 | E56: =D56+C56 -> 82407.52
A57: Bear Case / Bull Case | B57: Bear/Bull | C57: 87114.37 | D57: 20784.52 | E57: =D57+C57 -> 107898.89
A58: Bear Case / Bear Case | B58: Bear/Bear | C58: 47358.8 | D58: 19277.86 | E58: =D58+C58 -> 66636.66
A61: Discounted Cash Flow Method
A84: Enterprise Value based on Adjusted Present Value
A86: In Million USD | C86: PV Terminal Value | D86: PV Cash Flows | E86: PV Tax Shield | F86: Cost of Fin. Distress | G86: APV | I86: PV Terminal Value | J86: PV Cash Flows | K86: PV Tax Shield | L86: Cost of Fin. Distress | M86: APV
A88: Base Case / Base Case | C88: 72210.685 | D88: 21616.73 | E88: 9289.19 | F88: 6383.93 | G88: 96732.68 | H88: Base/Base | I88: 72210.685 | J88: 21616.73 | K88: 9289.19 | L88: 6383.93 | M88: 96732.68
A89: Base Case / Bull Case | C89: 100812.78 | D89: 22474.29 | E89: 9914.76 | F89: 8388.34 | G89: 124813.49 | H89: Base/Bull | I89: 100812.78 | J89: 22474.29 | K89: 9914.76 | L89: 8388.34 | M89: 124813.49
A90: Base Case / Bear Case | C90: 54805.79 | D90: 20809.24 | E90: 8710.4 | F90: 5144.78 | G90: 79180.65 | H90: Base/Bear | I90: 54805.79 | J90: 20809.24 | K90: 8710.4 | L90: 5144.78 | M90: 79180.65
A92: Bull Case / Base Case | C92: 80077 | D92: 22902.31 | E92: 9289.19 | F92: 7006.62 | G92: 105261.88 | H92: Bull/Base | I92: 80077 | J92: 22902.31 | K92: 9289.19 | L92: 7006.62 | M92: 105261.88
A93: Bull Case / Bull Case | C93: 111794.88 | D93: 23824.96 | E93: 9914.76 | F93: 9227.45 | G93: 136307.15 | H93: Bull/Bull | I93: 111794.88 | J93: 23824.96 | K93: 9914.76 | L93: 9227.45 | M93: 136307.15
A94: Bull Case / Bear Case | C94: 60776.1 | D94: 22033.93 | E94: 8710.4 | F94: 5634.32 | G94: 85886.1 | H94: Bull/Bear | I94: 60776.1 | J94: 22033.93 | K94: 8710.4 | L94: 5634.32 | M94: 85886.1
A96: Bear Case / Base Case | C96: 62398.72 | D96: 20008.8 | E96: 9289.19 | F96: 5606.93 | G96: 86089.77 | H96: Bear/Base | I96: 62398.72 | J96: 20008.8 | K96: 9289.19 | L96: 5606.93 | M96: 86089.77
A97: Bear Case / Bull Case | C97: 87114.37 | D97: 20784.52 | E97: 9914.76 | F97: 7341.34 | G97: 110472.31 | H97: Bear/Bull | I97: 87114.37 | J97: 20784.52 | K97: 9914.76 | L97: 7341.34 | M97: 110472.31
A98: Bear Case / Bear Case | C98: 47358.8 | D98: 19277.86 | E98: 8710.4 | F98: 4533.9 | G98: 70813.15 | H98: Bear/Bear | I98: 47358.8 | J98: 19277.86 | K98: 8710.4 | L98: 4533.9 | M98: 70813.15
A101: Adjusted Present Value Method

Sheet Business Opportunity
A2: NIKE Inc (NKE US) - Business Opportunity: Optimization of Capital Structure
A4: OPTIMIZATION CASE 1 | D4: OPTIMIZATION CASE 2 | G4: Summary of Results:
H5: =CONCATENATE("D/V: ",ROUND(WACC!B8*100,2),"%") -> D/V: 3,84% | I5: D/V: 5% | J5: D/V: 7%
G6: PV terminal value | H6: =APV!I29 -> 72210.685 | I6: =B36 -> 72210.685 | J6: =E36 -> 72210.685
A7: Total Capital terminal year | B7: ='Cost of Debt'!R33 -> 98166.089 | D7: Total Capital terminal year | E7: ='Cost of Debt'!R33 -> 98166.089 | G7: PV TS | H7: =APV!I30 -> 9289.1911 | I7: =B17 -> 20422.459 | J7: =E17 -> 28591.442
A8: Debt Ratio terminal year | B8: 0.05 | D8: Debt Ratio terminal year | E8: 0.07 | G8: C FD | H8: =APV!I31 -> 6383.9323 | I8: =B26 -> 6383.9323 | J8: =E26 -> 7170.0145
G9: PV TS - C FD | H9: =H7-H8 -> 2905.2588 | I9: =I7-I8 -> 14038.527 | J9: =J7-J8 -> 21421.428
A10: Present Value of Tax Shield | D10: Present Value of Tax Shield | G10: Enterprise Value | H10: =APV!I33 -> 96732.676 | I10: =B38 -> 107865.94 | J10: =E38 -> 115248.85
A12: Perpetuity growth rate | B12: =APV!B21 -> 0.0302 | D12: Perpetuity growth rate | E12: =APV!B21 -> 0.0302
A13: Discount factor | B13: =APV!B22 -> 0.63670591 | D13: Discount factor | E13: =APV!B22 -> 0.63670591
A14: Terminal year debt balance | B14: =B7*B8 -> 4908.3045 | D14: Terminal year debt balance | E14: =E7*E8 -> 6871.6262
A15: Terminal value of tax shield | B15: ='Marginal Tax Rate'!K18*B14*'Cost of Equity'!N12*(1+'Business Opportunity'!B12)/('Cost of Equity'!N12-'Business Opportunity'!B12)^2 -> 32075.183 | D15: Terminal value of tax shield | E15: ='Marginal Tax Rate'!K18*E14*'Cost of Equity'!N12*(1+'Business Opportunity'!E12)/('Cost of Equity'!N12-'Business Opportunity'!E12)^2 -> 44905.257
A17: Present value of tax shield (PVTS) | B17: =B15*B13 -> 20422.459 | D17: Present value of tax shield (PVTS) | E17: =E15*E13 -> 28591.442
A19: Costs of Financial Distress | D19: Costs of Financial Distress
A21: =APV!A28 -> q | B21: =APV!B28 -> 1.635 | D21: =A21 -> q | E21: =2.01 -> 2.01
A22: =APV!A29 -> ϕ | B22: =APV!B29 -> 16.5 | D22: =A22 -> ϕ | E22: =APV!B29 -> 16.5
A23: =APV!A30 -> rF | B23: =APV!B30 -> 2.33 | D23: =A23 -> rF | E23: =APV!B30 -> 2.33
A24: =APV!A31 -> Φ | B24: =APV!B31 -> 6.8039092 | D24: =A24 -> Φ | E24: =E21/(E21+E23)*E22 -> 7.6417051
A26: Costs of Financial Distress (CFD) | B26: =B24*(APV!I29+SUM(APV!I23:M23))/100 -> 6383.9323 | D26: Costs of Financial Distress (CFD) | E26: =E24*(APV!I29+SUM(APV!I23:M23))/100 -> 7170.0145
A28: PVTS - CFD | B28: =B17-B26 -> 14038.527 | D28: PVTS - CFD | E28: =E17-E26 -> 21421.428
D29: Enterprise Value
A30: rA | B30: =APV!I21 -> 0.094491073 | D30: rA | E30: =APV!I21 -> 0.094491073
A32: Free cash flow terminal year | B32: ='Free Cash Flows'!Q15 -> 6600.064 | D32: Free cash flow terminal year | E32: ='Free Cash Flows'!Q15 -> 6600.064
A33: Perpetuity growth rate | B33: =DCF!B19 -> 0.0343 | D33: Perpetuity growth rate | E33: =B33 -> 0.0343
A34: Terminal Value | B34: =B32*(1+B33)/(B30-B33) -> 113412.93 | D34: Terminal Value | E34: =E32*(1+E33)/(E30-E33) -> 113412.93
A35: Discount Factor | B35: =1/((1+B30)^5) -> 0.63670591 | D35: Discount Factor | E35: =1/((1+E30)^5) -> 0.63670591
A36: PV of Terminal Value | B36: =B34*B35 -> 72210.685 | D36: PV of Terminal Value | E36: =E34*E35 -> 72210.685
A38: Enterprise Value | B38: =B36+SUM(APV!I23:M23)+B28 -> 107865.94 | D38: Enterprise Value | E38: =E36+SUM(APV!I23:M23)+E28 -> 115248.85

Sheet Free Cash Flows
A2: NIKE Inc (NKE US) - Free Cash Flow Calculation
M4: Scenario 1: Base Case | S4: Scenario 2: Bull Case | Y4: Scenario 3: Bear Case
A6: In Millions of USD | B6: FY 2008 | C6: FY 2009 | D6: FY 2010 | E6: FY 2011 | F6: FY 2012 | G6: FY 2013 | H6: FY 2014 | I6: FY 2015 | J6: FY 2016 | K6: FY 2017 | M6: FY 2018E | N6: FY 2019E | O6: FY 2020E | P6: FY 2021E | Q6: FY 2022E | S6: FY 2018E | T6: FY 2019E | U6: FY 2020E | V6: FY 2021E | W6: FY 2022E | Y6: FY 2018E | Z6: FY 2019E | AA6: FY 2020E | AB6: FY 2021E | AC6: FY 2022E
A8: Tax Rate Tc | C8: ='Marginal Tax Rate'!C18 -> 0.29110854 | D8: ='Marginal Tax Rate'!D18 -> 0.29110854 | E8: ='Marginal Tax Rate'!E18 -> 0.29296488 | F8: ='Marginal Tax Rate'!F18 -> 0.29232702 | G8: ='Marginal Tax Rate'!G18 -> 0.29424393 | H8: ='Marginal Tax Rate'!H18 -> 0.29373906 | I8: ='Marginal Tax Rate'!I18 -> 0.29361558 | J8: ='Marginal Tax Rate'!J18 -> 0.29248053 | K8: ='Marginal Tax Rate'!K18 -> 0.29137263 | M8: =$K$8 -> 0.29137263 | N8: =$K$8 -> 0.29137263 | O8: =$K$8 -> 0.29137263 | P8: =$K$8 -> 0.29137263 | Q8: =$K$8 -> 0.29137263 | S8: =$K$8 -> 0.29137263 | T8: =$K$8 -> 0.29137263 | U8: =$K$8 -> 0.29137263 | V8: =$K$8 -> 0.29137263 | W8: =$K$8 -> 0.29137263 | Y8: =$K$8 -> 0.29137263 | Z8: =$K$8 -> 0.29137263 | AA8: =$K$8 -> 0.29137263 | AB8: =$K$8 -> 0.29137263 | AC8: =$K$8 -> 0.29137263
A9: Operating Profit | B9: ='Income Statement'!B12 -> 2433.7 | C9: ='Income Statement'!C12 -> 1858.5 | D9: ='Income Statement'!D12 -> 2474 | E9: ='Income Statement'!E12 -> 2815 | F9: ='Income Statement'!F12 -> 3040 | G9: ='Income Statement'!G12 -> 3254 | H9: ='Income Statement'!H12 -> 3680 | I9: ='Income Statement'!I12 -> 4175 | ... K9: ='Income Statement'!K12 -> 4749 | M9: ='Growth Scenarios'!M24 -> 5336.3817 | N9: ='Growth Scenarios'!N24 -> 5747.495 | O9: ='Growth Scenarios'!O24 -> 6190.2026 | P9: ='Growth Scenarios'!P24 -> 6666.9256 | Q9: ='Growth Scenarios'!Q24 -> 7180.27 | S9: ='Growth Scenarios'!M54 -> 5485.9713 | T9: ='Growth Scenarios'!N54 -> 6035.4972 | U9: ='Growth Scenarios'!O54 -> 6639.8551 | V9: ='Growth Scenarios'!P54 -> 7304.4906 | W9: ='Growth Scenarios'!Q54 -> 8035.3869 | Y9: ='Growth Scenarios'!M84 -> 5186.792 | Z9: ='Growth Scenarios'!N84 -> 5395.1314 | AA9: ='Growth Scenarios'!O84 -> 5611.6371 | AB9: ='Growth Scenarios'!P84 -> 5836.6169 | AC9: ='Growth Scenarios'!Q84 -> 6070.3894
A10: Depreciation | B10: ='Income Statement'!B43 -> 303.6 | C10: ='Income Statement'!C43 -> 335 | D10: ='Income Statement'!D43 -> 323.7 | E10: ='Income Statement'!E43 -> 335 | F10: ='Income Statement'!F43 -> 373 | G10: ='Income Statement'!G43 -> 438 | H10: ='Income Statement'!H43 -> 518 | I10: ='Income Statement'!I43 -> 606 | ... K10: ='Income Statement'!K43 -> 706 | M10: ='Growth Scenarios'!M23*-1 -> 757.57585 | N10: ='Growth Scenarios'!N23*-1 -> 824.14156 | O10: ='Growth Scenarios'!O23*-1 -> 896.55617 | P10: ='Growth Scenarios'!P23*-1 -> 975.33361 | Q10: ='Growth Scenarios'!Q23*-1 -> 1061.033 | S10: ='Growth Scenarios'!M53*-1 -> 778.46745 | T10: ='Growth Scenarios'!N53*-1 -> 870.22285 | U10: ='Growth Scenarios'!O53*-1 -> 972.79316 | V10: ='Growth Scenarios'!P53*-1 -> 1087.4531 | W10: ='Growth Scenarios'!Q53*-1 -> 1215.6276 | Y10: ='Growth Scenarios'!M83*-1 -> 736.68425 | Z10: ='Growth Scenarios'!N83*-1 -> 779.31375 | AA10: ='Growth Scenarios'!O83*-1 -> 824.41008 | AB10: ='Growth Scenarios'!P83*-1 -> 872.11598 | AC10: ='Growth Scenarios'!Q83*-1 -> 922.58247
A11: CAPEX | B11: ='Income Statement'!B46 -> -449.2 | C11: ='Income Statement'!C46 -> -455.7 | D11: ='Income Statement'!D46 -> -335.1 | E11: ='Income Statement'!E46 -> -432 | F11: ='Income Statement'!F46 -> -597 | G11: ='Income Statement'!G46 -> -598 | H11: ='Income Statement'!H46 -> -880 | I11: ='Income Statement'!I46 -> -963 | ... K11: ='Income Statement'!K46 -> -1105 | M11: ='Growth Scenarios'!M32 -> -1108.0762 | N11: ='Growth Scenarios'!N32 -> -1205.4392 | O11: ='Growth Scenarios'!O32 -> -1311.3572 | P11: ='Growth Scenarios'!P32 -> -1426.5818 | Q11: ='Growth Scenarios'!Q32 -> -1551.9309 | S11: ='Growth Scenarios'!M62 -> -1248.6378 | T11: ='Growth Scenarios'!N62 -> -1395.8106 | U11: ='Growth Scenarios'!O62 -> -1560.3302 | V11: ='Growth Scenarios'!P62 -> -1744.2412 | W11: ='Growth Scenarios'!Q62 -> -1949.8292 | Y11: ='Growth Scenarios'!M92 -> -967.51458 | Z11: ='Growth Scenarios'!N92 -> -1023.5015 | AA11: ='Growth Scenarios'!O92 -> -1082.7281 | AB11: ='Growth Scenarios'!P92 -> -1145.3821 | AC11: ='Growth Scenarios'!Q92 -> -1211.6616
A12: Change in Net Working Capital | C12: =('Balance Sheet'!C10+'Balance Sheet'!C11-'Balance Sheet'!C25)-('Balance Sheet'!B10+'Balance Sheet'!B11-'Balance Sheet'!B25) -> 262.9 | D12: =('Balance Sheet'!D10+'Balance Sheet'!D11-'Balance Sheet'!D25)-('Balance Sheet'!C10+'Balance Sheet'!C11-'Balance Sheet'!C25) -> -772.9 | E12: =('Balance Sheet'!E10+'Balance Sheet'!E11-'Balance Sheet'!E25)-('Balance Sheet'!D10+'Balance Sheet'!D11-'Balance Sheet'!D25) -> 947.9 | F12: =('Balance Sheet'!F10+'Balance Sheet'!F11-'Balance Sheet'!F25)-('Balance Sheet'!E10+'Balance Sheet'!E11-'Balance Sheet'!E25) -> 658 | G12: =('Balance Sheet'!G10+'Balance Sheet'!G11-'Balance Sheet'!G25)-('Balance Sheet'!F10+'Balance Sheet'!F11-'Balance Sheet'!F25) -> -87 | H12: =('Balance Sheet'!H10+'Balance Sheet'!H11-'Balance Sheet'!H25)-('Balance Sheet'!G10+'Balance Sheet'!G11-'Balance Sheet'!G25) -> 496 | I12: =('Balance Sheet'!I10+'Balance Sheet'!I11-'Balance Sheet'!I25)-('Balance Sheet'!H10+'Balance Sheet'!H11-'Balance Sheet'!H25) -> 113 | J12: =('Balance Sheet'!J10+'Balance Sheet'!J11-'Balance Sheet'!J25)-('Balance Sheet'!I10+'Balance Sheet'!I11-'Balance Sheet'!I25) -> 324 | K12: =('Balance Sheet'!K10+'Balance Sheet'!K11-'Balance Sheet'!K25)-('Balance Sheet'!J10+'Balance Sheet'!J11-'Balance Sheet'!J25) -> 796 | M12: ='Growth Scenarios'!M29 -> 392.8619 | N12: ='Growth Scenarios'!N29 -> 417.13309 | O12: ='Growth Scenarios'!O29 -> 442.90376 | P12: ='Growth Scenarios'!P29 -> 470.26655 | Q12: ='Growth Scenarios'!Q29 -> 499.31983 | S12: ='Growth Scenarios'!M59 -> 583.6319 | T12: ='Growth Scenarios'!N59 -> 637.1979 | U12: ='Growth Scenarios'!O59 -> 695.68021 | V12: ='Growth Scenarios'!P59 -> 759.53006 | W12: ='Growth Scenarios'!Q59 -> 829.24007 | Y12: ='Growth Scenarios'!M89 -> 202.0919 | Z12: ='Growth Scenarios'!N89 -> 208.51447 | AA12: ='Growth Scenarios'!O89 -> 215.14116 | AB12: ='Growth Scenarios'!P89 -> 221.97844 | AC12: ='Growth Scenarios'!Q89 -> 229.03301
A13: Change in Net Working Capital (short-term debt adjusted) | C13: =C12-'Balance Sheet'!C24 -> -80 | D13: =D12-'Balance Sheet'!D24 -> -911.5 | E13: =E12-'Balance Sheet'!E24 -> 760.9 | F13: =F12-'Balance Sheet'!F24 -> 550 | G13: =G12-'Balance Sheet'!G24 -> -208 | H13: =H12-'Balance Sheet'!H24 -> 329 | I13: =I12-'Balance Sheet'!I24 -> 39 | J13: =J12-'Balance Sheet'!J24 -> 323 | K13: =K12-'Balance Sheet'!K24 -> 471 | M13: =M12-'Growth Scenarios'!M36 -> 242.70079 | N13: =N12-'Growth Scenarios'!N36 -> 266.97197 | O13: =O12-'Growth Scenarios'!O36 -> 292.74265 | P13: =P12-'Growth Scenarios'!P36 -> 320.10544 | Q13: =Q12-'Growth Scenarios'!Q36 -> 349.15872 | S13: =S12-'Growth Scenarios'!M66 -> 433.47079 | T13: =T12-'Growth Scenarios'!N66 -> 487.03679 | U13: =U12-'Growth Scenarios'!O66 -> 545.5191 | V13: =V12-'Growth Scenarios'!P66 -> 609.36895 | W13: =W12-'Growth Scenarios'!Q66 -> 679.07896 | Y13: =Y12-'Growth Scenarios'!M96 -> 51.930789 | Z13: =Z12-'Growth Scenarios'!N96 -> 58.353361 | AA13: =AA12-'Growth Scenarios'!O96 -> 64.980045 | AB13: =AB12-'Growth Scenarios'!P96 -> 71.817329 | AC13: =AC12-'Growth Scenarios'!Q96 -> 78.871904
A15: Free Cash Flow (short-term debt adjusted) | C15: =(1-C8)*C9+C8*C10-C11-C13 -> 1950.6961 | D15: =(1-D8)*D9+D8*D10-D11-D13 -> 3094.6293 | E15: =(1-E8)*E9+E8*E10-E11-E13 -> 1759.5471 | F15: =(1-F8)*F9+F8*F10-F11-F13 -> 2307.3638 | G15: =(1-G8)*G9+G8*G10-G11-G13 -> 3231.4091 | H15: =(1-H8)*H9+H8*H10-H11-H13 -> 3302.1971 | I15: =(1-I8)*I9+I8*I10-I11-I13 -> 4051.086 | J15: =(1-J8)*J9+J8*J10-J11-J13 -> 4195.0725 | K15: =(1-K8)*K9+K8*K10-K11-K13 -> 4204.9804 | M15: =(1-M8)*M9+M8*M10-M11-M13 -> 4867.6183 | N15: =(1-N8)*N9+N8*N10-N11-N13 -> 5251.4318 | O15: =(1-O8)*O9+O8*O10-O11-O13 -> 5666.3935 | P15: =(1-P8)*P9+P8*P10-P11-P13 -> 6115.0279 | Q15: =(1-Q8)*Q9+Q8*Q10-Q11-Q13 -> 6600.064 | S15: =(1-S8)*S9+S8*S10-S11-S13 -> 4929.5005 | T15: =(1-T8)*T9+T8*T10-T11-T13 -> 5439.2514 | U15: =(1-U8)*U9+U8*U10-U11-U13 -> 6003.4395 | V15: =(1-V8)*V9+V8*V10-V11-V13 -> 6627.8883 | W15: =(1-W8)*W9+W8*W10-W11-W13 -> 7319.0459 | Y15: =(1-Y8)*Y9+Y8*Y10-Y11-Y13 -> 4805.7362 | Z15: =(1-Z8)*Z9+Z8*Z10-Z11-Z13 -> 5015.3565 | AA15: =(1-AA8)*AA9+AA8*AA10-AA11-AA13 -> 5234.5182 | AB15: =(1-AB8)*AB9+AB8*AB10-AB11-AB13 -> 5463.6619 | AC15: =(1-AC8)*AC9+AC8*AC10-AC11-AC13 -> 5703.249
A16: Source: own calculation
D21: =M6 -> FY 2018E | E21: =N6 -> FY 2019E | F21: =O6 -> FY 2020E | G21: =P6 -> FY 2021E | H21: =Q6 -> FY 2022E
A22: =$A$15 -> Free Cash Flow (short-term debt adjusted) | C22: ='Table of Contents'!J1 -> Scenario 1: Base Case | D22: =M15 -> 4867.6183 | E22: =N15 -> 5251.4318 | F22: =O15 -> 5666.3935 | G22: =P15 -> 6115.0279 | H22: =Q15 -> 6600.064
A23: =$A$15 -> Free Cash Flow (short-term debt adjusted) | C23: ='Table of Contents'!J2 -> Scenario 2: Bull Case | D23: =S15 -> 4929.5005 | E23: =T15 -> 5439.2514 | F23: =U15 -> 6003.4395 | G23: =V15 -> 6627.8883 | H23: =W15 -> 7319.0459
A24: =$A$15 -> Free Cash Flow (short-term debt adjusted) | C24: ='Table of Contents'!J3 -> Scenario 3: Bear Case | D24: =Y15 -> 4805.7362 | E24: =Z15 -> 5015.3565 | F24: =AA15 -> 5234.5182 | G24: =AB15 -> 5463.6619 | H24: =AC15 -> 5703.249

Sheet Beta Calculation
A2: NIKE Inc (NKE US) - Beta Calculation
A4: Monthly data for 5 and 10 years | G4: Daily data for 1 year
A6: Date | B6: S&P500 | C6: rm | D6: Nike Equity | E6: rNike Inc | G6: Date | H6: S&P500 | I6: rm | J6: Nike Equity | K6: rNike Inc
A7: 36830 | B7: 1429.4 | D7: 4.9922 | G7: 42648 | H7: 2159.73 | J7: 54.7305 | M7: Time horizon: 1 year
A8: 36860 | B8: 1314.95 | C8: =(B8-B7)/B7 -> -0.08006856 | D8: 5.3281 | E8: =(D8-D7)/D7 -> 0.067284965 | G8: 42649 | H8: 2160.77 | I8: =(H8-H7)/H7 -> 0.00048154167 | J8: 54.636 | K8: =(J8-J7)/J7 -> -0.0017266424
A9: 36889 | B9: 1320.28 | C9: =(B9-B8)/B8 -> 0.0040533861 | D9: 6.9916 | E9: =(D9-D8)/D8 -> 0.31221261 | G9: 42650 | H9: 2153.74 | I9: =(H9-H8)/H8 -> -0.0032534698 | J9: 54.384 | K9: =(J9-J8)/J8 -> -0.0046123435 | M9: β1year = | N9: =N27 -> 0.85865303 | P9: Calculatory test: | Q9: =_xlfn.COVARIANCE.S(K8:K258,I8:I258)/_xlfn.VAR.S(I8:I258) -> 0.85865303
A10: 36922 | B10: 1366.01 | C10: =(B10-B9)/B9 -> 0.034636592 | D10: 6.8923 | E10: =(D10-D9)/D9 -> -0.014202758 | G10: 42653 | H10: 2163.66 | I10: =(H10-H9)/H9 -> 0.0046059413 | J10: 54.384 | K10: =(J10-J9)/J9 -> 0
A11: 36950 | B11: 1239.94 | C11: =(B11-B10)/B10 -> -0.092290686 | D11: 4.8917 | E11: =(D11-D10)/D10 -> -0.29026595 | G11: 42654 | H11: 2136.73 | I11: =(H11-H10)/H10 -> -0.012446503 | J11: 54.4155 | K11: =(J11-J10)/J10 -> 0.00057921447 | M11: SUMMARY OUTPUT
A12: 36980 | B12: 1160.33 | C12: =(B12-B11)/B11 -> -0.06420472 | D12: 5.0947 | E12: =(D12-D11)/D11 -> 0.041498865 | G12: 42655 | H12: 2139.18 | I12: =(H12-H11)/H11 -> 0.0011466119 | J12: 55.0665 | K12: =(J12-J11)/J11 -> 0.011963503 | M12: Regression Statistics
A13: 37011 | B13: 1249.46 | C13: =(B13-B12)/B12 -> 0.076814355 | D13: 5.253 | E13: =(D13-D12)/D12 -> 0.031071506 | G13: 42656 | H13: 2132.55 | I13: =(H13-H12)/H12 -> -0.0030993184 | J13: 54.636 | K13: =(J13-J12)/J12 -> -0.0078178203 | M13: Multiple R | N13: 0.29192602
A14: 37042 | B14: 1255.82 | C14: =(B14-B13)/B13 -> 0.005090199 | D14: 5.1638 | E14: =(D14-D13)/D13 -> -0.016980773 | G14: 42657 | H14: 2132.98 | I14: =(H14-H13)/H13 -> 0.00020163654 | J14: 54.2054 | K14: =(J14-J13)/J13 -> -0.0078812505 | M14: R Square | N14: 0.085220799
A15: 37071 | B15: 1224.42 | C15: =(B15-B14)/B14 -> -0.025003583 | D15: 5.2907 | E15: =(D15-D14)/D14 -> 0.024574925 | G15: 42660 | H15: 2126.5 | I15: =(H15-H14)/H14 -> -0.0030380032 | J15: 53.5859 | K15: =(J15-J14)/J14 -> -0.011428751 | M15: Adjusted R Square | N15: 0.081546987
A16: 37103 | B16: 1211.23 | C16: =(B16-B15)/B15 -> -0.010772447 | D16: 5.9912 | E16: =(D16-D15)/D15 -> 0.13240214 | G16: 42661 | H16: 2139.6 | I16: =(H16-H15)/H15 -> 0.0061603574 | J16: 53.7854 | K16: =(J16-J15)/J15 -> 0.0037229943 | M16: Standard Error | N16: 0.013149599
A17: 37134 | B17: 1133.58 | C17: =(B17-B16)/B16 -> -0.064108386 | D17: 6.2999 | E17: =(D17-D16)/D16 -> 0.051525571 | G17: 42662 | H17: 2144.29 | I17: =(H17-H16)/H16 -> 0.0021919985 | J17: 54.3945 | K17: =(J17-J16)/J16 -> 0.011324635 | M17: Observations | N17: 251
A18: 37162 | B18: 1040.94 | C18: =(B18-B17)/B17 -> -0.08172339 | D18: 5.9131 | E18: =(D18-D17)/D17 -> -0.0613978 | G18: 42663 | H18: 2141.34 | I18: =(H18-H17)/H17 -> -0.0013757468 | J18: 54.489 | K18: =(J18-J17)/J17 -> 0.001737308
A19: 37195 | B19: 1059.78 | C19: =(B19-B18)/B18 -> 0.018099026 | D19: 6.2352 | E19: =(D19-D18)/D18 -> 0.054472273 | G19: 42664 | H19: 2141.16 | I19: =(H19-H18)/H18 -> -8.4059514e-05 | J19: 54.3629 | K19: =(J19-J18)/J18 -> -0.0023142286 | M19: ANOVA
A20: 37225 | B20: 1139.45 | C20: =(B20-B19)/B19 -> 0.07517598 | D20: 6.6938 | E20: =(D20-D19)/D19 -> 0.073550167 | G20: 42667 | H20: 2151.33 | I20: =(H20-H19)/H19 -> 0.0047497618 | J20: 54.468 | K20: =(J20-J19)/J19 -> 0.0019333038 | N20: df | P20: SS | Q20: MS | R20: F | S20: Significance F
A21: 37256 | B21: 1148.08 | C21: =(B21-B20)/B20 -> 0.0075738295 | D21: 7.1195 | E21: =(D21-D20)/D20 -> 0.063596164 | G21: 42668 | H21: 2143.16 | I21: =(H21-H20)/H20 -> -0.0037976508 | J21: 53.6069 | K21: =(J21-J20)/J20 -> -0.015809283 | M21: Regression | N21: 1 | P21: 0.0040110093 | Q21: 0.0040110093 | R21: 23.196831 | S21: 2.5414649e-06
A22: 37287 | B22: 1130.2 | C22: =(B22-B21)/B21 -> -0.015573828 | D22: 7.5841 | E22: =(D22-D21)/D21 -> 0.065257392 | G22: 42669 | H22: 2139.43 | I22: =(H22-H21)/H21 -> -0.0017404207 | J22: 54.573 | K22: =(J22-J21)/J21 -> 0.018021934 | M22: Residual | N22: 249 | P22: 0.043055075 | Q22: 0.00017291195
A23: 37315 | B23: 1106.73 | C23: =(B23-B22)/B22 -> -0.020766236 | D23: 7.4511 | E23: =(D23-D22)/D22 -> -0.017536689 | G23: 42670 | H23: 2133.04 | I23: =(H23-H22)/H22 -> -0.0029867769 | J23: 54.489 | K23: =(J23-J22)/J22 -> -0.0015392227 | M23: Total | N23: 250 | P23: 0.047066085
A24: 37343 | B24: 1147.39 | C24: =(B24-B23)/B23 -> 0.036738861 | D24: 7.6119 | E24: =(D24-D23)/D23 -> 0.021580706 | G24: 42671 | H24: 2126.41 | I24: =(H24-H23)/H23 -> -0.0031082399 | J24: 54.6255 | K24: =(J24-J23)/J23 -> 0.0025050928
A25: 37376 | B25: 1076.92 | C25: =(B25-B24)/B24 -> -0.061417652 | D25: 6.7646 | E25: =(D25-D24)/D24 -> -0.11131255 | G25: 42674 | H25: 2126.15 | I25: =(H25-H24)/H24 -> -0.00012227181 | J25: 52.6933 | K25: =(J25-J24)/J24 -> -0.035371759 | N25: Coefficients | P25: Standard Error | Q25: t Stat | R25: P-value | S25: Lower 95% | T25: Upper 95% | U25: Lower 95,0% | V25: Upper 95,0%
A26: 37407 | B26: 1067.14 | C26: =(B26-B25)/B25 -> -0.0090814545 | D26: 6.8179 | E26: =(D26-D25)/D25 -> 0.0078792538 | G26: 42675 | H26: 2111.72 | I26: =(H26-H25)/H25 -> -0.0067869153 | J26: 52.1053 | K26: =(J26-J25)/J25 -> -0.011158914 | M26: Intercept | N26: -0.00041776472 | P26: 0.00083813562 | Q26: -0.49844526 | R26: 0.61861024 | S26: -0.0020685037 | T26: 0.0012329743 | U26: -0.0020685037 | V26: 0.0012329743
A27: 37435 | B27: 989.81 | C27: =(B27-B26)/B26 -> -0.072464719 | D27: 6.8204 | E27: =(D27-D26)/D26 -> 0.00036668182 | G27: 42676 | H27: 2097.94 | I27: =(H27-H26)/H26 -> -0.0065254863 | J27: 52.2103 | K27: =(J27-J26)/J26 -> 0.0020151501 | M27: X Variable 1 | N27: 0.85865303 | P27: 0.17828031 | Q27: 4.8163089 | R27: 2.5414649e-06 | S27: 0.50752339 | T27: 1.2097827 | U27: 0.50752339 | V27: 1.2097827
A28: 37468 | B28: 911.62 | C28: =(B28-B27)/B27 -> -0.078994959 | D28: 6.2661 | E28: =(D28-D27)/D27 -> -0.081270893 | G28: 42677 | H28: 2088.66 | I28: =(H28-H27)/H27 -> -0.0044233868 | J28: 52.2208 | K28: =(J28-J27)/J27 -> 0.00020110974
A29: 37498 | B29: 916.07 | C29: =(B29-B28)/B28 -> 0.0048814199 | D29: 5.4894 | E29: =(D29-D28)/D28 -> -0.1239527 | G29: 42678 | H29: 2085.18 | I29: =(H29-H28)/H28 -> -0.00166614 | J29: 52.4623 | K29: =(J29-J28)/J28 -> 0.004624594
A30: 37529 | B30: 815.28 | C30: =(B30-B29)/B29 -> -0.11002434 | D30: 5.5046 | E30: =(D30-D29)/D29 -> 0.0027689729 | G30: 42681 | H30: 2131.52 | I30: =(H30-H29)/H29 -> 0.022223501 | J30: 53.4599 | K30: =(J30-J29)/J29 -> 0.01901556 | M30: Time horizon: 5 years
A31: 37560 | B31: 885.76 | C31: =(B31-B30)/B30 -> 0.086448827 | D31: 6.0158 | E31: =(D31-D30)/D30 -> 0.092867783 | G31: 42682 | H31: 2139.56 | I31: =(H31-H30)/H30 -> 0.0037719562 | J31: 53.6384 | K31: =(J31-J30)/J30 -> 0.0033389513
A32: 37589 | B32: 936.31 | C32: =(B32-B31)/B31 -> 0.057069635 | D32: 5.7086 | E32: =(D32-D31)/D31 -> -0.051065527 | G32: 42683 | H32: 2163.26 | I32: =(H32-H31)/H31 -> 0.011077044 | J32: 53.6804 | K32: =(J32-J31)/J31 -> 0.00078302112 | M32: β5years = | N32: =N50 -> 0.61417323 | P32: Calculatory test: | Q32: =_xlfn.COVARIANCE.S(E151:E210,C151:C210)/_xlfn.VAR.S(C151:C210) -> 0.61417323
A33: 37621 | B33: 879.82 | C33: =(B33-B32)/B32 -> -0.060332582 | D33: 5.6869 | E33: =(D33-D32)/D32 -> -0.0038012823 | G33: 42684 | H33: 2167.48 | I33: =(H33-H32)/H32 -> 0.0019507595 | J33: 52.9138 | K33: =(J33-J32)/J32 -> -0.014280818
A34: 37652 | B34: 855.7 | C34: =(B34-B33)/B33 -> -0.027414698 | D34: 5.6959 | E34: =(D34-D33)/D33 -> 0.0015825845 | G34: 42685 | H34: 2164.45 | I34: =(H34-H33)/H33 -> -0.0013979368 | J34: 53.3129 | K34: =(J34-J33)/J33 -> 0.0075424558 | M34: SUMMARY OUTPUT
A35: 37680 | B35: 841.15 | C35: =(B35-B34)/B34 -> -0.017003623 | D35: 5.9299 | E35: =(D35-D34)/D34 -> 0.041082182 | G35: 42688 | H35: 2164.2 | I35: =(H35-H34)/H34 -> -0.00011550278 | J35: 52.7248 | K35: =(J35-J34)/J34 -> -0.011031101 | M35: Regression Statistics
A36: 37711 | B36: 848.18 | C36: =(B36-B35)/B35 -> 0.0083576057 | D36: 6.5936 | E36: =(D36-D35)/D35 -> 0.11192432 | G36: 42689 | H36: 2180.39 | I36: =(H36-H35)/H35 -> 0.0074808243 | J36: 52.6408 | K36: =(J36-J35)/J35 -> -0.0015931782 | M36: Multiple R | N36: 0.31316928
A37: 37741 | B37: 916.92 | C37: =(B37-B36)/B36 -> 0.081044118 | D37: 6.8642 | E37: =(D37-D36)/D36 -> 0.041039796 | G37: 42690 | H37: 2176.94 | I37: =(H37-H36)/H36 -> -0.0015822857 | J37: 53.2184 | K37: =(J37-J36)/J36 -> 0.010972478 | M37: R Square | N37: 0.098074996
A38: 37771 | B38: 963.59 | C38: =(B38-B37)/B37 -> 0.050898661 | D38: 7.1796 | E38: =(D38-D37)/D37 -> 0.045948545 | G38: 42691 | H38: 2187.12 | I38: =(H38-H37)/H37 -> 0.0046762887 | J38: 54.1739 | K38: =(J38-J37)/J37 -> 0.017954317 | M38: Adjusted R Square | N38: 0.082524565
A39: 37802 | B39: 974.5 | C39: =(B39-B38)/B38 -> 0.011322243 | D39: 6.877 | E39: =(D39-D38)/D38 -> -0.042147195 | G39: 42692 | H39: 2181.9 | I39: =(H39-H38)/H38 -> -0.0023867003 | J39: 53.6594 | K39: =(J39-J38)/J38 -> -0.0094971933 | M39: Standard Error | N39: 0.051618379
A40: 37833 | B40: 990.31 | C40: =(B40-B39)/B39 -> 0.016223704 | D40: 6.652 | E40: =(D40-D39)/D39 -> -0.032717755 | G40: 42695 | H40: 2198.18 | I40: =(H40-H39)/H39 -> 0.0074613869 | J40: 53.8484 | K40: =(J40-J39)/J39 -> 0.0035222161 | M40: Observations | N40: 60
A41: 37862 | B41: 1008.01 | C41: =(B41-B40)/B40 -> 0.017873191 | D41: 7.3257 | E41: =(D41-D40)/D40 -> 0.10127781 | G41: 42696 | H41: 2202.94 | I41: =(H41-H40)/H40 -> 0.0021654278 | J41: 54.2999 | K41: =(J41-J40)/J40 -> 0.0083846502
A42: 37894 | B42: 995.97 | C42: =(B42-B41)/B41 -> -0.011944326 | D42: 7.8374 | E42: =(D42-D41)/D41 -> 0.06984998 | G42: 42697 | H42: 2204.72 | I42: =(H42-H41)/H41 -> 0.00080801111 | J42: 53.9114 | K42: =(J42-J41)/J41 -> -0.0071547093 | M42: ANOVA
A43: 37925 | B43: 1050.71 | C43: =(B43-B42)/B42 -> 0.054961495 | D43: 8.2343 | E43: =(D43-D42)/D42 -> 0.050641794 | G43: 42699 | H43: 2213.35 | I43: =(H43-H42)/H42 -> 0.0039143293 | J43: 54.1004 | K43: =(J43-J42)/J42 -> 0.003505752 | N43: df | P43: SS | Q43: MS | R43: F | S43: Significance F
A44: 37953 | B44: 1058.2 | C44: =(B44-B43)/B43 -> 0.0071285131 | D44: 8.666 | E44: =(D44-D43)/D43 -> 0.052427043 | G44: 42702 | H44: 2201.72 | I44: =(H44-H43)/H43 -> -0.0052544785 | J44: 53.5649 | K44: =(J44-J43)/J43 -> -0.0098982632 | M44: Regression | N44: 1 | P44: 0.016804461 | Q44: 0.016804461 | R44: 6.3068988 | S44: 0.014834289
A45: 37986 | B45: 1111.92 | C45: =(B45-B44)/B44 -> 0.050765451 | D45: 8.8477 | E45: =(D45-D44)/D44 -> 0.020966997 | G45: 42703 | H45: 2204.66 | I45: =(H45-H44)/H44 -> 0.0013353197 | J45: 53.1659 | K45: =(J45-J44)/J44 -> -0.0074489078 | M45: Residual | N45: 58 | P45: 0.15453851 | Q45: 0.0026644571
A46: 38016 | B46: 1131.13 | C46: =(B46-B45)/B45 -> 0.017276423 | D46: 9.0028 | E46: =(D46-D45)/D45 -> 0.01752998 | G46: 42704 | H46: 2198.81 | I46: =(H46-H45)/H45 -> -0.0026534704 | J46: 52.5778 | K46: =(J46-J45)/J45 -> -0.011061602 | M46: Total | N46: 59 | P46: 0.17134297
A47: 38044 | B47: 1144.94 | C47: =(B47-B46)/B46 -> 0.01220903 | D47: 9.4667 | E47: =(D47-D46)/D46 -> 0.051528413 | G47: 42705 | H47: 2191.08 | I47: =(H47-H46)/H46 -> -0.003515538 | J47: 53.3759 | K47: =(J47-J46)/J46 -> 0.01517941
A48: 38077 | B48: 1126.21 | C48: =(B48-B47)/B47 -> -0.016358936 | D48: 10.0897 | E48: =(D48-D47)/D47 -> 0.065809627 | G48: 42706 | H48: 2191.95 | I48: =(H48-H47)/H47 -> 0.00039706446 | J48: 53.1756 | K48: =(J48-J47)/J47 -> -0.0037526299 | N48: Coefficients | P48: Standard Error | Q48: t Stat | R48: P-value | S48: Lower 95% | T48: Upper 95% | U48: Lower 95,0% | V48: Upper 95,0%
A49: 38107 | B49: 1107.3 | C49: =(B49-B48)/B48 -> -0.016790829 | D49: 9.3226 | E49: =(D49-D48)/D48 -> -0.076028029 | G49: 42709 | H49: 2204.71 | I49: =(H49-H48)/H48 -> 0.0058213007 | J49: 54.6405 | K49: =(J49-J48)/J48 -> 0.027548349 | M49: Intercept | N49: 0.0095855974 | P49: 0.0070757483 | Q49: 1.3547115 | R49: 0.1807632 | S49: -0.0045780518 | T49: 0.023749246 | U49: -0.0045780518 | V49: 0.023749246
A50: 38135 | B50: 1120.68 | C50: =(B50-B49)/B49 -> 0.012083446 | D50: 9.219 | E50: =(D50-D49)/D49 -> -0.01111278 | G50: 42710 | H50: 2212.23 | I50: =(H50-H49)/H49 -> 0.0034108794 | J50: 53.2916 | K50: =(J50-J49)/J49 -> -0.024686817 | M50: X Variable 1 | N50: 0.61417323 | P50: 0.24455861 | Q50: 2.511354 | R50: 0.014834289 | S50: 0.12463599 | T50: 1.1037105 | U50: 0.12463599 | V50: 1.1037105
A51: 38168 | B51: 1140.84 | C51: =(B51-B50)/B50 -> 0.017989078 | D51: 9.8409 | E51: =(D51-D50)/D50 -> 0.06745851 | G51: 42711 | H51: 2241.35 | I51: =(H51-H50)/H50 -> 0.013163188 | J51: 54.9039 | K51: =(J51-J50)/J50 -> 0.030254299
A52: 38198 | B52: 1101.72 | C52: =(B52-B51)/B51 -> -0.034290523 | D52: 9.446 | E52: =(D52-D51)/D51 -> -0.040128444 | G52: 42712 | H52: 2246.19 | I52: =(H52-H51)/H51 -> 0.0021594129 | J52: 54.3243 | K52: =(J52-J51)/J51 -> -0.010556627
A53: 38230 | B53: 1104.24 | C53: =(B53-B52)/B52 -> 0.0022873325 | D53: 9.7837 | E53: =(D53-D52)/D52 -> 0.035750582 | G53: 42713 | H53: 2259.53 | I53: =(H53-H52)/H52 -> 0.0059389455 | J53: 54.5035 | K53: =(J53-J52)/J52 -> 0.0032987079 | M53: Time horizon: last 10 years
A54: 38260 | B54: 1114.58 | C54: =(B54-B53)/B53 -> 0.0093639064 | D54: 10.2631 | E54: =(D54-D53)/D53 -> 0.048999867 | G54: 42716 | H54: 2256.96 | I54: =(H54-H53)/H53 -> -0.0011374047 | J54: 54.3138 | K54: =(J54-J53)/J53 -> -0.0034805104
A55: 38289 | B55: 1130.2 | C55: =(B55-B54)/B54 -> 0.014014248 | D55: 10.59 | E55: =(D55-D54)/D54 -> 0.031851975 | G55: 42717 | H55: 2271.72 | I55: =(H55-H54)/H54 -> 0.0065397703 | J55: 55.1147 | K55: =(J55-J54)/J54 -> 0.014745792 | M55: β10years = | N55: =N73 -> 0.80201618 | P55: Calculatory test: | Q55: =_xlfn.COVARIANCE.S(E91:E210,C91:C210)/_xlfn.VAR.S(C91:C210) -> 0.80201618
A56: 38321 | B56: 1173.82 | C56: =(B56-B55)/B55 -> 0.038594939 | D56: 11.0263 | E56: =(D56-D55)/D55 -> 0.041199245 | G56: 42718 | H56: 2253.28 | I56: =(H56-H55)/H55 -> -0.0081171975 | J56: 54.5772 | K56: =(J56-J55)/J55 -> -0.0097523891
A57: 38352 | B57: 1211.92 | C57: =(B57-B56)/B56 -> 0.032458128 | D57: 11.8443 | E57: =(D57-D56)/D56 -> 0.074186264 | G57: 42719 | H57: 2262.03 | I57: =(H57-H56)/H56 -> 0.003883228 | J57: 54.0503 | K57: =(J57-J56)/J56 -> -0.0096542146 | M57: SUMMARY OUTPUT
A58: 38383 | B58: 1181.27 | C58: =(B58-B57)/B57 -> -0.025290448 | D58: 11.314 | E58: =(D58-D57)/D57 -> -0.044772591 | G58: 42720 | H58: 2258.07 | I58: =(H58-H57)/H57 -> -0.0017506399 | J58: 53.6604 | K58: =(J58-J57)/J57 -> -0.007213651 | M58: Regression Statistics
A59: 38411 | B59: 1203.6 | C59: =(B59-B58)/B58 -> 0.018903384 | D59: 11.3558 | E59: =(D59-D58)/D58 -> 0.0036945377 | G59: 42723 | H59: 2262.53 | I59: =(H59-H58)/H58 -> 0.0019751381 | J59: 53.5866 | K59: =(J59-J58)/J58 -> -0.0013753159 | M59: Multiple R | N59: 0.52337792
A60: 38442 | B60: 1180.59 | C60: =(B60-B59)/B59 -> -0.019117647 | D60: 10.9131 | E60: =(D60-D59)/D59 -> -0.038984484 | G60: 42724 | H60: 2270.76 | I60: =(H60-H59)/H59 -> 0.0036375208 | J60: 54.5772 | K60: =(J60-J59)/J59 -> 0.018485965 | M60: R Square | N60: 0.27392445
A61: 38471 | B61: 1156.85 | C61: =(B61-B60)/B60 -> -0.02010859 | D61: 10.0616 | E61: =(D61-D60)/D60 -> -0.078025492 | G61: 42725 | H61: 2265.18 | I61: =(H61-H60)/H60 -> -0.0024573271 | J61: 55.1147 | K61: =(J61-J60)/J60 -> 0.0098484349 | M61: Adjusted R Square | N61: 0.26777126
A62: 38503 | B62: 1191.5 | C62: =(B62-B61)/B61 -> 0.029952025 | D62: 10.7677 | E62: =(D62-D61)/D61 -> 0.070177705 | G62: 42726 | H62: 2260.96 | I62: =(H62-H61)/H61 -> -0.0018629866 | J62: 54.9461 | K62: =(J62-J61)/J61 -> -0.003059075 | M62: Standard Error | N62: 0.057333679
A63: 38533 | B63: 1191.33 | C63: =(B63-B62)/B62 -> -0.0001426773 | D63: 11.3768 | E63: =(D63-D62)/D62 -> 0.056567326 | G63: 42727 | H63: 2263.79 | I63: =(H63-H62)/H62 -> 0.0012516807 | J63: 54.7037 | K63: =(J63-J62)/J62 -> -0.0044115961 | M63: Observations | N63: 120
A64: 38562 | B64: 1234.18 | C64: =(B64-B63)/B63 -> 0.035968204 | D64: 11.0089 | E64: =(D64-D63)/D63 -> -0.03233774 | G64: 42731 | H64: 2268.88 | I64: =(H64-H63)/H63 -> 0.0022484418 | J64: 54.0503 | K64: =(J64-J63)/J63 -> -0.011944347
A65: 38595 | B65: 1220.33 | C65: =(B65-B64)/B64 -> -0.011222026 | D65: 10.3665 | E65: =(D65-D64)/D64 -> -0.058352787 | G65: 42732 | H65: 2249.92 | I65: =(H65-H64)/H64 -> -0.008356546 | J65: 53.7658 | K65: =(J65-J64)/J64 -> -0.0052636156 | M65: ANOVA
A66: 38625 | B66: 1228.81 | C66: =(B66-B65)/B65 -> 0.00694894 | D66: 10.7633 | E66: =(D66-D65)/D65 -> 0.038277143 | G66: 42733 | H66: 2249.26 | I66: =(H66-H65)/H65 -> -0.00029334376 | J66: 53.8079 | K66: =(J66-J65)/J65 -> 0.00078302564 | N66: df | P66: SS | Q66: MS | R66: F | S66: Significance F
A67: 38656 | B67: 1207.01 | C67: =(B67-B66)/B66 -> -0.017740741 | D67: 11.0756 | E67: =(D67-D66)/D66 -> 0.029015265 | G67: 42734 | H67: 2238.83 | I67: =(H67-H66)/H66 -> -0.0046370806 | J67: 53.5656 | K67: =(J67-J66)/J66 -> -0.0045030562 | M67: Regression | N67: 1 | P67: 0.14633581 | Q67: 0.14633581 | R67: 44.517522 | S67: 8.6113118e-10
A68: 38686 | B68: 1249.48 | C68: =(B68-B67)/B67 -> 0.035186121 | D68: 11.2403 | E68: =(D68-D67)/D67 -> 0.014870526 | G68: 42738 | H68: 2257.83 | I68: =(H68-H67)/H67 -> 0.0084865756 | J68: 54.7774 | K68: =(J68-J67)/J67 -> 0.022622728 | M68: Residual | N68: 118 | P68: 0.38788379 | Q68: 0.0032871507
A69: 38716 | B69: 1248.29 | C69: =(B69-B68)/B68 -> -0.0009523962 | D69: 11.4775 | E69: =(D69-D68)/D68 -> 0.02110264 | G69: 42739 | H69: 2270.75 | I69: =(H69-H68)/H68 -> 0.0057223086 | J69: 55.9261 | K69: =(J69-J68)/J68 -> 0.020970327 | M69: Total | N69: 119 | P69: 0.53421959
A70: 38748 | B70: 1280.08 | C70: =(B70-B69)/B69 -> 0.025466839 | D70: 10.7052 | E70: =(D70-D69)/D69 -> -0.067288173 | G70: 42740 | H70: 2269 | I70: =(H70-H69)/H69 -> -0.00077067048 | J70: 55.9156 | K70: =(J70-J69)/J69 -> -0.00018774776
A71: 38776 | B71: 1280.66 | C71: =(B71-B70)/B70 -> 0.00045309668 | D71: 11.4762 | E71: =(D71-D70)/D70 -> 0.072021074 | G71: 42741 | H71: 2276.98 | I71: =(H71-H70)/H70 -> 0.0035169678 | J71: 56.8113 | K71: =(J71-J70)/J70 -> 0.016018785 | N71: Coefficients | P71: Standard Error | Q71: t Stat | R71: P-value | S71: Lower 95% | T71: Upper 95% | U71: Lower 95,0% | V71: Upper 95,0%
A72: 38807 | B72: 1294.83 | C72: =(B72-B71)/B71 -> 0.011064607 | D72: 11.295 | E72: =(D72-D71)/D71 -> -0.015789199 | G72: 42744 | H72: 2268.9 | I72: =(H72-H71)/H71 -> -0.0035485599 | J72: 56.2528 | K72: =(J72-J71)/J71 -> -0.0098307907 | M72: Intercept | N72: 0.0098407357 | P72: 0.0052703067 | Q72: 1.8672036 | R72: 0.064354719 | S72: -0.00059590645 | T72: 0.020277378 | U72: -0.00059590645 | V72: 0.020277378
A73: 38835 | B73: 1310.61 | C73: =(B73-B72)/B72 -> 0.012186928 | D73: 10.8623 | E73: =(D73-D72)/D72 -> -0.038308986 | G73: 42745 | H73: 2268.9 | I73: =(H73-H72)/H72 -> 0 | J73: 55.9683 | K73: =(J73-J72)/J72 -> -0.005057526 | M73: X Variable 1 | N73: 0.80201618 | P73: 0.12020364 | Q73: 6.6721452 | R73: 8.6113118e-10 | S73: 0.56398024 | T73: 1.0400521 | U73: 0.56398024 | V73: 1.0400521
A74: 38868 | B74: 1270.09 | C74: =(B74-B73)/B73 -> -0.030916901 | D74: 10.6592 | E74: =(D74-D73)/D73 -> -0.018697698 | G74: 42746 | H74: 2275.32 | I74: =(H74-H73)/H73 -> 0.002829565 | J74: 55.5257 | K74: =(J74-J73)/J73 -> -0.0079080479
A75: 38898 | B75: 1270.2 | C75: =(B75-B74)/B74 -> 8.6608036e-05 | D75: 10.792 | E75: =(D75-D74)/D74 -> 0.012458721 | G75: 42747 | H75: 2270.44 | I75: =(H75-H74)/H74 -> -0.0021447533 | J75: 55.22 | K75: =(J75-J74)/J74 -> -0.0055055587
A76: 38929 | B76: 1276.66 | C76: =(B76-B75)/B75 -> 0.0050858133 | D76: 10.5255 | E76: =(D76-D75)/D75 -> -0.024694218 | G76: 42748 | H76: 2274.64 | I76: =(H76-H75)/H75 -> 0.0018498617 | J76: 55.768 | K76: =(J76-J75)/J75 -> 0.0099239406
A77: 38960 | B77: 1303.82 | C77: =(B77-B76)/B76 -> 0.021274263 | D77: 10.76 | E77: =(D77-D76)/D76 -> 0.022279227 | G77: 42752 | H77: 2267.89 | I77: =(H77-H76)/H76 -> -0.0029675025 | J77: 56.5373 | K77: =(J77-J76)/J76 -> 0.013794649
A78: 38989 | B78: 1335.85 | C78: =(B78-B77)/B77 -> 0.024566274 | D78: 11.7153 | E78: =(D78-D77)/D77 -> 0.088782528 | G78: 42753 | H78: 2271.89 | I78: =(H78-H77)/H77 -> 0.001763754 | J78: 56.1369 | K78: =(J78-J77)/J77 -> -0.0070820503
A79: 39021 | B79: 1377.94 | C79: =(B79-B78)/B78 -> 0.031508029 | D79: 12.2849 | E79: =(D79-D78)/D78 -> 0.04862018 | G79: 42754 | H79: 2263.69 | I79: =(H79-H78)/H78 -> -0.0036093297 | J79: 55.7786 | K79: =(J79-J78)/J78 -> -0.0063826111
A80: 39051 | B80: 1400.63 | C80: =(B80-B79)/B79 -> 0.01646661 | D80: 13.2302 | E80: =(D80-D79)/D79 -> 0.076948123 | G80: 42755 | H80: 2271.31 | I80: =(H80-H79)/H79 -> 0.0033661853 | J80: 56.0631 | K80: =(J80-J79)/J79 -> 0.0051005224
A81: 39080 | B81: 1418.3 | C81: =(B81-B80)/B80 -> 0.012615751 | D81: 13.2903 | E81: =(D81-D80)/D80 -> 0.0045426373 | G81: 42758 | H81: 2265.2 | I81: =(H81-H80)/H80 -> -0.0026900775 | J81: 56.1053 | K81: =(J81-J80)/J80 -> 0.00075272327
A82: 39113 | B82: 1438.24 | C82: =(B82-B81)/B81 -> 0.014059085 | D82: 13.2608 | E82: =(D82-D81)/D81 -> -0.002219664 | G82: 42759 | H82: 2280.07 | I82: =(H82-H81)/H81 -> 0.0065645418 | J82: 56.3266 | K82: =(J82-J81)/J81 -> 0.0039443689
A83: 39141 | B83: 1406.82 | C83: =(B83-B82)/B82 -> -0.021846145 | D83: 14.0204 | E83: =(D83-D82)/D82 -> 0.057281612 | G83: 42760 | H83: 2298.37 | I83: =(H83-H82)/H82 -> 0.0080260694 | J83: 56.7586 | K83: =(J83-J82)/J82 -> 0.0076695558
A84: 39171 | B84: 1420.86 | C84: =(B84-B83)/B83 -> 0.0099799548 | D84: 14.3103 | E84: =(D84-D83)/D83 -> 0.020677013 | G84: 42761 | H84: 2296.68 | I84: =(H84-H83)/H83 -> -0.00073530372 | J84: 56.5373 | K84: =(J84-J83)/J83 -> -0.0038989686
A85: 39202 | B85: 1482.37 | C85: =(B85-B84)/B84 -> 0.043290683 | D85: 14.5069 | E85: =(D85-D84)/D84 -> 0.013738356 | G85: 42762 | H85: 2294.69 | I85: =(H85-H84)/H84 -> -0.00086646812 | J85: 56.0526 | K85: =(J85-J84)/J84 -> -0.0085731013
... A210: 43007 | B210: 2519.36 | C210: =(B210-B209)/B209 -> 0.019302895 | D210: 64.6032 | E210: =(D210-D209)/D209 -> -0.018179497 | G210: 42943 | H210: 2475.42 | I210: =(H210-H209)/H209 -> -0.00097262524 | J210: 61.6819 | K210: =(J210-J209)/J209 -> -0.0035990805
A211: Source: Bloomberg | G211: 42944 | H211: 2472.1 | I211: =(H211-H210)/H210 -> -0.0013411865 | J211: 62.2335 | K211: =(J211-J210)/J210 -> 0.0089426558
G212: 42947 | H212: 2470.3 | I212: =(H212-H211)/H211 -> -0.00072812588 | J212: 62.6366 | K212: =(J212-J211)/J211 -> 0.0064772189
G213: 42948 | H213: 2476.35 | I213: =(H213-H212)/H212 -> 0.0024490953 | J213: 63.4745 | K213: =(J213-J212)/J212 -> 0.013377163
G214: 42949 | H214: 2477.57 | I214: =(H214-H213)/H213 -> 0.00049266057 | J214: 63.4215 | K214: =(J214-J213)/J213 -> -0.00083498098
G215: 42950 | H215: 2472.16 | I215: =(H215-H214)/H214 -> -0.0021835912 | J215: 63.7928 | K215: =(J215-J214)/J214 -> 0.0058544815
G216: 42951 | H216: 2476.83 | I216: =(H216-H215)/H215 -> 0.0018890363 | J216: 63.3897 | K216: =(J216-J215)/J215 -> -0.0063188949
G217: 42954 | H217: 2480.91 | I217: =(H217-H216)/H216 -> 0.0016472669 | J217: 63.4215 | K217: =(J217-J216)/J216 -> 0.00050165879
G218: 42955 | H218: 2474.92 | I218: =(H218-H217)/H217 -> -0.0024144366 | J218: 63.0715 | K218: =(J218-J217)/J217 -> -0.0055186333
G219: 42956 | H219: 2474.02 | I219: =(H219-H218)/H218 -> -0.00036364812 | J219: 63.5382 | K219: =(J219-J218)/J218 -> 0.0073995386
G220: 42957 | H220: 2438.21 | I220: =(H220-H219)/H219 -> -0.014474418 | J220: 62.6578 | K220: =(J220-J219)/J219 -> -0.013856231
G221: 42958 | H221: 2441.32 | I221: =(H221-H220)/H220 -> 0.0012755259 | J221: 62.5517 | K221: =(J221-J220)/J220 -> -0.0016933247
G222: 42961 | H222: 2465.84 | I222: =(H222-H221)/H221 -> 0.010043747 | J222: 63.4109 | K222: =(J222-J221)/J221 -> 0.013735838
G223: 42962 | H223: 2464.61 | I223: =(H223-H222)/H222 -> -0.00049881582 | J223: 62.1168 | K223: =(J223-J222)/J222 -> -0.020408163
... G258: 43012 | H258: 2537.74 | I258: =(H258-H257)/H257 -> 0.0012467549 | J258: 55.4315 | K258: =(J258-J257)/J257 -> 0.011850543
G259: Source: Bloomberg

Sheet Cost of Equity
A2: NIKE Inc (NKE US) - Cost of Equity
A4: Monthly data for 5 and 10 years
A6: Date | B6: S&P500 prices | C6: rm | D6: rf | E6: (rm - rf) | G6: Market Risk Premia | J6: Risk-free rate | M6: Cost of Equity
A7: 36830 | B7: 1429.4 | D7: 0.0056
A8: 36860 | B8: 1314.95 | C8: =(B8-B7)/B7 -> -0.08006856 | D8: 0.0051 | E8: =C8-D8 -> -0.08516856 | G8: Monthly MRP1year | H8: =AVERAGE(E199:E210) -> 0.012235197 | J8: Monthly rf 1year | K8: =AVERAGE(D199:D210) -> 0.00045833333 | M8: Average rE 1year | N8: =K12+'Beta Calculation'!N9*H12 -> 0.14042273
A9: 36889 | B9: 1320.28 | C9: =(B9-B8)/B8 -> 0.0040533861 | D9: 0.005 | E9: =C9-D9 -> -0.00094661394 | G9: Monthly MRP5years | H9: =AVERAGE(E151:E210) -> 0.0096034982 | J9: Monthly rf 5years | K9: =AVERAGE(D151:D210) -> 0.00012333333 | M9: Average rE 5years | N9: =K13+'Beta Calculation'!N32*H13 -> 0.076120312
A10: 36922 | B10: 1366.01 | C10: =(B10-B9)/B9 -> 0.034636592 | D10: 0.0054 | E10: =C10-D10 -> 0.029236592 | G10: Monthly MRP10years | H10: =AVERAGE(E91:E210) -> 0.0048574236 | J10: Monthly rf 10years | K10: =AVERAGE(D91:D210) -> 0.0002925 | M10: Average rE 10years | N10: =K14+'Beta Calculation'!N55*H14 -> 0.051533817
A11: 36950 | B11: 1239.94 | C11: =(B11-B10)/B10 -> -0.092290686 | D11: 0.0038 | E11: =C11-D11 -> -0.096090686
A12: 36980 | B12: 1160.33 | C12: =(B12-B11)/B11 -> -0.06420472 | D12: 0.0042 | E12: =C12-D12 -> -0.06840472 | G12: Yearly MRP1year | H12: =(1+H8)^12-1 -> 0.15711683 | J12: Yearly rf 1year | K12: =(1+K8)^12-1 -> 0.0055138858 | M12: Cost of Equity | N12: =0.4*N8+0.4*N9+0.2*N10 -> 0.09692398
A13: 37011 | B13: 1249.46 | C13: =(B13-B12)/B12 -> 0.076814355 | D13: 0.0039 | E13: =C13-D13 -> 0.072914355 | G13: Yearly MRP5years | H13: =(1+H9)^12-1 -> 0.1215281 | J13: Yearly rf 5years | K13: =(1+K9)^12-1 -> 0.0014810043
A14: 37042 | B14: 1255.82 | C14: =(B14-B13)/B13 -> 0.005090199 | D14: 0.0032 | E14: =C14-D14 -> 0.001890199 | G14: Yearly MRP10years | H14: =(1+H10)^12-1 -> 0.059871816 | J14: Yearly rf 10years | K14: =(1+K10)^12-1 -> 0.0035156522
A15: 37071 | B15: 1224.42 | C15: =(B15-B14)/B14 -> -0.025003583 | D15: 0.0028 | E15: =C15-D15 -> -0.027803583
A16: 37103 | B16: 1211.23 | C16: =(B16-B15)/B15 -> -0.010772447 | D16: 0.003 | E16: =C16-D16 -> -0.013772447
A17: 37134 | B17: 1133.58 | C17: =(B17-B16)/B16 -> -0.064108386 | D17: 0.0031 | E17: =C17-D17 -> -0.067208386
A18: 37162 | B18: 1040.94 | C18: =(B18-B17)/B17 -> -0.08172339 | D18: 0.0028 | E18: =C18-D18 -> -0.08452339
A19: 37195 | B19: 1059.78 | C19: =(B19-B18)/B18 -> 0.018099026 | D19: 0.0022 | E19: =C19-D19 -> 0.015899026
A20: 37225 | B20: 1139.45 | C20: =(B20-B19)/B19 -> 0.07517598 | D20: 0.0017 | E20: =C20-D20 -> 0.07347598
A21: 37256 | B21: 1148.08 | C21: =(B21-B20)/B20 -> 0.0075738295 | D21: 0.0015 | E21: =C21-D21 -> 0.0060738295
A22: 37287 | B22: 1130.2 | C22: =(B22-B21)/B21 -> -0.015573828 | D22: 0.0014 | E22: =C22-D22 -> -0.016973828
A23: 37315 | B23: 1106.73 | C23: =(B23-B22)/B22 -> -0.020766236 | D23: 0.0013 | E23: =C23-D23 -> -0.022066236
A24: 37344 | B24: 1147.39 | C24: =(B24-B23)/B23 -> 0.036738861 | D24: 0.0013 | E24: =C24-D24 -> 0.035438861
A25: 37376 | B25: 1076.92 | C25: =(B25-B24)/B24 -> -0.061417652 | D25: 0.0015 | E25: =C25-D25 -> -0.062917652
A26: 37407 | B26: 1067.14 | C26: =(B26-B25)/B25 -> -0.0090814545 | D26: 0.0014 | E26: =C26-D26 -> -0.010481455
... A210: 43007 | B210: 2519.36 | C210: =(B210-B209)/B209 -> 0.019302895 | D210: 0.0007 | E210: =C210-D210 -> 0.018602895
A211: Sources: Bloomberg, Kenneth R. French - Data Library

Sheet Cost of Debt
A2: NIKE Inc (NKE US) - Cost of Debt
A4: Corporate Bonds
A6: Maturities | B6: Original Principal | C6: Interest Rate | D6: Interest Payment | E6: first Cupon Date | F6: Par Amount | G6: Course October 4, 2017 | H6: Price October 4, 2017 | I6: rD | K6: Number of Bonds issued | L6: Market Value of debt October 4, 2017 | M6: Book Value of debt May 31, 2017 | P6: Book/Market Value Ratio
A7: May 1, 2023 | B7: 500000000 | C7: 0.0225 | D7: Semi-Anually | E7: 41579 | F7: 1000 | G7: 0.99787 | H7: =G7*F7 -> 997.87 | I7: ='Corporate Bond 1'!B21 -> 0.023012846 | K7: 500000 | L7: =K7*H7 -> 498935000 | M7: 497000000 | P7: =M7/L7 -> 0.99612174
A8: November 1, 2026 | B8: 1000000000 | C8: 0.0238 | D8: Semi-Anually | E8: 42856 | F8: 1000 | G8: 0.95349 | H8: =G8*F8 -> 953.49 | I8: ='Corporate Bond 2'!B28 -> 0.029666212 | K8: 1000000 | L8: =K8*H8 -> 9.5349e+08 | M8: 993000000 | P8: =M8/L8 -> 1.0414372
A9: May 1, 2043 | B9: 500000000 | C9: 0.0363 | D9: Semi-Anually | E9: 41579 | F9: 1000 | G9: 0.97935 | H9: =G9*F9 -> 979.35 | I9: ='Corporate Bond 3'!B61 -> 0.037903478 | K9: 500000 | L9: =K9*H9 -> 489675000 | M9: 495000000 | P9: =M9/L9 -> 1.0108746
A10: November 1, 2045 | B10: 1000000000 | C10: 0.0388 | D10: Semi-Anually | E10: 42491 | F10: 1000 | G10: 1.01553 | H10: =G10*F10 -> 1015.53 | I10: ='Corporate Bond 4'!B66 -> 0.038263357 | K10: 1000000 | L10: =K10*H10 -> 1.01553e+09 | M10: 981000000 | P10: =M10/L10 -> 0.96599805
A11: November 1, 2046 | B11: 500000000 | C11: 0.0388 | D11: Semi-Anually | E11: 42856 | F11: 1000 | G11: 0.93485 | H11: =G11*F11 -> 934.85 | I11: ='Corporate Bond 5'!B68 -> 0.038280396 | K11: 500000 | L11: =K11*H11 -> 4.67425e+08 | M11: 490000000 | P11: =M11/L11 -> 1.0482965
K12: TOTAL | L12: =SUM(L7:L11) -> 3425055000 | M12: =SUM(M7:M11) -> 3456000000 | O12: weighted average | P12: =P7*(M7/M12)+P8*(M8/M12)+P9*(M9/M12)+P10*(M10/M12)+P11*(M11/M12) -> 1.0101018
A13: Japanese Yen Notes
A15: Maturities | B15: Original Principal | C15: Interest Rate | D15: Interest Payment | L15: Market Value of debt outstanding October 4, 2017 | M15: Book Value of debt outstanding May 31, 2017
A16: August 20, 2001 through November 20, 2020 | B16: 9000000000 | C16: 0.026 | D16: Quarterly | L16: =M16*P12 -> 14141426 | M16: 14000000
A17: August 20, 2001 through November 20, 2020 | B17: 4000000000 | C17: 0.02 | D17: Quarterly | L17: =M17*P12 -> 7070712.9 | M17: 7000000
K18: TOTAL | L18: =SUM(L16:L17) -> 21212139 | M18: =SUM(M16:M17) -> 21000000
A19: weighted rD | B19: =I7*(L7/SUM(L7:L11,L16:L17))+I8*(L8/SUM(L7:L11,L16:L17))+I9*(L9/SUM(L7:L11,L16:L17))+I10*(L10/SUM(L7:L11,L16:L17))+I11*(L11/SUM(L7:L11,L16:L17))+C16*(L16/SUM(L7:L11,L16:L17))+C17*(L17/SUM(L7:L11,L16:L17)) -> 0.033540241
A21: Capital Structure
A23: In Millions of USD | B23: FY 2008 | C23: FY 2009 | D23: FY 2010 | E23: FY 2011 | F23: FY 2012 | G23: FY 2013 | H23: FY 2014 | I23: FY 2015 | K23: FY 2016 | L23: FY 2017 | M23: FY 2018E | O23: FY 2019E | P23: FY 2020E | Q23: FY 2021E | R23: FY 2022E
A25: Short-term Debt | B25: ='Balance Sheet'!B23+'Balance Sheet'!B24 -> 184 | C25: ='Balance Sheet'!C23+'Balance Sheet'!C24 -> 374.9 | D25: ='Balance Sheet'!D23+'Balance Sheet'!D24 -> 146 | E25: ='Balance Sheet'!E23+'Balance Sheet'!E24 -> 387 | F25: ='Balance Sheet'!F23+'Balance Sheet'!F24 -> 157 | G25: ='Balance Sheet'!G23+'Balance Sheet'!G24 -> 178 | H25: ='Balance Sheet'!H23+'Balance Sheet'!H24 -> 174 | I25: ='Balance Sheet'!I23+'Balance Sheet'!I24 -> 181 | K25: ='Balance Sheet'!J23+'Balance Sheet'!J24 -> 45 | L25: ='Balance Sheet'!K23+'Balance Sheet'!K24 -> 331 | M25: =M27*M33 -> 2098.6878 | O25: =O27*O33 -> 2131.3816 | P25: =P27*P33 -> 2164.5848 | Q25: =Q27*Q33 -> 2198.3052
A26: Long-term Debt | B26: ='Balance Sheet'!B30 -> 441.1 | C26: ='Balance Sheet'!C30 -> 437.2 | D26: ='Balance Sheet'!D30 -> 445.8 | E26: ='Balance Sheet'!E30 -> 276 | F26: ='Balance Sheet'!F30 -> 228 | G26: ='Balance Sheet'!G30 -> 1210 | H26: ='Balance Sheet'!H30 -> 1199 | I26: ='Balance Sheet'!I30 -> 1079 | K26: ='Balance Sheet'!J30 -> 2010 | L26: ='Balance Sheet'!K30 -> 3471 | R26: =R27*R33 -> 2232.5509
A27: weight of Debt | B27: =(B25+B26)/B33 -> 0.018276866 | C27: =(C25+C26)/C33 -> 0.028484767 | D27: =(D25+D26)/D33 -> 0.016645643 | E27: =(E25+E26)/E33 -> 0.016498447 | F27: =(F25+F26)/F33 -> 0.0077105727 | G27: =(G25+G26)/G33 -> 0.024561138 | H27: =(H25+H26)/H33 -> 0.020106993 | I27: =(I25+I26)/I33 -> 0.014254814 | K27: =(K25+K26)/K33 -> 0.021646381 | L27: =(L25+L26)/L33 -> 0.041842492 | M27: =(AVERAGE(G27:L27)+AVERAGE(B27:L27))/2 -> 0.022742587 | O27: =$M$27 -> 0.022742587 | P27: =$M$27 -> 0.022742587 | Q27: =$M$27 -> 0.022742587 | R27: =$M$27 -> 0.022742587
A29: historical Market Cap | B29: 33576.507 | C29: 27697.775 | D29: 34960.948 | E29: 39522.6 | F29: 49546.44 | G29: 55124.04 | H29: 66911.7 | I29: 87131.19 | K29: 92880.04 | L29: 87062.57
A30: preferred Equity | B30: ='Balance Sheet'!B33 -> 0.1 | C30: ='Balance Sheet'!C33 -> 0.1 | D30: ='Balance Sheet'!D33 -> 0.1 | E30: ='Balance Sheet'!E33 -> 0 | F30: ='Balance Sheet'!F33 -> 0 | G30: ='Balance Sheet'!G33 -> 0 | H30: ='Balance Sheet'!H33 -> 0 | I30: ='Balance Sheet'!I33 -> 0 | K30: ='Balance Sheet'!J33 -> 0 | L30: ='Balance Sheet'!K33 -> 0
A31: weight of Equity | B31: =(B29+B30)/B33 -> 0.98172313 | C31: =(C29+C30)/C33 -> 0.97151523 | D31: =(D29+D30)/D33 -> 0.98335436 | E31: =(E29+E30)/E33 -> 0.98350155 | F31: =(F29+F30)/F33 -> 0.99228943 | G31: =(G29+G30)/G33 -> 0.97543886 | H31: =(H29+H30)/H33 -> 0.97989301 | I31: =(I29+I30)/I33 -> 0.98574519 | K31: =(K29+K30)/K33 -> 0.97835362 | L31: =(L29+L30)/L33 -> 0.95815751
A33: Total Capital | B33: =B25+B26+B29+B30 -> 34201.707 | C33: =C25+C26+C29+C30 -> 28509.975 | D33: =D25+D26+D29+D30 -> 35552.848 | E33: =E25+E26+E29+E30 -> 40185.6 | F33: =F25+F26+F29+F30 -> 49931.44 | G33: =G25+G26+G29+G30 -> 56512.04 | H33: =H25+H26+H29+H30 -> 68284.7 | I33: =I25+I26+I29+I30 -> 88391.19 | K33: =K25+K26+K29+K30 -> 94935.04 | L33: =L25+L26+L29+L30 -> 90864.57 | M33: =L33*(1+$M$34) -> 92280.079 | O33: =M33*(1+$M$34) -> 93717.639 | P33: =O33*(1+$M$34) -> 95177.594 | Q33: =P33*(1+$M$34) -> 96660.293 | R33: =Q33*(1+$M$34) -> 98166.089
A34: % Change | C34: =(C33-B33)/B33 -> -0.16641661 | D34: =(D33-C33)/C33 -> 0.24703189 | E34: =(E33-D33)/D33 -> 0.13030607 | F34: =(F33-E33)/E33 -> 0.2425207 | G34: =(G33-F33)/F33 -> 0.13179271 | H34: =(H33-G33)/G33 -> 0.20832127 | I34: =(I33-H33)/H33 -> 0.29445088 | K34: =(K33-I33)/I33 -> 0.074032831 | L34: =(L33-K33)/K33 -> -0.042876371 | M34: =AVERAGE(K34:L34) -> 0.01557823
A35: Source: Bloomberg
A37: as of 04.10.2017
A38: Market value of debt | B38: =L18+L12 -> 3.4462671e+09
A39: Price per share | B39: ='Share Prices'!F13 -> 52.08
A40: Weighted average common shares outstanding | B40: 1657800000
A41: Diluted w. average common shares outstanding | B41: 1692000000
A43: Market value of equity = Market Cap | B43: =B39*B40 -> 86338224000

Sheet WACC
A2: NIKE Inc (NKE US) - WACC Calculation
E4: Sensitivity Analysis: rA | O4: After-tax WACC
A5: Market Value of Debt: D | B5: ='Cost of Debt'!L12+'Cost of Debt'!L18 -> 3.4462671e+09 | O5: ='Table of Contents'!J1 -> Scenario 1: Base Case | P5: =B20 -> 0.09411596
A6: Market Value of Equity: E | B6: ='Cost of Debt'!B43 -> 86338224000 | G6: Cost of Debt (rD) | O6: ='Table of Contents'!J2 -> Scenario 2: Bull Case | P6: =B21 -> 0.079998566
A7: Total Market Value of Debt and Equity: V | B7: =B6+B5 -> 8.9784491e+10 | F7: =B14 -> 0.094491073 | G7: 0.028509205 | H7: 0.030186217 | I7: 0.031863229 | J7: 0.033540241 | K7: 0.035217253 | L7: 0.036894265 | M7: 0.038571277 | O7: ='Table of Contents'!J3 -> Scenario 3: Bear Case | P7: =B22 -> 0.10823335
A8: D / V | B8: =B5/B7 -> 0.038383769 | E8: Cost of Equity (rE) | F8: 0.082385383 | G8: 0.080317412 | H8: 0.080381782 | I8: 0.080446152 | J8: 0.080510523 | K8: 0.080574893 | L8: 0.080639263 | M8: 0.080703633
A9: E / V | B9: =B6/B7 -> 0.96161623 | F9: 0.087231582 | G9: 0.084977596 | H9: 0.085041966 | I9: 0.085106336 | J9: 0.085170706 | K9: 0.085235076 | L9: 0.085299446 | M9: 0.085363816 | O9: rA
F10: 0.092077781 | G10: 0.08963778 | H10: 0.08970215 | I10: 0.08976652 | J10: 0.08983089 | K10: 0.08989526 | L10: 0.08995963 | M10: 0.090024 | O10: ='Table of Contents'!J1 -> Scenario 1: Base Case | P10: =B14 -> 0.094491073
A11: Cost of Debt (rD) | B11: ='Cost of Debt'!B19 -> 0.033540241 | F11: 0.09692398 | G11: 0.094297963 | H11: 0.094362333 | I11: 0.094426703 | J11: 0.094491073 | K11: 0.094555443 | L11: 0.094619814 | M11: 0.094684184 | O11: ='Table of Contents'!J2 -> Scenario 2: Bull Case | P11: =B15 -> 0.080317412
A12: Cost of Equity (rE) | B12: ='Cost of Equity'!N12 -> 0.09692398 | F12: 0.10177018 | G12: 0.098958147 | H12: 0.099022517 | I12: 0.099086887 | J12: 0.099151257 | K12: 0.099215627 | L12: 0.099279997 | M12: 0.099344367 | O12: ='Table of Contents'!J3 -> Scenario 3: Bear Case | P12: =B16 -> 0.10866473
F13: 0.10661638 | G13: 0.10361833 | H13: 0.1036827 | I13: 0.10374707 | J13: 0.10381144 | K13: 0.10387581 | L13: 0.10394018 | M13: 0.10400455
A14: rA Base Case | B14: =B8*B11+B9*B12 -> 0.094491073 | F14: 0.11146258 | G14: 0.10827851 | H14: 0.10834288 | I14: 0.10840725 | J14: 0.10847162 | K14: 0.10853599 | L14: 0.10860036 | M14: 0.10866473
A15: rA Bull Case | B15: =MIN(G8:M14) -> 0.080317412 | G15: 0.85 | H15: 0.9 | I15: 0.95 | J15: 1 | K15: 1.05 | L15: 1.1 | M15: 1.15
A16: rA Bear Case | B16: =MAX(G8:M14) -> 0.10866473 | F16: 0.85
F17: 0.9
A18: Marginal tax rate | B18: ='Marginal Tax Rate'!K18 -> 0.29137263 | F18: 0.95
F19: 1
A20: After-tax-WACC Base Case | B20: =B9*B12+B8*B11*(1-B18) -> 0.09411596 | F20: 1.05
A21: After-tax-WACC Bull Case | B21: =B9*F8+B8*G7*(1-B18) -> 0.079998566 | F21: 1.1
A22: After-tax-WACC Bear Case | B22: =B9*F14+B8*M7*(1-B18) -> 0.10823335 | F22: 1.15
A23: Source: own calculations

Sheet DCF
A2: NIKE Inc (NKE US) - Discounted Cash Flows
A4: Projected Cash Flows | H4: Discounted Cash Flows
A6: Case selection for cash flow projection: | H6: Case selection for WACC:
A7: Scenario 1: Base Case | H7: Scenario 1: Base Case | J7: >> WACC: | K7: =INDEX(WACC!O5:P7,MATCH(DCF!H7,WACC!O5:O7,0),2) -> 0.09411596
A9: In Millions of USD | B9: FY 2018E | C9: FY 2019E | D9: FY 2020E | E9: FY 2021E | F9: FY 2022E | H9: In Millions of USD | I9: FY 2018E | J9: FY 2019E | K9: FY 2020E | L9: FY 2021E | M9: FY 2022E
A11: Free Cash Flow | B11: {=INDEX('Free Cash Flows'!$D$22:$H$24,MATCH(DCF!$A$7,'Free Cash Flows'!$C$22:$C$24,0),MATCH(DCF!B9,'Free Cash Flows'!$D$21:$H$21,0))} -> 4867.6183 | C11: {=INDEX('Free Cash Flows'!$D$22:$H$24,MATCH(DCF!$A$7,'Free Cash Flows'!$C$22:$C$24,0),MATCH(DCF!C9,'Free Cash Flows'!$D$21:$H$21,0))} -> 5251.4318 | D11: {=INDEX('Free Cash Flows'!$D$22:$H$24,MATCH(DCF!$A$7,'Free Cash Flows'!$C$22:$C$24,0),MATCH(DCF!D9,'Free Cash Flows'!$D$21:$H$21,0))} -> 5666.3935 | E11: {=INDEX('Free Cash Flows'!$D$22:$H$24,MATCH(DCF!$A$7,'Free Cash Flows'!$C$22:$C$24,0),MATCH(DCF!E9,'Free Cash Flows'!$D$21:$H$21,0))} -> 6115.0279 | F11: {=INDEX('Free Cash Flows'!$D$22:$H$24,MATCH(DCF!$A$7,'Free Cash Flows'!$C$22:$C$24,0),MATCH(DCF!F9,'Free Cash Flows'!$D$21:$H$21,0))} -> 6600.064 | H11: Present Value of Free Cash Flow | I11: =I14*B11 -> 4448.9053 | J11: =J14*C11 -> 4386.8322 | K11: =K14*D11 -> 4326.3004 | L11: =L14*E11 -> 4267.2199 | M11: =M14*F11 -> 4209.5084
H13: Discounting Period | I13: 1 | J13: =I13+1 -> 2 | K13: =J13+1 -> 3 | L13: =K13+1 -> 4 | M13: =L13+1 -> 5
A14: Present Value of Nike Inc. | H14: Discounting Factor | I14: =1/((1+$K$7)^I13) -> 0.9139799 | J14: =1/((1+$K$7)^J13) -> 0.83535926 | K14: =1/((1+$K$7)^K13) -> 0.76350158 | L14: =1/((1+$K$7)^L13) -> 0.6978251 | M14: =1/((1+$K$7)^M13) -> 0.63779812
A16: Free cash flow terminal year | B16: =DCF!F11 -> 6600.064
A17: Inflation rate (as of 09/2017) | B17: 0.022
A18: GDP growth rate (as of Q2/2017) | B18: 0.0384
A19: Perpetuity growth rate | B19: =0.25*B17+0.75*B18 -> 0.0343
A20: Terminal Value | B20: =B16*(1+B19)/(K7-B19) -> 114124.16
A21: Discount Factor | B21: =1/((1+DCF!K7)^DCF!M13) -> 0.63779812
A22: PV of Terminal Value | B22: =B20*B21 -> 72788.174
A24: Enterprise Value (EV) | B24: =B22+DCF!I11+DCF!J11+DCF!K11+DCF!L11+DCF!M11 -> 94426.94 | E24: =ROUND(((B26-'Share Prices'!F13)/'Share Prices'!F13),3) -> 0.094
A26: Share Price (in $) | B26: =B24/'Income Statement'!K45 -> 56.959187 | C26: =IF(B26>'Share Prices'!F13,CONCATENATE("undervalued by ",(E24*100),"%"),CONCATENATE("overvalued by ",((-1*E24)*100),"%")) -> undervalued by 9,4%
A27: Source: own calculations
A29: Remark: If both scenarios are adapted - for instance, to the Bull Case - the derived EV will strongly deviate from the Base Case calculation due to the fact that an optimistic cash flow projection and an optimistic WACC will raise the EV to a much higher power. These extreme cases are assumed to be very unrealistic. Therefore, it is recommended to only change one of the parameters at a time in order to realistically calculate the EV. | I29: 93827.415 | J29: 94426.94
J30: =(J29-I29)/J29 -> 0.0063490982
J32: =J29/I29 -> 1.0063897

Sheet Share Prices
A2: NIKE Inc (NKE US) - Share Prices
A4: Share Prices | E4: Share Prices | I4: Total Returns | M4: Total Returns
A5: Security | B5: NKE US Equity | E5: Security | F5: NKE US Equity | I5: Security | J5: NKE US Equity | M5: Security | N5: NKE US Equity
A6: Start Date | B6: 36830 | E6: Start Date | F6: 40452 | I6: Start Date | J6: 36830 | M6: Start Date | N6: 41183
A7: End Date | B7: 43007 | E7: End Date | F7: 43013 | I7: End Date | J7: 43007 | M7: End Date | N7: 43027
A8: Period | B8: Monthly | E8: Period | F8: Daily | I8: Period | J8: Monthly | M8: Period | N8: Daily
A9: Currency | B9: USD | E9: Currency | F9: USD | I9: Currency | J9: USD | M9: Currency | N9: USD
A10: Source: | B10: Bloomberg | E10: Source: | F10: Bloomberg | I10: Source: | J10: Bloomberg | M10: Source: | N10: Bloomberg
A12: Date | B12: PX_LAST | C12: PX_VOLUME | E12: Date | F12: PX_LAST | G12: PX_VOLUME | I12: Date | J12: TOT_RETURN_INDEX_GROSS_DVDS | K12: TOT_RETURN_INDEX_NET_DVDS | M12: Date | N12: TOT_RETURN_INDEX_GROSS_DVDS | O12: TOT_RETURN_INDEX_NET_DVDS
A13: 43007 | B13: 51.85 | C13: 212311860 | E13: 43012 | F13: 52.08 | G13: 8204280 | I13: 36830 | J13: 4.9922 | K13: 4.9922 | M13: 43026 | N13: 55.6657 | O13: 55.6657
A14: 42978 | B14: 52.81 | C14: 174951250 | E14: 43011 | F14: 51.47 | G14: 8126729 | I14: 36860 | J14: 5.3281 | K14: 5.3281 | M14: 43025 | N14: 55.3464 | O14: 55.3464
A15: 42947 | B15: 59.05 | C15: 158127101 | E15: 43010 | F15: 51.87 | G15: 7516205 | I15: 36889 | J15: 6.9916 | K15: 6.9916 | M15: 43024 | N15: 54.6758 | O15: 54.6758
A16: 42916 | B16: 59 | C16: 275425135 | E16: 43007 | F16: 51.85 | G16: 12189882 | I16: 36922 | J16: 6.8923 | K16: 6.8923 | M16: 43021 | N16: 54.2607 | O16: 54.2607
A17: 42886 | B17: 52.99 | C17: 223448944 | E17: 43006 | F17: 52.63 | G17: 11334704 | I17: 36950 | J17: 4.8917 | K17: 4.8917 | M17: 43020 | N17: 54.1011 | O17: 54.1011
A18: 42853 | B18: 55.41 | C18: 137922961 | E18: 43005 | F18: 52.67 | G18: 36202500 | I18: 36980 | J18: 5.0947 | K18: 5.0947 | M18: 43019 | N18: 54.3139 | O18: 54.3139
A19: 42825 | B19: 55.73 | C19: 249523050 | E19: 43004 | F19: 53.7 | G19: 16183717 | I19: 37011 | J19: 5.253 | K19: 5.253 | M19: 43018 | N19: 54.8461 | O19: 54.8461
A20: 42794 | B20: 57.16 | C20: 178369648 | E20: 43003 | F20: 53.23 | G20: 12262360 | I20: 37042 | J20: 5.1638 | K20: 5.1638 | M20: 43017 | N20: 54.8355 | O20: 54.8355
A21: 42766 | B21: 52.9 | C21: 175931076 | E21: 43000 | F21: 53.24 | G21: 10962392 | I21: 37071 | J21: 5.2907 | K21: 5.2907 | M21: 43014 | N21: 55.7934 | O21: 55.7934
A22: 42734 | B22: 50.83 | C22: 215471219 | E22: 42999 | F22: 53.19 | G22: 8065367 | I22: 37103 | J22: 5.9912 | K22: 5.9912 | M22: 43013 | N22: 55.5379 | O22: 55.5379
A23: 42704 | B23: 50.07 | C23: 166220023 | E23: 42998 | F23: 53.56 | G23: 7058002 | I23: 37134 | J23: 6.2999 | K23: 6.2999 | M23: 43012 | N23: 55.4315 | O23: 55.4315
A24: 42674 | B24: 50.18 | C24: 190327931 | E24: 42997 | F24: 53.33 | G24: 14707174 | I24: 37162 | J24: 5.9131 | K24: 5.9131 | M24: 43011 | N24: 54.7823 | O24: 54.7823
... A216: 36830 | B216: 4.9922 | C216: 181374400 | E216: 42717 | F216: 52.3 | G216: 11442327 | I216: 43007 | J216: 64.6032 | K216: 64.6032 | M216: 42732 | N216: 53.7658 | O216: 53.7658
E217: 42716 | F217: 51.54 | G217: 11459541 | M217: 42731 | N217: 54.0503 | O217: 54.0503
E218: 42713 | F218: 51.72 | G218: 5869828 | M218: 42727 | N218: 54.7037 | O218: 54.7037
E219: 42712 | F219: 51.55 | G219: 9260850 | M219: 42726 | N219: 54.9461 | O219: 54.9461
E220: 42711 | F220: 52.1 | G220: 10412638 | M220: 42725 | N220: 55.1147 | O220: 55.1147
E221: 42710 | F221: 50.57 | G221: 12496332 | M221: 42724 | N221: 54.5772 | O221: 54.5772
E222: 42709 | F222: 51.85 | G222: 12031170 | M222: 42723 | N222: 53.5866 | O222: 53.5866
E223: 42706 | F223: 50.46 | G223: 6933279 | M223: 42720 | N223: 53.6604 | O223: 53.6604
E224: 42705 | F224: 50.65 | G224: 7610063 | M224: 42719 | N224: 54.0503 | O224: 54.0503
E225: 42704 | F225: 50.07 | G225: 8198418 | M225: 42718 | N225: 54.5772 | O225: 54.5772
E226: 42703 | F226: 50.63 | G226: 6065682 | M226: 42717 | N226: 55.1147 | O226: 55.1147
E227: 42702 | F227: 51.01 | G227: 8602118 | M227: 42716 | N227: 54.3138 | O227: 54.3138
E228: 42699 | F228: 51.52 | G228: 2736767 | M228: 42713 | N228: 54.5035 | O228: 54.5035
... E1283: 41169 | F1283: 24.4925 | G1283: 9378872 | M1283: 41183 | N1283: 23.8875 | O1283: 23.8875
E1284: 41166 | F1284: 24.16 | G1284: 22892364
E1285: 41165 | F1285: 24.8 | G1285: 17325628
E1286: 41164 | F1286: 25.21 | G1286: 9197820
E1287: 41163 | F1287: 24.92 | G1287: 9840004
E1288: 41162 | F1288: 25.01 | G1288: 8678360
E1289: 41159 | F1289: 24.8225 | G1289: 6991508
E1290: 41158 | F1290: 24.865 | G1290: 9090548
E1291: 41157 | F1291: 24.3375 | G1291: 6288000
E1292: 41156 | F1292: 24.315 | G1292: 7589144
E1293: 41152 | F1293: 24.34 | G1293: 8129188
E1294: 41151 | F1294: 24.4375 | G1294: 7020252
E1295: 41150 | F1295: 24.6725 | G1295: 9467856
... E1777: 40452 | F1777: 20.0625 | G1777: 14170220

Sheet APV
A2: NIKE Inc (NKE US) - Adjusted Present Value
A4: Projected Cash Flows | H4: Discounted Cash Flows
A6: Case selection for cash flow projection: | H6: Case selection for rA:
A7: Scenario 1: Base Case | H7: Scenario 1: Base Case | J7: >> rA: | K7: =INDEX(WACC!P10:P12,MATCH(APV!H7,WACC!O10:O12,0),1) -> 0.094491073
A9: In Millions of USD | B9: FY 2018E | C9: FY 2019E | D9: FY 2020E | E9: FY 2021E | F9: FY 2022E | H9: In Millions of USD | I9: FY 2018E | J9: FY 2019E | K9: FY 2020E | L9: FY 2021E | M9: FY 2022E
A11: Free Cash Flow | B11: {=INDEX('Free Cash Flows'!$D$22:$H$24,MATCH($A$7,'Free Cash Flows'!$C$22:$C$24,0),MATCH(B9,'Free Cash Flows'!$D$21:$H$21,0))} -> 4867.6183 | C11: {=INDEX('Free Cash Flows'!$D$22:$H$24,MATCH($A$7,'Free Cash Flows'!$C$22:$C$24,0),MATCH(C9,'Free Cash Flows'!$D$21:$H$21,0))} -> 5251.4318 | D11: {=INDEX('Free Cash Flows'!$D$22:$H$24,MATCH($A$7,'Free Cash Flows'!$C$22:$C$24,0),MATCH(D9,'Free Cash Flows'!$D$21:$H$21,0))} -> 5666.3935 | E11: {=INDEX('Free Cash Flows'!$D$22:$H$24,MATCH($A$7,'Free Cash Flows'!$C$22:$C$24,0),MATCH(E9,'Free Cash Flows'!$D$21:$H$21,0))} -> 6115.0279 | F11: {=INDEX('Free Cash Flows'!$D$22:$H$24,MATCH($A$7,'Free Cash Flows'!$C$22:$C$24,0),MATCH(F9,'Free Cash Flows'!$D$21:$H$21,0))} -> 6600.064 | H11: Present Value of Free Cash Flow | I11: =I14*B11 -> 4447.3806 | J11: =J14*C11 -> 4383.8257 | K11: =K14*D11 -> 4321.8536 | L11: =L14*E11 -> 4261.373 | M11: =M14*F11 -> 4202.2997
H13: Discounting Period | I13: 1 | J13: =I13+1 -> 2 | K13: =J13+1 -> 3 | L13: =K13+1 -> 4 | M13: =L13+1 -> 5
A14: Adjusted Present Value of Nike Inc. | H14: Discounting Factor | I14: =1/((1+$K$7)^I13) -> 0.91366666 | J14: =1/((1+$K$7)^J13) -> 0.83478676 | K14: =1/((1+$K$7)^K13) -> 0.76271683 | L14: =1/((1+$K$7)^L13) -> 0.69686893 | M14: =1/((1+$K$7)^M13) -> 0.63670591
A16: Total Capital terminal year | B16: ='Cost of Debt'!R33 -> 98166.089
A17: Debt Ratio terminal year | B17: ='Cost of Debt'!R27 -> 0.022742587
A19: Inflation rate (as of 09/2017) | B19: 0.022
A20: GDP growth rate (as of Q2/2017) | B20: 0.0384 | F20: Cash Flows | H20: Scenario 1: Base Case | I20: {=INDEX('Free Cash Flows'!$D$22:$H$24,MATCH($H$20,'Free Cash Flows'!$C$22:$C$24,0),MATCH(B9,'Free Cash Flows'!$D$21:$H$21,0))} -> 4867.6183 | J20: {=INDEX('Free Cash Flows'!$D$22:$H$24,MATCH($H$20,'Free Cash Flows'!$C$22:$C$24,0),MATCH(C9,'Free Cash Flows'!$D$21:$H$21,0))} -> 5251.4318 | K20: {=INDEX('Free Cash Flows'!$D$22:$H$24,MATCH($H$20,'Free Cash Flows'!$C$22:$C$24,0),MATCH(D9,'Free Cash Flows'!$D$21:$H$21,0))} -> 5666.3935 | L20: {=INDEX('Free Cash Flows'!$D$22:$H$24,MATCH($H$20,'Free Cash Flows'!$C$22:$C$24,0),MATCH(E9,'Free Cash Flows'!$D$21:$H$21,0))} -> 6115.0279 | M20: {=INDEX('Free Cash Flows'!$D$22:$H$24,MATCH($H$20,'Free Cash Flows'!$C$22:$C$24,0),MATCH(F9,'Free Cash Flows'!$D$21:$H$21,0))} -> 6600.064
A21: Perpetuity growth rate | B21: =AVERAGE(B19:B20) -> 0.0302 | F21: rA | H21: Scenario 1: Base Case | I21: {=INDEX(WACC!P10:P12,MATCH(APV!H21,WACC!O10:O12,0),1)} -> 0.094491073
A22: Discount factor | B22: =1/(1+K7)^M13 -> 0.63670591 | H22: Discounting Factor | I22: =1/((1+$I$21)^I13) -> 0.91366666 | J22: =1/((1+$I$21)^J13) -> 0.83478676 | K22: =1/((1+$I$21)^K13) -> 0.76271683 | L22: =1/((1+$I$21)^L13) -> 0.69686893 | M22: =1/((1+$I$21)^M13) -> 0.63670591
A23: Terminal year debt balance | B23: =B16*B17 -> 2232.5509 | H23: Present Value of Cash Flows | I23: =I20*I22 -> 4447.3806 | J23: =J20*J22 -> 4383.8257 | K23: =K20*K22 -> 4321.8536 | L23: =L20*L22 -> 4261.373 | M23: =M20*M22 -> 4202.2997
A24: Terminal value of tax shield | B24: ='Marginal Tax Rate'!K18*B23*'Cost of Equity'!N12*(1+APV!B21)/('Cost of Equity'!N12-APV!B21)^2 -> 14589.453
A26: Present value of tax shield | B26: =B24*B22 -> 9289.1911
A28: q | B28: =(1.26+2.01)/2 -> 1.635 | C28: q = corporate bond spread over Treasuries 1) | H28: PV of terminal value:
A29: ϕ | B29: =(0.1+0.23)/2*100 -> 16.5 | C29: ϕ = total loss in % of pre-distress firm value 2) | F29: PV of terminal value | H29: Scenario 1: Base Case | I29: =M20*(1+B36)/(I21-B36)*M22 -> 72210.685
A30: rF | B30: 2.33 | C30: rF = risk free rate 3) | F30: PV of tax shield | H30: Scenario 1: Base Case | I30: =B24*M22 -> 9289.1911
A31: Φ | B31: =(B28/(B28+B30))*B29 -> 6.8039092 | C31: Φ = NPV of FD in % of pre-distress firm value | F31: Cost of financial distress | H31: Scenario 1: Base Case | I31: =B31*(I29+SUM(I23:M23))/100 -> 6383.9323
A33: Costs of Financial Distress (CFD) 4) | B33: =B31*(B39+SUM(I11:M11))/100 -> 6383.9323 | F33: Enterprise value | I33: =I29+SUM(I23:M23)+I30-I31 -> 96732.676
A35: Free cash flow terminal year | B35: =F11 -> 6600.064
A36: Perpetuity growth rate | B36: =DCF!B19 -> 0.0343
A37: Terminal Value | B37: =B35*(1+B36)/(K7-B36) -> 113412.93
A38: Discount Factor | B38: =1/(1+K7)^M13 -> 0.63670591
A39: PV of Terminal Value | B39: =B37*B38 -> 72210.685
A41: Enterprise Value | B41: =B39+SUM(I11:M11)+B26-B33 -> 96732.676 | E41: =ROUND(((B43-'Share Prices'!F13)/'Share Prices'!F13),3) -> 0.12
A43: Share Price (in $) | B43: =B41/'Income Statement'!K45 -> 58.350028 | C43: =IF(B43>'Share Prices'!F13,CONCATENATE("undervalued by ",(E41*100),"%"),CONCATENATE("overvalued by ",((-1*E41)*100),"%")) -> undervalued by 12%
A44: Source: own calculations
A46: 1) average between Aaa and Baa Bonds, since Nike is A1 rated by Moody's and AA- rated by S&P; see FRED Economic Data, as of 04.10.2017
A47: 2) average of estimation in range of 10-23% of pre-distress firm value; see Gregor Andrade and Steven Kaplan, (1998), “How Costly is Financial (not Economic) Distress? Evidence from Highly Leveraged Transactions that Become Distressed,” Journal of Finance 53, pp. 1443-1493
A48: 3) 10 years Treasury Bill as of 04.10.2017; see US Department of the Treasury as of 04.10.2017
A49: 4) see Heitor Almeida, University of Illinois at Urbana-Champaign, and Thomas Philippon, New York University in: Journal of Applied Corporate Finance; Volume 20 Number 4

Sheet Trading Multiples
N1: EBITDA 2022E
A2: NIKE Inc (NKE US) - Trading Multiples
A4: Comparable Sportswear Companies | B4: Price per Share | C4: Market | D4: Enterprise | E4: Enterprise Value/EBITDA | H4: EBITDA LTM | I4: Bookvalue of Equity | J4: Shares Outstanding | K4: Current Shares Outstanding | L4: Diluted EPS | M4: P/E Ratio | N4: Price/Book Ratio
A5: In Millions of USD except Per Share | C5: Capitalization | D5: Value | E5: FY 2017 | F5: FY 2018 | G5: FY 2019
A6: Nike | B6: 52.69 | C6: 85964.707 | D6: 84259.707 | E6: 15.776017 | F6: 15.517644 | G6: 13.947809 | H6: 5341 | I6: =11992999936/1000000 -> 11993 | J6: 1636.9999 | K6: 1302.273 | L6: =I6/K6 -> 9.2092825 | M6: 22.421276 | N6: 7.1919893
A7: Adidas | B7: 220.492 | C7: 46130.506 | D7: 46447.939 | E7: 18.125747 | F7: 16.131951 | G7: 13.806369 | H7: 2367.9244 | I7: =6990462492.48889/1000000 -> 6990.4625 | J7: 202.65734 | K7: 209.2162 | L7: =I7/K7 -> 33.412625 | M7: 31.881571 | N7: 6.1810325
A8: VF Corporation | B8: 65.35 | C8: 25723.155 | D8: 28337.128 | E8: 15.003493 | F8: 14.84601 | G8: 13.988193 | H8: 1888.702 | I8: =3644338944/1000000 -> 3644.3389 | J8: 393.30867 | K8: 393.6213 | L8: =I8/K8 -> 9.2584902 | M8: 22.367987 | N8: 7.0527802
A9: Lululemon | B9: 60.09 | C9: 8135.1073 | D9: 7413.8953 | E9: 14.289395 | F9: 12.832781 | G9: 11.802878 | H9: 518.839 | I9: =1397809024/1000000 -> 1397.809 | J9: 135.478 | K9: 125.6011 | L9: =I9/K9 -> 11.128955 | M9: 28.15848 | N9: 5.8240239
A10: Under Amour | B10: 16.45 | C10: 6912.755 | D10: 7701.787 | E10: 14.581388 | F10: 17.321399 | G10: 14.862347 | H10: 528.193 | I10: =2023771008/1000000 -> 2023.771 | J10: 440.92259 | K10: 184.9505 | L10: =I10/K10 -> 10.942231 | M10: 34.060088 | N10: 3.5839909
A11: Puma | B11: 408.8803 | C11: 6166.9224 | D11: 5921.2551 | E11: N/A | F11: 16.888461 | G11: 13.411341 | H11: 372 | I11: =1876297139.16779/1000000 -> 1876.2971 | J11: 15.082464 | K11: 15.08246 | L11: =I11/K11 -> 124.40259 | M11: 48.727147 | N11: 3.233005
A12: Columbia Sportswear | B12: 60.8 | C12: 4240.615 | D12: 3643.775 | E12: 11.351607 | F12: 11.234672 | G12: 10.394956 | H12: 320.992 | I12: =1572199936/1000000 -> 1572.1999 | J12: 69.686 | K12: 69.74696 | L12: =I12/K12 -> 22.541483 | M12: 21.930892 | N12: 2.7391268
A13: Skechers | B13: 24.03 | C13: 3807.0977 | D13: 3204.8747 | E13: N/A | F13: 7.4034561 | G13: 5.9681093 | H13: 417.087 | I13: =1999697024/1000000 -> 1999.697 | J13: 158.43104 | K13: 133.8858 | L13: =I13/K13 -> 14.935841 | M13: 14.919276 | N13: 2.0220362
A14: Asics | B14: 15.21758 | C14: 3042.9534 | D14: 3029.7892 | E14: 10.638026 | F14: 10.57849 | G14: 9.5237582 | H14: 296.32196 | I14: =1762937236.01272/1000000 -> 1762.9372 | J14: 189.82264 | K14: 199.963 | L14: =I14/K14 -> 8.8163172 | M14: 21.2433 | N14: 1.6629617
A15: Geox | B15: 4.168466 | C15: 1080.4969 | D15: 1117.8491 | E15: 13.183676 | F15: 13.04961 | G15: 9.9034868 | H15: 78.420597 | I15: =395001616.332687/1000000 -> 395.00162 | J15: 259.20733 | K15: 259.2073 | L15: =I15/K15 -> 1.5238831 | M15: 93.82139 | N15: 2.6587441
A16: Average (excl. Nike) | B16: =AVERAGE(B7:B15) -> 97.275372 | C16: =AVERAGE(C7:C15) -> 11693.29 | D16: =AVERAGE(D7:D15) -> 11868.699 | E16: =AVERAGE(E7:E15) -> 13.881905 | F16: =AVERAGE(F7:F15) -> 13.365203 | G16: =AVERAGE(G7:G15) -> 11.517938 | H16: =AVERAGE(H7:H15) -> 754.27555 | I16: =AVERAGE(I7:I15) -> 2406.946 | ... N16: =AVERAGE(N7:N15) -> 3.884189
A17: 1st Quartile (excl. Nike) | B17: =_xlfn.QUARTILE.EXC(B7:B15,1) -> 15.83379 | C17: =_xlfn.QUARTILE.EXC(C7:C15,1) -> 3425.0256 | D17: =_xlfn.QUARTILE.EXC(D7:D15,1) -> 3117.332 | E17: =_xlfn.QUARTILE.EXC(E7:E15,1) -> 11.351607 | F17: =_xlfn.QUARTILE.EXC(F7:F15,1) -> 10.906581 | G17: =_xlfn.QUARTILE.EXC(G7:G15,1) -> 9.7136225 | H17: =_xlfn.QUARTILE.EXC(H7:H15,1) -> 308.65698 | I17: =_xlfn.QUARTILE.EXC(I7:I15,1) -> 1485.0045 | ... N17: =_xlfn.QUARTILE.EXC(N7:N15,1) -> 2.3403901
A18: Median (excl. Nike) | B18: =MEDIAN(B7:B15) -> 60.09 | C18: =MEDIAN(C7:C15) -> 6166.9224 | D18: =MEDIAN(D7:D15) -> 5921.2551 | E18: =MEDIAN(E6:E15) -> 14.435391 | F18: =MEDIAN(F6:F15) -> 13.94781 | G18: =MEDIAN(G6:G15) -> 12.60711 | H18: =MEDIAN(H6:H15) -> 467.963 | I18: =MEDIAN(I6:I15) -> 1937.9971 | J18: =MEDIAN(J6:J15) -> 196.23999 | K18: =MEDIAN(K6:K15) -> 192.45675 | L18: =MEDIAN(L6:L15) -> 11.035593 | ... N18: =MEDIAN(N6:N15) -> 3.4084979
A19: 3rd Quartile (excl. Nike) | B19: =_xlfn.QUARTILE.EXC(B7:B15,3) -> 142.921 | C19: =_xlfn.QUARTILE.EXC(C7:C15,3) -> 16929.131 | D19: =_xlfn.QUARTILE.EXC(D7:D15,3) -> 18019.458 | E19: =_xlfn.QUARTILE.EXC(E7:E15,3) -> 15.003493 | F19: =_xlfn.QUARTILE.EXC(F7:F15,3) -> 16.510206 | G19: =_xlfn.QUARTILE.EXC(G7:G15,3) -> 13.897281 | H19: =_xlfn.QUARTILE.EXC(H7:H15,3) -> 1208.4475 | I19: =_xlfn.QUARTILE.EXC(I7:I15,3) -> 2834.055 | ... N19: =_xlfn.QUARTILE.EXC(N7:N15,3) -> 6.0025282
A20: Bloomberg (as of 20.10.2017)
A23: 1. Value Multiples Based on Cash flows
A24: Comparable Sportswear Companies | B24: Enterprise Value | C24: EBITDA LTM (1) | D24: EBITDA LTM (2) | E24: EV/EBITDA LTM | F24: EV/EBITDA LTM | G24: EV Nike (Calculated) | H24: EV Nike
A25: In Millions of USD except Per Share
A26: Nike | B26: =D6 -> 84259.707 | C26: =H6 -> 5341 | D26: =B26/F26 -> 5341 | E26: =B26/C26 -> 15.776017 | F26: =E6 -> 15.776017
A27: Adidas | B27: =D7 -> 46447.939 | C27: =H7 -> 2367.9244 | D27: =B27/F27 -> 2562.5393 | E27: =B27/C27 -> 19.615466 | F27: =E7 -> 18.125747 | G27: =E27*$C$26 -> 104766.2 | H27: =F27*$D$26 -> 96809.615
A28: VF Corporation | B28: =D8 -> 28337.128 | C28: =H8 -> 1888.702 | D28: =B28/F28 -> 1888.702 | E28: =B28/C28 -> 15.003493 | F28: =E8 -> 15.003493 | G28: =E28*$C$26 -> 80133.659 | H28: =F28*$D$26 -> 80133.659
A29: Lululemon | B29: =D9 -> 7413.8953 | C29: =H9 -> 518.839 | D29: =B29/F29 -> 518.839 | E29: =B29/C29 -> 14.289395 | F29: =E9 -> 14.289395 | G29: =E29*$C$26 -> 76319.658 | H29: =F29*$D$26 -> 76319.658
A30: Under Amour | B30: =D10 -> 7701.787 | C30: =H10 -> 528.193 | D30: =B30/F30 -> 528.193 | E30: =B30/C30 -> 14.581388 | F30: =E10 -> 14.581388 | G30: =E30*$C$26 -> 77879.192 | H30: =F30*$D$26 -> 77879.192
A31: Puma | B31: =D11 -> 5921.2551 | C31: =H11 -> 372 | D31: =B31/F31 -> 350.60951 | E31: =B31/C31 -> 15.917352 | F31: =F11 -> 16.888461 | G31: =E31*$C$26 -> 85014.58 | H31: =F31*$D$26 -> 90201.271
A32: Columbia Sportswear | B32: =D12 -> 3643.775 | C32: =H12 -> 320.992 | D32: =B32/F32 -> 320.992 | E32: =B32/C32 -> 11.351607 | F32: =E12 -> 11.351607 | G32: =E32*$C$26 -> 60628.932 | H32: =F32*$D$26 -> 60628.932
A33: Skechers | B33: =D13 -> 3204.8747 | C33: =H13 -> 417.087 | D33: =B33/F33 -> 432.889 | E33: =B33/C33 -> 7.6839477 | F33: =F13 -> 7.4034561 | G33: =E33*$C$26 -> 41039.965 | H33: =F33*$D$26 -> 39541.859
A34: Asics | B34: =D14 -> 3029.7892 | C34: =H14 -> 296.32196 | D34: =B34/F34 -> 284.80746 | E34: =B34/C34 -> 10.224653 | F34: =E14 -> 10.638026 | G34: =E34*$C$26 -> 54609.873 | H34: =F34*$D$26 -> 56817.699
A35: Geox | B35: =D15 -> 1117.8491 | C35: =H15 -> 78.420597 | D35: =B35/F35 -> 84.790398 | E35: =B35/C35 -> 14.254535 | F35: =E15 -> 13.183676 | G35: =E35*$C$26 -> 76133.471 | H35: =F35*$D$26 -> 70414.014
A36: Median Peer Group | B36: =MEDIAN(B27:B35) -> 5921.2551 | C36: =MEDIAN(C27:C35) -> 417.087 | D36: =MEDIAN(D27:D35) -> 432.889 | E36: =MEDIAN(E27:E35) -> 14.289395 | F36: =MEDIAN(F27:F35) -> 14.289395 | G36: =MEDIAN(G27:G35) -> 76319.658 | H36: =MEDIAN(H27:H35) -> 76319.658
A37: 1st Quartile (excl. Nike) | B37: =_xlfn.QUARTILE.EXC(B27:B35,1) -> 3117.332 | C37: =_xlfn.QUARTILE.EXC(C27:C35,1) -> 308.65698 | D37: =_xlfn.QUARTILE.EXC(D27:D35,1) -> 302.89973 | E37: =_xlfn.QUARTILE.EXC(E27:E35,1) -> 10.78813 | F37: =_xlfn.QUARTILE.EXC(F27:F35,1) -> 10.994817 | G37: =_xlfn.QUARTILE.EXC(G27:G35,1) -> 57619.402 | H37: =_xlfn.QUARTILE.EXC(H27:H35,1) -> 58723.315
A38: 3rd Quartile (excl. Nike) | B38: =_xlfn.QUARTILE.EXC(B27:B35,3) -> 18019.458 | C38: =_xlfn.QUARTILE.EXC(C27:C35,3) -> 1208.4475 | D38: =_xlfn.QUARTILE.EXC(D27:D35,3) -> 1208.4475 | E38: =_xlfn.QUARTILE.EXC(E27:E35,3) -> 15.460423 | F38: =_xlfn.QUARTILE.EXC(F27:F35,3) -> 15.945977 | G38: =_xlfn.QUARTILE.EXC(G27:G35,3) -> 82574.119 | H38: =_xlfn.QUARTILE.EXC(H27:H35,3) -> 85167.465
A39: Bloomberg (as of 20.10.2017)
A42: 2. Multiples Based On Assets
A43: Comparable Sportswear Companies | B43: Price per Share | C43: Shares Outstanding | D43: Market Value of Equity | E43: Book Value of Equity | F43: Price/Book Ratio (1) | G43: Price/Book Ratio (2) | H43: BV Equity based on P/B (1) | I43: BV Equity based on P/B (2) | J43: EV Nike based on P/B (2)
A44: In Millions of USD except Per Share
A45: Nike | B45: ='Trading Multiples'!B6 -> 52.69 | C45: =J6 -> 1636.9999 | D45: =B45*C45 -> 86253.527 | E45: =I6 -> 11993 | F45: =D45/E45 -> 7.1919893 | G45: =N6 -> 7.1919893
A46: Adidas | B46: =B7 -> 220.492 | C46: =J7 -> 202.65734 | D46: =B46*C46 -> 44684.323 | E46: =I7 -> 6990.4625 | F46: =D46/E46 -> 6.3921841 | G46: =N7 -> 6.1810325 | H46: =F46*$E$45 -> 76661.463 | I46: =G46*$E$45 -> 74129.123 | J46: =I46+$B$79 -> 77606.123
A47: VF Corporation | B47: =B8 -> 65.35 | C47: =J8 -> 393.30867 | D47: =B47*C47 -> 25702.722 | E47: =I8 -> 3644.3389 | F47: =D47/E47 -> 7.0527802 | G47: =N8 -> 7.0527802 | H47: =F47*$E$45 -> 84583.993 | I47: =G47*$E$45 -> 84583.992 | J47: =I47+$B$79 -> 88060.992
A48: Lululemon | B48: =B9 -> 60.09 | C48: =J9 -> 135.478 | D48: =B48*C48 -> 8140.873 | E48: =I9 -> 1397.809 | F48: =D48/E48 -> 5.8240238 | G48: =N9 -> 5.8240239 | H48: =F48*$E$45 -> 69847.517 | I48: =G48*$E$45 -> 69847.518 | J48: =I48+$B$79 -> 73324.518
A49: Under Amour | B49: =B10 -> 16.45 | C49: =J10 -> 440.92259 | D49: =B49*C49 -> 7253.1766 | E49: =I10 -> 2023.771 | F49: =D49/E49 -> 3.5839908 | G49: =N10 -> 3.5839909 | H49: =F49*$E$45 -> 42982.801 | I49: =G49*$E$45 -> 42982.803 | J49: =I49+$B$79 -> 46459.803
A50: Puma | B50: =B11 -> 408.8803 | C50: =J11 -> 15.082464 | D50: =B50*C50 -> 6166.9224 | E50: =I11 -> 1876.2971 | F50: =D50/E50 -> 3.2867515 | G50: =N11 -> 3.233005 | H50: =F50*$E$45 -> 39418.01 | I50: =G50*$E$45 -> 38773.429 | J50: =I50+$B$79 -> 42250.429
A51: Columbia Sportswear | B51: =B12 -> 60.8 | C51: =J12 -> 69.686 | D51: =B51*C51 -> 4236.9088 | E51: =I12 -> 1572.1999 | F51: =D51/E51 -> 2.6948919 | G51: =N12 -> 2.7391268 | H51: =F51*$E$45 -> 32319.838 | I51: =G51*$E$45 -> 32850.348 | J51: =I51+$B$79 -> 36327.348
A52: Skechers | B52: =B13 -> 24.03 | C52: =J13 -> 158.43104 | D52: =B52*C52 -> 3807.0979 | E52: =I13 -> 1999.697 | F52: =D52/E52 -> 1.9038374 | G52: =N13 -> 2.0220362 | H52: =F52*$E$45 -> 22832.721 | I52: =G52*$E$45 -> 24250.28 | J52: =I52+$B$79 -> 27727.28
A53: Asics | B53: =B14 -> 15.21758 | C53: =J14 -> 189.82264 | D53: =B53*C53 -> 2888.6412 | E53: =I14 -> 1762.9372 | F53: =D53/E53 -> 1.6385389 | G53: =N14 -> 1.6629617 | H53: =F53*$E$45 -> 19650.997 | I53: =G53*$E$45 -> 19943.899 | J53: =I53+$B$79 -> 23420.899
A54: Geox | B54: =B15 -> 4.168466 | C54: =J15 -> 259.20733 | D54: =B54*C54 -> 1080.4969 | E54: =I15 -> 395.00162 | F54: =D54/E54 -> 2.7354241 | G54: =N15 -> 2.6587441 | H54: =F54*$E$45 -> 32805.941 | I54: =G54*$E$45 -> 31886.318 | J54: =I54+$B$79 -> 35363.318
A55: Median Peer Group | B55: =MEDIAN(B46:B54) -> 60.09 | C55: =MEDIAN(C46:C54) -> 189.82264 | D55: =MEDIAN(D46:D54) -> 6166.9224 | E55: =MEDIAN(E46:E54) -> 1876.2971 | F55: =MEDIAN(F46:F54) -> 3.2867515 | G55: =MEDIAN(G46:G54) -> 3.233005 | H55: =MEDIAN(H46:H54) -> 39418.01 | I55: =MEDIAN(I46:I54) -> 38773.429 | J55: =MEDIAN(J46:J54) -> 42250.429
A56: 1st Quartile (excl. Nike) | B56: =_xlfn.QUARTILE.EXC(B46:B54,1) -> 15.83379 | C56: =_xlfn.QUARTILE.EXC(C46:C54,1) -> 102.582 | D56: =_xlfn.QUARTILE.EXC(D46:D54,1) -> 3347.8696 | E56: =_xlfn.QUARTILE.EXC(E46:E54,1) -> 1485.0045 | F56: =_xlfn.QUARTILE.EXC(F46:F54,1) -> 2.2993646 | G56: =_xlfn.QUARTILE.EXC(G46:G54,1) -> 2.3403901 | H56: =_xlfn.QUARTILE.EXC(H46:H54,1) -> 27576.28 | I56: =_xlfn.QUARTILE.EXC(I46:I54,1) -> 28068.299 | J56: =_xlfn.QUARTILE.EXC(J46:J54,1) -> 31545.299
A57: 3rd Quartile (excl. Nike) | B57: =_xlfn.QUARTILE.EXC(B46:B54,3) -> 142.921 | C57: =_xlfn.QUARTILE.EXC(C46:C54,3) -> 326.258 | D57: =_xlfn.QUARTILE.EXC(D46:D54,3) -> 16921.797 | E57: =_xlfn.QUARTILE.EXC(E46:E54,3) -> 2834.055 | F57: =_xlfn.QUARTILE.EXC(F46:F54,3) -> 6.1081039 | G57: =_xlfn.QUARTILE.EXC(G46:G54,3) -> 6.0025282 | H57: =_xlfn.QUARTILE.EXC(H46:H54,3) -> 73254.49 | I57: =_xlfn.QUARTILE.EXC(I46:I54,3) -> 71988.321 | J57: =_xlfn.QUARTILE.EXC(J46:J54,3) -> 75465.321
A58: Bloomberg (as of 20.10.2017)
A61: 3. Price Multiples Based on Cash Flows
A62: Comparable Sportswear Companies | B62: Price per Share | C62: EPS | D62: P/E (1) | E62: P/E (2) | F62: Market Share Price (2) | G62: Market Value of Equity | H62: Market Value of Equity | I62: EV Nike | J62: EV Nike
A63: In Millions of USD except Per Share
A64: Nike | B64: =B6 -> 52.69 | C64: 2.35 | D64: =B64/C64 -> 22.421276 | E64: =M6 -> 22.421276 | F64: =$C$64*E64 -> 52.689999
A65: Adidas | B65: =B7 -> 220.492 | C65: 5.2787512 | D65: =B65/C65 -> 41.769727 | E65: =M7 -> 31.881571 | F65: =$C$64*E65 -> 74.921692 | G65: =F65*$B$82 -> 122646.06 | H65: =F65*$B$81 -> 97568.496 | I65: =G65+$B$79-$B$80 -> 122315.06 | J65: =H65+$B$79-$B$80 -> 97237.496
A66: VF Corporation | B66: =B8 -> 65.35 | C66: 2.5900001 | D66: =B66/C66 -> 25.23166 | E66: =M8 -> 22.367987 | F66: =$C$64*E66 -> 52.564771 | G66: =F66*$B$82 -> 86048.004 | H66: =F66*$B$81 -> 68453.682 | I66: =G66+B80-B81 -> 88553.731 | J66: =H66+$B$79-$B$80 -> 68122.682
A67: Lululemon | B67: =B9 -> 60.09 | C67: 2.08 | D67: =B67/C67 -> 28.889423 | E67: =M9 -> 28.15848 | F67: =$C$64*E67 -> 66.17243 | G67: =F67*$B$82 -> 108323.61 | H67: =F67*$B$81 -> 86174.569 | I67: =G67+B81-B82 -> 107988.89 | J67: =H67+$B$79-$B$80 -> 85843.569
A68: Under Amour | B68: =B10 -> 16.45 | C68: 0.48029001 | D68: =B68/C68 -> 34.25014 | E68: =M10 -> 34.060088 | F68: =$C$64*E68 -> 80.041208 | G68: =F68*$B$82 -> 131026.66 | H68: =F68*$B$81 -> 104235.5 | I68: =G68+B82-B83 -> 132663.65 | J68: =H68+$B$79-$B$80 -> 103904.5
A69: Puma | B69: =B11 -> 408.8803 | C69: 7.756559 | D69: =B69/C69 -> 52.714135 | E69: =M11 -> 48.727147 | F69: =$C$64*E69 -> 114.5088 | G69: =F69*$B$82 -> 187449.75 | H69: =F69*$B$81 -> 149121.71 | I69: =G69+B83-B84 -> 187449.75 | J69: =H69+$B$79-$B$80 -> 148790.71
A70: Columbia Sportswear | B70: =B12 -> 60.8 | C70: 2.72 | D70: =B70/C70 -> 22.352941 | E70: =M12 -> 21.930892 | F70: =$C$64*E70 -> 51.537597 | G70: =F70*$B$82 -> 84366.531 | H70: =F70*$B$81 -> 67116.021 | I70: =G70+B84-B85 -> 84366.531 | J70: =H70+$B$79-$B$80 -> 66785.021
A71: Skechers | B71: =B13 -> 24.03 | C71: 1.61 | D71: =B71/C71 -> 14.925466 | E71: =M13 -> 14.919276 | F71: =$C$64*E71 -> 35.060299 | G71: =F71*$B$82 -> 57393.359 | H71: =F71*$B$81 -> 45658.081 | I71: =G71+B85-B86 -> 57393.359 | J71: =H71+$B$79-$B$80 -> 45327.081
A72: Asics | B72: =B14 -> 15.21758 | C72: 0.69576745 | D72: =B72/C72 -> 21.871647 | E72: =M14 -> 21.2433 | F72: =$C$64*E72 -> 49.921755 | G72: =F72*$B$82 -> 81721.414 | H72: =F72*$B$81 -> 65011.754 | I72: =G72+B86-B87 -> 81721.414 | J72: =H72+$B$79-$B$80 -> 64680.754
A73: Geox | B73: =B15 -> 4.168466 | C73: 0.040883024 | D73: =B73/C73 -> 101.9608 | E73: =M15 -> 93.82139 | F73: =$C$64*E73 -> 220.48027 | G73: =F73*$B$82 -> 360924 | H73: =F73*$B$81 -> 287125.5 | I73: =G73+B87-B88 -> 360924 | J73: =H73+$B$79-$B$80 -> 286794.5
A74: Median Peer Group | B74: =MEDIAN(B65:B72) -> 60.445 | C74: =MEDIAN(C65:C72) -> 2.335 | D74: =MEDIAN(D65:D72) -> 27.060541 | E74: =MEDIAN(E65:E72) -> 25.263234 | F74: =MEDIAN(F65:F72) -> 59.3686 | G74: =MEDIAN(G65:G72) -> 97185.805 | H74: =MEDIAN(H65:H72) -> 77314.125 | I74: =MEDIAN(I65:I72) -> 98271.31 | J74: =MEDIAN(J65:J72) -> 76983.125
A75: 1st Quartile (excl. Nike) | B75: =_xlfn.QUARTILE.EXC(B65:B72,1) -> 18.345 | C75: =_xlfn.QUARTILE.EXC(C65:C72,1) -> 0.92432559 | D75: =_xlfn.QUARTILE.EXC(D65:D72,1) -> 21.99197 | E75: =_xlfn.QUARTILE.EXC(E65:E72,1) -> 21.415198 | F75: =_xlfn.QUARTILE.EXC(F65:F72,1) -> 50.325716 | G75: =_xlfn.QUARTILE.EXC(G65:G72,1) -> 82382.693 | H75: =_xlfn.QUARTILE.EXC(H65:H72,1) -> 65537.821 | I75: =_xlfn.QUARTILE.EXC(I65:I72,1) -> 82382.693 | J75: =_xlfn.QUARTILE.EXC(J65:J72,1) -> 65206.821
A76: 3rd Quartile (excl. Nike) | B76: =_xlfn.QUARTILE.EXC(B65:B72,3) -> 181.7065 | C76: =_xlfn.QUARTILE.EXC(C65:C72,3) -> 4.6390634 | D76: =_xlfn.QUARTILE.EXC(D65:D72,3) -> 39.88983 | E76: =_xlfn.QUARTILE.EXC(E65:E72,3) -> 33.515459 | F76: =_xlfn.QUARTILE.EXC(F65:F72,3) -> 78.761329 | G76: =_xlfn.QUARTILE.EXC(G65:G72,3) -> 128931.51 | H76: =_xlfn.QUARTILE.EXC(H65:H72,3) -> 102568.75 | I76: =_xlfn.QUARTILE.EXC(I65:I72,3) -> 130076.5 | J76: =_xlfn.QUARTILE.EXC(J65:J72,3) -> 102237.75
A77: Bloomberg (as of 20.10.2017)
A79: Bookvalue of Debt Nike FY 2017 | B79: 3477
A80: Cash and Equivalents FY 2017 | B80: 3808
A81: Current Shares Outstanding | B81: 1302.273
A82: Shares Outstanding | B82: 1636.99

Sheet Growth Scenarios
A2: NIKE Inc (NKE US) - Growth Scenarios
B4: Historic Periods | M4: Projected Periods
A6: In Millions of USD | B6: FY 2008 | C6: FY 2009 | D6: FY 2010 | E6: FY 2011 | F6: FY 2012 | G6: FY 2013 | H6: FY 2014 | I6: FY 2015 | J6: FY 2016 | K6: FY 2017 | M6: FY 2018E | N6: FY 2019E | O6: FY 2020E | P6: FY 2021E | Q6: FY 2022E
A8: Scenario 1: Base Case
A10: Sales | B10: 18627 | C10: 19176 | D10: ='Income Statement'!D7 -> 19014 | E10: ='Income Statement'!E7 -> 20862 | F10: ='Income Statement'!F7 -> 24128 | G10: ='Income Statement'!G7 -> 25313 | H10: ='Income Statement'!H7 -> 27799 | I10: ='Income Statement'!I7 -> 30601 | J10: ='Income Statement'!J7 -> 32376 | K10: ='Income Statement'!K7 -> 34350 | M10: =$K$10*(1+M11) -> 36835.858 | N10: =M10*(1+N11) -> 39501.614 | O10: =N10*(1+O11) -> 42360.287 | P10: =O10*(1+P11) -> 45425.838 | Q10: =P10*(1+Q11) -> 48713.238 | T10: =M6 -> FY 2018E | U10: =N6 -> FY 2019E | V10: =O6 -> FY 2020E | W10: =P6 -> FY 2021E | X10: =Q6 -> FY 2022E
A11: Growth (y-o-y) | C11: =(C10/B10)-1 -> 0.029473345 | D11: =(D10/C10)-1 -> -0.0084480601 | E11: =(E10/D10)-1 -> 0.097191543 | F11: =(F10/E10)-1 -> 0.15655258 | G11: =(G10/F10)-1 -> 0.049113064 | H11: =(H10/G10)-1 -> 0.098210406 | I11: =(I10/H10)-1 -> 0.10079499 | J11: =(J10/I10)-1 -> 0.05800464 | K11: =(K10/J10)-1 -> 0.06097109 | M11: =(AVERAGE($G$11:$K$11)+AVERAGE($C$11:$K$11))/2 -> 0.072368508 | N11: =(AVERAGE($G$11:$K$11)+AVERAGE($C$11:$K$11))/2 -> 0.072368508 | O11: =(AVERAGE($G$11:$K$11)+AVERAGE($C$11:$K$11))/2 -> 0.072368508 | P11: =(AVERAGE($G$11:$K$11)+AVERAGE($C$11:$K$11))/2 -> 0.072368508 | Q11: =(AVERAGE($G$11:$K$11)+AVERAGE($C$11:$K$11))/2 -> 0.072368508 | R11: EBITDA | S11: ='Table of Contents'!J1 -> Scenario 1: Base Case | T11: =M12 -> 6093.9575 | U11: =N12 -> 6571.6366 | V11: =O12 -> 7086.7588 | W11: =P12 -> 7642.2593 | X11: =Q12 -> 8241.303
A12: EBITDA | C12: =C24-C15 -> 2293.9 | D12: =D24-D15 -> 2860.4 | E12: =E24-E15 -> 3199 | F12: =F24-F15 -> 3373 | G12: =G24-G15 -> 3721 | H12: =H24-H15 -> 4106 | I12: =I24-I15 -> 4839 | J12: =J24-J15 -> 5291 | K12: =K24-K15 -> 5651 | M12: =M10*M13 -> 6093.9575 | N12: =N10*N13 -> 6571.6366 | O12: =O10*O13 -> 7086.7588 | P12: =P10*P13 -> 7642.2593 | Q12: =Q10*Q13 -> 8241.303 | R12: EBITDA | S12: ='Table of Contents'!J2 -> Scenario 2: Bull Case | T12: =M42 -> 6264.4388 | U12: =N42 -> 6905.72 | V12: =O42 -> 7612.6483 | W12: =P42 -> 8391.9437 | X12: =Q42 -> 9251.0145
A13: EBITDA margin | C13: =C12/C10 -> 0.11962349 | D13: =D12/D10 -> 0.15043652 | E13: =E12/E10 -> 0.153341 | F13: =F12/F10 -> 0.13979609 | G13: =G12/G10 -> 0.14699957 | H13: =H12/H10 -> 0.14770315 | I13: =I12/I10 -> 0.15813209 | J13: =J12/J10 -> 0.16342352 | K13: =K12/K10 -> 0.16451237 | M13: =K13*(1+(AVERAGE($D$14:$K$14))) -> 0.16543547 | N13: =M13*(1+(AVERAGE($D$14:$K$14))) -> 0.16636375 | O13: =N13*(1+(AVERAGE($D$14:$K$14))) -> 0.16729723 | P13: =O13*(1+(AVERAGE($D$14:$K$14))) -> 0.16823596 | Q13: =P13*(1+(AVERAGE($D$14:$K$14))) -> 0.16917995 | R13: EBITDA | S13: ='Table of Contents'!J3 -> Scenario 3: Bear Case | T13: =M72 -> 5923.4763 | U13: =N72 -> 6174.4451 | V13: =O72 -> 6436.0471 | W13: =P72 -> 6708.7329 | X13: =Q72 -> 6992.9719
A14: Average Growth of EBITDA margin | D14: =D13-C13 -> 0.030813033 | E14: =E13-D13 -> 0.0029044823 | F14: =F13-E13 -> -0.013544915 | G14: =G13-F13 -> 0.0072034779 | H14: =H13-G13 -> 0.00070358935 | I14: =I13-H13 -> 0.010428932 | J14: =J13-I13 -> 0.0052914364 | K14: =K13-J13 -> 0.001088849 | L14: =L13-K13 -> -0.16451237
A15: Depreciation & Amortization Based on Change of PPE and Intangible Assets | B15: =-('Income Statement'!$B$42+'Income Statement'!$B$43) -> -312.8 | C15: =-(C16*C18) -> -346.9 | D15: =-(D16*D18) -> -337.2 | E15: =-(E16*E18) -> -351 | F15: =-(F16*F18) -> -387 | G15: =-(G16*G18) -> -452 | H15: =-(H16*H18) -> -529 | I15: =-(I16*I18) -> -606 | J15: =-(J16*J18) -> -649 | K15: =-(K16*K18) -> -706 | M15: =-(M16*M18) -> -757.57585 | N15: =-(N16*N18) -> -824.14156 | O15: =-(O16*O18) -> -896.55617 | P15: =-(P16*P18) -> -975.33361 | Q15: =-(Q16*Q18) -> -1061.033
A16: PPE & Intangible Assets | B16: ='Balance Sheet'!B15+'Balance Sheet'!B16 -> 2634.2 | C16: ='Balance Sheet'!C15+'Balance Sheet'!C16 -> 2425.1 | D16: ='Balance Sheet'!D15+'Balance Sheet'!D16 -> 2398.9 | E16: ='Balance Sheet'!E15+'Balance Sheet'!E16 -> 2602 | F16: ='Balance Sheet'!F15+'Balance Sheet'!F16 -> 2814 | G16: ='Balance Sheet'!G15+'Balance Sheet'!G16 -> 2834 | H16: ='Balance Sheet'!H15+'Balance Sheet'!H16 -> 3116 | I16: ='Balance Sheet'!I15+'Balance Sheet'!I16 -> 3292 | ... K16: ='Balance Sheet'!K15+'Balance Sheet'!K16 -> 4272 | M16: =K16*(1+M17) -> 4647.3666 | N16: =M16*(1+N17) -> 5055.7154 | O16: =N16*(1+O17) -> 5499.9446 | P16: =O16*(1+P17) -> 5983.2066 | Q16: =P16*(1+Q17) -> 6508.9313
A17: Change in PPE & Intangible Assets | C17: =(C16/B16)-1 -> -0.079378939 | D17: =(D16/C16)-1 -> -0.010803678 | E17: =(E16/D16)-1 -> 0.084663804 | F17: =(F16/E16)-1 -> 0.081475788 | G17: =(G16/F16)-1 -> 0.0071073205 | H17: =(H16/G16)-1 -> 0.099505999 | I17: =(I16/H16)-1 -> 0.05648267 | J17: =(J16/I16)-1 -> 0.15461725 | K17: =(K16/J16)-1 -> 0.12391476 | M17: =M21 -> 0.087866715 | N17: =N21 -> 0.087866715 | O17: =O21 -> 0.087866715 | P17: =P21 -> 0.087866715 | Q17: =Q21 -> 0.087866715
A18: Average Depreciation & Amortization Rate | C18: =('Income Statement'!C42+'Income Statement'!C43)/C16 -> 0.14304565 | D18: =('Income Statement'!D42+'Income Statement'!D43)/D16 -> 0.14056443 | E18: =('Income Statement'!E42+'Income Statement'!E43)/E16 -> 0.13489623 | F18: =('Income Statement'!F42+'Income Statement'!F43)/F16 -> 0.13752665 | G18: =('Income Statement'!G42+'Income Statement'!G43)/G16 -> 0.15949188 | H18: =('Income Statement'!H42+'Income Statement'!H43)/H16 -> 0.16976893 | I18: =('Income Statement'!I42+'Income Statement'!I43)/I16 -> 0.18408262 | J18: =('Income Statement'!J42+'Income Statement'!J43)/J16 -> 0.17074454 | K18: =('Income Statement'!K42+'Income Statement'!K43)/K16 -> 0.16526217 | M18: =(AVERAGE(G18:K18)+AVERAGE(C18:K18))/2 -> 0.16301186 | N18: =$M$18 -> 0.16301186 | O18: =$M$18 -> 0.16301186 | P18: =$M$18 -> 0.16301186 | Q18: =$M$18 -> 0.16301186
A19: PPE | B19: ='Balance Sheet'!B15 -> 1891.1 | C19: ='Balance Sheet'!C15 -> 1957.7 | D19: ='Balance Sheet'!D15 -> 1931.9 | E19: ='Balance Sheet'!E15 -> 2115 | F19: ='Balance Sheet'!F15 -> 2279 | G19: ='Balance Sheet'!G15 -> 2452 | H19: ='Balance Sheet'!H15 -> 2834 | I19: ='Balance Sheet'!I15 -> 3011 | ... K19: ='Balance Sheet'!K15 -> 3989 | M19: =K19*(1+M21) -> 4339.5003 | N19: =M19*(1+N21) -> 4720.798 | O19: =N19*(1+O21) -> 5135.599 | P19: =O19*(1+P21) -> 5586.8472 | Q19: =P19*(1+Q21) -> 6077.7451
A20: Change in PPE | C20: ='Balance Sheet'!C15-'Balance Sheet'!B15 -> 66.6 | D20: ='Balance Sheet'!D15-'Balance Sheet'!C15 -> -25.8 | E20: ='Balance Sheet'!E15-'Balance Sheet'!D15 -> 183.1 | F20: ='Balance Sheet'!F15-'Balance Sheet'!E15 -> 164 | G20: ='Balance Sheet'!G15-'Balance Sheet'!F15 -> 173 | H20: ='Balance Sheet'!H15-'Balance Sheet'!G15 -> 382 | I20: ='Balance Sheet'!I15-'Balance Sheet'!H15 -> 177 | J20: ='Balance Sheet'!J15-'Balance Sheet'!I15 -> 509 | K20: ='Balance Sheet'!K15-'Balance Sheet'!J15 -> 469 | M20: =M19-K19 -> 350.50033 | N20: =N19-M19 -> 381.29764 | O20: =O19-N19 -> 414.80101 | P20: =P19-O19 -> 451.24821 | Q20: =Q19-P19 -> 490.89791
A21: % Change in PPE | C21: =(C19/B19)-1 -> 0.035217598 | D21: =(D19/C19)-1 -> -0.01317873 | E21: =(E19/D19)-1 -> 0.094777162 | F21: =(F19/E19)-1 -> 0.077541371 | G21: =(G19/F19)-1 -> 0.075910487 | H21: =(H19/G19)-1 -> 0.15579119 | I21: =(I19/H19)-1 -> 0.062455893 | J21: =(J19/I19)-1 -> 0.16904683 | K21: =(K19/J19)-1 -> 0.13323864 | M21: =AVERAGE(C21:K21) -> 0.087866715 | N21: =$M$21 -> 0.087866715 | O21: =$M$21 -> 0.087866715 | P21: =$M$21 -> 0.087866715 | Q21: =$M$21 -> 0.087866715
A22: Change in Intangible Assets | C22: ='Balance Sheet'!C16-'Balance Sheet'!B16 -> -275.7 | D22: ='Balance Sheet'!D16-'Balance Sheet'!C16 -> -0.4 | E22: ='Balance Sheet'!E16-'Balance Sheet'!D16 -> 20 | F22: ='Balance Sheet'!F16-'Balance Sheet'!E16 -> 48 | G22: ='Balance Sheet'!G16-'Balance Sheet'!F16 -> -153 | H22: ='Balance Sheet'!H16-'Balance Sheet'!G16 -> -100 | I22: ='Balance Sheet'!I16-'Balance Sheet'!H16 -> -1 | J22: ='Balance Sheet'!J16-'Balance Sheet'!I16 -> 0 | K22: ='Balance Sheet'!K16-'Balance Sheet'!J16 -> 2
A23: Average Depreciation | B23: =-('Income Statement'!B43) -> -303.6 | C23: =-('Income Statement'!C43) -> -335 | D23: =-('Income Statement'!D43) -> -323.7 | E23: =-('Income Statement'!E43) -> -335 | F23: =-('Income Statement'!F43) -> -373 | G23: =-('Income Statement'!G43) -> -438 | H23: =-('Income Statement'!H43) -> -518 | I23: =-('Income Statement'!I43) -> -606 | ... K23: =-('Income Statement'!K43) -> -706 | M23: =M15 -> -757.57585 | N23: =N15 -> -824.14156 | O23: =O15 -> -896.55617 | P23: =P15 -> -975.33361 | Q23: =Q15 -> -1061.033
A24: EBIT | B24: ='Income Statement'!B15 -> 2425.8 | C24: ='Income Statement'!C15 -> 1947 | D24: ='Income Statement'!D15 -> 2523.2 | E24: ='Income Statement'!E15 -> 2848 | F24: ='Income Statement'!F15 -> 2986 | G24: ='Income Statement'!G15 -> 3269 | H24: ='Income Statement'!H15 -> 3577 | I24: ='Income Statement'!I15 -> 4233 | ... K24: ='Income Statement'!K15 -> 4945 | M24: =M12+M15 -> 5336.3817 | N24: =N12+N15 -> 5747.495 | O24: =O12+O15 -> 6190.2026 | P24: =P12+P15 -> 6666.9256 | Q24: =Q12+Q15 -> 7180.27
A25: EBIT Growth | C25: =(C24/B24)-1 -> -0.19737818 | D25: =(D24/C24)-1 -> 0.29594248 | E25: =(E24/D24)-1 -> 0.12872543 | F25: =(F24/E24)-1 -> 0.048455056 | G25: =(G24/F24)-1 -> 0.09477562 | H25: =(H24/G24)-1 -> 0.094218415 | I25: =(I24/H24)-1 -> 0.18339391 | J25: =(J24/I24)-1 -> 0.096621781 | K25: =(K24/J24)-1 -> 0.065273589 | M25: =(M24/K24)-1 -> 0.079146949 | N25: =(N24/M24)-1 -> 0.077039719 | O25: =(O24/N24)-1 -> 0.077026188 | P25: =(P24/O24)-1 -> 0.077012505 | Q25: =(Q24/P24)-1 -> 0.076998666
A26: Taxes | B26: -920.1 | C26: -469.8 | D26: -610.2 | E26: -711 | F26: -760 | G26: -808 | H26: -851 | I26: -932 | J26: -863 | K26: -646 | M26: =-(M24*$M$34) -> -1145.9583 | N26: =-(N24*$M$34) -> -1234.2426 | O26: =-(O24*$M$34) -> -1329.3116 | P26: =-(P24*$M$34) -> -1431.6852 | Q26: =-(Q24*$M$34) -> -1541.9231
A28: Depreciation & Amortization | C28: =SUM('Income Statement'!C42:C43) -> 346.9 | D28: =SUM('Income Statement'!D42:D43) -> 337.2 | E28: =SUM('Income Statement'!E42:E43) -> 351 | F28: =SUM('Income Statement'!F42:F43) -> 387 | G28: =SUM('Income Statement'!G42:G43) -> 452 | H28: =SUM('Income Statement'!H42:H43) -> 529 | I28: =SUM('Income Statement'!I42:I43) -> 606 | J28: =SUM('Income Statement'!J42:J43) -> 649 | K28: =SUM('Income Statement'!K42:K43) -> 706 | M28: =-M15 -> 757.57585 | N28: =-N15 -> 824.14156 | O28: =-O15 -> 896.55617 | P28: =-P15 -> 975.33361 | Q28: =-Q15 -> 1061.033
A29: Change in Net Working Capital | C29: ='Free Cash Flows'!C13 -> -80 | D29: ='Free Cash Flows'!D13 -> -911.5 | E29: ='Free Cash Flows'!E13 -> 760.9 | F29: ='Free Cash Flows'!F13 -> 550 | G29: ='Free Cash Flows'!G13 -> -208 | H29: ='Free Cash Flows'!H13 -> 329 | I29: ='Free Cash Flows'!I13 -> 39 | J29: ='Free Cash Flows'!J13 -> 323 | K29: ='Free Cash Flows'!K13 -> 471 | M29: =M30-K30 -> 392.8619 | N29: =N30-M30 -> 417.13309 | O29: =O30-N30 -> 442.90376 | P29: =P30-O30 -> 470.26655 | Q29: =Q30-P30 -> 499.31983
A30: Net Working Capital | C30: =('Balance Sheet'!C10+'Balance Sheet'!C11-'Balance Sheet'!C25)-'Balance Sheet'!C24 -> 3866.1 | D30: =('Balance Sheet'!D10+'Balance Sheet'!D11-'Balance Sheet'!D25)-'Balance Sheet'!D24 -> 3297.5 | E30: =('Balance Sheet'!E10+'Balance Sheet'!E11-'Balance Sheet'!E25)-'Balance Sheet'!E24 -> 4197 | F30: =('Balance Sheet'!F10+'Balance Sheet'!F11-'Balance Sheet'!F25)-'Balance Sheet'!F24 -> 4934 | G30: =('Balance Sheet'!G10+'Balance Sheet'!G11-'Balance Sheet'!G25)-'Balance Sheet'!G24 -> 4834 | H30: =('Balance Sheet'!H10+'Balance Sheet'!H11-'Balance Sheet'!H25)-'Balance Sheet'!H24 -> 5284 | I30: =('Balance Sheet'!I10+'Balance Sheet'!I11-'Balance Sheet'!I25)-'Balance Sheet'!I24 -> 5490 | J30: =('Balance Sheet'!J10+'Balance Sheet'!J11-'Balance Sheet'!J25)-'Balance Sheet'!J24 -> 5887 | K30: =('Balance Sheet'!K10+'Balance Sheet'!K11-'Balance Sheet'!K25)-'Balance Sheet'!K24 -> 6359 | M30: =K30*(1+M31) -> 6751.8619 | N30: =M30*(1+N31) -> 7168.995 | O30: =N30*(1+O31) -> 7611.8987 | P30: =O30*(1+P31) -> 8082.1653 | Q30: =P30*(1+Q31) -> 8581.4851
A31: % Change in Net Working Capital | D31: =(D30/C30)-1 -> -0.14707328 | E31: =(E30/D30)-1 -> 0.27278241 | F31: =(F30/E30)-1 -> 0.17560162 | G31: =(G30/F30)-1 -> -0.020267531 | H31: =(H30/G30)-1 -> 0.093090608 | I31: =(I30/H30)-1 -> 0.038985617 | J31: =(J30/I30)-1 -> 0.072313297 | K31: =(K30/J30)-1 -> 0.08017666 | M31: =(AVERAGE(G31:K31)+AVERAGE(D31:K31))/2 -> 0.061780453 | N31: =$M$31 -> 0.061780453 | O31: =$M$31 -> 0.061780453 | P31: =$M$31 -> 0.061780453 | Q31: =$M$31 -> 0.061780453
A32: CAPEX | C32: ='Free Cash Flows'!C11 -> -455.7 | D32: ='Free Cash Flows'!D11 -> -335.1 | E32: ='Free Cash Flows'!E11 -> -432 | F32: ='Free Cash Flows'!F11 -> -597 | G32: ='Free Cash Flows'!G11 -> -598 | H32: ='Free Cash Flows'!H11 -> -880 | I32: ='Free Cash Flows'!I11 -> -963 | J32: ='Free Cash Flows'!J11 -> -1143 | K32: ='Free Cash Flows'!K11 -> -1105 | M32: =-(M20-M23) -> -1108.0762 | N32: =-(N20-N23) -> -1205.4392 | O32: =-(O20-O23) -> -1311.3572 | P32: =-(P20-P23) -> -1426.5818 | Q32: =-(Q20-Q23) -> -1551.9309
A34: Effective Income Tax Rate | B34: 0.248 | C34: 0.24 | D34: 0.242 | E34: 0.25 | F34: 0.255 | G34: 0.247 | H34: 0.24 | I34: 0.222 | J34: 0.187 | K34: 0.132 | M34: =(AVERAGE(G34:K34)+AVERAGE(C34:K34))/2 -> 0.21474444
A36: Short-term debt | C36: ='Balance Sheet'!C24 -> 342.9 | D36: ='Balance Sheet'!D24 -> 138.6 | E36: ='Balance Sheet'!E24 -> 187 | F36: ='Balance Sheet'!F24 -> 108 | G36: ='Balance Sheet'!G24 -> 121 | H36: ='Balance Sheet'!H24 -> 167 | I36: ='Balance Sheet'!I24 -> 74 | J36: ='Balance Sheet'!J24 -> 1 | K36: ='Balance Sheet'!K24 -> 325 | M36: =(AVERAGE(C36:K36)+AVERAGE(G36:K36))/2 -> 150.16111 | N36: =$M$36 -> 150.16111 | O36: =$M$36 -> 150.16111 | P36: =$M$36 -> 150.16111 | Q36: =$M$36 -> 150.16111
A38: Scenario 2: Bull Case | C38: >> applied adjustment: | E38: 0.03
A40: =A10 -> Sales | B40: 18627 | C40: =C10 -> 19176 | D40: =D10 -> 19014 | E40: =E10 -> 20862 | F40: =F10 -> 24128 | G40: =G10 -> 25313 | H40: =H10 -> 27799 | I40: =I10 -> 30601 | J40: =J10 -> 32376 | K40: =K10 -> 34350 | M40: =K40*(1+M41) -> 37866.358 | N40: =M40*(1+N41) -> 41742.681 | O40: =N40*(1+O41) -> 46015.817 | P40: =O40*(1+P41) -> 50726.387 | Q40: =P40*(1+Q41) -> 55919.172
A41: =A11 -> Growth (y-o-y) | C41: =C11 -> 0.029473345 | D41: =D11 -> -0.0084480601 | E41: =E11 -> 0.097191543 | F41: =F11 -> 0.15655258 | G41: =G11 -> 0.049113064 | H41: =H11 -> 0.098210406 | I41: =I11 -> 0.10079499 | J41: =J11 -> 0.05800464 | K41: =K11 -> 0.06097109 | M41: =M11+$E$38 -> 0.10236851 | N41: =N11+$E$38 -> 0.10236851 | O41: =O11+$E$38 -> 0.10236851 | P41: =P11+$E$38 -> 0.10236851 | Q41: =Q11+$E$38 -> 0.10236851
A42: =A12 -> EBITDA | C42: =C12 -> 2293.9 | D42: =D12 -> 2860.4 | E42: =E12 -> 3199 | F42: =F12 -> 3373 | G42: =G12 -> 3721 | H42: =H12 -> 4106 | I42: =I12 -> 4839 | J42: =J12 -> 5291 | K42: =K12 -> 5651 | M42: =M40*$M$43 -> 6264.4388 | N42: =N40*$M$43 -> 6905.72 | O42: =O40*$M$43 -> 7612.6483 | P42: =P40*$M$43 -> 8391.9437 | Q42: =Q40*$M$43 -> 9251.0145
A43: =A13 -> EBITDA margin | C43: =C13 -> 0.11962349 | D43: =D13 -> 0.15043652 | E43: =E13 -> 0.153341 | F43: =F13 -> 0.13979609 | G43: =G13 -> 0.14699957 | H43: =H13 -> 0.14770315 | I43: =I13 -> 0.15813209 | J43: =J13 -> 0.16342352 | K43: =K13 -> 0.16451237 | M43: =M13 -> 0.16543547 | N43: =N13 -> 0.16636375 | O43: =O13 -> 0.16729723 | P43: =P13 -> 0.16823596 | Q43: =Q13 -> 0.16917995
A44: Average Growth of EBITDA margin | D44: =D43-C43 -> 0.030813033 | E44: =E43-D43 -> 0.0029044823 | F44: =F43-E43 -> -0.013544915 | G44: =G43-F43 -> 0.0072034779 | H44: =H43-G43 -> 0.00070358935 | I44: =I43-H43 -> 0.010428932 | J44: =J43-I43 -> 0.0052914364 | K44: =K43-J43 -> 0.001088849
A45: Depreciation & Amortization Based on Change of PPE and Intangible Assets | C45: =C15 -> -346.9 | D45: =D15 -> -337.2 | E45: =E15 -> -351 | F45: =F15 -> -387 | G45: =G15 -> -452 | H45: =H15 -> -529 | I45: =I15 -> -606 | J45: =J15 -> -649 | K45: =K15 -> -706 | M45: =-(M46*M48) -> -778.46745 | N45: =-(N46*N48) -> -870.22285 | O45: =-(O46*O48) -> -972.79316 | P45: =-(P46*P48) -> -1087.4531 | Q45: =-(Q46*Q48) -> -1215.6276
A46: =A16 -> PPE & Intangible Assets | B46: 2425.8 | C46: =C16 -> 2425.1 | D46: =D16 -> 2398.9 | E46: =E16 -> 2602 | F46: =F16 -> 2814 | G46: =G16 -> 2834 | H46: =H16 -> 3116 | I46: =I16 -> 3292 | J46: =J16 -> 3801 | K46: =K16 -> 4272 | M46: =K46*(1+M47) -> 4775.5266 | N46: =M46*(1+N47) -> 5338.4022 | O46: =N46*(1+O47) -> 5967.6222 | P46: =O46*(1+P47) -> 6671.0062 | Q46: =P46*(1+Q47) -> 7457.2958
A47: =A17 -> Change in PPE & Intangible Assets | C47: =C17 -> -0.079378939 | D47: =D17 -> -0.010803678 | E47: =E17 -> 0.084663804 | F47: =F17 -> 0.081475788 | G47: =G17 -> 0.0071073205 | H47: =H17 -> 0.099505999 | I47: =I17 -> 0.05648267 | J47: =J17 -> 0.15461725 | K47: =K17 -> 0.12391476 | M47: =M17+$E$38 -> 0.11786672 | N47: =N17+$E$38 -> 0.11786672 | O47: =O17+$E$38 -> 0.11786672 | P47: =P17+$E$38 -> 0.11786672 | Q47: =Q17+$E$38 -> 0.11786672
A48: =A18 -> Average Depreciation & Amortization Rate | B48: -920.1 | C48: =C18 -> 0.14304565 | D48: =D18 -> 0.14056443 | E48: =E18 -> 0.13489623 | F48: =F18 -> 0.13752665 | G48: =G18 -> 0.15949188 | H48: =H18 -> 0.16976893 | I48: =I18 -> 0.18408262 | J48: =J18 -> 0.17074454 | K48: =K18 -> 0.16526217 | M48: =M18 -> 0.16301186 | N48: =N18 -> 0.16301186 | O48: =O18 -> 0.16301186 | P48: =P18 -> 0.16301186 | Q48: =Q18 -> 0.16301186
A49: =A19 -> PPE | B49: 1505.7 | C49: =C19 -> 1957.7 | D49: =D19 -> 1931.9 | E49: =E19 -> 2115 | F49: =F19 -> 2279 | G49: =G19 -> 2452 | H49: =H19 -> 2834 | I49: =I19 -> 3011 | J49: =J19 -> 3520 | K49: =K19 -> 3989 | M49: =K49*(1+M51) -> 4459.1703 | N49: =M49*(1+N51) -> 4984.7581 | O49: =N49*(1+O51) -> 5572.2951 | P49: =O49*(1+P51) -> 6229.0833 | Q49: =P49*(1+Q51) -> 6963.2849
A50: =A20 -> Change in PPE | C50: =C20 -> 66.6 | D50: =D20 -> -25.8 | E50: =E20 -> 183.1 | F50: =F20 -> 164 | G50: =G20 -> 173 | H50: =H20 -> 382 | I50: =I20 -> 177 | J50: =J20 -> 509 | K50: =K20 -> 469 | M50: =M49-K49 -> 470.17033 | N50: =N49-M49 -> 525.58776 | O50: =O49-N49 -> 587.53706 | P50: =P49-O49 -> 656.78813 | Q50: =Q49-P49 -> 734.20158
A51: =A21 -> % Change in PPE | C51: =C21 -> 0.035217598 | D51: =D21 -> -0.01317873 | E51: =E21 -> 0.094777162 | F51: =F21 -> 0.077541371 | G51: =G21 -> 0.075910487 | H51: =H21 -> 0.15579119 | I51: =I21 -> 0.062455893 | J51: =J21 -> 0.16904683 | K51: =K21 -> 0.13323864 | M51: =M21+$E$38 -> 0.11786672 | N51: =N21+$E$38 -> 0.11786672 | O51: =O21+$E$38 -> 0.11786672 | P51: =P21+$E$38 -> 0.11786672 | Q51: =Q21+$E$38 -> 0.11786672
A52: =A22 -> Change in Intangible Assets | C52: =C22 -> -275.7 | D52: =D22 -> -0.4 | E52: =E22 -> 20 | F52: =F22 -> 48 | G52: =G22 -> -153 | H52: =H22 -> -100 | I52: =I22 -> -1 | J52: =J22 -> 0 | K52: =K22 -> 2
A53: =A23 -> Average Depreciation | B53: 1505.7 | C53: =C23 -> -335 | D53: =D23 -> -323.7 | E53: =E23 -> -335 | F53: =F23 -> -373 | G53: =G23 -> -438 | H53: =H23 -> -518 | I53: =I23 -> -606 | J53: =J23 -> -649 | K53: =K23 -> -706 | M53: =M45 -> -778.46745 | N53: =N45 -> -870.22285 | O53: =O45 -> -972.79316 | P53: =P45 -> -1087.4531 | Q53: =Q45 -> -1215.6276
A54: =A24 -> EBIT | C54: =C24 -> 1947 | D54: =D24 -> 2523.2 | E54: =E24 -> 2848 | F54: =F24 -> 2986 | G54: =G24 -> 3269 | H54: =H24 -> 3577 | I54: =I24 -> 4233 | J54: =J24 -> 4642 | K54: =K24 -> 4945 | M54: =M42+M45 -> 5485.9713 | N54: =N42+N45 -> 6035.4972 | O54: =O42+O45 -> 6639.8551 | P54: =P42+P45 -> 7304.4906 | Q54: =Q42+Q45 -> 8035.3869
A55: =A25 -> EBIT Growth | C55: =C25 -> -0.19737818 | D55: =D25 -> 0.29594248 | E55: =E25 -> 0.12872543 | F55: =F25 -> 0.048455056 | G55: =G25 -> 0.09477562 | H55: =H25 -> 0.094218415 | I55: =I25 -> 0.18339391 | J55: =J25 -> 0.096621781 | K55: =K25 -> 0.065273589 | M55: =(M54/K54)-1 -> 0.10939764 | N55: =(N54/M54)-1 -> 0.10016929 | O55: =(O54/N54)-1 -> 0.10013391 | P55: =(P54/O54)-1 -> 0.10009789 | Q55: =(Q54/P54)-1 -> 0.10006122
A56: =A26 -> Taxes | C56: =C26 -> -469.8 | D56: =D26 -> -610.2 | E56: =E26 -> -711 | F56: =F26 -> -760 | G56: =G26 -> -808 | H56: =H26 -> -851 | I56: =I26 -> -932 | J56: =J26 -> -863 | K56: =K26 -> -646 | M56: =-(M54*$M$64) -> -1178.0819 | N56: =-(N54*$M$64) -> -1296.0895 | O56: =-(O54*$M$64) -> -1425.872 | P56: =-(P54*$M$64) -> -1568.5988 | Q56: =-(Q54*$M$64) -> -1725.5547
A58: =A28 -> Depreciation & Amortization | C58: =C28 -> 346.9 | D58: =D28 -> 337.2 | E58: =E28 -> 351 | F58: =F28 -> 387 | G58: =G28 -> 452 | H58: =H28 -> 529 | I58: =I28 -> 606 | J58: =J28 -> 649 | K58: =K28 -> 706 | M58: =-(M45) -> 778.46745 | N58: =-(N45) -> 870.22285 | O58: =-(O45) -> 972.79316 | P58: =-(P45) -> 1087.4531 | Q58: =-(Q45) -> 1215.6276
A59: =A29 -> Change in Net Working Capital | C59: =C29 -> -80 | D59: =D29 -> -911.5 | E59: =E29 -> 760.9 | F59: =F29 -> 550 | G59: =G29 -> -208 | H59: =H29 -> 329 | I59: =I29 -> 39 | J59: =J29 -> 323 | K59: =K29 -> 471 | M59: =M60-K60 -> 583.6319 | N59: =N60-M60 -> 637.1979 | O59: =O60-N60 -> 695.68021 | P59: =P60-O60 -> 759.53006 | Q59: =Q60-P60 -> 829.24007
A60: =A30 -> Net Working Capital | C60: =C30 -> 3866.1 | D60: =D30 -> 3297.5 | E60: =E30 -> 4197 | F60: =F30 -> 4934 | G60: =G30 -> 4834 | H60: =H30 -> 5284 | I60: =I30 -> 5490 | J60: =J30 -> 5887 | K60: =K30 -> 6359 | M60: =K60*(1+M61) -> 6942.6319 | N60: =M60*(1+N61) -> 7579.8298 | O60: =N60*(1+O61) -> 8275.51 | P60: =O60*(1+P61) -> 9035.0401 | Q60: =P60*(1+Q61) -> 9864.2801
A61: =A31 -> % Change in Net Working Capital | D61: =D31 -> -0.14707328 | E61: =E31 -> 0.27278241 | F61: =F31 -> 0.17560162 | G61: =G31 -> -0.020267531 | H61: =H31 -> 0.093090608 | I61: =I31 -> 0.038985617 | J61: =J31 -> 0.072313297 | K61: =K31 -> 0.08017666 | M61: =M31+$E$38 -> 0.091780453 | N61: =N31+$E$38 -> 0.091780453 | O61: =O31+$E$38 -> 0.091780453 | P61: =P31+$E$38 -> 0.091780453 | Q61: =Q31+$E$38 -> 0.091780453
A62: =A32 -> CAPEX | C62: =C32 -> -455.7 | D62: =D32 -> -335.1 | E62: =E32 -> -432 | F62: =F32 -> -597 | G62: =G32 -> -598 | H62: =H32 -> -880 | I62: =I32 -> -963 | J62: =J32 -> -1143 | K62: =K32 -> -1105 | M62: =-(M50-M53) -> -1248.6378 | N62: =-(N50-N53) -> -1395.8106 | O62: =-(O50-O53) -> -1560.3302 | P62: =-(P50-P53) -> -1744.2412 | Q62: =-(Q50-Q53) -> -1949.8292
A64: Effective Income Tax Rate | B64: 0.248 | C64: 0.24 | D64: 0.242 | E64: 0.25 | F64: 0.255 | G64: 0.247 | H64: 0.24 | I64: 0.222 | J64: 0.187 | K64: 0.132 | M64: =(AVERAGE(G64:K64)+AVERAGE(C64:K64))/2 -> 0.21474444
A66: Short-term debt | C66: ='Balance Sheet'!C24 -> 342.9 | D66: ='Balance Sheet'!D24 -> 138.6 | E66: ='Balance Sheet'!E24 -> 187 | F66: ='Balance Sheet'!F24 -> 108 | G66: ='Balance Sheet'!G24 -> 121 | H66: ='Balance Sheet'!H24 -> 167 | I66: ='Balance Sheet'!I24 -> 74 | J66: ='Balance Sheet'!J24 -> 1 | K66: ='Balance Sheet'!K24 -> 325 | M66: =(AVERAGE(C66:K66)+AVERAGE(G66:K66))/2 -> 150.16111 | N66: =$M$66 -> 150.16111 | O66: =$M$66 -> 150.16111 | P66: =$M$66 -> 150.16111 | Q66: =$M$66 -> 150.16111
A68: Scenario 3: Bear Case | C68: >> applied adjustment: | E68: -0.03
A70: Sales | B70: =B10 -> 18627 | C70: =C10 -> 19176 | D70: =D10 -> 19014 | E70: =E10 -> 20862 | F70: =F10 -> 24128 | G70: =G10 -> 25313 | H70: =H10 -> 27799 | I70: =I10 -> 30601 | ... K70: =K10 -> 34350 | M70: =K70*(1+M71) -> 35805.358 | N70: =M70*(1+N71) -> 37322.378 | O70: =N70*(1+O71) -> 38903.671 | P70: =O70*(1+P71) -> 40551.962 | Q70: =P70*(1+Q71) -> 42270.088
A71: Growth (y-o-y) | B71: =B11 -> 0 | C71: =C11 -> 0.029473345 | D71: =D11 -> -0.0084480601 | E71: =E11 -> 0.097191543 | F71: =F11 -> 0.15655258 | G71: =G11 -> 0.049113064 | H71: =H11 -> 0.098210406 | I71: =I11 -> 0.10079499 | ... K71: =K11 -> 0.06097109 | M71: =M11+$E$68 -> 0.042368508 | N71: =N11+$E$68 -> 0.042368508 | O71: =O11+$E$68 -> 0.042368508 | P71: =P11+$E$68 -> 0.042368508 | Q71: =Q11+$E$68 -> 0.042368508
A72: EBITDA | B72: =B12 -> 0 | C72: =C12 -> 2293.9 | D72: =D12 -> 2860.4 | E72: =E12 -> 3199 | F72: =F12 -> 3373 | G72: =G12 -> 3721 | H72: =H12 -> 4106 | I72: =I12 -> 4839 | ... K72: =K12 -> 5651 | M72: =M70*$M$73 -> 5923.4763 | N72: =N70*$M$73 -> 6174.4451 | O72: =O70*$M$73 -> 6436.0471 | P72: =P70*$M$73 -> 6708.7329 | Q72: =Q70*$M$73 -> 6992.9719
A73: EBITDA margin | B73: =B13 -> 0 | C73: =C13 -> 0.11962349 | D73: =D13 -> 0.15043652 | E73: =E13 -> 0.153341 | F73: =F13 -> 0.13979609 | G73: =G13 -> 0.14699957 | H73: =H13 -> 0.14770315 | I73: =I13 -> 0.15813209 | ... K73: =K13 -> 0.16451237 | M73: =M13 -> 0.16543547 | N73: =N13 -> 0.16636375 | O73: =O13 -> 0.16729723 | P73: =P13 -> 0.16823596 | Q73: =Q13 -> 0.16917995
A74: Average Growth of EBITDA margin | B74: =B14 -> 0 | D74: =D14 -> 0.030813033 | E74: =E14 -> 0.0029044823 | F74: =F14 -> -0.013544915 | G74: =G14 -> 0.0072034779 | H74: =H14 -> 0.00070358935 | I74: =I14 -> 0.010428932 | J74: =J14 -> 0.0052914364 | K74: =K14 -> 0.001088849
A75: Depreciation & Amortization Based on Change of PPE and Intangible Assets | B75: =B15 -> -312.8 | C75: =C15 -> -346.9 | D75: =D15 -> -337.2 | E75: =E15 -> -351 | F75: =F15 -> -387 | G75: =G15 -> -452 | H75: =H15 -> -529 | I75: =I15 -> -606 | ... K75: =K15 -> -706 | M75: =-(M76*M78) -> -736.68425 | N75: =-(N76*N78) -> -779.31375 | O75: =-(O76*O78) -> -824.41008 | P75: =-(P76*P78) -> -872.11598 | Q75: =-(Q76*Q78) -> -922.58247
A76: PPE & Intangible Assets | B76: =B16 -> 2634.2 | C76: =C16 -> 2425.1 | D76: =D16 -> 2398.9 | E76: =E16 -> 2602 | F76: =F16 -> 2814 | G76: =G16 -> 2834 | H76: =H16 -> 3116 | I76: =I16 -> 3292 | ... K76: =K16 -> 4272 | M76: =K76*(1+M77) -> 4519.2066 | N76: =M76*(1+N77) -> 4780.7182 | O76: =N76*(1+O77) -> 5057.3627 | P76: =O76*(1+P77) -> 5350.0157 | Q76: =P76*(1+Q77) -> 5659.6035
A77: Change in PPE & Intangible Assets | B77: =B17 -> 0 | C77: =C17 -> -0.079378939 | D77: =D17 -> -0.010803678 | E77: =E17 -> 0.084663804 | F77: =F17 -> 0.081475788 | G77: =G17 -> 0.0071073205 | H77: =H17 -> 0.099505999 | I77: =I17 -> 0.05648267 | ... K77: =K17 -> 0.12391476 | M77: =M17+$E$68 -> 0.057866715 | N77: =N17+$E$68 -> 0.057866715 | O77: =O17+$E$68 -> 0.057866715 | P77: =P17+$E$68 -> 0.057866715 | Q77: =Q17+$E$68 -> 0.057866715
A78: Average Depreciation & Amortization Rate | B78: =B18 -> 0 | C78: =C18 -> 0.14304565 | D78: =D18 -> 0.14056443 | E78: =E18 -> 0.13489623 | F78: =F18 -> 0.13752665 | G78: =G18 -> 0.15949188 | H78: =H18 -> 0.16976893 | I78: =I18 -> 0.18408262 | ... K78: =K18 -> 0.16526217 | M78: =M18 -> 0.16301186 | N78: =N18 -> 0.16301186 | O78: =O18 -> 0.16301186 | P78: =P18 -> 0.16301186 | Q78: =Q18 -> 0.16301186
A79: PPE | B79: =B19 -> 1891.1 | C79: =C19 -> 1957.7 | D79: =D19 -> 1931.9 | E79: =E19 -> 2115 | F79: =F19 -> 2279 | G79: =G19 -> 2452 | H79: =H19 -> 2834 | I79: =I19 -> 3011 | ... K79: =K19 -> 3989 | M79: =K79*(1+M81) -> 4219.8303 | N79: =M79*(1+N81) -> 4464.018 | O79: =N79*(1+O81) -> 4722.3361 | P79: =O79*(1+P81) -> 4995.6022 | Q79: =P79*(1+Q81) -> 5284.6813
A80: Change in PPE | B80: =B20 -> 0 | C80: =C20 -> 66.6 | D80: =D20 -> -25.8 | E80: =E20 -> 183.1 | F80: =F20 -> 164 | G80: =G20 -> 173 | H80: =H20 -> 382 | I80: =I20 -> 177 | ... K80: =K20 -> 469 | M80: =M79-K79 -> 230.83033 | N80: =N79-M79 -> 244.18772 | O80: =O79-N79 -> 258.31806 | P80: =P79-O79 -> 273.26608 | Q80: =Q79-P79 -> 289.07909
A81: % Change in PPE | B81: =B21 -> 0 | C81: =C21 -> 0.035217598 | D81: =D21 -> -0.01317873 | E81: =E21 -> 0.094777162 | F81: =F21 -> 0.077541371 | G81: =G21 -> 0.075910487 | H81: =H21 -> 0.15579119 | I81: =I21 -> 0.062455893 | ... K81: =K21 -> 0.13323864 | M81: =M21+$E$68 -> 0.057866715 | N81: =N21+$E$68 -> 0.057866715 | O81: =O21+$E$68 -> 0.057866715 | P81: =P21+$E$68 -> 0.057866715 | Q81: =Q21+$E$68 -> 0.057866715
A82: Change in Intangible Assets | B82: =B22 -> 0 | C82: =C22 -> -275.7 | D82: =D22 -> -0.4 | E82: =E22 -> 20 | F82: =F22 -> 48 | G82: =G22 -> -153 | H82: =H22 -> -100 | I82: =I22 -> -1 | ... K82: =K22 -> 2
A83: Average Depreciation | B83: =B23 -> -303.6 | C83: =C23 -> -335 | D83: =D23 -> -323.7 | E83: =E23 -> -335 | F83: =F23 -> -373 | G83: =G23 -> -438 | H83: =H23 -> -518 | I83: =I23 -> -606 | ... K83: =K23 -> -706 | M83: =M75 -> -736.68425 | N83: =N75 -> -779.31375 | O83: =O75 -> -824.41008 | P83: =P75 -> -872.11598 | Q83: =Q75 -> -922.58247
A84: EBIT | B84: =B24 -> 2425.8 | C84: =C24 -> 1947 | D84: =D24 -> 2523.2 | E84: =E24 -> 2848 | F84: =F24 -> 2986 | G84: =G24 -> 3269 | H84: =H24 -> 3577 | I84: =I24 -> 4233 | ... K84: =K24 -> 4945 | M84: =M72+M75 -> 5186.792 | N84: =N72+N75 -> 5395.1314 | O84: =O72+O75 -> 5611.6371 | P84: =P72+P75 -> 5836.6169 | Q84: =Q72+Q75 -> 6070.3894
A85: EBIT Growth | B85: =B25 -> 0 | C85: =C25 -> -0.19737818 | D85: =D25 -> 0.29594248 | E85: =E25 -> 0.12872543 | F85: =F25 -> 0.048455056 | G85: =G25 -> 0.09477562 | H85: =H25 -> 0.094218415 | I85: =I25 -> 0.18339391 | ... K85: =K25 -> 0.065273589 | M85: =(M84/K84)-1 -> 0.048896261 | N85: =(N84/M84)-1 -> 0.040167285 | O85: =(O84/N84)-1 -> 0.04012983 | P85: =(P84/O84)-1 -> 0.040091654 | Q85: =(Q84/P84)-1 -> 0.040052743
A86: Taxes | B86: =B26 -> -920.1 | C86: =C26 -> -469.8 | D86: =D26 -> -610.2 | E86: =E26 -> -711 | F86: =F26 -> -760 | G86: =G26 -> -808 | H86: =H26 -> -851 | I86: =I26 -> -932 | ... K86: =K26 -> -646 | M86: =-(M84*$M$94) -> -1113.8348 | N86: =-(N84*$M$94) -> -1158.5745 | O86: =-(O84*$M$94) -> -1205.0679 | P86: =-(P84*$M$94) -> -1253.381 | Q86: =-(Q84*$M$94) -> -1303.5824
A88: Depreciation & Amortization | B88: =B28 -> 0 | C88: =C28 -> 346.9 | D88: =D28 -> 337.2 | E88: =E28 -> 351 | F88: =F28 -> 387 | G88: =G28 -> 452 | H88: =H28 -> 529 | I88: =I28 -> 606 | ... K88: =K28 -> 706 | M88: =-(M83) -> 736.68425 | N88: =-(N83) -> 779.31375 | O88: =-(O83) -> 824.41008 | P88: =-(P83) -> 872.11598 | Q88: =-(Q83) -> 922.58247
A89: Change in Net Working Capital | B89: =B29 -> 0 | C89: =C29 -> -80 | D89: =D29 -> -911.5 | E89: =E29 -> 760.9 | F89: =F29 -> 550 | G89: =G29 -> -208 | H89: =H29 -> 329 | I89: =I29 -> 39 | ... K89: =K29 -> 471 | M89: =M90-K90 -> 202.0919 | N89: =N90-M90 -> 208.51447 | O89: =O90-N90 -> 215.14116 | P89: =P90-O90 -> 221.97844 | Q89: =Q90-P90 -> 229.03301
A90: Net Working Capital | B90: =B30 -> 0 | C90: =C30 -> 3866.1 | D90: =D30 -> 3297.5 | E90: =E30 -> 4197 | F90: =F30 -> 4934 | G90: =G30 -> 4834 | H90: =H30 -> 5284 | I90: =I30 -> 5490 | ... K90: =K30 -> 6359 | M90: =K90*(1+M91) -> 6561.0919 | N90: =M90*(1+N91) -> 6769.6064 | O90: =N90*(1+O91) -> 6984.7475 | P90: =O90*(1+P91) -> 7206.726 | Q90: =P90*(1+Q91) -> 7435.759
A91: % Change in Net Working Capital | B91: =B31 -> 0 | D91: =D31 -> -0.14707328 | E91: =E31 -> 0.27278241 | F91: =F31 -> 0.17560162 | G91: =G31 -> -0.020267531 | H91: =H31 -> 0.093090608 | I91: =I31 -> 0.038985617 | J91: =J31 -> 0.072313297 | K91: =K31 -> 0.08017666 | M91: =M31+$E$68 -> 0.031780453 | N91: =N31+$E$68 -> 0.031780453 | O91: =O31+$E$68 -> 0.031780453 | P91: =P31+$E$68 -> 0.031780453 | Q91: =Q31+$E$68 -> 0.031780453
A92: CAPEX | B92: =B32 -> 0 | C92: =C32 -> -455.7 | D92: =D32 -> -335.1 | E92: =E32 -> -432 | F92: =F32 -> -597 | G92: =G32 -> -598 | H92: =H32 -> -880 | I92: =I32 -> -963 | ... K92: =K32 -> -1105 | M92: =-(M80-M83) -> -967.51458 | N92: =-(N80-N83) -> -1023.5015 | O92: =-(O80-O83) -> -1082.7281 | P92: =-(P80-P83) -> -1145.3821 | Q92: =-(Q80-Q83) -> -1211.6616
A94: Effective Income Tax Rate | B94: 0.248 | C94: 0.24 | D94: 0.242 | E94: 0.25 | F94: 0.255 | G94: 0.247 | H94: 0.24 | I94: 0.222 | J94: 0.187 | K94: 0.132 | M94: =(AVERAGE(G94:K94)+AVERAGE(C94:K94))/2 -> 0.21474444
A96: Short-term debt | C96: ='Balance Sheet'!C24 -> 342.9 | D96: ='Balance Sheet'!D24 -> 138.6 | E96: ='Balance Sheet'!E24 -> 187 | F96: ='Balance Sheet'!F24 -> 108 | G96: ='Balance Sheet'!G24 -> 121 | H96: ='Balance Sheet'!H24 -> 167 | I96: ='Balance Sheet'!I24 -> 74 | J96: ='Balance Sheet'!J24 -> 1 | K96: ='Balance Sheet'!K24 -> 325 | M96: =(AVERAGE(C96:K96)+AVERAGE(G96:K96))/2 -> 150.16111 | N96: =$M$96 -> 150.16111 | O96: =$M$96 -> 150.16111 | P96: =$M$96 -> 150.16111 | Q96: =$M$96 -> 150.16111
A98: Sources: Bloomberg, own calculations

Sheet Marginal Tax Rate
A2: NIKE Inc (NKE US) - Marginal Tax Rate Calculation
A4: Operating Segments: Breakdown of Revenues
A6: In Millions of USD | B6: FY 2008 | C6: FY 2009 | D6: FY 2010 | E6: FY 2011 | F6: FY 2012 | G6: FY 2013 | H6: FY 2014 | I6: FY 2015 | J6: FY 2016 | K6: FY 2017 | M6: Marginal Tax Rate per Region
A8: North America | B8: - | C8: n/a | D8: 6696 | E8: 7578 | F8: 8839 | G8: 10387 | H8: 12299 | I8: 13740 | J8: 14764 | K8: 15216 | M8: 0.35 | N8: 1)
A9: Western Europe | B9: - | C9: n/a | D9: 3892 | E9: 3810 | F9: 4144 | G9: 4128 | H9: 4979 | I9: 5709 | J9: 5884 | K9: 6211 | M9: =(0.3399+0.22+0.2+0.3333+0.2979+0.2708+0.2+0.125+0.24+0.3333+0.25+0.24+0.21+0.25+0.22+0.1777+0.19)/17 -> 0.24105294 | N9: 2)
A10: Central & Eastern Europe | B10: - | C10: n/a | D10: 1150 | E10: 1031 | F10: 1200 | G10: 1287 | H10: 1387 | I10: 1417 | J10: 1431 | K10: 1487 | M10: =(0.25+0.2+0.19+0.09+0.125+0.19+0.21+0.19+0.2+0.15+0.15+0.15+0.2+0.2+0.2+0.2+0.18+0.18+0.12+0.15+0.1+0.1+0.29+0.1+0.09+0.16+0.15+0.2)/28 -> 0.16839286 | N10: 3)
A11: Greater China | B11: - | C11: n/a | D11: 1742 | E11: 2060 | F11: 2539 | G11: 2453 | H11: 2602 | I11: 3067 | J11: 3785 | K11: 4237 | M11: =(0.25+0.165+0.12+0.17)/4 -> 0.17625 | N11: 4)
A12: Japan | B12: - | C12: n/a | D12: 882 | E12: 766 | F12: 829 | G12: 791 | H12: 771 | I12: 755 | J12: 869 | K12: 1014 | M12: 0.3086
A13: Emerging Markets | B13: - | C13: n/a | D13: 2042 | E13: 2736 | F13: 3410 | G13: 3718 | H13: 3949 | I13: 3898 | J13: 3701 | K13: 3995 | M13: =(0.34+0.255+0.3+0.295+0.225+0.1+0.28+0.55+0.3+0.25+0.22+0.24+0.31+0.3+0.2)/15 -> 0.27766667 | N13: 5)
A14: Others (not attributable to countries) | B14: - | C14: n/a | D14: =105+2529-24 -> 2610 | E14: =123+2747+11 -> 2881 | F14: =111+3095-39 -> 3167 | G14: =117+2500-68 -> 2549 | H14: =125+1684+3 -> 1812 | I14: =115+1982-82 -> 2015 | J14: =73+1955-86 -> 1942 | K14: =73+2042+75 -> 2190 | M14: 0.35 | N14: 6)
A16: Total Revenues per Region | B16: - | C16: n/a | D16: =D8+D9+D10+D11+D12+D13+D14 -> 19014 | E16: =E8+E9+E10+E11+E12+E13+E14 -> 20862 | F16: =F8+F9+F10+F11+F12+F13+F14 -> 24128 | G16: =G8+G9+G10+G11+G12+G13+G14 -> 25313 | H16: =H8+H9+H10+H11+H12+H13+H14 -> 27799 | I16: =I8+I9+I10+I11+I12+I13+I14 -> 30601 | J16: =J8+J9+J10+J11+J12+J13+J14 -> 32376 | K16: =K8+K9+K10+K11+K12+K13+K14 -> 34350
A18: Marginal tax rate based on revenue per region | C18: =D18 -> 0.29110854 | D18: =((D8/(D16))*$M$8)+((D9/(D16))*$M$9)+((D10/(D16))*$M$10)+((D11/(D16))*$M$11)+((D12/(D16))*$M$12)+((D13/(D16))*$M$13)+(D14/D16)*$M$14 -> 0.29110854 | E18: =((E8/(E16))*$M$8)+((E9/(E16))*$M$9)+((E10/(E16))*$M$10)+((E11/(E16))*$M$11)+((E12/(E16))*$M$12)+((E13/(E16))*$M$13)+(E14/E16)*$M$14 -> 0.29296488 | F18: =((F8/(F16))*$M$8)+((F9/(F16))*$M$9)+((F10/(F16))*$M$10)+((F11/(F16))*$M$11)+((F12/(F16))*$M$12)+((F13/(F16))*$M$13)+(F14/F16)*$M$14 -> 0.29232702 | G18: =((G8/(G16))*$M$8)+((G9/(G16))*$M$9)+((G10/(G16))*$M$10)+((G11/(G16))*$M$11)+((G12/(G16))*$M$12)+((G13/(G16))*$M$13)+(G14/G16)*$M$14 -> 0.29424393 | H18: =((H8/(H16))*$M$8)+((H9/(H16))*$M$9)+((H10/(H16))*$M$10)+((H11/(H16))*$M$11)+((H12/(H16))*$M$12)+((H13/(H16))*$M$13)+(H14/H16)*$M$14 -> 0.29373906 | I18: =((I8/(I16))*$M$8)+((I9/(I16))*$M$9)+((I10/(I16))*$M$10)+((I11/(I16))*$M$11)+((I12/(I16))*$M$12)+((I13/(I16))*$M$13)+(I14/I16)*$M$14 -> 0.29361558 | J18: =((J8/(J16))*$M$8)+((J9/(J16))*$M$9)+((J10/(J16))*$M$10)+((J11/(J16))*$M$11)+((J12/(J16))*$M$12)+((J13/(J16))*$M$13)+(J14/J16)*$M$14 -> 0.29248053 | K18: =((K8/(K16))*$M$8)+((K9/(K16))*$M$9)+((K10/(K16))*$M$10)+((K11/(K16))*$M$11)+((K12/(K16))*$M$12)+((K13/(K16))*$M$13)+(K14/K16)*$M$14 -> 0.29137263
A19: Sources: annual reports, KPMG, MSCI
A21: 1) We assume that most of Nike's revenue in North America is generated in the US. Therefore, we assume a marginal tax rate of 35% not taking into account the corporate tax rate in Canada of 38%.
A22: 2) Average corporate tax rate of: Belgium, Denmark, Finland, France, Germany, Luxembourg, Iceland, Ireland, Italy, Monaco Netherlands, Norway, Portugal, Spain, Sweden, Switzerland, United Kingdom
A23: 3) Average corporat tax rate of Central & Eastern Europe. Central Europe: Austria, Croatia, Czech Republic, Hungary, Lichtenstein, Poland, Slovakia, Slovenia. Eastern Europe: Estonia, Latvia, Lithuania, Georgia, Armenia, Azerbaijan, Russia, Kazakhstan, Ukraine, Belarus, Moldova, Albania, Bosnia & Herzegovina, Bulgaria, Greece, Macedonia, Montenegro, Romania, Serbia, Turkey
A24: 4) Average of China, Hong Kong, Macau & Taiwan
A25: 5) Average corporate tax rate Emerging Markets. Region of Emerging Markets based on MSCI (excluding coutries that were already mentioned in other groups): Brazil, Chile, Colombia, Mexico, Peru, Egypt, Qatar, South Africa, UAE, India, Indonesia, Korea, Malaysia, Pakistan, Philippines, Thailand
A26: 6) Revenue will be taxed at the corporate tax rate of the USA since the revenue can not be attributed to a special region.

Sheet Corporate Bond 1
A2: NIKE Inc (NKE US) - Corporate Bond 1
A4: Maturity | B4: Original Principal | C4: Interest Rate | D4: Interest Payment | E4: first Cupon Date | F4: Par Amount | G4: Course October 4, 2017 | H4: Price October 4, 2017 | I4: Test: YTM lt. Bloomberg
A5: May 1, 2023 | B5: 500000000 | C5: 0.0225 | D5: Semi-Anually | E5: 41579 | F5: 1000 | G5: 0.99787 | H5: =G5*F5 -> 997.87
A7: Date | B7: Periods | C7: Cash flows | D7: Discount factor | E7: PV of CF | F7: Face value | G7: YTM | H7: Price | I7: Value of bond
A8: 43040 | B8: 1 | C8: =$F$5*$C$5/2 -> 11.25 | D8: =1/(1+$G$8/2)^B8 -> 0.98868844 | E8: =C8*D8 -> 11.122745 | F8: =F5 -> 1000 | G8: 0.02288195 | H8: =H5 -> 997.87 | I8: =SUM(E8:E19) -> 997.87
A9: 43221 | B9: 2 | C9: =$F$5*$C$5/2 -> 11.25 | D9: =1/(1+$G$8/2)^B9 -> 0.97750483 | E9: =C9*D9 -> 10.996929
A10: 43405 | B10: 3 | C10: =$F$5*$C$5/2 -> 11.25 | D10: =1/(1+$G$8/2)^B10 -> 0.96644773 | E10: =C10*D10 -> 10.872537
A11: 43586 | B11: 4 | C11: =$F$5*$C$5/2 -> 11.25 | D11: =1/(1+$G$8/2)^B11 -> 0.9555157 | E11: =C11*D11 -> 10.749552
A12: 43770 | B12: 5 | C12: =$F$5*$C$5/2 -> 11.25 | D12: =1/(1+$G$8/2)^B12 -> 0.94470732 | E12: =C12*D12 -> 10.627957
A13: 43952 | B13: 6 | C13: =$F$5*$C$5/2 -> 11.25 | D13: =1/(1+$G$8/2)^B13 -> 0.93402121 | E13: =C13*D13 -> 10.507739
A14: 44136 | B14: 7 | C14: =$F$5*$C$5/2 -> 11.25 | D14: =1/(1+$G$8/2)^B14 -> 0.92345597 | E14: =C14*D14 -> 10.38888
A15: 44317 | B15: 8 | C15: =$F$5*$C$5/2 -> 11.25 | D15: =1/(1+$G$8/2)^B15 -> 0.91301024 | E15: =C15*D15 -> 10.271365
A16: 44501 | B16: 9 | C16: =$F$5*$C$5/2 -> 11.25 | D16: =1/(1+$G$8/2)^B16 -> 0.90268267 | E16: =C16*D16 -> 10.15518
A17: 44682 | B17: 10 | C17: =$F$5*$C$5/2 -> 11.25 | D17: =1/(1+$G$8/2)^B17 -> 0.89247193 | E17: =C17*D17 -> 10.040309
A18: 44866 | B18: 11 | C18: =$F$5*$C$5/2 -> 11.25 | D18: =1/(1+$G$8/2)^B18 -> 0.88237668 | E18: =C18*D18 -> 9.9267376
A19: 45047 | B19: 12 | C19: =$F$5*$C$5/2+F5 -> 1011.25 | D19: =1/(1+$G$8/2)^B19 -> 0.87239562 | E19: =C19*D19 -> 882.21007
A21: rD = | B21: =(1+G8/2)^2-1 -> 0.023012846
A23: Sources: Bloomberg, own calculations

Sheet Corporate Bond 2
A2: NIKE Inc (NKE US) - Corporate Bond 2
A4: Maturity | B4: Original Principal | C4: Interest Rate | D4: Interest Payment | E4: first Cupon Date | F4: Par Amount | G4: Course October 4, 2017 | H4: Price October 4, 2017 | I4: Test: YTM lt. Bloomberg
A5: November 1, 2026 | B5: 1000000000 | C5: 0.0238 | D5: Semi-Anually | E5: 42856 | F5: 1000 | G5: 0.95349 | H5: =G5*F5 -> 953.49
A7: Date | B7: Periods | C7: Cash flows | D7: Discount factor | E7: PV of CF | F7: Face value | G7: YTM | H7: Price | I7: Value of bond
A8: 43040 | B8: 1 | C8: =$F$5*$C$5/2 -> 11.9 | D8: =1/(1+$G$8/2)^B8 -> 0.98548897 | E8: =C8*D8 -> 11.727319 | F8: =F5 -> 1000 | G8: 0.029449395 | H8: =H5 -> 953.49 | I8: =SUM(E8:E26) -> 953.48058
A9: 43221 | B9: 2 | C9: =$F$5*$C$5/2 -> 11.9 | D9: =1/(1+$G$8/2)^B9 -> 0.97118852 | E9: =C9*D9 -> 11.557143
A10: 43405 | B10: 3 | C10: =$F$5*$C$5/2 -> 11.9 | D10: =1/(1+$G$8/2)^B10 -> 0.95709557 | E10: =C10*D10 -> 11.389437
A11: 43586 | B11: 4 | C11: =$F$5*$C$5/2 -> 11.9 | D11: =1/(1+$G$8/2)^B11 -> 0.94320713 | E11: =C11*D11 -> 11.224165
A12: 43770 | B12: 5 | C12: =$F$5*$C$5/2 -> 11.9 | D12: =1/(1+$G$8/2)^B12 -> 0.92952023 | E12: =C12*D12 -> 11.061291
A13: 43952 | B13: 6 | C13: =$F$5*$C$5/2 -> 11.9 | D13: =1/(1+$G$8/2)^B13 -> 0.91603194 | E13: =C13*D13 -> 10.90078
A14: 44136 | B14: 7 | C14: =$F$5*$C$5/2 -> 11.9 | D14: =1/(1+$G$8/2)^B14 -> 0.90273937 | E14: =C14*D14 -> 10.742599
A15: 44317 | B15: 8 | C15: =$F$5*$C$5/2 -> 11.9 | D15: =1/(1+$G$8/2)^B15 -> 0.8896397 | E15: =C15*D15 -> 10.586712
A16: 44501 | B16: 9 | C16: =$F$5*$C$5/2 -> 11.9 | D16: =1/(1+$G$8/2)^B16 -> 0.87673011 | E16: =C16*D16 -> 10.433088
A17: 44682 | B17: 10 | C17: =$F$5*$C$5/2 -> 11.9 | D17: =1/(1+$G$8/2)^B17 -> 0.86400786 | E17: =C17*D17 -> 10.281693
A18: 44866 | B18: 11 | C18: =$F$5*$C$5/2 -> 11.9 | D18: =1/(1+$G$8/2)^B18 -> 0.85147021 | E18: =C18*D18 -> 10.132496
A19: 45047 | B19: 12 | C19: =$F$5*$C$5/2 -> 11.9 | D19: =1/(1+$G$8/2)^B19 -> 0.83911451 | E19: =C19*D19 -> 9.9854626
A20: 45231 | B20: 13 | C20: =$F$5*$C$5/2 -> 11.9 | D20: =1/(1+$G$8/2)^B20 -> 0.82693809 | E20: =C20*D20 -> 9.8405633
... A25: 46143 | B25: 18 | C25: =$F$5*$C$5/2 -> 11.9 | D25: =1/(1+$G$8/2)^B25 -> 0.76865569 | E25: =C25*D25 -> 9.1470027
A26: 46327 | B26: 19 | C26: =$F$5*$C$5/2+F5 -> 1011.9 | D26: =1/(1+$G$8/2)^B26 -> 0.7575017 | E26: =C26*D26 -> 766.51597
A28: rD = | B28: =(1+'Corporate Bond 2'!G8/2)^2-1 -> 0.029666212
A30: Sources: Bloomberg, own calculations

Sheet Corporate Bond 3
A2: NIKE Inc (NKE US) - Corporate Bond 3
A4: Maturity | B4: Original Principal | C4: Interest Rate | D4: Interest Payment | E4: first Cupon Date | F4: Par Amount | G4: Course October 4, 2017 | H4: Price October 4, 2017 | I4: Test: YTM lt. Bloomberg
A5: May 1, 2043 | B5: 500000000 | C5: 0.0363 | D5: Semi-Anually | E5: 41579 | F5: 1000 | G5: 0.97935 | H5: =G5*F5 -> 979.35
A7: Date | B7: Periods | C7: Cash flows | D7: Discount factor | E7: PV of CF | F7: Face value | G7: YTM | H7: Price | I7: Value of bond
A8: 43040 | B8: 1 | C8: =$F$5*$C$5/2 -> 18.15 | D8: =1/(1+$G$8/2)^B8 -> 0.98157054 | E8: =C8*D8 -> 17.815505 | F8: =F5 -> 1000 | G8: 0.037550959 | H8: =H5 -> 979.35 | I8: =SUM(E8:E59) -> 979.34949
A9: 43221 | B9: 2 | C9: =$F$5*$C$5/2 -> 18.15 | D9: =1/(1+$G$8/2)^B9 -> 0.96348073 | E9: =C9*D9 -> 17.487175
A10: 43405 | B10: 3 | C10: =$F$5*$C$5/2 -> 18.15 | D10: =1/(1+$G$8/2)^B10 -> 0.9457243 | E10: =C10*D10 -> 17.164896
A11: 43586 | B11: 4 | C11: =$F$5*$C$5/2 -> 18.15 | D11: =1/(1+$G$8/2)^B11 -> 0.92829512 | E11: =C11*D11 -> 16.848556
A12: 43770 | B12: 5 | C12: =$F$5*$C$5/2 -> 18.15 | D12: =1/(1+$G$8/2)^B12 -> 0.91118714 | E12: =C12*D12 -> 16.538047
A13: 43952 | B13: 6 | C13: =$F$5*$C$5/2 -> 18.15 | D13: =1/(1+$G$8/2)^B13 -> 0.89439446 | E13: =C13*D13 -> 16.233259
A14: 44136 | B14: 7 | C14: =$F$5*$C$5/2 -> 18.15 | D14: =1/(1+$G$8/2)^B14 -> 0.87791125 | E14: =C14*D14 -> 15.934089
A15: 44317 | B15: 8 | C15: =$F$5*$C$5/2 -> 18.15 | D15: =1/(1+$G$8/2)^B15 -> 0.86173182 | E15: =C15*D15 -> 15.640433
A16: 44501 | B16: 9 | C16: =$F$5*$C$5/2 -> 18.15 | D16: =1/(1+$G$8/2)^B16 -> 0.84585057 | E16: =C16*D16 -> 15.352188
A17: 44682 | B17: 10 | C17: =$F$5*$C$5/2 -> 18.15 | D17: =1/(1+$G$8/2)^B17 -> 0.83026201 | E17: =C17*D17 -> 15.069255
A18: 44866 | B18: 11 | C18: =$F$5*$C$5/2 -> 18.15 | D18: =1/(1+$G$8/2)^B18 -> 0.81496073 | E18: =C18*D18 -> 14.791537
A19: 45047 | B19: 12 | C19: =$F$5*$C$5/2 -> 18.15 | D19: =1/(1+$G$8/2)^B19 -> 0.79994144 | E19: =C19*D19 -> 14.518937
A20: 45231 | B20: 13 | C20: =$F$5*$C$5/2 -> 18.15 | D20: =1/(1+$G$8/2)^B20 -> 0.78519896 | E20: =C20*D20 -> 14.251361
... A58: 52171 | B58: 51 | C58: =$F$5*$C$5/2 -> 18.15 | D58: =1/(1+$G$8/2)^B58 -> 0.38725527 | E58: =C58*D58 -> 7.0286832
A59: 52352 | B59: 52 | C59: =$F$5*$C$5/2+F5 -> 1018.15 | D59: =1/(1+$G$8/2)^B59 -> 0.38011837 | E59: =C59*D59 -> 387.01751
A61: rD= | B61: =(1+G8/2)^2-1 -> 0.037903478
A63: Sources: Bloomberg, own calculations

Sheet Corporate Bond 4
A2: NIKE Inc (NKE US) - Corporate Bond 3
A4: Maturity | B4: Original Principal | C4: Interest Rate | D4: Interest Payment | E4: first Cupon Date | F4: Par Amount | G4: Course October 4, 2017 | H4: Price October 4, 2017 | I4: Test: YTM lt. Bloomberg
A5: November 1, 2045 | B5: 1000000000 | C5: 0.0388 | D5: Semi-Anually | E5: 42491 | F5: 1000 | G5: 1.01553 | H5: =G5*F5 -> 1015.53
A7: Date | B7: Periods | C7: Cash flows | D7: Discount factor | E7: PV of CF | F7: Face value | G7: YTM | H7: Price | I7: Value of bond
A8: 43040 | B8: 1 | C8: =$F$5*$C$5/2 -> 19.4 | D8: =1/(1+$G$8/2)^B8 -> 0.98140041 | E8: =C8*D8 -> 19.039168 | F8: =F5 -> 1000 | G8: 0.037904176 | H8: =H5 -> 1015.53 | I8: =SUM(E8:E64) -> 1015.5286
A9: 43221 | B9: 2 | C9: =$F$5*$C$5/2 -> 19.4 | D9: =1/(1+$G$8/2)^B9 -> 0.96314677 | E9: =C9*D9 -> 18.685047
A10: 43405 | B10: 3 | C10: =$F$5*$C$5/2 -> 19.4 | D10: =1/(1+$G$8/2)^B10 -> 0.94523264 | E10: =C10*D10 -> 18.337513
A11: 43586 | B11: 4 | C11: =$F$5*$C$5/2 -> 19.4 | D11: =1/(1+$G$8/2)^B11 -> 0.9276517 | E11: =C11*D11 -> 17.996443
A12: 43770 | B12: 5 | C12: =$F$5*$C$5/2 -> 19.4 | D12: =1/(1+$G$8/2)^B12 -> 0.91039776 | E12: =C12*D12 -> 17.661717
A13: 43952 | B13: 6 | C13: =$F$5*$C$5/2 -> 19.4 | D13: =1/(1+$G$8/2)^B13 -> 0.89346474 | E13: =C13*D13 -> 17.333216
A14: 44136 | B14: 7 | C14: =$F$5*$C$5/2 -> 19.4 | D14: =1/(1+$G$8/2)^B14 -> 0.87684667 | E14: =C14*D14 -> 17.010825
A15: 44317 | B15: 8 | C15: =$F$5*$C$5/2 -> 19.4 | D15: =1/(1+$G$8/2)^B15 -> 0.86053768 | E15: =C15*D15 -> 16.694431
A16: 44501 | B16: 9 | C16: =$F$5*$C$5/2 -> 19.4 | D16: =1/(1+$G$8/2)^B16 -> 0.84453203 | E16: =C16*D16 -> 16.383921
A17: 44682 | B17: 10 | C17: =$F$5*$C$5/2 -> 19.4 | D17: =1/(1+$G$8/2)^B17 -> 0.82882409 | E17: =C17*D17 -> 16.079187
A18: 44866 | B18: 11 | C18: =$F$5*$C$5/2 -> 19.4 | D18: =1/(1+$G$8/2)^B18 -> 0.8134083 | E18: =C18*D18 -> 15.780121
A19: 45047 | B19: 12 | C19: =$F$5*$C$5/2 -> 19.4 | D19: =1/(1+$G$8/2)^B19 -> 0.79827924 | E19: =C19*D19 -> 15.486617
A20: 45231 | B20: 13 | C20: =$F$5*$C$5/2 -> 19.4 | D20: =1/(1+$G$8/2)^B20 -> 0.78343158 | E20: =C20*D20 -> 15.198573
... A63: 53083 | B63: 56 | C63: =$F$5*$C$5/2 -> 19.4 | D63: =1/(1+$G$8/2)^B63 -> 0.34945338 | E63: =C63*D63 -> 6.7793955
A64: 53267 | B64: 57 | C64: =$F$5*$C$5/2+F5 -> 1019.4 | D64: =1/(1+$G$8/2)^B64 -> 0.34295369 | E64: =C64*D64 -> 349.60699
A66: rD = | B66: =(1+G8/2)^2-1 -> 0.038263357
A68: Sources: Bloomberg, own calculations

Sheet Corporate Bond 5
A2: NIKE Inc (NKE US) - Corporate Bond 3
A4: Maturity | B4: Original Principal | C4: Interest Rate | D4: Interest Payment | E4: first Cupon Date | F4: Par Amount | G4: Course October 4, 2017 | H4: Price October 4, 2017 | I4: Test: YTM lt. Bloomberg
A5: November 1, 2046 | B5: 500000000 | C5: 0.0388 | D5: Semi-Anually | E5: 42856 | F5: 1000 | G5: 0.93485 | H5: =G5*F5 -> 934.85
A7: Date | B7: Periods | C7: Cash flows | D7: Discount factor | E7: PV of CF | F7: Face value | G7: YTM | H7: Price | I7: Value of bond
A8: 43040 | B8: 1 | C8: =$F$5*$C$5/2 -> 19.4 | D8: =1/(1+$G$8/2)^B8 -> 0.98139236 | E8: =C8*D8 -> 19.039012 | F8: =F5 -> 1000 | G8: 0.037920898 | H8: =H5 -> 934.85 | I8: =SUM(E8:E66) -> 1015.5287
A9: 43221 | B9: 2 | C9: =$F$5*$C$5/2 -> 19.4 | D9: =1/(1+$G$8/2)^B9 -> 0.96313096 | E9: =C9*D9 -> 18.684741
A10: 43405 | B10: 3 | C10: =$F$5*$C$5/2 -> 19.4 | D10: =1/(1+$G$8/2)^B10 -> 0.94520937 | E10: =C10*D10 -> 18.337062
A11: 43586 | B11: 4 | C11: =$F$5*$C$5/2 -> 19.4 | D11: =1/(1+$G$8/2)^B11 -> 0.92762126 | E11: =C11*D11 -> 17.995852
A12: 43770 | B12: 5 | C12: =$F$5*$C$5/2 -> 19.4 | D12: =1/(1+$G$8/2)^B12 -> 0.91036041 | E12: =C12*D12 -> 17.660992
A13: 43952 | B13: 6 | C13: =$F$5*$C$5/2 -> 19.4 | D13: =1/(1+$G$8/2)^B13 -> 0.89342076 | E13: =C13*D13 -> 17.332363
A14: 44136 | B14: 7 | C14: =$F$5*$C$5/2 -> 19.4 | D14: =1/(1+$G$8/2)^B14 -> 0.8767963 | E14: =C14*D14 -> 17.009848
A15: 44317 | B15: 8 | C15: =$F$5*$C$5/2 -> 19.4 | D15: =1/(1+$G$8/2)^B15 -> 0.86048119 | E15: =C15*D15 -> 16.693335
A16: 44501 | B16: 9 | C16: =$F$5*$C$5/2 -> 19.4 | D16: =1/(1+$G$8/2)^B16 -> 0.84446967 | E16: =C16*D16 -> 16.382712
A17: 44682 | B17: 10 | C17: =$F$5*$C$5/2 -> 19.4 | D17: =1/(1+$G$8/2)^B17 -> 0.82875608 | E17: =C17*D17 -> 16.077868
A18: 44866 | B18: 11 | C18: =$F$5*$C$5/2 -> 19.4 | D18: =1/(1+$G$8/2)^B18 -> 0.81333489 | E18: =C18*D18 -> 15.778697
A19: 45047 | B19: 12 | C19: =$F$5*$C$5/2 -> 19.4 | D19: =1/(1+$G$8/2)^B19 -> 0.79820065 | E19: =C19*D19 -> 15.485093
A20: 45231 | B20: 13 | C20: =$F$5*$C$5/2 -> 19.4 | D20: =1/(1+$G$8/2)^B20 -> 0.78334802 | E20: =C20*D20 -> 15.196952
... A65: 53448 | B65: 58 | C65: =$F$5*$C$5/2 -> 19.4 | D65: =1/(1+$G$8/2)^B65 -> 0.33641475 | E65: =C65*D65 -> 6.5264461
A66: 53632 | B66: 59 | C66: =$F$5*$C$5/2+F5 -> 1019.4 | D66: =1/(1+$G$8/2)^B66 -> 0.33015486 | E66: =C66*D66 -> 336.55987
A68: rD = | B68: =(1+G8/2)^2-1 -> 0.038280396
A70: Sources: Bloomberg, own calculations

Sheet Balance Sheet
A2: NIKE Inc (NKE US) - Balance Sheet
A4: In Millions of USD except Per Share | B4: FY 2008 | C4: FY 2009 | D4: FY 2010 | E4: FY 2011 | F4: FY 2012 | G4: FY 2013 | H4: FY 2014 | I4: FY 2015 | J4: FY 2016 | K4: FY 2017
A5: 12 Months Ending | B5: 05/31/2008 | C5: 05/31/2009 | D5: 05/31/2010 | E5: 05/31/2011 | F5: 05/31/2012 | G5: 05/31/2013 | H5: 05/31/2014 | I5: 05/31/2015 | J5: 05/31/2016 | K5: 05/31/2017
A7: Assets
A8: Cash and Equivalents | B8: 2133.9 | C8: 2291.1 | D8: 3079.1 | E8: 1955 | F8: 2317 | G8: 3337 | H8: 2220 | I8: 3852 | J8: 3138 | K8: 3808
A9: Short-Term Investments | B9: 642.2 | C9: 1164 | D9: 2066.8 | E9: 2583 | F9: 1440 | G9: 2628 | H9: 2922 | I9: 2072 | J9: 2319 | K9: 2371
A10: Accounts Receivable, net | B10: 2795.3 | C10: 2883.9 | D10: 2649.8 | E10: 3138 | F10: 3280 | G10: 3117 | H10: 3434 | I10: 3358 | J10: 3241 | K10: 3677
A11: Inventories | B11: 2438.4 | C11: 2357 | D11: 2040.8 | E11: 2715 | F11: 3350 | G11: 3484 | H11: 3947 | I11: 4337 | J11: 4838 | K11: 5055
A12: Deferred Income Tax Asset (Short-Term) | B12: 227.2 | C12: 272.4 | D12: 248.8 | E12: 312 | F12: 274 | G12: 308 | H12: 355 | I12: 389 | J12: 0 | K12: 0
A13: Prepaid Expenses and Other current assets | B13: 602.3 | C13: 765.6 | D13: 873.9 | E13: 594 | F13: 870 | G13: 802 | H13: 818 | I13: 1968 | J13: 1489 | K13: 1150
A14: Total Current Assets | B14: 8839.3 | C14: 9734 | D14: 10959.2 | E14: 11297 | F14: 11531 | G14: 13626 | H14: 13696 | I14: 15976 | J14: 15025 | K14: 16061
A15: Property Plant & Equipment - Net | B15: 1891.1 | C15: 1957.7 | D15: 1931.9 | E15: 2115 | F15: 2279 | G15: 2452 | H15: 2834 | I15: 3011 | J15: 3520 | K15: 3989
A16: Identifiable Intangible Assets | B16: 743.1 | C16: 467.4 | D16: 467 | E16: 487 | F16: 535 | G16: 382 | H16: 282 | I16: 281 | J16: 281 | K16: 283
A17: Goodwill | B17: 448.8 | C17: 193.5 | D17: 187.6 | E17: 205 | F17: 201 | G17: 131 | H17: 131 | I17: 131 | J17: 131 | K17: 139
A18: Deferred Income Tax Asset (Long-Term) | B18: 520.4 | C18: 897 | D18: 873.6 | E18: 894 | F18: 919 | G18: 993 | H18: 1651 | I18: 2201 | J18: 2439 | K18: 2787
A19: Total Noncurrent Assets | B19: 3603.4 | C19: 3515.6 | D19: 3460.1 | E19: 3701 | F19: 3934 | G19: =SUM(G15:G18) -> 3958 | H19: 6549 | I19: 5624 | J19: 6371 | K19: 7198
A20: Total Assets | B20: 12442.7 | C20: 13249.6 | D20: 14419.3 | E20: 14998 | F20: 15465 | G20: 17584 | H20: 18594 | I20: 21600 | J20: 21396 | K20: 23259
A22: Liabilities
A23: Current Portion of Long-Term Debt | B23: 6.3 | C23: 32 | D23: 7.4 | E23: 200 | F23: 49 | G23: 57 | H23: 7 | I23: 107 | J23: 44 | K23: 6
A24: Notes Payable (Short-Term) | B24: 177.7 | C24: 342.9 | D24: 138.6 | E24: 187 | F24: 108 | G24: 121 | H24: 167 | I24: 74 | J24: 1 | K24: 325
A25: Accounts Payable | B25: 1287.6 | C25: 1031.9 | D25: 1254.5 | E25: 1469 | F25: 1588 | G25: 1646 | H25: 1930 | I25: 2131 | J25: 2191 | K25: 2048
A26: Accrued Expenses/liabilities | B26: 1761.9 | C26: 1783.9 | D26: 1904.4 | E26: 1985 | F26: 2053 | G26: 1986 | H26: 2491 | I26: 3951 | J26: 3037 | K26: 3011
A27: Income Taxes Accrued/Payable | B27: 88 | C27: 86.3 | D27: 59.3 | E27: 117 | F27: 67 | G27: 98 | H27: 432 | I27: 71 | J27: 85 | K27: 84
A28: Liabilities From Discontinued Operations (Short-Term) | B28: 0 | C28: 0 | D28: 0 | E28: 0 | F28: 0 | G28: 18 | H28: 0 | I28: 0 | J28: 0 | K28: 0
A29: Total Current Liabilities | B29: 3321.5 | C29: 3277 | D29: 3364.2 | E29: 3958 | F29: 3865 | G29: 3962 | H29: 5027 | I29: 6334 | J29: 5358 | K29: 5474
A30: Long Term Debt | B30: 441.1 | C30: 437.2 | D30: 445.8 | E30: 276 | F30: 228 | G30: 1210 | H30: 1199 | I30: 1079 | J30: 2010 | K30: 3471
A31: Deferred Income Taxes (Liabilities) | B31: 854.5 | C31: 842 | D31: 855.3 | E31: 921 | F31: 991 | G31: 1292 | H31: 1544 | I31: 1480 | J31: 1770 | K31: 1907
A32: Total Noncurrent Liabilities | B32: 1295.6 | C32: 1279.2 | D32: 1301.1 | E32: 1197 | F32: 1219 | G32: 2502 | H32: 4287 | I32: 2559 | J32: 3780 | K32: 5378
A33: Preferred Stock/Common Stock: Class A convertible | B33: 0.1 | C33: 0.1 | D33: 0.1 | E33: 0 | F33: 0 | G33: 0 | H33: 0 | I33: 0 | J33: 0 | K33: 0
A34: Common Stock/Common Stock: Class B | B34: 2.7 | C34: 2.7 | D34: 2.7 | E34: 3 | F34: 3 | G34: 3 | H34: 3 | I34: 3 | J34: 3 | K34: 3
... A41: Shares Outstanding | B41: 491.1 | C41: 485.5 | D41: 483.0195 | E41: 468 | F41: 916 | G41: 894 | H41: 870 | I41: 857 | J41: 1682 | K41: 1643
A43: Source: Bloomberg

Sheet Income Statement
A2: NIKE Inc (NKE US) - Income Statement
A4: In Millions of USD except Per Share | B4: FY 2008 | C4: FY 2009 | D4: FY 2010 | E4: FY 2011 | F4: FY 2012 | G4: FY 2013 | H4: FY 2014 | I4: FY 2015 | J4: FY 2016 | K4: FY 2017
A5: 12 Months Ending | B5: 05/31/2008 | C5: 05/31/2009 | D5: 05/31/2010 | E5: 05/31/2011 | F5: 05/31/2012 | G5: 05/31/2013 | H5: 05/31/2014 | I5: 05/31/2015 | J5: 05/31/2016 | K5: 05/31/2017
A7: Revenues | B7: 18627 | C7: 19176.1 | D7: 19014 | E7: 20862 | F7: 24128 | G7: 25313 | H7: 27799 | I7: 30601 | J7: 32376 | K7: 34350
A8: Cost of Goods Sold | B8: 10239.6 | C8: 10571.7 | D8: 10213.6 | E8: 11354 | F8: 13657 | G8: 14279 | H8: 15353 | I8: 16534 | J8: 17405 | K8: 19038
A9: Gross Profit | B9: 8387.4 | C9: 8604.4 | D9: 8800.4 | E9: 9508 | F9: 10471 | G9: 11034 | H9: 12446 | I9: 14067 | J9: 14971 | K9: 15312
A10: (% of net sales) | B10: 0.45028185 | C10: 0.44870438 | D10: 0.46283791 | E10: 0.45575688 | F10: 0.43397712 | G10: 0.4359025 | H10: 0.44771395 | I10: 0.45969086 | J10: 0.46241043 | K10: 0.44576419
A11: Total Operating Expenses | B11: 5953.7 | C11: 6745.9 | D11: 6326.4 | E11: 6693 | F11: 7431 | G11: 7780 | H11: 8766 | I11: 9892 | J11: 10469 | K11: 10563
A12: Operating Income / Loss | B12: 2433.7 | C12: 1858.5 | D12: 2474 | E12: 2815 | F12: 3040 | G12: 3254 | H12: 3680 | I12: 4175 | J12: 4502 | K12: 4749
A13: (% of net sales) | B13: 0.13065443 | C13: 0.096917517 | D13: 0.13011465 | E13: 0.13493433 | F13: 0.12599469 | G13: 0.12855055 | H13: 0.13237886 | I13: 0.13643345 | J13: 0.13905362 | K13: 0.13825328
A14: Other Non-Operating Income / Expenses - Net | B14: -7.9 | C14: 88.5 | D14: 49.2 | E14: 33 | F14: -54 | G14: 15 | H14: -103 | I14: 58 | J14: 140 | K14: 196
A15: Income Before Interest and Taxes | B15: 2425.8 | C15: 1947 | D15: 2523.2 | E15: 2848 | F15: 2986 | G15: 3269 | H15: 3577 | I15: 4233 | J15: 4642 | K15: 4945
A16: (% of net sales) | B16: 0.13023031 | C16: 0.10153264 | D16: 0.13270222 | E16: 0.13651615 | F16: 0.12375663 | G16: 0.12914313 | H16: 0.12867369 | I16: 0.13832881 | J16: 0.14337781 | K16: 0.14395924
A17: Interest Income - Net | B17: -77.1 | C17: -9.5 | D17: 0 | E17: 0 | F17: 0 | G17: 3 | H17: 0 | I17: 0 | J17: 0 | K17: 0
A18: Interest Expense - Net | B18: 0 | C18: 0 | D18: 6.3 | E18: 4 | F18: 3 | G18: 0 | H18: 33 | I18: 28 | J18: 19 | K18: 59
... A27: (% of net sales) | B27: 0.10111129 | C27: 0.077528799 | D27: 0.10027874 | E27: 0.10037389 | F27: 0.090227122 | G27: 0.0981709 | H27: 0.096873988 | I27: 0.10695729 | J27: 0.11613541 | K27: 0.12343523
A29: Earnings per Share
A31: Basic EPS Before XO Items | B31: 0 | C31: 0 | D31: 0 | E31: 0 | F31: 2.47 | G31: 2.74 | H31: 0 | I31: 0 | J31: 0 | K31: 0
A32: Basic EPS | B32: 3.8 | C32: 3.07 | D32: 3.93 | E32: 4.48 | F32: 2.42 | G32: 0 | H32: 0 | I32: 3.8 | J32: 2.21 | K32: 2.56
A33: Weighted Avg. Shares - Basic | B33: 0 | C33: 0 | D33: 0 | E33: 0 | F33: 0 | G33: 897.3 | H33: 883.4 | I33: 0 | J33: 0 | K33: 0
A34: Diluted EPS Before XO Items | B34: 0 | C34: 0 | D34: 0 | E34: 0 | F34: 2.42 | G34: 2.68 | H34: 0 | I34: 0 | J34: 0 | K34: 0
A35: Diluted EPS | B35: 3.74 | C35: 3.03 | D35: 3.86 | E35: 4.39 | F35: 2.37 | G35: 0 | H35: 0 | I35: 3.7 | J35: 2.16 | K35: 2.51
A36: Weighted Avg. Shares - Diluted | B36: 0 | C36: 0 | D36: 0 | E36: 0 | F36: 0 | G36: 916.4 | H36: 905.8 | I36: 0 | J36: 0 | K36: 0
A37: Discontinued Operations Per Share - Basic | B37: 0 | C37: 0 | D37: 0 | E37: 0 | F37: -0.05 | G37: 0.02 | H37: 0 | I37: 0 | J37: 0 | K37: 0
A38: Discontinued Operations Per Share - Diluted | B38: 0 | C38: 0 | D38: 0 | E38: 0 | F38: -0.05 | G38: 0.02 | H38: 0 | I38: 0 | J38: 0 | K38: 0
A40: Reference Items
A42: Amortization Expense | B42: 9.2 | C42: 11.9 | D42: 13.5 | E42: 16 | F42: 14 | G42: 14 | H42: 11 | I42: 0 | J42: 0 | K42: 0
A43: Depreciation Expense | B43: 303.6 | C43: 335 | D43: 323.7 | E43: 335 | F43: 373 | G43: 438 | H43: 518 | I43: 606 | J43: 649 | K43: 706
A44: Dividends Per Share | B44: 0.875 | C44: 0.98 | D44: 1.06 | E44: 1.2 | F44: 0.7 | G44: 0.81 | H44: 0.93 | I44: 1.08 | J44: 0.62 | K44: 0.7
A45: Weighted Avg. Shares - Basic | B45: 495.6 | C45: 484.9 | D45: 485.5 | E45: 475.5 | F45: 920 | G45: 897.3 | H45: 883.4 | I45: 861.7 | J45: 1697.9 | K45: 1657.8
A46: Capital Expenditures | B46: -449.2 | C46: -455.7 | D46: -335.1 | E46: -432 | F46: -597 | G46: -598 | H46: -880 | I46: -963 | J46: -1143 | K46: -1105
A47: Sources: Bloomberg, Yahoo Finance, Nike annual reports 2008-2017

Sheet Cash Flow Statement 
A2: NIKE Inc (NKE US) - Cash-Flow Statement
A4: In Millions of USD | B4: FY 2008 | C4: FY 2009 | D4: FY 2010 | E4: FY 2011 | F4: FY 2012 | G4: FY 2013 | H4: FY 2014 | I4: FY 2015 | J4: FY 2016 | K4: FY 2017
A5: 12 Months Ending | B5: 05/31/2008 | C5: 05/31/2009 | D5: 05/31/2010 | E5: 05/31/2011 | F5: 05/31/2012 | G5: 05/31/2013 | H5: 05/31/2014 | I5: 05/31/2015 | J5: 05/31/2016 | K5: 05/31/2017
A7: Cash From Operating Activities
A9: Net Income | B9: 1883.4 | C9: 1486.7 | D9: 1906.7 | E9: 2133 | F9: 2223 | G9: 2485 | H9: 2693 | I9: 3273 | J9: 3760 | K9: 4240
A10: Depreciation | B10: 303.6 | C10: 335 | D10: 323.7 | E10: 335 | F10: 373 | G10: 438 | H10: 518 | I10: 606 | J10: 649 | K10: 706
A11: Deferred Income Taxes - CF | B11: -300.6 | C11: -294.1 | D11: 8.3 | E11: -76 | F11: -60 | G11: 21 | H11: -11 | I11: -113 | J11: -80 | K11: -273
A12: Stock Based Compensation | B12: 141 | C12: 170.6 | D12: 159 | E12: 105 | F12: 130 | G12: 174 | H12: 177 | I12: 191 | J12: 236 | K12: 215
A13: Foreign Exchange Gains/Losses | B13: 0 | C13: 0 | D13: 0 | E13: 0 | F13: 0 | G13: 0 | H13: 0 | I13: 424 | J13: 98 | K13: -117
A14: Impairment Of Goodwill-CF | B14: 0 | C14: 401.3 | D14: 0 | E14: 0 | F14: 0 | G14: 0 | H14: 0 | I14: 0 | J14: 0 | K14: 0
A15: Other Non-Cash Items | B15: -60.6 | C15: 0 | D15: 0 | E15: 0 | F15: 0 | G15: -124 | H15: 0 | I15: 0 | J15: 0 | K15: 0
A16: Change in Inventories | B16: -249.8 | C16: 32.2 | D16: 284.6 | E16: -551 | F16: -805 | G16: -197 | H16: -505 | I16: -621 | J16: -590 | K16: -231
A17: Change in Accounts Receivable | B17: -118.3 | C17: -238 | D17: 181.7 | E17: -273 | F17: -323 | G17: 142 | H17: -298 | I17: -216 | J17: 60 | K17: -426
A18: Change in Prepaid Expenses | B18: -11.2 | C18: 14.1 | D18: -69.6 | E18: -35 | F18: -141 | G18: -28 | H18: -210 | I18: -144 | J18: -161 | K18: -120
A19: Change in Accounts Payable & Accrued Expenses | B19: 330.9 | C19: -220 | D19: 298 | E19: 151 | F19: 470 | G19: 41 | H19: 525 | I19: 1237 | J19: -889 | K19: -364
A20: Other Amortization of Non-Cash Expenses/Gains | B20: 17.9 | C20: 48.3 | D20: 71.8 | E20: 23 | F20: 32 | G20: 75 | H20: 114 | I20: 43 | J20: 13 | K20: 10
A21: Total Cash Flows From Operations | B21: 1936.3 | C21: 1736.1 | D21: 3164.2 | E21: 1812 | F21: 1899 | G21: 3027 | H21: 3003 | I21: 4680 | J21: 3096 | K21: 3640
A23: Cash From Investing Activities
A25: Disposal of Fixed Assets | B25: 1.9 | C25: 32 | D25: 10.1 | E25: 1 | F25: 2 | G25: 14 | H25: 3 | I25: 3 | J25: 10 | K25: 13
A26: Capital Expenditures | B26: -449.2 | C26: -455.7 | D26: -335.1 | E26: -432 | F26: -597 | G26: -636 | H26: -880 | I26: -963 | J26: -1143 | K26: -1105
A27: Proceeds From Short-Term Investments | B27: 2246 | C27: 2390 | D27: 2787.6 | E27: 7079 | F27: 3829 | G27: 2499 | H27: 5058 | I27: 5721 | J27: 5310 | K27: 6046
A28: Purchases of Short-Term Investments | B28: -1865.6 | C28: -2908.7 | D28: -3724.4 | E28: -7616 | F28: -2705 | G28: -3702 | H28: -5386 | I28: -4936 | J28: -5367 | K28: -5928
A29: Purchases of Investments | B29: 0 | C29: 0 | D29: 0 | E29: 0 | F29: 0 | G29: 0 | H29: 0 | I29: -150 | J29: 150 | K29: 0
A30: Acquisition of Business | B30: -571.1 | C30: 0 | D30: 0 | E30: 0 | F30: 0 | G30: 0 | H30: 0 | I30: 0 | J30: 0 | K30: 0
A31: Other Investing Activities | B31: -76 | C31: 191.3 | D31: 5.5 | E31: -23 | F31: 22 | G31: 0 | H31: -2 | I31: 0 | J31: 6 | K31: -34
A32: Divestiture of Business | B32: 246 | C32: 0 | D32: 0 | E32: 0 | F32: 0 | G32: 786 | H32: 0 | I32: 0 | J32: 0 | K32: 0
A33: Purchase of Assets | B33: -21.8 | C33: -47 | D33: -11.2 | E33: -30 | F33: -37 | G33: -28 | H33: 0 | I33: 0 | J33: 0 | K33: 0
A34: Total Cash Flows From Investing | B34: -489.8 | C34: -798.1 | D34: -1267.5 | E34: -1021 | F34: 514 | G34: -1067 | H34: -1207 | I34: -175 | J34: -1034 | K34: -1008
A36: Cash from Financing Activities
A38: Dividends Paid | B38: -412.9 | C38: -466.7 | D38: -505.4 | E38: -555 | F38: -619 | G38: -703 | H38: -799 | I38: -899 | J38: -1022 | K38: -1133
A39: Increase In Short-Term Borrowings | B39: 63.7 | C39: 177.1 | D39: 0 | E39: 41 | F39: 0 | G39: 15 | H39: 75 | I39: 0 | J39: 0 | K39: 327
A40: Decrease In Short-Term Borrowings | B40: 0 | C40: 0 | D40: 0 | E40: 0 | F40: -65 | G40: 0 | H40: 0 | I40: -63 | J40: -67 | K40: 0
A41: Increase In Long-Term Borrowings | B41: 0 | C41: 0 | D41: 0 | E41: 0 | F41: 0 | G41: 986 | H41: 0 | I41: 0 | J41: 981 | K41: 1482
A42: Decrease In Long-Term Borrowings | B42: -35.2 | C42: -6.8 | D42: -32.2 | E42: -8 | F42: -203 | G42: -49 | H42: -77 | I42: -26 | J42: -113 | K42: -61
A43: Increase (Decrease) Long-Term Borrowings - Net | B43: 0 | C43: 0 | D43: -205.4 | E43: 0 | F43: 0 | G43: 0 | H43: 0 | I43: 0 | J43: 0 | K43: 0
A44: Repurchase of Common Stock | B44: -1248 | C44: -649.2 | D44: -741.2 | E44: -1859 | F44: -1814 | G44: -1674 | H44: -2628 | I44: -2534 | J44: -3238 | K44: -3223
A45: Exercise of Stock Options | B45: 343.3 | C45: 186.6 | D45: 364.5 | E45: 345 | F45: 468 | G45: 313 | H45: 383 | I45: 514 | J45: 507 | K45: 489
A46: Tax Benefit From Stock Options - Financing | B46: 63 | C46: 25.1 | D46: 58.5 | E46: 64 | F46: 115 | G46: 72 | H46: 132 | I46: 218 | J46: 281 | K46: 177
A47: Total Cash Flows From Financing Activities | B47: -1226.1 | C47: -733.9 | D47: -1061.2 | E47: -1972 | F47: -2118 | G47: -1040 | H47: -2914 | I47: -2790 | J47: -2671 | K47: -1942
A49: Effect of Exchange Rates On Cash and Equivalents | B49: 56.8 | C49: -46.9 | D49: -47.5 | E49: 57 | F49: 67 | G49: 100 | H49: 1 | I49: -83 | J49: -105 | K49: -20
A51: Net Change In Cash | B51: 277.2 | C51: 157.2 | D51: 788 | E51: -1124 | F51: 362 | G51: 1020 | H51: -1117 | I51: 1632 | J51: -714 | K51: 670
... A58: Dividends Declared and Not Paid | B58: 112.9 | C58: 121.4 | D58: 130.7 | E58: 145 | F58: 165 | G58: 188 | H58: 209 | I58: 240 | J58: 271 | K58: 300
A59: Sources: Bloomberg, Yahoo Finance, Nike annual reports 2008-2017

Sheet SPX
A2: NIKE Inc (NKE US) - SPX
A4: Security | B4: NKE US Equity | E4: Security | F4: SPX Index
A5: Start Date | B5: 36830 | E5: Start Date | F5: 40452
A6: End Date | B6: 43007 | E6: End Date | F6: 43013
A7: Period | B7: Monthly | E7: Period | F7: Daily
A8: Currency | B8: USD | E8: Currency | F8: USD
A9: Source: | B9: Bloomberg | E9: Source: | F9: Bloomberg
A11: Date | B11: PX_LAST | C11: PX_VOLUME | E11: Date | F11: PX_LAST | G11: PX_VOLUME
A12: 43007 | B12: 2519.36 | C12: 11015444512 | E12: 43012 | F12: 2537.74 | G12: 436039776
A13: 42978 | B13: 2471.65 | C13: 11015182144 | E13: 43011 | F13: 2534.58 | G13: 424599456
A14: 42947 | B14: 2470.3 | C14: 10339722208 | E14: 43010 | F14: 2529.12 | G14: 471297248
A15: 42916 | B15: 2423.41 | C15: 14263481696 | E15: 43007 | F15: 2519.36 | G15: 533211296
A16: 42886 | B16: 2411.8 | C16: 11937341184 | E16: 43006 | F16: 2510.06 | G16: 469559328
A17: 42853 | B17: 2384.2 | C17: 10089314944 | E17: 43005 | F17: 2507.04 | G17: 522364512
A18: 42825 | B18: 2362.72 | C18: 13285302944 | E18: 43004 | F18: 2496.84 | G18: 471032576
A19: 42794 | B19: 2363.64 | C19: 10744943872 | E19: 43003 | F19: 2496.66 | G19: 562565184
A20: 42766 | B20: 2278.87 | C20: 11436748096 | E20: 43000 | F20: 2502.22 | G20: 452975168
A21: 42734 | B21: 2238.83 | C21: 12322338240 | E21: 42999 | F21: 2500.6 | G21: 464068032
A22: 42704 | B22: 2198.81 | C22: 14060816672 | E22: 42998 | F22: 2508.24 | G22: 538366592
A23: 42674 | B23: 2126.15 | C23: 11816386368 | E23: 42997 | F23: 2506.65 | G23: 501443008
... A215: 36830 | B215: 1429.4 | C215: 33327549184 | E215: 42717 | F215: 2271.72 | G215: 592540480
E216: 42716 | F216: 2256.96 | G216: 631895168
E217: 42713 | F217: 2259.53 | G217: 556353856
E218: 42712 | F218: 2246.19 | G218: 630279040
E219: 42711 | F219: 2241.35 | G219: 710260224
E220: 42710 | F220: 2212.23 | G220: 552502592
E221: 42709 | F221: 2204.71 | G221: 627944512
E222: 42706 | F222: 2191.95 | G222: 593367872
E223: 42705 | F223: 2191.08 | G223: 750913728
E224: 42704 | F224: 2198.81 | G224: 1060169600
E225: 42703 | F225: 2204.66 | G225: 588951872
E226: 42702 | F226: 2201.72 | G226: 567041344
E227: 42699 | F227: 2213.35 | G227: 262991648
... E1776: 40452 | F1776: 1146.24 | G1776: 845788608

Sheet Trading Multiples Bloomberg
A2: NIKE Inc (NKE US) - SPX
A4: Bloomberg Data as of 20.10.2017
A6: Ticker | B6: Name | C6: Mkt Cap (USD) | D6: Last Px | E6: Chg Pct 1D | F6: Chg Pct 1M | G6: Rev - 1 Yr Gr:Y | H6: EPS - 1 Yr Gr:Y | I6: P/E | J6: ROE | K6: Dvd 12M Yld
A7: EQY_FUND_CRNCY | B7: REL_INDEX | C7: FA_ADJUSTED
A8: USD | C8: ADJUSTED
A9: NKE US Equity | B9: NIKE INC -CL B | C9: 85964.707 | D9: 52.69 | E9: 0.7456979 | F9: -1.624349 | G9: 6.097109 | H9: 16.203704 | I9: 22.421276 | J9: 32.626873 | K9: 1.3659648
A10: ADS GR Equity | B10: ADIDAS AG | C10: 46130.506 | D10: 220.492 | E10: -0.01337964 | F10: -3.738127 | G10: 14.046704 | H10: 34.212308 | I10: 31.881571 | J10: 19.927041 | K10: 1.0706638
A11: VFC US Equity | B11: VF CORP | C11: 25723.155 | D11: 65.35 | E11: 0.4303058 | F11: 5.18268 | G11: -0.11345792 | H11: 0.82440774 | I11: 22.367987 | J11: 29.295704 | K11: 2.5703794
A12: LULU US Equity | B12: LULULEMON ATHLETICA INC | C12: 8135.1073 | D12: 60.09 | E12: 0.6195579 | F12: 2.612703 | G12: 13.776551 | H12: 15.169174 | I12: 28.15848 | J12: 22.911484 | K12: #N/A N/A
A13: UAA US Equity | B13: UNDER ARMOUR INC-CLASS A | C13: 6912.755 | D13: 16.45 | E13: 0.7348438 | F13: -0.5441409 | G13: 21.750036 | H13: 81.055023 | I13: 34.060088 | J13: 11.491908 | K13: #N/A N/A
A14: PUM GR Equity | B14: PUMA SE | C14: 6166.9224 | D14: 408.8803 | E14: 0.8588064 | F14: 7.576467 | G14: 7.0644152 | H14: 145.7563 | I14: 48.727147 | J14: 6.5949486 | K14: 0.21648145
A15: COLM US Equity | B15: COLUMBIA SPORTSWEAR CO | C15: 4240.615 | D15: 60.8 | E15: 0.2473207 | F15: 3.701175 | G15: 2.1866322 | H15: 15.139858 | I15: 21.930892 | J15: 13.244099 | K15: 1.1844054
A16: SKX US Equity | B16: SKECHERS USA INC-CL A | C16: 3807.0977 | D16: 24.03 | E16: -4.224791 | F16: -6.824354 | G16: 13.217201 | H16: 3.0787927 | I16: 14.919276 | J16: 14.521452 | K16: #N/A N/A
A17: 7936 JP Equity | B17: ASICS CORP | C17: 3042.9534 | D17: 15.21758 | E17: 0.3492433 | F17: 2.011834 | G17: -6.8570095 | H17: 57.865105 | I17: 21.2433 | J17: 8.7080899 | K17: 1.363109
A18: GEO IM Equity | B18: GEOX SPA | C18: 1080.4969 | D18: 4.168466 | E18: -1.450893 | F18: 3.03384 | G18: 3.0262929 | H18: -45.725 | I18: 93.82139 | J18: 5.3629585 | K18: 0.56401578
A19: Median | B19: Median | C19: 6539.8387 | D19: 56.39 | E19: 0.38977455 | F19: 2.3122685 | G19: 6.5807621 | H19: 15.686439 | I19: 25.289878 | J19: 13.882775 | K19: 1.1844054
A23: Ticker | B23: Name | C23: Ticker | D23: Mkt Cap | E23: Curr Shares Out | F23: P/B:Y | G23: P/B | H23: Tot Eqty LF | I23: Diluted EPS T12M | J23: Trailing 12M EPS after XO items | K23: Last Px | L23: Last Px Dt:D-1
A24: EQY_FUND_CRNCY | B24: REL_INDEX | C24: FA_ADJUSTED
A25: USD | C25: ADJUSTED
A26: NKE US Equity | B26: NIKE INC -CL B | C26: NKE US | D26: 85964.707 | E26: 1631.01 | F26: 7.0172137 | G26: 7.1919893 | H26: 11992999936 | I26: 2.35 | J26: 2.39 | K26: 52.69 | L26: 10/19/2017
A27: ADS GR Equity | B27: ADIDAS AG | C27: ADS GR | D27: 46263.221 | E27: 209.2162 | F27: 4.6745395 | G27: 6.1810325 | H27: 6.9904625e+09 | I27: 5.2787512 | J27: 6.4398756 | K27: 187.3 | L27: 10/19/2017
A28: VFC US Equity | B28: VF CORP | C28: VFC US | D28: 25723.155 | E28: 393.6213 | F28: 4.4703388 | G28: 7.0527802 | H28: 3644338944 | I28: 2.5900001 | J28: 2.952012 | K28: 65.35 | L28: 10/19/2017
A29: LULU US Equity | B29: LULULEMON ATHLETICA INC | C29: LULU US | D29: 8135.1073 | E29: 125.6011 | F29: 6.7354423 | G29: 5.8240239 | H29: 1397809024 | I29: 2.08 | J29: 2.13726 | K29: 60.09 | L29: 10/19/2017
A30: UAA US Equity | B30: UNDER ARMOUR INC-CLASS A | C30: UAA US | D30: 6912.755 | E30: 184.9505 | F30: 6.2714323 | G30: 3.5839909 | H30: 2023771008 | I30: 0.48029001 | J30: 0.498007 | K30: 16.45 | L30: 10/19/2017
A31: PUM GR Equity | B31: PUMA SE | C31: PUM GR | D31: 6274.9606 | E31: 15.08246 | F31: 2.1851012 | G31: 3.233005 | H31: 1.8762971e+09 | I31: 7.756559 | J31: 7.7844173 | K31: 352.4 | L31: 10/19/2017
A32: COLM US Equity | B32: COLUMBIA SPORTSWEAR CO | C32: COLM US | D32: 4240.615 | E32: 69.74696 | F32: 2.6099075 | G32: 2.7391268 | H32: 1572199936 | I32: 2.72 | J32: 2.815476 | K32: 60.8 | L32: 10/19/2017
A33: SKX US Equity | B33: SKECHERS USA INC-CL A | C33: SKX US | D33: 3807.0977 | E33: 133.8858 | F33: 2.3747354 | G33: 2.0220362 | H33: 1999697024 | I33: 1.61 | J33: 1.622469 | K33: 24.03 | L33: 10/19/2017
A34: 7936 JP Equity | B34: ASICS CORP | C34: 7936 JP | D34: 3042.1479 | E34: 199.963 | F34: 2.2148828 | G34: 1.6629617 | H34: 1.7629372e+09 | I34: 0.69576745 | J34: 0.78148881 | K34: 1724 | L34: 10/19/2017
A35: GEO IM Equity | B35: GEOX SPA | C35: GEO IM | D35: 1086.3716 | E35: 259.2073 | F35: 1.5924969 | G35: 2.6587441 | H35: 3.9500162e+08 | I35: 0.040883024 | J35: 0.078538339 | K35: 3.55 | L35: 10/19/2017
A36: Median | B36: Median | D36: 6593.8578 | E36: 192.45675 | F36: 3.5401232 | G36: 3.4084979 | H36: 1.9379971e+09 | I36: 2.215 | J36: 2.26363 | K36: 60.445 | L36: 10/19/2017
A40: Ticker | B40: Name | C40: Ticker | D40: Mkt Cap | E40: EBITDA T12M | F40: EBITDA Adj T12M
A41: EQY_FUND_CRNCY | B41: REL_INDEX | C41: FA_ADJUSTED
A42: USD | C42: ADJUSTED
A43: NKE US Equity | B43: NIKE INC -CL B | C43: NKE US | D43: 85964.707 | E43: 5341 | F43: 5340999936
A44: ADS GR Equity | B44: ADIDAS AG | C44: ADS GR | D44: 46360.31 | E44: 2367.9244 | F44: 2.3714208e+09
A45: VFC US Equity | B45: VF CORP | C45: VFC US | D45: 25723.155 | E45: 1888.702 | F45: 1888702016
A46: LULU US Equity | B46: LULULEMON ATHLETICA INC | C46: LULU US | D46: 8135.1073 | E46: 518.839 | F46: 518838992
A47: UAA US Equity | B47: UNDER ARMOUR INC-CLASS A | C47: UAA US | D47: 6912.755 | E47: 528.193 | F47: 528193000
A48: PUM GR Equity | B48: PUMA SE | C48: PUM GR | D48: 6223.0837 | E48: N/A
A49: COLM US Equity | B49: COLUMBIA SPORTSWEAR CO | C49: COLM US | D49: 4240.615 | E49: 320.992 | F49: 320992008
A50: SKX US Equity | B50: SKECHERS USA INC-CL A | C50: SKX US | D50: 3807.0977 | E50: 417.087 | F50: 417087008
A51: 7936 JP Equity | B51: ASICS CORP | C51: 7936 JP | D51: 3046.4491 | E51: 296.32196 | F51: 2.9679142e+08
A52: GEO IM Equity | B52: GEOX SPA | C52: GEO IM | D52: 1088.3325 | E52: 78.420597 | F52: 78344503
A53: Median | B53: Median | D53: 6567.9193 | E53: 518.839 | F53: 518838992
A57: Ticker | B57: Name | C57: Mkt Cap | D57: EV | E57: EV/TTM EBITDA | F57: EV/EBITDA FY1 | G57: EV/EBITDA FY2 | H57: P/E | I57: P/E FY1 | J57: P/E FY2 | K57: P/FCF | L57: Dividend Yield
A58: EQY_FUND_CRNCY | B58: REL_INDEX | C58: FA_ADJUSTED
A59: USD | C59: ADJUSTED
A60: NKE US Equity | B60: NIKE INC -CL B | C60: 85964.707 | D60: 84259.707 | E60: 15.776017 | F60: 15.517644 | G60: 13.947809 | H60: 22.421276 | I60: 22.536356 | J60: 19.860535 | K60: 36.321481 | L60: 1.3659648
A61: ADS GR Equity | B61: ADIDAS AG | C61: 46107.831 | D61: 46447.939 | E61: 18.125747 | F61: 16.131951 | G61: 13.806369 | H61: 31.868601 | I61: 28.428985 | J61: 23.408122 | K61: 38.776034 | L61: 1.0709505
A62: VFC US Equity | B62: VF CORP | C62: 25723.155 | D62: 28337.128 | E62: 15.003493 | F62: 14.84601 | G62: 13.988193 | H62: 22.367987 | I62: 21.914822 | J62: 19.374444 | K62: 20.831287 | L62: 2.5703794
A63: LULU US Equity | B63: LULULEMON ATHLETICA INC | C63: 8135.1073 | D63: 7413.8953 | E63: 14.289395 | F63: 12.832781 | G63: 11.802878 | H63: 28.15848 | I63: 24.657366 | J63: 22.132597 | K63: 31.753875 | L63: #N/A N/A
A64: UAA US Equity | B64: UNDER ARMOUR INC-CLASS A | C64: 6912.755 | D64: 7701.787 | E64: 14.581388 | F64: 17.321399 | G64: 14.862347 | H64: 34.060088 | I64: 44.339623 | J64: 37.643021 | K64: 78.740724 | L64: #N/A N/A
A65: PUM GR Equity | B65: PUMA SE | C65: 6175.9932 | D65: 5921.2551 | E65: #N/A N/A | F65: 16.888461 | G65: 13.411341 | H65: 48.802956 | I65: 39.466447 | J65: 29.146493 | K65: #N/A N/A | L65: 0.21614518
A66: COLM US Equity | B66: COLUMBIA SPORTSWEAR CO | C66: 4240.615 | D66: 3643.775 | E66: 11.351607 | F66: 11.234672 | G66: 10.394956 | H66: 21.930892 | I66: 21.667855 | J66: 19.934426 | K66: 15.254336 | L66: 1.1844054
A67: SKX US Equity | B67: SKECHERS USA INC-CL A | C67: 3807.0977 | D67: 3204.8747 | E67: #N/A N/A | F67: 7.4034561 | G67: 5.9681093 | H67: 14.919276 | I67: 15.065831 | J67: 11.90783 | K67: 25.262942 | L67: #N/A N/A
A68: 7936 JP Equity | B68: ASICS CORP | C68: 3042.9534 | D68: 3029.7892 | E68: 10.638026 | F68: 10.57849 | G68: 9.5237582 | H68: 21.2433 | I68: 21.401793 | J68: 18.916784 | K68: #N/A N/A | L68: 1.363109
A69: GEO IM Equity | B69: GEOX SPA | C69: 1080.4054 | D69: 1117.8491 | E69: 13.183676 | F69: 13.04961 | G69: 9.9034868 | H69: 93.82139 | I69: 40.136364 | J69: 24.527778 | K69: 91.809096 | L69: 0.56401578
A70: Median | B70: Median | C70: 6544.3741 | D70: 6667.5752 | E70: 14.435391 | F70: 13.94781 | G70: 12.60711 | H70: 25.289878 | I70: 23.596861 | J70: 21.033511 | K70: 34.037678 | L70: 1.1844054
A73: Ticker | B73: Name | C73: Ticker | D73: Curr Shares Out | E73: Shares Out LF
A74: EQY_FUND_CRNCY | B74: REL_INDEX | C74: FA_ADJUSTED
A75: USD | C75: ADJUSTED
A76: NKE US Equity | B76: NIKE INC -CL B | C76: NKE US | D76: 1302.273 | E76: =1636999936/1000000 -> 1636.9999
A77: ADS GR Equity | B77: ADIDAS AG | C77: ADS GR | D77: 209.2162 | E77: =202657344/1000000 -> 202.65734
A78: VFC US Equity | B78: VF CORP | C78: VFC US | D78: 393.6213 | E78: =393308672/1000000 -> 393.30867
A79: LULU US Equity | B79: LULULEMON ATHLETICA INC | C79: LULU US | D79: 125.6011 | E79: =135478000/1000000 -> 135.478
A80: UAA US Equity | B80: UNDER ARMOUR INC-CLASS A | C80: UAA US | D80: 184.9505 | E80: =440922592/1000000 -> 440.92259
A81: PUM GR Equity | B81: PUMA SE | C81: PUM GR | D81: 15.08246 | E81: =15082464/1000000 -> 15.082464
A82: COLM US Equity | B82: COLUMBIA SPORTSWEAR CO | C82: COLM US | D82: 69.74696 | E82: =69686000/1000000 -> 69.686
A83: SKX US Equity | B83: SKECHERS USA INC-CL A | C83: SKX US | D83: 133.8858 | E83: =158431040/1000000 -> 158.43104
A84: 7936 JP Equity | B84: ASICS CORP | C84: 7936 JP | D84: 199.963 | E84: =189822640/1000000 -> 189.82264
A85: GEO IM Equity | B85: GEOX SPA | C85: GEO IM | D85: 259.2073 | E85: =259207328/1000000 -> 259.20733
A86: Median | B86: Median | D86: 192.45675 | E86: =196239992/1000000 -> 196.23999
